Workbook

Sheet chorizo
A6: 3500
A7: 2600 | B7: 2 dias

Sheet choriboni
C2: Socios | D2: Aportes | G2: tipo | H2: Aporte
C3: José Gustavo | D3: =+SUMIF(G:G,C3,D:D) -> 27808267 | G3: Patrimonio | H3: =+SUMIF($E$23:$E$87,G3,$D$23:$D$87) -> 19944350
C4: Edwin | D4: =+SUMIF(G:G,C4,D:D) -> 3198300 | G4: Costo | H4: =+SUMIF($E$23:$E$87,G4,$D$23:$D$87) -> 3683750
C5: Total | D5: =+D3+D4 -> 31006567 | G5: Inversión a recuperar | H5: =+SUMIF($E$23:$E$87,G5,$D$23:$D$87) -> 4345965
G6: INVIMA | H6: =+SUMIF($E$23:$E$87,G6,$D$23:$D$87) -> 490000
C7: Mitad | D7: =+D5/2+16.6 -> 15503300 | G7: Gasto | H7: =+SUMIF($E$23:$E$87,G7,$D$23:$D$87) -> 2542502
G8: Total | H8: =+SUM(H3:H7) -> 31006567
C9: fecha | D9: Aporte | E9: Medio
C10: 46062 | D10: 300000 | E10: NEQUI
C11: 46073 | D11: 1000000 | E11: NEQUI
C12: 46073 | D12: 3000000 | E12: BANCO CAJA SOCIAL
C13: 46080 | D13: 1000000 | E13: NEQUI
C14: 46084 | D14: 1500000 | E14: NEQUI
C15: 46086 | D15: 3855000 | E15: BANCO CAJA SOCIAL | F15: =+D19-D7 -> -0.1 | G15: =3855000-SUM(L64,L71,L67)/2 -> 2324075 | H15: SALDO A FAVOR | L15: =+SUM(L64,L71,L67)/2 -> 1530925
C16: 46098 | D16: 1650000 | E16: ARRIENDO
C17: PENDIENTE | D17: =+SUM(D10:D16) -> 12305000
C18: PAGADO | D18: 3198300
C19: Mitad | D19: =+D17+D18 -> 15503300 | E19: Aporte Edwin
C21: Total | D21: =+SUBTOTAL(9,D24:D1048576) -> 4345965
B23: id | C23: fecha | D23: valor | E23: tipo | F23: Equipo | G23: Responsable | H23: Consepto | I23: Proveedor
B24: 1 | C24: 46049 | D24: =1350000+150000 -> 1500000 | E24: Patrimonio | F24: Maquina | G24: José Gustavo | H24: Parrilla para segundo Negocio | I24: Comercializadora Las Brumas
B25: 2 | C25: 46049 | D25: =2500000+1400000+400000 -> 4300000 | E25: Patrimonio | F25: Maquina | G25: José Gustavo | H25: Nevera y Vitrina | I25: Compra y Venta El Dorado
B26: 3 | C26: 46056 | D26: =5400000+500000+(25000*2) -> 5950000 | E26: Patrimonio | F26: Maquina | G26: José Gustavo | H26: Parrilla - Chepes | I26: Muebles y Enseres CHEPE
B27: 4 | C27: 46056 | D27: 80000 | E27: Patrimonio | F27: Maquinaria y Equipo | G27: José Gustavo | H27: 2 Grameras | I27: El Cubo
B28: 5 | C28: 46056 | D28: 100000 | E28: Patrimonio | F28: Maquinaria y Equipo | G28: José Gustavo | H28: Bascula electrónica verde | I28: Dussan
B29: 6 | C29: 46056 | D29: 30000 | E29: Patrimonio | F29: Utencilios | G29: José Gustavo | H29: Despostador | I29: Dussan
B30: 7 | C30: 46060 | D30: 200000 | E30: Patrimonio | F30: Maquinaria y Equipo | G30: José Gustavo | H30: Campana con extractor a mujer bonita | I30: Compra y Venta D.C.
B31: 8 | C31: 46060 | D31: 110000 | E31: Patrimonio | F31: Maquinaria y Equipo | G31: José Gustavo | H31: Tabla de Picar | I31: LICICOL
B32: 9 | C32: 46060 | D32: =27000+35000 -> 62000 | E32: Patrimonio | F32: Maquina | G32: José Gustavo | H32: Candados | I32: RICAURTE
B33: 10 | C33: 46056 | D33: 2400000 | E33: Patrimonio | F33: Maquinaria y Equipo | G33: José Gustavo | H33: Mesas y sillas | I33: Muebles y montajes
B34: 11 | C34: 46056 | D34: 108150 | E34: Patrimonio | F34: Maquinaria y Equipo | G34: José Gustavo | H34: Canastas de aseo º Redeban | I34: RICAURTE
B35: 11 | C35: 46056 | D35: 180000 | E35: Patrimonio | G35: José Gustavo | H35: Extractores de la 19 | I35: La av 19
B36: 13 | C36: 46050 | D36: 135400 | E36: Patrimonio | F36: Utencilios | G36: José Gustavo | H36: Canastas, cuchillo, pinza, colador y otros
B37: 13 | C37: 46051 | D37: =50000+40000+10000+22000 -> 122000 | E37: Patrimonio | F37: Utencilios | G37: José Gustavo | H37: Canastas , cuchillos , piedra y pinzas
B38: 14 | C38: 46051 | D38: 21900 | E38: Inversión a recuperar | F38: Gasto - Local | G38: Edwin | H38: Certi. Tradición y libertad
B39: 15 | C39: 46051 | D39: 380000 | E39: Inversión a recuperar | F39: Gasto - Local | G39: José Gustavo | H39: Acarreos
B40: 16 | C40: 46051 | D40: 100000 | E40: Inversión a recuperar | F40: Gasto - Local | G40: Edwin | H40: Acarreos
B41: 17 | C41: 46051 | D41: 30000 | E41: Inversión a recuperar | F41: Gasto - Local | G41: Edwin | H41: Acarreos
B42: 18 | C42: 46060 | D42: 50000 | E42: Inversión a recuperar | F42: Gasto - Local | G42: Edwin | H42: Acarreos
B43: 19 | C43: 46066 | D43: 70000 | E43: Inversión a recuperar | F43: Gasto - Local | G43: José Gustavo | H43: Acarreos
B44: 20 | C44: 46057 | D44: 490000 | E44: INVIMA | G44: Edwin | H44: Curso Invima - INVIMA
B45: 22 | C45: 46062 | D45: =1650000+50000 -> 1700000 | E45: Inversión a recuperar | G45: José Gustavo | H45: Instalación de gas - contador | I45: Fabiola Parra
B46: 23 | C46: 46065 | D46: =15500+49000+14400+83115+4900+47200+44500 -> 258615 | E46: Inversión a recuperar | G46: José Gustavo | H46: FERRETERIA
B47: 24 | C47: 46065 | D47: =38050+47400+30000 -> 115450 | E47: Inversión a recuperar | G47: José Gustavo | H47: ASEO
B48: 25 | C48: 46070 | D48: 60000 | E48: Gasto | G48: Edwin | H48: Cámara de Comercio 2026
B49: 26 | C49: 46071 | D49: =1345000+200000 -> 1545000 | E49: Patrimonio | F49: Maquinaria y Equipo | G49: José Gustavo | H49: TV y Parlantes | I49: Ktronix
B50: 27 | C50: 46071 | D50: 151300 | E50: Patrimonio | F50: Utencilios | G50: José Gustavo | H50: Caldero, colador y Bolsas | I50: Fontanar
B51: 28 | C51: 46072 | D51: 300000 | E51: Patrimonio | F51: Maquinaria y Equipo | G51: José Gustavo | H51: Sistma POS
B52: 29 | C52: 46048 | D52: 150000 | E52: Inversión a recuperar | G52: José Gustavo | H52: Estudio del contrato del arriendo
B53: 30 | C53: 46048 | D53: 750000 | E53: Gasto | G53: José Gustavo | H53: Arriendo - 16feb-15mar
B54: 31 | C54: 46069 | D54: 900000 | E54: Gasto | G54: Edwin | H54: Arriendo - 16feb-15mar
B55: 32 | C55: 46070 | D55: 730000 | E55: Inversión a recuperar | F55: MO | G55: José Gustavo | H55: Ducto, adecuaciòn campana y otros | I55: Don Oscar
B56: 33 | C56: 46070 | D56: 420000 | E56: Inversión a recuperar | F56: MO | G56: José Gustavo | H56: Pintura de reja y plomeria | I56: Libardo Ospina
B57: 34 | C57: 46070 | D57: 300000 | E57: Inversión a recuperar | G57: José Gustavo | H57: Pintura + otros
B58: 35 | C58: 46070 | D58: 140000 | E58: Patrimonio | G58: José Gustavo | H58: Espejo e instalación
B59: 36 | C59: 46070 | D59: 550000 | E59: Patrimonio | F59: Maquinaria y Equipo | G59: José Gustavo | H59: Aviso -choriboni
B60: 37 | C60: 46070 | D60: =415000+49000 -> 464000 | E60: Patrimonio | F60: Maquinaria y Equipo | G60: José Gustavo | H60: Licuadora + colador n acero
B61: 38 | C61: 46070 | D61: =30000+101000 -> 131000 | E61: Patrimonio | F61: Maquinaria y Equipo | G61: José Gustavo | H61: 2 canecas + charon
B62: 40 | C62: 46072 | D62: 40000 | E62: Costo | G62: José Gustavo | H62: Mantenimiento Pistones
B63: 41 | C63: 46072 | D63: 140000 | E63: Costo | G63: José Gustavo | H63: papa 2 bultos de papa
B64: 42 | C64: 46072 | D64: =+L64 -> 2030000 | E64: Costo | G64: José Gustavo | H64: ENTRADA DE INVENTARIO | L64: =3500*580 -> 2030000 | M64: =+L64/2 -> 1015000
B65: 43 | C65: 46070 | D65: 40000 | E65: Costo | G65: José Gustavo | H65: Acarreo "Chorizos"
B66: 44 | C66: 46073 | D66: 15000 | E66: Patrimonio | F66: Maquinaria y Equipo | G66: Edwin | H66: Simcard
B67: 45 | C67: 46073 | D67: =+L67 -> 619850 | E67: Costo | G67: José Gustavo | H67: Cerdo, costilla | L67: 619850 | M67: =+L67/2 -> 309925
B68: 46 | C68: 46073 | D68: 90000 | E68: Costo | G68: José Gustavo | H68: Surticentro, aceites, ingredientes.
B69: 47 | C69: 46073 | D69: 20000 | E69: Inversión a recuperar | G69: José Gustavo | H69: Distrielectrics - Enchufe
B70: 48 | C70: 46073 | D70: 260100 | E70: Patrimonio | F70: Utencilios | G70: José Gustavo | H70: Platicos, cubiertos, tenedores, plasticos
B71: 49 | C71: 46073 | D71: =+L71 -> 412000 | E71: Costo | G71: José Gustavo | H71: Distrigaseosa | L71: 412000 | M71: =+L71/2 -> 206000
B72: 50 | C72: 46073 | D72: 80000 | E72: Patrimonio | G72: Edwin | H72: Cáma de Vigilencia interna
B73: 51 | C73: 46074 | D73: 57000 | E73: Costo | G73: José Gustavo | H73: 15 paquetes de arepa (10 arepas)
B74: 52 | C74: 46074 | D74: 5600 | E74: Gasto | G74: José Gustavo | H74: Pila del control
B75: 53 | C75: 46074 | D75: 15000 | E75: Patrimonio | G75: José Gustavo | H75: Trapero
B76: 54 | C76: 46076 | D76: 58200 | E76: Gasto | G76: José Gustavo | H76: SalsamentareA
B77: 55 | C77: 46076 | D77: 63202 | E77: Gasto | G77: José Gustavo | H77: Aluminio, portacomida, palillos
B78: 56 | C78: 46076 | D78: =8200+1300 -> 9500 | E78: Gasto | G78: José Gustavo | H78: Varios
B79: 57 | C79: 46076 | D79: 20400 | E79: Costo | G79: José Gustavo | H79: Pan de hamburguesa (12 panes)
B80: 58 | C80: 46076 | D80: 42500 | E80: Costo | G80: José Gustavo | H80: Carne de Cerdo para hamburguesa
B81: 59 | C81: 46076 | D81: 192000 | E81: Costo | G81: José Gustavo | H81: Carne de Res para hamburguesa
B82: 60 | C82: 46076 | D82: 260000 | E82: Patrimonio | G82: José Gustavo | H82: Cubiertos, jarra, vjilla, jarra
B83: 61 | C83: 46076 | D83: 30000 | E83: Patrimonio | G83: Edwin | H83: Dispositivo Internet
B84: 62 | C84: 46076 | D84: 615000 | E84: Gasto | G84: Edwin | H84: Homecenter
B85: 63 | C85: 46076 | D85: 81000 | E85: Gasto | G85: Edwin | H85: - VARIOS - D1 CHÍA
B86: 64 | C86: 46084 | D86: 395000 | E86: Patrimonio | G86: Edwin | H86: Publicidad
B87: 65 | C87: 46083 | D87: 330400 | E87: Patrimonio | G87: Edwin | H87: utencilios, platos, delalntal chia

Sheet choriboni_II
B1: gas | C1: 1800000
B2: muro y coples | C2: 500000
F7: caja 4
F8: 4 | G8: coca caola
G9: te

Sheet costeo
B2: 1600 | C2: Unidades
B3: 3700000 | C3: Costo total materias priams
B4: =+B3/B2 -> 2312.5 | C4: costo por unidad de producción
B6: 3500 | C6: precio por unidad
B7: =+B6*B2 -> 5600000 | C7: venta de producción
B8: =+B7-B3 -> 1900000 | C8: Margen de Ganancia
A10: 8 de marzo | B10: =7000*B2 -> 11200000 | C10: Venta en punto comercial
B11: =+B10-B3 -> 7500000

Sheet maquina
F1: 1200000 | G1: estufa
G2: meson cuadrado
G3: Software
E5: =+IF(E6>0,"Saldo a favor de papá","Saldo a favor a Edwin") -> Saldo a favor a Edwin | F5: =+IF(F6>0,"Saldo a favor de papá","Saldo a favor a Edwin") -> Saldo a favor a Edwin
B6: fecha | C6: Responsable | D6: Total | E6: =+SUM(E7:E1048576) -> -581250 | F6: =+SUM(F7:F1048576) -> -355925 | H6: =+E6+F6 -> -937175
B7: 46089 | C7: =+IF(E7>1," Jose","Edwin") -> Jose | D7: estufa | E7: 1300000
B8: 46089 | C8: =+IF(E8>1," Jose","Edwin") -> Edwin | D8: parrilla | E8: -1350000
B9: 46089 | C9: =+IF(E9>1," Jose","Edwin") -> Edwin | D9: mesas | E9: -400000
B10: 46089 | C10: =+IF(E10>1," Jose","Edwin") -> Edwin | D10: Campana | E10: =-500000/2 -> -250000
B11: 46089 | C11: =+IF(E11>1," Jose","Edwin") -> Edwin | D11: motor | E11: =-180000/2 -> -90000
B12: 46089 | C12: =+IF(E12>1," Jose","Edwin") -> Edwin | D12: dispositivo wifi | E12: -30000
B13: 46076 | C13: =+IF(E13>1," Jose","Edwin") -> Jose | D13: chorizo | E13: =((550-185)*3500)/2 -> 638750
B14: 46089 | C14: =+IF(E14>1," Jose","Edwin") -> Edwin | D14: Software | E14: =-800000/2 -> -400000
B16: 46097 | C16: =+IF(F16>1," Jose","Edwin") -> Edwin | D16: Caneca | F16: -50000
B17: 46097 | C17: =+IF(F17>1," Jose","Edwin") -> Edwin | D17: CCB | F17: =-60000/2 -> -30000
B18: 46089 | C18: =+IF(F18>1," Jose","Edwin") -> Jose | D18: Chorizos | F18: =(500*3500)/2 -> 875000 | G18: =+H18/2 -> 250 | H18: 500
B19: 46106 | C19: =+IF(F19>1," Jose","Edwin") -> Jose | D19: Chorizos | F19: =(230*3500)/2 -> 402500 | G19: =+H19/2 -> 115 | H19: 230
B20: 46106 | C20: =+IF(F20>1," Jose","Edwin") -> Edwin | D20: Chorizos de baja | F20: =-(50*3500)/2 -> -87500 | G20: =+H20/2 -> -25 | H20: -50
B21: 46106 | C21: =+IF(F21>1," Jose","Edwin") -> Jose | D21: Chorizos de degustaciòn | F21: =(20*3500)/2 -> 35000 | G21: =+H21/2 -> 10 | H21: 20
B22: 46107 | C22: =+IF(F22>1," Jose","Edwin") -> Jose | D22: dispositivo wifi | F22: 30000
A23: 46072 | B23: 46089 | C23: =+IF(F23>1," Jose","Edwin") -> Edwin | D23: Chorizos - REPOSICIÓN | F23: =-choriboni!$M$64 -> -1015000 | G23: 290
A24: 46073 | B24: 46084 | C24: =+IF(F24>1," Jose","Edwin") -> Edwin | D24: Cerdo y costilla | F24: =-choriboni!$M$67 -> -309925
A25: 46073 | B25: 46107 | C25: =+IF(F25>1," Jose","Edwin") -> Edwin | D25: Gaseosa | F25: =-choriboni!$M$71 -> -206000

Sheet Arqueo de Caja
C1: =+TEXT(C2,"ddd") -> sáb | E1: =+TEXT(E2,"ddd") -> vie | G1: =+TEXT(G2,"ddd") -> jue | I1: =+TEXT(I2,"ddd") -> mié | K1: =+TEXT(K2,"ddd") -> mar | M1: =+TEXT(M2,"ddd") -> lun | O1: =+TEXT(O2,"ddd") -> dom | Q1: =+TEXT(Q2,"ddd") -> sáb | S1: =+TEXT(S2,"ddd") -> vie | U1: =+TEXT(U2,"ddd") -> jue | W1: =+TEXT(W2,"ddd") -> mié | Y1: =+TEXT(Y2,"ddd") -> mar | AA1: =+TEXT(AA2,"ddd") -> lun | AC1: =+TEXT(AC2,"ddd") -> dom | AE1: =+TEXT(AE2,"ddd") -> sáb | AG1: =+TEXT(AG2,"ddd") -> vie | AI1: =+TEXT(AI2,"ddd") -> jue | AK1: =+TEXT(AK2,"ddd") -> mié | AM1: =+TEXT(AM2,"ddd") -> mar | AO1: =+TEXT(AO2,"ddd") -> lun | AQ1: =+TEXT(AQ2,"ddd") -> dom | AS1: =+TEXT(AS2,"ddd") -> sáb | AU1: =+TEXT(AU2,"ddd") -> vie | AW1: =+TEXT(AW2,"ddd") -> jue | AY1: =+TEXT(AY2,"ddd") -> mié | BA1: =+TEXT(BA2,"ddd") -> mar | BC1: =+TEXT(BC2,"ddd") -> lun | BE1: =+TEXT(BE2,"ddd") -> dom | BG1: =+TEXT(BG2,"ddd") -> sáb | BI1: =+TEXT(BI2,"ddd") -> vie | BK1: =+TEXT(BK2,"ddd") -> jue | BM1: =+TEXT(BM2,"ddd") -> mié | BO1: =+TEXT(BO2,"ddd") -> mar | BQ1: =+TEXT(BQ2,"ddd") -> lun | BS1: =+TEXT(BS2,"ddd") -> dom | BU1: =+TEXT(BU2,"ddd") -> sáb | BW1: =+TEXT(BW2,"ddd") -> vie | BY1: =+TEXT(BY2,"ddd") -> jue | CA1: =+TEXT(CA2,"ddd") -> mié | CC1: =+TEXT(CC2,"ddd") -> mar | CE1: =+TEXT(CE2,"ddd") -> lun | CG1: =+TEXT(CG2,"ddd") -> dom | CI1: =+TEXT(CI2,"ddd") -> sáb | CK1: =+TEXT(CK2,"ddd") -> vie | CM1: =+TEXT(CM2,"ddd") -> jue | CO1: =+TEXT(CO2,"ddd") -> mié | CQ1: =+TEXT(CQ2,"ddd") -> mar | CS1: =+TEXT(CS2,"ddd") -> lun
A2: valor billete | B2: Q | C2: =+E2+1 -> 46123 | D2: Q | E2: =+G2+1 -> 46122 | F2: Q | G2: =+I2+1 -> 46121 | H2: Q | I2: =+K2+1 -> 46120 | J2: Q | K2: =+M2+1 -> 46119 | L2: Q | M2: =+O2+1 -> 46118 | N2: Q | O2: =+Q2+1 -> 46117 | P2: Q | Q2: =+S2+1 -> 46116 | R2: Q | S2: =+U2+1 -> 46115 | T2: Q | U2: =+W2+1 -> 46114 | V2: Q | W2: =+Y2+1 -> 46113 | X2: Q | Y2: =+AA2+1 -> 46112 | Z2: Q | AA2: =+AC2+1 -> 46111 | AB2: Q | AC2: =+AE2+1 -> 46110 | AD2: Q | AE2: =+AG2+1 -> 46109 | AF2: Q | AG2: =+AI2+1 -> 46108 | AH2: Q | AI2: =+AK2+1 -> 46107 | AJ2: Q | AK2: =+AM2+1 -> 46106 | AL2: Q | AM2: =+AO2+1 -> 46105 | AN2: Q | AO2: =+AQ2+1 -> 46104 | AP2: Q | AQ2: =+AS2+1 -> 46103 | AR2: Q | AS2: =+AU2+1 -> 46102 | AT2: Q | AU2: =+AW2+1 -> 46101 | AV2: Q | AW2: =+AY2+1 -> 46100 | AX2: Q | AY2: =+BA2+1 -> 46099 | AZ2: Q | BA2: =+BC2+1 -> 46098 | BB2: Q | BC2: =+BE2+1 -> 46097 | BD2: Q | BE2: 46096 | BF2: Q | BG2: 46095 | BH2: Q | BI2: 46094 | BJ2: Q | BK2: 46093 | BL2: Q | BM2: 46092 | BN2: Q | BO2: 46091 | BP2: Q | BQ2: 46090 | BR2: Q | BS2: 46089 | BT2: Q | BU2: 46088 | BV2: Q | BW2: =+BY2+1 -> 46087 | BX2: Q | BY2: 46086 | BZ2: Q | CA2: 46085 | CB2: Q | CC2: 46084 | CD2: Q | CE2: 46083 | CF2: Q | CG2: 46082 | CH2: Q | CI2: 46081 | CJ2: Q | CK2: 46080 | CL2: Q | CM2: 46079 | CN2: Q | CO2: 46078 | CP2: Q | CQ2: 46077 | CR2: Q | CS2: 46076
A3: 100000 | B3: 0 | C3: =+$A3*B3 -> 0 | D3: 0 | E3: CERRADO | F3: 0 | G3: SIN ARQUEO | H3: 0 | I3: SIN ARQUEO | J3: 0 | K3: SIN ARQUEO | L3: 0 | M3: CERRADO | N3: 0 | O3: DOMINGO SANTO | P3: 0 | Q3: SÁBADO SANTO | R3: 0 | S3: VIERNES SANTO | T3: 0 | U3: JUEVES SANTO | V3: 0 | W3: =+$A3*V3 -> 0 | X3: 0 | Y3: SIN ARQUEO | Z3: 0 | AA3: SIN ARQUEO | AB3: 0 | AC3: =+$A3*AB3 -> 0 | AD3: 0 | AE3: =+$A3*AD3 -> 0 | AF3: 0 | AG3: =+$A3*AF3 -> 0 | AH3: 0 | AI3: SIN ARQUEO | AJ3: 0 | AK3: SIN ARQUEO | AL3: 0 | AM3: =+$A3*AL3 -> 0 | AN3: 0 | AO3: CERRADO | AP3: 0 | AQ3: CERRADO | AR3: 0 | AS3: =+$A3*AR3 -> 0 | AT3: 0 | AU3: =+$A3*AT3 -> 0 | AV3: 1 | AW3: =+$A3*AV3 -> 100000 | AX3: 0 | AY3: =+$A3*AX3 -> 0 | AZ3: 0 | BA3: =+$A3*AZ3 -> 0 | BC3: SIN ARQUEO | BD3: 0 | BE3: =+$A3*BD3 -> 0 | BF3: 0 | BG3: =+$A3*BF3 -> 0 | BI3: SIN ARQUEO | BJ3: 0 | BK3: =+$A3*BJ3 -> 0 | BL3: 0 | BM3: =+$A3*BL3 -> 0 | BN3: 0 | BO3: =+$A3*BN3 -> 0 | BP3: 2 | BQ3: =+$A3*BP3 -> 200000 | BR3: 0 | BS3: 0 | BT3: 0 | BU3: 0 | BW3: CERRADO | BX3: 0 | BY3: 0 | BZ3: 0 | CA3: 0 | CB3: 0 | CC3: SIN ARQUEO | CD3: 0 | CE3: =+$A3*CD3 -> 0 | CG3: CERRADO | CI3: =+$A3*CH3 -> 0 | CJ3: 1 | CK3: =+$A3*CJ3 -> 100000 | CL3: 0 | CM3: =+$A3*CL3 -> 0 | CN3: 0 | CO3: SIN ARQUEO | CP3: 0 | CQ3: =+$A3*CP3 -> 0 | CR3: 0 | CS3: =+$A3*CR3 -> 0
A4: 50000 | B4: 3 | C4: =+$A4*B4 -> 150000 | D4: 0 | F4: 0 | H4: 0 | J4: 0 | L4: 0 | N4: 0 | P4: 0 | R4: 0 | T4: 0 | V4: 0 | W4: =+$A4*V4 -> 0 | X4: 0 | Z4: 0 | AB4: 0 | AC4: =+$A4*AB4 -> 0 | AD4: 3 | AE4: =+$A4*AD4 -> 150000 | AF4: 0 | AG4: =+$A4*AF4 -> 0 | AH4: 0 | AJ4: 0 | AL4: 0 | AM4: =+$A4*AL4 -> 0 | AN4: 0 | AP4: 0 | AR4: 0 | AS4: =+$A4*AR4 -> 0 | AT4: 0 | AU4: =+$A4*AT4 -> 0 | AV4: 2 | AW4: =+$A4*AV4 -> 100000 | AX4: 0 | AY4: =+$A4*AX4 -> 0 | AZ4: 0 | BA4: =+$A4*AZ4 -> 0 | BD4: 0 | BE4: =+$A4*BD4 -> 0 | BF4: 0 | BG4: =+$A4*BF4 -> 0 | BJ4: 0 | BK4: =+$A4*BJ4 -> 0 | BL4: 0 | BM4: =+$A4*BL4 -> 0 | BN4: 1 | BO4: =+$A4*BN4 -> 50000 | BP4: 0 | BQ4: =+$A4*BP4 -> 0 | BR4: 1 | BS4: =+$A4*BR4 -> 50000 | BT4: 0 | BU4: =+$A4*BT4 -> 0 | BV4: 0 | BX4: 1 | BY4: =+$A4*BX4 -> 50000 | BZ4: 0 | CA4: =+$A4*BZ4 -> 0 | CB4: 1 | CD4: 1 | CE4: =+$A4*CD4 -> 50000 | CF4: 0 | CH4: 0 | CI4: =+$A4*CH4 -> 0 | CJ4: 2 | CK4: =+$A4*CJ4 -> 100000 | CL4: 0 | CM4: =+$A4*CL4 -> 0 | CN4: 1 | CP4: 1 | CQ4: =+$A4*CP4 -> 50000 | CR4: 1 | CS4: =+A4*CR4 -> 50000
A5: 20000 | B5: 4 | C5: =+$A5*B5 -> 80000 | D5: 0 | F5: 0 | H5: 0 | J5: 0 | L5: 0 | N5: 0 | P5: 0 | R5: 0 | T5: 0 | V5: 0 | W5: =+$A5*V5 -> 0 | X5: 0 | Z5: 0 | AB5: 2 | AC5: =+$A5*AB5 -> 40000 | AD5: 6 | AE5: =+$A5*AD5 -> 120000 | AF5: 0 | AG5: =+$A5*AF5 -> 0 | AH5: 0 | AJ5: 0 | AL5: 4 | AM5: =+$A5*AL5 -> 80000 | AN5: 0 | AP5: 0 | AR5: 3 | AS5: =+$A5*AR5 -> 60000 | AT5: 0 | AU5: =+$A5*AT5 -> 0 | AV5: 0 | AW5: =+$A5*AV5 -> 0 | AX5: 0 | AY5: =+$A5*AX5 -> 0 | AZ5: 0 | BA5: =+$A5*AZ5 -> 0 | BD5: 0 | BE5: =+$A5*BD5 -> 0 | BF5: 2 | BG5: =+$A5*BF5 -> 40000 | BJ5: 0 | BK5: =+$A5*BJ5 -> 0 | BL5: 0 | BM5: =+$A5*BL5 -> 0 | BN5: 0 | BO5: =+$A5*BN5 -> 0 | BP5: 0 | BQ5: =+$A5*BP5 -> 0 | BR5: 1 | BS5: =+$A5*BR5 -> 20000 | BT5: 0 | BU5: =+$A5*BT5 -> 0 | BV5: 0 | BX5: 0 | BY5: =+$A5*BX5 -> 0 | BZ5: 0 | CA5: =+$A5*BZ5 -> 0 | CB5: 1 | CD5: 1 | CE5: =+$A5*CD5 -> 20000 | CF5: 0 | CH5: 0 | CI5: =+$A5*CH5 -> 0 | CK5: =+$A5*CJ5 -> 0 | CL5: 4 | CM5: =+$A5*CL5 -> 80000 | CN5: 5 | CP5: 5 | CQ5: =+$A5*CP5 -> 100000 | CR5: 4 | CS5: =+A5*CR5 -> 80000
A6: 10000 | B6: 4 | C6: =+$A6*B6 -> 40000 | D6: 0 | F6: 0 | H6: 0 | J6: 0 | L6: 0 | N6: 0 | P6: 0 | R6: 0 | T6: 0 | V6: 0 | W6: =+$A6*V6 -> 0 | X6: 0 | Z6: 0 | AB6: 5 | AC6: =+$A6*AB6 -> 50000 | AD6: 7 | AE6: =+$A6*AD6 -> 70000 | AF6: 0 | AG6: =+$A6*AF6 -> 0 | AH6: 0 | AJ6: 0 | AL6: 6 | AM6: =+$A6*AL6 -> 60000 | AN6: 0 | AP6: 0 | AR6: 0 | AS6: =+$A6*AR6 -> 0 | AT6: 0 | AU6: =+$A6*AT6 -> 0 | AV6: 1 | AW6: =+$A6*AV6 -> 10000 | AX6: 5 | AY6: =+$A6*AX6 -> 50000 | AZ6: 4 | BA6: =+$A6*AZ6 -> 40000 | BD6: 0 | BE6: =+$A6*BD6 -> 0 | BF6: 4 | BG6: =+$A6*BF6 -> 40000 | BJ6: 1 | BK6: =+$A6*BJ6 -> 10000 | BL6: 0 | BM6: =+$A6*BL6 -> 0 | BN6: 1 | BO6: =+$A6*BN6 -> 10000 | BP6: 2 | BQ6: =+$A6*BP6 -> 20000 | BR6: 1 | BS6: =+$A6*BR6 -> 10000 | BT6: 1 | BU6: =+$A6*BT6 -> 10000 | BV6: 0 | BX6: 2 | BY6: =+$A6*BX6 -> 20000 | BZ6: 4 | CA6: =+$A6*BZ6 -> 40000 | CB6: 4 | CD6: 4 | CE6: =+$A6*CD6 -> 40000 | CF6: 0 | CH6: 5 | CI6: =+$A6*CH6 -> 50000 | CJ6: 1 | CK6: =+$A6*CJ6 -> 10000 | CL6: 1 | CM6: =+$A6*CL6 -> 10000 | CN6: 2 | CP6: 2 | CQ6: =+$A6*CP6 -> 20000 | CR6: 2 | CS6: =+A6*CR6 -> 20000
A7: 5000 | B7: 5 | C7: =+$A7*B7 -> 25000 | D7: 0 | F7: 0 | H7: 0 | J7: 0 | L7: 0 | N7: 0 | P7: 0 | R7: 0 | T7: 0 | V7: 0 | W7: =+$A7*V7 -> 0 | X7: 0 | Z7: 0 | AB7: 6 | AC7: =+$A7*AB7 -> 30000 | AD7: 6 | AE7: =+$A7*AD7 -> 30000 | AF7: 0 | AG7: =+$A7*AF7 -> 0 | AH7: 0 | AJ7: 0 | AL7: 1 | AM7: =+$A7*AL7 -> 5000 | AN7: 0 | AP7: 0 | AR7: 3 | AS7: =+$A7*AR7 -> 15000 | AT7: 6 | AU7: =+$A7*AT7 -> 30000 | AV7: 8 | AW7: =+$A7*AV7 -> 40000 | AX7: 10 | AY7: =+$A7*AX7 -> 50000 | AZ7: 3 | BA7: =+$A7*AZ7 -> 15000 | BD7: 3 | BE7: =+$A7*BD7 -> 15000 | BF7: 8 | BG7: =+$A7*BF7 -> 40000 | BJ7: 3 | BK7: =+$A7*BJ7 -> 15000 | BL7: 5 | BM7: =+$A7*BL7 -> 25000 | BN7: 3 | BO7: =+$A7*BN7 -> 15000 | BP7: 3 | BQ7: =+$A7*BP7 -> 15000 | BR7: 0 | BS7: =+$A7*BR7 -> 0 | BT7: 0 | BU7: =+$A7*BT7 -> 0 | BV7: 0 | BX7: 4 | BY7: =+$A7*BX7 -> 20000 | BZ7: 3 | CA7: =+$A7*BZ7 -> 15000 | CB7: 3 | CD7: 3 | CE7: =+$A7*CD7 -> 15000 | CF7: 0 | CH7: 5 | CI7: =+$A7*CH7 -> 25000 | CJ7: 5 | CK7: =+$A7*CJ7 -> 25000 | CL7: 6 | CM7: =+$A7*CL7 -> 30000 | CN7: 4 | CP7: 4 | CQ7: =+$A7*CP7 -> 20000 | CR7: 2 | CS7: =+A7*CR7 -> 10000
A8: 2000 | B8: 21 | C8: =+$A8*B8 -> 42000 | D8: 0 | F8: 0 | H8: 0 | J8: 0 | L8: 0 | N8: 0 | P8: 0 | R8: 0 | T8: 0 | V8: 17 | W8: =+$A8*V8 -> 34000 | X8: 0 | Z8: 0 | AB8: 13 | AC8: =+$A8*AB8 -> 26000 | AD8: 13 | AE8: =+$A8*AD8 -> 26000 | AF8: 0 | AG8: =+$A8*AF8 -> 0 | AH8: 0 | AJ8: 0 | AL8: 18 | AM8: =+$A8*AL8 -> 36000 | AN8: 0 | AP8: 0 | AR8: 18 | AS8: =+$A8*AR8 -> 36000 | AT8: 21 | AU8: =+$A8*AT8 -> 42000 | AV8: 23 | AW8: =+$A8*AV8 -> 46000 | AX8: 15 | AY8: =+$A8*AX8 -> 30000 | AZ8: 3 | BA8: =+$A8*AZ8 -> 6000 | BD8: 18 | BE8: =+$A8*BD8 -> 36000 | BF8: 23 | BG8: =+$A8*BF8 -> 46000 | BJ8: 20 | BK8: =+$A8*BJ8 -> 40000 | BL8: 25 | BM8: =+$A8*BL8 -> 50000 | BN8: 25 | BO8: =+$A8*BN8 -> 50000 | BP8: 25 | BQ8: =+$A8*BP8 -> 50000 | BR8: 20 | BS8: =+$A8*BR8 -> 40000 | BT8: 23 | BU8: =+$A8*BT8 -> 46000 | BV8: 0 | BX8: 22 | BY8: =+$A8*BX8 -> 44000 | BZ8: 12 | CA8: =+$A8*BZ8 -> 24000 | CB8: 10 | CD8: 10 | CE8: =+$A8*CD8 -> 20000 | CF8: 0 | CH8: 14 | CI8: =+$A8*CH8 -> 28000 | CJ8: 17 | CK8: =+$A8*CJ8 -> 34000 | CL8: 12 | CM8: =+$A8*CL8 -> 24000 | CN8: 5 | CP8: 5 | CQ8: =+$A8*CP8 -> 10000 | CR8: 4 | CS8: =+A8*CR8 -> 8000
A9: 1000 | B9: 2 | C9: =+$A9*B9 -> 2000 | D9: 0 | F9: 0 | H9: 0 | J9: 0 | L9: 0 | N9: 0 | P9: 0 | R9: 0 | T9: 0 | V9: 11 | W9: =+$A9*V9 -> 11000 | X9: 0 | Z9: 0 | AB9: 10 | AC9: =+$A9*AB9 -> 10000 | AD9: 10 | AE9: =+$A9*AD9 -> 10000 | AF9: 0 | AG9: =+$A9*AF9 -> 0 | AH9: 0 | AJ9: 0 | AL9: 6 | AM9: =+$A9*AL9 -> 6000 | AN9: 0 | AP9: 0 | AR9: 6 | AS9: =+$A9*AR9 -> 6000 | AT9: 7 | AU9: =+$A9*AT9 -> 7000 | AV9: 7 | AW9: =+$A9*AV9 -> 7000 | AX9: 14 | AY9: =+$A9*AX9 -> 14000 | AZ9: 3 | BA9: =+$A9*AZ9 -> 3000 | BD9: 9 | BE9: =+$A9*BD9 -> 9000 | BF9: 11 | BG9: =+$A9*BF9 -> 11000 | BJ9: 6 | BK9: =+$A9*BJ9 -> 6000 | BL9: 10 | BM9: =+$A9*BL9 -> 10000 | BN9: 11 | BO9: =+$A9*BN9 -> 11000 | BP9: 6 | BQ9: =+$A9*BP9 -> 6000 | BR9: 9 | BS9: =+$A9*BR9 -> 9000 | BT9: 12 | BU9: =+$A9*BT9 -> 12000 | BV9: 0 | BX9: 16 | BY9: =+$A9*BX9 -> 16000 | BZ9: 20 | CA9: =+$A9*BZ9 -> 20000 | CB9: 0 | CD9: 0 | CE9: =+$A9*CD9 -> 0 | CF9: 0 | CH9: 0 | CI9: =+$A9*CH9 -> 0 | CJ9: 2 | CK9: =+$A9*CJ9 -> 2000 | CL9: 3 | CM9: =+$A9*CL9 -> 3000 | CN9: 8 | CP9: 8 | CQ9: =+$A9*CP9 -> 8000 | CR9: 7 | CS9: =+A9*CR9 -> 7000
A10: 500 | B10: 51 | C10: =+$A10*B10 -> 25500 | D10: 0 | F10: 0 | H10: 0 | J10: 0 | L10: 0 | N10: 0 | P10: 0 | R10: 0 | T10: 0 | V10: 49 | W10: =+$A10*V10 -> 24500 | X10: 0 | Z10: 0 | AB10: 49 | AC10: =+$A10*AB10 -> 24500 | AD10: 49 | AE10: =+$A10*AD10 -> 24500 | AF10: 0 | AG10: =+$A10*AF10 -> 0 | AH10: 0 | AJ10: 0 | AL10: 49 | AM10: =+$A10*AL10 -> 24500 | AN10: 0 | AP10: 0 | AR10: 48 | AS10: =+$A10*AR10 -> 24000 | AT10: 49 | AU10: =+$A10*AT10 -> 24500 | AV10: 49 | AW10: =+$A10*AV10 -> 24500 | AX10: 50 | AY10: =+$A10*AX10 -> 25000 | AZ10: 46 | BA10: =+$A10*AZ10 -> 23000 | BD10: 44 | BE10: =+$A10*BD10 -> 22000 | BF10: 42 | BG10: =+$A10*BF10 -> 21000 | BJ10: 20 | BK10: =+$A10*BJ10 -> 10000 | BL10: 35 | BM10: =+$A10*BL10 -> 17500 | BN10: 21 | BO10: =+$A10*BN10 -> 10500 | BP10: 21 | BQ10: =+$A10*BP10 -> 10500 | BR10: 20 | BS10: =+$A10*BR10 -> 10000 | BT10: 31 | BU10: =+$A10*BT10 -> 15500 | BV10: 0 | BX10: 45 | BY10: =+$A10*BX10 -> 22500 | BZ10: 40 | CA10: =+$A10*BZ10 -> 20000 | CB10: 36 | CD10: 36 | CE10: =+$A10*CD10 -> 18000 | CF10: 0 | CH10: 36 | CI10: =+$A10*CH10 -> 18000 | CJ10: 37 | CK10: =+$A10*CJ10 -> 18500 | CL10: 38 | CM10: =+$A10*CL10 -> 19000 | CN10: 32 | CP10: 32 | CQ10: =+$A10*CP10 -> 16000 | CR10: 31 | CS10: =+A10*CR10 -> 15500
A11: 200 | B11: 21 | C11: =+$A11*B11 -> 4200 | D11: 0 | F11: 0 | H11: 0 | J11: 0 | L11: 0 | N11: 0 | P11: 0 | R11: 0 | T11: 0 | V11: 14 | W11: =+$A11*V11 -> 2800 | X11: 0 | Z11: 0 | AB11: 14 | AC11: =+$A11*AB11 -> 2800 | AD11: 14 | AE11: =+$A11*AD11 -> 2800 | AF11: 0 | AG11: =+$A11*AF11 -> 0 | AH11: 0 | AJ11: 0 | AL11: 9 | AM11: =+$A11*AL11 -> 1800 | AN11: 0 | AP11: 0 | AR11: 9 | AS11: =+$A11*AR11 -> 1800 | AT11: 14 | AU11: =+$A11*AT11 -> 2800 | AV11: 10 | AW11: =+$A11*AV11 -> 2000 | AX11: 10 | AY11: =+$A11*AX11 -> 2000 | AZ11: 25 | BA11: =+$A11*AZ11 -> 5000 | BD11: 13 | BE11: =+$A11*BD11 -> 2600 | BF11: 10 | BG11: =+$A11*BF11 -> 2000 | BJ11: 6 | BK11: =+$A11*BJ11 -> 1200 | BL11: 9 | BM11: =+$A11*BL11 -> 1800 | BN11: 13 | BO11: =+$A11*BN11 -> 2600 | BP11: 7 | BQ11: =+$A11*BP11 -> 1400 | BR11: 4 | BS11: =+$A11*BR11 -> 800 | BT11: 4 | BU11: =+$A11*BT11 -> 800 | BV11: 0 | BX11: 5 | BY11: =+$A11*BX11 -> 1000 | BZ11: 3 | CA11: =+$A11*BZ11 -> 600 | CB11: 81 | CD11: 81 | CE11: =+$A11*CD11 -> 16200 | CF11: 0 | CH11: 68 | CI11: =+$A11*CH11 -> 13600 | CJ11: 62 | CK11: =+$A11*CJ11 -> 12400 | CL11: 62 | CM11: =+$A11*CL11 -> 12400 | CN11: 56 | CP11: 56 | CQ11: =+$A11*CP11 -> 11200 | CR11: 54 | CS11: =+A11*CR11 -> 10800
A12: 100 | B12: 18 | C12: =+$A12*B12 -> 1800 | D12: 0 | F12: 0 | H12: 0 | J12: 0 | L12: 0 | N12: 0 | P12: 0 | R12: 0 | T12: 0 | V12: 20 | W12: =+$A12*V12 -> 2000 | X12: 0 | Z12: 0 | AB12: 15 | AC12: =+$A12*AB12 -> 1500 | AD12: 15 | AE12: =+$A12*AD12 -> 1500 | AF12: 0 | AG12: =+$A12*AF12 -> 0 | AH12: 0 | AJ12: 0 | AL12: 13 | AM12: =+$A12*AL12 -> 1300 | AN12: 0 | AP12: 0 | AR12: 13 | AS12: =+$A12*AR12 -> 1300 | AT12: 13 | AU12: =+$A12*AT12 -> 1300 | AV12: 11 | AW12: =+$A12*AV12 -> 1100 | AX12: 12 | AY12: =+$A12*AX12 -> 1200 | AZ12: 30 | BA12: =+$A12*AZ12 -> 3000 | BD12: 29 | BE12: =+$A12*BD12 -> 2900 | BF12: 29 | BG12: =+$A12*BF12 -> 2900 | BJ12: 17 | BK12: =+$A12*BJ12 -> 1700 | BL12: 15 | BM12: =+$A12*BL12 -> 1500 | BN12: 15 | BO12: =+$A12*BN12 -> 1500 | BP12: 14 | BQ12: =+$A12*BP12 -> 1400 | BR12: 13 | BS12: =+$A12*BR12 -> 1300 | BT12: 13 | BU12: =+$A12*BT12 -> 1300 | BV12: 0 | BX12: 11 | BY12: =+$A12*BX12 -> 1100 | BZ12: 9 | CA12: =+$A12*BZ12 -> 900 | CB12: 77 | CD12: 77 | CE12: =+$A12*CD12 -> 7700 | CF12: 0 | CH12: 63 | CI12: =+$A12*CH12 -> 6300 | CJ12: 48 | CK12: =+$A12*CJ12 -> 4800 | CL12: 51 | CM12: =+$A12*CL12 -> 5100 | CN12: 39 | CP12: 39 | CQ12: =+$A12*CP12 -> 3900 | CR12: 38 | CS12: =+A12*CR12 -> 3800
A13: 50 | B13: 1 | C13: =+$A13*B13 -> 50 | D13: 0 | F13: 0 | H13: 0 | J13: 0 | L13: 0 | N13: 0 | P13: 0 | R13: 0 | T13: 0 | V13: 29 | W13: =+$A13*V13 -> 1450 | X13: 0 | Z13: 0 | AB13: 29 | AC13: =+$A13*AB13 -> 1450 | AD13: 29 | AE13: =+$A13*AD13 -> 1450 | AF13: 0 | AG13: =+$A13*AF13 -> 0 | AH13: 0 | AJ13: 0 | AL13: 12 | AM13: =+$A13*AL13 -> 600 | AN13: 0 | AP13: 0 | AR13: 12 | AS13: =+$A13*AR13 -> 600 | AT13: 12 | AU13: =+$A13*AT13 -> 600 | AV13: 12 | AW13: =+$A13*AV13 -> 600 | AX13: 11 | AY13: =+$A13*AX13 -> 550 | AZ13: 10 | BA13: =+$A13*AZ13 -> 500 | BD13: 10 | BE13: =+$A13*BD13 -> 500 | BF13: 9 | BG13: =+$A13*BF13 -> 450 | BJ13: 7 | BK13: =+$A13*BJ13 -> 350 | BL13: 8 | BM13: =+$A13*BL13 -> 400 | BN13: 8 | BO13: =+$A13*BN13 -> 400 | BP13: 9 | BQ13: =+$A13*BP13 -> 450 | BR13: 11 | BS13: =+$A13*BR13 -> 550 | BT13: 8 | BU13: =+$A13*BT13 -> 400 | BV13: 0 | BX13: 9 | BY13: =+$A13*BX13 -> 450 | BZ13: 9 | CA13: =+$A13*BZ13 -> 450 | CB13: 14 | CD13: 14 | CE13: =+$A13*CD13 -> 700 | CF13: 0 | CH13: 10 | CI13: =+$A13*CH13 -> 500 | CJ13: 10 | CK13: =+$A13*CJ13 -> 500 | CL13: 10 | CM13: =+$A13*CL13 -> 500 | CN13: 10 | CP13: 10 | CQ13: =+$A13*CP13 -> 500 | CR13: 10 | CS13: =+A13*CR13 -> 500
C14: =+SUM(C3:C13) -> 370550 | E14: =+E23 -> 122750 | G14: =+G23 -> -6250 | I14: =+I23 -> 349000 | K14: =+K23 -> 259750 | M14: =+M23 -> 75750 | O14: =+O23 -> 75750 | Q14: =+Q23 -> 75750 | S14: =+S23 -> 75750 | U14: =+U23 -> 75750 | W14: =SUM(W3:W13) -> 75750 | Y14: =+Y23 -> 72250 | AA14: =+AA23 -> 196250 | AC14: =SUM(AC3:AC13) -> 186250 | AE14: =SUM(AE3:AE13) -> 436250 | AG14: =+AG23 -> 314850 | AI14: =+AI23 -> 334850 | AK14: =+AK23 -> 250850 | AM14: =SUM(AM3:AM13) -> 215200 | AO14: =+AO23 -> 144700 | AQ14: =+AQ23 -> 144700 | AS14: =SUM(AS3:AS13) -> 144700 | AU14: =SUM(AU3:AU13) -> 108200 | AW14: =SUM(AW3:AW13) -> 331200 | AY14: =SUM(AY3:AY13) -> 172750 | BA14: =SUM(BA3:BA13) -> 95500 | BC14: =+BC23 -> 172000 | BE14: =SUM(BE3:BE13) -> 88000 | BG14: =SUM(BG3:BG13) -> 203350 | BI14: =+BI23 -> 230450 | BK14: =SUM(BK3:BK13) -> 84250 | BM14: =SUM(BM3:BM13) -> 106200 | BO14: =SUM(BO3:BO13) -> 151000 | BQ14: =+BQ23 -> 100000 | BS14: =SUM(BS3:BS13) -> 141650 | BU14: =SUM(BU3:BU13) -> 86000 | BW14: 0 | BY14: =SUM(BY3:BY13) -> 175050 | CA14: =SUM(CA3:CA13) -> 120950 | CC14: =+CC23 -> 247700 | CE14: =SUM(CE3:CE13) -> 187600 | CG14: 0 | CI14: =SUM(CI3:CI13) -> 141400 | CK14: =+CK23 -> 43100 | CM14: =100000+(315000-10000) -> 405000 | CO14: =+CO23 -> 412900 | CQ14: =+SUM(CQ3:CQ13)+SUM('historial de venta'!G32:G37) -> 315600 | CS14: =+SUM(CS3:CS13) -> 205600
AQ15: =+AS14-AM18 -> 0 | BQ15: 62700 | CA15: 324300
AS16: =+AS18+AQ15 -> 108200 | BA16: =+BA18-BC23 -> 0 | BQ16: =18000+8000+8000 -> 34000
A17: Consepto | C17: =+C1 -> sáb | E17: =+E1 -> vie | G17: =+G1 -> jue | I17: =+I1 -> mié | K17: =+K1 -> mar | M17: =+M1 -> lun | O17: =+O1 -> dom | Q17: =+Q1 -> sáb | S17: =+S1 -> vie | U17: =+U1 -> jue | W17: =+W1 -> mié | Y17: =+Y1 -> mar | AA17: =+AA1 -> lun | AC17: =+AC1 -> dom | AE17: =+AE1 -> sáb | AG17: =+AG1 -> vie | AI17: =+AI1 -> jue | AK17: =+AK1 -> mié | AM17: =+AM1 -> mar | AO17: =+AO1 -> lun | AQ17: =+AQ1 -> dom | AS17: =+AS1 -> sáb | AU17: =+AR1 -> 0 | AW17: =+AW1 -> jue | AY17: =+AY1 -> mié | BA17: =+BA1 -> mar | BC17: =+BC1 -> lun | BE17: =+BE1 -> dom | BG17: =+BG1 -> sáb | BI17: =+BI1 -> vie | BK17: =+BK1 -> jue | BM17: =+BM1 -> mié | BO17: =+BO1 -> mar | BQ17: =+BQ1 -> lun | BS17: =+BS1 -> dom | BU17: =+BU1 -> sáb | BW17: =+BW1 -> vie | BY17: =+BY1 -> jue | CA17: =+CA1 -> mié | CC17: =+CC1 -> mar | CE17: =+CE1 -> lun | CG17: =+CG1 -> dom | CI17: sábado | CK17: viernes | CM17: jueves | CO17: miercoles | CQ17: martes | CS17: lunes
A18: Base | C18: =+E23 -> 122750 | E18: =+G23 -> -6250 | G18: =+I23 -> 349000 | I18: =+K23 -> 259750 | K18: =+M23 -> 75750 | M18: =+O23 -> 75750 | O18: =+Q23 -> 75750 | Q18: =+S23 -> 75750 | S18: =+U23 -> 75750 | U18: =+W23 -> 75750 | W18: =+Y23 -> 72250 | Y18: =+AA23 -> 196250 | AA18: =+AC23 -> 186250 | AC18: =+AE23 -> 436250 | AE18: =+AG23 -> 314850 | AG18: =+AI23 -> 334850 | AI18: =+AK23 -> 250850 | AK18: =+AM23 -> 215200 | AM18: =+AO23 -> 144700 | AO18: =+AQ18 -> 144700 | AQ18: =+AS23 -> 144700 | AS18: =+AU23 -> 108200 | AU18: =+AW23 -> 331200 | AW18: =+AY23 -> 172750 | AY18: =+BA23 -> 95500 | BA18: =+BC23 -> 172000 | BC18: =+BE23 -> 88000 | BE18: =+BG23 -> 149950 | BG18: =+BI23 -> 230450 | BI18: =+BK23 -> 97950 | BK18: =+BM23 -> 88400 | BM18: =+BO23 -> 151000 | BO18: =+BQ23 -> 100000 | BQ18: =+BS23 -> 110200 | BS18: =+BU23 -> 143550 | BU18: =+BY23 -> 131350 | BW18: 0 | BY18: =+CA23 -> 73250 | CA18: =+CC23 -> 247700 | CC18: =+CE23 -> 201400 | CE18: =+CI23 -> 141400 | CG18: 0 | CI18: =+CK23 -> 43100 | CK18: =+CM23 -> 405000 | CM18: =+CO23 -> 412900 | CO18: =+CQ23 -> 315600 | CQ18: =$CS$23 -> 205600 | CS18: 73700
A19: Caja Menor | C19: 0 | E19: 0 | G19: 0 | I19: 40250 | K19: 0 | M19: 0 | O19: 0 | Q19: 0 | S19: 0 | U19: 0 | W19: 0 | Y19: 0 | AA19: 0 | AC19: 0 | AE19: -2600 | AG19: 0 | AI19: 0 | AK19: 0 | AM19: =1800 -> 1800 | AO19: 0 | AU19: 0 | AW19: 0 | AY19: 0 | BA19: -3000 | BC19: 0 | BE19: =+SUM(BM25,BK25,BG25)+2900 -> 60400 | BI19: 0 | BK19: 0 | BM19: 0 | BO19: 0 | BQ19: =-SUM(CE25,CA25,BY25,BU25,BS25)-1200 -> -52700 | BW19: 0 | BY19: 0 | CC19: 0 | CE19: 0 | CG19: 0 | CI19: 88200 | CK19: -7900 | CM19: -7900 | CO19: 0 | CQ19: -3000 | CS19: 0
A20: Venta | C20: 282000 | E20: 153000 | G20: 68000 | I20: 134000 | K20: 247000 | M20: 0 | O20: 0 | Q20: 0 | S20: 0 | U20: 0 | W20: 3500 | Y20: 76000 | AA20: 30000 | AC20: 0 | AE20: 139000 | AG20: 0 | AI20: 104000 | AK20: 58500 | AM20: =130700+8000 -> 138700 | AO20: 0 | AS20: 126500 | AU20: 107000 | AW20: 207700 | AY20: 77250 | BA20: 176500 | BC20: 99000 | BE20: 99000 | BG20: 271000 | BI20: =Registros!$C$13 -> 132500 | BK20: =67000+24000 -> 91000 | BM20: 338500 | BO20: 51000 | BQ20: 172500 | BS20: 123500 | BU20: 225500 | BW20: 0 | BY20: 143500 | CA20: =260000-18000-8000 -> 234000 | CC20: 105000 | CE20: 60000 | CG20: 0 | CI20: 456500 | CK20: 186000 | CM20: 84000 | CO20: 344000 | CQ20: 213000 | CS20: 191900
A21: Gastos | C21: 14400 | E21: =16000+8000 -> 24000 | G21: 0 | I21: 0 | K21: 63000 | M21: 0 | O21: 0 | Q21: 0 | S21: 0 | U21: 0 | W21: 0 | Y21: 0 | AA21: 20000 | AC21: 0 | AE21: 15000 | AG21: 20000 | AI21: 20000 | AK21: 22850 | AM21: 70000 | AO21: 0 | AS21: =70000+20000 -> 90000 | AU21: =30000+70000 -> 100000 | AW21: =13500+7800+27950 -> 49250 | BC21: 15000 | BE21: =Gas!$C$15 -> 221350 | BG21: =30000+120000+50000+51500 -> 251500 | BK21: =4500+21600 -> 26100 | BM21: =140000+1000+20500+55800+43800+40000 -> 301100 | BO21: 0 | BQ21: 30000 | BS21: =10000+20000+26850 -> 56850 | BU21: 213300 | BW21: 0 | BY21: =38050+17000+7450+22400+500 -> 85400 | CA21: =20000+124400+3500+11000+16500+46350+50000+14000 -> 285750 | CC21: =30000+28700 -> 58700 | CE21: 0 | CG21: 0 | CI21: =20000+70000+6400 -> 96400 | CK21: =10000+70000+20000+20000+(120000) -> 240000 | CM21: =$CM$20 -> 84000 | CO21: =70000+36700+120000+20000 -> 246700 | CQ21: 100000 | CS21: =60000 -> 60000
A22: Retiros | C22: 0 | E22: 0 | G22: 423250 | I22: =65000+20000 -> 85000 | K22: 0 | M22: 0 | O22: 0 | Q22: 0 | S22: 0 | U22: 0 | W22: 0 | Y22: 200000 | AA22: 0 | AC22: 250000 | AE22: 0 | AG22: 0 | AI22: 0 | AK22: 0 | AM22: 0 | AO22: 0 | AQ22: 0 | AS22: 0 | AU22: 230000 | AW22: 0 | AY22: 0 | BA22: 250000 | BG22: 100000 | BK22: =4000+51350 -> 55350 | BM22: 100000 | BO22: 0 | BQ22: 100000 | BS22: 100000 | BW22: 0 | CA22: 122700 | CC22: 0 | CE22: 0 | CG22: 0 | CI22: =350000 -> 350000 | CK22: 300000
C23: =+SUM(C18:C20)-SUM(C21:C22) -> 390350 | E23: =+SUM(E18:E20)-SUM(E21:E22) -> 122750 | G23: =+SUM(G18:G20)-SUM(G21:G22) -> -6250 | I23: =+SUM(I18:I20)-SUM(I21:I22) -> 349000 | K23: =+SUM(K18:K20)-SUM(K21:K22) -> 259750 | M23: =+SUM(M18:M20)-SUM(M21:M22) -> 75750 | O23: =+SUM(O18:O20)-SUM(O21:O22) -> 75750 | Q23: =+SUM(Q18:Q20)-SUM(Q21:Q22) -> 75750 | S23: =+SUM(S18:S20)-SUM(S21:S22) -> 75750 | U23: =+SUM(U18:U20)-SUM(U21:U22) -> 75750 | W23: =+SUM(W18:W20)-SUM(W21:W22) -> 75750 | Y23: =+SUM(Y18:Y20)-SUM(Y21:Y22) -> 72250 | AA23: =+SUM(AA18:AA20)-SUM(AA21:AA22) -> 196250 | AC23: =+SUM(AC18:AC20)-SUM(AC21:AC22) -> 186250 | AE23: =+SUM(AE18:AE20)-SUM(AE21:AE22) -> 436250 | AG23: =+SUM(AG18:AG20)-SUM(AG21:AG22) -> 314850 | AI23: =+SUM(AI18:AI20)-SUM(AI21:AI22) -> 334850 | AK23: =+SUM(AK18:AK20)-SUM(AK21:AK22) -> 250850 | AM23: =+SUM(AM18:AM20)-SUM(AM21:AM22) -> 215200 | AO23: =+SUM(AO18:AO20)-SUM(AO21:AO22) -> 144700 | AQ23: =+SUM(AQ18:AQ20)-SUM(AQ21:AQ22) -> 144700 | AS23: =+SUM(AS18:AS20)-SUM(AS21:AS22) -> 144700 | AU23: =+SUM(AU18:AU20)-SUM(AU21:AU22) -> 108200 | AW23: =+SUM(AW18:AW20)-SUM(AW21:AW22) -> 331200 | AY23: =+SUM(AY18:AY20)-SUM(AY21:AY22) -> 172750 | BA23: =+SUM(BA18:BA20)-SUM(BA21:BA22) -> 95500 | BC23: =+SUM(BC18:BC20)-SUM(BC21:BC22) -> 172000 | BE23: =+SUM(BE18:BE20)-SUM(BE21:BE22) -> 88000 | BG23: =+SUM(BG18:BG20)-SUM(BG21:BG22) -> 149950 | BI23: =+SUM(BI18:BI20)-SUM(BI21:BI22) -> 230450 | BK23: =+SUM(BK18:BK20)-SUM(BK21:BK22) -> 97950 | BM23: =+SUM(BM18:BM20)-SUM(BM21:BM22) -> 88400 | BO23: =+SUM(BO18:BO20)-SUM(BO21:BO22) -> 151000 | BQ23: =+SUM(BQ18:BQ20)-SUM(BQ21:BQ22) -> 100000 | BS23: =+SUM(BS18:BS20)-SUM(BS21:BS22) -> 110200 | BU23: =+SUM(BU18:BU20)-BU21 -> 143550 | BW23: 0 | BY23: =+SUM(BY18:BY20)-BY21 -> 131350 | CA23: =+SUM(CA18:CA20)-SUM(CA21:CA22) -> 73250 | CC23: =+SUM(CC18:CC20)-SUM(CC21:CC22) -> 247700 | CE23: =+SUM(CE18:CE20)-SUM(CE21:CE22) -> 201400 | CG23: 0 | CI23: =+SUM(CI18:CI20)-SUM(CI21:CI22) -> 141400 | CK23: =+SUM(CK18:CK20)-SUM(CK21:CK22) -> 43100 | CM23: =+SUM(CM18:CM20)-CM21 -> 405000 | CO23: =+CO18+CO20-CO21 -> 412900 | CQ23: =+SUM(CQ18:CQ20)-SUM(CQ21:CQ22) -> 315600 | CS23: =+CS18+CS20-CS21 -> 205600
A25: Diferencia | C25: =C14-C23 -> -19800 | E25: =E14-E23 -> 0 | G25: =G14-G23 -> 0 | I25: =I14-I23 -> 0 | K25: =K14-K23 -> 0 | M25: =M14-M23 -> 0 | O25: =O14-O23 -> 0 | Q25: =Q14-Q23 -> 0 | S25: =S14-S23 -> 0 | U25: =U14-U23 -> 0 | W25: =W14-W23 -> 0 | Y25: =Y14-Y23 -> 0 | AA25: =AA14-AA23 -> 0 | AC25: =AC14-AC23 -> 0 | AE25: =AE14-AE23 -> 0 | AG25: =AG14-AG23 -> 0 | AI25: =AI14-AI23 -> 0 | AK25: =AK14-AK23 -> 0 | AM25: =AM14-AM23 -> 0 | AO25: =AO14-AO23 -> 0 | AQ25: =AQ14-AQ23 -> 0 | AS25: =AS14-AS23 -> 0 | AU25: =AU14-AU23 -> 0 | AW25: =AW14-AW23 -> 0 | AY25: =AY14-AY23 -> 0 | BA25: =BA14-BA23 -> 0 | BC25: =BC14-BC23 -> 0 | BE25: =BE14-BE23 -> 0 | BG25: =BG14-BG23 -> 53400 | BI25: =BI14-BI23 -> 0 | BK25: =BK14-BK23 -> -13700 | BM25: =BM14-BM23 -> 17800 | BO25: =BO14-BO23 -> 0 | BQ25: =BQ14-BQ23 -> 0 | BS25: =BS14-BS23 -> 31450 | BU25: =BU14-BU23 -> -57550 | BW25: =BW14-BW23 -> 0 | BY25: =BY14-BY23 -> 43700 | CA25: =CA14-CA23 -> 47700 | CC25: =CC14-CC23 -> 0 | CE25: =CE14-CE23 -> -13800 | CG25: =CG14-CG23 -> 0 | CI25: =CI14-CI23 -> 0 | CK25: =CK14-CK23 -> 0 | CM25: =CM14-CM23 -> 0 | CO25: =CO14-CO23 -> 0 | CQ25: =CQ14-CQ23 -> 0 | CS25: =CS14-CS23 -> 0
A27: Caja Menor EA | C27: 0 | E27: 0 | G27: 0 | I27: 0 | K27: 0 | M27: 0 | O27: 0 | Q27: 0 | S27: 0 | U27: 0 | W27: 0 | Y27: 0 | AA27: 0 | AC27: 0 | AE27: 0 | AG27: 0 | AI27: 0 | AK27: 0 | AM27: 0 | AO27: 0 | AQ27: 0 | AS27: 0 | AU27: 0 | AW27: 0 | AY27: 0 | BA27: =+BC27+BA22 -> 344950 | BC27: =+BE27 -> 94950 | BE27: =+BG27-50000 -> 94950 | BG27: =+BI27+BG22 -> 144950 | BI27: =+BK27 -> 44950 | BK27: =+BM27-43000 -> 44950 | BM27: =100000-12050 -> 87950 | BO27: =100000-12050 -> 87950 | BQ27: =+BQ22 -> 100000 | BS27: 0 | BU27: 0 | BW27: 0 | BY27: 0 | CA27: 0 | CC27: 0 | CE27: 0 | CG27: 0 | CI27: 0 | CK27: 0 | CM27: 0 | CO27: 0 | CQ27: 0 | CS27: 0
A28: Caja Menor JG | C28: 0 | E28: 0 | G28: 0 | I28: 0 | K28: 0 | M28: 0 | O28: 0 | Q28: 0 | S28: 0 | U28: 0 | W28: 0 | Y28: 0 | AA28: 0 | AC28: 0 | AE28: 0 | AG28: 0 | AI28: 0 | AK28: 0 | AM28: 0 | AO28: 0 | AQ28: 0 | AS28: 0 | AU28: =+AW28 -> 0 | AW28: =+AY28 -> 0 | AY28: =+BA28 -> 0 | BA28: =+BC28 -> 0 | BC28: =+BE28 -> 0 | BE28: =+BG28 -> 0 | BG28: =+BI28 -> 0 | BI28: =+BK28 -> 0 | BK28: =+BM28-100000 -> 0 | BM28: =+BM22 -> 100000 | BO28: 0 | BQ28: 0 | BS28: 0 | BU28: =+BU22+BW28-BU31 -> 0 | BW28: =+BW22+BY28-BW31 -> 0 | BY28: 0 | CA28: =+CC28-370000 -> 0 | CC28: =+CC22+CE28 -> 370000 | CE28: =+CE22+CG28 -> 370000 | CG28: =+CG22+CI28 -> 370000 | CI28: =+CI22+CK28-CI31 -> 370000 | CK28: =+CK22 -> 300000 | CM28: 0 | CO28: 0 | CQ28: 0 | CS28: 0
A30: NEQUI - venta | C30: 19000 | E30: 104000 | G30: 8000 | I30: 27000 | K30: 19000 | M30: 0 | O30: 0 | Q30: 0 | S30: 0 | U30: 0 | W30: =4500*20 -> 90000 | Y30: 0 | AA30: 85500 | AC30: 211000 | AE30: 86000 | AG30: 0 | AI30: 24000 | AK30: 48000 | AM30: 127000 | AO30: 0 | AQ30: 0 | AS30: 11000 | AU30: 65700 | AW30: 169800 | AY30: =71000 -> 71000 | BA30: =78000+32000 -> 110000 | BC30: =11000+10000 -> 21000 | BE30: =19000+(45000-9000) -> 55000 | BG30: =+(98000-5000) -> 93000 | BI30: 0 | BK30: 70000 | BM30: 113000 | BO30: =43000-2000 -> 41000 | BQ30: 0 | BS30: =92000+16000+30000 -> 138000 | BU30: =43000+28000 -> 71000 | BW30: 0 | BY30: =115500+16000 -> 131500 | CA30: =83000+18000+8000+8000 -> 117000 | CC30: =33000+27000+20000 -> 80000 | CE30: 0 | CG30: 0 | CI30: 47000 | CK30: 45000 | CM30: 125000 | CO30: 46500 | CQ30: =8000+3000 -> 11000 | CS30: =24000+6500 -> 30500
A31: NEQUI - transfer/egreso | C31: 0 | E31: 0 | G31: 0 | I31: 0 | K31: 0 | M31: 0 | O31: 0 | Q31: 0 | S31: 0 | U31: -60000 | W31: =-350000 -> -350000 | Y31: 0 | AA31: 0 | AC31: =-363853+AC22 -> -113853 | AE31: 0 | AG31: 0 | AI31: 0 | AK31: =-114000-40000 -> -154000 | AM31: 0 | AO31: 0 | AQ31: 0 | AS31: 0 | AU31: =AU22-21000 -> 209000 | AW31: =-404000-50000 -> -454000 | AY31: =+BA27-260500 -> 84450 | BA31: =-60000 -> -60000 | BM31: 0 | BO31: =-BO34-412000 -> -322000 | BQ31: 0 | BS31: 0 | BU31: 0 | BW31: 0 | BY31: 0 | CA31: 0 | CC31: -619850 | CE31: 0 | CG31: 0 | CI31: 280000 | CK31: 0 | CM31: 0 | CO31: 0 | CQ31: 0 | CS31: 0
A32: NEQUI Acum. | C32: =+E32+SUM(C30:C31) -> 951247 | E32: =+G32+SUM(E30:E31) -> 932247 | G32: =+I32+SUM(G30:G31) -> 828247 | I32: =+K32+SUM(I30:I31) -> 820247 | K32: =+M32+SUM(K30:K31) -> 793247 | M32: =+O32+SUM(M30:M31) -> 774247 | O32: =+Q32+SUM(O30:O31) -> 774247 | Q32: =+S32+SUM(Q30:Q31) -> 774247 | S32: =+U32+SUM(S30:S31) -> 774247 | U32: =+W32+SUM(U30:U31) -> 774247 | W32: =+Y32+SUM(W30:W31) -> 834247 | Y32: =+AA32+SUM(Y30:Y31) -> 1094247 | AA32: =+AC32+SUM(AA30:AA31) -> 1094247 | AC32: =+AE32+SUM(AC30:AC31) -> 1008747 | AE32: =+AG32+SUM(AE30:AE31) -> 911600 | AG32: =+AI32+SUM(AG30:AG31) -> 825600 | AI32: =+AK32+SUM(AI30:AI31) -> 825600 | AK32: =+AM32+SUM(AK30:AK31) -> 801600 | AM32: =+AO32+SUM(AM30:AM31) -> 907600 | AO32: =+AS32+SUM(AO30:AO31) -> 780600 | AQ32: =+AS32+SUM(AQ30:AQ31) -> 780600 | AS32: =+AU32+SUM(AS30:AS31) -> 780600 | AU32: =+AW32+SUM(AU30:AU31) -> 769600 | AW32: =+AY32+SUM(AW30:AW31) -> 494900 | AY32: =+BA32+SUM(AY30:AY31) -> 779100 | BA32: =+BC32+SUM(BA30:BA31) -> 623650 | BC32: =+BE32+SUM(BC30:BC31) -> 573650 | BE32: =+BG32+SUM(BE30:BE31) -> 552650 | BG32: =+BI32+SUM(BG30:BG31) -> 497650 | BI32: =+BK32+SUM(BI30:BI31) -> 404650 | BK32: =+BM32+SUM(BK30:BK31) -> 404650 | BM32: =+BO32+SUM(BM30:BM31) -> 334650 | BO32: =+BQ32+SUM(BO30:BO31) -> 221650 | BQ32: =+BS32+SUM(BQ30:BQ31) -> 502650 | BS32: =+BU32+SUM(BS30:BS31) -> 502650 | BU32: =+BW32+SUM(BU30:BU31) -> 364650 | BW32: =+BY32+SUM(BW30:BW31) -> 293650 | BY32: =+CA32+SUM(BY30:BY31) -> 293650 | CA32: =+CC32+SUM(CA30:CA31) -> 162150 | CC32: =+CE32+SUM(CC30:CC31) -> 45150 | CE32: =+CG32+SUM(CE30:CE31) -> 585000 | CG32: =+CI32+SUM(CG30:CG31) -> 585000 | CI32: =+CK32+SUM(CI30:CI31) -> 585000 | CK32: =+CM32+SUM(CK30:CK31) -> 258000 | CM32: =+CO32+SUM(CM30:CM31) -> 213000 | CO32: =+CQ32+SUM(CO30:CO31) -> 88000 | CQ32: =+CS32+SUM(CQ30:CQ31) -> 41500 | CS32: =SUM(CS30:CS31) -> 30500
A33: DaviPLATA | C33: 0 | E33: 0 | G33: 11000 | I33: 0 | K33: 0 | M33: 0 | O33: 0 | Q33: 0 | S33: 0 | U33: 0 | W33: 0 | Y33: 0 | AA33: 0 | AC33: 0 | AE33: 0 | AG33: 0 | AI33: 0 | AK33: 11000 | AM33: 27000 | AO33: 0 | AQ33: 0 | AS33: 0 | AU33: 0 | AW33: 11000 | AY33: 0 | BA33: =15000+8000 -> 23000 | BC33: 0 | BE33: 0 | BG33: =23000 -> 23000 | BI33: 0 | BK33: 82000 | BM33: =22000+1000 -> 23000 | BO33: 0 | BQ33: 0 | BS33: =3000 -> 3000 | BU33: 0 | BW33: 0 | BY33: 0 | CA33: 0 | CC33: 11000 | CE33: 0 | CG33: 0 | CI33: 0 | CK33: 11000 | CM33: 0 | CO33: 16000 | CQ33: 0 | CS33: 0
A34: NEQUI - transfer/egreso | BA34: 0 | BC34: 0 | BM34: 0 | BO34: -90000 | BQ34: 76000 | BS34: 0 | CA34: 0 | CC34: -27000 | CE34: 0 | CG34: 0 | CI34: 0 | CK34: 0 | CM34: 0 | CO34: 0 | CQ34: 0 | CS34: 0
A35: DaviPLATA Acum. | C35: =+C33+E35 -> 211000 | E35: =+E33+G35 -> 211000 | G35: =+G33+I35 -> 211000 | I35: =+I33+K35 -> 200000 | K35: =+K33+M35 -> 200000 | M35: =+M33+O35 -> 200000 | O35: =+O33+Q35 -> 200000 | Q35: =+Q33+S35 -> 200000 | S35: =+S33+U35 -> 200000 | U35: =+U33+W35 -> 200000 | W35: =+W33+Y35 -> 200000 | Y35: =+Y33+AA35 -> 200000 | AA35: =+AA33+AC35 -> 200000 | AC35: =+AC33+AE35 -> 200000 | AE35: =+AE33+AG35 -> 200000 | AG35: =+AG33+AI35 -> 200000 | AI35: =+AI33+AK35 -> 200000 | AK35: =+AK33+AM35 -> 200000 | AM35: =+AM33+AO35 -> 189000 | AO35: =+AO33+AS35 -> 162000 | AQ35: =+AQ33+AS35 -> 162000 | AS35: =+AS33+AU35 -> 162000 | AU35: =+AU33+AW35 -> 162000 | AW35: =+AW33+AY35 -> 162000 | AY35: =+AY33+BA35 -> 151000 | BA35: =+BA33+BC35 -> 151000 | BC35: =+BC33+BE35 -> 128000 | BE35: =+BE33+BG35 -> 128000 | BG35: =+BG33+BI35 -> 128000 | BI35: =+BI33+BK35 -> 105000 | BK35: =+BK33+BM35 -> 105000 | BM35: =+BM33 -> 23000 | BO35: =+BQ35+SUM(BO33:BO34) -> 0 | BQ35: =+BS35+SUM(BQ33:BQ34) -> 90000 | BS35: =+BU35+SUM(BS33:BS34) -> 14000 | BU35: =+BW35+SUM(BU33:BU34) -> 11000 | BW35: =+BY35+SUM(BW33:BW34) -> 11000 | BY35: =+CA35+SUM(BY33:BY34) -> 11000 | CA35: =+CC35+SUM(CA33:CA34) -> 11000 | CC35: =+CE35+SUM(CC33:CC34) -> 11000 | CE35: =+CE33+CG35 -> 27000 | CG35: =+CG33+CI35 -> 27000 | CI35: =+CI33+CK35 -> 27000 | CK35: =+CK33+CM35 -> 27000 | CM35: =+CM33+CO35 -> 16000 | CO35: =+CO33+CQ35 -> 16000 | CQ35: =+CQ33+CS35 -> 0 | CS35: =+CS33 -> 0
A36: CXC | C36: =+E36 -> 34000 | E36: =+G36 -> 34000 | G36: =+I36 -> 34000 | I36: =+K36 -> 34000 | K36: =+M36 -> 34000 | M36: =+O36 -> 34000 | O36: =+Q36 -> 34000 | Q36: =+S36 -> 34000 | S36: =+U36 -> 34000 | U36: =+W36 -> 34000 | W36: =+Y36 -> 34000 | Y36: =+AA36 -> 34000 | AA36: =+AC36 -> 34000 | AC36: =+AE36 -> 34000 | AE36: =+TICO!F19 -> 34000
A38: Venta | C38: =+C20+C30+C33 -> 301000 | E38: =+E20+E30+E33 -> 257000 | G38: =+G20+G30+G33 -> 87000 | I38: =+I20+I30+I33 -> 161000 | K38: =+K20+K30+K33 -> 266000 | M38: =+M20+M30+M33 -> 0 | O38: =+O20+O30+O33 -> 0 | Q38: =+Q20+Q30+Q33 -> 0 | S38: =+S20+S30+S33 -> 0 | U38: =+U20+U30+U33 -> 0 | W38: =+W20+W30+W33 -> 93500 | Y38: =+Y20+Y30+Y33 -> 76000 | AA38: =+AA20+AA30+AA33 -> 115500 | AC38: =+AC20+AC30+AC33 -> 211000 | AE38: =+AE20+AE30+AE33+AE36 -> 259000 | AG38: =+AG20+AG30+AG33 -> 0 | AI38: =+AI20+AI30+AI33 -> 128000 | AK38: =+AK20+AK30+AK33 -> 117500 | AM38: =+AM20+AM30+AM33 -> 292700 | AO38: =+AO20+AO30+AO33 -> 0 | AQ38: =+AQ20+AQ30+AQ33 -> 0 | AS38: =+AS20+AS30+AS33 -> 137500 | AU38: =+AU20+AU30+AU33 -> 172700 | AW38: =+AW20+AW30+AW33 -> 388500 | AY38: =+AY20+AY30+AY33 -> 148250 | BA38: =+BA20+BA30+BA33 -> 309500 | BC38: =+BC20+BC30+BC33 -> 120000 | BE38: =+BE20+BE30+BE33 -> 154000 | BG38: =+BG20+BG30+BG33 -> 387000 | BI38: =+BI20+BI30+BI33 -> 132500 | BK38: =+BK20+BK30+BK33 -> 243000 | BM38: =+BM20+BM30+BM33 -> 474500 | BO38: =+BO20+BO30+BO33 -> 92000 | BQ38: =+BQ20+BQ30+BQ33 -> 172500 | BS38: =+BS20+BS30+BS33 -> 264500 | BU38: =+BU20+BU30+BU33 -> 296500 | BW38: =+BW20+BW30+BW33 -> 0 | BY38: =+BY20+BY30+BY33 -> 275000 | CA38: =+CA20+CA30+CA33 -> 351000 | CC38: =+CC20+CC30+CC33 -> 196000 | CE38: =+CE20+CE30+CE33 -> 60000 | CG38: =+CG20+CG30+CG33 -> 0 | CI38: =+CI20+CI30+CI33 -> 503500 | CK38: =+CK20+CK30+CK33 -> 242000 | CM38: =+CM20+CM30+CM33 -> 209000 | CO38: =+CO20+CO30+CO33 -> 406500 | CQ38: =+CQ20+CQ30+CQ33 -> 224000 | CS38: =+CS20+CS30+CS33 -> 222400
A39: Acumulado | C39: =+C23+C32+C35 -> 1552597 | E39: =+E23+E32+E35 -> 1265997 | G39: =+G23+G32+G35 -> 1032997 | I39: =+I23+I32+I35 -> 1369247 | K39: =+K23+K32+K35 -> 1252997 | M39: =+M23+M32+M35 -> 1049997 | O39: =+O23+O32+O35 -> 1049997 | Q39: =+Q23+Q32+Q35 -> 1049997 | S39: =+S23+S32+S35 -> 1049997 | U39: =+U23+U32+U35 -> 1049997 | W39: =+W23+W32+W35 -> 1109997 | Y39: =+Y23+Y32+Y35 -> 1366497 | AA39: =+AA23+AA32+AA35 -> 1490497 | AC39: =+AC23+AC32+AC35 -> 1394997 | AE39: =+AE23+AE32+AE35 -> 1547850 | AG39: =+AG23+AG32+AG35 -> 1340450 | AI39: =+AI23+AI32+AI35 -> 1360450 | AK39: =+AK23+AK32+AK35 -> 1252450 | AM39: =+AM23+AM32+AM35 -> 1311800 | AO39: =+AO23+AO32+AO35 -> 1087300 | AQ39: =+AQ23+AQ32+AQ35 -> 1087300 | AS39: =+AS23+AS32+AS35 -> 1087300 | AU39: =+AU23+AU32+AU35 -> 1039800 | AW39: =+AW23+AW32+AW35 -> 988100 | AY39: =+AY23+AY32+AY35 -> 1102850 | BA39: =+BA23+BA32+BA35 -> 870150 | BC39: =+BC23+BC32+BC35 -> 873650 | BE39: =+BE23+BE32+BE35 -> 768650 | BG39: =+BG23+BG32+BG35 -> 775600 | BI39: =+BI23+BI32+BI35 -> 740100 | BK39: =+BK23+BK32+BK35 -> 607600 | BM39: =+BM23+BM32+BM35 -> 446050 | BO39: =+BO23+BO32+BO35 -> 372650 | BQ39: =+BQ23+BQ32+BQ35 -> 692650 | BS39: =+BS23+BS32+BS35 -> 626850 | BU39: =+BU23+BU32+BU35 -> 519200 | BW39: =+BY39 -> 436000 | BY39: =+BY23+BY32+BY35 -> 436000 | CA39: =+CA23+CA32+CA35 -> 246400 | CC39: =+CC23+CC32+CC35 -> 303850 | CE39: =+CE23+CE32+CE35 -> 813400 | CG39: =+CI39 -> 753400 | CI39: =+CI23+CI32+CI35 -> 753400 | CK39: =+CK23+CK32+CK35 -> 328100 | CM39: =+CM23+CM32+CM35 -> 634000 | CO39: =+CO23+CO32+CO35 -> 516900 | CQ39: =+CQ23+CQ32+CQ35 -> 357100 | CS39: =+CS23+CS32+CS35 -> 236100
A41: CXP | C41: 77612 | E41: 77612 | G41: =+I41 -> 423300 | I41: =+K41 -> 423300 | K41: =+M41 -> 423300 | M41: =+O41 -> 423300 | O41: =+Q41 -> 423300 | Q41: =+S41 -> 423300 | S41: =+U41 -> 423300 | U41: =+W41 -> 423300 | W41: =+Y41 -> 423300 | Y41: =+AA41 -> 423300 | AA41: =+AC41 -> 423300 | AC41: =+AE41 -> 423300 | AE41: =+AG41 -> 423300 | AG41: =+AI41 -> 423300 | AI41: =+AK41 -> 423300 | AK41: =+AM41 -> 423300 | AM41: =+AQ41 -> 423300 | AO41: =+AS41 -> 423300 | AQ41: =+AS41 -> 423300 | AS41: =+AU41 -> 423300 | AU41: 423300
AU42: dairoc
AU43: cepeda

Sheet Extracto
C1: Nequi | D1: =+SUMIF($H$7:$H$1048576,C1,$D$7:$D$1048576) -> 932247
C2: DaviPlata | D2: =+SUMIF($H$7:$H$1048576,C2,$D$7:$D$1048576) -> 211000
D3: =+SUM(D7:D1048576) -> 1143247 | H3: Total
D5: =+SUBTOTAL(9,D7:D1048576) -> 1143247
A6: fecha | B6: dia_sem | C6: hora | D6: valor | E6: Sopor. | F6: fact | G6: Estado | H6: cuenta | I6: nombre_cliente | J6: telefono
A7: 46076 | B7: =+TEXT(A7,"ddd") -> lun | C7: 0.72986111 | D7: 6500 | E7: fact | H7: Nequi | I7: Papá | J7: Error
A8: 46076 | B8: =+TEXT(A8,"ddd") -> lun | D8: 24000 | E8: fact | H8: Nequi | I8: Diana Carolina Colorado Penagos
A9: 46077 | B9: =+TEXT(A9,"ddd") -> mar | C9: 0.79375 | D9: 3000 | E9: fact | F9: 00024 | H9: Nequi | I9: Lucelyz Pelaez
A10: 46077 | B10: =+TEXT(A10,"ddd") -> mar | C10: 0.82777778 | D10: 8000 | E10: fact | F10: 00024 | H10: Nequi | I10: Jeisson Gutierrez
A11: 46078 | B11: =+TEXT(A11,"ddd") -> mié | C11: 0.69444444 | D11: 8000 | E11: fact | H11: Nequi | I11: María Torres
A12: 46078 | B12: =+TEXT(A12,"ddd") -> mié | C12: 0.79444444 | D12: 8000 | E12: fact | H12: Nequi | I12: Ori****Rod*****Ma | J12: Breb-B
A13: 46078 | B13: =+TEXT(A13,"ddd") -> mié | C13: 0.80694444 | D13: 22500 | E13: fact | H13: Nequi | I13: Papá | J13: Error
A14: 46078 | B14: =+TEXT(A14,"ddd") -> mié | C14: 0.83958333 | D14: 8000 | E14: fact | H14: Nequi | I14: Juan Heredia
A15: 46078 | B15: =+TEXT(A15,"ddd") -> mié | C15: 0.79375 | D15: 16000 | E15: fact | H15: DaviPlata | I15: ND | J15: DaviPlata
A16: 46079 | B16: =+TEXT(A16,"ddd") -> jue | C16: 0.56458333 | D16: 25000 | E16: fact | H16: Nequi | I16: Claudia Arevalo | J16: 322 381 0697
A17: 46079 | B17: =+TEXT(A17,"ddd") -> jue | C17: 0.84513889 | D17: 51000 | E17: fact | H17: Nequi | I17: Papá | J17: Error
A18: 46079 | B18: =+TEXT(A18,"ddd") -> jue | C18: 0.72777778 | D18: 49000 | E18: fact | H18: Nequi | I18: Darwin Casallas
A19: 46080 | B19: =+TEXT(A19,"ddd") -> vie | C19: 0.82291667 | D19: 11000 | E19: fact | H19: DaviPlata | I19: ND | J19: DaviPlata
A20: 46080 | B20: =+TEXT(A20,"ddd") -> vie | C20: 0.84236111 | D20: 10000 | E20: fact | H20: Nequi | I20: David Aparicio
A21: 46080 | B21: =+TEXT(A21,"ddd") -> vie | C21: 0.76319444 | D21: 24000 | E21: fact | H21: Nequi | I21: Natalia Bolivar
A22: 46080 | B22: =+TEXT(A22,"ddd") -> vie | C22: 0.75972222 | D22: 11000 | E22: fact | H22: Nequi | I22: Carlos Gonzalez
A23: 46081 | B23: =+TEXT(A23,"ddd") -> sáb | D23: 280000 | E23: fact | H23: Nequi | I23: Consignación a Edwin | J23: Consignación
A24: 46081 | B24: =+TEXT(A24,"ddd") -> sáb | C24: 0.79305556 | D24: 18000 | E24: fact | H24: Nequi | I24: Mel**** ***Alb Vil*** | J24: Breb-B
A25: 46081 | B25: =+TEXT(A25,"ddd") -> sáb | C25: 0.65208333 | D25: 16000 | E25: fact | H25: Nequi | I25: María Barrios | J25: 315 826 7681
A26: 46081 | B26: =+TEXT(A26,"ddd") -> sáb | C26: 0.65138889 | D26: 13000 | E26: fact | H26: Nequi | I26: David Aparicio | J26: 321 923 1130
A27: 46084 | B27: =+TEXT(A27,"ddd") -> mar | D27: =-(D19+D15) -> -27000 | E27: Nd-Nc | H27: DaviPlata | I27: Transferencia interbancos
A28: 46084 | B28: =+TEXT(A28,"ddd") -> mar | D28: 27000 | E28: fact | H28: Nequi | I28: Transferencia interbancos -papá
A29: 46084 | B29: =+TEXT(A29,"ddd") -> mar | D29: =5000*4 -> 20000 | E29: fact | H29: Nequi | I29: NO NEQUI - Hamburguesas para la casa
A30: 46084 | B30: =+TEXT(A30,"ddd") -> mar | D30: 33000 | E30: fact | H30: Nequi | I30: José Isidro Pinzòn Corredor
A31: 46084 | B31: =+TEXT(A31,"ddd") -> mar | D31: -619850 | E31: Nd-Nc | H31: Nequi | I31: Pago factura del cerdo
A32: 46085 | B32: =+TEXT(A32,"ddd") -> mié | D32: 19000 | E32: fact | H32: Nequi | I32: Edu***loz***Boh**
A33: 46085 | B33: =+TEXT(A33,"ddd") -> mié | D33: 8000 | E33: fact | H33: Nequi | I33: Gre***Leo***Cor**
A34: 46085 | B34: =+TEXT(A34,"ddd") -> mié | D34: 18000 | E34: fact | H34: Nequi | I34: Recarga desde Bancolomba
A35: 46085 | B35: =+TEXT(A35,"ddd") -> mié | D35: 8000 | E35: fact | H35: Nequi | I35: Willian Gutierrez
A36: 46085 | B36: =+TEXT(A36,"ddd") -> mié | D36: 64000 | E36: fact | H36: Nequi | I36: Sergio Alarcón | M36: =+SUM(D32:D36) -> 117000
A37: 46086 | B37: =+TEXT(A37,"ddd") -> jue | D37: 30000 | E37: fact | H37: Nequi | I37: Henry Aguirre | M37: =#REF!+8000 -> #REF!
A38: 46086 | B38: =+TEXT(A38,"ddd") -> jue | D38: 11000 | E38: fact | H38: Nequi | I38: Miguel Rodriguez
A39: 46086 | B39: =+TEXT(A39,"ddd") -> jue | D39: 16000 | E39: fact | H39: Nequi | I39: Diego Tijaro
A40: 46086 | B40: =+TEXT(A40,"ddd") -> jue | D40: 39500 | E40: fact | H40: Nequi | I40: Leidy Camacho | M40: =+#REF! -> #REF!
A41: 46086 | B41: =+TEXT(A41,"ddd") -> jue | D41: 35000 | E41: fact | H41: Nequi | I41: Manuel Fernando Ramirez | M41: =+SUM(D37:D41) -> 131500
A42: 46088 | B42: =+TEXT(A42,"ddd") -> sáb | D42: 28000 | E42: fact | H42: Nequi | I42: Yeimmerson Velandia
A43: 46088 | B43: =+TEXT(A43,"ddd") -> sáb | D43: 43000 | E43: fact | H43: Nequi | I43: Adriana Pinto
A44: 46089 | B44: =+TEXT(A44,"ddd") -> dom | D44: 30000 | E44: fact | H44: Nequi | I44: Gloria Rodriguez
A45: 46089 | B45: =+TEXT(A45,"ddd") -> dom | D45: 54000 | E45: fact | H45: Nequi | I45: ALI***PAT***GUT
A46: 46089 | B46: =+TEXT(A46,"ddd") -> dom | D46: 8000 | E46: fact | H46: Nequi | I46: Marcelo Cespedes
A47: 46089 | B47: =+TEXT(A47,"ddd") -> dom | D47: 30000 | E47: fact | H47: Nequi | I47: FLO***ANG***ITA***OR
A48: 46089 | B48: =+TEXT(A48,"ddd") -> dom | D48: 16000 | E48: fact | H48: Nequi | I48: Papá del 7 de marzo
A49: 46091 | B49: =+TEXT(A49,"ddd") -> mar | D49: 90000 | E49: fact | H49: Nequi | I49: Consignaciòn DaviPlata
A50: 46091 | B50: =+TEXT(A50,"ddd") -> mar | D50: -412000 | H50: Nequi | I50: Pago de la gaseosa
A51: 46091 | B51: =+TEXT(A51,"ddd") -> mar | D51: 30000 | E51: fact | H51: Nequi | I51: NEL***HER***LOP
A52: 46091 | B52: =+TEXT(A52,"ddd") -> mar | D52: 11000 | E52: fact | H52: Nequi | I52: BRIAN SANTANA
A53: 46092 | B53: =+TEXT(A53,"ddd") -> mié | D53: 8000 | E53: fact | H53: Nequi | I53: ALEX SOCARRAS
A54: 46092 | B54: =+TEXT(A54,"ddd") -> mié | D54: 24000 | E54: fact | H54: Nequi | I54: EDISON PENAGOS
A55: 46092 | B55: =+TEXT(A55,"ddd") -> mié | D55: 22000 | E55: fact | H55: Nequi | I55: BRIAN SANTANA
A56: 46092 | B56: =+TEXT(A56,"ddd") -> mié | D56: 8000 | E56: fact | H56: Nequi | I56: KATERINE SIERRA
A57: 46092 | B57: =+TEXT(A57,"ddd") -> mié | D57: 32000 | E57: fact | H57: Nequi | I57: MAI***JOS**MAI
A58: 46092 | B58: =+TEXT(A58,"ddd") -> mié | D58: 8000 | E58: fact | H58: Nequi | I58: JUAN BERMUDEZ
A59: 46092 | B59: =+TEXT(A59,"ddd") -> mié | D59: 11000 | E59: fact | H59: Nequi | I59: SAN***BEN**ROD
A60: 46084 | B60: =+TEXT(A60,"ddd") -> mar | D60: 11000 | E60: fact | H60: DaviPlata
A61: 46089 | B61: =+TEXT(A61,"ddd") -> dom | D61: 3000 | E61: fact | H61: DaviPlata
A62: 46090 | B62: =+TEXT(A62,"ddd") -> lun | D62: 76000 | E62: GIRO | H62: DaviPlata | I62: Transferencia interbancos de papa
A63: 46091 | B63: =+TEXT(A63,"ddd") -> mar | D63: -90000 | E63: Nd-Nc | H63: DaviPlata
A64: 46092 | B64: =+TEXT(A64,"ddd") -> mié | D64: 1000 | E64: fact | H64: DaviPlata
A65: 46092 | B65: =+TEXT(A65,"ddd") -> mié | D65: 22000 | E65: fact | H65: DaviPlata
A66: 46093 | B66: =+TEXT(A66,"ddd") -> jue | D66: 82000 | E66: fact | F66: 00095 | H66: DaviPlata
A67: 46093 | B67: =+TEXT(A67,"ddd") -> jue | C67: 0.73125 | D67: 11000 | E67: fact | F67: 000198 | H67: Nequi | I67: BRIAN SANTANA
A68: 46093 | B68: =+TEXT(A68,"ddd") -> jue | C68: 0.78611111 | D68: 24000 | E68: fact | F68: 000202 | H68: Nequi | I68: JOHN CRISOSTOMO
A69: 46093 | B69: =+TEXT(A69,"ddd") -> jue | D69: 24000 | E69: fact | F69: 000196 | H69: Nequi | I69: WEN***ALE***PUL
A70: 46093 | B70: =+TEXT(A70,"ddd") -> jue | D70: 11000 | E70: fact | H70: Nequi | I70: JEI***PEN***BEN***
A71: 46095 | B71: =+TEXT(A71,"ddd") -> sáb | D71: 23000 | E71: fact | F71: 00095 | H71: DaviPlata
A72: 46095 | B72: =+TEXT(A72,"ddd") -> sáb | D72: 11000 | E72: fact | F72: 00212 | H72: Nequi | I72: JEISON URIBE
A73: 46095 | B73: =+TEXT(A73,"ddd") -> sáb | D73: 11000 | E73: fact | F73: 00216 | H73: Nequi | I73: ANGIE ZUNIGA
A74: 46095 | B74: =+TEXT(A74,"ddd") -> sáb | D74: 57500 | E74: fact | H74: Nequi | I74: JUA***PAB***GAL***G
A75: 46095 | B75: =+TEXT(A75,"ddd") -> sáb | D75: 13500 | E75: fact | F75: 00217 | H75: Nequi | I75: LUIS ALBERTO ROMERO CALDERON
A76: 46096 | B76: =+TEXT(A76,"ddd") -> dom | D76: 19000 | E76: fact | H76: Nequi | I76: JUAN JOYA
A77: 46096 | B77: =+TEXT(A77,"ddd") -> dom | C77: 0.78819444 | D77: 36000 | E77: fact | H77: Nequi | I77: LUIS ALBERTO ROMERO CALDERON
A78: 46097 | B78: =+TEXT(A78,"ddd") -> lun | D78: 10000 | E78: fact | H78: Nequi | I78: DANIEL RAMOS
A79: 46097 | B79: =+TEXT(A79,"ddd") -> lun | D79: 11000 | E79: fact | H79: Nequi | I79: FELIPE GUTIERREZ
A80: 46098 | B80: =+TEXT(A80,"ddd") -> mar | D80: 8000 | E80: fact | H80: DaviPlata
A81: 46098 | B81: =+TEXT(A81,"ddd") -> mar | D81: 15000 | E81: fact | H81: DaviPlata
A82: 46098 | B82: =+TEXT(A82,"ddd") -> mar | C82: 0.66041667 | D82: 50000 | E82: fact | F82: 00240 | H82: Nequi | I82: LIDIA CAMACHO CARRERO
A83: 46098 | B83: =+TEXT(A83,"ddd") -> mar | D83: 11000 | E83: fact | F83: 00238 | H83: Nequi | I83: BRI***STI***SAN***
A84: 46098 | B84: =+TEXT(A84,"ddd") -> mar | D84: 8000 | E84: fact | F84: 0000 | H84: Nequi | I84: JESUS BOJACA
A85: 46098 | B85: =+TEXT(A85,"ddd") -> mar | D85: 9000 | E85: fact | F85: 00247 | H85: Nequi | I85: CAROLINA LEON
A86: 46098 | B86: =+TEXT(A86,"ddd") -> mar | D86: =-(40000+20000) -> -60000 | E86: Egreso | H86: Nequi | I86: Pago publicidad - banner y registradora
A87: 46099 | B87: =+TEXT(A87,"ddd") -> mié | D87: 344950 | E87: Base | H87: Nequi | I87: Transferencia del efectivo
A88: 46098 | B88: =+TEXT(A88,"ddd") -> mar | D88: 24000 | E88: fact | F88: uni | G88: Pendiente | H88: Nequi | I88: Chorizos el de publicidad
A89: 46098 | B89: =+TEXT(A89,"ddd") -> mar | D89: -24000 | E89: fact | F89: uni | G89: Pendiente | H89: Nequi | I89: Ajuste administrativo, si se tuvo en cuenta en el acumulado
A90: 46098 | B90: =+TEXT(A90,"ddd") -> mar | D90: =8000*4 -> 32000 | E90: fact | F90: 00255 | G90: Pendiente | H90: Nequi | I90: Chorizos el de publicidad
A91: 46099 | B91: =+TEXT(A91,"ddd") -> mié | D91: -40000 | E91: Egreso | H91: Nequi | I91: Pago transportes Ed
A92: 46099 | B92: =+TEXT(A92,"ddd") -> mié | D92: -40000 | E92: Egreso | H92: Nequi | I92: Pago transportes JG y Ed - 17 de marzo
A93: 46099 | B93: =+TEXT(A93,"ddd") -> mié | D93: -116000 | E93: Egreso | H93: Nequi | I93: Servicio de gas
A94: 46099 | B94: =+TEXT(A94,"ddd") -> mié | D94: =+-8500-6000 -> -14500 | E94: Egreso | H94: Nequi | I94: Llaves y ganchos
A95: 46099 | B95: =+TEXT(A95,"ddd") -> mié | D95: -50000 | E95: Egreso | H95: Nequi | I95: Transportes EA y JG
A96: 46099 | B96: =+TEXT(A96,"ddd") -> mié | D96: 38000 | E96: fact | H96: Nequi
A97: 46099 | B97: =+TEXT(A97,"ddd") -> mié | D97: 16000 | E97: fact | H97: Nequi
A98: 46099 | B98: =+TEXT(A98,"ddd") -> mié | D98: 8000 | E98: fact | H98: Nequi
A99: 46099 | B99: =+TEXT(A99,"ddd") -> mié | D99: 9000 | E99: fact | H99: Nequi
A100: 46100 | B100: =+TEXT(A100,"ddd") -> jue | D100: 11000 | E100: fact | H100: DaviPlata
A101: 46100 | B101: =+TEXT(A101,"ddd") -> jue | D101: 8000 | E101: fact | F101: 268 | H101: Nequi | I101: ALEXA PENA
...

Sheet Inv-2abr
A1: materia_prima | B1: TIPO | C1: stock real 2 de abril | D1: ENTRADAS 7 y 8 abril | E1: SALIDAS 7 y 8 abril | F1: stock actual | G1: stock real 8 de abril | H1: Ajuste | I1: comentarios | K1: =+SUM(K12:K1048576) -> -245080 | L1: =24*4 -> 96
A2: CHORIZO | B2: | | C2: =(100*2)+8 -> 208 | D2: 20 | E2: 41 | F2: 210 | G2: =+C2+D2-E2 -> 187 | H2: =+G2-F2 -> -23 | I2: DEGUSTACIÓN | J2: 3500 | K2: =+J2*H2 -> -80500
A3: PAPA | B3: | | C3: =+(50000/(150*3))*1.5 -> 166.66667 | E3: 39 | F3: -53 | G3: =+C3-E3 -> 127.66667 | H3: =+G3-F3 -> 180.66667 | I3: AJUSTE | J3: 750 | K3: =+J3*H3 -> 135500
A4: HAMBURGUESA | B4: | | C4: 39 | E4: 2 | F4: 38 | G4: =+C4-E4 -> 37 | H4: =+G4-F4 -> -1 | I4: DEGUSTACIÓN | J4: 5000 | K4: =+J4*H4 -> -5000
A5: Costillas BBQ | B5: | | C5: 9 | G5: =+C5-E5 -> 9 | H5: =+G5-F5 -> 9 | I5: AJUSTE | J5: 15000 | K5: =+J5*H5 -> 135000
A6: Carne 400 gramos | B6: | | C6: 5 | E6: 1 | F6: -30 | G6: =+C6-E6 -> 4 | H6: =+G6-F6 -> 34 | I6: AJUSTE | J6: 19000 | K6: =+J6*H6 -> 646000
A7: Carne 250 gramos | B7: | | F7: -21 | G7: =+C7-E7 -> 0 | H7: =+G7-F7 -> 21 | I7: AJUSTE | J7: 10000 | K7: =+J7*H7 -> 210000
A8: Lomo de cerdo | B8: | | C8: 3 | F8: 0 | G8: =+C8-E8 -> 3 | H8: =+G8-F8 -> 3 | I8: AJUSTE | J8: 10000 | K8: =+J8*H8 -> 30000
A9: Pechuga | B9: | | F9: -1 | G9: 0 | H9: 1 | I9: AJUSTE | J9: 17000 | K9: =+J9*H9 -> 17000
A10: Churrasco | B10: | | C10: 4 | F10: 0 | G10: =+C10-E10 -> 4 | H10: =+G10-F10 -> 4 | I10: AJUSTE | J10: 17000 | K10: =+J10*H10 -> 68000
A11: mojarra | B11: | | C11: 5 | E11: 5 | F11: 0 | G11: =+C11-E11 -> 0 | H11: =+G11-F11 -> 0 | I11: NOMINA + CASINO
A12: BEBIDA - AGUA 600 ML | B12: ||| | C12: 17 | F12: 34 | G12: =+C12-E12 -> 17 | H12: =+G12-F12 -> -17 | I12: PÉRDIDA | J12: 1417 | K12: =+J12*H12 -> -24089
A13: BEBIDA - Aguila | B13: ||| | C13: 0 | F13: 3 | G13: =+C13-E13 -> 0 | H13: =+G13-F13 -> -3 | I13: PÉRDIDA | J13: 3000 | K13: =+J13*H13 -> -9000
A14: BEBIDA - Cerveza Central | B14: ||| | C14: =8+48 -> 56 | E14: 9 | F14: 80 | G14: =+C14-E14 -> 47 | H14: =+G14-F14 -> -33 | I14: PÉRDIDA | J14: 1188 | K14: =+J14*H14 -> -39204
A15: BEBIDA - Cerveza Club Colombia | B15: ||| | C15: 0 | F15: 5 | G15: =+C15-E15 -> 0 | H15: =+G15-F15 -> -5 | I15: PÉRDIDA | J15: 3300 | K15: =+J15*H15 -> -16500
A16: BEBIDA - COCA COLA 237ML | B16: ||| | C16: 126 | E16: 16 | F16: 146 | G16: =+C16-E16 -> 110 | H16: =+G16-F16 -> -36 | I16: PÉRDIDA | J16: 1200 | K16: =+J16*H16 -> -43200 | M16: =+K16+K17 -> -107781
A17: BEBIDA - POSTOBON 250ML | B17: ||| | C17: 88 | F17: 145 | G17: =+C17-E17 -> 88 | H17: =+G17-F17 -> -57 | I17: PÉRDIDA | J17: 1133 | K17: =+J17*H17 -> -64581
A18: GASEOSA | B18: ||| | C18: =+C16+C17 -> 214 | F18: =+F16+F17 -> 291 | G18: =+G16+G17 -> 198 | H18: =+H16+H17 -> -93 | L18: =+SUM(K16:K17)/SUM(H16:H17) -> 1158.9355 | M18: =+L18*H18 -> -107781
A19: BEBIDA - COCA COLA ZERO | B19: ||| | C19: 16 | F19: 20 | G19: =+C19-E19 -> 16 | H19: =+G19-F19 -> -4 | I19: PÉRDIDA | J19: 1250 | K19: =+J19*H19 -> -5000
A20: BEBIDA - HIT 237ML | B20: ||| | C20: 13 | E20: 4 | F20: 27 | G20: =+C20-E20 -> 9 | H20: =+G20-F20 -> -18 | I20: PÉRDIDA | J20: 2417 | K20: =+J20*H20 -> -43506
A21: Arepa | B21: || | C21: 25 | E21: 303 | F21: -25 | G21: 30 | H21: =+G21-F21 -> 55 | I21: VENCIDO
A22: Pan Perro | B22: || | C22: 4 | E22: 4 | F22: 0 | G22: =+C22-E22 -> 0 | H22: =+G22-F22 -> 0 | I22: VENCIDO
A23: Pan Hamburguesa | B23: || | C23: =4*3 -> 12 | F23: 22 | G23: =+C23-E23 -> 12 | H23: =+G23-F23 -> -10 | I23: VENCIDO
A25: bolsa grande de cerdo | C25: 1 | G25: =+C25-E25 -> 1
A26: bolsa de cerdo varios kilos | C26: 1 | G26: =+C26-E26 -> 1
A27: Papa francesa grande | C27: 3 | G27: =+C27-E27 -> 3
A28: Papa francesa pequeña | C28: 8 | G28: =+C28-E28 -> 8
D30: =3500*187 -> 654500

Sheet Carta

Sheet DevOps
B1: DevOps
B2: fecha | C2: Detalle | D2: Backlog | E2: Código | F2: Nombre commit
B3: 46090 | C3: Como usuario general requiero abrir la caja para ágilizar el proceso de devolución de vueltas | D3: Done | E3: HU38 | F3: HU38: Botón de emergencia
B4: 46090 | C4: El título de la sección de efectivo no corresponde: "Registro Base" ---> "Registro de entradas y retiros de efectivo" | D4: Done | E4: BU001 | F4: BU001: El título de la sección no corresponde
B5: 46093 | C5: Se agrega botón "Abrir Caja", se mejora el dashboard de "Transacciones" para facilitar la consistencia de los datos" | D5: Done | E5: BU002 | F5: BU002: "Usabilidad y consistecia de la información"
B6: 46093 | C6: Se mejora la ordenación del orden de las facturar para validarlas mejor, se agrega el botón "Abrir Caja" en la sección de factura, y se omite desde dashboard para facilitar la seguridad del sistema. | D6: Done | E6: BU003 | F6: BU003: "Usabilidad para el cajero y seguridad"
B7: 46093 | C7: Cambiar a item por producto y materia prima. Cambiar el título de "Entradas" por "MP" de materias primas | D7: Done | E7: BU004 | F7: BU004: "Usabilidad el admon y cajero"
B8: 46093 | C8: Crea un warning que diga "No ha guardado los registros, ¿estas seguro que quiere salir? | D8: Done | E8: BU005 | F8: BU005: "Usabilidad cajero - warning"
B9: 46093 | C9: No hay diferencia entre las entradas y salidas el efectivo con los egresos en el dashboard "ADMON: "Consignación" | D9: Done | E9: BU006 | F9: BU006: "Usabilidad y consistencia de la información"
B10: 46093 | C10: Nequi y DaviPlata deben estar en filas diferentes | D10: Done | E10: BU007 | F10: BU007: "Usabilidad y consistencia de la información"
B11: 46093 | C11: Como cajero, quiero filtrar el medio de pago de las facturas y egresos para facilizar la conciliación bancaria | D11: Done | E11: HU39 | F11: HU39: Filtrar Medio de pago
B12: 46099 | C12: Como cajero, quiero poder hacer un descuento a un producto para agilizar el proceso y ser consistente con la información | D12: Done | E12: BU008 | F12: BU008: "Usabilidad y consistencia de la información"
B13: 46099 | C13: al finalizar el dia la venta del dia suma el acumulado del dia siguiente para Nequi y Daviplata | D13: Done | E13: BU009 | F13: BU009: "Usabilidad y consistencia de la información"
B14: 46100 | C14: Como usuaio quiero ver estilo de colores en el dashboard para diferenciar más las transacciones. | D14: Done | E14: BU010 | F14: BU010: "UX-Design"
... B37: 46121 | C37: Como Usuario admin, quiero ver adicionar la información del inventario | D37: Done | E37: BU26 | F37: BU026: " Disponibilidad y Usabilidad"
C38: Omitir abrir caja para transacciones de nequi y daviplata | F38: }
C39: abrir solo cuando hay efectivo
C40: clasificar entrada y salida no es claro
C41: SUMARSE EL VALOR DE INVENTARIO
C42: NO SE PUEDE agregar nuevos items al ingresar o retirar inventarios
C43: Visor para domicilios | D43: Backlog
C45: Filtrar mejor las transacciones, nequi, suma gastos
C46: se abre multiples ventanas | D46: Backlog | F46: se abre multiples ventanas
C47: imprimir informe | D47: Backlog | F47: imprimir informe
D48: Backlog | F48: el caja se abre cada rato
C49: picadas, no hay manera de digitar picadas | D49: Backlog | F49: picadas, no hay manera de digitar picadas
C50: el visor no es muy pràctico | D50: Backlog | F50: el visor no es muy pràctico
C51: no hay ruta rapida de chorizo | D51: Backlog | F51: no hay ruta rapida de chorizo
C52: correir informaciòn del inventario | D52: Backlog | F52: correir informaciòn del inventario

Sheet precio_mp

Sheet MP
D1: tipo_unidad
D2: 10 un | J2: 3400
B5: fecha | C5: Categoria | D5: nombre_producto | E5: tipo_unidad | F5: precio_embalaje | G5: unidades_embalaje | H5: unidades_x_embalaje | I5: total | J5: unidades | K5: precio_unidad | L5: total
B6: 46076 | C6: MATERIA PRIMA | D6: Chorizo | E6: unidad | I6: =+F6*G6 -> 0 | J6: 365 | K6: 3500 | L6: =+J6*K6 -> 1277500
B7: 46089 | C7: MATERIA PRIMA | D7: Chorizo | E7: bolsa | F7: =3500*100 -> 350000 | G7: 5 | H7: 100 | I7: =+F7*G7 -> 1750000 | J7: =+G7*H7 -> 500 | K7: 3500 | L7: =+K7*J7 -> 1750000
B8: 46106 | C8: MATERIA PRIMA | D8: Chorizo | E8: unidad | I8: =+F8*G8 -> 0 | J8: 230 | K8: 3500 | L8: =+K8*J8 -> 805000
B9: 46072 | C9: MATERIA PRIMA | D9: papa salada | E9: Bulto | F9: 70000 | G9: 2 | H9: =50000/(150*3) -> 111.11111 | I9: =+F9*G9 -> 140000 | J9: =+G9*H9 -> 222.22222 | K9: =+I9/J9 -> 630 | L9: =+K9*J9 -> 140000
B10: 46112 | C10: MATERIA PRIMA | D10: papa salada | E10: Bulto | F10: 70000 | G10: 2 | H10: =50000/(150*3) -> 111.11111 | I10: =+F10*G10 -> 140000 | J10: =+G10*H10 -> 222.22222 | K10: =+I10/J10 -> 630 | L10: =+K10*J10 -> 140000
B11: 46109 | C11: MATERIA PRIMA | D11: papa salada | E11: Bulto | F11: 80000 | G11: 1 | H11: =50000/(150*3) -> 111.11111 | I11: =+F11*G11 -> 80000 | J11: =+G11*H11 -> 111.11111 | K11: =+I11/J11 -> 720 | L11: =+K11*J11 -> 80000
B12: 46089 | C12: MATERIA PRIMA | D12: arepa | E12: unidad | F12: 3800 | G12: 10 | H12: 10 | I12: =+F12*G12 -> 38000 | J12: 100 | K12: 380 | L12: =+J12*K12 -> 38000
B13: 46077 | C13: MATERIA PRIMA | D13: Hamburguesa | E13: unidad | I13: =+F13*G13 -> 0 | J13: 50 | K13: 5000 | L13: =+J13*K13 -> 250000
B14: 46073 | C14: BEBIDA | D14: Coca Cola -237ML | E14: canasta | F14: 36000 | G14: 6 | H14: 30 | I14: =+F14*G14 -> 216000 | J14: =+H14*G14 -> 180 | K14: =+I14/(G14*H14) -> 1200 | L14: =+K14*J14 -> 216000
B15: 46073 | C15: BEBIDA | D15: Postobon -250ML | E15: canasta | F15: 35000 | G15: 3 | H15: 30 | I15: =+F15*G15 -> 105000 | J15: =+H15*G15 -> 90 | K15: =+I15/(G15*H15) -> 1166.6667 | L15: =+K15*J15 -> 105000
B16: 46073 | C16: BEBIDA | D16: Hit-500ML | E16: doce un. | F16: 29000 | G16: 2 | H16: 12 | I16: =+F16*G16 -> 58000 | J16: =+H16*G16 -> 24 | K16: =+I16/(G16*H16) -> 2416.6667 | L16: =+K16*J16 -> 58000
B17: 46073 | C17: BEBIDA | D17: Agua -600ML | E17: 2 docenas | F17: 33000 | G17: 1 | H17: 24 | I17: =+F17*G17 -> 33000 | J17: =+H17*G17 -> 24 | K17: =+I17/(G17*H17) -> 1375 | L17: =+K17*J17 -> 33000
B18: 46100 | C18: BEBIDA | D18: Coca Cola -237ML | E18: canasta | F18: 36000 | G18: 5 | H18: 30 | I18: =+F18*G18 -> 180000 | J18: 30 | K18: =+I18/(G18*H18) -> 1200 | L18: =+F18*G18 -> 180000
B19: 46100 | C19: BEBIDA | D19: Postobon -250ML | E19: canasta | F19: 34000 | G19: 3 | H19: 30 | I19: =+F19*G19 -> 102000 | J19: 30 | K19: =+I19/(G19*H19) -> 1133.3333 | L19: =+F19*G19 -> 102000
B20: 46100 | C20: BEBIDA | D20: Coca Cola Zero -250ML | E20: six pack | F20: 15000 | G20: 2 | H20: 12 | I20: =+F20*G20 -> 30000 | J20: 12 | K20: =+I20/(G20*H20) -> 1250 | L20: =+F20*G20 -> 30000
B21: 46100 | C21: BEBIDA | D21: Hit-500ML | E21: docena | F21: 29000 | G21: 2 | H21: 12 | I21: =+F21*G21 -> 58000 | J21: 12 | K21: =+I21/(G21*H21) -> 2416.6667 | L21: =+F21*G21 -> 58000
B22: 46100 | C22: BEBIDA | D22: Agua -600ML | E22: 2 docenas | F22: 34000 | G22: 1 | H22: 24 | I22: =+F22*G22 -> 34000 | J22: 24 | K22: =+I22/(G22*H22) -> 1416.6667 | L22: =+F22*G22 -> 34000
B23: 46102 | C23: BEBIDA | D23: CERVEZA CENTRAL | E23: Paca | F23: 28500 | G23: 4 | H23: =6*4 -> 24 | I23: =+F23*G23 -> 114000 | J23: =+G23*H23 -> 96 | K23: =+I23/(G23*H23) -> 1187.5 | L23: =+J23*K23 -> 114000
B24: 46091 | C24: BEBIDA | D24: CLUB COLOMBIA | E24: six pack | F24: 19800 | G24: 1 | H24: 6 | I24: =+F24*G24 -> 19800 | J24: =+G24*H24 -> 6 | K24: =+I24/(G24*H24) -> 3300 | L24: =+F24*G24 -> 19800
B25: 46091 | C25: BEBIDA | D25: CLUB AGUILA | E25: six pack | F25: 18000 | G25: 2 | H25: 6 | I25: =+F25*G25 -> 36000 | J25: =+G25*H25 -> 12 | K25: =+I25/(G25*H25) -> 3000 | L25: =+F25*G25 -> 36000
B26: 46085 | C26: MATERIA PRIMA | D26: Filete de pechuga | E26: kilo | F26: 11700 | G26: 2.56 | H26: 2 | I26: =+F26*G26 -> 29952 | J26: =+G26*H26 -> 5.12 | K26: =+I26/(G26*H26) -> 5850 | L26: =+F26*G26 -> 29952
B29: 46073 | C29: BEBIDA | D29: Coca Cola -237ML | E29: canasta | F29: 36000 | G29: 4 | H29: 30 | I29: =+F29*G29 -> 144000 | J29: =+H29*G29 -> 120 | K29: =+I29/(G29*H29) -> 1200 | L29: =+K29*J29 -> 144000
B30: 46073 | C30: BEBIDA | D30: Agua -600ML | E30: 2 docenas | F30: 33000 | G30: 1 | H30: 24 | I30: =+F30*G30 -> 33000 | J30: =+H30*G30 -> 24 | K30: =+I30/(G30*H30) -> 1375 | L30: =+K30*J30 -> 33000
B31: 46073 | C31: BEBIDA | D31: Agua -600ML | E31: 2 docenas | F31: 33000 | G31: 1 | H31: 24 | I31: =+F31*G31 -> 33000 | J31: =+H31*G31 -> 24 | K31: =+I31/(G31*H31) -> 1375 | L31: =+K31*J31 -> 33000
B32: 46100 | C32: BEBIDA | D32: Coca Cola Zero -250ML | E32: six pack | F32: 15000 | G32: 3 | H32: 12 | I32: =+F32*G32 -> 45000 | J32: 12 | K32: =+I32/(G32*H32) -> 1250 | L32: =+F32*G32 -> 45000

Sheet MP2
G2: 3500 | H2: 11000 | I2: 13000 | J2: 19000 | K2: 13000 | L2: 17000 | M2: 20000 | N2: 12000 | O2: 20000 | P2: 26000 | Q2: 10000 | R2: 14000 | S2: 1950 | T2: 5000 | U2: 800 | V2: 2000 | W2: 400 | X2: 840 | Y2: 600 | Z2: 2500 | AA2: 2800 | AB2: 3200 | AC2: 1416.67 | AD2: 1200 | AE2: 1200 | AF2: 1250 | AG2: 2416.67 | AH2: 1133.33 | AI2: 1133.33
A3: id_producto | B3: nombre_producto | C3: precio | D3: costo | E3: MG | F3: %MG | G3: chorizo | H3: Carne 250 gr | I3: Carne asada 250 gr | J3: Carne asada 400 gr | K3: Costillas BBQ 250gr | L3: lomo cerdo | M3: Churrasco | N3: Medìa Carne | O3: Mojarra | P3: Costillas BBQ 400gr | Q3: Pechuga 250 pg | R3: Carne 350 gr | S3: Pan Bimbo | T3: Hamburguesa | U3: Tinto | V3: papa francesa | W3: pan choriboni | X3: papa (3 papas) | Y3: patacon | Z3: guacamole | AA3: BEBIDA - Aguila | AB3: BEBIDA - Club Colombia | AC3: BEBIDA - Botella de Agua | AD3: BEBIDA - Coca Cola | AE3: BEBIDA - Coca Cola 237ML | AF3: BEBIDA - Coca Cola ZERO | AG3: BEBIDA - Jugo Hit | AH3: BEBIDA - Postobon 350ML | AI3: BEBIDA - Postobón
A4: 1 | B4: Chorizo con papa/arepa | C4: 8000 | D4: =+SUMPRODUCT(G4:AI4,G$2:AI$2) -> 4340 | E4: =+C4-D4 -> 3660 | F4: =1-D4/C4 -> 0.4575 | G4: 1 | H4: 0 | Q4: 0 | R4: 0 | S4: 0 | T4: 0 | U4: 0 | V4: 0 | W4: 0 | X4: 1 | Y4: 0 | Z4: 0 | AA4: 0 | AB4: 0 | AC4: 0 | AD4: 0 | AE4: 0 | AF4: 0 | AG4: 0 | AH4: 0 | AI4: 0
A5: 39 | B5: Chorizo solo | C5: 7000 | D5: =+SUMPRODUCT(G5:AI5,G$2:AI$2) -> 3500 | E5: =+C5-D5 -> 3500 | F5: =1-D5/C5 -> 0.5 | G5: 1 | H5: 0 | Q5: 0 | R5: 0 | S5: 0 | T5: 0 | U5: 0 | V5: 0 | W5: 0 | X5: 0 | Y5: 0 | Z5: 0 | AA5: 0 | AB5: 0 | AC5: 0 | AD5: 0 | AE5: 0 | AF5: 0 | AG5: 0 | AH5: 0 | AI5: 0
A6: 19 | B6: Bandeja Choriboni - 25 | C6: 25000 | D6: =+SUMPRODUCT(G6:AI6,G$2:AI$2) -> 7440 | E6: =+C6-D6 -> 17560 | F6: =1-D6/C6 -> 0.7024 | G6: 1 | H6: 0 | Q6: 0 | R6: 0 | S6: 0 | T6: 0 | U6: 0 | V6: 0 | W6: 0 | X6: 1 | Y6: 1 | Z6: 1 | AA6: 0 | AB6: 0 | AC6: 0 | AD6: 0 | AE6: 0 | AF6: 0 | AG6: 0 | AH6: 0 | AI6: 0
A7: 24 | B7: Bandeja Choriboni - 30 | C7: 30000 | D7: =+SUMPRODUCT(G7:AI7,G$2:AI$2) -> 7440 | E7: =+C7-D7 -> 22560 | F7: =1-D7/C7 -> 0.752 | G7: 1 | H7: 0 | Q7: 0 | R7: 0 | S7: 0 | T7: 0 | U7: 0 | V7: 0 | W7: 0 | X7: 1 | Y7: 1 | Z7: 1 | AA7: 0 | AB7: 0 | AC7: 0 | AD7: 0 | AE7: 0 | AF7: 0 | AG7: 0 | AH7: 0 | AI7: 0
A8: 29 | B8: Bandeja Choriboni - 35 | C8: 35000 | D8: =+SUMPRODUCT(G8:AI8,G$2:AI$2) -> 7440 | E8: =+C8-D8 -> 27560 | F8: =1-D8/C8 -> 0.78742857 | G8: 1 | H8: 0 | Q8: 0 | R8: 0 | S8: 0 | T8: 0 | U8: 0 | V8: 0 | W8: 0 | X8: 1 | Y8: 1 | Z8: 1 | AA8: 0 | AB8: 0 | AC8: 0 | AD8: 0 | AE8: 0 | AF8: 0 | AG8: 0 | AH8: 0 | AI8: 0
A9: 44 | B9: BEBIDA - Aguila | C9: 4500 | D9: =+SUMPRODUCT(G9:AI9,G$2:AI$2) -> 2800 | E9: =+C9-D9 -> 1700 | F9: =1-D9/C9 -> 0.37777778 | G9: 0 | H9: 0 | Q9: 0 | R9: 0 | S9: 0 | T9: 0 | U9: 0 | V9: 0 | W9: 0 | X9: 0 | Y9: 0 | Z9: 0 | AA9: 1 | AB9: 0 | AC9: 0 | AD9: 0 | AE9: 0 | AF9: 0 | AG9: 0 | AH9: 0 | AI9: 0
A10: 45 | B10: BEBIDA - Club Colombia | C10: 6000 | D10: =+SUMPRODUCT(G10:AI10,G$2:AI$2) -> 3200 | E10: =+C10-D10 -> 2800 | F10: =1-D10/C10 -> 0.46666667 | G10: 0 | H10: 0 | Q10: 0 | R10: 0 | S10: 0 | T10: 0 | U10: 0 | V10: 0 | W10: 0 | X10: 0 | Y10: 0 | Z10: 0 | AA10: 0 | AB10: 1 | AC10: 0 | AD10: 0 | AE10: 0 | AF10: 0 | AG10: 0 | AH10: 0 | AI10: 0
A11: 4 | B11: BEBIDA - Botella de Agua | C11: 3500 | D11: =+SUMPRODUCT(G11:AI11,G$2:AI$2) -> 1416.67 | E11: =+C11-D11 -> 2083.33 | F11: =1-D11/C11 -> 0.59523714 | G11: 0 | H11: 0 | Q11: 0 | R11: 0 | S11: 0 | T11: 0 | U11: 0 | V11: 0 | W11: 0 | X11: 0 | Y11: 0 | Z11: 0 | AA11: 0 | AB11: 0 | AC11: 1 | AD11: 0 | AE11: 0 | AF11: 0 | AG11: 0 | AH11: 0 | AI11: 0
A12: 2 | B12: BEBIDA - Coca Cola | C12: 3000 | D12: =+SUMPRODUCT(G12:AI12,G$2:AI$2) -> 1200 | E12: =+C12-D12 -> 1800 | F12: =1-D12/C12 -> 0.6 | G12: 0 | H12: 0 | Q12: 0 | R12: 0 | S12: 0 | T12: 0 | U12: 0 | V12: 0 | W12: 0 | X12: 0 | Y12: 0 | Z12: 0 | AA12: 0 | AB12: 0 | AC12: 0 | AD12: 1 | AE12: 0 | AF12: 0 | AG12: 0 | AH12: 0 | AI12: 0
A13: 49 | B13: BEBIDA - Coca Cola 237ML | C13: 1200 | D13: =+SUMPRODUCT(G13:AI13,G$2:AI$2) -> 1200 | E13: =+C13-D13 -> 0 | F13: =1-D13/C13 -> 0 | G13: 0 | H13: 0 | Q13: 0 | R13: 0 | S13: 0 | T13: 0 | U13: 0 | V13: 0 | W13: 0 | X13: 0 | Y13: 0 | Z13: 0 | AA13: 0 | AB13: 0 | AC13: 0 | AD13: 0 | AE13: 1 | AF13: 0 | AG13: 0 | AH13: 0 | AI13: 0
A14: 48 | B14: BEBIDA - Coca Cola ZERO | C14: 3200 | D14: =+SUMPRODUCT(G14:AI14,G$2:AI$2) -> 1250 | E14: =+C14-D14 -> 1950 | F14: =1-D14/C14 -> 0.609375 | G14: 0 | H14: 0 | Q14: 0 | R14: 0 | S14: 0 | T14: 0 | U14: 0 | V14: 0 | W14: 0 | X14: 0 | Y14: 0 | Z14: 0 | AA14: 0 | AB14: 0 | AC14: 0 | AD14: 0 | AE14: 0 | AF14: 1 | AG14: 0 | AH14: 0 | AI14: 0
A15: 7 | B15: BEBIDA - Jugo Hit | C15: 4500 | D15: =+SUMPRODUCT(G15:AI15,G$2:AI$2) -> 2416.67 | E15: =+C15-D15 -> 2083.33 | F15: =1-D15/C15 -> 0.46296222 | G15: 0 | H15: 0 | Q15: 0 | R15: 0 | S15: 0 | T15: 0 | U15: 0 | V15: 0 | W15: 0 | X15: 0 | Y15: 0 | Z15: 0 | AA15: 0 | AB15: 0 | AC15: 0 | AD15: 0 | AE15: 0 | AF15: 0 | AG15: 1 | AH15: 0 | AI15: 0
... A17: 3 | B17: BEBIDA - Postobón | C17: 3000 | D17: =+SUMPRODUCT(G17:AI17,G$2:AI$2) -> 1133.33 | E17: =+C17-D17 -> 1866.67 | F17: =1-D17/C17 -> 0.62222333 | G17: 0 | H17: 0 | Q17: 0 | R17: 0 | S17: 0 | T17: 0 | U17: 0 | V17: 0 | W17: 0 | X17: 0 | Y17: 0 | Z17: 0 | AA17: 0 | AB17: 0 | AC17: 0 | AD17: 0 | AE17: 0 | AF17: 0 | AG17: 0 | AH17: 0 | AI17: 1
A18: 42 | B18: CARNES - Carne asada - 20 | C18: 20000 | D18: =+SUMPRODUCT(G18:AI18,G$2:AI$2) -> 15600 | E18: =+C18-D18 -> 4400 | F18: =1-D18/C18 -> 0.22 | G18: 0 | H18: 0 | I18: 1 | J18: 0 | K18: 0 | L18: 0 | M18: 0 | N18: 0 | O18: 0 | P18: 0 | Q18: 0 | R18: 0 | S18: 0 | T18: 0 | U18: 0 | V18: 1 | W18: 0 | X18: 0 | Y18: 1 | Z18: 0 | AA18: 0 | AB18: 0 | AC18: 0 | AD18: 0 | AE18: 0 | AF18: 0 | AG18: 0 | AH18: 0 | AI18: 0
A19: 33 | B19: CARNES - Carne Asada de 40 | C19: 40000 | D19: =+SUMPRODUCT(G19:AI19,G$2:AI$2) -> 21600 | E19: =+C19-D19 -> 18400 | F19: =1-D19/C19 -> 0.46 | G19: 0 | H19: 0 | I19: 0 | J19: 1 | K19: 0 | L19: 0 | M19: 0 | N19: 0 | O19: 0 | P19: 0 | Q19: 0 | R19: 0 | S19: 0 | T19: 0 | U19: 0 | V19: 1 | W19: 0 | X19: 0 | Y19: 1 | Z19: 0 | AA19: 0 | AB19: 0 | AC19: 0 | AD19: 0 | AE19: 0 | AF19: 0 | AG19: 0 | AH19: 0 | AI19: 0
A20: 41 | B20: CARNES - Carne asada 23 | C20: 23000 | D20: =+SUMPRODUCT(G20:AI20,G$2:AI$2) -> 15600 | E20: =+C20-D20 -> 7400 | F20: =1-D20/C20 -> 0.32173913 | G20: 0 | H20: 0 | I20: 1 | J20: 0 | K20: 0 | L20: 0 | M20: 0 | N20: 0 | O20: 0 | P20: 0 | Q20: 0 | R20: 0 | S20: 0 | T20: 0 | U20: 0 | V20: 1 | W20: 0 | X20: 0 | Y20: 1 | Z20: 0 | AA20: 0 | AB20: 0 | AC20: 0 | AD20: 0 | AE20: 0 | AF20: 0 | AG20: 0 | AH20: 0 | AI20: 0
A21: 11 | B21: CARNES - Churrasco Gaucho - 30 | C21: 30000 | D21: =+SUMPRODUCT(G21:AI21,G$2:AI$2) -> 22600 | E21: =+C21-D21 -> 7400 | F21: =1-D21/C21 -> 0.24666667 | G21: 0 | H21: 0 | I21: 0 | J21: 0 | K21: 0 | L21: 0 | M21: 1 | N21: 0 | O21: 0 | P21: 0 | Q21: 0 | R21: 0 | S21: 0 | T21: 0 | U21: 0 | V21: 1 | W21: 0 | X21: 0 | Y21: 1 | Z21: 0 | AA21: 0 | AB21: 0 | AC21: 0 | AD21: 0 | AE21: 0 | AF21: 0 | AG21: 0 | AH21: 0 | AI21: 0
A22: 27 | B22: CARNES - Costillas BBQ - 50 | C22: 50000 | D22: =+SUMPRODUCT(G22:AI22,G$2:AI$2) -> 28600 | E22: =+C22-D22 -> 21400 | F22: =1-D22/C22 -> 0.428 | G22: 0 | H22: 0 | I22: 0 | J22: 0 | K22: 0 | L22: 0 | M22: 0 | N22: 0 | O22: 0 | P22: 1 | Q22: 0 | R22: 0 | S22: 0 | T22: 0 | U22: 0 | V22: 1 | W22: 0 | X22: 0 | Y22: 1 | Z22: 0 | AA22: 0 | AB22: 0 | AC22: 0 | AD22: 0 | AE22: 0 | AF22: 0 | AG22: 0 | AH22: 0 | AI22: 0
A23: 14 | B23: CARNES - Costillas BBQ - 25 | C23: 25000 | D23: =+SUMPRODUCT(G23:AI23,G$2:AI$2) -> 15600 | E23: =+C23-D23 -> 9400 | F23: =1-D23/C23 -> 0.376 | G23: 0 | H23: 0 | I23: 0 | J23: 0 | K23: 1 | L23: 0 | M23: 0 | N23: 0 | O23: 0 | P23: 0 | Q23: 0 | R23: 0 | S23: 0 | T23: 0 | U23: 0 | V23: 1 | W23: 0 | X23: 0 | Y23: 1 | Z23: 0 | AA23: 0 | AB23: 0 | AC23: 0 | AD23: 0 | AE23: 0 | AF23: 0 | AG23: 0 | AH23: 0 | AI23: 0
A24: 12 | B24: CARNES - Lomo de Cerdo -25 | C24: 25000 | D24: =+SUMPRODUCT(G24:AI24,G$2:AI$2) -> 19600 | E24: =+C24-D24 -> 5400 | F24: =1-D24/C24 -> 0.216 | G24: 0 | H24: 0 | I24: 0 | J24: 0 | K24: 0 | L24: 1 | M24: 0 | N24: 0 | O24: 0 | P24: 0 | Q24: 0 | R24: 0 | S24: 0 | T24: 0 | U24: 0 | V24: 1 | W24: 0 | X24: 0 | Y24: 1 | Z24: 0 | AA24: 0 | AB24: 0 | AC24: 0 | AD24: 0 | AE24: 0 | AF24: 0 | AG24: 0 | AH24: 0 | AI24: 0
A25: 40 | B25: CARNES - Media carne | C25: 15000 | D25: =+SUMPRODUCT(G25:AI25,G$2:AI$2) -> 14000 | E25: =+C25-D25 -> 1000 | F25: =1-D25/C25 -> 0.066666667 | G25: 0 | H25: 0 | I25: 0 | J25: 0 | K25: 0 | L25: 0 | M25: 0 | N25: 1 | O25: 0 | P25: 0 | Q25: 0 | R25: 0 | S25: 0 | T25: 0 | U25: 0 | V25: 1 | W25: 0 | X25: 0 | Y25: 0 | Z25: 0 | AA25: 0 | AB25: 0 | AC25: 0 | AD25: 0 | AE25: 0 | AF25: 0 | AG25: 0 | AH25: 0 | AI25: 0
A26: 46 | B26: CARNES - Mojarra | C26: 30000 | D26: =+SUMPRODUCT(G26:AI26,G$2:AI$2) -> 15600 | E26: =+C26-D26 -> 14400 | F26: =1-D26/C26 -> 0.48 | G26: 0 | H26: 0 | I26: 0 | J26: 0 | K26: 1 | L26: 0 | M26: 0 | N26: 0 | O26: 0 | P26: 0 | Q26: 0 | R26: 0 | S26: 0 | T26: 0 | U26: 0 | V26: 1 | W26: 0 | X26: 0 | Y26: 1 | Z26: 0 | AA26: 0 | AB26: 0 | AC26: 0 | AD26: 0 | AE26: 0 | AF26: 0 | AG26: 0 | AH26: 0 | AI26: 0
A27: 13 | B27: CARNES - Pechuga | C27: 25000 | D27: =+SUMPRODUCT(G27:AI27,G$2:AI$2) -> 12600 | E27: =+C27-D27 -> 12400 | F27: =1-D27/C27 -> 0.496 | G27: 0 | H27: 0 | I27: 0 | J27: 0 | K27: 0 | L27: 0 | M27: 0 | N27: 0 | O27: 0 | P27: 0 | Q27: 1 | R27: 0 | S27: 0 | T27: 0 | U27: 0 | V27: 1 | W27: 0 | X27: 0 | Y27: 1 | Z27: 0 | AA27: 0 | AB27: 0 | AC27: 0 | AD27: 0 | AE27: 0 | AF27: 0 | AG27: 0 | AH27: 0 | AI27: 0
A28: 15 | B28: CARNES - Sobrebarriga - 25 | C28: 25000 | D28: =+SUMPRODUCT(G28:AI28,G$2:AI$2) -> 2600 | E28: =+C28-D28 -> 22400 | F28: =1-D28/C28 -> 0.896 | G28: 0 | H28: 0 | I28: 0 | J28: 0 | K28: 0 | L28: 0 | M28: 0 | N28: 0 | O28: 0 | P28: 0 | Q28: 0 | R28: 0 | S28: 0 | T28: 0 | U28: 0 | V28: 1 | W28: 0 | X28: 0 | Y28: 1 | Z28: 0 | AA28: 0 | AB28: 0 | AC28: 0 | AD28: 0 | AE28: 0 | AF28: 0 | AG28: 0 | AH28: 0 | AI28: 0
A29: 26 | B29: ChoriPan | C29: 10000 | D29: =+SUMPRODUCT(G29:AI29,G$2:AI$2) -> 3900 | E29: =+C29-D29 -> 6100 | F29: =1-D29/C29 -> 0.61 | G29: 1 | H29: 0 | Q29: 0 | R29: 0 | S29: 0 | T29: 0 | U29: 0 | V29: 0 | W29: 1 | X29: 0 | Y29: 0 | Z29: 0 | AA29: 0 | AB29: 0 | AC29: 0 | AD29: 0 | AE29: 0 | AF29: 0 | AG29: 0 | AH29: 0 | AI29: 0
A30: 9 | B30: Ham. Choriboni | C30: 20000 | D30: =+SUMPRODUCT(G30:AI30,G$2:AI$2) -> 8500 | E30: =+C30-D30 -> 11500 | F30: =1-D30/C30 -> 0.575 | G30: 1 | H30: 0 | Q30: 0 | R30: 0 | S30: 0 | T30: 1 | U30: 0 | V30: 0 | W30: 0 | X30: 0 | Y30: 0 | Z30: 0 | AA30: 0 | AB30: 0 | AC30: 0 | AD30: 0 | AE30: 0 | AF30: 0 | AG30: 0 | AH30: 0 | AI30: 0
A31: 10 | B31: Ham. Choriboni - Combo | C31: 25000 | D31: =+SUMPRODUCT(G31:AI31,G$2:AI$2) -> 10500 | E31: =+C31-D31 -> 14500 | F31: =1-D31/C31 -> 0.58 | G31: 1 | H31: 0 | Q31: 0 | R31: 0 | S31: 0 | T31: 1 | U31: 0 | V31: 1 | W31: 0 | X31: 0 | Y31: 0 | Z31: 0 | AA31: 0 | AB31: 0 | AC31: 0 | AD31: 0 | AE31: 0 | AF31: 0 | AG31: 0 | AH31: 0 | AI31: 0
A32: 38 | B32: Ham. Doble combo - ELIMINAR | C32: 27000 | D32: =+SUMPRODUCT(G32:AI32,G$2:AI$2) -> 10500 | E32: =+C32-D32 -> 16500 | F32: =1-D32/C32 -> 0.61111111 | G32: 1 | H32: 0 | Q32: 0 | R32: 0 | S32: 0 | T32: 1 | U32: 0 | V32: 1 | W32: 0 | X32: 0 | Y32: 0 | Z32: 0 | AA32: 0 | AB32: 0 | AC32: 0 | AD32: 0 | AE32: 0 | AF32: 0 | AG32: 0 | AH32: 0 | AI32: 0
A33: 6 | B33: Ham. combo | C33: 22000 | D33: =+SUMPRODUCT(G33:AI33,G$2:AI$2) -> 10500 | E33: =+C33-D33 -> 11500 | F33: =1-D33/C33 -> 0.52272727 | G33: 1 | H33: 0 | Q33: 0 | R33: 0 | S33: 0 | T33: 1 | U33: 0 | V33: 1 | W33: 0 | X33: 0 | Y33: 0 | Z33: 0 | AA33: 0 | AB33: 0 | AC33: 0 | AD33: 0 | AE33: 0 | AF33: 0 | AG33: 0 | AH33: 0 | AI33: 0
A34: 5 | B34: Ham. sencilla | C34: 17000 | D34: =+SUMPRODUCT(G34:AI34,G$2:AI$2) -> 8500 | E34: =+C34-D34 -> 8500 | F34: =1-D34/C34 -> 0.5 | G34: 1 | H34: 0 | Q34: 0 | R34: 0 | S34: 0 | T34: 1 | U34: 0 | V34: 0 | W34: 0 | X34: 0 | Y34: 0 | Z34: 0 | AA34: 0 | AB34: 0 | AC34: 0 | AD34: 0 | AE34: 0 | AF34: 0 | AG34: 0 | AH34: 0 | AI34: 0
A35: 37 | B35: PORCIÒN - papa francesa | C35: 1000000 | D35: =+SUMPRODUCT(G35:AI35,G$2:AI$2) -> 2000 | E35: =+C35-D35 -> 998000 | F35: =1-D35/C35 -> 0.998 | G35: 0 | H35: 0 | Q35: 0 | R35: 0 | S35: 0 | T35: 0 | U35: 0 | V35: 1 | W35: 0 | X35: 0 | Y35: 0 | Z35: 0 | AA35: 0 | AB35: 0 | AC35: 0 | AD35: 0 | AE35: 0 | AF35: 0 | AG35: 0 | AH35: 0 | AI35: 0
A36: 30 | B36: PROMO pedazo de carne | C36: 2000 | D36: =+SUMPRODUCT(G36:AI36,G$2:AI$2) -> 0 | E36: =+C36-D36 -> 2000 | F36: =1-D36/C36 -> 1 | G36: 0 | H36: 0 | Q36: 0 | R36: 0 | S36: 0 | T36: 0 | U36: 0 | V36: 0 | W36: 0 | X36: 0 | Y36: 0 | Z36: 0 | AA36: 0 | AB36: 0 | AC36: 0 | AD36: 0 | AE36: 0 | AF36: 0 | AG36: 0 | AH36: 0 | AI36: 0
A37: 31 | B37: PROMO: promo vecino de jenesano | C37: 15000 | D37: =+SUMPRODUCT(G37:AI37,G$2:AI$2) -> 0 | E37: =+C37-D37 -> 15000 | F37: =1-D37/C37 -> 1 | G37: 0 | H37: 0 | Q37: 0 | R37: 0 | S37: 0 | T37: 0 | U37: 0 | V37: 0 | W37: 0 | X37: 0 | Y37: 0 | Z37: 0 | AA37: 0 | AB37: 0 | AC37: 0 | AD37: 0 | AE37: 0 | AF37: 0 | AG37: 0 | AH37: 0 | AI37: 0
A38: 35 | B38: Parrillada de 30 | C38: 30000 | D38: =+SUMPRODUCT(G38:AI38,G$2:AI$2) -> 17940 | E38: =+C38-D38 -> 12060 | F38: =1-D38/C38 -> 0.402 | G38: 1 | H38: 0 | I38: 1 | Q38: 0 | R38: 0 | S38: 0 | T38: 0 | U38: 0 | V38: 0 | W38: 0 | X38: 1 | Y38: 1 | Z38: 0 | AA38: 0 | AB38: 0 | AC38: 0 | AD38: 0 | AE38: 0 | AF38: 0 | AG38: 0 | AH38: 0 | AI38: 0
A39: 18 | B39: Parrillada de 35 | C39: 35000 | D39: =+SUMPRODUCT(G39:AI39,G$2:AI$2) -> 17940 | E39: =+C39-D39 -> 17060 | F39: =1-D39/C39 -> 0.48742857 | G39: 1 | H39: 0 | I39: 1 | Q39: 0 | R39: 0 | S39: 0 | T39: 0 | U39: 0 | V39: 0 | W39: 0 | X39: 1 | Y39: 1 | Z39: 0 | AA39: 0 | AB39: 0 | AC39: 0 | AD39: 0 | AE39: 0 | AF39: 0 | AG39: 0 | AH39: 0 | AI39: 0
A40: 23 | B40: Parrillada de 40 | C40: 40000 | D40: =+SUMPRODUCT(G40:AI40,G$2:AI$2) -> 17940 | E40: =+C40-D40 -> 22060 | F40: =1-D40/C40 -> 0.5515 | G40: 1 | H40: 0 | I40: 1 | Q40: 0 | R40: 0 | S40: 0 | T40: 0 | U40: 0 | V40: 0 | W40: 0 | X40: 1 | Y40: 1 | Z40: 0 | AA40: 0 | AB40: 0 | AC40: 0 | AD40: 0 | AE40: 0 | AF40: 0 | AG40: 0 | AH40: 0 | AI40: 0
A41: 21 | B41: Parrillada de 48 | C41: 48000 | D41: =+SUMPRODUCT(G41:AI41,G$2:AI$2) -> 17940 | E41: =+C41-D41 -> 30060 | F41: =1-D41/C41 -> 0.62625 | G41: 1 | H41: 0 | I41: 1 | Q41: 0 | R41: 0 | S41: 0 | T41: 0 | U41: 0 | V41: 0 | W41: 0 | X41: 1 | Y41: 1 | Z41: 0 | AA41: 0 | AB41: 0 | AC41: 0 | AD41: 0 | AE41: 0 | AF41: 0 | AG41: 0 | AH41: 0 | AI41: 0
A42: 43 | B42: Parrillada de 50 | C42: 50000 | D42: =+SUMPRODUCT(G42:AI42,G$2:AI$2) -> 17940 | E42: =+C42-D42 -> 32060 | F42: =1-D42/C42 -> 0.6412 | G42: 1 | H42: 0 | I42: 1 | Q42: 0 | R42: 0 | S42: 0 | T42: 0 | U42: 0 | V42: 0 | W42: 0 | X42: 1 | Y42: 1 | Z42: 0 | AA42: 0 | AB42: 0 | AC42: 0 | AD42: 0 | AE42: 0 | AF42: 0 | AG42: 0 | AH42: 0 | AI42: 0
A43: 32 | B43: Parrillada de 60 | C43: 60000 | D43: =+SUMPRODUCT(G43:AI43,G$2:AI$2) -> 36940 | E43: =+C43-D43 -> 23060 | F43: =1-D43/C43 -> 0.38433333 | G43: 1 | H43: 0 | I43: 1 | J43: 1 | Q43: 0 | R43: 0 | S43: 0 | T43: 0 | U43: 0 | V43: 0 | W43: 0 | X43: 1 | Y43: 1 | Z43: 0 | AA43: 0 | AB43: 0 | AC43: 0 | AD43: 0 | AE43: 0 | AF43: 0 | AG43: 0 | AH43: 0 | AI43: 0
A44: 22 | B44: Parrillada de 70 | C44: 70000 | D44: =+SUMPRODUCT(G44:AI44,G$2:AI$2) -> 36940 | E44: =+C44-D44 -> 33060 | F44: =1-D44/C44 -> 0.47228571 | G44: 1 | H44: 0 | I44: 1 | J44: 1 | Q44: 0 | R44: 0 | S44: 0 | T44: 0 | U44: 0 | V44: 0 | W44: 0 | X44: 1 | Y44: 1 | Z44: 0 | AA44: 0 | AB44: 0 | AC44: 0 | AD44: 0 | AE44: 0 | AF44: 0 | AG44: 0 | AH44: 0 | AI44: 0
A45: 28 | B45: Propina - Gustavo | C45: 5000 | D45: =+SUMPRODUCT(G45:AI45,G$2:AI$2) -> 0 | E45: =+C45-D45 -> 5000 | F45: =1-D45/C45 -> 1 | G45: 0 | H45: 0 | Q45: 0 | R45: 0 | S45: 0 | T45: 0 | U45: 0 | V45: 0 | W45: 0 | X45: 0 | Y45: 0 | Z45: 0 | AA45: 0 | AB45: 0 | AC45: 0 | AD45: 0 | AE45: 0 | AF45: 0 | AG45: 0 | AH45: 0 | AI45: 0
A46: 20 | B46: Tinto | C46: 2000 | D46: =+SUMPRODUCT(G46:AI46,G$2:AI$2) -> 800 | E46: =+C46-D46 -> 1200 | F46: =1-D46/C46 -> 0.6 | G46: 0 | H46: 0 | Q46: 0 | R46: 0 | S46: 0 | T46: 0 | U46: 1 | V46: 0 | W46: 0 | X46: 0 | Y46: 0 | Z46: 0 | AA46: 0 | AB46: 0 | AC46: 0 | AD46: 0 | AE46: 0 | AF46: 0 | AG46: 0 | AH46: 0 | AI46: 0
A47: 47 | B47: chorixo solo | C47: 3500 | D47: =+SUMPRODUCT(G47:AI47,G$2:AI$2) -> 3500 | E47: =+C47-D47 -> 0 | F47: =1-D47/C47 -> 0 | G47: 1 | H47: 0 | Q47: 0 | R47: 0 | S47: 0 | T47: 0 | U47: 0 | V47: 0 | W47: 0 | X47: 0 | Y47: 0 | Z47: 0 | AA47: 0 | AB47: 0 | AC47: 0 | AD47: 0 | AE47: 0 | AF47: 0 | AG47: 0 | AH47: 0 | AI47: 0
A48: 17 | B48: z. MP - Chorizo CRUDO | C48: 4500 | D48: =+SUMPRODUCT(G48:AI48,G$2:AI$2) -> 3500 | E48: =+C48-D48 -> 1000 | F48: =1-D48/C48 -> 0.22222222 | G48: 1 | H48: 0 | Q48: 0 | R48: 0 | S48: 0 | T48: 0 | U48: 0 | V48: 0 | W48: 0 | X48: 0 | Y48: 0 | Z48: 0 | AA48: 0 | AB48: 0 | AC48: 0 | AD48: 0 | AE48: 0 | AF48: 0 | AG48: 0 | AH48: 0 | AI48: 0
A49: 25 | B49: z. MP - Hamb. CRUDA | C49: 5000 | D49: =+SUMPRODUCT(G49:AI49,G$2:AI$2) -> 0 | E49: =+C49-D49 -> 5000 | F49: =1-D49/C49 -> 1 | G49: 0 | H49: 0 | Q49: 0 | R49: 0 | S49: 0 | T49: 0 | U49: 0 | V49: 0 | W49: 0 | X49: 0 | Y49: 0 | Z49: 0 | AA49: 0 | AB49: 0 | AC49: 0 | AD49: 0 | AE49: 0 | AF49: 0 | AG49: 0 | AH49: 0 | AI49: 0
A50: 36 | B50: z. MP - papa | C50: 70000 | D50: =+SUMPRODUCT(G50:AI50,G$2:AI$2) -> 0 | E50: =+C50-D50 -> 70000 | F50: =1-D50/C50 -> 1 | G50: 0 | H50: 0 | Q50: 0 | R50: 0 | S50: 0 | T50: 0 | U50: 0 | V50: 0 | W50: 0 | X50: 0 | Y50: 0 | Z50: 0 | AA50: 0 | AB50: 0 | AC50: 0 | AD50: 0 | AE50: 0 | AF50: 0 | AG50: 0 | AH50: 0 | AI50: 0
A51: 8 | B51: z. MP - Arepa | C51: 1000 | D51: =+SUMPRODUCT(G51:AI51,G$2:AI$2) -> 0 | E51: =+C51-D51 -> 1000 | F51: =1-D51/C51 -> 1 | G51: 0 | H51: 0 | Q51: 0 | R51: 0 | S51: 0 | T51: 0 | U51: 0 | V51: 0 | W51: 0 | X51: 0 | Y51: 0 | Z51: 0 | AA51: 0 | AB51: 0 | AC51: 0 | AD51: 0 | AE51: 0 | AF51: 0 | AG51: 0 | AH51: 0 | AI51: 0
X52: 1

Sheet TICO
C2: Producto | F2: Valor
C3: Carnes | F3: 10000
C4: Chorizo | F4: 14000
B5: Tanda 1 | C5: Anguila | D5: 1 | E5: 4500 | F5: 3500 | G5: =+E5-F5 -> 1000
C6: Anguila | D6: 1 | E6: 4500 | F6: 3500 | G6: =+E6-F6 -> 1000
B7: Tanda 2 | C7: Club | D7: 1 | E7: 6000 | F7: 4000 | G7: =+E7-F7 -> 2000
C8: Central | D8: 1 | E8: 3000 | F8: 2500 | G8: =+E8-F8 -> 500
B9: Tanda 3 | C9: Central | D9: 1 | E9: 3000 | F9: 2500 | G9: =+E9-F9 -> 500 | K9: 0.10208333
C10: Central | D10: 1 | E10: 3000 | F10: 2500 | G10: =+E10-F10 -> 500
B11: Tanda 4 | C11: Central | D11: 1 | E11: 3000 | F11: 2500 | G11: =+E11-F11 -> 500
C12: Central | D12: 1 | E12: 3000 | F12: 2500 | G12: =+E12-F12 -> 500
B13: Tanda 5 | C13: Central | D13: 1 | E13: 3000 | F13: =+F12 -> 2500 | G13: =+E13-F13 -> 500
G14: =+E14-F14 -> 0
E15: Total | F15: =+SUM(F3:F14) -> 50000
E18: Nequi | F18: 16000
E19: PENDIENTE | F19: =+F15-F18 -> 34000

Sheet 16mar
C1: 15 de marzo | D1: 16 de marzo | E1: 17 de marzo
C2: 88000 | D2: =SUM(D4:D1048576) -> 84000 | E2: 176500 | F2: =+SUM(C2:E2) -> 348500
B4: 3 | C4: chorizo | D4: =8000*3 -> 24000
B5: 1 | C5: chorizo | D5: -4000 | I5: =190+20 -> 210
B6: 1 | C6: chorizo | D6: 8000
B7: 1 | C7: gaseosa | D7: 3000 | I7: =257-56 -> 201 | K7: =8*7 -> 56
B8: 1 | C8: chorizo | D8: 8000
B9: 1 | C9: gaseosa | D9: 3000
B10: 6 | C10: chorizo | D10: 48000 | H10: 197
B11: 3 | C11: gaseosa | D11: 9000 | F11: =20000+8000+8000+48000+9000+3000+3000 -> 99000 | H11: 40
C12: Transportes | D12: -15000 | H12: 20 | I12: 50
I13: =+SUM(H10:H12)-I12 -> 207
I14: 197
B15: nequi | C15: 11000
B16: nequi | C16: 10000 | G16: 207
G17: 198
G18: =+G16-G17 -> 9

Sheet Extracto (2)
C1: Nequi | D1: =+SUMIF($I$6:$I$1048576,C1,$D$6:$D$1048576) -> 762600
C2: DaviPlata | D2: =+SUMIF($I$6:$I$1048576,C2,$D$6:$D$1048576) -> 200000
D3: =+SUM(D6:D1048576) -> 1005600 | I3: Total
A5: fecha | B5: dia_sem | C5: hora | D5: valor | F5: Sopor. | G5: fact | I5: cuenta | J5: nombre_cliente | K5: telefono
A6: 46076 | B6: =+TEXT(A6,"ddd") -> lun | C6: 0.72986111 | D6: 6500 | F6: fact | I6: Nequi | J6: Papá | K6: Error
A7: 46076 | B7: =+TEXT(A7,"ddd") -> lun | D7: 24000 | F7: fact | I7: Nequi | J7: Diana Carolina Colorado Penagos
A8: 46077 | B8: =+TEXT(A8,"ddd") -> mar | C8: 0.79375 | D8: 3000 | F8: fact | I8: Nequi | J8: Lucelyz Pelaez
A9: 46077 | B9: =+TEXT(A9,"ddd") -> mar | C9: 0.82777778 | D9: 8000 | F9: fact | I9: Nequi | J9: Jeisson Gutierrez
A10: 46078 | B10: =+TEXT(A10,"ddd") -> mié | C10: 0.69444444 | D10: 8000 | F10: fact | I10: Nequi | J10: María Torres
A11: 46078 | B11: =+TEXT(A11,"ddd") -> mié | C11: 0.79444444 | D11: 8000 | F11: fact | I11: Nequi | J11: Ori****Rod*****Ma | K11: Breb-B
A12: 46078 | B12: =+TEXT(A12,"ddd") -> mié | C12: 0.80694444 | D12: 22500 | F12: fact | I12: Nequi | J12: Papá | K12: Error
A13: 46078 | B13: =+TEXT(A13,"ddd") -> mié | C13: 0.83958333 | D13: 8000 | F13: fact | I13: Nequi | J13: Juan Heredia
A14: 46078 | B14: =+TEXT(A14,"ddd") -> mié | C14: 0.79375 | D14: 16000 | F14: fact | I14: DaviPlata | J14: ND | K14: DaviPlata
A15: 46079 | B15: =+TEXT(A15,"ddd") -> jue | C15: 0.56458333 | D15: 25000 | F15: fact | I15: Nequi | J15: Claudia Arevalo | K15: 322 381 0697
A16: 46079 | B16: =+TEXT(A16,"ddd") -> jue | C16: 0.84513889 | D16: 51000 | F16: fact | I16: Nequi | J16: Papá | K16: Error
A17: 46079 | B17: =+TEXT(A17,"ddd") -> jue | C17: 0.72777778 | D17: 49000 | F17: fact | I17: Nequi | J17: Darwin Casallas
A18: 46080 | B18: =+TEXT(A18,"ddd") -> vie | C18: 0.82291667 | D18: 11000 | F18: fact | I18: DaviPlata | J18: ND | K18: DaviPlata
A19: 46080 | B19: =+TEXT(A19,"ddd") -> vie | C19: 0.84236111 | D19: 10000 | F19: fact | I19: Nequi | J19: David Aparicio
A20: 46080 | B20: =+TEXT(A20,"ddd") -> vie | C20: 0.76319444 | D20: 24000 | F20: fact | I20: Nequi | J20: Natalia Bolivar
A21: 46080 | B21: =+TEXT(A21,"ddd") -> vie | C21: 0.75972222 | D21: 11000 | F21: fact | I21: Nequi | J21: Carlos Gonzalez
A22: 46081 | B22: =+TEXT(A22,"ddd") -> sáb | D22: 280000 | F22: fact | I22: Nequi | J22: Consignación a Edwin | K22: Consignación
A23: 46081 | B23: =+TEXT(A23,"ddd") -> sáb | C23: 0.79305556 | D23: 18000 | F23: fact | I23: Nequi | J23: Mel**** ***Alb Vil*** | K23: Breb-B
A24: 46081 | B24: =+TEXT(A24,"ddd") -> sáb | C24: 0.65208333 | D24: 16000 | F24: fact | I24: Nequi | J24: María Barrios | K24: 315 826 7681
A25: 46081 | B25: =+TEXT(A25,"ddd") -> sáb | C25: 0.65138889 | D25: 13000 | F25: fact | I25: Nequi | J25: David Aparicio | K25: 321 923 1130
A26: 46084 | B26: =+TEXT(A26,"ddd") -> mar | D26: =-(D18+D14) -> -27000 | F26: Nd-Nc | I26: DaviPlata | J26: Transferencia interbancos
A27: 46084 | B27: =+TEXT(A27,"ddd") -> mar | D27: 27000 | F27: Nd-Nc | I27: Nequi | J27: Transferencia interbancos
A28: 46084 | B28: =+TEXT(A28,"ddd") -> mar | D28: -619850 | F28: Nd-Nc | I28: Nequi | J28: Pago factura del cerdo
A29: 46084 | B29: =+TEXT(A29,"ddd") -> mar | D29: 33000 | F29: fact | I29: Nequi | J29: José Isidro Pinzòn Corredor
A30: 46085 | B30: =+TEXT(A30,"ddd") -> mié | D30: 19000 | F30: fact | I30: Nequi | J30: Edu***loz***Boh**
A31: 46085 | B31: =+TEXT(A31,"ddd") -> mié | D31: 8000 | F31: fact | I31: Nequi | J31: Gre***Leo***Cor**
A32: 46085 | B32: =+TEXT(A32,"ddd") -> mié | D32: 18000 | F32: fact | I32: Nequi | J32: Recarga desde Bancolomba
A33: 46085 | B33: =+TEXT(A33,"ddd") -> mié | D33: 8000 | F33: fact | I33: Nequi | J33: Willian Gutierrez
A34: 46085 | B34: =+TEXT(A34,"ddd") -> mié | D34: 64000 | F34: fact | I34: Nequi | J34: Sergio Alarcón | N34: =+SUM(D30:D34) -> 117000
A35: 46086 | B35: =+TEXT(A35,"ddd") -> jue | D35: 30000 | F35: fact | I35: Nequi | J35: Henry Aguirre | N35: =#REF!+8000 -> #REF!
A36: 46086 | B36: =+TEXT(A36,"ddd") -> jue | D36: 11000 | F36: fact | I36: Nequi | J36: Miguel Rodriguez
A37: 46086 | B37: =+TEXT(A37,"ddd") -> jue | D37: 16000 | F37: fact | I37: Nequi | J37: Diego Tijaro
A38: 46086 | B38: =+TEXT(A38,"ddd") -> jue | D38: 39500 | F38: fact | I38: Nequi | J38: Leidy Camacho | N38: =+#REF! -> #REF!
A39: 46086 | B39: =+TEXT(A39,"ddd") -> jue | D39: 35000 | F39: fact | I39: Nequi | J39: Manuel Fernando Ramirez | N39: =+SUM(D35:D39) -> 131500
A40: 46088 | B40: =+TEXT(A40,"ddd") -> sáb | D40: 28000 | F40: fact | I40: Nequi | J40: Yeimmerson Velandia
A41: 46088 | B41: =+TEXT(A41,"ddd") -> sáb | D41: 43000 | F41: fact | J41: Adriana Pinto
A42: 46089 | B42: =+TEXT(A42,"ddd") -> dom | D42: 30000 | F42: fact | I42: Nequi | J42: Gloria Rodriguez
A43: 46089 | B43: =+TEXT(A43,"ddd") -> dom | D43: 54000 | F43: fact | I43: Nequi | J43: ALI***PAT***GUT
A44: 46089 | B44: =+TEXT(A44,"ddd") -> dom | D44: 8000 | F44: fact | I44: Nequi | J44: Marcelo Cespedes
A45: 46089 | B45: =+TEXT(A45,"ddd") -> dom | D45: 30000 | F45: fact | I45: Nequi | J45: FLO***ANG***ITA***OR
B46: =+TEXT(A46,"ddd") | C46: PENDIENTE | D46: 16000 | F46: fact | I46: Nequi | J46: Papá del 7 de marzo
A47: 46091 | B47: =+TEXT(A47,"ddd") -> mar | D47: 90000 | F47: fact | I47: Nequi | J47: Consignaciòn DaviPlata
A48: 46091 | B48: =+TEXT(A48,"ddd") -> mar | D48: -412000 | I48: Nequi | J48: Pago de la gaseosa
A49: 46091 | B49: =+TEXT(A49,"ddd") -> mar | D49: 30000 | F49: fact | I49: Nequi | J49: NEL***HER***LOP
A50: 46091 | B50: =+TEXT(A50,"ddd") -> mar | D50: 11000 | F50: fact | I50: Nequi | J50: BRIAN SANTANA
A51: 46092 | B51: =+TEXT(A51,"ddd") -> mié | D51: 8000 | F51: fact | I51: Nequi | J51: ALEX SOCARRAS
A52: 46092 | B52: =+TEXT(A52,"ddd") -> mié | D52: 24000 | F52: fact | I52: Nequi | J52: EDISON PENAGOS
A53: 46092 | B53: =+TEXT(A53,"ddd") -> mié | D53: 22000 | F53: fact | I53: Nequi | J53: BRIAN SANTANA
A54: 46092 | B54: =+TEXT(A54,"ddd") -> mié | D54: 8000 | F54: fact | I54: Nequi | J54: KATERINE SIERRA
A55: 46092 | B55: =+TEXT(A55,"ddd") -> mié | D55: 32000 | F55: fact | I55: Nequi | J55: MAI***JOS**MAI
A56: 46092 | B56: =+TEXT(A56,"ddd") -> mié | D56: 8000 | F56: fact | I56: Nequi | J56: JUAN BERMUDEZ
A57: 46092 | B57: =+TEXT(A57,"ddd") -> mié | D57: 11000 | F57: fact | I57: Nequi | J57: SAN***BEN**ROD
A58: 46084 | B58: =+TEXT(A58,"ddd") -> mar | D58: 11000 | F58: fact | I58: DaviPlata
A59: 46089 | B59: =+TEXT(A59,"ddd") -> dom | D59: 3000 | F59: fact | I59: DaviPlata
A60: 46089 | B60: =+TEXT(A60,"ddd") -> dom | D60: 76000 | F60: GIRO | I60: DaviPlata
A61: 46091 | B61: =+TEXT(A61,"ddd") -> mar | D61: -90000 | F61: Nd-Nc | I61: DaviPlata
A62: 46092 | B62: =+TEXT(A62,"ddd") -> mié | D62: 1000 | F62: fact | I62: DaviPlata
A63: 46092 | B63: =+TEXT(A63,"ddd") -> mié | D63: 22000 | F63: fact | I63: DaviPlata
A64: 46093 | B64: =+TEXT(A64,"ddd") -> jue | D64: 82000 | F64: fact | G64: 00095 | I64: DaviPlata
A65: 46093 | B65: =+TEXT(A65,"ddd") -> jue | C65: 0.73125 | D65: 11000 | F65: fact | G65: 000198 | I65: Nequi | J65: BRIAN SANTANA
A66: 46093 | B66: =+TEXT(A66,"ddd") -> jue | C66: 0.78611111 | D66: 24000 | F66: fact | G66: 000202 | I66: Nequi | J66: JOHN CRISOSTOMO
A67: 46093 | B67: =+TEXT(A67,"ddd") -> jue | D67: 24000 | F67: fact | G67: 000196 | I67: Nequi | J67: WEN***ALE***PUL
A68: 46093 | B68: =+TEXT(A68,"ddd") -> jue | D68: 11000 | F68: fact | I68: Nequi | J68: JEI***PEN***BEN***
A69: 46095 | B69: =+TEXT(A69,"ddd") -> sáb | D69: 23000 | F69: fact | G69: 00095 | I69: DaviPlata
A70: 46095 | B70: =+TEXT(A70,"ddd") -> sáb | D70: 11000 | F70: fact | G70: 00212 | I70: Nequi | J70: JEISON URIBE
A71: 46095 | B71: =+TEXT(A71,"ddd") -> sáb | D71: 11000 | F71: fact | G71: 00216 | I71: Nequi | J71: ANGIE ZUNIGA
A72: 46095 | B72: =+TEXT(A72,"ddd") -> sáb | D72: 57500 | F72: fact | I72: Nequi | J72: JUA***PAB***GAL***G
A73: 46095 | B73: =+TEXT(A73,"ddd") -> sáb | D73: 13500 | F73: fact | G73: 00217 | I73: Nequi | J73: LUIS ALBERTO ROMERO CALDERON
A74: 46096 | B74: =+TEXT(A74,"ddd") -> dom | D74: 19000 | F74: fact | I74: Nequi | J74: JUAN JOYA
A75: 46096 | B75: =+TEXT(A75,"ddd") -> dom | C75: 0.78819444 | D75: 36000 | F75: fact | I75: Nequi | J75: LUIS ALBERTO ROMERO CALDERON
A76: 46097 | B76: =+TEXT(A76,"ddd") -> lun | D76: 10000 | F76: fact | I76: Nequi | J76: DANIEL RAMOS
A77: 46097 | B77: =+TEXT(A77,"ddd") -> lun | D77: 11000 | F77: fact | I77: Nequi | J77: FELIPE GUTIERREZ
A78: 46098 | B78: =+TEXT(A78,"ddd") -> mar | D78: 8000 | F78: fact | I78: DaviPlata
A79: 46098 | B79: =+TEXT(A79,"ddd") -> mar | D79: 15000 | F79: fact | I79: DaviPlata
A80: 46098 | B80: =+TEXT(A80,"ddd") -> mar | C80: 0.66041667 | D80: 50000 | F80: fact | G80: 00240 | I80: Nequi | J80: LIDIA CAMACHO CARRERO
A81: 46098 | B81: =+TEXT(A81,"ddd") -> mar | D81: 11000 | F81: fact | G81: 00238 | I81: Nequi | J81: BRI***STI***SAN***
A82: 46098 | B82: =+TEXT(A82,"ddd") -> mar | D82: 8000 | F82: fact | G82: 0000 | I82: Nequi | J82: JESUS BOJACA
A83: 46098 | B83: =+TEXT(A83,"ddd") -> mar | D83: 9000 | F83: fact | G83: 00247 | I83: Nequi | J83: CAROLINA LEON
A84: 46098 | B84: =+TEXT(A84,"ddd") -> mar | D84: =-(40000+20000) -> -60000 | F84: Egreso | I84: Nequi | J84: Pago publicidad - banner y registradora
A85: 46099 | B85: =+TEXT(A85,"ddd") -> mié | D85: 344950 | F85: Base | I85: Nequi | J85: Transferencia del efectivo
A86: 46098 | B86: =+TEXT(A86,"ddd") -> mar | D86: 24000 | F86: fact | G86: uni | H86: Pendiente | I86: Nequi | J86: Chorizos el de publicidad
A87: 46098 | B87: =+TEXT(A87,"ddd") -> mar | D87: -24000 | F87: fact | G87: uni | H87: Pendiente | I87: Nequi | J87: Ajuste administrativo, si se tuvo en cuenta en el acumulado
A88: 46098 | B88: =+TEXT(A88,"ddd") -> mar | D88: =8000*4 -> 32000 | F88: fact | G88: 00255 | H88: Pendiente | I88: Nequi | J88: Chorizos el de publicidad
A89: 46099 | B89: =+TEXT(A89,"ddd") -> mié | D89: -40000 | F89: Egreso | I89: Nequi | J89: Pago transportes Ed
A90: 46099 | B90: =+TEXT(A90,"ddd") -> mié | D90: -40000 | F90: Egreso | I90: Nequi | J90: Pago transportes JG y Ed - 17 de marzo
A91: 46099 | B91: =+TEXT(A91,"ddd") -> mié | D91: -116000 | F91: Egreso | I91: Nequi | J91: Servicio de gas
A92: 46099 | B92: =+TEXT(A92,"ddd") -> mié | D92: =+-8500-6000 -> -14500 | F92: Egreso | I92: Nequi | J92: Llaves y ganchos
A93: 46099 | B93: =+TEXT(A93,"ddd") -> mié | D93: -50000 | F93: Egreso | I93: Nequi | J93: Transportes EA y JG
A94: 46099 | B94: =+TEXT(A94,"ddd") -> mié | D94: 38000 | F94: fact | I94: Nequi
A95: 46099 | B95: =+TEXT(A95,"ddd") -> mié | D95: 16000 | F95: fact | I95: Nequi
A96: 46099 | B96: =+TEXT(A96,"ddd") -> mié | D96: 8000 | F96: fact | I96: Nequi
A97: 46099 | B97: =+TEXT(A97,"ddd") -> mié | D97: 9000 | F97: fact | I97: Nequi
A98: 46100 | B98: =+TEXT(A98,"ddd") -> jue | D98: 11000 | F98: fact | I98: DaviPlata
A99: 46100 | B99: =+TEXT(A99,"ddd") -> jue | D99: 8000 | F99: fact | G99: 268 | I99: Nequi | J99: ALEXA PENA
A100: 46100 | B100: =+TEXT(A100,"ddd") -> jue | D100: 14000 | F100: fact | G100: 270 | I100: Nequi | J100: JULIAN NIETO
A101: 46100 | B101: =+TEXT(A101,"ddd") -> jue | D101: 8000 | F101: fact | G101: 270 | I101: Nequi | J101: JULIAN NIETO
...

Sheet Inf - Extracto
A1: cuenta | B1: Nequi
A3: Etiquetas de fila | B3: Suma de valor | C3: Extracto | E3: Libro Aux
A4: 46076 | B4: 30500
A5: 46077 | B5: 11000 | C5: =+B4+B5 -> 41500 | D5: =+_xlfn.XLOOKUP(A5,'[1]inf_Libro Auxiliar'!$A:$A,'[1]inf_Libro Auxiliar'!$G:$G) -> #NAME? | E5: =+C5-D5 -> #NAME?
A6: 46078 | B6: 46500 | C6: =+C5+B6 -> 88000 | D6: =+_xlfn.XLOOKUP(A6,'[1]inf_Libro Auxiliar'!$A:$A,'[1]inf_Libro Auxiliar'!$G:$G) -> #NAME? | E6: =+C6-D6 -> #NAME?
A7: 46079 | B7: 125000 | C7: =+C6+B7 -> 213000 | D7: =+_xlfn.XLOOKUP(A7,'[1]inf_Libro Auxiliar'!$A:$A,'[1]inf_Libro Auxiliar'!$G:$G) -> #NAME? | E7: =+C7-D7 -> #NAME?
A8: 46080 | B8: 45000 | C8: =+C7+B8 -> 258000 | D8: =+_xlfn.XLOOKUP(A8,'[1]inf_Libro Auxiliar'!$A:$A,'[1]inf_Libro Auxiliar'!$G:$G) -> #NAME? | E8: =+C8-D8 -> #NAME?
A9: 46081 | B9: 327000 | C9: =+C8+B9 -> 585000 | D9: =+_xlfn.XLOOKUP(A9,'[1]inf_Libro Auxiliar'!$A:$A,'[1]inf_Libro Auxiliar'!$G:$G) -> #NAME? | E9: =+C9-D9 -> #NAME?
A10: 46084 | B10: -539850 | C10: =+C9+B10 -> 45150 | D10: =+_xlfn.XLOOKUP(A10,'[1]inf_Libro Auxiliar'!$A:$A,'[1]inf_Libro Auxiliar'!$G:$G) -> #NAME? | E10: =+C10-D10 -> #NAME?
A11: 46085 | B11: 117000 | C11: =+C10+B11 -> 162150 | D11: =+_xlfn.XLOOKUP(A11,'[1]inf_Libro Auxiliar'!$A:$A,'[1]inf_Libro Auxiliar'!$G:$G) -> #NAME? | E11: =+C11-D11 -> #NAME?
A12: 46086 | B12: 131500 | C12: =+C11+B12 -> 293650 | D12: =+_xlfn.XLOOKUP(A12,'[1]inf_Libro Auxiliar'!$A:$A,'[1]inf_Libro Auxiliar'!$G:$G) -> #NAME? | E12: =+C12-D12 -> #NAME?
A13: 46088 | B13: 71000 | C13: =+C12+B13 -> 364650 | D13: =+_xlfn.XLOOKUP(A13,'[1]inf_Libro Auxiliar'!$A:$A,'[1]inf_Libro Auxiliar'!$G:$G) -> #NAME? | E13: =+C13-D13 -> #NAME?
A14: 46089 | B14: 138000 | C14: =+C13+B14 -> 502650 | D14: =+_xlfn.XLOOKUP(A14,'[1]inf_Libro Auxiliar'!$A:$A,'[1]inf_Libro Auxiliar'!$G:$G) -> #NAME? | E14: =+C14-D14 -> #NAME?
A15: 46091 | B15: -281000 | C15: =+C14+B15 -> 221650 | D15: =+_xlfn.XLOOKUP(A15,'[1]inf_Libro Auxiliar'!$A:$A,'[1]inf_Libro Auxiliar'!$G:$G) -> #NAME? | E15: =+C15-D15 -> #NAME?
A16: 46092 | B16: 113000 | C16: =+C15+B16 -> 334650 | D16: =+_xlfn.XLOOKUP(A16,'[1]inf_Libro Auxiliar'!$A:$A,'[1]inf_Libro Auxiliar'!$G:$G) -> #NAME? | E16: =+C16-D16 -> #NAME?
A17: 46093 | B17: 70000 | C17: =+C16+B17 -> 404650 | D17: =+_xlfn.XLOOKUP(A17,'[1]inf_Libro Auxiliar'!$A:$A,'[1]inf_Libro Auxiliar'!$G:$G) -> #NAME? | E17: =+C17-D17 -> #NAME?
... A29: 46109 | B29: 86000 | C29: =+C28+B29 -> 911600 | D29: =+_xlfn.XLOOKUP(A29,'[1]inf_Libro Auxiliar'!$A:$A,'[1]inf_Libro Auxiliar'!$G:$G) -> #NAME? | E29: =+C29-D29 -> #NAME?
A30: Total general | B30: 911600 | D30: =+_xlfn.XLOOKUP(A30,'[1]inf_Libro Auxiliar'!$A:$A,'[1]inf_Libro Auxiliar'!$G:$G) -> #NAME? | E30: =+C30-D30 -> #NAME?

Sheet Prestamos
B1: Valor a favor de Gustavo | C1: =+SUM(C3:C1048576) -> 40
A2: fecha | B2: Consepto | C2: Valor
A3: 46076 | B3: Base prestamo José | C3: 73700
A4: 46080 | B4: prestamo a jose | C4: -300000
A5: 46081 | B5: devolución a Nequi | C5: 280000
A6: 46080 | B6: Pago de nequi pendiente | C6: -16000
A7: 46081 | B7: Retiro efectivo de la semana | C7: -350000
A8: 46081 | B8: Prestamo consepto aguacate | C8: 30000
A9: 46076 | B9: Hamburguesa: Carne de res, cerdo, ingredientes | C9: =195000+140000+20000 -> 355000
A10: 46084 | B10: Cerdo para servicios | C10: 619850
A11: 46084 | B11: Pago Cerdo para cervicios | C11: -619850
A12: 46083 | B12: nomina mayerli | C12: 50000
A13: 46085 | B13: Filete y pierna de pechuga | C13: 46350
A14: 46085 | B14: huevos | C14: 16500
A15: 46085 | B15: regillas para la losa | C15: 11000
A16: 46085 | B16: jabón liquido | C16: 3500
A17: 46085 | B17: Districarnes | C17: 124400
A18: 46085 | B18: Pago prestamo | C18: -201750
A19: 46085 | B19: Pago prestamo | C19: -122700
A21: 46086 | B21: Propina a Gustavo | C21: 5000
A22: 46089 | B22: Carne de res - porciones | C22: 129000
A23: 46089 | B23: Carne de cerdo -6 libras | C23: =6*8000 -> 48000
A24: 46089 | B24: Pago prestamo | C24: -100000
A25: 46092 | B25: Producido del dia | C25: -100000
A26: 46093 | B26: Aceite premium | C26: 23990 | D26: mP
A27: 46093 | B27: mercado, lechuga, mango… | C27: 45400
A28: 46185 | B28: Pago prestamo | C28: -51350

Sheet Arqueo de Caja (2)
C1: =+TEXT(C2,"ddd") -> lun | E1: =+TEXT(E2,"ddd") -> mar | G1: =+TEXT(G2,"ddd") -> mié | I1: =+TEXT(I2,"ddd") -> jue | K1: =+TEXT(K2,"ddd") -> vie | M1: =+TEXT(M2,"ddd") -> sáb | O1: =+TEXT(O2,"ddd") -> dom | Q1: =+TEXT(Q2,"ddd") -> lun | S1: =+TEXT(S2,"ddd") -> mar | U1: =+TEXT(U2,"ddd") -> mié | W1: =+TEXT(W2,"ddd") -> jue | Y1: =+TEXT(Y2,"ddd") -> sáb | AA1: =+TEXT(AA2,"ddd") -> dom | AC1: =+TEXT(AC2,"ddd") -> lun | AE1: =+TEXT(AE2,"ddd") -> mar | AG1: =+TEXT(AG2,"ddd") -> mié | AI1: =+TEXT(AI2,"ddd") -> jue | AK1: =+TEXT(AK2,"ddd") -> vie | AM1: =+TEXT(AM2,"ddd") -> sáb | AO1: =+TEXT(AO2,"ddd") -> dom | AQ1: =+TEXT(AQ2,"ddd") -> lun | AS1: =+TEXT(AS2,"ddd") -> mar | AU1: =+TEXT(AU2,"ddd") -> mié | AW1: =+TEXT(AW2,"ddd") -> jue | AY1: =+TEXT(AY2,"ddd") -> vie | BA1: =+TEXT(BA2,"ddd") -> sáb | BC1: =+TEXT(BC2,"ddd") -> dom | BE1: =+TEXT(BE2,"ddd") -> lun | BG1: =+TEXT(BG2,"ddd") -> mar | BI1: =+TEXT(BI2,"ddd") -> mié | BK1: =+TEXT(BK2,"ddd") -> jue
A2: valor billete | B2: Q | C2: 46076 | D2: Q | E2: 46077 | F2: Q | G2: 46078 | H2: Q | I2: 46079 | J2: Q | K2: 46080 | L2: Q | M2: 46081 | N2: Q | O2: 46082 | P2: Q | Q2: 46083 | R2: Q | S2: 46084 | T2: Q | U2: 46085 | V2: Q | W2: 46086 | X2: Q | Y2: 46088 | Z2: Q | AA2: 46089 | AB2: Q | AC2: 46090 | AD2: Q | AE2: 46091 | AF2: Q | AG2: 46092 | AH2: Q | AI2: 46093 | AJ2: Q | AK2: 46094 | AL2: Q | AM2: 46095 | AN2: Q | AO2: 46096 | AP2: Q | AQ2: =+AO2+1 -> 46097 | AR2: Q | AS2: =+AQ2+1 -> 46098 | AT2: Q | AU2: =+AS2+1 -> 46099 | AV2: Q | AW2: =+AU2+1 -> 46100 | AX2: Q | AY2: =+AW2+1 -> 46101 | AZ2: Q | BA2: =+AY2+1 -> 46102 | BB2: Q | BC2: =+BA2+1 -> 46103 | BD2: Q | BE2: =+BC2+1 -> 46104 | BF2: Q | BG2: =+BE2+1 -> 46105 | BH2: Q | BI2: =+BG2+1 -> 46106 | BJ2: Q | BK2: =+BI2+1 -> 46107
A3: 100000 | B3: 0 | C3: =+$A3*B3 -> 0 | D3: 0 | E3: =+$A3*D3 -> 0 | F3: 0 | H3: 0 | I3: =+$A3*H3 -> 0 | J3: 1 | K3: =+$A3*J3 -> 100000 | M3: =+$A3*L3 -> 0 | O3: =+$A3*N3 -> 0 | P3: 0 | Q3: =+$A3*P3 -> 0 | R3: 0 | T3: 0 | U3: 0 | V3: 0 | W3: 0 | X3: 0 | Y3: 0 | Z3: 0 | AA3: 0 | AB3: 2 | AC3: =+$A3*AB3 -> 200000 | AD3: 0 | AE3: =+$A3*AD3 -> 0 | AF3: 0 | AG3: =+$A3*AF3 -> 0 | AH3: 0 | AI3: =+$A3*AH3 -> 0 | AL3: 0 | AM3: =+$A3*AL3 -> 0 | AN3: 0 | AO3: =+$A3*AN3 -> 0 | AQ3: =+$A3*AP3 -> 0 | AR3: 0 | AS3: =+$A3*AR3 -> 0 | AT3: 0 | AU3: =+$A3*AT3 -> 0 | AV3: 1 | AW3: =+$A3*AV3 -> 100000 | AX3: 0 | AY3: =+$A3*AX3 -> 0 | AZ3: 0 | BA3: =+$A3*AZ3 -> 0 | BB3: 0 | BC3: =+$A3*BB3 -> 0 | BD3: 0 | BE3: =+$A3*BD3 -> 0 | BF3: 0 | BG3: =+$A3*BF3 -> 0 | BH3: 0 | BI3: =+$A3*BH3 -> 0 | BJ3: 0 | BK3: =+$A3*BJ3 -> 0
A4: 50000 | B4: 1 | C4: =+A4*B4 -> 50000 | D4: 1 | E4: =+$A4*D4 -> 50000 | F4: 1 | H4: 0 | I4: =+$A4*H4 -> 0 | J4: 2 | K4: =+$A4*J4 -> 100000 | L4: 0 | M4: =+$A4*L4 -> 0 | N4: 0 | O4: =+$A4*N4 -> 0 | P4: 1 | Q4: =+$A4*P4 -> 50000 | R4: 1 | T4: 0 | U4: =+$A4*T4 -> 0 | V4: 1 | W4: =+$A4*V4 -> 50000 | X4: 0 | Y4: =+$A4*X4 -> 0 | Z4: 1 | AA4: =+$A4*Z4 -> 50000 | AB4: 0 | AC4: =+$A4*AB4 -> 0 | AD4: 1 | AE4: =+$A4*AD4 -> 50000 | AF4: 0 | AG4: =+$A4*AF4 -> 0 | AH4: 0 | AI4: =+$A4*AH4 -> 0 | AL4: 0 | AM4: =+$A4*AL4 -> 0 | AN4: 0 | AO4: =+$A4*AN4 -> 0 | AQ4: =+$A4*AP4 -> 0 | AR4: 0 | AS4: =+$A4*AR4 -> 0 | AT4: 0 | AU4: =+$A4*AT4 -> 0 | AV4: 2 | AW4: =+$A4*AV4 -> 100000 | AX4: 0 | AY4: =+$A4*AX4 -> 0 | AZ4: 0 | BA4: =+$A4*AZ4 -> 0 | BB4: 0 | BC4: =+$A4*BB4 -> 0 | BD4: 0 | BE4: =+$A4*BD4 -> 0 | BF4: 0 | BG4: =+$A4*BF4 -> 0 | BH4: 0 | BI4: =+$A4*BH4 -> 0 | BJ4: 0 | BK4: =+$A4*BJ4 -> 0
A5: 20000 | B5: 4 | C5: =+A5*B5 -> 80000 | D5: 5 | E5: =+$A5*D5 -> 100000 | F5: 5 | H5: 4 | I5: =+$A5*H5 -> 80000 | K5: =+$A5*J5 -> 0 | L5: 0 | M5: =+$A5*L5 -> 0 | N5: 0 | O5: =+$A5*N5 -> 0 | P5: 1 | Q5: =+$A5*P5 -> 20000 | R5: 1 | T5: 0 | U5: =+$A5*T5 -> 0 | V5: 0 | W5: =+$A5*V5 -> 0 | X5: 0 | Y5: =+$A5*X5 -> 0 | Z5: 1 | AA5: =+$A5*Z5 -> 20000 | AB5: 0 | AC5: =+$A5*AB5 -> 0 | AD5: 0 | AE5: =+$A5*AD5 -> 0 | AF5: 0 | AG5: =+$A5*AF5 -> 0 | AH5: 0 | AI5: =+$A5*AH5 -> 0 | AL5: 2 | AM5: =+$A5*AL5 -> 40000 | AN5: 0 | AO5: =+$A5*AN5 -> 0 | AQ5: =+$A5*AP5 -> 0 | AR5: 0 | AS5: =+$A5*AR5 -> 0 | AT5: 0 | AU5: =+$A5*AT5 -> 0 | AV5: 0 | AW5: =+$A5*AV5 -> 0 | AX5: 0 | AY5: =+$A5*AX5 -> 0 | AZ5: 3 | BA5: =+$A5*AZ5 -> 60000 | BB5: 0 | BC5: =+$A5*BB5 -> 0 | BD5: 0 | BE5: =+$A5*BD5 -> 0 | BF5: 4 | BG5: =+$A5*BF5 -> 80000 | BH5: 0 | BI5: =+$A5*BH5 -> 0 | BJ5: 0 | BK5: =+$A5*BJ5 -> 0
A6: 10000 | B6: 2 | C6: =+A6*B6 -> 20000 | D6: 2 | E6: =+$A6*D6 -> 20000 | F6: 2 | H6: 1 | I6: =+$A6*H6 -> 10000 | J6: 1 | K6: =+$A6*J6 -> 10000 | L6: 5 | M6: =+$A6*L6 -> 50000 | N6: 5 | O6: =+$A6*N6 -> 50000 | P6: 4 | Q6: =+$A6*P6 -> 40000 | R6: 4 | T6: 4 | U6: =+$A6*T6 -> 40000 | V6: 2 | W6: =+$A6*V6 -> 20000 | X6: 1 | Y6: =+$A6*X6 -> 10000 | Z6: 1 | AA6: =+$A6*Z6 -> 10000 | AB6: 2 | AC6: =+$A6*AB6 -> 20000 | AD6: 1 | AE6: =+$A6*AD6 -> 10000 | AF6: 0 | AG6: =+$A6*AF6 -> 0 | AH6: 1 | AI6: =+$A6*AH6 -> 10000 | AL6: 4 | AM6: =+$A6*AL6 -> 40000 | AN6: 0 | AO6: =+$A6*AN6 -> 0 | AQ6: =+$A6*AP6 -> 0 | AR6: 4 | AS6: =+$A6*AR6 -> 40000 | AT6: 5 | AU6: =+$A6*AT6 -> 50000 | AV6: 1 | AW6: =+$A6*AV6 -> 10000 | AX6: 0 | AY6: =+$A6*AX6 -> 0 | AZ6: 0 | BA6: =+$A6*AZ6 -> 0 | BB6: 0 | BC6: =+$A6*BB6 -> 0 | BD6: 0 | BE6: =+$A6*BD6 -> 0 | BF6: 6 | BG6: =+$A6*BF6 -> 60000 | BH6: 0 | BI6: =+$A6*BH6 -> 0 | BJ6: 0 | BK6: =+$A6*BJ6 -> 0
A7: 5000 | B7: 2 | C7: =+A7*B7 -> 10000 | D7: 4 | E7: =+$A7*D7 -> 20000 | F7: 4 | H7: 6 | I7: =+$A7*H7 -> 30000 | J7: 5 | K7: =+$A7*J7 -> 25000 | L7: 5 | M7: =+$A7*L7 -> 25000 | N7: 5 | O7: =+$A7*N7 -> 25000 | P7: 3 | Q7: =+$A7*P7 -> 15000 | R7: 3 | T7: 3 | U7: =+$A7*T7 -> 15000 | V7: 4 | W7: =+$A7*V7 -> 20000 | X7: 0 | Y7: =+$A7*X7 -> 0 | Z7: 0 | AA7: =+$A7*Z7 -> 0 | AB7: 3 | AC7: =+$A7*AB7 -> 15000 | AD7: 3 | AE7: =+$A7*AD7 -> 15000 | AF7: 5 | AG7: =+$A7*AF7 -> 25000 | AH7: 3 | AI7: =+$A7*AH7 -> 15000 | AL7: 8 | AM7: =+$A7*AL7 -> 40000 | AN7: 3 | AO7: =+$A7*AN7 -> 15000 | AQ7: =+$A7*AP7 -> 0 | AR7: 3 | AS7: =+$A7*AR7 -> 15000 | AT7: 10 | AU7: =+$A7*AT7 -> 50000 | AV7: 8 | AW7: =+$A7*AV7 -> 40000 | AX7: 6 | AY7: =+$A7*AX7 -> 30000 | AZ7: 3 | BA7: =+$A7*AZ7 -> 15000 | BB7: 0 | BC7: =+$A7*BB7 -> 0 | BD7: 0 | BE7: =+$A7*BD7 -> 0 | BF7: 1 | BG7: =+$A7*BF7 -> 5000 | BH7: 0 | BI7: =+$A7*BH7 -> 0 | BJ7: 0 | BK7: =+$A7*BJ7 -> 0
A8: 2000 | B8: 4 | C8: =+A8*B8 -> 8000 | D8: 5 | E8: =+$A8*D8 -> 10000 | F8: 5 | H8: 12 | I8: =+$A8*H8 -> 24000 | J8: 17 | K8: =+$A8*J8 -> 34000 | L8: 14 | M8: =+$A8*L8 -> 28000 | N8: 14 | O8: =+$A8*N8 -> 28000 | P8: 10 | Q8: =+$A8*P8 -> 20000 | R8: 10 | T8: 12 | U8: =+$A8*T8 -> 24000 | V8: 22 | W8: =+$A8*V8 -> 44000 | X8: 23 | Y8: =+$A8*X8 -> 46000 | Z8: 20 | AA8: =+$A8*Z8 -> 40000 | AB8: 25 | AC8: =+$A8*AB8 -> 50000 | AD8: 25 | AE8: =+$A8*AD8 -> 50000 | AF8: 25 | AG8: =+$A8*AF8 -> 50000 | AH8: 20 | AI8: =+$A8*AH8 -> 40000 | AL8: 23 | AM8: =+$A8*AL8 -> 46000 | AN8: 18 | AO8: =+$A8*AN8 -> 36000 | AQ8: =+$A8*AP8 -> 0 | AR8: 3 | AS8: =+$A8*AR8 -> 6000 | AT8: 15 | AU8: =+$A8*AT8 -> 30000 | AV8: 23 | AW8: =+$A8*AV8 -> 46000 | AX8: 21 | AY8: =+$A8*AX8 -> 42000 | AZ8: 18 | BA8: =+$A8*AZ8 -> 36000 | BB8: 0 | BC8: =+$A8*BB8 -> 0 | BD8: 0 | BE8: =+$A8*BD8 -> 0 | BF8: 18 | BG8: =+$A8*BF8 -> 36000 | BH8: 0 | BI8: =+$A8*BH8 -> 0 | BJ8: 0 | BK8: =+$A8*BJ8 -> 0
A9: 1000 | B9: 7 | C9: =+A9*B9 -> 7000 | D9: 8 | E9: =+$A9*D9 -> 8000 | F9: 8 | H9: 3 | I9: =+$A9*H9 -> 3000 | J9: 2 | K9: =+$A9*J9 -> 2000 | L9: 0 | M9: =+$A9*L9 -> 0 | N9: 0 | O9: =+$A9*N9 -> 0 | P9: 0 | Q9: =+$A9*P9 -> 0 | R9: 0 | T9: 20 | U9: =+$A9*T9 -> 20000 | V9: 16 | W9: =+$A9*V9 -> 16000 | X9: 12 | Y9: =+$A9*X9 -> 12000 | Z9: 9 | AA9: =+$A9*Z9 -> 9000 | AB9: 6 | AC9: =+$A9*AB9 -> 6000 | AD9: 11 | AE9: =+$A9*AD9 -> 11000 | AF9: 10 | AG9: =+$A9*AF9 -> 10000 | AH9: 6 | AI9: =+$A9*AH9 -> 6000 | AL9: 11 | AM9: =+$A9*AL9 -> 11000 | AN9: 9 | AO9: =+$A9*AN9 -> 9000 | AQ9: =+$A9*AP9 -> 0 | AR9: 3 | AS9: =+$A9*AR9 -> 3000 | AT9: 14 | AU9: =+$A9*AT9 -> 14000 | AV9: 7 | AW9: =+$A9*AV9 -> 7000 | AX9: 7 | AY9: =+$A9*AX9 -> 7000 | AZ9: 6 | BA9: =+$A9*AZ9 -> 6000 | BB9: 0 | BC9: =+$A9*BB9 -> 0 | BD9: 0 | BE9: =+$A9*BD9 -> 0 | BF9: 6 | BG9: =+$A9*BF9 -> 6000 | BH9: 0 | BI9: =+$A9*BH9 -> 0 | BJ9: 0 | BK9: =+$A9*BJ9 -> 0
A10: 500 | B10: 31 | C10: =+A10*B10 -> 15500 | D10: 32 | E10: =+$A10*D10 -> 16000 | F10: 32 | H10: 38 | I10: =+$A10*H10 -> 19000 | J10: 37 | K10: =+$A10*J10 -> 18500 | L10: 36 | M10: =+$A10*L10 -> 18000 | N10: 36 | O10: =+$A10*N10 -> 18000 | P10: 36 | Q10: =+$A10*P10 -> 18000 | R10: 36 | T10: 40 | U10: =+$A10*T10 -> 20000 | V10: 45 | W10: =+$A10*V10 -> 22500 | X10: 31 | Y10: =+$A10*X10 -> 15500 | Z10: 20 | AA10: =+$A10*Z10 -> 10000 | AB10: 21 | AC10: =+$A10*AB10 -> 10500 | AD10: 21 | AE10: =+$A10*AD10 -> 10500 | AF10: 35 | AG10: =+$A10*AF10 -> 17500 | AH10: 20 | AI10: =+$A10*AH10 -> 10000 | AL10: 42 | AM10: =+$A10*AL10 -> 21000 | AN10: 44 | AO10: =+$A10*AN10 -> 22000 | AQ10: =+$A10*AP10 -> 0 | AR10: 46 | AS10: =+$A10*AR10 -> 23000 | AT10: 50 | AU10: =+$A10*AT10 -> 25000 | AV10: 49 | AW10: =+$A10*AV10 -> 24500 | AX10: 49 | AY10: =+$A10*AX10 -> 24500 | AZ10: 48 | BA10: =+$A10*AZ10 -> 24000 | BB10: 0 | BC10: =+$A10*BB10 -> 0 | BD10: 0 | BE10: =+$A10*BD10 -> 0 | BF10: 49 | BG10: =+$A10*BF10 -> 24500 | BH10: 0 | BI10: =+$A10*BH10 -> 0 | BJ10: 0 | BK10: =+$A10*BJ10 -> 0
A11: 200 | B11: 54 | C11: =+A11*B11 -> 10800 | D11: 56 | E11: =+$A11*D11 -> 11200 | F11: 56 | H11: 62 | I11: =+$A11*H11 -> 12400 | J11: 62 | K11: =+$A11*J11 -> 12400 | L11: 68 | M11: =+$A11*L11 -> 13600 | N11: 68 | O11: =+$A11*N11 -> 13600 | P11: 81 | Q11: =+$A11*P11 -> 16200 | R11: 81 | T11: 3 | U11: =+$A11*T11 -> 600 | V11: 5 | W11: =+$A11*V11 -> 1000 | X11: 4 | Y11: =+$A11*X11 -> 800 | Z11: 4 | AA11: =+$A11*Z11 -> 800 | AB11: 7 | AC11: =+$A11*AB11 -> 1400 | AD11: 13 | AE11: =+$A11*AD11 -> 2600 | AF11: 9 | AG11: =+$A11*AF11 -> 1800 | AH11: 6 | AI11: =+$A11*AH11 -> 1200 | AL11: 10 | AM11: =+$A11*AL11 -> 2000 | AN11: 13 | AO11: =+$A11*AN11 -> 2600 | AQ11: =+$A11*AP11 -> 0 | AR11: 25 | AS11: =+$A11*AR11 -> 5000 | AT11: 10 | AU11: =+$A11*AT11 -> 2000 | AV11: 10 | AW11: =+$A11*AV11 -> 2000 | AX11: 14 | AY11: =+$A11*AX11 -> 2800 | AZ11: 9 | BA11: =+$A11*AZ11 -> 1800 | BB11: 0 | BC11: =+$A11*BB11 -> 0 | BD11: 0 | BE11: =+$A11*BD11 -> 0 | BF11: 9 | BG11: =+$A11*BF11 -> 1800 | BH11: 0 | BI11: =+$A11*BH11 -> 0 | BJ11: 0 | BK11: =+$A11*BJ11 -> 0
A12: 100 | B12: 38 | C12: =+A12*B12 -> 3800 | D12: 39 | E12: =+$A12*D12 -> 3900 | F12: 39 | H12: 51 | I12: =+$A12*H12 -> 5100 | J12: 48 | K12: =+$A12*J12 -> 4800 | L12: 63 | M12: =+$A12*L12 -> 6300 | N12: 63 | O12: =+$A12*N12 -> 6300 | P12: 77 | Q12: =+$A12*P12 -> 7700 | R12: 77 | T12: 9 | U12: =+$A12*T12 -> 900 | V12: 11 | W12: =+$A12*V12 -> 1100 | X12: 13 | Y12: =+$A12*X12 -> 1300 | Z12: 13 | AA12: =+$A12*Z12 -> 1300 | AB12: 14 | AC12: =+$A12*AB12 -> 1400 | AD12: 15 | AE12: =+$A12*AD12 -> 1500 | AF12: 15 | AG12: =+$A12*AF12 -> 1500 | AH12: 17 | AI12: =+$A12*AH12 -> 1700 | AL12: 29 | AM12: =+$A12*AL12 -> 2900 | AN12: 29 | AO12: =+$A12*AN12 -> 2900 | AQ12: =+$A12*AP12 -> 0 | AR12: 30 | AS12: =+$A12*AR12 -> 3000 | AT12: 12 | AU12: =+$A12*AT12 -> 1200 | AV12: 11 | AW12: =+$A12*AV12 -> 1100 | AX12: 13 | AY12: =+$A12*AX12 -> 1300 | AZ12: 13 | BA12: =+$A12*AZ12 -> 1300 | BB12: 0 | BC12: =+$A12*BB12 -> 0 | BD12: 0 | BE12: =+$A12*BD12 -> 0 | BF12: 13 | BG12: =+$A12*BF12 -> 1300 | BH12: 0 | BI12: =+$A12*BH12 -> 0 | BJ12: 0 | BK12: =+$A12*BJ12 -> 0
A13: 50 | B13: 10 | C13: =+A13*B13 -> 500 | D13: 10 | E13: =+$A13*D13 -> 500 | F13: 10 | H13: 10 | I13: =+$A13*H13 -> 500 | J13: 10 | K13: =+$A13*J13 -> 500 | L13: 10 | M13: =+$A13*L13 -> 500 | N13: 10 | O13: =+$A13*N13 -> 500 | P13: 14 | Q13: =+$A13*P13 -> 700 | R13: 14 | T13: 9 | U13: =+$A13*T13 -> 450 | V13: 9 | W13: =+$A13*V13 -> 450 | X13: 8 | Y13: =+$A13*X13 -> 400 | Z13: 11 | AA13: =+$A13*Z13 -> 550 | AB13: 9 | AC13: =+$A13*AB13 -> 450 | AD13: 8 | AE13: =+$A13*AD13 -> 400 | AF13: 8 | AG13: =+$A13*AF13 -> 400 | AH13: 7 | AI13: =+$A13*AH13 -> 350 | AL13: 9 | AM13: =+$A13*AL13 -> 450 | AN13: 10 | AO13: =+$A13*AN13 -> 500 | AQ13: =+$A13*AP13 -> 0 | AR13: 10 | AS13: =+$A13*AR13 -> 500 | AT13: 11 | AU13: =+$A13*AT13 -> 550 | AV13: 12 | AW13: =+$A13*AV13 -> 600 | AX13: 12 | AY13: =+$A13*AX13 -> 600 | AZ13: 12 | BA13: =+$A13*AZ13 -> 600 | BB13: 0 | BC13: =+$A13*BB13 -> 0 | BD13: 0 | BE13: =+$A13*BD13 -> 0 | BF13: 12 | BG13: =+$A13*BF13 -> 600 | BH13: 0 | BI13: =+$A13*BH13 -> 0 | BJ13: 0 | BK13: =+$A13*BJ13 -> 0
C14: =+SUM(C3:C13) -> 205600 | E14: =+SUM(E3:E13)+SUM('historial de venta'!G32:G37) -> 315600 | G14: 0 | I14: =100000+(315000-10000) -> 405000 | K14: =115000+105200 -> 220200 | M14: =SUM(M3:M13) -> 141400 | O14: =SUM(O3:O13) -> 141400 | Q14: =SUM(Q3:Q13) -> 187600 | U14: =SUM(U3:U13) -> 120950 | W14: =SUM(W3:W13) -> 175050 | Y14: =SUM(Y3:Y13) -> 86000 | AA14: =SUM(AA3:AA13) -> 141650 | AC14: =SUM(AC3:AC13) -> 304750 | AE14: =SUM(AE3:AE13) -> 151000 | AG14: =SUM(AG3:AG13) -> 106200 | AI14: =SUM(AI3:AI13) -> 84250 | AK14: =SUM(AK3:AK13) -> 0 | AM14: =SUM(AM3:AM13) -> 203350 | AO14: =SUM(AO3:AO13) -> 88000 | AQ14: =SUM(AQ3:AQ13) -> 0 | AS14: =SUM(AS3:AS13) -> 95500 | AU14: =SUM(AU3:AU13) -> 172750 | AW14: =SUM(AW3:AW13) -> 331200 | AY14: =SUM(AY3:AY13) -> 108200 | BA14: =SUM(BA3:BA13) -> 144700 | BC14: =SUM(BC3:BC13) -> 0 | BE14: =SUM(BE3:BE13) -> 0 | BG14: =SUM(BG3:BG13) -> 215200 | BI14: =SUM(BI3:BI13) -> 0 | BK14: =SUM(BK3:BK13) -> 0
U15: 324300 | BC15: =+BA14-BG18 -> 0
M16: =+K14-M18 -> 95200 | BA16: =+BA18+BC15 -> 108200
A17: Consepto | C17: lunes | E17: martes | G17: miercoles | I17: jueves | K17: viernes | M17: sábado | O17: =+O1 -> dom | Q17: =+Q1 -> lun | S17: =+S1 -> mar | U17: =+U1 -> mié | W17: =+W1 -> jue | Y17: =+Y1 -> sáb | AA17: =+AA1 -> dom | AC17: =+AC1 -> lun | AE17: =+AE1 -> mar | AG17: =+AG1 -> mié | AI17: =+AI1 -> jue | AK17: =+AK1 -> vie | AM17: =+AM1 -> sáb | AO17: =+AO1 -> dom | AQ17: =+AQ1 -> lun | AS17: =+AS1 -> mar | AU17: =+AU1 -> mié | AW17: =+AW1 -> jue | AY17: =+AY1 -> vie | BA17: =+BA1 -> sáb | BC17: =+BC1 -> dom | BE17: =+BE1 -> lun | BG17: =+BG1 -> mar | BI17: =+BI1 -> mié | BK17: =+BK1 -> jue
A18: Base | C18: 73700 | E18: =$C$23 -> 205600 | G18: =+E23 -> 315600 | I18: =+G23 -> 412900 | K18: =+I23 -> 405000 | M18: 125000 | O18: =+M14 -> 141400 | Q18: =+O18 -> 141400 | S18: =+Q23 -> 201400 | U18: =+S23 -> 252000 | W18: =+U23 -> 103550 | Y18: =+W23 -> 179050 | AA18: =$Y$14 -> 86000 | AC18: =+AA14 -> 141650 | AE18: 100000 | AG18: =+AE18+AE20 -> 151000 | AI18: =+AG14 -> 106200 | AK18: =+AI14 -> 84250 | AM18: =+AK23 -> 216750 | AO18: =+AM14 -> 203350 | AQ18: =+AO14 -> 88000 | AS18: =+AQ23 -> 172000 | AU18: =+AS23 -> 95500 | AW18: =+AU14 -> 172750 | AY18: =+AW14 -> 331200 | BA18: =+AY23 -> 108200 | BC18: =+BA14 -> 144700 | BE18: =+BC18 -> 144700 | BG18: =+BC23 -> 144700 | BI18: =$BG$14 -> 215200 | BK18: =+BI23 -> 212850
A19: Caja Menor | C19: 0 | E19: 0 | G19: 0 | I19: -7900 | K19: 0 | M19: -350000 | O19: 0 | Q19: 0 | S19: 4300 | W19: =+U25 -> 17400 | AA19: 75050 | AE19: 0 | AG19: -100000 | AI19: 0 | AK19: 0 | AM19: -100000 | AQ19: ='16mar'!$F$11 -> 99000 | AS19: -250000 | AU19: 0 | AW19: 0 | AY19: -230000 | BE19: 0 | BG19: =1800 -> 1800 | BI19: 0 | BK19: 0
A20: Venta | C20: 192000 | E20: 213000 | G20: 344000 | I20: 84000 | K20: 186000 | M20: 456500 | O20: 0 | Q20: 60000 | S20: 105000 | U20: 260000 | W20: 143500 | AA20: 123500 | AC20: 172500 | AE20: 51000 | AG20: 335500 | AI20: 67000 | AK20: =Registros!$C$13 -> 132500 | AM20: 271000 | AO20: 99000 | AS20: 176500 | AU20: 77250 | AW20: 207700 | AY20: 107000 | BA20: 126500 | BE20: 0 | BG20: =130700+8000 -> 138700 | BI20: 58500 | BK20: 104000
A21: Gastos | C21: =60000+100 -> 60100 | E21: 103000 | G21: =70000+36700+120000+20000 -> 246700 | I21: =$I$20 -> 84000 | K21: =10000+70000+20000+20000+(120000+300000)+7900 -> 547900 | M21: =20000+70000+6400 -> 96400 | S21: =30000+28700 -> 58700 | U21: =20000+122700+124400+3500+11000+16500+46350+50000+14000 -> 408450 | W21: =38050+17000+7450+22400+500 -> 85400 | AA21: =10000+20000+26850 -> 56850 | AC21: 30000 | AE21: 0 | AG21: =140000+1000+20500+55800+43800+40000 -> 301100 | AI21: =4500+21600 -> 26100 | AM21: =30000+120000+50000+51500 -> 251500 | AO21: =Gas!$C$15 -> 221350 | AQ21: 15000 | AW21: =13500+7800+27950 -> 49250 | AY21: =30000+70000 -> 100000 | BA21: =70000+20000 -> 90000 | BE21: 0 | BG21: 70000 | BI21: 60850 | BK21: 20000
A22: Retiros | AA22: 100000 | AC22: 82000 | AE22: 0 | AG22: 0 | AI22: =4000+51350 -> 55350 | AS22: 3000 | AU22: 0 | AW22: 0 | AY22: 0 | BA22: 0 | BC22: 0 | BE22: 0 | BG22: 0 | BI22: 0 | BK22: 0
C23: =+C18+C20-C21 -> 205600 | E23: =+E18+E20-E21 -> 315600 | G23: =+G18+G20-G21 -> 412900 | I23: =+SUM(I18:I20)-I21 -> 405000 | K23: =+SUM(K18:K20)-K21 -> 43100 | M23: =+SUM(M18:M20)-M21 -> 135100 | O23: =+SUM(O18:O20)-O21 -> 141400 | Q23: =+SUM(Q18:Q20)-Q21 -> 201400 | S23: =+SUM(S18:S20)-S21 -> 252000 | U23: =+SUM(U18:U20)-U21 -> 103550 | W23: =+SUM(W18:W20)-W21 -> 179050 | Y23: =+SUM(Y18:Y20)-Y21 -> 179050 | AA23: =+SUM(AA18:AA20)-SUM(AA21:AA22) -> 127700 | AC23: =+SUM(AC18:AC20)-SUM(AC21:AC22) -> 202150 | AE23: =+SUM(AE18:AE20)-SUM(AE21:AE22) -> 151000 | AG23: =+SUM(AG18:AG20)-SUM(AG21:AG22) -> 85400 | AI23: =+SUM(AI18:AI20)-SUM(AI21:AI22) -> 91750 | AK23: =+SUM(AK18:AK20)-SUM(AK21:AK22) -> 216750 | AM23: =+SUM(AM18:AM20)-SUM(AM21:AM22) -> 136250 | AO23: =+SUM(AO18:AO20)-SUM(AO21:AO22) -> 81000 | AQ23: =+SUM(AQ18:AQ20)-SUM(AQ21:AQ22) -> 172000 | AS23: =+SUM(AS18:AS20)-SUM(AS21:AS22) -> 95500 | AU23: =+SUM(AU18:AU20)-SUM(AU21:AU22) -> 172750 | AW23: =+SUM(AW18:AW20)-SUM(AW21:AW22) -> 331200 | AY23: =+SUM(AY18:AY20)-SUM(AY21:AY22) -> 108200 | BA23: =+SUM(BA18:BA20)-SUM(BA21:BA22) -> 144700 | BC23: =+SUM(BC18:BC20)-SUM(BC21:BC22) -> 144700 | BE23: =+SUM(BE18:BE20)-SUM(BE21:BE22) -> 144700 | BG23: =+SUM(BG18:BG20)-SUM(BG21:BG22) -> 215200 | BI23: =+SUM(BI18:BI20)-SUM(BI21:BI22) -> 212850 | BK23: =+SUM(BK18:BK20)-SUM(BK21:BK22) -> 296850
A25: Diferencia | C25: =C14-C23 -> 0 | E25: =E14-E23 -> 0 | G25: =G14-G23 -> -412900 | I25: =I14-I23 -> 0 | K25: =K14-K23 -> 177100 | M25: =M14-M23 -> 6300 | O25: =O14-O23 -> 0 | Q25: =Q14-Q23 -> -13800 | S25: =S14-S23 -> -252000 | U25: =U14-U23 -> 17400 | W25: =W14-W23 -> -4000 | Y25: =Y14-Y23 -> -93050 | AA25: =AA14-AA23 -> 13950 | AC25: =AC14-AC23 -> 102600 | AE25: =AE14-AE23 -> 0 | AG25: =AG14-AG23 -> 20800 | AI25: =AI14-AI23 -> -7500 | AK25: =AK14-AK23 -> -216750 | AM25: =AM14-AM23 -> 67100 | AO25: =AO14-AO23 -> 7000 | AQ25: =AQ14-AQ23 -> -172000 | AS25: =AS14-AS23 -> 0 | AU25: =AU14-AU23 -> 0 | AW25: =AW14-AW23 -> 0 | AY25: =AY14-AY23 -> 0 | BA25: =BA14-BA23 -> 0 | BC25: =BC14-BC23 -> -144700 | BE25: =BE14-BE23 -> -144700 | BG25: =BG14-BG23 -> 0 | BI25: =BI14-BI23 -> -212850 | BK25: =BK14-BK23 -> -296850
A27: Caja Menor EA | E27: =+E23+E18 -> 521200 | AE27: =100000-12050 -> 87950 | AG27: =100000-12050 -> 87950 | AI27: =+AG27-43000 -> 44950 | AK27: =+AI27 -> 44950 | AM27: =+AK27+100000 -> 144950 | AO27: =+AM27-50000 -> 94950 | AQ27: =+AO27 -> 94950 | AS27: =+AQ27-AS19 -> 344950 | AU27: 0 | AW27: 0 | AY27: 0 | BA27: 0 | BC27: 0 | BE27: 0 | BG27: 0 | BI27: 0 | BK27: 0
A28: Caja Menor JG | W28: 75050 | Y28: 75050 | AG28: 100000 | AI28: 0 | AK28: 0 | AM28: 0 | AO28: 0 | AQ28: 0 | AS28: 0 | AU28: 0 | AW28: 0 | AY28: 0 | BA28: 0 | BC28: 0 | BE28: 0 | BG28: 0 | BI28: 0 | BK28: 0
A30: NEQUI - venta | C30: =24000+8000 -> 32000 | E30: 8000 | G30: 46500 | I30: 125000 | K30: 51000 | M30: 47000 | AE30: =+(32000-2000)+11000+90000+3650 -> 134650 | AG30: 113000 | AI30: 94000 | AK30: 0 | AM30: =+(98000-5000) -> 93000 | AO30: =19000+(45000-9000) -> 55000 | AQ30: =11000+10000 -> 21000 | AS30: 78000 | AU30: =71000+(8000*4) -> 103000 | AW30: 169800 | AY30: 65700 | BA30: 11000 | BC30: 0 | BE30: 0 | BG30: 127000 | BI30: 48000 | BK30: 24000
A31: NEQUI - transfer/egreso | C31: 0 | E31: 0 | G31: 0 | I31: 0 | K31: 0 | M31: 0 | AU31: =+AS27-(40000+40000+50000+8500+6000+116000) -> 84450 | AW31: -454000 | AY31: =230000-21000 -> 209000 | BA31: 0 | BC31: 0 | BE31: 0 | BG31: 0 | BI31: =-114000-40000 -> -154000 | BK31: 0
A32: NEQUI Acum. | C32: =SUM(C30:C31) -> 32000 | E32: =+C32+SUM(E30:E31) -> 40000 | G32: =+E32+SUM(G30:G31) -> 86500 | I32: =+G32+SUM(I30:I31) -> 211500 | K32: =+I32+SUM(K30:K31) -> 262500 | M32: =+K32+SUM(M30:M31) -> 309500 | AE32: =+AE30 -> 134650 | AG32: =+AG30+AE32 -> 247650 | AI32: =+AI30+AG32 -> 341650 | AK32: =+AK30+AI32 -> 341650 | AM32: =+AM30+AK32 -> 434650 | AO32: =+AO30+AM32 -> 489650 | AQ32: =+AQ30+AO32 -> 510650 | AS32: =+AS30+AQ32-(40000+20000) -> 528650 | AU32: =+AS32+SUM(AU30:AU31) -> 716100 | AW32: =+AU32+SUM(AW30:AW31) -> 431900 | AY32: =+AW32+SUM(AY30:AY31) -> 706600 | BA32: =+AY32+SUM(BA30:BA31) -> 717600 | BC32: =+BA32+SUM(BC30:BC31) -> 717600 | BE32: =+BA32+SUM(BE30:BE31) -> 717600 | BG32: =+BE32+SUM(BG30:BG31) -> 844600 | BI32: =+BG32+SUM(BI30:BI31) -> 738600 | BK32: =+BI32+SUM(BK30:BK31) -> 762600
A33: DaviPLATA | C33: 0 | E33: 0 | G33: 0 | I33: 0 | K33: 11000 | M33: 0 | AE33: 0 | AG33: =22000+1000 -> 23000 | AI33: 82000 | AK33: 0 | AM33: =23000 -> 23000 | AO33: 0 | AQ33: 0 | AS33: =15000+8000 -> 23000 | AU33: 0 | AW33: 11000 | AY33: 0 | BA33: 0 | BC33: 0 | BE33: 0 | BG33: 27000 | BI33: 11000 | BK33: 0
A34: DaviPLATA Acum. | C34: =+C33 -> 0 | E34: =+E33+C34 -> 0 | G34: =+G33+E34 -> 0 | I34: =+I33+G34 -> 0 | K34: =+K33+I34 -> 11000 | M34: =+M33+K34 -> 11000 | AE34: 0 | AG34: =+AG33 -> 23000 | AI34: =+AI33+AG34 -> 105000 | AK34: =+AK33+AI34 -> 105000 | AM34: =+AM33+AK34 -> 128000 | AO34: =+AO33+AM34 -> 128000 | AQ34: =+AQ33+AO34 -> 128000 | AS34: =+AS33+AQ34 -> 151000 | AU34: =+AU33+AS34 -> 151000 | AW34: =+AW33+AU34 -> 162000 | AY34: =+AY33+AW34 -> 162000 | BA34: =+BA33+AY34 -> 162000 | BC34: =+BC33+BA34 -> 162000 | BE34: =+BE33+BA34 -> 162000 | BG34: =+BG33+BE34 -> 189000 | BI34: =+BI33+BG34 -> 200000 | BK34: =+BK33+BI34 -> 200000
A36: Venta | C36: =+C20+C30+C33 -> 224000 | E36: =+E20+E30+E33 -> 221000 | G36: =+G20+G30+G33 -> 390500 | I36: =+I20+I30+I33 -> 209000 | K36: =+K20+K30+K33 -> 248000 | M36: =+M20+M30+M33 -> 503500 | AS36: =+AS20+AS30+AS33 -> 277500 | AU36: =+AU20+AU30+AU33 -> 180250 | AW36: =+AW20+AW30+AW33 -> 388500 | AY36: =+AY20+AY30+AY33 -> 172700 | BA36: =+BA20+BA30+BA33 -> 137500 | BC36: =+BC20+BC30+BC33 -> 0 | BE36: =+BE20+BE30+BE33 -> 0 | BG36: =+BG20+BG30+BG33 -> 292700 | BI36: =+BI20+BI30+BI33 -> 117500 | BK36: =+BK20+BK30+BK33 -> 128000
A37: Acumulado | C37: =+C23+C32+C34 -> 237600 | E37: =+E23+E32+E34 -> 355600 | G37: =+G23+G32+G34 -> 499400 | I37: =+I23+I32+I34 -> 616500 | K37: =+K23+K32+K34 -> 316600 | M37: =+M23+M32+M34 -> 455600 | AS37: =+AS23+AS32+AS34 -> 775150 | AU37: =+AU23+AU32+AU34 -> 1039850 | AW37: =+AW23+AW32+AW34 -> 925100 | AY37: =+AY23+AY32+AY34 -> 976800 | BA37: =+BA23+BA32+BA34 -> 1024300 | BC37: =+BC23+BC32+BC34 -> 1024300 | BE37: =+BE23+BE32+BE34 -> 1024300 | BG37: =+BG23+BG32+BG34 -> 1248800 | BI37: =+BI23+BI32+BI34 -> 1151450 | BK37: =+BK23+BK32+BK34 -> 1259450
A39: CXC | AI39: 24000 | AK39: =16000+AI39 -> 40000 | AM39: =8000*5 -> 40000 | AQ39: =16000+AM39 -> 56000
A40: CXP | AY40: 423300 | BA40: =+AY40 -> 423300 | BC40: =+BA40 -> 423300 | BE40: =+BA40 -> 423300 | BG40: =+BC40 -> 423300 | BI40: =+BG40 -> 423300 | BK40: =+BI40 -> 423300
AM42: =+SUM(AM23,AM27,AM32,AM34) -> 843850

Sheet 25 marzo
D2: 25 de marzo
E3: kilos
C4: Cerdo | D4: 106500 | E4: 6.66 | F4: kilos | G4: entrada

Sheet Gas
A1: 161810
A2: 45000
A3: =+A1-A2 -> 116810 | E3: 84250
B4: =20-9 -> 11 | E4: 134500
B5: =+B4-4 -> 7 | E5: 271000
E6: =30000+120000+50000+51500 -> 251500 | G6: =#REF! -> #REF! | H6: =+E6-G6 -> #REF!
E7: =+SUM(E3:E5)-E6 -> 238250
B10: Cubiertos | C10: 116300 | D10: pérdida
B11: Portacomidas | C11: 17400
B12: Ferreteria | C12: 8000
B13: mercado | C13: 72150 | D13: =+C13+C14 -> 79650
B14: mercado | C14: 7500
C15: =+SUM(C10:C14) -> 221350

Sheet Registros
A1: 41334
E2: =8000+16000+13500+18000+8000+6000+9000+30000+24000 -> 132500
G3: 216
A4: 1 | B4: chorizo | C4: 8000 | D4: x | F4: 3 chorizos
A5: 2 | B5: chorizos | C5: 16000 | D5: x | F5: 2 para llevar
A6: 2 | B6: gaseosas | C6: 6000 | D6: 3
A7: 3 | B7: chorizos crudos | C7: =4500*3 -> 13500 | D7: 3
A8: 3 | B8: chorizos | C8: 24000
A9: 3 | B9: gaseosas | C9: =3000*3 -> 9000 | D9: 3 | F9: 35 | G9: 60
A10: 4 | B10: chorizos crudos | C10: =4500*4 -> 18000 | D10: 3 | F10: 12
A11: 1 | B11: chorizo | C11: 8000 | F11: 6
B12: Parrillada | C12: 30000 | F12: 4.5
C13: =+SUM(C3:C12) -> 132500 | F13: 57500
A17: 41699
A19: 2 | B19: chorizos | C19: 16000
A20: 2 | B20: gaseosas | C20: 6000
A21: 1 | B21: chorizo | C21: 8000
A22: 1 | B22: gaseosa | C22: 3000
A23: 2 | B23: chorizo crudos | C23: 9000
A24: 2 | B24: chorizos | C24: 16000
A25: 2 | B25: gaseosas | C25: 6000
A27: 1 | B27: carne | C27: 37000 | D27: domicilio | E27: =30+7 -> 37
A28: 3 | B28: chorizos | C28: 24000
A29: 1 | B29: media carne | C29: 15000
A30: 1 | B30: gaseosa | C30: 3000
B31: carne | C31: 23000 | D31: daviplata
A33: 1 | B33: chorizo | C33: 8000 | D33: nequi
A34: 1 | B34: gaseosa | C34: 3000 | D34: nequi

Sheet Forecast_dia
A3: 46110 | B3: partido colombia-francia

Sheet Hoja2
C2: 100
C5: 0.1 | D5: 0.9 | E5: meta por mes | F5: vendedores | G5: meta equipo | H5: ingresos free lance | I5: ingresos Digilivo una persona
B6: 2000000 | C6: =+B6*$C$5 -> 200000 | D6: =+B6*$D$5 -> 1800000 | E6: 10 | F6: =3+1+1+1+1 -> 7 | G6: =+E6*F6 -> 70 | H6: =+E6*C6 -> 2000000 | I6: =+D6*E6 -> 18000000 | J6: =+G6*D6 -> 126000000
B7: 250000 | J7: =+J6*35% -> 44100000 | K7: Impuesto
J9: =+J6-J7 -> 81900000

Sheet Clientes
A1: Sandra Patricia | B1: 314 433 7558

Sheet Empaques
A1: Empaques
A2: Chorizo y papa o arepa | B2: 10000 | C2: =+B2*4 -> 40000
A3: papa francesa
A4: hamburguesa
A5: Carnes
E6: =100000-16000 -> 84000
A9: 8*12 | B9: emp. Bolsa plastica
A10: L21 | B10: emp. Metalico
A13: Empaques
C16: un | D16: un
A17: Portacomida | B17: 9000 | C17: 20 | D17: =+B17/C17 -> 450 | E17: unidad para domicilio
A18: Portacomida | B18: 8400 | C18: 20 | D18: =+B18/C18 -> 420 | E18: unidad para domicilio

Sheet proveedores
A1: Proveedor | B1: Dirección | C1: Teléfono | D1: Descripción
A2: Comercializadora Las Brumas | B2: Cr 10#23-43 sur | C2: 3206946710 | D2: Maquinaria pesada y complementaria
A3: Dussan | B3: Cra 10#22 -10 sur - local 3 | C3: 3104158673 | D3: Sierras de corte, empacadoras al vació-embutidoras, tajadoras, cutters
A4: Muebles y Enseres CHEPE | B4: Cr10 # 17 -69 sur | C4: 2398504 -311 212 4856 | D4: Maquinaria pesada
A5: Compra y Venta D.C. | B5: Cr10#18 -41 sur | C5: 3204482491 -3124504414 | D5: Maquinaria principal complementarea
A6: Compra y Venta El Dorado | B6: Cr10 # 22A -52 sur | C6: 3103232264 | D6: Neveras y vitrinas
A7: LICICOL | B7: CR 27 10 -98 | C7: 3222124844 | D7: Tablas, licuaduras, menaje para restaurante
A8: El Cubo | B8: Cr 10 Sur # 18 -90 | C8: 302 722 2323 | D8: Maquinaria cárnica NUEVA
A9: Cerdo | B9: Cll 15 No. 9 -22 centro | C9: 3213130050 | D9: Porcinos Chìa DC SAS
A10: Arepas Guerrero | C10: 311 206 1929 6800858-6850461 | D10: Cll 135 No 94C 15, Suba - Bogotá
A11: Productos de aseo y desengrasante | C11: 320 595 6611
A12: Edison Valbuena - Gaseosa | C12: 322 460 2946
A13: Coca- Cola | B13: 6016050600
C16: H

Sheet informe
A1: Equipo | B1: (Todas) | D1: Equipo | E1: (Todas)
A3: Etiquetas de fila | B3: Suma de valor | D3: Etiquetas de fila | E3: Suma de valor | F3: Suma de valor2
A4: Inversión - Local | B4: 4637265 | D4: Patrimonio | E4: 18622650 | F4: 0.64590739
A5: Instalación de gas - contador | B5: 1700000 | D5: Inversión - Local | E5: 4637265 | F5: 0.16083875
A6: Ducto, adecuaciòn campana y otros | B6: 730000 | D6: Costo | E6: 3371850 | F6: 0.11694914
A7: Acarreos | B7: 630000 | D7: Gasto | E7: 1710000 | F7: 0.059309584
A8: Pintura de reja y plomeria | B8: 420000 | D8: Inversión - Invima | E8: 490000 | F8: 0.016995144
A9: Pintura + otros | B9: 300000 | D9: Total general | E9: 28831765 | F9: 1
A10: FERRETERIA | B10: 258615
A11: Caldero, colador y Bolsas | B11: 151300
A12: Estudio del contrato del arriendo | B12: 150000
A13: Espejo e instalación | B13: 140000
A14: ASEO | B14: 115450
A15: Certi. Tradición y libertad | B15: 21900
A16: Distrielectrics - Enchufe | B16: 20000
A17: Total general | B17: 4637265

Sheet Costos
B3: Embalajes | C3: Precio embalaje | D3: Total | E3: Und | F3: Subtotal
A4: Agua | B4: 1 | C4: 33000 | D4: =+B4*C4 -> 33000 | E4: 24 | F4: =C4/E4 -> 1375
A5: Hit | B5: 2 | C5: 29000 | D5: =+B5*C5 -> 58000 | E5: 12 | F5: =C5/E5 -> 2416.6667
A6: Postobon | B6: 3 | C6: 35000 | D6: =+B6*C6 -> 105000 | E6: 30 | F6: =C6/E6 -> 1166.6667
A7: Coca Cola | B7: 6 | C7: 36000 | D7: =+B7*C7 -> 216000 | E7: 30 | F7: =C7/E7 -> 1200
D9: =+SUM(D4:D7) -> 412000

Sheet Inventario
A1: 5 | B1: 100 | C1: =+A1*B1*3500 -> 1750000

Sheet Reporte
A2: Extracto | E2: =+SUM(E4:E9) -> -4500
A3: Etiquetas de fila | B3: Suma de valor | D3: Software | E3: saldo
A4: 46076 | B4: 30500 | D4: 32000 | E4: =+B4-D4 -> -1500 | F4: Nota debito | G4: Un cliente pago 6,500 en nequi y 1500 en efectivo
A5: 46077 | B5: 11000 | D5: 8000 | E5: =+B5-D5 -> 3000 | F5: Nota crédito | G5: Un cliente pago 3,000 en nequi y 5000 en efectivo
A6: 46078 | B6: 62500 | D6: 62500 | E6: =+B6-D6 -> 0 | F6: Ok
A7: 46079 | B7: 125000 | D7: 125000 | E7: =+B7-D7 -> 0 | F7: Ok
A8: 46080 | B8: 56000 | D8: =11000+51000 -> 62000 | E8: =+B8-D8 -> -6000
A9: 46081 | B9: 327000 | D9: =47000+280000 -> 327000 | E9: =+B9-D9 -> 0 | F9: Ok
A10: Total general | B10: 612000
A15: Suma de valor | B15: Etiquetas de columna
A16: Etiquetas de fila | B16: DaviPlata | C16: Nequi | D16: Total general
A17: 46076 | C17: 30500 | D17: 30500
A18: 46077 | C18: 11000 | D18: 11000
A19: 46078 | B19: 16000 | C19: 46500 | D19: 62500
A20: 46079 | C20: 125000 | D20: 125000
A21: 46080 | B21: 11000 | C21: 45000 | D21: 56000
A22: Total general | B22: 27000 | C22: 258000 | D22: 285000

Sheet Rappi
B2: 7 kilometros | E2: dar de baja con 90 dias
B3: sin membresia
B4: Laura Manzera
B5: hay un descuento | D5: 7 | E5: pm
B6: 0 | C6: primer mes | G6: 16 al 22
G7: 26
B8: 23% comisiòn | D8: 10000
D9: =+E9*D8 -> 2300 | E9: 0.23
G11: =4.5*4 -> 18

Sheet Hoja3
A1: id | B1: nombre_producto | C1: choriboni | D1: casa del antojo
A2: 39 | B2: Chorizo solo | C2: 7000 | D2: 10000 | F2: =+C2*23% -> 1610 | G2: =+C2-F2 -> 5390
A3: 19 | B3: Bandeja Choriboni - 25 | C3: 25000 | F3: =+C3*23% -> 5750 | G3: =+C3-F3 -> 19250
A4: 24 | B4: Bandeja Choriboni - 30 | C4: 30000 | F4: =+C4*23% -> 6900 | G4: =+C4-F4 -> 23100
A5: 29 | B5: Bandeja Choriboni - 35 | C5: 35000 | F5: =+C5*23% -> 8050 | G5: =+C5-F5 -> 26950
A6: 4 | B6: BEBIDA - Botella de Agua | C6: 3500 | D6: =+C6*1.25 -> 4375 | F6: =+C6*23% -> 805 | G6: =+C6-F6 -> 2695
A7: 44 | B7: BEBIDA - Cerveza Aguila | C7: 4500 | D7: =+C7*1.25 -> 5625 | F7: =+C7*23% -> 1035 | G7: =+C7-F7 -> 3465
A8: 53 | B8: BEBIDA - Cerveza Central | C8: 3000 | D8: =+C8*1.25 -> 3750 | F8: =+C8*23% -> 690 | G8: =+C8-F8 -> 2310
A9: 45 | B9: BEBIDA - Cerveza Club Colombia | C9: 6000 | D9: =+C9*1.25 -> 7500 | F9: =+C9*23% -> 1380 | G9: =+C9-F9 -> 4620
A10: 2 | B10: BEBIDA - Coca Cola | C10: 3000 | D10: =+C10*1.25 -> 3750 | F10: =+C10*23% -> 690 | G10: =+C10-F10 -> 2310
A11: 49 | B11: BEBIDA - Coca Cola 237ML | C11: 3000 | D11: =+C11*1.25 -> 3750 | F11: =+C11*23% -> 690 | G11: =+C11-F11 -> 2310
A12: 48 | B12: BEBIDA - Coca Cola ZERO | C12: 3200 | D12: =+C12*1.25 -> 4000 | F12: =+C12*23% -> 736 | G12: =+C12-F12 -> 2464
A13: 7 | B13: BEBIDA - Jugo Hit | C13: 4500 | D13: =+C13*1.25 -> 5625 | F13: =+C13*23% -> 1035 | G13: =+C13-F13 -> 3465 | H13: 4.5
A14: 3 | B14: BEBIDA - Postobón | C14: 3000 | D14: =+C14*1.25 -> 3750 | F14: =+C14*23% -> 690 | G14: =+C14-F14 -> 2310
A15: 50 | B15: BEBIDA - Postobon 350ML | C15: 3000 | D15: =+C15*1.25 -> 3750 | F15: =+C15*23% -> 690 | G15: =+C15-F15 -> 2310
A16: 42 | B16: CARNES - Carne asada - 20 | C16: 20000 | D16: =+C16*1.25 -> 25000 | F16: =+C16*23% -> 4600 | G16: =+C16-F16 -> 15400
A17: 41 | B17: CARNES - Carne asada 23 | C17: 23000 | D17: =+C17*1.25 -> 28750 | F17: =+C17*23% -> 5290 | G17: =+C17-F17 -> 17710
A18: 58 | B18: CARNES - Carne asada 30 | C18: 30000 | D18: =+C18*1.25 -> 37500 | F18: =+C18*23% -> 6900 | G18: =+C18-F18 -> 23100
A19: 33 | B19: CARNES - Carne Asada de 40 | C19: 40000 | D19: =+C19*1.25 -> 50000 | F19: =+C19*23% -> 9200 | G19: =+C19-F19 -> 30800
A20: 11 | B20: CARNES - Churrasco Gaucho - 30 | C20: 30000 | D20: =+C20*1.25 -> 37500 | F20: =+C20*23% -> 6900 | G20: =+C20-F20 -> 23100
A21: 27 | B21: CARNES - Costillas BBQ - 50 | C21: 50000 | D21: =+C21*1.25 -> 62500 | F21: =+C21*23% -> 11500 | G21: =+C21-F21 -> 38500
A22: 14 | B22: CARNES - Costillas BBQ - 25 | C22: 25000 | D22: =+C22*1.25 -> 31250 | F22: =+C22*23% -> 5750 | G22: =+C22-F22 -> 19250
A23: 12 | B23: CARNES - Lomo de Cerdo -25 | C23: 25000 | D23: =+C23*1.25 -> 31250 | F23: =+C23*23% -> 5750 | G23: =+C23-F23 -> 19250
A24: 57 | B24: CARNES - Media carne - 10 | C24: 10000 | D24: =+C24*1.25 -> 12500 | F24: =+C24*23% -> 2300 | G24: =+C24-F24 -> 7700
A25: 40 | B25: CARNES - Media carne - 15 | C25: 15000 | D25: =+C25*1.25 -> 18750 | F25: =+C25*23% -> 3450 | G25: =+C25-F25 -> 11550
... A31: 47 | B31: chorixo solo | C31: 3500 | D31: =+C31*1.25 -> 4375 | F31: =+C31*23% -> 805 | G31: =+C31-F31 -> 2695
A32: 1 | B32: Chorizo con papa/arepa | C32: 8000 | D32: =+C32*1.25 -> 10000 | E32: 10000 | F32: =+C32*23% -> 1840 | G32: =+C32-F32 -> 6160
A33: 10 | B33: Ham. Choriboni - Combo | C33: 25000 | D33: =+C33*1.25 -> 31250 | F33: =+C33*23% -> 5750 | G33: =+C33-F33 -> 19250
A34: 9 | B34: Ham. Choriboni -20 | C34: 20000 | D34: =+C34*1.25 -> 25000 | F34: =+C34*23% -> 4600 | G34: =+C34-F34 -> 15400
A35: 6 | B35: Ham. combo - 22 | C35: 22000 | D35: =+C35*1.25 -> 27500 | F35: =+C35*23% -> 5060 | G35: =+C35-F35 -> 16940 | H35: 3
A36: 38 | B36: Ham. Doble combo - ELIMINAR | C36: 27000 | D36: =+C36*1.25 -> 33750 | F36: =+C36*23% -> 6210 | G36: =+C36-F36 -> 20790
A37: 5 | B37: Ham. sencilla - 17 | C37: 17000 | D37: =+C37*1.25 -> 21250 | F37: =+C37*23% -> 3910 | G37: =+C37-F37 -> 13090 | H37: =8*3 -> 24
A38: 35 | B38: Parrillada de 30 | C38: 30000 | D38: =+C38*1.25 -> 37500 | F38: =+C38*23% -> 6900 | G38: =+C38-F38 -> 23100
A39: 18 | B39: Parrillada de 35 | C39: 35000 | D39: =+C39*1.25 -> 43750 | F39: =+C39*23% -> 8050 | G39: =+C39-F39 -> 26950
A40: 23 | B40: Parrillada de 40 | C40: 40000 | D40: =+C40*1.25 -> 50000 | F40: =+C40*23% -> 9200 | G40: =+C40-F40 -> 30800
A41: 21 | B41: Parrillada de 48 | C41: 48000 | D41: =+C41*1.25 -> 60000 | F41: =+C41*23% -> 11040 | G41: =+C41-F41 -> 36960
A42: 43 | B42: Parrillada de 50 | C42: 50000 | D42: =+C42*1.25 -> 62500 | F42: =+C42*23% -> 11500 | G42: =+C42-F42 -> 38500
A43: 32 | B43: Parrillada de 60 | C43: 60000 | D43: =+C43*1.25 -> 75000 | F43: =+C43*23% -> 13800 | G43: =+C43-F43 -> 46200
A44: 22 | B44: Parrillada de 70 | C44: 70000 | D44: =+C44*1.25 -> 87500 | F44: =+C44*23% -> 16100 | G44: =+C44-F44 -> 53900
A45: 56 | B45: Parrillada de 80 | C45: 80000 | D45: =+C45*1.25 -> 100000 | F45: =+C45*23% -> 18400 | G45: =+C45-F45 -> 61600
A46: 55 | B46: Picada - 20 | C46: 20000 | D46: =+C46*1.25 -> 25000 | F46: =+C46*23% -> 4600 | G46: =+C46-F46 -> 15400
A47: 54 | B47: Picada - 15 | C47: 15000 | D47: =+C47*1.25 -> 18750 | F47: =+C47*23% -> 3450 | G47: =+C47-F47 -> 11550
A48: 37 | B48: PORCIÒN - papa francesa | C48: 2000 | D48: =+C48*1.25 -> 2500 | F48: =+C48*23% -> 460 | G48: =+C48-F48 -> 1540
A49: 30 | B49: PROMO pedazo de carne | C49: 2000 | D49: =+C49*1.25 -> 2500 | F49: =+C49*23% -> 460 | G49: =+C49-F49 -> 1540
... A55: 25 | B55: z. MP - Hamb. CRUDA | C55: 5000 | D55: =+C55*1.25 -> 6250 | F55: =+C55*23% -> 1150 | G55: =+C55-F55 -> 3850

Sheet 7-MARZO
F1: =+SUM(F3:F1048576) -> 89700 | H1: =#REF! -> #REF! | I1: =+F1-H1 -> #REF! | J1: 93000
A2: Cuenta | B2: un | C2: Precio | D2: Consepto | F2: Efectivo | G2: Bancos
A3: Base | D3: Base | F3: 93000
A4: Nomina | D4: Nomina | F4: -70000
A5: Gastos | D5: Inventario | E5: 10 un/paquete de arepa | F5: =-3800*10 -> -38000
A6: Gastos | D6: Inventario | E6: papa | F6: -28500
A7: Gastos | D7: Platano, cebolla, cilantro | F7: -27800
A8: Gastos | D8: Café | F8: -27000
D9: taxi | F9: -22000
A10: efectivo | B10: 2 | C10: 8000 | D10: Chorizo | F10: =+B10*C10 -> 16000
A11: efectivo | B11: 2 | C11: 8000 | D11: Chorizo | F11: =+B11*C11 -> 16000
A12: efectivo | B12: 4 | C12: 8000 | D12: Chorizo | F12: =+B12*C12 -> 32000
A13: efectivo | B13: 1 | C13: 8000 | D13: Chorizo | F13: =+B13*C13 -> 8000
A14: efectivo | B14: 2 | C14: 8000 | D14: Chorizo | F14: =+B14*C14 -> 16000
A15: efectivo | B15: 5 | C15: 3000 | D15: Coca Cola | F15: =+B15*C15 -> 15000
A16: nequi | B16: 2 | C16: 8000 | D16: Chorizo | G16: =+B16*C16 -> 16000
A17: nequi | D17: +3 chorixp y jugo | G17: 28000
A18: efectivo | D18: carne jenesano | F18: 15000
A19: efectivo | D19: Parrillada | F19: 60000
A20: efectivo | D20: chorizo y jugo | F20: 12000
A21: nequi | D21: 40 carne +gaseosa | G21: 43000
A22: efectivo | D22: 2 chorizps y hit | F22: =16000+4000 -> 20000

Sheet Informe ventas
A3: Suma de entrada | B3: Etiquetas de columna | F3: Suma de egreso | G3: Etiquetas de columna
B4: EFECTIVO | D4: Total general | G4: EFECTIVO | K4: NEQUI | L4: Total general
A5: Etiquetas de fila | B5: BASE | C5: VENTA | F5: Etiquetas de fila | G5: BASE | H5: GASTO | I5: RETIRO | J5: VENTA | K5: VENTA | N5: EFECTIVO
A6: 23-feb | B6: 73700 | C6: 192000 | D6: 265700 | F6: 23-feb | G6: 0 | H6: 60000 | I6: 100 | J6: 0 | K6: 0 | L6: 60100 | N6: =+D6-L6 -> 205600
A7: 24-feb | B7: 205600 | C7: 213000 | D7: 418600 | F7: 24-feb | G7: 0 | H7: 103000 | J7: 0 | K7: 0 | L7: 103000 | N7: =+D7-L7 -> 315600
A8: 25-feb | C8: 344000 | D8: 344000 | F8: 25-feb | H8: 226700 | J8: 0 | K8: 0 | L8: 226700 | N8: =+D8-L8 -> 117300
A9: 26-feb | C9: 84000 | D9: 84000 | F9: 26-feb | H9: 84000 | J9: 0 | K9: 0 | L9: 84000 | N9: =+D9-L9 -> 0
A10: Total general | B10: 279300 | C10: 833000 | D10: 1112300 | F10: Total general | G10: 0 | H10: 473700 | I10: 100 | J10: 0 | K10: 0 | L10: 473800
A14: nombre_transaccion | B14: VENTA
A16: Suma de entrada | B16: Etiquetas de columna
A17: Etiquetas de fila | B17: EFECTIVO | C17: NEQUI | D17: Total general
A18: 23-feb | B18: 192000 | C18: 32000 | D18: 224000
A19: 24-feb | B19: 213000 | C19: 8000 | D19: 221000
A20: 25-feb | B20: 344000 | C20: 46500 | D20: 390500
A21: 26-feb | B21: 84000 | C21: 125000 | D21: 209000
A22: Total general | B22: 833000 | C22: 211500 | D22: 1044500

Sheet historial de venta
A1: nombre_transaccion | B1: VENTA
A2: tipo_cuenta | B2: EFECTIVO
A4: fecha (día) | B4: fecha | C4: nombre_producto | D4: precio_producto | E4: cantidad | F4: Recuento de id_item | G4: Valor factura | J4: fecha (día) | K4: Valor venta en efectivo
A5: 23-feb | B5: 46076.692 | C5: Chorizo | D5: 8000 | E5: 2 | F5: 1 | G5: =+D5*E5 -> 16000 | J5: 46076 | K5: =+SUMIF(A:A,J5,G:G) -> 192000
A6: 23-feb | B6: 46076.717 | C6: Chorizo | D6: 8000 | E6: 2 | F6: 1 | G6: =+D6*E6 -> 16000 | J6: 46077 | K6: =+SUMIF(A:A,J6,G:G) -> 213000
A7: 23-feb | C7: Coca cola | D7: 3000 | E7: 2 | F7: 1 | G7: =+D7*E7 -> 6000 | J7: 46078 | K7: =+SUMIF(A:A,J7,G:G) -> 344000
A8: 23-feb | B8: 46076.75 | C8: Agua | D8: 3000 | E8: 2 | F8: 1 | G8: =+D8*E8 -> 6000 | J8: 46079 | K8: =+SUMIF(A:A,J8,G:G) -> 84000
A9: 23-feb | C9: Chorizo | D9: 8000 | E9: 2 | F9: 1 | G9: =+D9*E9 -> 16000
A10: 23-feb | B10: 46076.752 | C10: Chorizo | D10: 8000 | E10: 2 | F10: 1 | G10: =+D10*E10 -> 16000
A11: 23-feb | C11: Postobon | D11: 3000 | E11: 1 | F11: 1 | G11: =+D11*E11 -> 3000
A12: 23-feb | B12: 46076.787 | C12: Chorizo | D12: 8000 | E12: 1 | F12: 1 | G12: =+D12*E12 -> 8000
A13: 23-feb | B13: 46076.795 | C13: Chorizo | D13: 8000 | E13: 2 | F13: 1 | G13: =+D13*E13 -> 16000
A14: 23-feb | C14: Coca cola | D14: 3000 | E14: 2 | F14: 1 | G14: =+D14*E14 -> 6000
A15: 23-feb | B15: 46076.818 | C15: Chorizo | D15: 8000 | E15: 3 | F15: 1 | G15: =+D15*E15 -> 24000
A16: 23-feb | B16: 46076.842 | C16: Chorizo | D16: 8000 | E16: 1 | F16: 1 | G16: =+D16*E16 -> 8000
A17: 23-feb | B17: 46076.844 | C17: Chorizo | D17: 8000 | E17: 1 | F17: 1 | G17: =+D17*E17 -> 8000
A18: 23-feb | B18: 46076.846 | C18: Chorizo | D18: 8000 | E18: 1 | F18: 1 | G18: =+D18*E18 -> 8000
A19: 23-feb | C19: Postobon | D19: 3000 | E19: 1 | F19: 1 | G19: =+D19*E19 -> 3000
A20: 23-feb | B20: 46076.85 | C20: Chorizo | D20: 8000 | E20: 3 | F20: 1 | G20: =+D20*E20 -> 24000
A21: 23-feb | B21: 46076.853 | C21: Chorizo | D21: 8000 | E21: 1 | F21: 1 | G21: =+D21*E21 -> 8000
A22: 24-feb | B22: 46077.649 | C22: Chorizo | D22: 8000 | E22: 5 | F22: 1 | G22: =+D22*E22 -> 40000
A23: 24-feb | B23: 46077.649 | C23: Chorizo | D23: 8000 | E23: 3 | F23: 1 | G23: =+D23*E23 -> 24000
A24: 24-feb | B24: 46077.74 | C24: Chorizo | D24: 8000 | E24: 1 | F24: 1 | G24: =+D24*E24 -> 8000
A25: 24-feb | B25: 46077.76 | C25: Chorizo | D25: 8000 | E25: 1 | F25: 1 | G25: =+D25*E25 -> 8000
A26: 24-feb | B26: 46077.774 | C26: Chorizo | D26: 8000 | E26: 2 | F26: 1 | G26: =+D26*E26 -> 16000
A27: 24-feb | B27: 46077.775 | C27: Chorizo | D27: 8000 | E27: 1 | F27: 1 | G27: =+D27*E27 -> 8000
A28: 24-feb | B28: 46077.78 | C28: Chori- CRUDO | D28: 4500 | E28: 2 | F28: 1 | G28: =+D28*E28 -> 9000
A29: 24-feb | C29: Chorizo | D29: 8000 | E29: 1 | F29: 1 | G29: =+D29*E29 -> 8000
A30: 24-feb | B30: 46077.797 | C30: Chorizo | D30: 8000 | E30: 1 | F30: 1 | G30: =+D30*E30 -> 8000
A31: 24-feb | B31: 46077.837 | C31: Chorizo | D31: 8000 | E31: 1 | F31: 1 | G31: =+D31*E31 -> 8000 | H31: =+SUM(G22:G31) -> 137000
A32: 24-feb | B32: 46077.847 | C32: Agua | D32: 3000 | E32: 1 | F32: 1 | G32: =+D32*E32 -> 3000
A33: 24-feb | C33: Chorizo | D33: 8000 | E33: 3 | F33: 1 | G33: =+D33*E33 -> 24000
A34: 24-feb | C34: Postobon | D34: 3000 | E34: 1 | F34: 1 | G34: =+D34*E34 -> 3000
A35: 24-feb | B35: 46077.85 | C35: Chorizo | D35: 8000 | E35: 4 | F35: 1 | G35: =+D35*E35 -> 32000
A36: 24-feb | C36: Coca cola | D36: 3000 | E36: 2 | F36: 1 | G36: =+D36*E36 -> 6000
A37: 24-feb | B37: 46077.868 | C37: Chorizo | D37: 8000 | E37: 1 | F37: 1 | G37: =+D37*E37 -> 8000 | H37: =+SUM(G22:G37) -> 213000
A38: 25-feb | B38: 46078.578 | C38: Chorizo | D38: 8000 | E38: 1 | F38: 1 | G38: =+D38*E38 -> 8000
A39: 25-feb | B39: 46078.58 | C39: Chorizo | D39: 8000 | E39: 1 | F39: 1 | G39: =+D39*E39 -> 8000
A40: 25-feb | B40: 46078.587 | C40: Chorizo | D40: 8000 | E40: 1 | F40: 1 | G40: =+D40*E40 -> 8000
A41: 25-feb | B41: 46078.591 | C41: parri tres carnes | D41: 35000 | E41: 1 | F41: 1 | G41: =+D41*E41 -> 35000
A42: 25-feb | B42: 46078.601 | C42: parri tres carnes | D42: 35000 | E42: 1 | F42: 1 | G42: =+D42*E42 -> 35000
A43: 25-feb | B43: 46078.601 | C43: Chorizo | D43: 8000 | E43: 2 | F43: 1 | G43: =+D43*E43 -> 16000
A44: 25-feb | B44: 46078.695 | C44: Chorizo | D44: 8000 | E44: 1 | F44: 1 | G44: =+D44*E44 -> 8000
A45: 25-feb | B45: 46078.762 | C45: Chorizo | D45: 8000 | E45: 1 | F45: 1 | G45: =+D45*E45 -> 8000
A46: 25-feb | B46: 46078.764 | C46: Chorizo | D46: 8000 | E46: 1 | F46: 1 | G46: =+D46*E46 -> 8000
A47: 25-feb | B47: 46078.768 | C47: Chorizo | D47: 8000 | E47: 1 | F47: 1 | G47: =+D47*E47 -> 8000
A48: 25-feb | B48: 46078.774 | C48: Chorizo | D48: 8000 | E48: 5 | F48: 1 | G48: =+D48*E48 -> 40000
A49: 25-feb | B49: 46078.774 | C49: Coca cola | D49: 3000 | E49: 2 | F49: 1 | G49: =+D49*E49 -> 6000
A50: 25-feb | C50: Postobon | D50: 3000 | E50: 1 | F50: 1 | G50: =+D50*E50 -> 3000
A51: 25-feb | B51: 46078.778 | C51: Chorizo | D51: 8000 | E51: 3 | F51: 1 | G51: =+D51*E51 -> 24000
A52: 25-feb | B52: 46078.8 | C52: Chorizo | D52: 8000 | E52: 1 | F52: 1 | G52: =+D52*E52 -> 8000
A53: 25-feb | C53: Coca cola | D53: 3000 | E53: 1 | F53: 1 | G53: =+D53*E53 -> 3000
A54: 25-feb | B54: 46078.819 | C54: parri tres carnes | D54: 35000 | E54: 1 | F54: 1 | G54: =+D54*E54 -> 35000
A55: 25-feb | C55: Postobon | D55: 3000 | E55: 1 | F55: 1 | G55: =+D55*E55 -> 3000
A56: 25-feb | B56: 46078.82 | C56: Chorizo | D56: 8000 | E56: 2 | F56: 1 | G56: =+D56*E56 -> 16000
A57: 25-feb | B57: 46078.833 | C57: Chorizo | D57: 8000 | E57: 2 | F57: 1 | G57: =+D57*E57 -> 16000
A58: 25-feb | B58: 46078.838 | C58: Chorizo | D58: 8000 | E58: 4 | F58: 1 | G58: =+D58*E58 -> 32000
A59: 25-feb | B59: 46078.848 | C59: Chorizo | D59: 8000 | E59: 2 | F59: 1 | G59: =+D59*E59 -> 16000
A60: 26-feb | B60: 46079.557 | C60: Chori- CRUDO | D60: 4500 | E60: 2 | F60: 1 | G60: =+D60*E60 -> 9000
A61: 26-feb | B61: 46079.561 | C61: Chorizo | D61: 8000 | E61: 2 | F61: 1 | G61: =+D61*E61 -> 16000
A62: 26-feb | B62: 46079.753 | C62: Chorizo | D62: 8000 | E62: 1 | F62: 1 | G62: =+D62*E62 -> 8000
A63: 26-feb | B63: 46079.764 | C63: Chorizo | D63: 8000 | E63: 1 | F63: 1 | G63: =+D63*E63 -> 8000
A64: 26-feb | B64: 46079.795 | C64: Chorizo | D64: 8000 | E64: 2 | F64: 1 | G64: =+D64*E64 -> 16000
A65: 26-feb | B65: 46079.814 | C65: Chorizo | D65: 8000 | E65: 1 | F65: 1 | G65: =+D65*E65 -> 8000
A66: 26-feb | B66: 46079.815 | C66: Chorizo | D66: 8000 | E66: 1 | F66: 1 | G66: =+D66*E66 -> 8000
A67: 26-feb | B67: 46079.844 | C67: Chorizo | D67: 8000 | E67: 1 | F67: 1 | G67: =+D67*E67 -> 8000
A68: 26-feb | C68: Postobon | D68: 3000 | E68: 1 | F68: 1 | G68: =+D68*E68 -> 3000
A69: Total general | F69: 64
