Workbook
Name Costo_MP: [1]!Inventario6[#Data]
Name Cuentas_x_pagar: Pasivos[]
Name Cuentas_x_pagar: Pasivos8[]
Name Cuentas_x_pagar: Pasivos[]
Name Cuentas_x_pagar: Pasivos[]
Name Cuentas_x_pagar: Pasivos[]
Name Efectivo: [1]!Pérdidas_Ganancias[#Data]
Name SegmentaciónDeDatos_Mes: #N/A
Name SegmentaciónDeDatos_Tipo_día: #N/A
Name Stock_Inventario: [1]!Inventario_SICOV2[#Data]

Sheet maestro
A1: Fecha | B1: dia_semana | C1: No. Semana de operación | D1: Tipo día2
A2: 46076 | B2: =+TEXT(A2,"dddd") -> lunes | C2: 1 | D2: A) Día hábil
A3: 46076 | B3: =+TEXT(A3,"dddd") -> lunes | C3: 1 | D3: A) Día hábil
A4: 46077 | B4: =+TEXT(A4,"dddd") -> martes | C4: 1 | D4: A) Día hábil
A5: 46078 | B5: =+TEXT(A5,"dddd") -> miércoles | C5: 1 | D5: A) Día hábil
A6: 46079 | B6: =+TEXT(A6,"dddd") -> jueves | C6: 1 | D6: A) Día hábil
A7: 46080 | B7: =+TEXT(A7,"dddd") -> viernes | C7: 1 | D7: C) Viernes
A8: 46081 | B8: =+TEXT(A8,"dddd") -> sábado | C8: 1 | D8: C) Sábado
A9: 46082 | B9: =+TEXT(A9,"dddd") -> domingo | C9: 1 | D9: D) Domingo
A10: 46083 | B10: =+TEXT(A10,"dddd") -> lunes | C10: 2 | D10: A) Día hábil
A11: 46084 | B11: =+TEXT(A11,"dddd") -> martes | C11: 2 | D11: A) Día hábil
A12: 46085 | B12: =+TEXT(A12,"dddd") -> miércoles | C12: 2 | D12: A) Día hábil
A13: 46086 | B13: =+TEXT(A13,"dddd") -> jueves | C13: 2 | D13: A) Día hábil
... A16: 46089 | B16: =+TEXT(A16,"dddd") -> domingo | C16: 2 | D16: D) Domingo
A17: 46090 | B17: =+TEXT(A17,"dddd") -> lunes | C17: =+C10+1 -> 3 | D17: A) Día hábil
A18: 46091 | B18: =+TEXT(A18,"dddd") -> martes | C18: =+C11+1 -> 3 | D18: A) Día hábil
A19: 46092 | B19: =+TEXT(A19,"dddd") -> miércoles | C19: =+C12+1 -> 3 | D19: A) Día hábil
A20: 46093 | B20: =+TEXT(A20,"dddd") -> jueves | C20: =+C13+1 -> 3 | D20: A) Día hábil
A21: 46094 | B21: =+TEXT(A21,"dddd") -> viernes | C21: =+C14+1 -> 3 | D21: C) Viernes
A22: 46095 | B22: =+TEXT(A22,"dddd") -> sábado | C22: =+C15+1 -> 3 | D22: C) Sábado
A23: 46096 | B23: =+TEXT(A23,"dddd") -> domingo | C23: =+C16+1 -> 3 | D23: D) Domingo
A24: 46097 | B24: =+TEXT(A24,"dddd") -> lunes | C24: =+C17+1 -> 4 | D24: A) Día hábil
A25: 46098 | B25: =+TEXT(A25,"dddd") -> martes | C25: =+C18+1 -> 4 | D25: A) Día hábil
A26: 46099 | B26: =+TEXT(A26,"dddd") -> miércoles | C26: =+C19+1 -> 4 | D26: A) Día hábil
A27: 46100 | B27: =+TEXT(A27,"dddd") -> jueves | C27: =+C20+1 -> 4 | D27: A) Día hábil
A28: 46101 | B28: =+TEXT(A28,"dddd") -> viernes | C28: =+C21+1 -> 4 | D28: C) Viernes
... A314: 46387 | B314: =+TEXT(A314,"dddd") -> jueves | C314: =+C307+1 -> 45 | D314: A) Día hábil

Sheet sales
M1: =+VLOOKUP(sales[[#This Row],[Día]],Forecast!AK:AM,2,0) -> #VALUE!
B2: Fecha | C2: Hora | D2: Tipo día | E2: nombre_producto | F2: No. Semana de operación | G2: Gastos | H2: Tipo día2 | I2: Día | J2: Mes | K2: Margen de contribución | L2: Venta | M2: Caja | N2: Bancos
B3: =[2]sales_BI!J2 -> 46076 | C3: =[2]sales_BI!$K$2 -> 04:36 p. m. | D3: Normal | E3: =[2]sales!C5 -> Chorizo | F3: =+VLOOKUP(sales[[#This Row],[Fecha]],maestro!A:C,3,0) -> 1 | H3: =+VLOOKUP(sales[[#This Row],[Fecha]],maestro!A:D,4,0) -> A) Día hábil | I3: =+TEXT(B3,"ddd") -> lun | J3: =+TEXT(B3,"mmmm") -> febrero | K3: =+M3*0.4 -> 6400 | L3: =[2]sales_BI!H2 -> 16000 | M3: =[2]sales_BI!L2 -> 16000 | N3: =[2]sales_BI!M2 -> 0
B4: =[2]sales_BI!J3 -> 46076 | C4: =[2]sales_BI!$K$2 -> 04:36 p. m. | D4: Normal | E4: =[2]sales!C6 -> Chorizo | F4: =+VLOOKUP(sales[[#This Row],[Fecha]],maestro!A:C,3,0) -> 1 | H4: =+VLOOKUP(sales[[#This Row],[Fecha]],maestro!A:D,4,0) -> A) Día hábil | I4: =+TEXT(B4,"ddd") -> lun | J4: =+TEXT(B4,"mmmm") -> febrero | K4: =+M4*0.4 -> 0 | L4: =[2]sales_BI!H3 -> 8000 | M4: =[2]sales_BI!L3 -> 0 | N4: 0
B5: =[2]sales_BI!J4 -> 46076 | C5: =[2]sales_BI!$K$2 -> 04:36 p. m. | D5: Normal | E5: =[2]sales!C7 -> Chorizo | F5: =+VLOOKUP(sales[[#This Row],[Fecha]],maestro!A:C,3,0) -> 1 | H5: =+VLOOKUP(sales[[#This Row],[Fecha]],maestro!A:D,4,0) -> A) Día hábil | I5: =+TEXT(B5,"ddd") -> lun | J5: =+TEXT(B5,"mmmm") -> febrero | K5: =+M5*0.4 -> 6400 | L5: =[2]sales_BI!H4 -> 16000 | M5: =[2]sales_BI!L4 -> 16000 | N5: 0
B6: =[2]sales_BI!J5 -> 46076 | C6: =[2]sales_BI!$K$2 -> 04:36 p. m. | D6: Normal | E6: =[2]sales!C8 -> Coca cola | F6: =+VLOOKUP(sales[[#This Row],[Fecha]],maestro!A:C,3,0) -> 1 | H6: =+VLOOKUP(sales[[#This Row],[Fecha]],maestro!A:D,4,0) -> A) Día hábil | I6: =+TEXT(B6,"ddd") -> lun | J6: =+TEXT(B6,"mmmm") -> febrero | K6: =+M6*0.4 -> 2400 | L6: =[2]sales_BI!H5 -> 6000 | M6: =[2]sales_BI!L5 -> 6000 | N6: 0
B7: =[2]sales_BI!J6 -> 46076 | C7: =[2]sales_BI!$K$2 -> 04:36 p. m. | D7: Normal | E7: =[2]sales!C9 -> Chorizo | F7: =+VLOOKUP(sales[[#This Row],[Fecha]],maestro!A:C,3,0) -> 1 | H7: =+VLOOKUP(sales[[#This Row],[Fecha]],maestro!A:D,4,0) -> A) Día hábil | I7: =+TEXT(B7,"ddd") -> lun | J7: =+TEXT(B7,"mmmm") -> febrero | K7: =+M7*0.4 -> 0 | L7: =[2]sales_BI!H6 -> 24000 | M7: =[2]sales_BI!L6 -> 0 | N7: 0
B8: =[2]sales_BI!J7 -> 46076 | C8: =[2]sales_BI!$K$2 -> 04:36 p. m. | D8: Normal | E8: =[2]sales!C10 -> Agua | F8: =+VLOOKUP(sales[[#This Row],[Fecha]],maestro!A:C,3,0) -> 1 | H8: =+VLOOKUP(sales[[#This Row],[Fecha]],maestro!A:D,4,0) -> A) Día hábil | I8: =+TEXT(B8,"ddd") -> lun | J8: =+TEXT(B8,"mmmm") -> febrero | K8: =+M8*0.4 -> 2400 | L8: =[2]sales_BI!H7 -> 6000 | M8: =[2]sales_BI!L7 -> 6000 | N8: 0
B9: =[2]sales_BI!J8 -> 46076 | C9: =[2]sales_BI!$K$2 -> 04:36 p. m. | D9: Normal | E9: =[2]sales!C11 -> Chorizo | F9: =+VLOOKUP(sales[[#This Row],[Fecha]],maestro!A:C,3,0) -> 1 | H9: =+VLOOKUP(sales[[#This Row],[Fecha]],maestro!A:D,4,0) -> A) Día hábil | I9: =+TEXT(B9,"ddd") -> lun | J9: =+TEXT(B9,"mmmm") -> febrero | K9: =+M9*0.4 -> 6400 | L9: =[2]sales_BI!H8 -> 16000 | M9: =[2]sales_BI!L8 -> 16000 | N9: 0
B10: =[2]sales_BI!J9 -> 46076 | C10: =[2]sales_BI!$K$2 -> 04:36 p. m. | D10: Normal | E10: =[2]sales!C12 -> Chorizo | F10: =+VLOOKUP(sales[[#This Row],[Fecha]],maestro!A:C,3,0) -> 1 | H10: =+VLOOKUP(sales[[#This Row],[Fecha]],maestro!A:D,4,0) -> A) Día hábil | I10: =+TEXT(B10,"ddd") -> lun | J10: =+TEXT(B10,"mmmm") -> febrero | K10: =+M10*0.4 -> 6400 | L10: =[2]sales_BI!H9 -> 16000 | M10: =[2]sales_BI!L9 -> 16000 | N10: 0
B11: =[2]sales_BI!J10 -> 46076 | C11: =[2]sales_BI!$K$2 -> 04:36 p. m. | D11: Normal | E11: =[2]sales!C13 -> Postobon | F11: =+VLOOKUP(sales[[#This Row],[Fecha]],maestro!A:C,3,0) -> 1 | H11: =+VLOOKUP(sales[[#This Row],[Fecha]],maestro!A:D,4,0) -> A) Día hábil | I11: =+TEXT(B11,"ddd") -> lun | J11: =+TEXT(B11,"mmmm") -> febrero | K11: =+M11*0.4 -> 1200 | L11: =[2]sales_BI!H10 -> 3000 | M11: =[2]sales_BI!L10 -> 3000 | N11: 0
B12: =[2]sales_BI!J11 -> 46076 | C12: =[2]sales_BI!$K$2 -> 04:36 p. m. | D12: Normal | E12: =[2]sales!C14 -> Chorizo | F12: =+VLOOKUP(sales[[#This Row],[Fecha]],maestro!A:C,3,0) -> 1 | H12: =+VLOOKUP(sales[[#This Row],[Fecha]],maestro!A:D,4,0) -> A) Día hábil | I12: =+TEXT(B12,"ddd") -> lun | J12: =+TEXT(B12,"mmmm") -> febrero | K12: =+M12*0.4 -> 3200 | L12: =[2]sales_BI!H11 -> 8000 | M12: =[2]sales_BI!L11 -> 8000 | N12: 0
B13: =[2]sales_BI!J12 -> 46076 | C13: =[2]sales_BI!$K$2 -> 04:36 p. m. | D13: Normal | E13: =[2]sales!C15 -> Chorizo | F13: =+VLOOKUP(sales[[#This Row],[Fecha]],maestro!A:C,3,0) -> 1 | H13: =+VLOOKUP(sales[[#This Row],[Fecha]],maestro!A:D,4,0) -> A) Día hábil | I13: =+TEXT(B13,"ddd") -> lun | J13: =+TEXT(B13,"mmmm") -> febrero | K13: =+M13*0.4 -> 6400 | L13: =[2]sales_BI!H12 -> 16000 | M13: =[2]sales_BI!L12 -> 16000 | N13: 0
B14: =[2]sales_BI!J13 -> 46076 | C14: =[2]sales_BI!$K$2 -> 04:36 p. m. | D14: Normal | E14: =[2]sales!C16 -> Coca cola | F14: =+VLOOKUP(sales[[#This Row],[Fecha]],maestro!A:C,3,0) -> 1 | H14: =+VLOOKUP(sales[[#This Row],[Fecha]],maestro!A:D,4,0) -> A) Día hábil | I14: =+TEXT(B14,"ddd") -> lun | J14: =+TEXT(B14,"mmmm") -> febrero | K14: =+M14*0.4 -> 2400 | L14: =[2]sales_BI!H13 -> 6000 | M14: =[2]sales_BI!L13 -> 6000 | N14: 0
B15: =[2]sales_BI!J14 -> 46076 | C15: =[2]sales_BI!$K$2 -> 04:36 p. m. | D15: Normal | E15: =[2]sales!C17 -> Chorizo | F15: =+VLOOKUP(sales[[#This Row],[Fecha]],maestro!A:C,3,0) -> 1 | H15: =+VLOOKUP(sales[[#This Row],[Fecha]],maestro!A:D,4,0) -> A) Día hábil | I15: =+TEXT(B15,"ddd") -> lun | J15: =+TEXT(B15,"mmmm") -> febrero | K15: =+M15*0.4 -> 9600 | L15: =[2]sales_BI!H14 -> 24000 | M15: =[2]sales_BI!L14 -> 24000 | N15: 0
... B24: =[2]sales_BI!J23 -> 46077 | C24: =[2]sales_BI!$K$2 -> 04:36 p. m. | D24: Normal | E24: =[2]sales!C26 -> Chorizo | F24: =+VLOOKUP(sales[[#This Row],[Fecha]],maestro!A:C,3,0) -> 1 | H24: =+VLOOKUP(sales[[#This Row],[Fecha]],maestro!A:D,4,0) -> A) Día hábil | I24: =+TEXT(B24,"ddd") -> mar | J24: =+TEXT(B24,"mmmm") -> febrero | K24: =+M24*0.4 -> 3200 | L24: =[2]sales_BI!H23 -> 8000 | M24: =[2]sales_BI!L23 -> 8000 | N24: 0
B25: =[2]sales_BI!J24 -> 46077 | C25: =[2]sales_BI!$K$2 -> 04:36 p. m. | D25: Normal | E25: =[2]sales!C27 -> Chorizo | F25: =+VLOOKUP(sales[[#This Row],[Fecha]],maestro!A:C,3,0) -> 1 | H25: =+VLOOKUP(sales[[#This Row],[Fecha]],maestro!A:D,4,0) -> A) Día hábil | I25: =+TEXT(B25,"ddd") -> mar | J25: =+TEXT(B25,"mmmm") -> febrero | K25: =+M25*0.35 -> 2800 | L25: =[2]sales_BI!H24 -> 8000 | M25: =[2]sales_BI!L24 -> 8000 | N25: 0
B26: =[2]sales_BI!J25 -> 46077 | C26: =[2]sales_BI!$K$2 -> 04:36 p. m. | D26: Normal | E26: =[2]sales!C28 -> Chorizo | F26: =+VLOOKUP(sales[[#This Row],[Fecha]],maestro!A:C,3,0) -> 1 | H26: =+VLOOKUP(sales[[#This Row],[Fecha]],maestro!A:D,4,0) -> A) Día hábil | I26: =+TEXT(B26,"ddd") -> mar | J26: =+TEXT(B26,"mmmm") -> febrero | K26: =+M26*0.35 -> 5600 | L26: =[2]sales_BI!H25 -> 16000 | M26: =[2]sales_BI!L25 -> 16000 | N26: 0
B27: =[2]sales_BI!J26 -> 46077 | C27: =[2]sales_BI!$K$2 -> 04:36 p. m. | D27: Normal | E27: =[2]sales!C29 -> Chorizo | F27: =+VLOOKUP(sales[[#This Row],[Fecha]],maestro!A:C,3,0) -> 1 | H27: =+VLOOKUP(sales[[#This Row],[Fecha]],maestro!A:D,4,0) -> A) Día hábil | I27: =+TEXT(B27,"ddd") -> mar | J27: =+TEXT(B27,"mmmm") -> febrero | K27: =+M27*0.35 -> 2800 | L27: =[2]sales_BI!H26 -> 8000 | M27: =[2]sales_BI!L26 -> 8000 | N27: 0
B28: =[2]sales_BI!J27 -> 46077 | C28: =[2]sales_BI!$K$2 -> 04:36 p. m. | D28: Normal | E28: =[2]sales!C30 -> Chori- CRUDO | F28: =+VLOOKUP(sales[[#This Row],[Fecha]],maestro!A:C,3,0) -> 1 | H28: =+VLOOKUP(sales[[#This Row],[Fecha]],maestro!A:D,4,0) -> A) Día hábil | I28: =+TEXT(B28,"ddd") -> mar | J28: =+TEXT(B28,"mmmm") -> febrero | K28: =+M28*0.35 -> 3150 | L28: =[2]sales_BI!H27 -> 9000 | M28: =[2]sales_BI!L27 -> 9000 | N28: 0
B29: =[2]sales_BI!J28 -> 46077 | C29: =[2]sales_BI!$K$2 -> 04:36 p. m. | D29: Normal | E29: =[2]sales!C31 -> Chorizo | F29: =+VLOOKUP(sales[[#This Row],[Fecha]],maestro!A:C,3,0) -> 1 | H29: =+VLOOKUP(sales[[#This Row],[Fecha]],maestro!A:D,4,0) -> A) Día hábil | I29: =+TEXT(B29,"ddd") -> mar | J29: =+TEXT(B29,"mmmm") -> febrero | K29: =+M29*0.35 -> 2800 | L29: =[2]sales_BI!H28 -> 8000 | M29: =[2]sales_BI!L28 -> 8000 | N29: 0
B30: =[2]sales_BI!J29 -> 46077 | C30: =[2]sales_BI!$K$2 -> 04:36 p. m. | D30: Normal | E30: =[2]sales!C32 -> Chorizo | F30: =+VLOOKUP(sales[[#This Row],[Fecha]],maestro!A:C,3,0) -> 1 | H30: =+VLOOKUP(sales[[#This Row],[Fecha]],maestro!A:D,4,0) -> A) Día hábil | I30: =+TEXT(B30,"ddd") -> mar | J30: =+TEXT(B30,"mmmm") -> febrero | K30: =+M30*0.35 -> 2800 | L30: =[2]sales_BI!H29 -> 8000 | M30: =[2]sales_BI!L29 -> 8000 | N30: 0
B31: =[2]sales_BI!J30 -> 46077 | C31: =[2]sales_BI!$K$2 -> 04:36 p. m. | D31: Normal | E31: =[2]sales!C33 -> Chorizo | F31: =+VLOOKUP(sales[[#This Row],[Fecha]],maestro!A:C,3,0) -> 1 | H31: =+VLOOKUP(sales[[#This Row],[Fecha]],maestro!A:D,4,0) -> A) Día hábil | I31: =+TEXT(B31,"ddd") -> mar | J31: =+TEXT(B31,"mmmm") -> febrero | K31: =+M31*0.35 -> 0 | L31: =[2]sales_BI!H30 -> 8000 | M31: =[2]sales_BI!L30 -> 0 | N31: 0
B32: =[2]sales_BI!J31 -> 46077 | C32: =[2]sales_BI!$K$2 -> 04:36 p. m. | D32: Normal | E32: =[2]sales!C34 -> Chorizo | F32: =+VLOOKUP(sales[[#This Row],[Fecha]],maestro!A:C,3,0) -> 1 | H32: =+VLOOKUP(sales[[#This Row],[Fecha]],maestro!A:D,4,0) -> A) Día hábil | I32: =+TEXT(B32,"ddd") -> mar | J32: =+TEXT(B32,"mmmm") -> febrero | K32: =+M32*0.35 -> 2800 | L32: =[2]sales_BI!H31 -> 8000 | M32: =[2]sales_BI!L31 -> 8000 | N32: 0
B33: =[2]sales_BI!J32 -> 46077 | C33: =[2]sales_BI!$K$2 -> 04:36 p. m. | D33: Normal | E33: =[2]sales!C35 -> Agua | F33: =+VLOOKUP(sales[[#This Row],[Fecha]],maestro!A:C,3,0) -> 1 | H33: =+VLOOKUP(sales[[#This Row],[Fecha]],maestro!A:D,4,0) -> A) Día hábil | I33: =+TEXT(B33,"ddd") -> mar | J33: =+TEXT(B33,"mmmm") -> febrero | K33: =+M33*0.35 -> 1050 | L33: =[2]sales_BI!H32 -> 3000 | M33: =[2]sales_BI!L32 -> 3000 | N33: 0
B34: =[2]sales_BI!J33 -> 46077 | C34: =[2]sales_BI!$K$2 -> 04:36 p. m. | D34: Normal | E34: =[2]sales!C36 -> Chorizo | F34: =+VLOOKUP(sales[[#This Row],[Fecha]],maestro!A:C,3,0) -> 1 | H34: =+VLOOKUP(sales[[#This Row],[Fecha]],maestro!A:D,4,0) -> A) Día hábil | I34: =+TEXT(B34,"ddd") -> mar | J34: =+TEXT(B34,"mmmm") -> febrero | K34: =+M34*0.35 -> 8400 | L34: =[2]sales_BI!H33 -> 24000 | M34: =[2]sales_BI!L33 -> 24000 | N34: 0
B35: =[2]sales_BI!J34 -> 46077 | C35: =[2]sales_BI!$K$2 -> 04:36 p. m. | D35: Normal | E35: =[2]sales!C37 -> Postobon | F35: =+VLOOKUP(sales[[#This Row],[Fecha]],maestro!A:C,3,0) -> 1 | H35: =+VLOOKUP(sales[[#This Row],[Fecha]],maestro!A:D,4,0) -> A) Día hábil | I35: =+TEXT(B35,"ddd") -> mar | J35: =+TEXT(B35,"mmmm") -> febrero | K35: =+M35*0.35 -> 1050 | L35: =[2]sales_BI!H34 -> 3000 | M35: =[2]sales_BI!L34 -> 3000 | N35: 0
B36: =[2]sales_BI!J35 -> 46077 | C36: =[2]sales_BI!$K$2 -> 04:36 p. m. | D36: Normal | E36: =[2]sales!C38 -> Chorizo | F36: =+VLOOKUP(sales[[#This Row],[Fecha]],maestro!A:C,3,0) -> 1 | H36: =+VLOOKUP(sales[[#This Row],[Fecha]],maestro!A:D,4,0) -> A) Día hábil | I36: =+TEXT(B36,"ddd") -> mar | J36: =+TEXT(B36,"mmmm") -> febrero | K36: =+M36*0.35 -> 11200 | L36: =[2]sales_BI!H35 -> 32000 | M36: =[2]sales_BI!L35 -> 32000 | N36: 0
... B94: =[2]sales_BI!J93 -> 46080 | C94: =[2]sales_BI!$K$2 -> 04:36 p. m. | D94: Normal | E94: =[2]sales!C96 -> Chorizo | F94: =+VLOOKUP(sales[[#This Row],[Fecha]],maestro!A:C,3,0) -> 1 | H94: =+VLOOKUP(sales[[#This Row],[Fecha]],maestro!A:D,4,0) -> C) Viernes | I94: =+TEXT(B94,"ddd") -> vie | J94: =+TEXT(B94,"mmmm") -> febrero | K94: =+M94*0.35 -> 0 | L94: =[2]sales_BI!H93 -> 24000 | M94: =[2]sales_BI!L93 -> 0 | N94: 0
B95: =[2]sales_BI!J94 -> 46080 | C95: =[2]sales_BI!$K$2 -> 04:36 p. m. | D95: Normal | E95: =[2]sales!C97 -> Agua | F95: =+VLOOKUP(sales[[#This Row],[Fecha]],maestro!A:C,3,0) -> 1 | H95: =+VLOOKUP(sales[[#This Row],[Fecha]],maestro!A:D,4,0) -> C) Viernes | I95: =+TEXT(B95,"ddd") -> vie | J95: =+TEXT(B95,"mmmm") -> febrero | K95: =+M95*0.35 -> 0 | L95: =[2]sales_BI!H94 -> 3000 | M95: =[2]sales_BI!L94 -> 0 | N95: 0 | O95: ='Cuentas x Pagar'!$L$26 -> 0
B96: =[2]sales_BI!J95 -> 46080 | C96: =[2]sales_BI!$K$2 -> 04:36 p. m. | D96: Normal | E96: =[2]sales!C98 -> Chorizo | F96: =+VLOOKUP(sales[[#This Row],[Fecha]],maestro!A:C,3,0) -> 1 | H96: =+VLOOKUP(sales[[#This Row],[Fecha]],maestro!A:D,4,0) -> C) Viernes | I96: =+TEXT(B96,"ddd") -> vie | J96: =+TEXT(B96,"mmmm") -> febrero | K96: =+M96*0.35 -> 0 | L96: =[2]sales_BI!H95 -> 8000 | M96: =[2]sales_BI!L95 -> 0 | N96: 0
B97: =[2]sales_BI!J96 -> 46080 | C97: =[2]sales_BI!$K$2 -> 04:36 p. m. | D97: Normal | E97: =[2]sales!C99 -> Chorizo | F97: =+VLOOKUP(sales[[#This Row],[Fecha]],maestro!A:C,3,0) -> 1 | H97: =+VLOOKUP(sales[[#This Row],[Fecha]],maestro!A:D,4,0) -> C) Viernes | I97: =+TEXT(B97,"ddd") -> vie | J97: =+TEXT(B97,"mmmm") -> febrero | K97: =+M97*0.35 -> 0 | L97: =[2]sales_BI!H96 -> 16000 | M97: =[2]sales_BI!L96 -> 0 | N97: 0
B98: =[2]sales_BI!J97 -> 46080 | C98: =[2]sales_BI!$K$2 -> 04:36 p. m. | D98: Normal | E98: =[2]sales!C100 -> Chorizo | F98: =+VLOOKUP(sales[[#This Row],[Fecha]],maestro!A:C,3,0) -> 1 | H98: =+VLOOKUP(sales[[#This Row],[Fecha]],maestro!A:D,4,0) -> C) Viernes | I98: =+TEXT(B98,"ddd") -> vie | J98: =+TEXT(B98,"mmmm") -> febrero | K98: =+M98*0.35 -> 11200 | L98: =[2]sales_BI!H97 -> 32000 | M98: =[2]sales_BI!L97 -> 32000 | N98: 0
B99: =[2]sales_BI!J98 -> 46080 | C99: =[2]sales_BI!$K$2 -> 04:36 p. m. | D99: Normal | E99: =[2]sales!C101 -> Coca cola | F99: =+VLOOKUP(sales[[#This Row],[Fecha]],maestro!A:C,3,0) -> 1 | H99: =+VLOOKUP(sales[[#This Row],[Fecha]],maestro!A:D,4,0) -> C) Viernes | I99: =+TEXT(B99,"ddd") -> vie | J99: =+TEXT(B99,"mmmm") -> febrero | K99: =+M99*0.35 -> 3150 | L99: =[2]sales_BI!H98 -> 9000 | M99: =[2]sales_BI!L98 -> 9000 | N99: 0
B100: =[2]sales_BI!J99 -> 46080 | C100: =[2]sales_BI!$K$2 -> 04:36 p. m. | D100: Normal | E100: =[2]sales!C102 -> Chorizo | F100: =+VLOOKUP(sales[[#This Row],[Fecha]],maestro!A:C,3,0) -> 1 | H100: =+VLOOKUP(sales[[#This Row],[Fecha]],maestro!A:D,4,0) -> C) Viernes | I100: =+TEXT(B100,"ddd") -> vie | J100: =+TEXT(B100,"mmmm") -> febrero | K100: =+M100*0.35 -> 2800 | L100: =[2]sales_BI!H99 -> 8000 | M100: =[2]sales_BI!L99 -> 8000 | N100: 0
B101: =[2]sales_BI!J100 -> 46081 | C101: =[2]sales_BI!$K$2 -> 04:36 p. m. | D101: Normal | E101: =[2]sales!C103 -> Chori- CRUDO | F101: =+VLOOKUP(sales[[#This Row],[Fecha]],maestro!A:C,3,0) -> 1 | H101: =+VLOOKUP(sales[[#This Row],[Fecha]],maestro!A:D,4,0) -> C) Sábado | I101: =+TEXT(B101,"ddd") -> sáb | J101: =+TEXT(B101,"mmmm") -> febrero | K101: =+M101*0.35 -> 9450 | L101: =[2]sales_BI!H100 -> 27000 | M101: =[2]sales_BI!L100 -> 27000 | N101: 0
B102: =[2]sales_BI!J101 -> 46081 | C102: =[2]sales_BI!$K$2 -> 04:36 p. m. | D102: Normal | E102: =[2]sales!C104 -> Chorizo | F102: =+VLOOKUP(sales[[#This Row],[Fecha]],maestro!A:C,3,0) -> 1 | H102: =+VLOOKUP(sales[[#This Row],[Fecha]],maestro!A:D,4,0) -> C) Sábado | I102: =+TEXT(B102,"ddd") -> sáb | J102: =+TEXT(B102,"mmmm") -> febrero | K102: =+M102*0.35 -> 0 | L102: =[2]sales_BI!H101 -> 16000 | M102: =[2]sales_BI!L101 -> 0 | N102: 0
B103: =[2]sales_BI!J102 -> 46081 | C103: =[2]sales_BI!$K$2 -> 04:36 p. m. | D103: Normal | E103: =[2]sales!C105 -> Agua | F103: =+VLOOKUP(sales[[#This Row],[Fecha]],maestro!A:C,3,0) -> 1 | H103: =+VLOOKUP(sales[[#This Row],[Fecha]],maestro!A:D,4,0) -> C) Sábado | I103: =+TEXT(B103,"ddd") -> sáb | J103: =+TEXT(B103,"mmmm") -> febrero | K103: =+M103*0.35 -> 0 | L103: =[2]sales_BI!H102 -> 3000 | M103: =[2]sales_BI!L102 -> 0 | N103: 0
B104: =[2]sales_BI!J103 -> 46081 | C104: =[2]sales_BI!$K$2 -> 04:36 p. m. | D104: Normal | E104: =[2]sales!C106 -> Chorizo | F104: =+VLOOKUP(sales[[#This Row],[Fecha]],maestro!A:C,3,0) -> 1 | H104: =+VLOOKUP(sales[[#This Row],[Fecha]],maestro!A:D,4,0) -> C) Sábado | I104: =+TEXT(B104,"ddd") -> sáb | J104: =+TEXT(B104,"mmmm") -> febrero | K104: =+M104*0.35 -> 0 | L104: =[2]sales_BI!H103 -> 8000 | M104: =[2]sales_BI!L103 -> 0 | N104: 0
B105: =[2]sales_BI!J104 -> 46081 | C105: =[2]sales_BI!$K$2 -> 04:36 p. m. | D105: Normal | E105: =[2]sales!C107 -> tinto | F105: =+VLOOKUP(sales[[#This Row],[Fecha]],maestro!A:C,3,0) -> 1 | H105: =+VLOOKUP(sales[[#This Row],[Fecha]],maestro!A:D,4,0) -> C) Sábado | I105: =+TEXT(B105,"ddd") -> sáb | J105: =+TEXT(B105,"mmmm") -> febrero | K105: =+M105*0.35 -> 0 | L105: =[2]sales_BI!H104 -> 2000 | M105: =[2]sales_BI!L104 -> 0 | N105: 0
B106: =[2]sales_BI!J105 -> 46081 | C106: =[2]sales_BI!$K$2 -> 04:36 p. m. | D106: Normal | E106: =[2]sales!C108 -> Chorizo | F106: =+VLOOKUP(sales[[#This Row],[Fecha]],maestro!A:C,3,0) -> 1 | H106: =+VLOOKUP(sales[[#This Row],[Fecha]],maestro!A:D,4,0) -> C) Sábado | I106: =+TEXT(B106,"ddd") -> sáb | J106: =+TEXT(B106,"mmmm") -> febrero | K106: =+M106*0.35 -> 5600 | L106: =[2]sales_BI!H105 -> 16000 | M106: =[2]sales_BI!L105 -> 16000 | N106: 0
B107: =[2]sales_BI!J106 -> 46081 | C107: =[2]sales_BI!$K$2 -> 04:36 p. m. | D107: Normal | E107: =[2]sales!C109 -> Coca cola | F107: =+VLOOKUP(sales[[#This Row],[Fecha]],maestro!A:C,3,0) -> 1 | H107: =+VLOOKUP(sales[[#This Row],[Fecha]],maestro!A:D,4,0) -> C) Sábado | I107: =+TEXT(B107,"ddd") -> sáb | J107: =+TEXT(B107,"mmmm") -> febrero | K107: =+M107*0.35 -> 1050 | L107: =[2]sales_BI!H106 -> 3000 | M107: =[2]sales_BI!L106 -> 3000 | N107: 0
B108: =[2]sales_BI!J107 -> 46081 | C108: =[2]sales_BI!$K$2 -> 04:36 p. m. | D108: Normal | E108: =[2]sales!C110 -> Chorizo | F108: =+VLOOKUP(sales[[#This Row],[Fecha]],maestro!A:C,3,0) -> 1 | H108: =+VLOOKUP(sales[[#This Row],[Fecha]],maestro!A:D,4,0) -> C) Sábado | I108: =+TEXT(B108,"ddd") -> sáb | J108: =+TEXT(B108,"mmmm") -> febrero | K108: =+M108*0.35 -> 5600 | L108: =[2]sales_BI!H107 -> 16000 | M108: =[2]sales_BI!L107 -> 16000 | N108: 0
B109: =[2]sales_BI!J108 -> 46081 | C109: =[2]sales_BI!$K$2 -> 04:36 p. m. | D109: Normal | E109: =[2]sales!C111 -> Coca cola | F109: =+VLOOKUP(sales[[#This Row],[Fecha]],maestro!A:C,3,0) -> 1 | H109: =+VLOOKUP(sales[[#This Row],[Fecha]],maestro!A:D,4,0) -> C) Sábado | I109: =+TEXT(B109,"ddd") -> sáb | J109: =+TEXT(B109,"mmmm") -> febrero | K109: =+VLOOKUP(sales[[#This Row],[nombre_producto]],products!A:C,3,0) -> 1200 | L109: =[2]sales_BI!H108 -> 3000 | M109: =[2]sales_BI!L108 -> 3000 | N109: 0
B110: =[2]sales_BI!J109 -> 46081 | C110: =[2]sales_BI!$K$2 -> 04:36 p. m. | D110: Normal | E110: =[2]sales!C112 -> Chorizo | F110: =+VLOOKUP(sales[[#This Row],[Fecha]],maestro!A:C,3,0) -> 1 | H110: =+VLOOKUP(sales[[#This Row],[Fecha]],maestro!A:D,4,0) -> C) Sábado | I110: =+TEXT(B110,"ddd") -> sáb | J110: =+TEXT(B110,"mmmm") -> febrero | K110: =+M110*0.35 -> 2800 | L110: =[2]sales_BI!H109 -> 8000 | M110: =[2]sales_BI!L109 -> 8000 | N110: 0
B111: =[2]sales_BI!J110 -> 46081 | C111: =[2]sales_BI!$K$2 -> 04:36 p. m. | D111: Normal | E111: =[2]sales!C113 -> Coca cola | F111: =+VLOOKUP(sales[[#This Row],[Fecha]],maestro!A:C,3,0) -> 1 | H111: =+VLOOKUP(sales[[#This Row],[Fecha]],maestro!A:D,4,0) -> C) Sábado | I111: =+TEXT(B111,"ddd") -> sáb | J111: =+TEXT(B111,"mmmm") -> febrero | K111: =+M111*0.35 -> 1050 | L111: =[2]sales_BI!H110 -> 3000 | M111: =[2]sales_BI!L110 -> 3000 | N111: 0
B112: =[2]sales_BI!J111 -> 46081 | C112: =[2]sales_BI!$K$2 -> 04:36 p. m. | D112: Normal | E112: =[2]sales!C114 -> Chorizo | F112: =+VLOOKUP(sales[[#This Row],[Fecha]],maestro!A:C,3,0) -> 1 | H112: =+VLOOKUP(sales[[#This Row],[Fecha]],maestro!A:D,4,0) -> C) Sábado | I112: =+TEXT(B112,"ddd") -> sáb | J112: =+TEXT(B112,"mmmm") -> febrero | K112: =+M112*0.35 -> 11200 | L112: =[2]sales_BI!H111 -> 32000 | M112: =[2]sales_BI!L111 -> 32000 | N112: 0
B113: =[2]sales_BI!J112 -> 46081 | C113: =[2]sales_BI!$K$2 -> 04:36 p. m. | D113: Normal | E113: =[2]sales!C115 -> Coca cola | F113: =+VLOOKUP(sales[[#This Row],[Fecha]],maestro!A:C,3,0) -> 1 | H113: =+VLOOKUP(sales[[#This Row],[Fecha]],maestro!A:D,4,0) -> C) Sábado | I113: =+TEXT(B113,"ddd") -> sáb | J113: =+TEXT(B113,"mmmm") -> febrero | K113: =+M113*0.35 -> 2100 | L113: =[2]sales_BI!H112 -> 6000 | M113: =[2]sales_BI!L112 -> 6000 | N113: 25000
B114: =[2]sales_BI!J113 -> 46081 | C114: =[2]sales_BI!$K$2 -> 04:36 p. m. | D114: Normal | E114: =[2]sales!C116 -> Chorizo | F114: =+VLOOKUP(sales[[#This Row],[Fecha]],maestro!A:C,3,0) -> 1 | H114: =+VLOOKUP(sales[[#This Row],[Fecha]],maestro!A:D,4,0) -> C) Sábado | I114: =+TEXT(B114,"ddd") -> sáb | J114: =+TEXT(B114,"mmmm") -> febrero | K114: =+M114*0.35 -> 5600 | L114: =[2]sales_BI!H113 -> 16000 | M114: =[2]sales_BI!L113 -> 16000 | N114: 0
B115: =[2]sales_BI!J114 -> 46081 | C115: =[2]sales_BI!$K$2 -> 04:36 p. m. | D115: Normal | E115: =[2]sales!C117 -> Chorizo | F115: =+VLOOKUP(sales[[#This Row],[Fecha]],maestro!A:C,3,0) -> 1 | H115: =+VLOOKUP(sales[[#This Row],[Fecha]],maestro!A:D,4,0) -> C) Sábado | I115: =+TEXT(B115,"ddd") -> sáb | J115: =+TEXT(B115,"mmmm") -> febrero | K115: =+M115*0.35 -> 8400 | L115: =[2]sales_BI!H114 -> 24000 | M115: =[2]sales_BI!L114 -> 24000 | N115: 0
B116: =[2]sales_BI!J115 -> 46081 | C116: =[2]sales_BI!$K$2 -> 04:36 p. m. | D116: Normal | E116: =[2]sales!C118 -> Hit | F116: =+VLOOKUP(sales[[#This Row],[Fecha]],maestro!A:C,3,0) -> 1 | H116: =+VLOOKUP(sales[[#This Row],[Fecha]],maestro!A:D,4,0) -> C) Sábado | I116: =+TEXT(B116,"ddd") -> sáb | J116: =+TEXT(B116,"mmmm") -> febrero | K116: =+M116*0.35 -> 1575 | L116: =[2]sales_BI!H115 -> 4500 | M116: =[2]sales_BI!L115 -> 4500 | N116: 0
B117: =[2]sales_BI!J116 -> 46081 | C117: =[2]sales_BI!$K$2 -> 04:36 p. m. | D117: Normal | E117: =[2]sales!C119 -> parri tres carnes | F117: =+VLOOKUP(sales[[#This Row],[Fecha]],maestro!A:C,3,0) -> 1 | H117: =+VLOOKUP(sales[[#This Row],[Fecha]],maestro!A:D,4,0) -> C) Sábado | I117: =+TEXT(B117,"ddd") -> sáb | J117: =+TEXT(B117,"mmmm") -> febrero | K117: =+M117*0.35 -> 12250 | L117: =[2]sales_BI!H116 -> 35000 | M117: =[2]sales_BI!L116 -> 35000 | N117: 0
B118: =[2]sales_BI!J117 -> 46081 | C118: =[2]sales_BI!$K$2 -> 04:36 p. m. | D118: Normal | E118: =[2]sales!C120 -> parri tres carnes | F118: =+VLOOKUP(sales[[#This Row],[Fecha]],maestro!A:C,3,0) -> 1 | H118: =+VLOOKUP(sales[[#This Row],[Fecha]],maestro!A:D,4,0) -> C) Sábado | I118: =+TEXT(B118,"ddd") -> sáb | J118: =+TEXT(B118,"mmmm") -> febrero | K118: =+M118*0.35 -> 12250 | L118: =[2]sales_BI!H117 -> 35000 | M118: =[2]sales_BI!L117 -> 35000 | N118: 0
B119: =[2]sales_BI!J118 -> 46081 | C119: =[2]sales_BI!$K$2 -> 04:36 p. m. | D119: Normal | E119: =[2]sales!C121 -> parri 48 | F119: =+VLOOKUP(sales[[#This Row],[Fecha]],maestro!A:C,3,0) -> 1 | H119: =+VLOOKUP(sales[[#This Row],[Fecha]],maestro!A:D,4,0) -> C) Sábado | I119: =+TEXT(B119,"ddd") -> sáb | J119: =+TEXT(B119,"mmmm") -> febrero | K119: =+M119*0.35 -> 16800 | L119: =[2]sales_BI!H118 -> 48000 | M119: =[2]sales_BI!L118 -> 48000 | N119: 0
B120: =[2]sales_BI!J119 -> 46081 | C120: =[2]sales_BI!$K$2 -> 04:36 p. m. | D120: Normal | E120: =[2]sales!C122 -> parri 70 | F120: =+VLOOKUP(sales[[#This Row],[Fecha]],maestro!A:C,3,0) -> 1 | H120: =+VLOOKUP(sales[[#This Row],[Fecha]],maestro!A:D,4,0) -> C) Sábado | I120: =+TEXT(B120,"ddd") -> sáb | J120: =+TEXT(B120,"mmmm") -> febrero | K120: =+M120*0.35 -> 49000 | L120: =[2]sales_BI!H119 -> 140000 | M120: =[2]sales_BI!L119 -> 140000 | N120: 0
B121: =[2]sales_BI!J120 -> 46081 | C121: =[2]sales_BI!$K$2 -> 04:36 p. m. | D121: Normal | E121: =[2]sales!C123 -> parri 40 | F121: =+VLOOKUP(sales[[#This Row],[Fecha]],maestro!A:C,3,0) -> 1 | H121: =+VLOOKUP(sales[[#This Row],[Fecha]],maestro!A:D,4,0) -> C) Sábado | I121: =+TEXT(B121,"ddd") -> sáb | J121: =+TEXT(B121,"mmmm") -> febrero | K121: =+M121*0.35 -> 14000 | L121: =[2]sales_BI!H120 -> 40000 | M121: =[2]sales_BI!L120 -> 40000 | N121: 0
B122: =[2]sales_BI!J121 -> 46081 | C122: =[2]sales_BI!$K$2 -> 04:36 p. m. | D122: Normal | E122: =[2]sales!C124 -> Chori- CRUDO | F122: =+VLOOKUP(sales[[#This Row],[Fecha]],maestro!A:C,3,0) -> 1 | H122: =+VLOOKUP(sales[[#This Row],[Fecha]],maestro!A:D,4,0) -> C) Sábado | I122: =+TEXT(B122,"ddd") -> sáb | J122: =+TEXT(B122,"mmmm") -> febrero | K122: =+M122*0.35 -> 0 | L122: =[2]sales_BI!H121 -> 18000 | M122: =[2]sales_BI!L121 -> 0 | N122: 0

Sheet products
A1: nombre_producto | B1: precio_producto | C1: costo_producto
A2: Chorizo | B2: 8000 | C2: =3500+8000 -> 11500
A3: Hit | B3: 4500 | C3: 2416.6667
A4: Coca cola | B4: 3000 | C4: 1200
A5: Agua | B5: 3000 | C5: 1200
A6: Postobon | B6: 3000 | C6: 1166.6667 | F6: agua | G6: 33000 | H6: 24 | I6: =+G6/H6 -> 1375
A7: Chori- CRUDO | B7: 4500 | C7: 3500 | F7: hit | G7: 29000 | H7: 12 | I7: =+G7/H7 -> 2416.6667
A8: parri tres carnes | B8: 35000 | C8: 25000 | F8: postobon | G8: 35000 | H8: 30 | I8: =+G8/H8 -> 1166.6667
A9: carne + chorizo | B9: 25000 | C9: 15000 | F9: coca cola | G9: 36000 | H9: 30 | I9: =+G9/H9 -> 1200
A10: tinto | B10: 2000 | C10: 800
A11: parri 48 | B11: 48000 | C11: 30000
A12: parri 70 | B12: 70000 | C12: 45000
A13: parri 40 | B13: 40000 | C13: 25000

Sheet egresos
B2: Fecha | C2: dia_sem | D2: Gastos | E2: Arriendo | F2: Servicios | G2: Gas | H2: Agua | I2: Internet | J2: Electricidad | K2: Nomina | L2: Cajero | M2: Parrillero | N2: Domiciliario
B3: 46068 | C3: =+TEXT(sales2[[#This Row],[Fecha]],"ddd") -> dom | D3: =+sales2[[#This Row],[Arriendo]]+sales2[[#This Row],[Gas]]+sales2[[#This Row],[Agua]]+sales2[[#This Row],[Electricidad]]+sales2[[#This Row],[Nomina]] -> 0 | E3: =+VLOOKUP(sales2[[#This Row],[Fecha]],Opex!C:J,8,1) -> 0 | F3: =+SUM(sales2[[#This Row],[Gas]:[Electricidad]]) -> 0 | K3: =+SUM(sales2[[#This Row],[Cajero]:[Domiciliario]]) -> 0 | L3: 0 | M3: 0 | N3: 0 | Q3: =+#REF! -> #REF!
B4: =+B3+1 -> 46069 | C4: =+TEXT(sales2[[#This Row],[Fecha]],"ddd") -> lun | D4: =+sales2[[#This Row],[Arriendo]]+sales2[[#This Row],[Gas]]+sales2[[#This Row],[Agua]]+sales2[[#This Row],[Electricidad]]+sales2[[#This Row],[Nomina]] -> 0 | E4: =+VLOOKUP(sales2[[#This Row],[Fecha]],Opex!C:J,8,1) -> 0 | F4: =+SUM(sales2[[#This Row],[Gas]:[Electricidad]]) -> 0 | K4: =+SUM(sales2[[#This Row],[Cajero]:[Domiciliario]]) -> 0 | L4: 0 | M4: 0 | N4: 0
B5: =+B4+1 -> 46070 | C5: =+TEXT(sales2[[#This Row],[Fecha]],"ddd") -> mar | D5: =+sales2[[#This Row],[Arriendo]]+sales2[[#This Row],[Gas]]+sales2[[#This Row],[Agua]]+sales2[[#This Row],[Electricidad]]+sales2[[#This Row],[Nomina]] -> 0 | E5: =+VLOOKUP(sales2[[#This Row],[Fecha]],Opex!C:J,8,1) -> 0 | F5: =+SUM(sales2[[#This Row],[Gas]:[Electricidad]]) -> 0 | K5: =+SUM(sales2[[#This Row],[Cajero]:[Domiciliario]]) -> 0 | L5: 0 | M5: 0 | N5: 0
B6: =+B5+1 -> 46071 | C6: =+TEXT(sales2[[#This Row],[Fecha]],"ddd") -> mié | D6: =+sales2[[#This Row],[Arriendo]]+sales2[[#This Row],[Gas]]+sales2[[#This Row],[Agua]]+sales2[[#This Row],[Electricidad]]+sales2[[#This Row],[Nomina]] -> 0 | E6: =+VLOOKUP(sales2[[#This Row],[Fecha]],Opex!C:J,8,1) -> 0 | F6: =+SUM(sales2[[#This Row],[Gas]:[Electricidad]]) -> 0 | K6: =+SUM(sales2[[#This Row],[Cajero]:[Domiciliario]]) -> 0 | L6: 0 | M6: 0 | N6: 0
B7: =+B6+1 -> 46072 | C7: =+TEXT(sales2[[#This Row],[Fecha]],"ddd") -> jue | D7: =+sales2[[#This Row],[Arriendo]]+sales2[[#This Row],[Gas]]+sales2[[#This Row],[Agua]]+sales2[[#This Row],[Electricidad]]+sales2[[#This Row],[Nomina]] -> 0 | E7: =+VLOOKUP(sales2[[#This Row],[Fecha]],Opex!C:J,8,1) -> 0 | F7: =+SUM(sales2[[#This Row],[Gas]:[Electricidad]]) -> 0 | K7: =+SUM(sales2[[#This Row],[Cajero]:[Domiciliario]]) -> 0 | L7: 0 | M7: 0 | N7: 0
B8: =+B7+1 -> 46073 | C8: =+TEXT(sales2[[#This Row],[Fecha]],"ddd") -> vie | D8: =+sales2[[#This Row],[Arriendo]]+sales2[[#This Row],[Gas]]+sales2[[#This Row],[Agua]]+sales2[[#This Row],[Electricidad]]+sales2[[#This Row],[Nomina]] -> 0 | E8: =+VLOOKUP(sales2[[#This Row],[Fecha]],Opex!C:J,8,1) -> 0 | F8: =+SUM(sales2[[#This Row],[Gas]:[Electricidad]]) -> 0 | K8: =+SUM(sales2[[#This Row],[Cajero]:[Domiciliario]]) -> 0 | L8: 0 | M8: 0 | N8: 0 | Q8: =25000*30 -> 750000
B9: =+B8+1 -> 46074 | C9: =+TEXT(sales2[[#This Row],[Fecha]],"ddd") -> sáb | D9: =+sales2[[#This Row],[Arriendo]]+sales2[[#This Row],[Gas]]+sales2[[#This Row],[Agua]]+sales2[[#This Row],[Electricidad]]+sales2[[#This Row],[Nomina]] -> 0 | E9: =+VLOOKUP(sales2[[#This Row],[Fecha]],Opex!C:J,8,1) -> 0 | F9: =+SUM(sales2[[#This Row],[Gas]:[Electricidad]]) -> 0 | K9: =+SUM(sales2[[#This Row],[Cajero]:[Domiciliario]]) -> 0 | L9: 0 | M9: 0 | N9: 0
B10: =+B9+1 -> 46075 | C10: =+TEXT(sales2[[#This Row],[Fecha]],"ddd") -> dom | D10: =+sales2[[#This Row],[Arriendo]]+sales2[[#This Row],[Gas]]+sales2[[#This Row],[Agua]]+sales2[[#This Row],[Electricidad]]+sales2[[#This Row],[Nomina]] -> 0 | E10: =+VLOOKUP(sales2[[#This Row],[Fecha]],Opex!C:J,8,1) -> 0 | F10: =+SUM(sales2[[#This Row],[Gas]:[Electricidad]]) -> 0 | K10: =+SUM(sales2[[#This Row],[Cajero]:[Domiciliario]]) -> 0 | L10: 0 | M10: 0 | N10: 0
B11: =+B10+1 -> 46076 | C11: =+TEXT(sales2[[#This Row],[Fecha]],"ddd") -> lun | D11: =+sales2[[#This Row],[Arriendo]]+sales2[[#This Row],[Gas]]+sales2[[#This Row],[Agua]]+sales2[[#This Row],[Electricidad]]+sales2[[#This Row],[Nomina]] -> 60000 | E11: =+VLOOKUP(sales2[[#This Row],[Fecha]],Opex!C:J,8,1) -> 0 | F11: =+SUM(sales2[[#This Row],[Gas]:[Electricidad]]) -> 0 | K11: =+SUM(sales2[[#This Row],[Cajero]:[Domiciliario]]) -> 60000 | L11: 60000 | M11: 0 | N11: 0
B12: =+B11+1 -> 46077 | C12: =+TEXT(sales2[[#This Row],[Fecha]],"ddd") -> mar | D12: =+sales2[[#This Row],[Arriendo]]+sales2[[#This Row],[Gas]]+sales2[[#This Row],[Agua]]+sales2[[#This Row],[Electricidad]]+sales2[[#This Row],[Nomina]] -> 70000 | E12: =+VLOOKUP(sales2[[#This Row],[Fecha]],Opex!C:J,8,1) -> 0 | F12: =+SUM(sales2[[#This Row],[Gas]:[Electricidad]]) -> 0 | K12: =+SUM(sales2[[#This Row],[Cajero]:[Domiciliario]]) -> 70000 | L12: 70000 | M12: 0 | N12: 0
B13: =+B12+1 -> 46078 | C13: =+TEXT(sales2[[#This Row],[Fecha]],"ddd") -> mié | D13: =+sales2[[#This Row],[Arriendo]]+sales2[[#This Row],[Gas]]+sales2[[#This Row],[Agua]]+sales2[[#This Row],[Electricidad]]+sales2[[#This Row],[Nomina]] -> 70000 | E13: =+VLOOKUP(sales2[[#This Row],[Fecha]],Opex!C:J,8,1) -> 0 | F13: =+SUM(sales2[[#This Row],[Gas]:[Electricidad]]) -> 0 | K13: =+SUM(sales2[[#This Row],[Cajero]:[Domiciliario]]) -> 70000 | L13: 70000 | M13: 0 | N13: 0
B14: =+B13+1 -> 46079 | C14: =+TEXT(sales2[[#This Row],[Fecha]],"ddd") -> jue | D14: =+sales2[[#This Row],[Arriendo]]+sales2[[#This Row],[Gas]]+sales2[[#This Row],[Agua]]+sales2[[#This Row],[Electricidad]]+sales2[[#This Row],[Nomina]] -> 70000 | E14: =+VLOOKUP(sales2[[#This Row],[Fecha]],Opex!C:J,8,1) -> 0 | F14: =+SUM(sales2[[#This Row],[Gas]:[Electricidad]]) -> 0 | K14: =+SUM(sales2[[#This Row],[Cajero]:[Domiciliario]]) -> 70000 | L14: 70000 | M14: 0 | N14: 0
B15: =+B14+1 -> 46080 | C15: =+TEXT(sales2[[#This Row],[Fecha]],"ddd") -> vie | D15: =+sales2[[#This Row],[Arriendo]]+sales2[[#This Row],[Gas]]+sales2[[#This Row],[Agua]]+sales2[[#This Row],[Electricidad]]+sales2[[#This Row],[Nomina]] -> 70000 | E15: =+VLOOKUP(sales2[[#This Row],[Fecha]],Opex!C:J,8,1) -> 0 | F15: =+SUM(sales2[[#This Row],[Gas]:[Electricidad]]) -> 0 | K15: =+SUM(sales2[[#This Row],[Cajero]:[Domiciliario]]) -> 70000 | L15: 70000 | M15: 0 | N15: 0
B16: =+B15+1 -> 46081 | C16: =+TEXT(sales2[[#This Row],[Fecha]],"ddd") -> sáb | D16: =+sales2[[#This Row],[Arriendo]]+sales2[[#This Row],[Gas]]+sales2[[#This Row],[Agua]]+sales2[[#This Row],[Electricidad]]+sales2[[#This Row],[Nomina]] -> 70000 | E16: =+VLOOKUP(sales2[[#This Row],[Fecha]],Opex!C:J,8,1) -> 0 | F16: =+SUM(sales2[[#This Row],[Gas]:[Electricidad]]) -> 0 | K16: =+SUM(sales2[[#This Row],[Cajero]:[Domiciliario]]) -> 70000 | L16: 70000 | M16: 0 | N16: 0
B17: =+B16+1 -> 46082 | C17: =+TEXT(sales2[[#This Row],[Fecha]],"ddd") -> dom | D17: =+sales2[[#This Row],[Arriendo]]+sales2[[#This Row],[Gas]]+sales2[[#This Row],[Agua]]+sales2[[#This Row],[Electricidad]]+sales2[[#This Row],[Nomina]] -> 0 | E17: =+VLOOKUP(sales2[[#This Row],[Fecha]],Opex!C:J,8,1) -> 0 | F17: =+SUM(sales2[[#This Row],[Gas]:[Electricidad]]) -> 0 | K17: =+SUM(sales2[[#This Row],[Cajero]:[Domiciliario]]) -> 0 | L17: 0 | M17: 0 | N17: 0
B18: =+B17+1 -> 46083 | C18: =+TEXT(sales2[[#This Row],[Fecha]],"ddd") -> lun | D18: =+sales2[[#This Row],[Arriendo]]+sales2[[#This Row],[Gas]]+sales2[[#This Row],[Agua]]+sales2[[#This Row],[Electricidad]]+sales2[[#This Row],[Nomina]] -> 0 | E18: =+VLOOKUP(sales2[[#This Row],[Fecha]],Opex!C:J,8,1) -> 0 | F18: =+SUM(sales2[[#This Row],[Gas]:[Electricidad]]) -> 0 | K18: =+SUM(sales2[[#This Row],[Cajero]:[Domiciliario]]) -> 0 | L18: 0 | M18: 0 | N18: 0
B19: =+B18+1 -> 46084 | C19: =+TEXT(sales2[[#This Row],[Fecha]],"ddd") -> mar | D19: =+sales2[[#This Row],[Arriendo]]+sales2[[#This Row],[Gas]]+sales2[[#This Row],[Agua]]+sales2[[#This Row],[Electricidad]]+sales2[[#This Row],[Nomina]] -> 0 | E19: =+VLOOKUP(sales2[[#This Row],[Fecha]],Opex!C:J,8,1) -> 0 | F19: =+SUM(sales2[[#This Row],[Gas]:[Electricidad]]) -> 0 | K19: =+SUM(sales2[[#This Row],[Cajero]:[Domiciliario]]) -> 0 | L19: 0 | M19: 0 | N19: 0
B20: =+B19+1 -> 46085 | C20: =+TEXT(sales2[[#This Row],[Fecha]],"ddd") -> mié | D20: =+sales2[[#This Row],[Arriendo]]+sales2[[#This Row],[Gas]]+sales2[[#This Row],[Agua]]+sales2[[#This Row],[Electricidad]]+sales2[[#This Row],[Nomina]] -> 0 | E20: =+VLOOKUP(sales2[[#This Row],[Fecha]],Opex!C:J,8,1) -> 0 | F20: =+SUM(sales2[[#This Row],[Gas]:[Electricidad]]) -> 0 | K20: =+SUM(sales2[[#This Row],[Cajero]:[Domiciliario]]) -> 0 | L20: 0 | M20: 0 | N20: 0
... B40: =+B39+1 -> 46105 | C40: =+TEXT(sales2[[#This Row],[Fecha]],"ddd") -> mar | D40: =+sales2[[#This Row],[Arriendo]]+sales2[[#This Row],[Gas]]+sales2[[#This Row],[Agua]]+sales2[[#This Row],[Electricidad]]+sales2[[#This Row],[Nomina]] -> 55000 | E40: =+VLOOKUP(sales2[[#This Row],[Fecha]],Opex!C:J,8,1) -> 55000 | F40: =+SUM(sales2[[#This Row],[Gas]:[Electricidad]]) -> 0 | K40: =+SUM(sales2[[#This Row],[Cajero]:[Domiciliario]]) -> 0 | L40: 0 | M40: 0 | N40: 0
B41: =+B40+1 -> 46106 | C41: =+TEXT(sales2[[#This Row],[Fecha]],"ddd") -> mié | D41: =+sales2[[#This Row],[Arriendo]]+sales2[[#This Row],[Gas]]+sales2[[#This Row],[Agua]]+sales2[[#This Row],[Electricidad]]+sales2[[#This Row],[Nomina]] -> 55000 | E41: =+VLOOKUP(sales2[[#This Row],[Fecha]],Opex!C:J,8,1) -> 55000 | F41: =+SUM(sales2[[#This Row],[Gas]:[Electricidad]]) -> 0 | K41: =+SUM(sales2[[#This Row],[Cajero]:[Domiciliario]]) -> 0 | L41: 0 | M41: 0 | N41: 0 | P41: 150 a Janet
B42: =+B41+1 -> 46107 | C42: =+TEXT(sales2[[#This Row],[Fecha]],"ddd") -> jue | D42: =+sales2[[#This Row],[Arriendo]]+sales2[[#This Row],[Gas]]+sales2[[#This Row],[Agua]]+sales2[[#This Row],[Electricidad]]+sales2[[#This Row],[Nomina]] -> 55000 | E42: =+VLOOKUP(sales2[[#This Row],[Fecha]],Opex!C:J,8,1) -> 55000 | F42: =+SUM(sales2[[#This Row],[Gas]:[Electricidad]]) -> 0 | K42: =+SUM(sales2[[#This Row],[Cajero]:[Domiciliario]]) -> 0 | L42: 0 | M42: 0 | N42: 0 | P42: le pago 100 al de la fama
B43: =+B42+1 -> 46108 | C43: =+TEXT(sales2[[#This Row],[Fecha]],"ddd") -> vie | D43: =+sales2[[#This Row],[Arriendo]]+sales2[[#This Row],[Gas]]+sales2[[#This Row],[Agua]]+sales2[[#This Row],[Electricidad]]+sales2[[#This Row],[Nomina]] -> 55000 | E43: =+VLOOKUP(sales2[[#This Row],[Fecha]],Opex!C:J,8,1) -> 55000 | F43: =+SUM(sales2[[#This Row],[Gas]:[Electricidad]]) -> 0 | K43: =+SUM(sales2[[#This Row],[Cajero]:[Domiciliario]]) -> 0 | L43: 0 | M43: 0 | N43: 0 | P43: 50,000 platano
B44: =+B43+1 -> 46109 | C44: =+TEXT(sales2[[#This Row],[Fecha]],"ddd") -> sáb | D44: =+sales2[[#This Row],[Arriendo]]+sales2[[#This Row],[Gas]]+sales2[[#This Row],[Agua]]+sales2[[#This Row],[Electricidad]]+sales2[[#This Row],[Nomina]] -> 55000 | E44: =+VLOOKUP(sales2[[#This Row],[Fecha]],Opex!C:J,8,1) -> 55000 | F44: =+SUM(sales2[[#This Row],[Gas]:[Electricidad]]) -> 0 | K44: =+SUM(sales2[[#This Row],[Cajero]:[Domiciliario]]) -> 0 | L44: 0 | M44: 0 | N44: 0
B45: =+B44+1 -> 46110 | C45: =+TEXT(sales2[[#This Row],[Fecha]],"ddd") -> dom | D45: =+sales2[[#This Row],[Arriendo]]+sales2[[#This Row],[Gas]]+sales2[[#This Row],[Agua]]+sales2[[#This Row],[Electricidad]]+sales2[[#This Row],[Nomina]] -> 55000 | E45: =+VLOOKUP(sales2[[#This Row],[Fecha]],Opex!C:J,8,1) -> 55000 | F45: =+SUM(sales2[[#This Row],[Gas]:[Electricidad]]) -> 0 | K45: =+SUM(sales2[[#This Row],[Cajero]:[Domiciliario]]) -> 0 | L45: 0 | M45: 0 | N45: 0
B46: =+B45+1 -> 46111 | C46: =+TEXT(sales2[[#This Row],[Fecha]],"ddd") -> lun | D46: =+sales2[[#This Row],[Arriendo]]+sales2[[#This Row],[Gas]]+sales2[[#This Row],[Agua]]+sales2[[#This Row],[Electricidad]]+sales2[[#This Row],[Nomina]] -> 55000 | E46: =+VLOOKUP(sales2[[#This Row],[Fecha]],Opex!C:J,8,1) -> 55000 | F46: =+SUM(sales2[[#This Row],[Gas]:[Electricidad]]) -> 0 | K46: =+SUM(sales2[[#This Row],[Cajero]:[Domiciliario]]) -> 0 | L46: 0 | M46: 0 | N46: 0 | P46: 50,000 platano
B47: =+B46+1 -> 46112 | C47: =+TEXT(sales2[[#This Row],[Fecha]],"ddd") -> mar | D47: =+sales2[[#This Row],[Arriendo]]+sales2[[#This Row],[Gas]]+sales2[[#This Row],[Agua]]+sales2[[#This Row],[Electricidad]]+sales2[[#This Row],[Nomina]] -> 55000 | E47: =+VLOOKUP(sales2[[#This Row],[Fecha]],Opex!C:J,8,1) -> 55000 | F47: =+SUM(sales2[[#This Row],[Gas]:[Electricidad]]) -> 0 | K47: =+SUM(sales2[[#This Row],[Cajero]:[Domiciliario]]) -> 0 | L47: 0 | M47: 0 | N47: 0
B48: =+B47+1 -> 46113 | C48: =+TEXT(sales2[[#This Row],[Fecha]],"ddd") -> mié | D48: =+sales2[[#This Row],[Arriendo]]+sales2[[#This Row],[Gas]]+sales2[[#This Row],[Agua]]+sales2[[#This Row],[Electricidad]]+sales2[[#This Row],[Nomina]] -> 55000 | E48: =+VLOOKUP(sales2[[#This Row],[Fecha]],Opex!C:J,8,1) -> 55000 | F48: =+SUM(sales2[[#This Row],[Gas]:[Electricidad]]) -> 0 | K48: =+SUM(sales2[[#This Row],[Cajero]:[Domiciliario]]) -> 0 | L48: 0 | M48: 0 | N48: 0 | P48: 3 almuerzo y petaco de cerveza
B49: =+B48+1 -> 46114 | C49: =+TEXT(sales2[[#This Row],[Fecha]],"ddd") -> jue | D49: =+sales2[[#This Row],[Arriendo]]+sales2[[#This Row],[Gas]]+sales2[[#This Row],[Agua]]+sales2[[#This Row],[Electricidad]]+sales2[[#This Row],[Nomina]] -> 55000 | E49: =+VLOOKUP(sales2[[#This Row],[Fecha]],Opex!C:J,8,1) -> 55000 | F49: =+SUM(sales2[[#This Row],[Gas]:[Electricidad]]) -> 0 | L49: 0 | M49: 0 | N49: 0 | Q49: vereda el verganzo | R49: sector, escuela, asadres
B50: =+B49+1 -> 46115 | C50: =+TEXT(sales2[[#This Row],[Fecha]],"ddd") -> vie | D50: =+sales2[[#This Row],[Arriendo]]+sales2[[#This Row],[Gas]]+sales2[[#This Row],[Agua]]+sales2[[#This Row],[Electricidad]]+sales2[[#This Row],[Nomina]] -> 55000 | E50: =+VLOOKUP(sales2[[#This Row],[Fecha]],Opex!C:J,8,1) -> 55000 | F50: =+SUM(sales2[[#This Row],[Gas]:[Electricidad]]) -> 0 | L50: 0 | M50: 0 | N50: 0
B51: =+B50+1 -> 46116 | C51: =+TEXT(sales2[[#This Row],[Fecha]],"ddd") -> sáb | D51: =+sales2[[#This Row],[Arriendo]]+sales2[[#This Row],[Gas]]+sales2[[#This Row],[Agua]]+sales2[[#This Row],[Electricidad]]+sales2[[#This Row],[Nomina]] -> 55000 | E51: =+VLOOKUP(sales2[[#This Row],[Fecha]],Opex!C:J,8,1) -> 55000 | F51: =+SUM(sales2[[#This Row],[Gas]:[Electricidad]]) -> 0 | L51: 0 | M51: 0 | N51: 0
B52: =+B51+1 -> 46117 | C52: =+TEXT(sales2[[#This Row],[Fecha]],"ddd") -> dom | D52: =+sales2[[#This Row],[Arriendo]]+sales2[[#This Row],[Gas]]+sales2[[#This Row],[Agua]]+sales2[[#This Row],[Electricidad]]+sales2[[#This Row],[Nomina]] -> 55000 | E52: =+VLOOKUP(sales2[[#This Row],[Fecha]],Opex!C:J,8,1) -> 55000 | F52: =+SUM(sales2[[#This Row],[Gas]:[Electricidad]]) -> 0 | L52: 0 | M52: 0 | N52: 0 | P52: 3000 | R52: Almierzo de $ 10,000
B53: =+B52+1 -> 46118 | C53: =+TEXT(sales2[[#This Row],[Fecha]],"ddd") -> lun | D53: =+sales2[[#This Row],[Arriendo]]+sales2[[#This Row],[Gas]]+sales2[[#This Row],[Agua]]+sales2[[#This Row],[Electricidad]]+sales2[[#This Row],[Nomina]] -> 55000 | E53: =+VLOOKUP(sales2[[#This Row],[Fecha]],Opex!C:J,8,1) -> 55000 | F53: =+SUM(sales2[[#This Row],[Gas]:[Electricidad]]) -> 0 | L53: 0 | M53: 0 | N53: 0 | P53: Pollo. $ 9000 | R53: Pollo. $ 20,000
B54: =+B53+1 -> 46119 | C54: =+TEXT(sales2[[#This Row],[Fecha]],"ddd") -> mar | D54: =+sales2[[#This Row],[Arriendo]]+sales2[[#This Row],[Gas]]+sales2[[#This Row],[Agua]]+sales2[[#This Row],[Electricidad]]+sales2[[#This Row],[Nomina]] -> 55000 | E54: =+VLOOKUP(sales2[[#This Row],[Fecha]],Opex!C:J,8,1) -> 55000 | F54: =+SUM(sales2[[#This Row],[Gas]:[Electricidad]]) -> 0 | L54: 0 | M54: 0 | N54: 0
B55: =+B54+1 -> 46120 | C55: =+TEXT(sales2[[#This Row],[Fecha]],"ddd") -> mié | D55: =+sales2[[#This Row],[Arriendo]]+sales2[[#This Row],[Gas]]+sales2[[#This Row],[Agua]]+sales2[[#This Row],[Electricidad]]+sales2[[#This Row],[Nomina]] -> 55000 | E55: =+VLOOKUP(sales2[[#This Row],[Fecha]],Opex!C:J,8,1) -> 55000 | F55: =+SUM(sales2[[#This Row],[Gas]:[Electricidad]]) -> 0 | L55: 0 | M55: 0 | N55: 0
B56: =+B55+1 -> 46121 | C56: =+TEXT(sales2[[#This Row],[Fecha]],"ddd") -> jue | D56: =+sales2[[#This Row],[Arriendo]]+sales2[[#This Row],[Gas]]+sales2[[#This Row],[Agua]]+sales2[[#This Row],[Electricidad]]+sales2[[#This Row],[Nomina]] -> 55000 | E56: =+VLOOKUP(sales2[[#This Row],[Fecha]],Opex!C:J,8,1) -> 55000 | F56: =+SUM(sales2[[#This Row],[Gas]:[Electricidad]]) -> 0 | L56: 0 | M56: 0 | N56: 0
B57: =+B56+1 -> 46122 | C57: =+TEXT(sales2[[#This Row],[Fecha]],"ddd") -> vie | D57: =+sales2[[#This Row],[Arriendo]]+sales2[[#This Row],[Gas]]+sales2[[#This Row],[Agua]]+sales2[[#This Row],[Electricidad]]+sales2[[#This Row],[Nomina]] -> 55000 | E57: =+VLOOKUP(sales2[[#This Row],[Fecha]],Opex!C:J,8,1) -> 55000 | F57: =+SUM(sales2[[#This Row],[Gas]:[Electricidad]]) -> 0 | L57: 0 | M57: 0 | N57: 0
B58: =+B57+1 -> 46123 | C58: =+TEXT(sales2[[#This Row],[Fecha]],"ddd") -> sáb | D58: =+sales2[[#This Row],[Arriendo]]+sales2[[#This Row],[Gas]]+sales2[[#This Row],[Agua]]+sales2[[#This Row],[Electricidad]]+sales2[[#This Row],[Nomina]] -> 55000 | E58: =+VLOOKUP(sales2[[#This Row],[Fecha]],Opex!C:J,8,1) -> 55000 | F58: =+SUM(sales2[[#This Row],[Gas]:[Electricidad]]) -> 0 | L58: 0 | M58: 0 | N58: 0
B59: =+B58+1 -> 46124 | C59: =+TEXT(sales2[[#This Row],[Fecha]],"ddd") -> dom | D59: =+sales2[[#This Row],[Arriendo]]+sales2[[#This Row],[Gas]]+sales2[[#This Row],[Agua]]+sales2[[#This Row],[Electricidad]]+sales2[[#This Row],[Nomina]] -> 55000 | E59: =+VLOOKUP(sales2[[#This Row],[Fecha]],Opex!C:J,8,1) -> 55000 | F59: =+SUM(sales2[[#This Row],[Gas]:[Electricidad]]) -> 0 | L59: 0 | M59: 0 | N59: 0
B60: =+B59+1 -> 46125 | C60: =+TEXT(sales2[[#This Row],[Fecha]],"ddd") -> lun | D60: =+sales2[[#This Row],[Arriendo]]+sales2[[#This Row],[Gas]]+sales2[[#This Row],[Agua]]+sales2[[#This Row],[Electricidad]]+sales2[[#This Row],[Nomina]] -> 55000 | E60: =+VLOOKUP(sales2[[#This Row],[Fecha]],Opex!C:J,8,1) -> 55000 | F60: =+SUM(sales2[[#This Row],[Gas]:[Electricidad]]) -> 0 | L60: 0 | M60: 0 | N60: 0
B61: =+B60+1 -> 46126 | C61: =+TEXT(sales2[[#This Row],[Fecha]],"ddd") -> mar | D61: =+sales2[[#This Row],[Arriendo]]+sales2[[#This Row],[Gas]]+sales2[[#This Row],[Agua]]+sales2[[#This Row],[Electricidad]]+sales2[[#This Row],[Nomina]] -> 55000 | E61: =+VLOOKUP(sales2[[#This Row],[Fecha]],Opex!C:J,8,1) -> 55000 | F61: =+SUM(sales2[[#This Row],[Gas]:[Electricidad]]) -> 0 | L61: 0 | M61: 0 | N61: 0
B62: =+B61+1 -> 46127 | C62: =+TEXT(sales2[[#This Row],[Fecha]],"ddd") -> mié | D62: =+sales2[[#This Row],[Arriendo]]+sales2[[#This Row],[Gas]]+sales2[[#This Row],[Agua]]+sales2[[#This Row],[Electricidad]]+sales2[[#This Row],[Nomina]] -> 56896.552 | E62: =+VLOOKUP(sales2[[#This Row],[Fecha]],Opex!C:J,8,1) -> 56896.552 | F62: =+SUM(sales2[[#This Row],[Gas]:[Electricidad]]) -> 0 | L62: 0 | M62: 0 | N62: 0
B63: =+B62+1 -> 46128 | C63: =+TEXT(sales2[[#This Row],[Fecha]],"ddd") -> jue | D63: =+sales2[[#This Row],[Arriendo]]+sales2[[#This Row],[Gas]]+sales2[[#This Row],[Agua]]+sales2[[#This Row],[Electricidad]]+sales2[[#This Row],[Nomina]] -> 56896.552 | E63: =+VLOOKUP(sales2[[#This Row],[Fecha]],Opex!C:J,8,1) -> 56896.552 | F63: =+SUM(sales2[[#This Row],[Gas]:[Electricidad]]) -> 0 | L63: 0 | M63: 0 | N63: 0
B64: =+B63+1 -> 46129 | C64: =+TEXT(sales2[[#This Row],[Fecha]],"ddd") -> vie | D64: =+sales2[[#This Row],[Arriendo]]+sales2[[#This Row],[Gas]]+sales2[[#This Row],[Agua]]+sales2[[#This Row],[Electricidad]]+sales2[[#This Row],[Nomina]] -> 56896.552 | E64: =+VLOOKUP(sales2[[#This Row],[Fecha]],Opex!C:J,8,1) -> 56896.552 | F64: =+SUM(sales2[[#This Row],[Gas]:[Electricidad]]) -> 0 | L64: 0 | M64: 0 | N64: 0
B65: =+B64+1 -> 46130 | C65: =+TEXT(sales2[[#This Row],[Fecha]],"ddd") -> sáb | D65: =+sales2[[#This Row],[Arriendo]]+sales2[[#This Row],[Gas]]+sales2[[#This Row],[Agua]]+sales2[[#This Row],[Electricidad]]+sales2[[#This Row],[Nomina]] -> 56896.552 | E65: =+VLOOKUP(sales2[[#This Row],[Fecha]],Opex!C:J,8,1) -> 56896.552 | F65: =+SUM(sales2[[#This Row],[Gas]:[Electricidad]]) -> 0 | L65: 0 | M65: 0 | N65: 0
... B94: =+B93+1 -> 46159 | C94: =+TEXT(sales2[[#This Row],[Fecha]],"ddd") -> dom | D94: =+sales2[[#This Row],[Arriendo]]+sales2[[#This Row],[Gas]]+sales2[[#This Row],[Agua]]+sales2[[#This Row],[Electricidad]]+sales2[[#This Row],[Nomina]] -> 55000 | E94: =+VLOOKUP(sales2[[#This Row],[Fecha]],Opex!C:J,8,1) -> 55000 | F94: =+SUM(sales2[[#This Row],[Gas]:[Electricidad]]) -> 0 | L94: 0 | M94: 0 | N94: 0
B95: =+B94+1 -> 46160 | C95: =+TEXT(sales2[[#This Row],[Fecha]],"ddd") -> lun | D95: =+sales2[[#This Row],[Arriendo]]+sales2[[#This Row],[Gas]]+sales2[[#This Row],[Agua]]+sales2[[#This Row],[Electricidad]]+sales2[[#This Row],[Nomina]] -> 55000 | E95: =+VLOOKUP(sales2[[#This Row],[Fecha]],Opex!C:J,8,1) -> 55000 | F95: =+SUM(sales2[[#This Row],[Gas]:[Electricidad]]) -> 0 | L95: 0 | M95: 0 | N95: 0 | O95: ='Cuentas x Pagar'!$L$26 -> 0
B96: =+B95+1 -> 46161 | C96: =+TEXT(sales2[[#This Row],[Fecha]],"ddd") -> mar | D96: =+sales2[[#This Row],[Arriendo]]+sales2[[#This Row],[Gas]]+sales2[[#This Row],[Agua]]+sales2[[#This Row],[Electricidad]]+sales2[[#This Row],[Nomina]] -> 55000 | E96: =+VLOOKUP(sales2[[#This Row],[Fecha]],Opex!C:J,8,1) -> 55000 | F96: =+SUM(sales2[[#This Row],[Gas]:[Electricidad]]) -> 0 | L96: 0 | M96: 0 | N96: 0
B97: =+B96+1 -> 46162 | C97: =+TEXT(sales2[[#This Row],[Fecha]],"ddd") -> mié | D97: =+sales2[[#This Row],[Arriendo]]+sales2[[#This Row],[Gas]]+sales2[[#This Row],[Agua]]+sales2[[#This Row],[Electricidad]]+sales2[[#This Row],[Nomina]] -> 55000 | E97: =+VLOOKUP(sales2[[#This Row],[Fecha]],Opex!C:J,8,1) -> 55000 | F97: =+SUM(sales2[[#This Row],[Gas]:[Electricidad]]) -> 0 | L97: 0 | M97: 0 | N97: 0
B98: =+B97+1 -> 46163 | C98: =+TEXT(sales2[[#This Row],[Fecha]],"ddd") -> jue | D98: =+sales2[[#This Row],[Arriendo]]+sales2[[#This Row],[Gas]]+sales2[[#This Row],[Agua]]+sales2[[#This Row],[Electricidad]]+sales2[[#This Row],[Nomina]] -> 55000 | E98: =+VLOOKUP(sales2[[#This Row],[Fecha]],Opex!C:J,8,1) -> 55000 | F98: =+SUM(sales2[[#This Row],[Gas]:[Electricidad]]) -> 0 | L98: 0 | M98: 0 | N98: 0
B99: =+B98+1 -> 46164 | C99: =+TEXT(sales2[[#This Row],[Fecha]],"ddd") -> vie | D99: =+sales2[[#This Row],[Arriendo]]+sales2[[#This Row],[Gas]]+sales2[[#This Row],[Agua]]+sales2[[#This Row],[Electricidad]]+sales2[[#This Row],[Nomina]] -> 55000 | E99: =+VLOOKUP(sales2[[#This Row],[Fecha]],Opex!C:J,8,1) -> 55000 | F99: =+SUM(sales2[[#This Row],[Gas]:[Electricidad]]) -> 0 | L99: 0 | M99: 0 | N99: 0
B100: =+B99+1 -> 46165 | C100: =+TEXT(sales2[[#This Row],[Fecha]],"ddd") -> sáb | D100: =+sales2[[#This Row],[Arriendo]]+sales2[[#This Row],[Gas]]+sales2[[#This Row],[Agua]]+sales2[[#This Row],[Electricidad]]+sales2[[#This Row],[Nomina]] -> 55000 | E100: =+VLOOKUP(sales2[[#This Row],[Fecha]],Opex!C:J,8,1) -> 55000 | F100: =+SUM(sales2[[#This Row],[Gas]:[Electricidad]]) -> 0 | L100: 0 | M100: 0 | N100: 0
B101: =+B100+1 -> 46166 | C101: =+TEXT(sales2[[#This Row],[Fecha]],"ddd") -> dom | D101: =+sales2[[#This Row],[Arriendo]]+sales2[[#This Row],[Gas]]+sales2[[#This Row],[Agua]]+sales2[[#This Row],[Electricidad]]+sales2[[#This Row],[Nomina]] -> 55000 | E101: =+VLOOKUP(sales2[[#This Row],[Fecha]],Opex!C:J,8,1) -> 55000 | F101: =+SUM(sales2[[#This Row],[Gas]:[Electricidad]]) -> 0 | L101: 0 | M101: 0 | N101: 0
B102: =+B101+1 -> 46167 | C102: =+TEXT(sales2[[#This Row],[Fecha]],"ddd") -> lun | D102: =+sales2[[#This Row],[Arriendo]]+sales2[[#This Row],[Gas]]+sales2[[#This Row],[Agua]]+sales2[[#This Row],[Electricidad]]+sales2[[#This Row],[Nomina]] -> 55000 | E102: =+VLOOKUP(sales2[[#This Row],[Fecha]],Opex!C:J,8,1) -> 55000 | F102: =+SUM(sales2[[#This Row],[Gas]:[Electricidad]]) -> 0 | L102: 0 | M102: 0 | N102: 0
B103: =+B102+1 -> 46168 | C103: =+TEXT(sales2[[#This Row],[Fecha]],"ddd") -> mar | D103: =+sales2[[#This Row],[Arriendo]]+sales2[[#This Row],[Gas]]+sales2[[#This Row],[Agua]]+sales2[[#This Row],[Electricidad]]+sales2[[#This Row],[Nomina]] -> 55000 | E103: =+VLOOKUP(sales2[[#This Row],[Fecha]],Opex!C:J,8,1) -> 55000 | F103: =+SUM(sales2[[#This Row],[Gas]:[Electricidad]]) -> 0 | L103: 0 | M103: 0 | N103: 0
B104: =+B103+1 -> 46169 | C104: =+TEXT(sales2[[#This Row],[Fecha]],"ddd") -> mié | D104: =+sales2[[#This Row],[Arriendo]]+sales2[[#This Row],[Gas]]+sales2[[#This Row],[Agua]]+sales2[[#This Row],[Electricidad]]+sales2[[#This Row],[Nomina]] -> 55000 | E104: =+VLOOKUP(sales2[[#This Row],[Fecha]],Opex!C:J,8,1) -> 55000 | F104: =+SUM(sales2[[#This Row],[Gas]:[Electricidad]]) -> 0 | L104: 0 | M104: 0 | N104: 0
B105: =+B104+1 -> 46170 | C105: =+TEXT(sales2[[#This Row],[Fecha]],"ddd") -> jue | D105: =+sales2[[#This Row],[Arriendo]]+sales2[[#This Row],[Gas]]+sales2[[#This Row],[Agua]]+sales2[[#This Row],[Electricidad]]+sales2[[#This Row],[Nomina]] -> 55000 | E105: =+VLOOKUP(sales2[[#This Row],[Fecha]],Opex!C:J,8,1) -> 55000 | F105: =+SUM(sales2[[#This Row],[Gas]:[Electricidad]]) -> 0 | L105: 0 | M105: 0 | N105: 0
B106: =+B105+1 -> 46171 | C106: =+TEXT(sales2[[#This Row],[Fecha]],"ddd") -> vie | D106: =+sales2[[#This Row],[Arriendo]]+sales2[[#This Row],[Gas]]+sales2[[#This Row],[Agua]]+sales2[[#This Row],[Electricidad]]+sales2[[#This Row],[Nomina]] -> 55000 | E106: =+VLOOKUP(sales2[[#This Row],[Fecha]],Opex!C:J,8,1) -> 55000 | F106: =+SUM(sales2[[#This Row],[Gas]:[Electricidad]]) -> 0 | L106: 0 | M106: 0 | N106: 0
B107: =+B106+1 -> 46172 | C107: =+TEXT(sales2[[#This Row],[Fecha]],"ddd") -> sáb | D107: =+sales2[[#This Row],[Arriendo]]+sales2[[#This Row],[Gas]]+sales2[[#This Row],[Agua]]+sales2[[#This Row],[Electricidad]]+sales2[[#This Row],[Nomina]] -> 55000 | E107: =+VLOOKUP(sales2[[#This Row],[Fecha]],Opex!C:J,8,1) -> 55000 | F107: =+SUM(sales2[[#This Row],[Gas]:[Electricidad]]) -> 0 | L107: 0 | M107: 0 | N107: 0
... B122: =+B121+1 -> 46187 | C122: =+TEXT(sales2[[#This Row],[Fecha]],"ddd") -> dom | D122: =+sales2[[#This Row],[Arriendo]]+sales2[[#This Row],[Gas]]+sales2[[#This Row],[Agua]]+sales2[[#This Row],[Electricidad]]+sales2[[#This Row],[Nomina]] -> 55000 | E122: =+VLOOKUP(sales2[[#This Row],[Fecha]],Opex!C:J,8,1) -> 55000 | F122: =+SUM(sales2[[#This Row],[Gas]:[Electricidad]]) -> 0 | L122: 0 | M122: 0 | N122: 0

Sheet bolsas
E1: 320 | F1: apartamentos | G1: octubre
C2: 6300
C3: 7100
C4: =+SUM(C2:C3) -> 13400
C5: 15240 | D5: bolsas
C6: =+C4+C5 -> 28640

Sheet Opex
B1: Tipo | C1: Fecha | D1: fecha_fin | E1: Mes | F1: Cuentas x Pagar | G1: Día C x P | H1: Arriendo | I1: No. Días Arriendo | J1: Día Arriendo | K1: Gas | L1: No. Días Gas | M1: Consumo (m3) | N1: Costo prom. Gas | O1: Día Gas | P1: Agua | Q1: Dìa Agua | R1: Energia | S1: Financiació Energia | T1: No. Días Energia | U1: Consumo (KhW | V1: Costo prom. Energia | W1: Fecha corte enega | X1: Día Energia
B2: Histórico | C2: 46068 | D2: 46095 | E2: =+TEXT(C2,"mmmm") -> febrero | G2: =+Opex[[#This Row],[Cuentas x Pagar]]/31 -> 0 | H2: 0 | I2: =+Opex[[#This Row],[fecha_fin]]-Opex[[#This Row],[Fecha]] -> 27 | J2: =IFERROR(Opex[[#This Row],[Arriendo]]/Opex[[#This Row],[No. Días Arriendo]],0) -> 0 | K2: 430 | L2: 0 | M2: 0 | N2: =IFERROR(Opex[[#This Row],[Gas]]/Opex[[#This Row],[Consumo (m3)]],0) -> 0 | O2: =IFERROR(Opex[[#This Row],[Gas]]/Opex[[#This Row],[No. Días Arriendo]],0) -> 15.925926 | Q2: =IFERROR(Opex[[#This Row],[Agua]]/Opex[[#This Row],[No. Días Arriendo]],0) -> 0 | T2: =+AA2 -> 0 | V2: =IFERROR(Opex[[#This Row],[Energia]]/Opex[[#This Row],[Consumo (KhW]],0) -> 0 | X2: =IFERROR(Opex[[#This Row],[Energia]]/Opex[[#This Row],[No. Días Arriendo]],0) -> 0
B3: Forecast | C3: =+D2+1 -> 46096 | D3: 46126 | E3: =+TEXT(C3,"mmmm") -> marzo | G3: =+Opex[[#This Row],[Cuentas x Pagar]]/31 -> 0 | H3: 1650000 | I3: =+Opex[[#This Row],[fecha_fin]]-Opex[[#This Row],[Fecha]] -> 30 | J3: =IFERROR(Opex[[#This Row],[Arriendo]]/Opex[[#This Row],[No. Días Arriendo]],0) -> 55000 | K3: ='[3]Análisis Gas'!$I$22 -> 247319 | L3: =+#REF! -> #REF! | M3: =+AVERAGE(#REF!/#REF!,#REF!/#REF!,#REF!/#REF!)*Opex[[#This Row],[No. Días Gas]] -> #REF! | N3: =+AVERAGE(#REF!) -> #REF! | O3: =IFERROR(Opex[[#This Row],[Gas]]/Opex[[#This Row],[No. Días Arriendo]],0) -> 8243.9667 | P3: 120000 | Q3: =IFERROR(Opex[[#This Row],[Agua]]/Opex[[#This Row],[No. Días Arriendo]],0) -> 4000 | R3: ='[3]Análisis Energia'!$I$24 -> 319050 | S3: ='[4]Radicado Energia'!$C33 -> 264247 | T3: =+#REF! -> #REF! | U3: =+AVERAGE(#REF!/#REF!,#REF!/#REF!) -> #REF! | V3: =+AVERAGE(#REF!) -> #REF! | W3: Nd | X3: =IFERROR(Opex[[#This Row],[Energia]]/Opex[[#This Row],[No. Días Arriendo]],0) -> 10635
B4: Forecast | C4: =+D3+1 -> 46127 | D4: 46156 | E4: =+TEXT(C4,"mmmm") -> abril | G4: =+Opex[[#This Row],[Cuentas x Pagar]]/31 -> 0 | H4: 1650000 | I4: =+Opex[[#This Row],[fecha_fin]]-Opex[[#This Row],[Fecha]] -> 29 | J4: =IFERROR(Opex[[#This Row],[Arriendo]]/Opex[[#This Row],[No. Días Arriendo]],0) -> 56896.552 | K4: ='[3]Análisis Gas'!$I$22 -> 247319 | L4: =+I3 -> 30 | M4: =+AVERAGE(#REF!/#REF!,#REF!/#REF!,M3/L3)*Opex[[#This Row],[No. Días Gas]] -> #REF! | N4: =+AVERAGE(N3:N3) -> #REF! | O4: =IFERROR(Opex[[#This Row],[Gas]]/Opex[[#This Row],[No. Días Arriendo]],0) -> 8528.2414 | P4: 120000 | Q4: =IFERROR(Opex[[#This Row],[Agua]]/Opex[[#This Row],[No. Días Arriendo]],0) -> 4137.931 | R4: =+AVERAGE(R3:R3) -> 319050 | S4: ='[4]Radicado Energia'!$C34 -> 264247 | T4: =+#REF! -> #REF! | U4: =+AVERAGE(#REF!/#REF!,#REF!/#REF!,#REF!/V3) -> #REF! | V4: =+AVERAGE(V3:V3) -> #REF! | W4: Nd | X4: =IFERROR(Opex[[#This Row],[Energia]]/Opex[[#This Row],[No. Días Arriendo]],0) -> 11001.724
B5: Forecast | C5: =+D4+1 -> 46157 | D5: 46187 | E5: =+TEXT(C5,"mmmm") -> mayo | G5: =+Opex[[#This Row],[Cuentas x Pagar]]/31 -> 0 | H5: 1650000 | I5: =+Opex[[#This Row],[fecha_fin]]-Opex[[#This Row],[Fecha]] -> 30 | J5: =IFERROR(Opex[[#This Row],[Arriendo]]/Opex[[#This Row],[No. Días Arriendo]],0) -> 55000 | K5: ='[3]Análisis Gas'!$I$22 -> 247319 | L5: =+I4 -> 29 | M5: =+AVERAGE(#REF!/#REF!,M3/L3,M4/L4)*Opex[[#This Row],[No. Días Gas]] -> #REF! | N5: =+AVERAGE(N3:N4) -> #REF! | O5: =IFERROR(Opex[[#This Row],[Gas]]/Opex[[#This Row],[No. Días Arriendo]],0) -> 8243.9667 | P5: 120000 | Q5: =IFERROR(Opex[[#This Row],[Agua]]/Opex[[#This Row],[No. Días Arriendo]],0) -> 4000 | R5: =+AVERAGE(R3:R4) -> 319050 | S5: ='[4]Radicado Energia'!$C35 -> 264247 | T5: =+#REF! -> #REF! | U5: =+AVERAGE(#REF!/#REF!,#REF!/V3,#REF!/V4) -> #REF! | V5: =+AVERAGE(V3:V4) -> #REF! | W5: Nd | X5: =IFERROR(Opex[[#This Row],[Energia]]/Opex[[#This Row],[No. Días Arriendo]],0) -> 10635
B6: Forecast | C6: =+D5+1 -> 46188 | D6: 46217 | E6: =+TEXT(C6,"mmmm") -> junio | G6: =+Opex[[#This Row],[Cuentas x Pagar]]/31 -> 0 | H6: 1650000 | I6: =+Opex[[#This Row],[fecha_fin]]-Opex[[#This Row],[Fecha]] -> 29 | J6: =IFERROR(Opex[[#This Row],[Arriendo]]/Opex[[#This Row],[No. Días Arriendo]],0) -> 56896.552 | K6: ='[3]Análisis Gas'!$I$22 -> 247319 | L6: =+I5 -> 30 | M6: =+AVERAGE(M3/L3,M4/L4,M5/L5)*Opex[[#This Row],[No. Días Gas]] -> #REF! | N6: =+AVERAGE(N3:N5) -> #REF! | O6: =IFERROR(Opex[[#This Row],[Gas]]/Opex[[#This Row],[No. Días Arriendo]],0) -> 8528.2414 | P6: 120000 | Q6: =IFERROR(Opex[[#This Row],[Agua]]/Opex[[#This Row],[No. Días Arriendo]],0) -> 4137.931 | R6: =+AVERAGE(R4:R5) -> 319050 | S6: ='[4]Radicado Energia'!$C36 -> 264247 | T6: =+#REF! -> #REF! | U6: =+AVERAGE(#REF!/V3,#REF!/V4,#REF!/V5) -> #REF! | V6: =+AVERAGE(V3:V5) -> #REF! | W6: Nd | X6: =IFERROR(Opex[[#This Row],[Energia]]/Opex[[#This Row],[No. Días Arriendo]],0) -> 11001.724
B7: Forecast | C7: =+D6+1 -> 46218 | D7: 46248 | E7: =+TEXT(C7,"mmmm") -> julio | G7: =+Opex[[#This Row],[Cuentas x Pagar]]/31 -> 0 | H7: 1650000 | I7: =+Opex[[#This Row],[fecha_fin]]-Opex[[#This Row],[Fecha]] -> 30 | J7: =IFERROR(Opex[[#This Row],[Arriendo]]/Opex[[#This Row],[No. Días Arriendo]],0) -> 55000 | K7: ='[3]Análisis Gas'!$I$22 -> 247319 | L7: =+I6 -> 29 | M7: =+AVERAGE(M4/L4,M5/L5,M6/L6)*Opex[[#This Row],[No. Días Gas]] -> #REF! | N7: =+AVERAGE(N4:N6) -> #REF! | O7: =IFERROR(Opex[[#This Row],[Gas]]/Opex[[#This Row],[No. Días Arriendo]],0) -> 8243.9667 | P7: 120000 | Q7: =IFERROR(Opex[[#This Row],[Agua]]/Opex[[#This Row],[No. Días Arriendo]],0) -> 4000 | R7: =+AVERAGE(R5:R6) -> 319050 | S7: ='[4]Radicado Energia'!$C37 -> 0 | T7: =+#REF! -> #REF! | U7: =+AVERAGE(#REF!/V4,#REF!/V5,#REF!/V6) -> #REF! | V7: =+AVERAGE(V4:V6) -> #REF! | W7: Nd | X7: =IFERROR(Opex[[#This Row],[Energia]]/Opex[[#This Row],[No. Días Arriendo]],0) -> 10635
B8: Forecast | C8: =+D7+1 -> 46249 | D8: 46279 | E8: =+TEXT(C8,"mmmm") -> agosto | G8: =+Opex[[#This Row],[Cuentas x Pagar]]/31 -> 0 | H8: 1650000 | I8: =+Opex[[#This Row],[fecha_fin]]-Opex[[#This Row],[Fecha]] -> 30 | J8: =IFERROR(Opex[[#This Row],[Arriendo]]/Opex[[#This Row],[No. Días Arriendo]],0) -> 55000 | K8: ='[3]Análisis Gas'!$I$22 -> 247319 | L8: =+I7 -> 30 | M8: =+AVERAGE(M5/L5,M6/L6,M7/L7)*Opex[[#This Row],[No. Días Gas]] -> #REF! | N8: =+AVERAGE(N5:N7) -> #REF! | O8: =IFERROR(Opex[[#This Row],[Gas]]/Opex[[#This Row],[No. Días Arriendo]],0) -> 8243.9667 | P8: 120000 | Q8: =IFERROR(Opex[[#This Row],[Agua]]/Opex[[#This Row],[No. Días Arriendo]],0) -> 4000 | R8: =+AVERAGE(R6:R7) -> 319050 | S8: ='[4]Radicado Energia'!$C38 -> 0 | T8: =+#REF! -> #REF! | U8: =+AVERAGE(#REF!/V5,#REF!/V6,#REF!/V7) -> #REF! | V8: =+AVERAGE(V5:V7) -> #REF! | W8: Nd | X8: =IFERROR(Opex[[#This Row],[Energia]]/Opex[[#This Row],[No. Días Arriendo]],0) -> 10635
B9: Forecast | C9: =+D8+1 -> 46280 | D9: 46309 | E9: =+TEXT(C9,"mmmm") -> septiembre | G9: =+Opex[[#This Row],[Cuentas x Pagar]]/31 -> 0 | H9: 1650000 | I9: =+Opex[[#This Row],[fecha_fin]]-Opex[[#This Row],[Fecha]] -> 29 | J9: =IFERROR(Opex[[#This Row],[Arriendo]]/Opex[[#This Row],[No. Días Arriendo]],0) -> 56896.552 | K9: ='[3]Análisis Gas'!$I$22 -> 247319 | L9: =+I8 -> 30 | M9: =+AVERAGE(M6/L6,M7/L7,M8/L8)*Opex[[#This Row],[No. Días Gas]] -> #REF! | N9: =+AVERAGE(N6:N8) -> #REF! | O9: =IFERROR(Opex[[#This Row],[Gas]]/Opex[[#This Row],[No. Días Arriendo]],0) -> 8528.2414 | P9: 120000 | Q9: =IFERROR(Opex[[#This Row],[Agua]]/Opex[[#This Row],[No. Días Arriendo]],0) -> 4137.931 | R9: =+AVERAGE(R7:R8) -> 319050 | S9: ='[4]Radicado Energia'!$C39 -> 0 | T9: =+#REF! -> #REF! | U9: =+AVERAGE(#REF!/V6,#REF!/V7,#REF!/V8) -> #REF! | V9: =+AVERAGE(V6:V8) -> #REF! | W9: Nd | X9: =IFERROR(Opex[[#This Row],[Energia]]/Opex[[#This Row],[No. Días Arriendo]],0) -> 11001.724
B10: Forecast | C10: =+D9+1 -> 46310 | D10: 46340 | E10: =+TEXT(C10,"mmmm") -> octubre | G10: =+Opex[[#This Row],[Cuentas x Pagar]]/31 -> 0 | H10: 1650000 | I10: =+Opex[[#This Row],[fecha_fin]]-Opex[[#This Row],[Fecha]] -> 30 | J10: =IFERROR(Opex[[#This Row],[Arriendo]]/Opex[[#This Row],[No. Días Arriendo]],0) -> 55000 | K10: ='[3]Análisis Gas'!$I$22 -> 247319 | L10: =+I9 -> 29 | M10: =+AVERAGE(M7/L7,M8/L8,M9/L9)*Opex[[#This Row],[No. Días Gas]] -> #REF! | N10: =+AVERAGE(N7:N9) -> #REF! | O10: =IFERROR(Opex[[#This Row],[Gas]]/Opex[[#This Row],[No. Días Arriendo]],0) -> 8243.9667 | P10: 120000 | Q10: =IFERROR(Opex[[#This Row],[Agua]]/Opex[[#This Row],[No. Días Arriendo]],0) -> 4000 | R10: =+AVERAGE(R8:R9) -> 319050 | S10: ='[4]Radicado Energia'!$C40 -> 0 | T10: =+#REF! -> #REF! | U10: =+AVERAGE(#REF!/V7,#REF!/V8,#REF!/V9) -> #REF! | V10: =+AVERAGE(V7:V9) -> #REF! | W10: Nd | X10: =IFERROR(Opex[[#This Row],[Energia]]/Opex[[#This Row],[No. Días Arriendo]],0) -> 10635
B11: Forecast | C11: =+D10+1 -> 46341 | D11: 46370 | E11: =+TEXT(C11,"mmmm") -> noviembre | G11: =+Opex[[#This Row],[Cuentas x Pagar]]/31 -> 0 | H11: 1650000 | I11: =+Opex[[#This Row],[fecha_fin]]-Opex[[#This Row],[Fecha]] -> 29 | J11: =IFERROR(Opex[[#This Row],[Arriendo]]/Opex[[#This Row],[No. Días Arriendo]],0) -> 56896.552 | K11: ='[3]Análisis Gas'!$I$22 -> 247319 | L11: =+I10 -> 30 | M11: =+AVERAGE(M8/L8,M9/L9,M10/L10)*Opex[[#This Row],[No. Días Gas]] -> #REF! | N11: =+AVERAGE(N8:N10) -> #REF! | O11: =IFERROR(Opex[[#This Row],[Gas]]/Opex[[#This Row],[No. Días Arriendo]],0) -> 8528.2414 | P11: 120000 | Q11: =IFERROR(Opex[[#This Row],[Agua]]/Opex[[#This Row],[No. Días Arriendo]],0) -> 4137.931 | R11: =+AVERAGE(R9:R10) -> 319050 | S11: ='[4]Radicado Energia'!$C41 -> 0 | T11: =+#REF! -> #REF! | U11: =+AVERAGE(#REF!/V8,#REF!/V9,#REF!/V10) -> #REF! | V11: =+AVERAGE(V8:V10) -> #REF! | W11: Nd | X11: =IFERROR(Opex[[#This Row],[Energia]]/Opex[[#This Row],[No. Días Arriendo]],0) -> 11001.724
B12: Forecast | C12: =+D11+1 -> 46371 | D12: 46401 | E12: =+TEXT(C12,"mmmm") -> diciembre | G12: =+Opex[[#This Row],[Cuentas x Pagar]]/31 -> 0 | H12: 1650000 | I12: =+Opex[[#This Row],[fecha_fin]]-Opex[[#This Row],[Fecha]] -> 30 | J12: =IFERROR(Opex[[#This Row],[Arriendo]]/Opex[[#This Row],[No. Días Arriendo]],0) -> 55000 | K12: ='[3]Análisis Gas'!$I$22 -> 247319 | L12: =+I11 -> 29 | M12: =+AVERAGE(M9/L9,M10/L10,M11/L11)*Opex[[#This Row],[No. Días Gas]] -> #REF! | N12: =+AVERAGE(N9:N11) -> #REF! | O12: =IFERROR(Opex[[#This Row],[Gas]]/Opex[[#This Row],[No. Días Arriendo]],0) -> 8243.9667 | P12: 120000 | Q12: =IFERROR(Opex[[#This Row],[Agua]]/Opex[[#This Row],[No. Días Arriendo]],0) -> 4000 | R12: =+AVERAGE(R10:R11) -> 319050 | S12: ='[4]Radicado Energia'!$C42 -> 0 | T12: =+#REF! -> #REF! | U12: =+AVERAGE(#REF!/V9,#REF!/V10,#REF!/V11) -> #REF! | V12: =+AVERAGE(V9:V11) -> #REF! | W12: Nd | X12: =IFERROR(Opex[[#This Row],[Energia]]/Opex[[#This Row],[No. Días Arriendo]],0) -> 10635
B13: Forecast | C13: =+D12+1 -> 46402 | D13: 46432 | E13: =+TEXT(C13,"mmmm") -> enero | G13: =+Opex[[#This Row],[Cuentas x Pagar]]/31 -> 0 | H13: 1650000 | I13: =+Opex[[#This Row],[fecha_fin]]-Opex[[#This Row],[Fecha]] -> 30 | J13: =IFERROR(Opex[[#This Row],[Arriendo]]/Opex[[#This Row],[No. Días Arriendo]],0) -> 55000 | K13: ='[3]Análisis Gas'!$I$22 -> 247319 | L13: =+I12 -> 30 | M13: =+AVERAGE(M10/L10,M11/L11,M12/L12)*Opex[[#This Row],[No. Días Gas]] -> #REF! | N13: =+AVERAGE(N10:N12) -> #REF! | O13: =IFERROR(Opex[[#This Row],[Gas]]/Opex[[#This Row],[No. Días Arriendo]],0) -> 8243.9667 | P13: 120000 | Q13: =IFERROR(Opex[[#This Row],[Agua]]/Opex[[#This Row],[No. Días Arriendo]],0) -> 4000 | R13: =+AVERAGE(R11:R12) -> 319050 | S13: ='[4]Radicado Energia'!$C43 -> 0 | T13: =+#REF! -> #REF! | U13: =+AVERAGE(#REF!/V10,#REF!/V11,#REF!/V12) -> #REF! | V13: =+AVERAGE(V10:V12) -> #REF! | W13: Nd | X13: =IFERROR(Opex[[#This Row],[Energia]]/Opex[[#This Row],[No. Días Arriendo]],0) -> 10635

Sheet Hoja3
A1: fecha_inicio | B1: fecha_fin | C1: tipo | E1: fecha
A2: 46068 | B2: 46095 | C2: uno | E2: 46095 | F2: =VLOOKUP(E2,A:C,3,TRUE) -> uno
A3: =+B2+1 -> 46096 | B3: 46126 | C3: do

Sheet Inicio
AB1: 0

Sheet Activos
B4: Tipo de obligación | C4: Proveedor | D4: Nombre proveedor | E4: Valor | F4: Plan B | H4: Tipo de gasto | I4: Valor | K4: Activo | L4: Patrimonio | M4: =+M5+M6 -> 18150000 | N4: =+M4/$K$5 -> 0.61570257
B5: Pasivo de corto plazo | C5: FINANCIERO | D5: Gota x Gota | E5: 350000 | F5: 0 | H5: Mes de Arriendo Marzo | I5: 1000000 | K5: =+M4+M7 -> 29478519 | L5: Planta y Equipo | M5: =+Planta_y_Equipo[[#Totals],[Valor]] -> 16020000 | N5: =+M5/$M$4 -> 0.88264463
B6: Pasivo de corto plazo | C6: ARRIENDO | D6: Arredatario | E6: 0 | F6: 0 | H6: Arriendo Apto. Marzo | I6: =550000/2 -> 275000 | L6: Inventario (Stock) | M6: =+Stock_Actual[[#Totals],[Valor]] -> 2130000 | N6: =+M6/$M$4 -> 0.11735537
B7: Pasivo de corto plazo | C7: Carne de cerdo | D7: Diego | E7: 1088000 | F7: 0 | H7: Acarreo | I7: 200000 | L7: Pasivo Total | M7: =+M8+M9 -> 11328519 | N7: =+M7/$K$5 -> 0.38429743 | O7: =+M7/M4 -> 0.62416083 | P7: =+M4-M7 -> 6821481
B8: Pasivo de corto plazo | C8: Carne de res | D8: Vecino | E8: 380000 | F8: 0 | H8: Publidad tarjeteria | I8: 100000 | L8: Pasivo de corto plazo | M8: =+SUMIF(B5:B23,L8,E5:E23) -> 4728920 | N8: =+M8/$M$7 -> 0.41743497
B9: Pasivo de corto plazo | C9: Carne de Pollo | D9: Nd | E9: 750000 | F9: 0 | H9: Total | I9: =SUBTOTAL(109,Gastos_entrada[Valor]) -> 1575000 | L9: Pasivo de largo plazo | M9: =+SUMIF(B5:B23,L9,E5:E23) -> 6599599 | N9: =+M9/$M$7 -> 0.58256503
B10: Pasivo de corto plazo | C10: NOMINA | D10: Nomina | E10: 150000 | F10: 0
B11: Pasivo de corto plazo | C11: PUBLICIDAD | D11: Nd | E11: 400000 | F11: =+E11 -> 400000 | M11: Ideal | N11: Actual
B12: Pasivo de corto plazo | C12: Pintura, local | D12: Nd | E12: 370000 | F12: 0 | L12: Nivel de Endeudamiento (NE) | M12: =+M15/K5 -> 0.15604583 | N12: =+M7/K5 -> 0.38429743 | O12: Nivel de endeudamiento crítico
B13: Pasivo de corto plazo | C13: Vitrina, ollas | D13: Vitrina, ollas | E13: 180000 | F13: 0 | L13: Autonomía | M13: =M15/M4 -> 0.25344353 | N13: =+M7/M4 -> 0.62416083 | O13: El 70% del patrimonio esta comprometido con deudas
B14: Pasivo de corto plazo | C14: CODENSA | D14: enel - 6451508-5 | E14: 1060920 | F14: =+E14 -> 1060920
B15: Pasivo de corto plazo | C15: Arriendo Apto. | D15: Sandra | E15: 0 | F15: =+E15 -> 0 | L15: Meta ideal deuda | M15: =$I$54 -> 4600000
B16: Pasivo de corto plazo | C16: Contingencia: Gas | D16: Ladron de Gas | E16: 0 | F16: 0 | L16: Meta a Pagar | M16: =+M7-M15 -> 6728519
B17: Pasivo de corto plazo | C17: Contingencia: Licuadora | D17: Licuadora | E17: 0 | F17: 0
B18: Pasivo de largo plazo | C18: FINANCIERO | D18: Saul | E18: 3000000 | F18: 0
B19: Pasivo de largo plazo | C19: Carne de cerdo | D19: Martin | E19: 300000 | F19: 0
B20: Pasivo de largo plazo | C20: Carne de cerdo | D20: Sarmiento | E20: 350000 | F20: 0
B21: Pasivo de largo plazo | C21: Carne de res | D21: Leornardo | E21: 1350000 | F21: 100000
B22: Pasivo de largo plazo | C22: Menudo y prestamo | D22: Hector | E22: 0 | F22: 0
B23: Pasivo de largo plazo | C23: Mercado | D23: Orlando | E23: 1599599 | F23: =+SUM(F5:F22) -> 1560920
B24: Total general | E24: 11328519
B34: Inversion Proyecto | C34: Origen Equipo | D34: Valor | H34: Materia Prima | I34: Valor
B35: Horno de pollos | C35: Nuevo | D35: 10000000 | H35: Carne | I35: 200000
B36: Bicicleta - Parrilla | C36: Propio | D36: 1800000 | H36: Pollo | I36: =50*20000 -> 1000000 | K36: 50 pollos
B37: olla arrocera | C37: Antiguo | D37: 600000 | H37: Hamburguesa | I37: 0 | K37: 25.000 a 10 cada
B38: Nevera | C38: Antiguo | D38: 600000 | H38: Bebidas | I38: 280000 | K38: 49 gaseosas litro y media
B39: Mesas 4 meseras | C39: Antiguo | D39: 500000 | H39: Sazón | I39: 300000 | K39: gaseosas pequeñas 50
B40: Estufa | C40: Nuevo | D40: 480000 | H40: Cerdo | I40: 0
B41: Campana | C41: Nuevo | D41: 320000 | H41: Mercado y Hamburguesa | I41: 200000 | K41: Sason para un mes | L41: 200000
B42: Licuadrora | C42: Nuevo | D42: 200000 | H42: Pescado | I42: 150000
B43: olla espres | C43: Antiguo | D43: 200000 | H43: Total | I43: =SUBTOTAL(109,Stock_Actual[Valor]) -> 2130000
B44: Platos, cubiertos, Tablas bajijas de plasticos | C44: Antiguo | D44: 200000
B45: Extractor | C45: Antiguo | D45: 200000
B46: Equipo de sonido | C46: Antiguo | D46: 150000 | H46: Materia Prima | I46: Valor
B47: Platero | C47: Nuevo | D47: 120000 | H47: Carne | I47: 1500000
B48: Mesa para lavar pollo | C48: Antiguo | D48: 120000 | H48: Pollo | I48: =50*20000 -> 1000000
B49: Otras ollas | C49: Antiguo | D49: 100000 | H49: Bebidas | I49: 800000 | K49: 50 pollos un millon | M49: 60.000 por millar
B50: Mesa para dejar ollas | C50: Antiguo | D50: 90000 | H50: Sazón | I50: 300000 | M50: 35000 por millar
B51: Bascula | C51: Nuevo | D51: 70000 | H51: Cerdo | I51: 500000
B52: Mesa madera | C52: Antiguo | D52: 70000 | H52: Mercado y Hamburguesa | I52: 200000
B53: Botes de basura | C53: Antiguo | D53: =35000*2 -> 70000 | H53: Pescado | I53: 300000
B54: Bicicleta | C54: Antiguo | D54: 70000 | H54: Total | I54: =SUBTOTAL(109,Stock_Ideal[Valor]) -> 4600000
B55: Mesa bajita de metal | C55: Antiguo | D55: 60000
B56: Total | D56: =SUBTOTAL(109,Planta_y_Equipo[Valor]) -> 16020000

Sheet Ingresos
A2: Tipo día | B2: (Todas) | W2: Mes de análisis | X2: Venta | Y2: Promedio Venta | Z2: Gastos | AA2: Rent. trabajo | AB2: Prom. Rent. Trabajo | AQ2: Tipo día | AR2: (Todas)
W3: abril | X3: 5230000 | Y3: 174333.33 | Z3: 1082730 | AA3: 747770 | AB3: 24925.667
A4: Mes | B4: Fecha | C4: Día | D4: Venta | E4: Gastos | AJ4: Mes | AK4: Fecha | AL4: Día | AM4: Venta | AQ4: Mes | AR4: Fecha | AS4: Día | AT4: Gastos
A5: abril | B5: 10-abr | C5: vie | D5: 150000 | E5: 25091 | AJ5: abril | AK5: 10-abr | AL5: vie | AM5: 150000 | AQ5: abril | AR5: 10-abr | AS5: vie | AT5: 25091
B6: 11-abr | C6: sáb | D6: 160000 | E6: 25091 | W6: Tendencia | X6: Ventas | Y6: Rentabilidad | Z6: Gastos | AA6: Utilidad trabajo | AB6: E (Renta) | AC6: Target MC | AD6: Target Ventas | AK6: 11-abr | AL6: sáb | AM6: 160000 | AR6: 11-abr | AS6: sáb | AT6: 25091
B7: 12-abr | C7: dom | D7: 160000 | E7: 25091 | W7: Días trascurridos | X7: =+SUBTOTAL(3,B5:B1048576) -> 30 | AK7: 12-abr | AL7: dom | AM7: 160000 | AR7: 12-abr | AS7: dom | AT7: 25091
B8: 13-abr | C8: lun | D8: 160000 | E8: 35091 | W8: Rentabilidad x día | X8: =+SUBTOTAL(9,D5:D1048576)/SUBTOTAL(3,B5:B1048576) -> 174333.33 | Y8: =+SUBTOTAL(9,E5:E1048576)/SUBTOTAL(3,B5:B1048576) -> 36091 | Z8: =+SUBTOTAL(9,F5:F1048576)/SUBTOTAL(3,B5:B1048576) -> 0 | AA8: =+Y8-Z8 -> 36091 | AB8: =+AB9/30 -> 53333.333 | AC8: =+AB8+Z8 -> 53333.333 | AD8: =+AD9/30 -> 177777.78 | AF8: 143241 | AK8: 13-abr | AL8: lun | AM8: 160000 | AR8: 13-abr | AS8: lun | AT8: 35091
B9: 14-abr | C9: mar | D9: 160000 | E9: 35091 | W9: Rentabilidad x mes | X9: =+X8*30 -> 5230000 | Y9: =+Y8*30 -> 1082730 | Z9: =+Z8*30 -> 0 | AA9: =+AA8*30 -> 1082730 | AB9: =+(20000*30)+1000000 -> 1600000 | AC9: =+AB9+Z9 -> 1600000 | AD9: =(AC9*100)/30 -> 5333333.3 | AF9: 174333.33 | AG9: =+AF9/AF8 -> 1.2170631 | AH9: =+AF9-AF8 -> 31092.333 | AK9: 14-abr | AL9: mar | AM9: 160000 | AR9: 14-abr | AS9: mar | AT9: 35091
B10: 15-abr | C10: mié | D10: 80000 | E10: 35091 | AK10: 15-abr | AL10: mié | AM10: 80000 | AR10: 15-abr | AS10: mié | AT10: 35091
B11: 16-abr | C11: jue | D11: 200000 | E11: 35091 | X11: Ventas | Y11: Rentabilidad | Z11: Gastos | AA11: Ganacia / Nomina | AB11: % Target | AC11: Target Día | AD11: Target % | AK11: 16-abr | AL11: jue | AM11: 200000 | AR11: 16-abr | AS11: jue | AT11: 35091
B12: 17-abr | C12: vie | D12: 80000 | E12: 35091 | W12: lunes | X12: =+AVERAGEIF($C$5:$C$1048576,$W12,$D$5:$D$1048576) -> #DIV/0! | Y12: =+AVERAGEIF($C$5:$C$1048576,W12,$E$5:$E$1048576) -> #DIV/0! | Z12: =+AVERAGEIF($C$5:$C$1048576,W12,$F$5:$F$1048576) -> #DIV/0! | AA12: =+Y12-Z12 -> #DIV/0! | AB12: =+X12/$X$20 -> #DIV/0! | AC12: =+AB12*$AD$8 -> #DIV/0! | AD12: =+AC12/X12-1 -> #DIV/0! | AK12: 17-abr | AL12: vie | AM12: 80000 | AR12: 17-abr | AS12: vie | AT12: 35091
B13: 18-abr | C13: sáb | D13: 300000 | E13: 35091 | W13: martes | X13: =+AVERAGEIF($C$5:$C$1048576,$W13,$D$5:$D$1048576) -> #DIV/0! | Y13: =+AVERAGEIF($C$5:$C$1048576,W13,$E$5:$E$1048576) -> #DIV/0! | Z13: =+AVERAGEIF($C$5:$C$1048576,W13,$F$5:$F$1048576) -> #DIV/0! | AA13: =+Y13-Z13 -> #DIV/0! | AB13: =+X13/$X$20 -> #DIV/0! | AC13: =+AB13*$AD$8 -> #DIV/0! | AD13: =+AC13/X13-1 -> #DIV/0! | AK13: 18-abr | AL13: sáb | AM13: 300000 | AR13: 18-abr | AS13: sáb | AT13: 35091
B14: 19-abr | C14: dom | D14: 320000 | E14: 35091 | W14: miércoles | X14: =+AVERAGEIF($C$5:$C$1048576,$W14,$D$5:$D$1048576) -> #DIV/0! | Y14: =+AVERAGEIF($C$5:$C$1048576,W14,$E$5:$E$1048576) -> #DIV/0! | Z14: =+AVERAGEIF($C$5:$C$1048576,W14,$F$5:$F$1048576) -> #DIV/0! | AA14: =+Y14-Z14 -> #DIV/0! | AB14: =+X14/$X$20 -> #DIV/0! | AC14: =+AB14*$AD$8 -> #DIV/0! | AD14: =+AC14/X14-1 -> #DIV/0! | AK14: 19-abr | AL14: dom | AM14: 320000 | AR14: 19-abr | AS14: dom | AT14: 35091
B15: 20-abr | C15: lun | D15: 150000 | E15: 35091 | W15: jueves | X15: =+AVERAGEIF($C$5:$C$1048576,$W15,$D$5:$D$1048576) -> #DIV/0! | Y15: =+AVERAGEIF($C$5:$C$1048576,W15,$E$5:$E$1048576) -> #DIV/0! | Z15: =+AVERAGEIF($C$5:$C$1048576,W15,$F$5:$F$1048576) -> #DIV/0! | AA15: =+Y15-Z15 -> #DIV/0! | AB15: =+X15/$X$20 -> #DIV/0! | AC15: =+AB15*$AD$8 -> #DIV/0! | AD15: =+AC15/X15-1 -> #DIV/0! | AK15: 20-abr | AL15: lun | AM15: 150000 | AR15: 20-abr | AS15: lun | AT15: 35091
B16: 21-abr | C16: mar | D16: 100000 | E16: 35091 | W16: viernes | X16: =+AVERAGEIF($C$5:$C$1048576,$W16,$D$5:$D$1048576) -> #DIV/0! | Y16: =+AVERAGEIF($C$5:$C$1048576,W16,$E$5:$E$1048576) -> #DIV/0! | Z16: =+AVERAGEIF($C$5:$C$1048576,W16,$F$5:$F$1048576) -> #DIV/0! | AA16: =+Y16-Z16 -> #DIV/0! | AB16: =+X16/$X$20 -> #DIV/0! | AC16: =+AB16*$AD$8 -> #DIV/0! | AD16: =+AC16/X16-1 -> #DIV/0! | AK16: 21-abr | AL16: mar | AM16: 100000 | AR16: 21-abr | AS16: mar | AT16: 35091
B17: 22-abr | C17: mié | D17: 70000 | E17: 35091 | W17: sábado | X17: =+AVERAGEIF($C$5:$C$1048576,$W17,$D$5:$D$1048576) -> #DIV/0! | Y17: =+AVERAGEIF($C$5:$C$1048576,W17,$E$5:$E$1048576) -> #DIV/0! | Z17: =+AVERAGEIF($C$5:$C$1048576,W17,$F$5:$F$1048576) -> #DIV/0! | AA17: =+Y17-Z17 -> #DIV/0! | AB17: =+X17/$X$20 -> #DIV/0! | AC17: =+AB17*$AD$8 -> #DIV/0! | AD17: =+AC17/X17-1 -> #DIV/0! | AK17: 22-abr | AL17: mié | AM17: 70000 | AR17: 22-abr | AS17: mié | AT17: 35091
B18: 23-abr | C18: jue | D18: 120000 | E18: 35091 | W18: domingo | X18: =+AVERAGEIF($C$5:$C$1048576,$W18,$D$5:$D$1048576) -> #DIV/0! | Y18: =+AVERAGEIF($C$5:$C$1048576,W18,$E$5:$E$1048576) -> #DIV/0! | Z18: =+AVERAGEIF($C$5:$C$1048576,W18,$F$5:$F$1048576) -> #DIV/0! | AA18: =+Y18-Z18 -> #DIV/0! | AB18: =+X18/$X$20 -> #DIV/0! | AC18: =+AB18*$AD$8 -> #DIV/0! | AD18: =+AC18/X18-1 -> #DIV/0! | AK18: 23-abr | AL18: jue | AM18: 120000 | AR18: 23-abr | AS18: jue | AT18: 35091
B19: 24-abr | C19: vie | D19: 120000 | E19: 35091 | AK19: 24-abr | AL19: vie | AM19: 120000 | AR19: 24-abr | AS19: vie | AT19: 35091
B20: 25-abr | C20: sáb | D20: 320000 | E20: 35091 | X20: =+AVERAGE(X12:X18) -> #DIV/0! | Y20: =+AVERAGE(Y12:Y18) -> #DIV/0! | Z20: =+AVERAGE(Z12:Z18) -> #DIV/0! | AC20: =+AVERAGE(AC12:AC18) -> #DIV/0! | AD20: =+AC20/X20-1 -> #DIV/0! | AK20: 25-abr | AL20: sáb | AM20: 320000 | AR20: 25-abr | AS20: sáb | AT20: 35091
B21: 26-abr | C21: dom | D21: 450000 | E21: 35091 | X21: =+AVERAGE(X12:X15) -> #DIV/0! | Y21: =+AVERAGE(Y12:Y15) -> #DIV/0! | Z21: =+AVERAGE(Z12:Z15) -> #DIV/0! | AK21: 26-abr | AL21: dom | AM21: 450000 | AR21: 26-abr | AS21: dom | AT21: 35091
B22: 27-abr | C22: lun | D22: 160000 | E22: 35091 | AK22: 27-abr | AL22: lun | AM22: 160000 | AR22: 27-abr | AS22: lun | AT22: 35091
B23: 28-abr | C23: mar | D23: 160000 | E23: 35091 | AB23: =15000*30 -> 450000 | AK23: 28-abr | AL23: mar | AM23: 160000 | AR23: 28-abr | AS23: mar | AT23: 35091
B24: 29-abr | C24: mié | D24: 360000 | E24: 35091 | AK24: 29-abr | AL24: mié | AM24: 360000 | AR24: 29-abr | AS24: mié | AT24: 35091
B25: 30-abr | C25: jue | D25: 160000 | E25: 35091 | AK25: 30-abr | AL25: jue | AM25: 160000 | AR25: 30-abr | AS25: jue | AT25: 35091
B26: 1-abr | C26: mié | D26: 60000 | E26: 55091 | AK26: 1-abr | AL26: mié | AM26: 60000 | AR26: 1-abr | AS26: mié | AT26: 55091
B27: 2-abr | C27: jue | D27: 120000 | E27: 55091 | AK27: 2-abr | AL27: jue | AM27: 120000 | AR27: 2-abr | AS27: jue | AT27: 55091
B28: 3-abr | C28: vie | D28: 200000 | E28: 55091 | AK28: 3-abr | AL28: vie | AM28: 200000 | AR28: 3-abr | AS28: vie | AT28: 55091
B29: 4-abr | C29: sáb | D29: 220000 | E29: 55091 | AK29: 4-abr | AL29: sáb | AM29: 220000 | AR29: 4-abr | AS29: sáb | AT29: 55091
B30: 5-abr | C30: dom | D30: 380000 | E30: 55091 | AK30: 5-abr | AL30: dom | AM30: 380000 | AR30: 5-abr | AS30: dom | AT30: 55091
B31: 6-abr | C31: lun | D31: 80000 | E31: 25091 | AK31: 6-abr | AL31: lun | AM31: 80000 | AR31: 6-abr | AS31: lun | AT31: 25091
B32: 7-abr | C32: mar | D32: 140000 | E32: 25091 | AK32: 7-abr | AL32: mar | AM32: 140000 | AR32: 7-abr | AS32: mar | AT32: 25091
B33: 8-abr | C33: mié | D33: 50000 | E33: 25091 | AK33: 8-abr | AL33: mié | AM33: 50000 | AR33: 8-abr | AS33: mié | AT33: 25091
B34: 9-abr | C34: jue | D34: 40000 | E34: 25091 | AK34: 9-abr | AL34: jue | AM34: 40000 | AR34: 9-abr | AS34: jue | AT34: 25091

Sheet Cuentas x Pagar
X1: Forecast
U2: =+T2*100 -> 0 | X2: Budget (Gastos)
G3: 70000
L4: Septimebre | U4: Programación | Y4: Pagos programados Abril -2020
A5: Nombre proveedor | B5: Proveedor | C5: Tipo de obligación | D5: Marzo | E5: Valor pagado Marzo | F5: Abril | G5: Valor pagado Abril | H5: Mayo | I5: Valor pagado Mayo | J5: Junio | K5: Valor pagado Junio | L5: Julio | M5: Pagos Julio x programar | N5: Valor pagado Julio | O5: Valor por Pagar | P5: Estado Tesoreria | Q5: Origen | R5: Saldo nuevo admón | U5: Mes de acuerdo de pago | V5: Tiempo a diferir (meses) | W5: Cuota mensual | X5: Interés pactado | Z5: Sem. 1 | AA5: Sem. 2 | AB5: Sem. 3 | AC5: Sem. 4 | AD5: Cuotas pendientes | AE5: Valor pagado
A6: Diego | B6: Carne de cerdo | C6: Pasivo de corto plazo | D6: 1088000 | E6: 0 | F6: 1088000 | G6: 0 | H6: =+Pasivos[[#This Row],[Abril]] -> 1088000 | I6: 0 | J6: 1088000 | K6: 0 | L6: 1088000 | M6: 0 | N6: 0 | O6: 0 | P6: Congelado | Q6: Papá | R6: 0 | U6: Abril | X6: 0.05 | AE6: =+SUM(Z6:AC6) -> 0
A7: Martin | B7: Carne de cerdo | C7: Pasivo de largo plazo | D7: 300000 | E7: 0 | F7: 300000 | G7: 60000 | H7: 240000 | I7: 0 | J7: 240000 | K7: 0 | L7: 240000 | M7: 0 | N7: 0 | O7: 0 | P7: Congelado | Q7: Vigente | R7: =+L7 -> 240000 | U7: Abril | X7: 0 | AE7: =+SUM(Z7:AC7) -> 0
A8: Sarmiento | B8: Carne de cerdo | C8: Pasivo de largo plazo | D8: 350000 | E8: 0 | F8: 350000 | G8: 0 | H8: 350000 | I8: 0 | J8: 350000 | K8: 0 | L8: 350000 | M8: 0 | N8: 0 | O8: 0 | P8: Congelado | Q8: Papá | R8: 0 | U8: Abril | X8: 0.05 | AE8: =+SUM(Z8:AC8) -> 0
A9: Leornardo | B9: Carne de res | C9: Pasivo de largo plazo | D9: 1350000 | E9: 0 | F9: 1350000 | G9: 0 | H9: 1350000 | I9: 0 | J9: 1350000 | K9: 0 | L9: 1350000 | M9: 0 | N9: 0 | O9: 0 | P9: Congelado | Q9: Vigente | R9: =+L9/2 -> 675000 | U9: Abril | X9: 0 | AE9: =+SUM(Z9:AC9) -> 0
A10: Orlando | B10: Mercado | C10: Pasivo de largo plazo | D10: =1399599+200000 -> 1599599 | E10: 0 | F10: 1599599 | G10: 0 | H10: 1599599 | I10: 0 | J10: 1599599 | K10: 0 | L10: 1599599 | M10: 0 | N10: 0 | O10: 0 | P10: Congelado | Q10: Vigente | R10: =+L10/2 -> 799799.5 | U10: Abril | Z10: =+Pasivos[[#This Row],[Valor pagado Marzo]] -> 0
A11: Hector | B11: Menudo y prestamo | C11: Pasivo de largo plazo | D11: 800000 | E11: 0 | F11: 0 | G11: 0 | H11: 0 | I11: 0 | J11: 0 | K11: =+Pasivos[[#This Row],[Junio]] -> 0 | L11: 0 | M11: 0 | N11: 0 | O11: 0 | P11: Pagado | Q11: Pagado | R11: =+Pasivos[[#This Row],[Julio]] -> 0 | U11: Abril
A12: Vecino | B12: Carne de res | C12: Pasivo de corto plazo | D12: 480000 | E12: =+Pasivos[[#This Row],[Marzo]]-Pasivos[[#This Row],[Abril]] -> 100000 | F12: 380000 | G12: 0 | H12: 380000 | I12: 0 | J12: 380000 | K12: 0 | L12: 380000 | M12: 0 | N12: 0 | O12: 0 | P12: Congelado | Q12: Vigente | R12: =+L12 -> 380000 | U12: Abril | X12: 0 | AE12: =+SUM(Z12:AC12) -> 0
A13: Nd | B13: Carne de Pollo | C13: Pasivo de corto plazo | D13: 750000 | E13: 0 | F13: 750000 | G13: 0 | H13: 750000 | I13: 0 | J13: 750000 | K13: 0 | L13: 750000 | M13: 150000 | O13: 150000 | P13: Pagar Urgente | Q13: Vigente | R13: =+L13 -> 750000 | U13: Abril | AE13: =+SUM(Z13:AC13) -> 0
A14: Nd | B14: PUBLICIDAD | C14: Pasivo de corto plazo | D14: 400000 | E14: 0 | F14: 400000 | G14: 0 | H14: 400000 | I14: 0 | J14: 400000 | K14: 0 | L14: 400000 | M14: 0 | N14: 0 | O14: 0 | P14: Congelado | Q14: Papá | R14: 0 | U14: Abril
A15: nd | B15: Pintura, local | C15: Pasivo de corto plazo | D15: 370000 | E15: 0 | F15: 370000 | G15: 0 | H15: 370000 | I15: 0 | J15: 370000 | K15: 0 | L15: 370000 | M15: 0 | N15: 0 | O15: 0 | P15: Congelado | Q15: Papá | R15: 0 | U15: Abril
A16: Arredatario | B16: ARRIENDO | C16: Pasivo de corto plazo | D16: 0 | E16: 0 | F16: 0 | G16: 0 | H16: 240000 | I16: 0 | J16: 0 | K16: 0 | L16: 750000 | M16: 750000 | N16: 0 | O16: =+Pasivos[[#This Row],[Pagos Julio x programar]] -> 750000 | P16: Pagar Urgente | Q16: Vigente | R16: =+L16 -> 750000 | U16: Abril | AE16: =+SUM(Z16:AC16) -> 0
A17: =+Pasivos[[#This Row],[Proveedor]] -> Vitrina, ollas | B17: Vitrina, ollas | C17: Pasivo de corto plazo | D17: 180000 | E17: 0 | F17: 180000 | G17: 0 | H17: 180000 | I17: 0 | J17: 120000 | K17: =+Pasivos[[#This Row],[Junio]] -> 120000 | L17: 0 | M17: 0 | N17: 0 | O17: 0 | P17: Pagado | Q17: Papá | R17: =+Pasivos[[#This Row],[Julio]] -> 0 | U17: Abril | W17: 150000
A18: Saul | B18: FINANCIERO | C18: Pasivo de largo plazo | D18: 3000000 | E18: 0 | F18: 3000000 | G18: 150000 | H18: 3000000 | I18: 150000 | J18: 3000000 | K18: 150000 | L18: 3000000 | M18: 150000 | N18: 150000 | O18: 0 | P18: Financiero | Q18: Vigente | R18: =+L18/2 -> 1500000
A19: Gota x Gota | B19: FINANCIERO | C19: Pasivo de corto plazo | D19: 500000 | E19: =+Pasivos[[#This Row],[Marzo]]-Pasivos[[#This Row],[Abril]] -> 150000 | F19: 350000 | G19: 0 | H19: 260000 | I19: 0 | J19: 150000 | K19: =+Pasivos[[#This Row],[Junio]] -> 150000 | L19: 0 | M19: 0 | N19: 0 | O19: 0 | P19: Pagado | Q19: Papá | R19: =+Pasivos[[#This Row],[Julio]] -> 0 | U19: Abril | V19: Semanal | Z19: =+Pasivos[[#This Row],[Valor pagado Marzo]] -> 150000 | AE19: =+SUM(Z19:AC19) -> 150000
A20: Nomina | B20: NOMINA | C20: Pasivo de corto plazo | D20: =(30000*3)+(150000+60000) -> 300000 | E20: 150000 | F20: 150000 | G20: 150000 | H20: 0 | I20: 0 | J20: 100000 | K20: =+Pasivos[[#This Row],[Junio]] -> 100000 | L20: 0 | M20: 0 | N20: 0 | O20: 0 | P20: Pagado | Q20: Vigente | R20: =+Pasivos[[#This Row],[Julio]] -> 0 | U20: Abril | V20: Mensual | AE20: =+SUM(Z20:AC20) -> 0
A21: enel - 6451508-5 | B21: CODENSA | C21: Pasivo de corto plazo | D21: 429710 | E21: =+Pasivos[[#This Row],[Marzo]]-Pasivos[[#This Row],[Abril]] -> -631210 | F21: 1060920 | G21: =+Pasivos[[#This Row],[Abril]]-Pasivos[[#This Row],[Mayo]] -> -463290 | H21: 1524210 | I21: 37000 | J21: 1524210 | K21: 30000 | L21: 734830 | M21: 150000 | O21: =+Pasivos[[#This Row],[Pagos Julio x programar]] -> 150000 | P21: Pagar Urgente | Q21: Vigente | R21: =+Pasivos[[#This Row],[Julio]] -> 734830
A22: Sandra | B22: Arriendo Apto. | C22: Pasivo de corto plazo | D22: 0 | E22: 0 | F22: 0 | G22: 0 | H22: 0 | I22: 0 | J22: 400000 | K22: =+Pasivos[[#This Row],[Junio]] -> 400000 | L22: 450000 | M22: 450000 | N22: 0 | O22: =+Pasivos[[#This Row],[Pagos Julio x programar]] -> 450000 | P22: Pagar Urgente | Q22: Vigente | R22: =+Pasivos[[#This Row],[Julio]] -> 450000
A23: Ladron de Gas | B23: Contingencia: Gas | C23: Pasivo de corto plazo | D23: 0 | F23: 0 | H23: 0 | J23: 100000 | K23: =+Pasivos[[#This Row],[Junio]] -> 100000 | L23: 0 | M23: 0 | N23: 0 | O23: 0 | P23: Pagado | Q23: Pagado | R23: =+Pasivos[[#This Row],[Julio]] -> 0
A24: Licuadora | B24: Contingencia: Licuadora | C24: Pasivo de corto plazo | D24: 0 | F24: 0 | H24: 0 | J24: 0 | K24: 20000 | L24: 0 | M24: 0 | N24: 0 | O24: 0 | P24: Pagado | Q24: Pagado | R24: =+Pasivos[[#This Row],[Julio]] -> 0 | W24: =+SUM(W6:W13) -> 0 | Z24: =+SUM(Z6:Z19) -> 150000 | AA24: =+SUM(AA6:AA19) -> 0 | AB24: =+SUM(AB6:AB19) -> 0 | AC24: =+SUM(AC6:AC19) -> 0 | AE24: =+SUM(AE6:AE19) -> 150000
B25: Total | D25: =SUBTOTAL(109,Pasivos[Marzo]) -> 11897309 | E25: =+SUM(Pasivos[Valor pagado Marzo]) -> -231210 | F25: =+SUM(Pasivos[Abril]) -> 11328519 | G25: =+SUM(Pasivos[Valor pagado Abril]) -> -103290 | H25: =+SUM(Pasivos[Mayo]) -> 11731809 | I25: =+SUM(Pasivos[Valor pagado Mayo]) -> 187000 | J25: =+SUM(Pasivos[Junio]) -> 11921809 | K25: =+SUM(Pasivos[Valor pagado Junio]) -> 1070000 | L25: =+SUM(Pasivos[Julio]) -> 11462429 | M25: =+SUM(Pasivos[Pagos Julio x programar]) -> 1650000 | N25: =+SUM(Pasivos[Valor pagado Julio]) -> 150000 | O25: =+SUM(Pasivos[Valor por Pagar]) -> 1500000 | R25: =+SUM(Pasivos[Saldo nuevo admón]) -> 6279629.5
U26: Abril
A27: Coca Cola | B27: Nueva obligación | C27: Nd | D27: 280000 | E27: 0 | F27: 280000 | G27: 280000 | H27: 250000 | I27: 0 | J27: 250000 | L27: 250000 | P27: Corto Plazo | Q27: Pagar Urgente
G30: Moto
A31: Servicios, GAS | B31: Nueva obligación | C31: Vantì-Cta: 3721477 | D31: 428760
A32: Servicios, LUZ | B32: Nueva obligación | C32: enel - 6451508-5 | D32: 161750
A33: Servicios, AGUA | B33: Nueva obligación | C33: ESP de Tocancipá | D33: 400000 | G33: =+#REF!*#REF! -> #REF!
G36: nevera

Sheet Cuentas x Cobrar
A5: Proveedor | B5: Tipo de obligación | C5: Nombre proveedor | D5: Junio
A6: Carne de cerdo | B6: Antigua deuda | C6: Cliente 1 | D6: 150000
A7: Carne de cerdo | B7: Antigua deuda | C7: Cliente 2 | D7: 20000
A8: Total | D8: =+SUM(Pasivos8[Junio]) -> 170000

Sheet Forecast
D1: Marzo | I1: Abril | M1: Mayo | R1: Junio | V1: Julio | AA1: Agosto | AK1: Forecast | AO1: Target
AO2: Mes | AP2: agosto
A3: Suma de Venta | B3: Semana | AL3: =+AVERAGE(AL5:AL11) -> 346142.86 | AP3: =+AVERAGE(AP5:AP11) -> 133641.29
A4: Día | B4: 0 | C4: 1 | D4: 2 | E4: 3 | F4: 4 | G4: 5 | H4: 6 | I4: 7 | J4: 8 | K4: 9 | L4: 10 | M4: 11 | N4: 12 | O4: 13 | P4: 14 | Q4: 15 | R4: 16 | S4: 17 | T4: 18 | U4: 19 | V4: 20 | W4: 21 | X4: 22 | Y4: 23 | Z4: 24 | AA4: 25 | AB4: 26 | AC4: 27 | AD4: 28 | AE4: 29 | AF4: 30 | AG4: 31 | AH4: Total general | AK4: Día | AL4: Forecast | AM4: ∆% | AO4: Día | AP4: Prom. Venta PE & CP | AQ4: ∆%
A5: lun | C5: 0 | D5: 200000 | E5: 90000 | F5: 100000 | G5: 30000 | H5: 80000 | I5: 160000 | J5: 150000 | K5: 160000 | L5: 160000 | M5: 80000 | N5: 90000 | O5: 180000 | P5: 375000 | Q5: 200000 | R5: 330000 | S5: 380000 | T5: 200000 | U5: 215000 | V5: 162000 | W5: 230000 | X5: 344000 | Y5: 170000 | Z5: 248000 | AA5: 248000 | AB5: 248000 | AC5: 248000 | AD5: 248000 | AE5: 248000 | AF5: 248000 | AG5: 248000 | AH5: 6070000 | AK5: lun | AL5: =+AVERAGE(W5:Y5) -> 248000 | AM5: =X5/AL5-1 -> 0.38709677 | AO5: lun | AP5: 115836.21 | AQ5: =+AP5/AL5-1 -> -0.53291851
A6: mar | C6: 0 | D6: 240000 | E6: 90000 | F6: 130000 | G6: 50000 | H6: 140000 | I6: 160000 | J6: 100000 | K6: 160000 | L6: 120000 | M6: 170000 | N6: 110000 | O6: 150000 | P6: 170000 | Q6: 220000 | R6: 400000 | S6: 250000 | T6: 300000 | U6: 250000 | V6: 281000 | W6: 218000 | X6: 220000 | Y6: 260000 | Z6: 232666.67 | AA6: 232666.67 | AB6: 232666.67 | AC6: 232666.67 | AD6: 232666.67 | AE6: 232666.67 | AF6: 232666.67 | AG6: 232666.67 | AH6: 6050333.3 | AK6: mar | AL6: =+AVERAGE(W6:Y6) -> 232666.67 | AM6: =W6/AL6-1 -> -0.063037249 | AO6: mar | AP6: 115836.21 | AQ6: =+AP6/AL6-1 -> -0.50213663
A7: mié | C7: 0 | D7: 280000 | E7: 150000 | F7: 180000 | G7: 60000 | H7: 50000 | I7: 80000 | J7: 70000 | K7: 360000 | L7: 250000 | M7: 240000 | N7: 170000 | O7: 140000 | P7: 260000 | Q7: 220000 | R7: 320000 | S7: 300000 | T7: 380000 | U7: 150000 | V7: 50000 | W7: 98000 | X7: 175000 | Y7: 250000 | Z7: 174333.33 | AA7: 174333.33 | AB7: 174333.33 | AC7: 174333.33 | AD7: 174333.33 | AE7: 174333.33 | AF7: 174333.33 | AG7: 174333.33 | AH7: 5627666.7 | AK7: mié | AL7: =+AVERAGE(W7:Y7) -> 174333.33 | AM7: =W7/AL7-1 -> -0.43785851 | AO7: mié | AP7: 115836.21 | AQ7: =+AP7/AL7-1 -> -0.33554755
A8: jue | C8: 0 | D8: 90000 | E8: 240000 | F8: 80000 | G8: 120000 | H8: 40000 | I8: 200000 | J8: 120000 | K8: 160000 | L8: 120000 | M8: 150000 | N8: 180000 | O8: 180000 | P8: 230000 | Q8: 170000 | R8: 330000 | S8: 200000 | T8: 407100 | U8: 160000 | V8: 436000 | W8: 347000 | X8: 280000 | Y8: 335000 | Z8: 320666.67 | AA8: 320666.67 | AB8: 320666.67 | AC8: 320666.67 | AD8: 320666.67 | AE8: 320666.67 | AF8: 320666.67 | AH8: 6819766.7 | AK8: jue | AL8: =+AVERAGE(W8:Y8) -> 320666.67 | AM8: =W8/AL8-1 -> 0.082120582 | AO8: jue | AP8: 115836.21 | AQ8: =+AP8/AL8-1 -> -0.63876442
A9: vie | C9: 0 | D9: 330000 | E9: 210000 | F9: 100000 | G9: 200000 | H9: 150000 | I9: 80000 | J9: 120000 | K9: 160000 | L9: 150000 | M9: 390000 | N9: 170000 | O9: 300000 | P9: 350000 | Q9: 270000 | R9: 285000 | S9: 450000 | T9: 380000 | U9: 240000 | V9: 415000 | W9: 406000 | X9: 272000 | Y9: 407000 | Z9: 361666.67 | AA9: 361666.67 | AB9: 361666.67 | AC9: 361666.67 | AD9: 361666.67 | AE9: 361666.67 | AF9: 361666.67 | AH9: 8366666.7 | AK9: vie | AL9: =+AVERAGE(W9:Y9) -> 361666.67 | AM9: =W9/AL9-1 -> 0.12258065 | AO9: vie | AP9: 115836.21 | AQ9: =+AP9/AL9-1 -> -0.67971555
A10: sáb | C10: 200000 | D10: 900000 | E10: 130000 | F10: 120000 | G10: 220000 | H10: 160000 | I10: 300000 | J10: 320000 | K10: 460000 | L10: 80000 | M10: 550000 | N10: 360000 | O10: 470000 | P10: 300000 | Q10: 370000 | R10: 350000 | S10: 180000 | T10: 490000 | U10: 360000 | V10: 275000 | W10: 230000 | X10: 418000 | Y10: 622000 | Z10: 423333.33 | AA10: 423333.33 | AB10: 423333.33 | AC10: 423333.33 | AD10: 423333.33 | AE10: 423333.33 | AF10: 423333.33 | AH10: 10828333 | AK10: sáb | AL10: =+AVERAGE(W10:Y10) -> 423333.33 | AM10: =W10/AL10-1 -> -0.45669291 | AO10: sáb | AP10: 177971.77 | AQ10: =+AP10/AL10-1 -> -0.57959423
A11: dom | B11: 0 | C11: 800000 | D11: 600000 | E11: 200000 | F11: 150000 | G11: 380000 | H11: 160000 | I11: 320000 | J11: 450000 | K11: 350000 | L11: 1100000 | M11: 430000 | N11: 150000 | O11: 400000 | P11: 200000 | Q11: 400000 | R11: 380000 | S11: 300000 | T11: 450000 | U11: 700000 | V11: 320000 | W11: 933000 | X11: 681000 | Y11: 373000 | Z11: 662333.33 | AA11: 662333.33 | AB11: 662333.33 | AC11: 662333.33 | AD11: 662333.33 | AE11: 662333.33 | AF11: 662333.33 | AH11: 14863333 | AK11: dom | AL11: =+AVERAGE(W11:Y11) -> 662333.33 | AM11: =W11/AL11-1 -> 0.40865627 | AO11: dom | AP11: 178336.21 | AQ11: =+AP11/AL11-1 -> -0.73074553
A12: Total general | B12: 0 | C12: 1000000 | D12: 2640000 | E12: 1110000 | F12: 860000 | G12: 1060000 | H12: 780000 | I12: 1300000 | J12: 1330000 | K12: 1810000 | L12: 1980000 | M12: 2010000 | N12: 1230000 | O12: 1820000 | P12: 1885000 | Q12: 1850000 | R12: 2395000 | S12: 2060000 | T12: 2607100 | U12: 2075000 | V12: 1939000 | W12: 2462000 | X12: 2390000 | Y12: 2417000 | Z12: 2423000 | AA12: 2423000 | AB12: 2423000 | AC12: 2423000 | AD12: 2423000 | AE12: 2423000 | AF12: 2423000 | AG12: 655000 | AH12: 58626100 | AK12: Total general | AL12: =+AVERAGE(W12:Y12) -> 2423000 | AM12: =+AVERAGE(AM5:AM11) -> 0.0061236566 | AO12: Total general | AP12: 135938.72 | AQ12: =+AP12/AL12-1 -> -0.94389652
D13: =+D12/C12-1 -> 1.64 | E13: =+E12/D12-1 -> -0.57954545 | F13: =+F12/E12-1 -> -0.22522523 | G13: =+G12/F12-1 -> 0.23255814 | H13: =+H12/G12-1 -> -0.26415094 | I13: =+I12/H12-1 -> 0.66666667 | J13: =+J12/I12-1 -> 0.023076923 | K13: =+K12/J12-1 -> 0.36090226 | ... AB13: =+AB12/AA12-1 -> 0
A16: Día | B16: 0 | C16: 1 | D16: 2 | E16: 3 | F16: 4 | G16: 5 | H16: 6 | I16: 7 | J16: 8 | K16: 9 | L16: 10 | M16: 11 | N16: 12 | O16: 13 | P16: 14 | Q16: =+P16+1 -> 15 | R16: =+Q16+1 -> 16 | S16: =+R16+1 -> 17 | T16: =+S16+1 -> 18 | U16: =+T16+1 -> 19 | V16: =+U16+1 -> 20 | W16: =+V16+1 -> 21
A17: lun | C17: 0 | D17: 0 | E17: =+E5/D5-1 -> -0.55 | F17: =+F5/E5-1 -> 0.11111111 | G17: =+G5/F5-1 -> -0.7 | H17: =+H5/G5-1 -> 1.6666667 | I17: =+I5/H5-1 -> 1 | J17: =+J5/I5-1 -> -0.0625 | K17: =+K5/J5-1 -> 0.066666667 | L17: =+L5/K5-1 -> 0 | ... W17: =+W5/V5-1 -> 0.41975309
A18: mar | C18: 0 | D18: 0 | E18: =+E6/D6-1 -> -0.625 | F18: =+F6/E6-1 -> 0.44444444 | G18: =+G6/F6-1 -> -0.61538462 | H18: =+H6/G6-1 -> 1.8 | I18: =+I6/H6-1 -> 0.14285714 | J18: =+J6/I6-1 -> -0.375 | K18: =+K6/J6-1 -> 0.6 | L18: =+L6/K6-1 -> -0.25 | ... W18: =+W6/V6-1 -> -0.22419929
A19: mié | C19: 0 | D19: 0 | E19: =+E7/D7-1 -> -0.46428571 | F19: =+F7/E7-1 -> 0.2 | G19: =+G7/F7-1 -> -0.66666667 | H19: =+H7/G7-1 -> -0.16666667 | I19: =+I7/H7-1 -> 0.6 | J19: =+J7/I7-1 -> -0.125 | K19: =+K7/J7-1 -> 4.1428571 | L19: =+L7/K7-1 -> -0.30555556 | ... W19: =+W7/V7-1 -> 0.96
A20: jue | C20: 0 | D20: 0 | E20: =+E8/D8-1 -> 1.6666667 | F20: =+F8/E8-1 -> -0.66666667 | G20: =+G8/F8-1 -> 0.5 | H20: =+H8/G8-1 -> -0.66666667 | I20: =+I8/H8-1 -> 4 | J20: =+J8/I8-1 -> -0.4 | K20: =+K8/J8-1 -> 0.33333333 | L20: =+L8/K8-1 -> -0.25 | ... W20: =+W8/V8-1 -> -0.20412844
A21: vie | C21: 0 | D21: 0 | E21: =+E9/D9-1 -> -0.36363636 | F21: =+F9/E9-1 -> -0.52380952 | G21: =+G9/F9-1 -> 1 | H21: =+H9/G9-1 -> -0.25 | I21: =+I9/H9-1 -> -0.46666667 | J21: =+J9/I9-1 -> 0.5 | K21: =+K9/J9-1 -> 0.33333333 | L21: =+L9/K9-1 -> -0.0625 | ... W21: =+W9/V9-1 -> -0.021686747
A22: sáb | C22: 0 | D22: =+D10/C10-1 -> 3.5 | E22: =+E10/D10-1 -> -0.85555556 | F22: =+F10/E10-1 -> -0.076923077 | G22: =+G10/F10-1 -> 0.83333333 | H22: =+H10/G10-1 -> -0.27272727 | I22: =+I10/H10-1 -> 0.875 | J22: =+J10/I10-1 -> 0.066666667 | K22: =+K10/J10-1 -> 0.4375 | ... W22: =+W10/V10-1 -> -0.16363636
A23: dom | B23: 0 | C23: 0 | D23: =+D11/C11-1 -> -0.25 | E23: =+E11/D11-1 -> -0.66666667 | F23: =+F11/E11-1 -> -0.25 | G23: =+G11/F11-1 -> 1.5333333 | H23: =+H11/G11-1 -> -0.57894737 | I23: =+I11/H11-1 -> 1 | J23: =+J11/I11-1 -> 0.40625 | K23: =+K11/J11-1 -> -0.22222222 | ... W23: =+W11/V11-1 -> 1.915625
A24: Total general | B24: 0 | C24: 142857.14 | D24: =+D12/C12-1 -> 1.64 | E24: =+E12/D12-1 -> -0.57954545 | F24: =+F12/E12-1 -> -0.22522523 | G24: =+G12/F12-1 -> 0.23255814 | H24: =+H12/G12-1 -> -0.26415094 | I24: =+I12/H12-1 -> 0.66666667 | J24: =+J12/I12-1 -> 0.023076923 | K24: =+K12/J12-1 -> 0.36090226 | ... W24: =+W12/V12-1 -> 0.26972666
A26: Día | B26: 0 | C26: 1 | D26: 2 | E26: 3 | F26: 4 | G26: 5 | H26: 6 | I26: 7 | J26: 8 | K26: 9 | L26: 10 | M26: 11 | N26: 12 | O26: 13 | P26: 14 | Q26: =+P26+1 -> 15 | R26: =+Q26+1 -> 16 | S26: =+R26+1 -> 17 | T26: =+S26+1 -> 18 | U26: =+T26+1 -> 19 | V26: =+U26+1 -> 20 | W26: =+V26+1 -> 21
A27: lun | C27: 0 | D27: 0 | E27: =+E5-D5 -> -110000 | F27: =+F5-E5 -> 10000 | G27: =+G5-F5 -> -70000 | H27: =+H5-G5 -> 50000 | I27: =+I5-H5 -> 80000 | J27: =+J5-I5 -> -10000 | K27: =+K5-J5 -> 10000 | L27: =+L5-K5 -> 0 | ... W27: =+W5-V5 -> 68000
A28: mar | C28: 0 | D28: 0 | E28: =+E6-D6 -> -150000 | F28: =+F6-E6 -> 40000 | G28: =+G6-F6 -> -80000 | H28: =+H6-G6 -> 90000 | I28: =+I6-H6 -> 20000 | J28: =+J6-I6 -> -60000 | K28: =+K6-J6 -> 60000 | L28: =+L6-K6 -> -40000 | ... W28: =+W6-V6 -> -63000
A29: mié | C29: 0 | D29: 0 | E29: =+E7-D7 -> -130000 | F29: =+F7-E7 -> 30000 | G29: =+G7-F7 -> -120000 | H29: =+H7-G7 -> -10000 | I29: =+I7-H7 -> 30000 | J29: =+J7-I7 -> -10000 | K29: =+K7-J7 -> 290000 | L29: =+L7-K7 -> -110000 | ... W29: =+W7-V7 -> 48000
A30: jue | C30: 0 | D30: 0 | E30: =+E8-D8 -> 150000 | F30: =+F8-E8 -> -160000 | G30: =+G8-F8 -> 40000 | H30: =+H8-G8 -> -80000 | I30: =+I8-H8 -> 160000 | J30: =+J8-I8 -> -80000 | K30: =+K8-J8 -> 40000 | L30: =+L8-K8 -> -40000 | ... W30: =+W8-V8 -> -89000
A31: vie | C31: 0 | D31: 0 | E31: =+E9-D9 -> -120000 | F31: =+F9-E9 -> -110000 | G31: =+G9-F9 -> 100000 | H31: =+H9-G9 -> -50000 | I31: =+I9-H9 -> -70000 | J31: =+J9-I9 -> 40000 | K31: =+K9-J9 -> 40000 | L31: =+L9-K9 -> -10000 | ... W31: =+W9-V9 -> -9000
A32: sáb | C32: 0 | D32: =+D10-C10 -> 700000 | E32: =+E10-D10 -> -770000 | F32: =+F10-E10 -> -10000 | G32: =+G10-F10 -> 100000 | H32: =+H10-G10 -> -60000 | I32: =+I10-H10 -> 140000 | J32: =+J10-I10 -> 20000 | K32: =+K10-J10 -> 140000 | ... W32: =+W10-V10 -> -45000
A33: dom | B33: 0 | C33: 0 | D33: =+D11-C11 -> -200000 | E33: =+E11-D11 -> -400000 | F33: =+F11-E11 -> -50000 | G33: =+G11-F11 -> 230000 | H33: =+H11-G11 -> -220000 | I33: =+I11-H11 -> 160000 | J33: =+J11-I11 -> 130000 | K33: =+K11-J11 -> -100000 | ... W33: =+W11-V11 -> 613000
A34: Total general | B34: 0 | C34: 142857.14 | D34: =+D12-C12 -> 1640000 | E34: =+E12-D12 -> -1530000 | F34: =+F12-E12 -> -250000 | G34: =+G12-F12 -> 200000 | H34: =+H12-G12 -> -280000 | I34: =+I12-H12 -> 520000 | J34: =+J12-I12 -> 30000 | K34: =+K12-J12 -> 480000 | ... W34: =+W12-V12 -> 523000

Sheet Hoja1
A1: Día
A2: dom | B2: D) Domingo
A3: lun | B3: A) Día hábil
A4: mar | B4: A) Día hábil
A5: mié | B5: A) Día hábil
A6: jue | B6: A) Día hábil
A7: vie | B7: C) Viernes
A8: sáb | B8: C) Sábado

Sheet Opex (2)
B1: Tipo | C1: Fecha | D1: Mes | E1: Arriendo | F1: No. Días Arriendo | G1: Día Arriendo | H1: Gas | I1: No. Días Gas | J1: Consumo (m3) | K1: Costo prom. Gas | L1: Día Gas | M1: Agua | N1: Dìa Agua | O1: Energia | P1: Financiació Energia | Q1: No. Días Energia | R1: Consumo (KhW | S1: Costo prom. Energia | T1: Fecha corte enega | U1: Día Energia
B2: Histórico | C2: 43624 | D2: =+TEXT(C2,"mmmm") -> junio | E2: 1000000 | G2: =IFERROR(Opex9[[#This Row],[Arriendo]]/Opex9[[#This Row],[No. Días Arriendo]],0) -> 0 | H2: 430 | I2: 0 | J2: 0 | K2: =IFERROR(Opex9[[#This Row],[Gas]]/Opex9[[#This Row],[Consumo (m3)]],0) -> 0 | L2: =IFERROR(Opex9[[#This Row],[Gas]]/Opex9[[#This Row],[No. Días Arriendo]],0) -> 0 | N2: =IFERROR(Opex9[[#This Row],[Agua]]/Opex9[[#This Row],[No. Días Arriendo]],0) -> 0 | Q2: =+X2 -> 0 | S2: =IFERROR(Opex9[[#This Row],[Energia]]/Opex9[[#This Row],[Consumo (KhW]],0) -> 0 | U2: =IFERROR(Opex9[[#This Row],[Energia]]/Opex9[[#This Row],[No. Días Arriendo]],0) -> 0
B3: Histórico | C3: 43654 | D3: =+TEXT(C3,"mmmm") -> julio | E3: 1000000 | G3: =IFERROR(Opex9[[#This Row],[Arriendo]]/Opex9[[#This Row],[No. Días Arriendo]],0) -> 0 | H3: 88870 | I3: =+F2 -> 0 | J3: 112 | K3: =IFERROR(Opex9[[#This Row],[Gas]]/Opex9[[#This Row],[Consumo (m3)]],0) -> 793.48214 | L3: =IFERROR(Opex9[[#This Row],[Gas]]/Opex9[[#This Row],[No. Días Arriendo]],0) -> 0 | N3: =IFERROR(Opex9[[#This Row],[Agua]]/Opex9[[#This Row],[No. Días Arriendo]],0) -> 0 | Q3: =+X3 -> 0 | S3: =IFERROR(Opex9[[#This Row],[Energia]]/Opex9[[#This Row],[Consumo (KhW]],0) -> 0 | U3: =IFERROR(Opex9[[#This Row],[Energia]]/Opex9[[#This Row],[No. Días Arriendo]],0) -> 0
B4: Histórico | C4: 43685 | D4: =+TEXT(C4,"mmmm") -> agosto | E4: 1000000 | G4: =IFERROR(Opex9[[#This Row],[Arriendo]]/Opex9[[#This Row],[No. Días Arriendo]],0) -> 0 | H4: 201040 | I4: =+F3 -> 0 | J4: 233 | K4: =IFERROR(Opex9[[#This Row],[Gas]]/Opex9[[#This Row],[Consumo (m3)]],0) -> 862.83262 | L4: =IFERROR(Opex9[[#This Row],[Gas]]/Opex9[[#This Row],[No. Días Arriendo]],0) -> 0 | N4: =IFERROR(Opex9[[#This Row],[Agua]]/Opex9[[#This Row],[No. Días Arriendo]],0) -> 0 | Q4: =+X4 -> 0 | S4: =IFERROR(Opex9[[#This Row],[Energia]]/Opex9[[#This Row],[Consumo (KhW]],0) -> 0 | U4: =IFERROR(Opex9[[#This Row],[Energia]]/Opex9[[#This Row],[No. Días Arriendo]],0) -> 0
B5: Histórico | C5: 43715 | D5: =+TEXT(C5,"mmmm") -> septiembre | E5: 1000000 | G5: =IFERROR(Opex9[[#This Row],[Arriendo]]/Opex9[[#This Row],[No. Días Arriendo]],0) -> 0 | H5: 177990 | I5: =+F4 -> 0 | J5: 209 | K5: =IFERROR(Opex9[[#This Row],[Gas]]/Opex9[[#This Row],[Consumo (m3)]],0) -> 851.62679 | L5: =IFERROR(Opex9[[#This Row],[Gas]]/Opex9[[#This Row],[No. Días Arriendo]],0) -> 0 | N5: =IFERROR(Opex9[[#This Row],[Agua]]/Opex9[[#This Row],[No. Días Arriendo]],0) -> 0 | Q5: =+X5 -> 0 | S5: =IFERROR(Opex9[[#This Row],[Energia]]/Opex9[[#This Row],[Consumo (KhW]],0) -> 0 | U5: =IFERROR(Opex9[[#This Row],[Energia]]/Opex9[[#This Row],[No. Días Arriendo]],0) -> 0
B6: Histórico | C6: 43745 | D6: =+TEXT(C6,"mmmm") -> octubre | E6: 1000000 | G6: =IFERROR(Opex9[[#This Row],[Arriendo]]/Opex9[[#This Row],[No. Días Arriendo]],0) -> 0 | H6: 174280 | I6: =+F5 -> 0 | J6: 201 | K6: =IFERROR(Opex9[[#This Row],[Gas]]/Opex9[[#This Row],[Consumo (m3)]],0) -> 867.06468 | L6: =IFERROR(Opex9[[#This Row],[Gas]]/Opex9[[#This Row],[No. Días Arriendo]],0) -> 0 | N6: =IFERROR(Opex9[[#This Row],[Agua]]/Opex9[[#This Row],[No. Días Arriendo]],0) -> 0 | Q6: =+X6 -> 0 | S6: =IFERROR(Opex9[[#This Row],[Energia]]/Opex9[[#This Row],[Consumo (KhW]],0) -> 0 | U6: =IFERROR(Opex9[[#This Row],[Energia]]/Opex9[[#This Row],[No. Días Arriendo]],0) -> 0
B7: Histórico | C7: 43777 | D7: =+TEXT(C7,"mmmm") -> noviembre | E7: 1000000 | G7: =IFERROR(Opex9[[#This Row],[Arriendo]]/Opex9[[#This Row],[No. Días Arriendo]],0) -> 0 | H7: 181790 | I7: =+F6 -> 0 | J7: 201 | K7: =IFERROR(Opex9[[#This Row],[Gas]]/Opex9[[#This Row],[Consumo (m3)]],0) -> 904.42786 | L7: =IFERROR(Opex9[[#This Row],[Gas]]/Opex9[[#This Row],[No. Días Arriendo]],0) -> 0 | N7: =IFERROR(Opex9[[#This Row],[Agua]]/Opex9[[#This Row],[No. Días Arriendo]],0) -> 0 | Q7: =+X7 -> 0 | R7: 805 | S7: =IFERROR(Opex9[[#This Row],[Energia]]/Opex9[[#This Row],[Consumo (KhW]],0) -> 0 | U7: =IFERROR(Opex9[[#This Row],[Energia]]/Opex9[[#This Row],[No. Días Arriendo]],0) -> 0
B8: Histórico | C8: 43806 | D8: =+TEXT(C8,"mmmm") -> diciembre | E8: 1000000 | F8: 31 | G8: =IFERROR(Opex9[[#This Row],[Arriendo]]/Opex9[[#This Row],[No. Días Arriendo]],0) -> 32258.065 | H8: 161900 | I8: =+F7 -> 0 | J8: 187 | K8: =IFERROR(Opex9[[#This Row],[Gas]]/Opex9[[#This Row],[Consumo (m3)]],0) -> 865.7754 | L8: =IFERROR(Opex9[[#This Row],[Gas]]/Opex9[[#This Row],[No. Días Arriendo]],0) -> 5222.5806 | M8: 150000 | N8: =IFERROR(Opex9[[#This Row],[Agua]]/Opex9[[#This Row],[No. Días Arriendo]],0) -> 4838.7097 | O8: 0 | Q8: =+X8 -> 29 | R8: 742 | S8: =IFERROR(Opex9[[#This Row],[Energia]]/Opex9[[#This Row],[Consumo (KhW]],0) -> 0 | T8: 21Nov -20Dic | U8: =IFERROR(Opex9[[#This Row],[Energia]]/Opex9[[#This Row],[No. Días Arriendo]],0) -> 0 | V8: 43790 | W8: 43819 | X8: =+W8-V8 -> 29 | Z8: =+Opex9[[#This Row],[Día Energia]]+Opex9[[#This Row],[Día Gas]]+Opex9[[#This Row],[Día Arriendo]] -> 37480.645
B9: Histórico | C9: 43839 | D9: =+TEXT(C9,"mmmm") -> enero | E9: 1000000 | F9: 31 | G9: =IFERROR(Opex9[[#This Row],[Arriendo]]/Opex9[[#This Row],[No. Días Arriendo]],0) -> 32258.065 | H9: 152570 | I9: =+F8 -> 31 | J9: 168 | K9: =IFERROR(Opex9[[#This Row],[Gas]]/Opex9[[#This Row],[Consumo (m3)]],0) -> 908.15476 | L9: =IFERROR(Opex9[[#This Row],[Gas]]/Opex9[[#This Row],[No. Días Arriendo]],0) -> 4921.6129 | M9: 150000 | N9: =IFERROR(Opex9[[#This Row],[Agua]]/Opex9[[#This Row],[No. Días Arriendo]],0) -> 4838.7097 | O9: 0 | Q9: =+X9 -> 33 | R9: 775 | S9: =IFERROR(Opex9[[#This Row],[Energia]]/Opex9[[#This Row],[Consumo (KhW]],0) -> 0 | T9: 20Dic-22Ene | U9: =IFERROR(Opex9[[#This Row],[Energia]]/Opex9[[#This Row],[No. Días Arriendo]],0) -> 0 | V9: 43819 | W9: 43852 | X9: =+W9-V9 -> 33 | Z9: =+Opex9[[#This Row],[Día Energia]]+Opex9[[#This Row],[Día Gas]]+Opex9[[#This Row],[Día Arriendo]] -> 37179.677
B10: Histórico | C10: 43868 | D10: =+TEXT(C10,"mmmm") -> febrero | E10: 1000000 | F10: 29 | G10: =IFERROR(Opex9[[#This Row],[Arriendo]]/Opex9[[#This Row],[No. Días Arriendo]],0) -> 34482.759 | H10: 155100 | I10: =+F9 -> 31 | J10: 183 | K10: =IFERROR(Opex9[[#This Row],[Gas]]/Opex9[[#This Row],[Consumo (m3)]],0) -> 847.54098 | L10: =IFERROR(Opex9[[#This Row],[Gas]]/Opex9[[#This Row],[No. Días Arriendo]],0) -> 5348.2759 | M10: 150000 | N10: =IFERROR(Opex9[[#This Row],[Agua]]/Opex9[[#This Row],[No. Días Arriendo]],0) -> 5172.4138 | O10: 0 | Q10: =+X10 -> 30 | R10: 521 | S10: =IFERROR(Opex9[[#This Row],[Energia]]/Opex9[[#This Row],[Consumo (KhW]],0) -> 0 | T10: 22Ene-20Feb | U10: =IFERROR(Opex9[[#This Row],[Energia]]/Opex9[[#This Row],[No. Días Arriendo]],0) -> 0 | V10: 43851 | W10: 43881 | X10: =+W10-V10 -> 30 | Z10: =+Opex9[[#This Row],[Día Energia]]+Opex9[[#This Row],[Día Gas]]+Opex9[[#This Row],[Día Arriendo]] -> 39831.034
B11: Histórico | C11: 43897 | D11: =+TEXT(C11,"mmmm") -> marzo | E11: 1000000 | F11: 31 | G11: =IFERROR(Opex9[[#This Row],[Arriendo]]/Opex9[[#This Row],[No. Días Arriendo]],0) -> 32258.065 | H11: 224724 | I11: =+F10 -> 29 | J11: 239 | K11: =IFERROR(Opex9[[#This Row],[Gas]]/Opex9[[#This Row],[Consumo (m3)]],0) -> 940.26778 | L11: =IFERROR(Opex9[[#This Row],[Gas]]/Opex9[[#This Row],[No. Días Arriendo]],0) -> 7249.1613 | M11: 150000 | N11: =IFERROR(Opex9[[#This Row],[Agua]]/Opex9[[#This Row],[No. Días Arriendo]],0) -> 4838.7097 | O11: 0 | Q11: =+X11 -> 28 | R11: 608 | S11: =IFERROR(Opex9[[#This Row],[Energia]]/Opex9[[#This Row],[Consumo (KhW]],0) -> 0 | T11: 20Feb-19Mar | U11: =IFERROR(Opex9[[#This Row],[Energia]]/Opex9[[#This Row],[No. Días Arriendo]],0) -> 0 | V11: 43881 | W11: 43909 | X11: =+W11-V11 -> 28 | Z11: =+Opex9[[#This Row],[Día Energia]]+Opex9[[#This Row],[Día Gas]]+Opex9[[#This Row],[Día Arriendo]] -> 39507.226
B12: Histórico | C12: 43928 | D12: =+TEXT(C12,"mmmm") -> abril | E12: 500000 | F12: 30 | G12: =IFERROR(Opex9[[#This Row],[Arriendo]]/Opex9[[#This Row],[No. Días Arriendo]],0) -> 16666.667 | H12: 102730 | I12: =+F11 -> 31 | J12: 110 | K12: =IFERROR(Opex9[[#This Row],[Gas]]/Opex9[[#This Row],[Consumo (m3)]],0) -> 933.90909 | L12: =IFERROR(Opex9[[#This Row],[Gas]]/Opex9[[#This Row],[No. Días Arriendo]],0) -> 3424.3333 | M12: 150000 | N12: =IFERROR(Opex9[[#This Row],[Agua]]/Opex9[[#This Row],[No. Días Arriendo]],0) -> 5000 | O12: 0 | Q12: =+X12 -> 33 | R12: 757 | S12: =IFERROR(Opex9[[#This Row],[Energia]]/Opex9[[#This Row],[Consumo (KhW]],0) -> 0 | T12: 19Mar-21Abr | U12: =IFERROR(Opex9[[#This Row],[Energia]]/Opex9[[#This Row],[No. Días Arriendo]],0) -> 0 | V12: 43909 | W12: 43942 | X12: =+W12-V12 -> 33 | Z12: =+Opex9[[#This Row],[Día Energia]]+Opex9[[#This Row],[Día Gas]]+Opex9[[#This Row],[Día Arriendo]] -> 20091
B13: Histórico | C13: 43959 | D13: =+TEXT(C13,"mmmm") -> mayo | E13: 500000 | F13: 31 | G13: =IFERROR(Opex9[[#This Row],[Arriendo]]/Opex9[[#This Row],[No. Días Arriendo]],0) -> 16129.032 | H13: 220770 | I13: =+F12 -> 30 | J13: 221 | K13: =IFERROR(Opex9[[#This Row],[Gas]]/Opex9[[#This Row],[Consumo (m3)]],0) -> 998.95928 | L13: =IFERROR(Opex9[[#This Row],[Gas]]/Opex9[[#This Row],[No. Días Arriendo]],0) -> 7121.6129 | M13: 70000 | N13: =IFERROR(Opex9[[#This Row],[Agua]]/Opex9[[#This Row],[No. Días Arriendo]],0) -> 2258.0645 | O13: 0 | P13: 0 | Q13: =+X13 -> 29 | R13: 713 | S13: =IFERROR(Opex9[[#This Row],[Energia]]/Opex9[[#This Row],[Consumo (KhW]],0) -> 0 | T13: 21Abr-20May | U13: =IFERROR(Opex9[[#This Row],[Energia]]/Opex9[[#This Row],[No. Días Arriendo]],0) -> 0 | V13: 43942 | W13: 43971 | X13: =+W13-V13 -> 29 | Z13: =+Opex9[[#This Row],[Día Energia]]+Opex9[[#This Row],[Día Gas]]+Opex9[[#This Row],[Día Arriendo]] -> 23250.645
B14: Forecast | C14: 43990 | D14: =+TEXT(C14,"mmmm") -> junio | E14: 500000 | F14: 30 | G14: =IFERROR(Opex9[[#This Row],[Arriendo]]/Opex9[[#This Row],[No. Días Arriendo]],0) -> 16666.667 | H14: 234638 | I14: =+F13 -> 31 | J14: =+AVERAGE(J11/I11,J12/I12,J13/I13)*Opex9[[#This Row],[No. Días Gas]] -> 197.94981 | K14: =+AVERAGE(K11:K13) -> 957.71205 | L14: =IFERROR(Opex9[[#This Row],[Gas]]/Opex9[[#This Row],[No. Días Arriendo]],0) -> 7821.2667 | M14: 70000 | N14: =IFERROR(Opex9[[#This Row],[Agua]]/Opex9[[#This Row],[No. Días Arriendo]],0) -> 2333.3333 | O14: ='[5]Análisis Energia'!$G$25 -> 220800 | P14: ='[5]Análisis Energia'!$G$24-'[5]Análisis Energia'!$G$25 -> 109770 | Q14: =+X14 -> 30 | R14: =+AVERAGE($O$11/S11,$O$12/S12,$O$13/S13) -> #DIV/0! | S14: =+AVERAGE(S11:S13) -> 0 | T14: 21May-20Jun | U14: =IFERROR(Opex9[[#This Row],[Energia]]/Opex9[[#This Row],[No. Días Arriendo]],0) -> 7360 | V14: 43971 | W14: 44001 | X14: =+W14-V14 -> 30 | Z14: =+Opex9[[#This Row],[Día Energia]]+Opex9[[#This Row],[Día Gas]]+Opex9[[#This Row],[Día Arriendo]] -> 31847.933
B15: Forecast | C15: 44020 | D15: =+TEXT(C15,"mmmm") -> julio | E15: 500000 | F15: 31 | G15: =IFERROR(Opex9[[#This Row],[Arriendo]]/Opex9[[#This Row],[No. Días Arriendo]],0) -> 16129.032 | H15: =+Opex9[[#This Row],[Consumo (m3)]]*Opex9[[#This Row],[Costo prom. Gas]] -> 166695.26 | I15: =+F14 -> 30 | J15: =+AVERAGE(J12/I12,J13/I13,J14/I14)*Opex9[[#This Row],[No. Días Gas]] -> 173.00531 | K15: =+AVERAGE(K12:K14) -> 963.52681 | L15: =IFERROR(Opex9[[#This Row],[Gas]]/Opex9[[#This Row],[No. Días Arriendo]],0) -> 5377.2664 | M15: 110000 | N15: =IFERROR(Opex9[[#This Row],[Agua]]/Opex9[[#This Row],[No. Días Arriendo]],0) -> 3548.3871 | O15: ='[5]Análisis Energia'!$G$25 -> 220800 | P15: ='[5]Análisis Energia'!$F$24/2 -> 367415 | Q15: =+X15 -> 30 | R15: =+AVERAGE($O$11/S12,$O$12/S13,$O$13/S14) -> #DIV/0! | S15: =+AVERAGE(S12:S14) -> 0 | T15: Nd | U15: =IFERROR(Opex9[[#This Row],[Energia]]/Opex9[[#This Row],[No. Días Arriendo]],0) -> 7122.5806 | V15: =+V14+30 -> 44001 | W15: =+V16 -> 44031 | X15: =+W15-V15 -> 30 | Z15: =+Opex9[[#This Row],[Día Energia]]+Opex9[[#This Row],[Día Gas]]+Opex9[[#This Row],[Día Arriendo]] -> 28628.879
B16: Forecast | C16: 44051 | D16: =+TEXT(C16,"mmmm") -> agosto | E16: 500000 | F16: 31 | G16: =IFERROR(Opex9[[#This Row],[Arriendo]]/Opex9[[#This Row],[No. Días Arriendo]],0) -> 16129.032 | H16: =+Opex9[[#This Row],[Consumo (m3)]]*Opex9[[#This Row],[Costo prom. Gas]] -> 196330.97 | I16: =+F15 -> 31 | J16: =+AVERAGE(J13/I13,J14/I14,J15/I15)*Opex9[[#This Row],[No. Días Gas]] -> 201.69621 | K16: =+AVERAGE(K13:K15) -> 973.39938 | L16: =IFERROR(Opex9[[#This Row],[Gas]]/Opex9[[#This Row],[No. Días Arriendo]],0) -> 6333.257 | M16: 110000 | N16: =IFERROR(Opex9[[#This Row],[Agua]]/Opex9[[#This Row],[No. Días Arriendo]],0) -> 3548.3871 | O16: =+O15 -> 220800 | P16: ='[5]Análisis Energia'!$F$24/2 -> 367415 | Q16: =+X16 -> 30 | R16: =+AVERAGE($O$11/S13,$O$12/S14,$O$13/S15) -> #DIV/0! | S16: =+AVERAGE(S13:S15) -> 0 | T16: Nd | U16: =IFERROR(Opex9[[#This Row],[Energia]]/Opex9[[#This Row],[No. Días Arriendo]],0) -> 7122.5806 | V16: =+V15+30 -> 44031 | W16: =+V17 -> 44061 | X16: =+W16-V16 -> 30 | Z16: =+Opex9[[#This Row],[Día Energia]]+Opex9[[#This Row],[Día Gas]]+Opex9[[#This Row],[Día Arriendo]] -> 29584.87
B17: Forecast | C17: 44082 | D17: =+TEXT(C17,"mmmm") -> septiembre | E17: 500000 | F17: 30 | G17: =IFERROR(Opex9[[#This Row],[Arriendo]]/Opex9[[#This Row],[No. Días Arriendo]],0) -> 16666.667 | H17: =+Opex9[[#This Row],[Consumo (m3)]]*Opex9[[#This Row],[Costo prom. Gas]] -> 186034.6 | I17: =+F16 -> 31 | J17: =+AVERAGE(J14/I14,J15/I15,J16/I16)*Opex9[[#This Row],[No. Días Gas]] -> 192.80606 | K17: =+AVERAGE(K14:K16) -> 964.87941 | L17: =IFERROR(Opex9[[#This Row],[Gas]]/Opex9[[#This Row],[No. Días Arriendo]],0) -> 6201.1532 | M17: 110000 | N17: =IFERROR(Opex9[[#This Row],[Agua]]/Opex9[[#This Row],[No. Días Arriendo]],0) -> 3666.6667 | O17: =+O16 -> 220800 | P17: 0 | Q17: =+X17 -> 30 | R17: =+AVERAGE($O$11/S14,$O$12/S15,$O$13/S16) -> #DIV/0! | S17: =+AVERAGE(S14:S16) -> 0 | T17: Nd | U17: =IFERROR(Opex9[[#This Row],[Energia]]/Opex9[[#This Row],[No. Días Arriendo]],0) -> 7360 | V17: =+V16+30 -> 44061 | W17: =+V18 -> 44091 | X17: =+W17-V17 -> 30 | Z17: =+Opex9[[#This Row],[Día Energia]]+Opex9[[#This Row],[Día Gas]]+Opex9[[#This Row],[Día Arriendo]] -> 30227.82
B18: Forecast | C18: 44112 | D18: =+TEXT(C18,"mmmm") -> octubre | E18: 500000 | F18: 31 | G18: =IFERROR(Opex9[[#This Row],[Arriendo]]/Opex9[[#This Row],[No. Días Arriendo]],0) -> 16129.032 | H18: =+Opex9[[#This Row],[Consumo (m3)]]*Opex9[[#This Row],[Costo prom. Gas]] -> 178874.3 | I18: =+F17 -> 30 | J18: =+AVERAGE(J15/I15,J16/I16,J17/I17)*Opex9[[#This Row],[No. Días Gas]] -> 184.92724 | K18: =+AVERAGE(K15:K17) -> 967.26853 | L18: =IFERROR(Opex9[[#This Row],[Gas]]/Opex9[[#This Row],[No. Días Arriendo]],0) -> 5770.1386 | M18: 110000 | N18: =IFERROR(Opex9[[#This Row],[Agua]]/Opex9[[#This Row],[No. Días Arriendo]],0) -> 3548.3871 | O18: =+O17 -> 220800 | P18: 0 | Q18: =+X18 -> 30 | R18: =+AVERAGE($O$11/S15,$O$12/S16,$O$13/S17) -> #DIV/0! | S18: =+AVERAGE(S15:S17) -> 0 | T18: Nd | U18: =IFERROR(Opex9[[#This Row],[Energia]]/Opex9[[#This Row],[No. Días Arriendo]],0) -> 7122.5806 | V18: =+V17+30 -> 44091 | W18: =+V19 -> 44121 | X18: =+W18-V18 -> 30 | Z18: =+Opex9[[#This Row],[Día Energia]]+Opex9[[#This Row],[Día Gas]]+Opex9[[#This Row],[Día Arriendo]] -> 29021.751
B19: Forecast | C19: 44143 | D19: =+TEXT(C19,"mmmm") -> noviembre | E19: 500000 | F19: 30 | G19: =IFERROR(Opex9[[#This Row],[Arriendo]]/Opex9[[#This Row],[No. Días Arriendo]],0) -> 16666.667 | H19: =+Opex9[[#This Row],[Consumo (m3)]]*Opex9[[#This Row],[Costo prom. Gas]] -> 189052.26 | I19: =+F18 -> 31 | J19: =+AVERAGE(J16/I16,J17/I17,J18/I18)*Opex9[[#This Row],[No. Días Gas]] -> 195.19792 | K19: =+AVERAGE(K16:K18) -> 968.51577 | L19: =IFERROR(Opex9[[#This Row],[Gas]]/Opex9[[#This Row],[No. Días Arriendo]],0) -> 6301.742 | M19: 110000 | N19: =IFERROR(Opex9[[#This Row],[Agua]]/Opex9[[#This Row],[No. Días Arriendo]],0) -> 3666.6667 | O19: =+O18 -> 220800 | P19: 0 | Q19: =+X19 -> 30 | R19: =+AVERAGE($O$11/S16,$O$12/S17,$O$13/S18) -> #DIV/0! | S19: =+AVERAGE(S16:S18) -> 0 | T19: Nd | U19: =IFERROR(Opex9[[#This Row],[Energia]]/Opex9[[#This Row],[No. Días Arriendo]],0) -> 7360 | V19: =+V18+30 -> 44121 | W19: =+V20 -> 44151 | X19: =+W19-V19 -> 30 | Z19: =+Opex9[[#This Row],[Día Energia]]+Opex9[[#This Row],[Día Gas]]+Opex9[[#This Row],[Día Arriendo]] -> 30328.409
B20: Forecast | C20: 44173 | D20: =+TEXT(C20,"mmmm") -> diciembre | E20: 500000 | F20: 31 | G20: =IFERROR(Opex9[[#This Row],[Arriendo]]/Opex9[[#This Row],[No. Días Arriendo]],0) -> 16129.032 | H20: =+Opex9[[#This Row],[Consumo (m3)]]*Opex9[[#This Row],[Costo prom. Gas]] -> 180619.48 | I20: =+F19 -> 30 | J20: =+AVERAGE(J17/I17,J18/I18,J19/I19)*Opex9[[#This Row],[No. Días Gas]] -> 186.80498 | K20: =+AVERAGE(K17:K19) -> 966.88791 | L20: =IFERROR(Opex9[[#This Row],[Gas]]/Opex9[[#This Row],[No. Días Arriendo]],0) -> 5826.4348 | M20: 110000 | N20: =IFERROR(Opex9[[#This Row],[Agua]]/Opex9[[#This Row],[No. Días Arriendo]],0) -> 3548.3871 | O20: =+O19 -> 220800 | P20: ='[4]Radicado Energia'!$C37 -> 0 | Q20: =+X20 -> 30 | R20: =+AVERAGE($O$11/S17,$O$12/S18,$O$13/S19) -> #DIV/0! | S20: =+AVERAGE(S17:S19) -> 0 | T20: Nd | U20: =IFERROR(Opex9[[#This Row],[Energia]]/Opex9[[#This Row],[No. Días Arriendo]],0) -> 7122.5806 | V20: =+V19+30 -> 44151 | W20: =+V21 -> 44181 | X20: =+W20-V20 -> 30 | Z20: =+Opex9[[#This Row],[Día Energia]]+Opex9[[#This Row],[Día Gas]]+Opex9[[#This Row],[Día Arriendo]] -> 29078.048
V21: =+V20+30 -> 44181
H23: 2 dia | I23: 240000 | J23: =20000*5 -> 100000 | K23: =+J23*4 -> 400000

Sheet cc

Sheet Misión y visión

Sheet Aliados
C5: Tramites y consultas portal cámara de comercio | D5: https://www.ccb.org.co/Tramites-y-Consultas
C6: Correción | D6: https://www.ccb.org.co/Tramites-y-Consultas/Mas-informacion/Correccion-de-certificados
B7: Gues15 | C7: Actualización | D7: https://muisca.dian.gov.co/WebArquitectura/DefLogin.faces
C8: Pagar certiificado digital | D8: https://linea.ccb.org.co/CertificadosElectronicosR/Index.html#/buscar-inscritos
D10: 20HMVPHI
C12: tramites x correo | D12: https://linea.ccb.org.co/TiendaConsultas/Servicios/Consultas/Default.aspx

Sheet Servicios
B1: GOMEZ GUATIVA VICTOR MANUEL | F1: VICTOR MANUEL GOMEZ GUATIVA
B2: CL 17 SUR 11
B3: TOCANCIPA, VEREDA VERGANZO, Anillo Vial Verganzo, Local esquinero-Frente al parqueadero. - TC VILLA LUZ
B4: VDA EL VERGANZO, ANILLO VIAL VERGANZO - LOCAL ESQUINERO, FRENTE AL PARQUEADERO, FC VILLA LUZ
B5: VDA EL VERGANZO ANILLO VIAL EL VERGANZO ZN FC VILLA LUZ-LOCAL FRENTE AL PARQUEADERO | K5: 20HMVPHI
B6: Anillo Vial Verganzo, Verganza, Tocancipá, Cundinamarca
B7: MP TOCANCIPÁ VD VERGANZO FC VILLA LUZ | F7: Finca

Sheet Fondo-Emprender
A1: Trabajadores | B1: Costo nomina | C1: SLMV | G1: http://www.fondoemprender.com/SitePages/Contactenos.aspx#Cundinamarca
A2: 3 | B2: =($H$3+250000)*A2 -> 3234348 | C2: 80 | D2: =+C2*$H$3 -> 66249280 | F2: =+B2/D2 -> 0.048820878 | H2: SLMV
A3: 5 | B3: =($H$3+250000)*A3 -> 5390580 | C3: 150 | D3: =+C3*$H$3 -> 124217400 | F3: =+B3/D3 -> 0.043396336 | H3: 828116
A4: 6 | B4: =($H$3+250000)*A4 -> 6468696 | C4: 180 | D4: =+C4*$H$3 -> 149060880 | F4: =+B4/D4 -> 0.043396336 | H4: http://www.fondoemprender.com/SitePages/Normatividad.aspx
A6: No | B6: Ciudad: | C6: Dirección: | D6: Email: | E6: Horario: | F6: Líder: | G6: Teléfono: | H6: Centro
A7: 1 | B7: Bogotá | C7: Calle 65 Número 11 – 70 Piso 1. | D7: mdiaza@sena.edu.co | E7: Lunes a Viernes de 8 am - 12 m y 2 pm - 5 pm | F7: Manuel Fernando Díaz Aldana | G7: 5461600 IP: 14487
A8: =+A7+1 -> 2 | B8: Bogotá | C8: Calle 54 Número 10 - 39 Piso 8. | D8: cromerof@sena.edu.co | E8: Lunes a Viernes de 8 am - 12 m y 2 pm - 5 pm | F8: Carolina Romero Figueroa | G8: 5461600 IP: 16843 | H8: Centro de Gestión de Mercados, Logística y Tecnologías de la Información (SENA - Distrito Capital)
A9: =+A8+1 -> 3 | B9: Bogotá | C9: Calle 15 Número 35 - 42 | D9: mariasb@sena.edu.co | E9: Lunes a Viernes de 8 am - 12 m y 2 pm - 5 pm | F9: María del Pilar Arias Bohorquez | G9: 5461600 IP 15591 | H9: Centro para la Industria de la Comunicación Grafica (SENA - Distrito Capital)
A10: =+A9+1 -> 4 | B10: Bogotá | C10: Calle 18 A Número 2 – 18 Sur | D10: ifreyes@sena.edu.co | E10: Lunes a Viernes de 8 am - 12 m y 2 pm - 5 pm | F10: Ivan Fernando Reyes Pérez | G10: 5461600 IP 16593 | H10: Centro de Formación de Talento Humano en Salud (SENA - Distrito Capital)
A11: =+A10+1 -> 5 | B11: Bogotá | C11: Avenida 30 Número 17 B -25 Sur | D11: ygaitan@sena.edu.co | E11: Lunes a Viernes de 8 am - 12 m y 2 pm - 5 pm | F11: Yesid Alejandro Alturo Gaitán | G11: 5461600 IP 15019 | H11: Centro de Manufactura en Textil y Cuero (SENA - Distrito Capital)
A12: =+A11+1 -> 6 | B12: Bogotá | C12: Av. 30 No. 17b--25 Sur | D12: jmonroy@sena.edu.co | E12: Lunes a Viernes de 8 am - 12 m y 2 pm - 5 pm | F12: Jazmin Monroy Cubillos | G12: 5461600 IP 15402 | H12: Centro de Electricidad, Electrónica y Telecomunicaciones (SENA - Distrito Capital)
A13: =+A12+1 -> 7 | B13: Bogotá | C13: Autopista Sur Carrera 4 Número 53 - 54 | D13: njcespedes@sena.edu.co | E13: Lunes a Viernes de 8 am - 12 m y 2 pm - 5 pm | F13: Nestor Javier Cespedes Quevedo | G13: 5461600 IP 18540 | H13: Centro de Tecnologías del Transporte (SENA - Distrito Capital)
A14: =+A13+1 -> 8 | B14: Bogotá | C14: Calle 15 N 31 42 | D14: dsvargasr@sena.edu.co | E14: Lunes a Viernes de 8 am - 12 m y 2 pm - 5 pm | F14: Diana Soraya Vargas Ramírez | G14: 5461600 IP 15531 | H14: Centro de Diseño y Metrología (SENA - Distrito Capital)
A15: =+A14+1 -> 9 | B15: Bogotá | C15: Avenida Caracas Número 13 – 80. | D15: mcastanedaca@sena.edu.co | E15: Lunes a Viernes de 8 am - 12 m y 2 pm - 5 pm | F15: Marcela Castañeda Caicedo | G15: 5461600 IP 16039 | H15: Centro de Gestión Administrativa (SENA - Distrito Capital)
A16: =+A15+1 -> 10 | B16: Bogotá | C16: Carrera 30 Numero 13 53 | D16: mcaycedo@sena.edu.co | E16: Lunes a Viernes de 8 am - 12 m y 2 pm - 5 pm | F16: Magaly Caycedo Molano | G16: 54616004 IP 15560 | H16: Centro Nacional de Hoteleria, Turismo y Alimentos (SENA - Distrito Capital)
A17: =+A16+1 -> 11 | B17: Bogotá | C17: Autopista Sur Carrera 4 Número 53 - 54 | D17: mcharry@sena.edu.co | E17: Lunes a Viernes de 8 am - 12 m y 2 pm - 5 pm | F17: Mauricio Charry Prada | G17: 5461600 IP 18586 | H17: Centro de Tecnologías para la Construcción y la Madera (SENA - Distrito Capital)
A18: =+A17+1 -> 12 | B18: Bogotá | C18: Avenida 30 Número 17 B -25 Sur | D18: lhbuitrago@sena.edu.co | E18: Lunes a Viernes de 8 am - 12 m y 2 pm - 5 pm | F18: Luis Hernando Buitrago Ruiz | G18: 5461600 IP 14955 | H18: Centro Metalmecánico (SENA - Distrito Capital)
A19: =+A18+1 -> 13 | B19: Bogotá | C19: Calle 15 Número 31 - 42 | D19: fsuarezc@sena.edu.co | E19: Lunes a Viernes de 8 am - 12 m y 2 pm - 5 pm | F19: Fabian Ricardo Suarez Contreras | G19: 5461600 IP 15501 | H19: Centro de Gestión Industrial (SENA - Distrito Capital)
... A24: =+A23+1 -> 18 | B24: Bogotá | C24: Carrera 13 No 65-10 | D24: jbetancourt@sena.edu.co | E24: Lunes a Viernes de 8 am - 12 m y 2 pm - 5 pm | F24: Jorge Alberto Betancourt Rodriguez | G24: 594 40 72 - Ext 14415 | H24: Centro de Servicios Financieros (SENA - Distrito Capital)
A25: =+A24+1 -> 19 | B25: Bogotá | C25: Calle 13 no 10 -60 Cazucá | D25: tecnoparquecazucasena@gmail.com | E25: Lunes a Viernes de 8 am - 12 m y 2 pm - 5 pm | F25: Luz Marina Leon Ruiz | G25: 5461500 | H25: TECNO PARQUE CENTRO INDUSTRIAL Y DE DESARROLLO EMPRESARIAL DE SOACHA (TECNO PARQUE CENTRO INDUSTRIAL Y DE DESARROLLO EMPRESARIAL DE SOACHA)
