Workbook
Name Costo_MP: #REF!
Name Cuentas_x_pagar: Pasivos[]
Name Cuentas_x_pagar: Pasivos[]
Name Cuentas_x_pagar: Pasivos[]
Name Efectivo: #REF!
Name SegmentaciónDeDatos_Tipo_día: #N/A
Name Stock_Inventario: #REF!

Sheet Inicio
AA1: 0

Sheet OPEX_SALES
L1: 8 | N1: 24 | O1: 13 | P1: 15 | Q1: 22
A2: Fecha | B2: No. Semana de operación | C2: dia | D2: Tipo día | E2: Tipo día2 | F2: Venta | G2: MG | H2: Rentabilidad | I2: Tipo | J2: Venta PE | K2: Opex | L2: Arriendo | M2: Servicios publicos | N2: Internet | O2: Gas | P2: Agua | Q2: Electricidad | R2: Nomina | S2: Cajero | T2: Parrillero | U2: Domiciliario
A3: 46068 | B3: 0 | C3: =+TEXT(Opex_VE[[#This Row],[Fecha]],"ddd") -> dom | D3: cerrado | E3: D) Domingo | F3: 0 | G3: 0 | H3: =+Opex_VE[[#This Row],[MG]]-Opex_VE[[#This Row],[Opex]] -> 0 | I3: Histórico | J3: =+Opex_VE[[#This Row],[Opex]] -> 0 | K3: 0 | L3: =+VLOOKUP(Opex_VE[[#This Row],[Fecha]],Opex!$B:$Y,OPEX_SALES!L$1,1) -> 61111.111 | M3: =+SUM(Opex_VE[[#This Row],[Internet]:[Electricidad]]) -> 0 | N3: =+VLOOKUP(Opex_VE[[#This Row],[Fecha]],Opex!$B:$Y,OPEX_SALES!N$1,1) -> 0 | O3: =+VLOOKUP(Opex_VE[[#This Row],[Fecha]],Opex!$B:$Y,OPEX_SALES!O$1,1) -> 0 | P3: =+VLOOKUP(Opex_VE[[#This Row],[Fecha]],Opex!$B:$Y,OPEX_SALES!P$1,1) -> 0 | Q3: =+VLOOKUP(Opex_VE[[#This Row],[Fecha]],Opex!$B:$Y,OPEX_SALES!Q$1,1) -> 0 | R3: =+SUM(Opex_VE[[#This Row],[Cajero]:[Domiciliario]]) -> 0 | S3: 0 | T3: 0 | U3: 0
A4: 46069 | B4: 1 | C4: =+TEXT(Opex_VE[[#This Row],[Fecha]],"ddd") -> lun | D4: cerrado | E4: A) Día hábil | F4: 0 | G4: 0 | H4: =+Opex_VE[[#This Row],[MG]]-Opex_VE[[#This Row],[Opex]] -> 0 | I4: Histórico | J4: =+Opex_VE[[#This Row],[Opex]] -> 0 | K4: 0 | L4: =+VLOOKUP(Opex_VE[[#This Row],[Fecha]],Opex!$B:$Y,OPEX_SALES!L$1,1) -> 61111.111 | M4: =+SUM(Opex_VE[[#This Row],[Internet]:[Electricidad]]) -> 0 | N4: =+VLOOKUP(Opex_VE[[#This Row],[Fecha]],Opex!$B:$Y,OPEX_SALES!N$1,1) -> 0 | O4: =+VLOOKUP(Opex_VE[[#This Row],[Fecha]],Opex!$B:$Y,OPEX_SALES!O$1,1) -> 0 | P4: =+VLOOKUP(Opex_VE[[#This Row],[Fecha]],Opex!$B:$Y,OPEX_SALES!P$1,1) -> 0 | Q4: =+VLOOKUP(Opex_VE[[#This Row],[Fecha]],Opex!$B:$Y,OPEX_SALES!Q$1,1) -> 0 | R4: =+SUM(Opex_VE[[#This Row],[Cajero]:[Domiciliario]]) -> 0 | S4: 0 | T4: 0 | U4: 0
A5: 46070 | B5: 1 | C5: =+TEXT(Opex_VE[[#This Row],[Fecha]],"ddd") -> mar | D5: cerrado | E5: A) Día hábil | F5: 0 | G5: 0 | H5: =+Opex_VE[[#This Row],[MG]]-Opex_VE[[#This Row],[Opex]] -> 0 | I5: Histórico | J5: =+Opex_VE[[#This Row],[Opex]] -> 0 | K5: 0 | L5: =+VLOOKUP(Opex_VE[[#This Row],[Fecha]],Opex!$B:$Y,OPEX_SALES!L$1,1) -> 61111.111 | M5: =+SUM(Opex_VE[[#This Row],[Internet]:[Electricidad]]) -> 0 | N5: =+VLOOKUP(Opex_VE[[#This Row],[Fecha]],Opex!$B:$Y,OPEX_SALES!N$1,1) -> 0 | O5: =+VLOOKUP(Opex_VE[[#This Row],[Fecha]],Opex!$B:$Y,OPEX_SALES!O$1,1) -> 0 | P5: =+VLOOKUP(Opex_VE[[#This Row],[Fecha]],Opex!$B:$Y,OPEX_SALES!P$1,1) -> 0 | Q5: =+VLOOKUP(Opex_VE[[#This Row],[Fecha]],Opex!$B:$Y,OPEX_SALES!Q$1,1) -> 0 | R5: =+SUM(Opex_VE[[#This Row],[Cajero]:[Domiciliario]]) -> 0 | S5: 0 | T5: 0 | U5: 0
A6: 46071 | B6: 1 | C6: =+TEXT(Opex_VE[[#This Row],[Fecha]],"ddd") -> mié | D6: cerrado | E6: A) Día hábil | F6: 0 | G6: 0 | H6: =+Opex_VE[[#This Row],[MG]]-Opex_VE[[#This Row],[Opex]] -> 0 | I6: Histórico | J6: =+Opex_VE[[#This Row],[Opex]] -> 0 | K6: 0 | L6: =+VLOOKUP(Opex_VE[[#This Row],[Fecha]],Opex!$B:$Y,OPEX_SALES!L$1,1) -> 61111.111 | M6: =+SUM(Opex_VE[[#This Row],[Internet]:[Electricidad]]) -> 0 | N6: =+VLOOKUP(Opex_VE[[#This Row],[Fecha]],Opex!$B:$Y,OPEX_SALES!N$1,1) -> 0 | O6: =+VLOOKUP(Opex_VE[[#This Row],[Fecha]],Opex!$B:$Y,OPEX_SALES!O$1,1) -> 0 | P6: =+VLOOKUP(Opex_VE[[#This Row],[Fecha]],Opex!$B:$Y,OPEX_SALES!P$1,1) -> 0 | Q6: =+VLOOKUP(Opex_VE[[#This Row],[Fecha]],Opex!$B:$Y,OPEX_SALES!Q$1,1) -> 0 | R6: =+SUM(Opex_VE[[#This Row],[Cajero]:[Domiciliario]]) -> 0 | S6: 0 | T6: 0 | U6: 0
A7: 46072 | B7: 1 | C7: =+TEXT(Opex_VE[[#This Row],[Fecha]],"ddd") -> jue | D7: cerrado | E7: A) Día hábil | F7: 0 | G7: 0 | H7: =+Opex_VE[[#This Row],[MG]]-Opex_VE[[#This Row],[Opex]] -> 0 | I7: Histórico | J7: =+Opex_VE[[#This Row],[Opex]] -> 0 | K7: 0 | L7: =+VLOOKUP(Opex_VE[[#This Row],[Fecha]],Opex!$B:$Y,OPEX_SALES!L$1,1) -> 61111.111 | M7: =+SUM(Opex_VE[[#This Row],[Internet]:[Electricidad]]) -> 0 | N7: =+VLOOKUP(Opex_VE[[#This Row],[Fecha]],Opex!$B:$Y,OPEX_SALES!N$1,1) -> 0 | O7: =+VLOOKUP(Opex_VE[[#This Row],[Fecha]],Opex!$B:$Y,OPEX_SALES!O$1,1) -> 0 | P7: =+VLOOKUP(Opex_VE[[#This Row],[Fecha]],Opex!$B:$Y,OPEX_SALES!P$1,1) -> 0 | Q7: =+VLOOKUP(Opex_VE[[#This Row],[Fecha]],Opex!$B:$Y,OPEX_SALES!Q$1,1) -> 0 | R7: =+SUM(Opex_VE[[#This Row],[Cajero]:[Domiciliario]]) -> 0 | S7: 0 | T7: 0 | U7: 0
A8: 46073 | B8: 1 | C8: =+TEXT(Opex_VE[[#This Row],[Fecha]],"ddd") -> vie | D8: cerrado | E8: B) Viernes | F8: 0 | G8: 0 | H8: =+Opex_VE[[#This Row],[MG]]-Opex_VE[[#This Row],[Opex]] -> 0 | I8: Histórico | J8: =+Opex_VE[[#This Row],[Opex]] -> 0 | K8: 0 | L8: =+VLOOKUP(Opex_VE[[#This Row],[Fecha]],Opex!$B:$Y,OPEX_SALES!L$1,1) -> 61111.111 | M8: =+SUM(Opex_VE[[#This Row],[Internet]:[Electricidad]]) -> 0 | N8: =+VLOOKUP(Opex_VE[[#This Row],[Fecha]],Opex!$B:$Y,OPEX_SALES!N$1,1) -> 0 | O8: =+VLOOKUP(Opex_VE[[#This Row],[Fecha]],Opex!$B:$Y,OPEX_SALES!O$1,1) -> 0 | P8: =+VLOOKUP(Opex_VE[[#This Row],[Fecha]],Opex!$B:$Y,OPEX_SALES!P$1,1) -> 0 | Q8: =+VLOOKUP(Opex_VE[[#This Row],[Fecha]],Opex!$B:$Y,OPEX_SALES!Q$1,1) -> 0 | R8: =+SUM(Opex_VE[[#This Row],[Cajero]:[Domiciliario]]) -> 0 | S8: 0 | T8: 0 | U8: 0
A9: 46074 | B9: 1 | C9: =+TEXT(Opex_VE[[#This Row],[Fecha]],"ddd") -> sáb | D9: cerrado | E9: C) Sábado | F9: 0 | G9: 0 | H9: =+Opex_VE[[#This Row],[MG]]-Opex_VE[[#This Row],[Opex]] -> 0 | I9: Histórico | J9: =+Opex_VE[[#This Row],[Opex]] -> 0 | K9: 0 | L9: =+VLOOKUP(Opex_VE[[#This Row],[Fecha]],Opex!$B:$Y,OPEX_SALES!L$1,1) -> 61111.111 | M9: =+SUM(Opex_VE[[#This Row],[Internet]:[Electricidad]]) -> 0 | N9: =+VLOOKUP(Opex_VE[[#This Row],[Fecha]],Opex!$B:$Y,OPEX_SALES!N$1,1) -> 0 | O9: =+VLOOKUP(Opex_VE[[#This Row],[Fecha]],Opex!$B:$Y,OPEX_SALES!O$1,1) -> 0 | P9: =+VLOOKUP(Opex_VE[[#This Row],[Fecha]],Opex!$B:$Y,OPEX_SALES!P$1,1) -> 0 | Q9: =+VLOOKUP(Opex_VE[[#This Row],[Fecha]],Opex!$B:$Y,OPEX_SALES!Q$1,1) -> 0 | R9: =+SUM(Opex_VE[[#This Row],[Cajero]:[Domiciliario]]) -> 0 | S9: 0 | T9: 0 | U9: 0
A10: 46075 | B10: 1 | C10: =+TEXT(Opex_VE[[#This Row],[Fecha]],"ddd") -> dom | D10: cerrado | E10: D) Domingo | F10: 0 | G10: 0 | H10: =+Opex_VE[[#This Row],[MG]]-Opex_VE[[#This Row],[Opex]] -> 0 | I10: Histórico | J10: =+Opex_VE[[#This Row],[Opex]] -> 0 | K10: 0 | L10: =+VLOOKUP(Opex_VE[[#This Row],[Fecha]],Opex!$B:$Y,OPEX_SALES!L$1,1) -> 61111.111 | M10: =+SUM(Opex_VE[[#This Row],[Internet]:[Electricidad]]) -> 0 | N10: =+VLOOKUP(Opex_VE[[#This Row],[Fecha]],Opex!$B:$Y,OPEX_SALES!N$1,1) -> 0 | O10: =+VLOOKUP(Opex_VE[[#This Row],[Fecha]],Opex!$B:$Y,OPEX_SALES!O$1,1) -> 0 | P10: =+VLOOKUP(Opex_VE[[#This Row],[Fecha]],Opex!$B:$Y,OPEX_SALES!P$1,1) -> 0 | Q10: =+VLOOKUP(Opex_VE[[#This Row],[Fecha]],Opex!$B:$Y,OPEX_SALES!Q$1,1) -> 0 | R10: =+SUM(Opex_VE[[#This Row],[Cajero]:[Domiciliario]]) -> 0 | S10: 0 | T10: 0 | U10: 0
A11: 46082 | B11: 1 | C11: =+TEXT(Opex_VE[[#This Row],[Fecha]],"ddd") -> dom | D11: cerrado | E11: D) Domingo | F11: 0 | G11: 0 | H11: =+Opex_VE[[#This Row],[MG]]-Opex_VE[[#This Row],[Opex]] -> 0 | I11: Histórico | J11: =+Opex_VE[[#This Row],[Opex]] -> 0 | K11: 0 | L11: =+VLOOKUP(Opex_VE[[#This Row],[Fecha]],Opex!$B:$Y,OPEX_SALES!L$1,1) -> 61111.111 | M11: =+SUM(Opex_VE[[#This Row],[Internet]:[Electricidad]]) -> 0 | N11: =+VLOOKUP(Opex_VE[[#This Row],[Fecha]],Opex!$B:$Y,OPEX_SALES!N$1,1) -> 0 | O11: =+VLOOKUP(Opex_VE[[#This Row],[Fecha]],Opex!$B:$Y,OPEX_SALES!O$1,1) -> 0 | P11: =+VLOOKUP(Opex_VE[[#This Row],[Fecha]],Opex!$B:$Y,OPEX_SALES!P$1,1) -> 0 | Q11: =+VLOOKUP(Opex_VE[[#This Row],[Fecha]],Opex!$B:$Y,OPEX_SALES!Q$1,1) -> 0 | R11: =+SUM(Opex_VE[[#This Row],[Cajero]:[Domiciliario]]) -> 0 | S11: 0 | T11: 0 | U11: 0
A12: 46087 | B12: 1 | C12: =+TEXT(Opex_VE[[#This Row],[Fecha]],"ddd") -> vie | D12: cerrado | E12: B) Viernes | F12: 0 | G12: 0 | H12: =+Opex_VE[[#This Row],[MG]]-Opex_VE[[#This Row],[Opex]] -> 0 | I12: Histórico | J12: =+Opex_VE[[#This Row],[Opex]] -> 0 | K12: 0 | L12: =+VLOOKUP(Opex_VE[[#This Row],[Fecha]],Opex!$B:$Y,OPEX_SALES!L$1,1) -> 61111.111 | M12: =+SUM(Opex_VE[[#This Row],[Internet]:[Electricidad]]) -> 0 | N12: =+VLOOKUP(Opex_VE[[#This Row],[Fecha]],Opex!$B:$Y,OPEX_SALES!N$1,1) -> 0 | O12: =+VLOOKUP(Opex_VE[[#This Row],[Fecha]],Opex!$B:$Y,OPEX_SALES!O$1,1) -> 0 | P12: =+VLOOKUP(Opex_VE[[#This Row],[Fecha]],Opex!$B:$Y,OPEX_SALES!P$1,1) -> 0 | Q12: =+VLOOKUP(Opex_VE[[#This Row],[Fecha]],Opex!$B:$Y,OPEX_SALES!Q$1,1) -> 0 | R12: =+SUM(Opex_VE[[#This Row],[Cajero]:[Domiciliario]]) -> 0 | S12: 0 | T12: 0 | U12: 0
A13: 46076 | B13: 1 | C13: =+TEXT(Opex_VE[[#This Row],[Fecha]],"ddd") -> lun | D13: Normal | E13: A) Día hábil | F13: =IFERROR(VLOOKUP(Opex_VE[[#This Row],[Fecha]],Historia!A:B,2,0),_xlfn.XLOOKUP(Opex_VE[[#This Row],[dia]],Forecast!I:I,Forecast!J:J)) -> 225000 | G13: =IFERROR(VLOOKUP(Opex_VE[[#This Row],[Fecha]],Historia!A:C,3,0),_xlfn.XLOOKUP(Opex_VE[[#This Row],[dia]],Forecast!I:I,Forecast!K:K)) -> 90000 | H13: =+Opex_VE[[#This Row],[MG]]-Opex_VE[[#This Row],[Opex]] -> -21111.111 | I13: =IFERROR(VLOOKUP(Opex_VE[[#This Row],[Fecha]],Historia!A:D,4,0),"Forecast") -> Histórico | J13: =+K13/0.4 -> 277777.78 | K13: =+Opex_VE[[#This Row],[Arriendo]]+Opex_VE[[#This Row],[Servicios publicos]]+Opex_VE[[#This Row],[Nomina]] -> 111111.11 | L13: =+VLOOKUP(Opex_VE[[#This Row],[Fecha]],Opex!$B:$Y,OPEX_SALES!L$1,1) -> 61111.111 | M13: =+SUM(Opex_VE[[#This Row],[Internet]:[Electricidad]]) -> 0 | N13: =+VLOOKUP(Opex_VE[[#This Row],[Fecha]],Opex!$B:$Y,OPEX_SALES!N$1,1) -> 0 | O13: =+VLOOKUP(Opex_VE[[#This Row],[Fecha]],Opex!$B:$Y,OPEX_SALES!O$1,1) -> 0 | P13: =+VLOOKUP(Opex_VE[[#This Row],[Fecha]],Opex!$B:$Y,OPEX_SALES!P$1,1) -> 0 | Q13: =+VLOOKUP(Opex_VE[[#This Row],[Fecha]],Opex!$B:$Y,OPEX_SALES!Q$1,1) -> 0 | R13: =+SUM(Opex_VE[[#This Row],[Cajero]:[Domiciliario]]) -> 50000 | S13: 50000 | T13: 0 | U13: 0
A14: 46077 | B14: 1 | C14: =+TEXT(Opex_VE[[#This Row],[Fecha]],"ddd") -> mar | D14: Normal | E14: A) Día hábil | F14: =IFERROR(VLOOKUP(Opex_VE[[#This Row],[Fecha]],Historia!A:B,2,0),_xlfn.XLOOKUP(Opex_VE[[#This Row],[dia]],Forecast!I:I,Forecast!J:J)) -> 221500 | G14: =IFERROR(VLOOKUP(Opex_VE[[#This Row],[Fecha]],Historia!A:C,3,0),_xlfn.XLOOKUP(Opex_VE[[#This Row],[dia]],Forecast!I:I,Forecast!K:K)) -> 88600 | H14: =+Opex_VE[[#This Row],[MG]]-Opex_VE[[#This Row],[Opex]] -> -42511.111 | I14: =IFERROR(VLOOKUP(Opex_VE[[#This Row],[Fecha]],Historia!A:D,4,0),"Forecast") -> Histórico | J14: =+K14/0.4 -> 327777.78 | K14: =+Opex_VE[[#This Row],[Arriendo]]+Opex_VE[[#This Row],[Servicios publicos]]+Opex_VE[[#This Row],[Nomina]] -> 131111.11 | L14: =+VLOOKUP(Opex_VE[[#This Row],[Fecha]],Opex!$B:$Y,OPEX_SALES!L$1,1) -> 61111.111 | M14: =+SUM(Opex_VE[[#This Row],[Internet]:[Electricidad]]) -> 0 | N14: =+VLOOKUP(Opex_VE[[#This Row],[Fecha]],Opex!$B:$Y,OPEX_SALES!N$1,1) -> 0 | O14: =+VLOOKUP(Opex_VE[[#This Row],[Fecha]],Opex!$B:$Y,OPEX_SALES!O$1,1) -> 0 | P14: =+VLOOKUP(Opex_VE[[#This Row],[Fecha]],Opex!$B:$Y,OPEX_SALES!P$1,1) -> 0 | Q14: =+VLOOKUP(Opex_VE[[#This Row],[Fecha]],Opex!$B:$Y,OPEX_SALES!Q$1,1) -> 0 | R14: =+SUM(Opex_VE[[#This Row],[Cajero]:[Domiciliario]]) -> 70000 | S14: 70000 | T14: 0 | U14: 0
A15: 46078 | B15: 1 | C15: =+TEXT(Opex_VE[[#This Row],[Fecha]],"ddd") -> mié | D15: Normal | E15: A) Día hábil | F15: =IFERROR(VLOOKUP(Opex_VE[[#This Row],[Fecha]],Historia!A:B,2,0),_xlfn.XLOOKUP(Opex_VE[[#This Row],[dia]],Forecast!I:I,Forecast!J:J)) -> 390500 | G15: =IFERROR(VLOOKUP(Opex_VE[[#This Row],[Fecha]],Historia!A:C,3,0),_xlfn.XLOOKUP(Opex_VE[[#This Row],[dia]],Forecast!I:I,Forecast!K:K)) -> 156200 | H15: =+Opex_VE[[#This Row],[MG]]-Opex_VE[[#This Row],[Opex]] -> 5088.8889 | I15: =IFERROR(VLOOKUP(Opex_VE[[#This Row],[Fecha]],Historia!A:D,4,0),"Forecast") -> Histórico | J15: =+K15/0.4 -> 377777.78 | K15: =+Opex_VE[[#This Row],[Arriendo]]+Opex_VE[[#This Row],[Servicios publicos]]+Opex_VE[[#This Row],[Nomina]] -> 151111.11 | L15: =+VLOOKUP(Opex_VE[[#This Row],[Fecha]],Opex!$B:$Y,OPEX_SALES!L$1,1) -> 61111.111 | M15: =+SUM(Opex_VE[[#This Row],[Internet]:[Electricidad]]) -> 0 | N15: =+VLOOKUP(Opex_VE[[#This Row],[Fecha]],Opex!$B:$Y,OPEX_SALES!N$1,1) -> 0 | O15: =+VLOOKUP(Opex_VE[[#This Row],[Fecha]],Opex!$B:$Y,OPEX_SALES!O$1,1) -> 0 | P15: =+VLOOKUP(Opex_VE[[#This Row],[Fecha]],Opex!$B:$Y,OPEX_SALES!P$1,1) -> 0 | Q15: =+VLOOKUP(Opex_VE[[#This Row],[Fecha]],Opex!$B:$Y,OPEX_SALES!Q$1,1) -> 0 | R15: =+SUM(Opex_VE[[#This Row],[Cajero]:[Domiciliario]]) -> 90000 | S15: 70000 | T15: 20000 | U15: 0
A16: 46079 | B16: 1 | C16: =+TEXT(Opex_VE[[#This Row],[Fecha]],"ddd") -> jue | E16: A) Día hábil | F16: =IFERROR(VLOOKUP(Opex_VE[[#This Row],[Fecha]],Historia!A:B,2,0),_xlfn.XLOOKUP(Opex_VE[[#This Row],[dia]],Forecast!I:I,Forecast!J:J)) -> 209000 | G16: =IFERROR(VLOOKUP(Opex_VE[[#This Row],[Fecha]],Historia!A:C,3,0),_xlfn.XLOOKUP(Opex_VE[[#This Row],[dia]],Forecast!I:I,Forecast!K:K)) -> 83600 | H16: =+Opex_VE[[#This Row],[MG]]-Opex_VE[[#This Row],[Opex]] -> -67511.111 | I16: =IFERROR(VLOOKUP(Opex_VE[[#This Row],[Fecha]],Historia!A:D,4,0),"Forecast") -> Histórico | J16: =+K16/0.4 -> 377777.78 | K16: =+Opex_VE[[#This Row],[Arriendo]]+Opex_VE[[#This Row],[Servicios publicos]]+Opex_VE[[#This Row],[Nomina]] -> 151111.11 | L16: =+VLOOKUP(Opex_VE[[#This Row],[Fecha]],Opex!$B:$Y,OPEX_SALES!L$1,1) -> 61111.111 | M16: =+SUM(Opex_VE[[#This Row],[Internet]:[Electricidad]]) -> 0 | N16: =+VLOOKUP(Opex_VE[[#This Row],[Fecha]],Opex!$B:$Y,OPEX_SALES!N$1,1) -> 0 | O16: =+VLOOKUP(Opex_VE[[#This Row],[Fecha]],Opex!$B:$Y,OPEX_SALES!O$1,1) -> 0 | P16: =+VLOOKUP(Opex_VE[[#This Row],[Fecha]],Opex!$B:$Y,OPEX_SALES!P$1,1) -> 0 | Q16: =+VLOOKUP(Opex_VE[[#This Row],[Fecha]],Opex!$B:$Y,OPEX_SALES!Q$1,1) -> 0 | R16: =+SUM(Opex_VE[[#This Row],[Cajero]:[Domiciliario]]) -> 90000 | S16: 70000 | T16: 20000 | U16: 0
A17: 46080 | B17: 1 | C17: =+TEXT(Opex_VE[[#This Row],[Fecha]],"ddd") -> vie | E17: B) Viernes | F17: =IFERROR(VLOOKUP(Opex_VE[[#This Row],[Fecha]],Historia!A:B,2,0),_xlfn.XLOOKUP(Opex_VE[[#This Row],[dia]],Forecast!I:I,Forecast!J:J)) -> 248500 | G17: =IFERROR(VLOOKUP(Opex_VE[[#This Row],[Fecha]],Historia!A:C,3,0),_xlfn.XLOOKUP(Opex_VE[[#This Row],[dia]],Forecast!I:I,Forecast!K:K)) -> 99400 | H17: =+Opex_VE[[#This Row],[MG]]-Opex_VE[[#This Row],[Opex]] -> -51711.111 | I17: =IFERROR(VLOOKUP(Opex_VE[[#This Row],[Fecha]],Historia!A:D,4,0),"Forecast") -> Histórico | J17: =+K17/0.4 -> 377777.78 | K17: =+Opex_VE[[#This Row],[Arriendo]]+Opex_VE[[#This Row],[Servicios publicos]]+Opex_VE[[#This Row],[Nomina]] -> 151111.11 | L17: =+VLOOKUP(Opex_VE[[#This Row],[Fecha]],Opex!$B:$Y,OPEX_SALES!L$1,1) -> 61111.111 | M17: =+SUM(Opex_VE[[#This Row],[Internet]:[Electricidad]]) -> 0 | N17: =+VLOOKUP(Opex_VE[[#This Row],[Fecha]],Opex!$B:$Y,OPEX_SALES!N$1,1) -> 0 | O17: =+VLOOKUP(Opex_VE[[#This Row],[Fecha]],Opex!$B:$Y,OPEX_SALES!O$1,1) -> 0 | P17: =+VLOOKUP(Opex_VE[[#This Row],[Fecha]],Opex!$B:$Y,OPEX_SALES!P$1,1) -> 0 | Q17: =+VLOOKUP(Opex_VE[[#This Row],[Fecha]],Opex!$B:$Y,OPEX_SALES!Q$1,1) -> 0 | R17: =+SUM(Opex_VE[[#This Row],[Cajero]:[Domiciliario]]) -> 90000 | S17: 70000 | T17: 20000 | U17: 0
A18: 46081 | B18: 1 | C18: =+TEXT(Opex_VE[[#This Row],[Fecha]],"ddd") -> sáb | E18: C) Sábado | F18: =IFERROR(VLOOKUP(Opex_VE[[#This Row],[Fecha]],Historia!A:B,2,0),_xlfn.XLOOKUP(Opex_VE[[#This Row],[dia]],Forecast!I:I,Forecast!J:J)) -> 504000 | G18: =IFERROR(VLOOKUP(Opex_VE[[#This Row],[Fecha]],Historia!A:C,3,0),_xlfn.XLOOKUP(Opex_VE[[#This Row],[dia]],Forecast!I:I,Forecast!K:K)) -> 201600 | H18: =+Opex_VE[[#This Row],[MG]]-Opex_VE[[#This Row],[Opex]] -> 50488.889 | I18: =IFERROR(VLOOKUP(Opex_VE[[#This Row],[Fecha]],Historia!A:D,4,0),"Forecast") -> Histórico | J18: =+K18/0.4 -> 377777.78 | K18: =+Opex_VE[[#This Row],[Arriendo]]+Opex_VE[[#This Row],[Servicios publicos]]+Opex_VE[[#This Row],[Nomina]] -> 151111.11 | L18: =+VLOOKUP(Opex_VE[[#This Row],[Fecha]],Opex!$B:$Y,OPEX_SALES!L$1,1) -> 61111.111 | M18: =+SUM(Opex_VE[[#This Row],[Internet]:[Electricidad]]) -> 0 | N18: =+VLOOKUP(Opex_VE[[#This Row],[Fecha]],Opex!$B:$Y,OPEX_SALES!N$1,1) -> 0 | O18: =+VLOOKUP(Opex_VE[[#This Row],[Fecha]],Opex!$B:$Y,OPEX_SALES!O$1,1) -> 0 | P18: =+VLOOKUP(Opex_VE[[#This Row],[Fecha]],Opex!$B:$Y,OPEX_SALES!P$1,1) -> 0 | Q18: =+VLOOKUP(Opex_VE[[#This Row],[Fecha]],Opex!$B:$Y,OPEX_SALES!Q$1,1) -> 0 | R18: =+SUM(Opex_VE[[#This Row],[Cajero]:[Domiciliario]]) -> 90000 | S18: 70000 | T18: 20000 | U18: 0
A19: 46082 | B19: 1 | C19: =+TEXT(Opex_VE[[#This Row],[Fecha]],"ddd") -> dom | E19: D) Domingo | F19: =IFERROR(VLOOKUP(Opex_VE[[#This Row],[Fecha]],Historia!A:B,2,0),_xlfn.XLOOKUP(Opex_VE[[#This Row],[dia]],Forecast!I:I,Forecast!J:J)) -> 168750 | G19: =IFERROR(VLOOKUP(Opex_VE[[#This Row],[Fecha]],Historia!A:C,3,0),_xlfn.XLOOKUP(Opex_VE[[#This Row],[dia]],Forecast!I:I,Forecast!K:K)) -> 67500 | H19: =+Opex_VE[[#This Row],[MG]]-Opex_VE[[#This Row],[Opex]] -> 6388.8889 | I19: Histórico | J19: =+K19/0.4 -> 152777.78 | K19: =+Opex_VE[[#This Row],[Arriendo]]+Opex_VE[[#This Row],[Servicios publicos]]+Opex_VE[[#This Row],[Nomina]] -> 61111.111 | L19: =+VLOOKUP(Opex_VE[[#This Row],[Fecha]],Opex!$B:$Y,OPEX_SALES!L$1,1) -> 61111.111 | M19: =+SUM(Opex_VE[[#This Row],[Internet]:[Electricidad]]) -> 0 | N19: =+VLOOKUP(Opex_VE[[#This Row],[Fecha]],Opex!$B:$Y,OPEX_SALES!N$1,1) -> 0 | O19: =+VLOOKUP(Opex_VE[[#This Row],[Fecha]],Opex!$B:$Y,OPEX_SALES!O$1,1) -> 0 | P19: =+VLOOKUP(Opex_VE[[#This Row],[Fecha]],Opex!$B:$Y,OPEX_SALES!P$1,1) -> 0 | Q19: =+VLOOKUP(Opex_VE[[#This Row],[Fecha]],Opex!$B:$Y,OPEX_SALES!Q$1,1) -> 0 | R19: =+SUM(Opex_VE[[#This Row],[Cajero]:[Domiciliario]]) -> 0 | S19: 0 | T19: 0 | U19: 0
A20: 46083 | B20: =+B13+1 -> 2 | C20: =+TEXT(Opex_VE[[#This Row],[Fecha]],"ddd") -> lun | E20: A) Día hábil | F20: =IFERROR(VLOOKUP(Opex_VE[[#This Row],[Fecha]],Historia!A:B,2,0),_xlfn.XLOOKUP(Opex_VE[[#This Row],[dia]],Forecast!I:I,Forecast!J:J)) -> 60000 | G20: =IFERROR(VLOOKUP(Opex_VE[[#This Row],[Fecha]],Historia!A:C,3,0),_xlfn.XLOOKUP(Opex_VE[[#This Row],[dia]],Forecast!I:I,Forecast!K:K)) -> 24000 | H20: =+Opex_VE[[#This Row],[MG]]-Opex_VE[[#This Row],[Opex]] -> -57111.111 | I20: =IFERROR(VLOOKUP(Opex_VE[[#This Row],[Fecha]],Historia!A:D,4,0),"Forecast") -> Histórico | J20: =+K20/0.4 -> 202777.78 | K20: =+Opex_VE[[#This Row],[Arriendo]]+Opex_VE[[#This Row],[Servicios publicos]]+Opex_VE[[#This Row],[Nomina]] -> 81111.111 | L20: =+VLOOKUP(Opex_VE[[#This Row],[Fecha]],Opex!$B:$Y,OPEX_SALES!L$1,1) -> 61111.111 | M20: =+SUM(Opex_VE[[#This Row],[Internet]:[Electricidad]]) -> 0 | N20: =+VLOOKUP(Opex_VE[[#This Row],[Fecha]],Opex!$B:$Y,OPEX_SALES!N$1,1) -> 0 | O20: =+VLOOKUP(Opex_VE[[#This Row],[Fecha]],Opex!$B:$Y,OPEX_SALES!O$1,1) -> 0 | P20: =+VLOOKUP(Opex_VE[[#This Row],[Fecha]],Opex!$B:$Y,OPEX_SALES!P$1,1) -> 0 | Q20: =+VLOOKUP(Opex_VE[[#This Row],[Fecha]],Opex!$B:$Y,OPEX_SALES!Q$1,1) -> 0 | R20: =+SUM(Opex_VE[[#This Row],[Cajero]:[Domiciliario]]) -> 20000 | S20: 0 | T20: 20000 | U20: 0
A21: 46084 | B21: =+B14+1 -> 2 | C21: =+TEXT(Opex_VE[[#This Row],[Fecha]],"ddd") -> mar | E21: A) Día hábil | F21: =IFERROR(VLOOKUP(Opex_VE[[#This Row],[Fecha]],Historia!A:B,2,0),_xlfn.XLOOKUP(Opex_VE[[#This Row],[dia]],Forecast!I:I,Forecast!J:J)) -> 169000 | G21: =IFERROR(VLOOKUP(Opex_VE[[#This Row],[Fecha]],Historia!A:C,3,0),_xlfn.XLOOKUP(Opex_VE[[#This Row],[dia]],Forecast!I:I,Forecast!K:K)) -> 67600 | H21: =+Opex_VE[[#This Row],[MG]]-Opex_VE[[#This Row],[Opex]] -> -13511.111 | I21: =IFERROR(VLOOKUP(Opex_VE[[#This Row],[Fecha]],Historia!A:D,4,0),"Forecast") -> Histórico | J21: =+K21/0.4 -> 202777.78 | K21: =+Opex_VE[[#This Row],[Arriendo]]+Opex_VE[[#This Row],[Servicios publicos]]+Opex_VE[[#This Row],[Nomina]] -> 81111.111 | L21: =+VLOOKUP(Opex_VE[[#This Row],[Fecha]],Opex!$B:$Y,OPEX_SALES!L$1,1) -> 61111.111 | M21: =+SUM(Opex_VE[[#This Row],[Internet]:[Electricidad]]) -> 0 | N21: =+VLOOKUP(Opex_VE[[#This Row],[Fecha]],Opex!$B:$Y,OPEX_SALES!N$1,1) -> 0 | O21: =+VLOOKUP(Opex_VE[[#This Row],[Fecha]],Opex!$B:$Y,OPEX_SALES!O$1,1) -> 0 | P21: =+VLOOKUP(Opex_VE[[#This Row],[Fecha]],Opex!$B:$Y,OPEX_SALES!P$1,1) -> 0 | Q21: =+VLOOKUP(Opex_VE[[#This Row],[Fecha]],Opex!$B:$Y,OPEX_SALES!Q$1,1) -> 0 | R21: =+SUM(Opex_VE[[#This Row],[Cajero]:[Domiciliario]]) -> 20000 | S21: 0 | T21: 20000 | U21: 0
A22: 46085 | B22: =+B15+1 -> 2 | C22: =+TEXT(Opex_VE[[#This Row],[Fecha]],"ddd") -> mié | E22: A) Día hábil | F22: =IFERROR(VLOOKUP(Opex_VE[[#This Row],[Fecha]],Historia!A:B,2,0),_xlfn.XLOOKUP(Opex_VE[[#This Row],[dia]],Forecast!I:I,Forecast!J:J)) -> 344000 | G22: =IFERROR(VLOOKUP(Opex_VE[[#This Row],[Fecha]],Historia!A:C,3,0),_xlfn.XLOOKUP(Opex_VE[[#This Row],[dia]],Forecast!I:I,Forecast!K:K)) -> 137600 | H22: =+Opex_VE[[#This Row],[MG]]-Opex_VE[[#This Row],[Opex]] -> 56488.889 | I22: =IFERROR(VLOOKUP(Opex_VE[[#This Row],[Fecha]],Historia!A:D,4,0),"Forecast") -> Histórico | J22: =+K22/0.4 -> 202777.78 | K22: =+Opex_VE[[#This Row],[Arriendo]]+Opex_VE[[#This Row],[Servicios publicos]]+Opex_VE[[#This Row],[Nomina]] -> 81111.111 | L22: =+VLOOKUP(Opex_VE[[#This Row],[Fecha]],Opex!$B:$Y,OPEX_SALES!L$1,1) -> 61111.111 | M22: =+SUM(Opex_VE[[#This Row],[Internet]:[Electricidad]]) -> 0 | N22: =+VLOOKUP(Opex_VE[[#This Row],[Fecha]],Opex!$B:$Y,OPEX_SALES!N$1,1) -> 0 | O22: =+VLOOKUP(Opex_VE[[#This Row],[Fecha]],Opex!$B:$Y,OPEX_SALES!O$1,1) -> 0 | P22: =+VLOOKUP(Opex_VE[[#This Row],[Fecha]],Opex!$B:$Y,OPEX_SALES!P$1,1) -> 0 | Q22: =+VLOOKUP(Opex_VE[[#This Row],[Fecha]],Opex!$B:$Y,OPEX_SALES!Q$1,1) -> 0 | R22: =+SUM(Opex_VE[[#This Row],[Cajero]:[Domiciliario]]) -> 20000 | S22: 0 | T22: 20000 | U22: 0
A23: 46086 | B23: =+B16+1 -> 2 | C23: =+TEXT(Opex_VE[[#This Row],[Fecha]],"ddd") -> jue | E23: A) Día hábil | F23: =IFERROR(VLOOKUP(Opex_VE[[#This Row],[Fecha]],Historia!A:B,2,0),_xlfn.XLOOKUP(Opex_VE[[#This Row],[dia]],Forecast!I:I,Forecast!J:J)) -> 259000 | G23: =IFERROR(VLOOKUP(Opex_VE[[#This Row],[Fecha]],Historia!A:C,3,0),_xlfn.XLOOKUP(Opex_VE[[#This Row],[dia]],Forecast!I:I,Forecast!K:K)) -> 103600 | H23: =+Opex_VE[[#This Row],[MG]]-Opex_VE[[#This Row],[Opex]] -> 22488.889 | I23: =IFERROR(VLOOKUP(Opex_VE[[#This Row],[Fecha]],Historia!A:D,4,0),"Forecast") -> Histórico | J23: =+K23/0.4 -> 202777.78 | K23: =+Opex_VE[[#This Row],[Arriendo]]+Opex_VE[[#This Row],[Servicios publicos]]+Opex_VE[[#This Row],[Nomina]] -> 81111.111 | L23: =+VLOOKUP(Opex_VE[[#This Row],[Fecha]],Opex!$B:$Y,OPEX_SALES!L$1,1) -> 61111.111 | M23: =+SUM(Opex_VE[[#This Row],[Internet]:[Electricidad]]) -> 0 | N23: =+VLOOKUP(Opex_VE[[#This Row],[Fecha]],Opex!$B:$Y,OPEX_SALES!N$1,1) -> 0 | O23: =+VLOOKUP(Opex_VE[[#This Row],[Fecha]],Opex!$B:$Y,OPEX_SALES!O$1,1) -> 0 | P23: =+VLOOKUP(Opex_VE[[#This Row],[Fecha]],Opex!$B:$Y,OPEX_SALES!P$1,1) -> 0 | Q23: =+VLOOKUP(Opex_VE[[#This Row],[Fecha]],Opex!$B:$Y,OPEX_SALES!Q$1,1) -> 0 | R23: =+SUM(Opex_VE[[#This Row],[Cajero]:[Domiciliario]]) -> 20000 | S23: 0 | T23: 20000 | U23: 0
A24: 46087 | B24: =+B17+1 -> 2 | C24: =+TEXT(Opex_VE[[#This Row],[Fecha]],"ddd") -> vie | E24: E) Festivo | F24: =IFERROR(VLOOKUP(Opex_VE[[#This Row],[Fecha]],Historia!A:B,2,0),_xlfn.XLOOKUP(Opex_VE[[#This Row],[dia]],Forecast!I:I,Forecast!J:J)) -> 184566.67 | G24: =IFERROR(VLOOKUP(Opex_VE[[#This Row],[Fecha]],Historia!A:C,3,0),_xlfn.XLOOKUP(Opex_VE[[#This Row],[dia]],Forecast!I:I,Forecast!K:K)) -> 73826.667 | H24: =+Opex_VE[[#This Row],[MG]]-Opex_VE[[#This Row],[Opex]] -> 12715.556 | I24: =IFERROR(VLOOKUP(Opex_VE[[#This Row],[Fecha]],Historia!A:D,4,0),"Forecast") -> Forecast | J24: =+K24/0.4 -> 152777.78 | K24: =+Opex_VE[[#This Row],[Arriendo]]+Opex_VE[[#This Row],[Servicios publicos]]+Opex_VE[[#This Row],[Nomina]] -> 61111.111 | L24: =+VLOOKUP(Opex_VE[[#This Row],[Fecha]],Opex!$B:$Y,OPEX_SALES!L$1,1) -> 61111.111 | M24: =+SUM(Opex_VE[[#This Row],[Internet]:[Electricidad]]) -> 0 | N24: =+VLOOKUP(Opex_VE[[#This Row],[Fecha]],Opex!$B:$Y,OPEX_SALES!N$1,1) -> 0 | O24: =+VLOOKUP(Opex_VE[[#This Row],[Fecha]],Opex!$B:$Y,OPEX_SALES!O$1,1) -> 0 | P24: =+VLOOKUP(Opex_VE[[#This Row],[Fecha]],Opex!$B:$Y,OPEX_SALES!P$1,1) -> 0 | Q24: =+VLOOKUP(Opex_VE[[#This Row],[Fecha]],Opex!$B:$Y,OPEX_SALES!Q$1,1) -> 0 | R24: =+SUM(Opex_VE[[#This Row],[Cajero]:[Domiciliario]]) -> 0 | S24: 0 | T24: 0 | U24: 0
A25: 46088 | B25: =+B18+1 -> 2 | C25: =+TEXT(Opex_VE[[#This Row],[Fecha]],"ddd") -> sáb | E25: C) Sábado | F25: =IFERROR(VLOOKUP(Opex_VE[[#This Row],[Fecha]],Historia!A:B,2,0),_xlfn.XLOOKUP(Opex_VE[[#This Row],[dia]],Forecast!I:I,Forecast!J:J)) -> 298500 | G25: =IFERROR(VLOOKUP(Opex_VE[[#This Row],[Fecha]],Historia!A:C,3,0),_xlfn.XLOOKUP(Opex_VE[[#This Row],[dia]],Forecast!I:I,Forecast!K:K)) -> 119400 | H25: =+Opex_VE[[#This Row],[MG]]-Opex_VE[[#This Row],[Opex]] -> -33711.111 | I25: Histórico | J25: =+K25/0.4 -> 382777.78 | K25: =+Opex_VE[[#This Row],[Arriendo]]+Opex_VE[[#This Row],[Servicios publicos]]+Opex_VE[[#This Row],[Nomina]] -> 153111.11 | L25: =+VLOOKUP(Opex_VE[[#This Row],[Fecha]],Opex!$B:$Y,OPEX_SALES!L$1,1) -> 61111.111 | M25: =+SUM(Opex_VE[[#This Row],[Internet]:[Electricidad]]) -> 0 | N25: =+VLOOKUP(Opex_VE[[#This Row],[Fecha]],Opex!$B:$Y,OPEX_SALES!N$1,1) -> 0 | O25: =+VLOOKUP(Opex_VE[[#This Row],[Fecha]],Opex!$B:$Y,OPEX_SALES!O$1,1) -> 0 | P25: =+VLOOKUP(Opex_VE[[#This Row],[Fecha]],Opex!$B:$Y,OPEX_SALES!P$1,1) -> 0 | Q25: =+VLOOKUP(Opex_VE[[#This Row],[Fecha]],Opex!$B:$Y,OPEX_SALES!Q$1,1) -> 0 | R25: =+SUM(Opex_VE[[#This Row],[Cajero]:[Domiciliario]]) -> 92000 | S25: 70000 | T25: 22000 | U25: 0
A26: 46089 | B26: =+B19+1 -> 2 | C26: =+TEXT(Opex_VE[[#This Row],[Fecha]],"ddd") -> dom | E26: D) Domingo | F26: =IFERROR(VLOOKUP(Opex_VE[[#This Row],[Fecha]],Historia!A:B,2,0),_xlfn.XLOOKUP(Opex_VE[[#This Row],[dia]],Forecast!I:I,Forecast!J:J)) -> 219500 | G26: =IFERROR(VLOOKUP(Opex_VE[[#This Row],[Fecha]],Historia!A:C,3,0),_xlfn.XLOOKUP(Opex_VE[[#This Row],[dia]],Forecast!I:I,Forecast!K:K)) -> 87800 | H26: =+Opex_VE[[#This Row],[MG]]-Opex_VE[[#This Row],[Opex]] -> -3311.1111 | I26: =IFERROR(VLOOKUP(Opex_VE[[#This Row],[Fecha]],Historia!A:D,4,0),"Forecast") -> Histórico | J26: =+K26/0.4 -> 227777.78 | K26: =+Opex_VE[[#This Row],[Arriendo]]+Opex_VE[[#This Row],[Servicios publicos]]+Opex_VE[[#This Row],[Nomina]] -> 91111.111 | L26: =+VLOOKUP(Opex_VE[[#This Row],[Fecha]],Opex!$B:$Y,OPEX_SALES!L$1,1) -> 61111.111 | M26: =+SUM(Opex_VE[[#This Row],[Internet]:[Electricidad]]) -> 0 | N26: =+VLOOKUP(Opex_VE[[#This Row],[Fecha]],Opex!$B:$Y,OPEX_SALES!N$1,1) -> 0 | O26: =+VLOOKUP(Opex_VE[[#This Row],[Fecha]],Opex!$B:$Y,OPEX_SALES!O$1,1) -> 0 | P26: =+VLOOKUP(Opex_VE[[#This Row],[Fecha]],Opex!$B:$Y,OPEX_SALES!P$1,1) -> 0 | Q26: =+VLOOKUP(Opex_VE[[#This Row],[Fecha]],Opex!$B:$Y,OPEX_SALES!Q$1,1) -> 0 | R26: =+SUM(Opex_VE[[#This Row],[Cajero]:[Domiciliario]]) -> 30000 | S26: 20000 | T26: 10000 | U26: 0
A27: 46090 | B27: =+B20+1 -> 3 | C27: =+TEXT(Opex_VE[[#This Row],[Fecha]],"ddd") -> lun | E27: A) Día hábil | F27: =IFERROR(VLOOKUP(Opex_VE[[#This Row],[Fecha]],Historia!A:B,2,0),_xlfn.XLOOKUP(Opex_VE[[#This Row],[dia]],Forecast!I:I,Forecast!J:J)) -> 248500 | G27: =IFERROR(VLOOKUP(Opex_VE[[#This Row],[Fecha]],Historia!A:C,3,0),_xlfn.XLOOKUP(Opex_VE[[#This Row],[dia]],Forecast!I:I,Forecast!K:K)) -> 99400 | H27: =+Opex_VE[[#This Row],[MG]]-Opex_VE[[#This Row],[Opex]] -> -11711.111 | I27: =IFERROR(VLOOKUP(Opex_VE[[#This Row],[Fecha]],Historia!A:D,4,0),"Forecast") -> Histórico | J27: =+K27/0.4 -> 277777.78 | K27: =+Opex_VE[[#This Row],[Arriendo]]+Opex_VE[[#This Row],[Servicios publicos]]+Opex_VE[[#This Row],[Nomina]] -> 111111.11 | L27: =+VLOOKUP(Opex_VE[[#This Row],[Fecha]],Opex!$B:$Y,OPEX_SALES!L$1,1) -> 61111.111 | M27: =+SUM(Opex_VE[[#This Row],[Internet]:[Electricidad]]) -> 0 | N27: =+VLOOKUP(Opex_VE[[#This Row],[Fecha]],Opex!$B:$Y,OPEX_SALES!N$1,1) -> 0 | O27: =+VLOOKUP(Opex_VE[[#This Row],[Fecha]],Opex!$B:$Y,OPEX_SALES!O$1,1) -> 0 | P27: =+VLOOKUP(Opex_VE[[#This Row],[Fecha]],Opex!$B:$Y,OPEX_SALES!P$1,1) -> 0 | Q27: =+VLOOKUP(Opex_VE[[#This Row],[Fecha]],Opex!$B:$Y,OPEX_SALES!Q$1,1) -> 0 | R27: =+SUM(Opex_VE[[#This Row],[Cajero]:[Domiciliario]]) -> 50000 | S27: 30000 | T27: 20000 | U27: 0
A28: 46091 | B28: =+B21+1 -> 3 | C28: =+TEXT(Opex_VE[[#This Row],[Fecha]],"ddd") -> mar | E28: A) Día hábil | F28: =IFERROR(VLOOKUP(Opex_VE[[#This Row],[Fecha]],Historia!A:B,2,0),_xlfn.XLOOKUP(Opex_VE[[#This Row],[dia]],Forecast!I:I,Forecast!J:J)) -> 94000 | G28: =IFERROR(VLOOKUP(Opex_VE[[#This Row],[Fecha]],Historia!A:C,3,0),_xlfn.XLOOKUP(Opex_VE[[#This Row],[dia]],Forecast!I:I,Forecast!K:K)) -> 37600 | H28: =+Opex_VE[[#This Row],[MG]]-Opex_VE[[#This Row],[Opex]] -> -73511.111 | I28: =IFERROR(VLOOKUP(Opex_VE[[#This Row],[Fecha]],Historia!A:D,4,0),"Forecast") -> Histórico | J28: =+K28/0.4 -> 277777.78 | K28: =+Opex_VE[[#This Row],[Arriendo]]+Opex_VE[[#This Row],[Servicios publicos]]+Opex_VE[[#This Row],[Nomina]] -> 111111.11 | L28: =+VLOOKUP(Opex_VE[[#This Row],[Fecha]],Opex!$B:$Y,OPEX_SALES!L$1,1) -> 61111.111 | M28: =+SUM(Opex_VE[[#This Row],[Internet]:[Electricidad]]) -> 0 | N28: =+VLOOKUP(Opex_VE[[#This Row],[Fecha]],Opex!$B:$Y,OPEX_SALES!N$1,1) -> 0 | O28: =+VLOOKUP(Opex_VE[[#This Row],[Fecha]],Opex!$B:$Y,OPEX_SALES!O$1,1) -> 0 | P28: =+VLOOKUP(Opex_VE[[#This Row],[Fecha]],Opex!$B:$Y,OPEX_SALES!P$1,1) -> 0 | Q28: =+VLOOKUP(Opex_VE[[#This Row],[Fecha]],Opex!$B:$Y,OPEX_SALES!Q$1,1) -> 0 | R28: =+SUM(Opex_VE[[#This Row],[Cajero]:[Domiciliario]]) -> 50000 | S28: 30000 | T28: 20000 | U28: 0
A29: 46092 | B29: =+B22+1 -> 3 | C29: =+TEXT(Opex_VE[[#This Row],[Fecha]],"ddd") -> mié | E29: A) Día hábil | F29: =IFERROR(VLOOKUP(Opex_VE[[#This Row],[Fecha]],Historia!A:B,2,0),_xlfn.XLOOKUP(Opex_VE[[#This Row],[dia]],Forecast!I:I,Forecast!J:J)) -> 473500 | G29: =IFERROR(VLOOKUP(Opex_VE[[#This Row],[Fecha]],Historia!A:C,3,0),_xlfn.XLOOKUP(Opex_VE[[#This Row],[dia]],Forecast!I:I,Forecast!K:K)) -> 189400 | H29: =+Opex_VE[[#This Row],[MG]]-Opex_VE[[#This Row],[Opex]] -> 88288.889 | I29: =IFERROR(VLOOKUP(Opex_VE[[#This Row],[Fecha]],Historia!A:D,4,0),"Forecast") -> Histórico | J29: =+K29/0.4 -> 252777.78 | K29: =+Opex_VE[[#This Row],[Arriendo]]+Opex_VE[[#This Row],[Servicios publicos]]+Opex_VE[[#This Row],[Nomina]] -> 101111.11 | L29: =+VLOOKUP(Opex_VE[[#This Row],[Fecha]],Opex!$B:$Y,OPEX_SALES!L$1,1) -> 61111.111 | M29: =+SUM(Opex_VE[[#This Row],[Internet]:[Electricidad]]) -> 0 | N29: =+VLOOKUP(Opex_VE[[#This Row],[Fecha]],Opex!$B:$Y,OPEX_SALES!N$1,1) -> 0 | O29: =+VLOOKUP(Opex_VE[[#This Row],[Fecha]],Opex!$B:$Y,OPEX_SALES!O$1,1) -> 0 | P29: =+VLOOKUP(Opex_VE[[#This Row],[Fecha]],Opex!$B:$Y,OPEX_SALES!P$1,1) -> 0 | Q29: =+VLOOKUP(Opex_VE[[#This Row],[Fecha]],Opex!$B:$Y,OPEX_SALES!Q$1,1) -> 0 | R29: =+SUM(Opex_VE[[#This Row],[Cajero]:[Domiciliario]]) -> 40000 | S29: 20000 | T29: 20000 | U29: 0
A30: 46093 | B30: =+B23+1 -> 3 | C30: =+TEXT(Opex_VE[[#This Row],[Fecha]],"ddd") -> jue | E30: A) Día hábil | F30: =IFERROR(VLOOKUP(Opex_VE[[#This Row],[Fecha]],Historia!A:B,2,0),_xlfn.XLOOKUP(Opex_VE[[#This Row],[dia]],Forecast!I:I,Forecast!J:J)) -> 243000 | G30: =IFERROR(VLOOKUP(Opex_VE[[#This Row],[Fecha]],Historia!A:C,3,0),_xlfn.XLOOKUP(Opex_VE[[#This Row],[dia]],Forecast!I:I,Forecast!K:K)) -> 97200 | H30: =+Opex_VE[[#This Row],[MG]]-Opex_VE[[#This Row],[Opex]] -> -13911.111 | I30: =IFERROR(VLOOKUP(Opex_VE[[#This Row],[Fecha]],Historia!A:D,4,0),"Forecast") -> Histórico | J30: =+K30/0.4 -> 277777.78 | K30: =+Opex_VE[[#This Row],[Arriendo]]+Opex_VE[[#This Row],[Servicios publicos]]+Opex_VE[[#This Row],[Nomina]] -> 111111.11 | L30: =+VLOOKUP(Opex_VE[[#This Row],[Fecha]],Opex!$B:$Y,OPEX_SALES!L$1,1) -> 61111.111 | M30: =+SUM(Opex_VE[[#This Row],[Internet]:[Electricidad]]) -> 0 | N30: =+VLOOKUP(Opex_VE[[#This Row],[Fecha]],Opex!$B:$Y,OPEX_SALES!N$1,1) -> 0 | O30: =+VLOOKUP(Opex_VE[[#This Row],[Fecha]],Opex!$B:$Y,OPEX_SALES!O$1,1) -> 0 | P30: =+VLOOKUP(Opex_VE[[#This Row],[Fecha]],Opex!$B:$Y,OPEX_SALES!P$1,1) -> 0 | Q30: =+VLOOKUP(Opex_VE[[#This Row],[Fecha]],Opex!$B:$Y,OPEX_SALES!Q$1,1) -> 0 | R30: =+SUM(Opex_VE[[#This Row],[Cajero]:[Domiciliario]]) -> 50000 | S30: 30000 | T30: 20000 | U30: 0
A31: 46094 | B31: =+B24+1 -> 3 | C31: =+TEXT(Opex_VE[[#This Row],[Fecha]],"ddd") -> vie | E31: B) Viernes | F31: =IFERROR(VLOOKUP(Opex_VE[[#This Row],[Fecha]],Historia!A:B,2,0),_xlfn.XLOOKUP(Opex_VE[[#This Row],[dia]],Forecast!I:I,Forecast!J:J)) -> 132500 | G31: =IFERROR(VLOOKUP(Opex_VE[[#This Row],[Fecha]],Historia!A:C,3,0),_xlfn.XLOOKUP(Opex_VE[[#This Row],[dia]],Forecast!I:I,Forecast!K:K)) -> 53000 | H31: =+Opex_VE[[#This Row],[MG]]-Opex_VE[[#This Row],[Opex]] -> -58111.111 | I31: =IFERROR(VLOOKUP(Opex_VE[[#This Row],[Fecha]],Historia!A:D,4,0),"Forecast") -> Histórico | J31: =+K31/0.4 -> 277777.78 | K31: =+Opex_VE[[#This Row],[Arriendo]]+Opex_VE[[#This Row],[Servicios publicos]]+Opex_VE[[#This Row],[Nomina]] -> 111111.11 | L31: =+VLOOKUP(Opex_VE[[#This Row],[Fecha]],Opex!$B:$Y,OPEX_SALES!L$1,1) -> 61111.111 | M31: =+SUM(Opex_VE[[#This Row],[Internet]:[Electricidad]]) -> 0 | N31: =+VLOOKUP(Opex_VE[[#This Row],[Fecha]],Opex!$B:$Y,OPEX_SALES!N$1,1) -> 0 | O31: =+VLOOKUP(Opex_VE[[#This Row],[Fecha]],Opex!$B:$Y,OPEX_SALES!O$1,1) -> 0 | P31: =+VLOOKUP(Opex_VE[[#This Row],[Fecha]],Opex!$B:$Y,OPEX_SALES!P$1,1) -> 0 | Q31: =+VLOOKUP(Opex_VE[[#This Row],[Fecha]],Opex!$B:$Y,OPEX_SALES!Q$1,1) -> 0 | R31: =+SUM(Opex_VE[[#This Row],[Cajero]:[Domiciliario]]) -> 50000 | S31: 30000 | T31: 20000 | U31: 0
A32: 46095 | B32: =+B25+1 -> 3 | C32: =+TEXT(Opex_VE[[#This Row],[Fecha]],"ddd") -> sáb | E32: C) Sábado | F32: =IFERROR(VLOOKUP(Opex_VE[[#This Row],[Fecha]],Historia!A:B,2,0),_xlfn.XLOOKUP(Opex_VE[[#This Row],[dia]],Forecast!I:I,Forecast!J:J)) -> 392500 | G32: =IFERROR(VLOOKUP(Opex_VE[[#This Row],[Fecha]],Historia!A:C,3,0),_xlfn.XLOOKUP(Opex_VE[[#This Row],[dia]],Forecast!I:I,Forecast!K:K)) -> 157000 | H32: =+Opex_VE[[#This Row],[MG]]-Opex_VE[[#This Row],[Opex]] -> 45888.889 | I32: =IFERROR(VLOOKUP(Opex_VE[[#This Row],[Fecha]],Historia!A:D,4,0),"Forecast") -> Histórico | J32: =+K32/0.4 -> 277777.78 | K32: =+Opex_VE[[#This Row],[Arriendo]]+Opex_VE[[#This Row],[Servicios publicos]]+Opex_VE[[#This Row],[Nomina]] -> 111111.11 | L32: =+VLOOKUP(Opex_VE[[#This Row],[Fecha]],Opex!$B:$Y,OPEX_SALES!L$1,1) -> 61111.111 | M32: =+SUM(Opex_VE[[#This Row],[Internet]:[Electricidad]]) -> 0 | N32: =+VLOOKUP(Opex_VE[[#This Row],[Fecha]],Opex!$B:$Y,OPEX_SALES!N$1,1) -> 0 | O32: =+VLOOKUP(Opex_VE[[#This Row],[Fecha]],Opex!$B:$Y,OPEX_SALES!O$1,1) -> 0 | P32: =+VLOOKUP(Opex_VE[[#This Row],[Fecha]],Opex!$B:$Y,OPEX_SALES!P$1,1) -> 0 | Q32: =+VLOOKUP(Opex_VE[[#This Row],[Fecha]],Opex!$B:$Y,OPEX_SALES!Q$1,1) -> 0 | R32: =+SUM(Opex_VE[[#This Row],[Cajero]:[Domiciliario]]) -> 50000 | S32: 30000 | T32: 20000 | U32: 0
A33: 46096 | B33: =+B26+1 -> 3 | C33: =+TEXT(Opex_VE[[#This Row],[Fecha]],"ddd") -> dom | E33: D) Domingo | F33: =IFERROR(VLOOKUP(Opex_VE[[#This Row],[Fecha]],Historia!A:B,2,0),_xlfn.XLOOKUP(Opex_VE[[#This Row],[dia]],Forecast!I:I,Forecast!J:J)) -> 118000 | G33: =IFERROR(VLOOKUP(Opex_VE[[#This Row],[Fecha]],Historia!A:C,3,0),_xlfn.XLOOKUP(Opex_VE[[#This Row],[dia]],Forecast!I:I,Forecast!K:K)) -> 47200 | H33: =+Opex_VE[[#This Row],[MG]]-Opex_VE[[#This Row],[Opex]] -> -80678.967 | I33: =IFERROR(VLOOKUP(Opex_VE[[#This Row],[Fecha]],Historia!A:D,4,0),"Forecast") -> Histórico | J33: =+K33/0.4 -> 319697.42 | K33: =+Opex_VE[[#This Row],[Arriendo]]+Opex_VE[[#This Row],[Servicios publicos]]+Opex_VE[[#This Row],[Nomina]] -> 127878.97 | L33: =+VLOOKUP(Opex_VE[[#This Row],[Fecha]],Opex!$B:$Y,OPEX_SALES!L$1,1) -> 55000 | M33: =+SUM(Opex_VE[[#This Row],[Internet]:[Electricidad]]) -> 22878.967 | N33: =+VLOOKUP(Opex_VE[[#This Row],[Fecha]],Opex!$B:$Y,OPEX_SALES!N$1,1) -> 0 | O33: =+VLOOKUP(Opex_VE[[#This Row],[Fecha]],Opex!$B:$Y,OPEX_SALES!O$1,1) -> 8243.9667 | P33: =+VLOOKUP(Opex_VE[[#This Row],[Fecha]],Opex!$B:$Y,OPEX_SALES!P$1,1) -> 4000 | Q33: =+VLOOKUP(Opex_VE[[#This Row],[Fecha]],Opex!$B:$Y,OPEX_SALES!Q$1,1) -> 10635 | R33: =+SUM(Opex_VE[[#This Row],[Cajero]:[Domiciliario]]) -> 50000 | S33: 30000 | T33: 20000 | U33: 0
A34: 46097 | B34: =+B27+1 -> 4 | C34: =+TEXT(Opex_VE[[#This Row],[Fecha]],"ddd") -> lun | E34: A) Día hábil | F34: =IFERROR(VLOOKUP(Opex_VE[[#This Row],[Fecha]],Historia!A:B,2,0),_xlfn.XLOOKUP(Opex_VE[[#This Row],[dia]],Forecast!I:I,Forecast!J:J)) -> 124000 | G34: =IFERROR(VLOOKUP(Opex_VE[[#This Row],[Fecha]],Historia!A:C,3,0),_xlfn.XLOOKUP(Opex_VE[[#This Row],[dia]],Forecast!I:I,Forecast!K:K)) -> 49600 | H34: =+Opex_VE[[#This Row],[MG]]-Opex_VE[[#This Row],[Opex]] -> -78278.967 | I34: =IFERROR(VLOOKUP(Opex_VE[[#This Row],[Fecha]],Historia!A:D,4,0),"Forecast") -> Histórico | J34: =+K34/0.4 -> 319697.42 | K34: =+Opex_VE[[#This Row],[Arriendo]]+Opex_VE[[#This Row],[Servicios publicos]]+Opex_VE[[#This Row],[Nomina]] -> 127878.97 | L34: =+VLOOKUP(Opex_VE[[#This Row],[Fecha]],Opex!$B:$Y,OPEX_SALES!L$1,1) -> 55000 | M34: =+SUM(Opex_VE[[#This Row],[Internet]:[Electricidad]]) -> 22878.967 | N34: =+VLOOKUP(Opex_VE[[#This Row],[Fecha]],Opex!$B:$Y,OPEX_SALES!N$1,1) -> 0 | O34: =+VLOOKUP(Opex_VE[[#This Row],[Fecha]],Opex!$B:$Y,OPEX_SALES!O$1,1) -> 8243.9667 | P34: =+VLOOKUP(Opex_VE[[#This Row],[Fecha]],Opex!$B:$Y,OPEX_SALES!P$1,1) -> 4000 | Q34: =+VLOOKUP(Opex_VE[[#This Row],[Fecha]],Opex!$B:$Y,OPEX_SALES!Q$1,1) -> 10635 | R34: =+SUM(Opex_VE[[#This Row],[Cajero]:[Domiciliario]]) -> 50000 | S34: 30000 | T34: 20000 | U34: 0
A35: 46098 | B35: =+B28+1 -> 4 | C35: =+TEXT(Opex_VE[[#This Row],[Fecha]],"ddd") -> mar | E35: A) Día hábil | F35: =IFERROR(VLOOKUP(Opex_VE[[#This Row],[Fecha]],Historia!A:B,2,0),_xlfn.XLOOKUP(Opex_VE[[#This Row],[dia]],Forecast!I:I,Forecast!J:J)) -> 314000 | G35: =IFERROR(VLOOKUP(Opex_VE[[#This Row],[Fecha]],Historia!A:C,3,0),_xlfn.XLOOKUP(Opex_VE[[#This Row],[dia]],Forecast!I:I,Forecast!K:K)) -> 125600 | H35: =+Opex_VE[[#This Row],[MG]]-Opex_VE[[#This Row],[Opex]] -> -2278.9667 | I35: =IFERROR(VLOOKUP(Opex_VE[[#This Row],[Fecha]],Historia!A:D,4,0),"Forecast") -> Histórico | J35: =+K35/0.4 -> 319697.42 | K35: =+Opex_VE[[#This Row],[Arriendo]]+Opex_VE[[#This Row],[Servicios publicos]]+Opex_VE[[#This Row],[Nomina]] -> 127878.97 | L35: =+VLOOKUP(Opex_VE[[#This Row],[Fecha]],Opex!$B:$Y,OPEX_SALES!L$1,1) -> 55000 | M35: =+SUM(Opex_VE[[#This Row],[Internet]:[Electricidad]]) -> 22878.967 | N35: =+VLOOKUP(Opex_VE[[#This Row],[Fecha]],Opex!$B:$Y,OPEX_SALES!N$1,1) -> 0 | O35: =+VLOOKUP(Opex_VE[[#This Row],[Fecha]],Opex!$B:$Y,OPEX_SALES!O$1,1) -> 8243.9667 | P35: =+VLOOKUP(Opex_VE[[#This Row],[Fecha]],Opex!$B:$Y,OPEX_SALES!P$1,1) -> 4000 | Q35: =+VLOOKUP(Opex_VE[[#This Row],[Fecha]],Opex!$B:$Y,OPEX_SALES!Q$1,1) -> 10635 | R35: =+SUM(Opex_VE[[#This Row],[Cajero]:[Domiciliario]]) -> 50000 | S35: 30000 | T35: 20000 | U35: 0
A36: 46099 | B36: =+B29+1 -> 4 | C36: =+TEXT(Opex_VE[[#This Row],[Fecha]],"ddd") -> mié | E36: A) Día hábil | F36: =IFERROR(VLOOKUP(Opex_VE[[#This Row],[Fecha]],Historia!A:B,2,0),_xlfn.XLOOKUP(Opex_VE[[#This Row],[dia]],Forecast!I:I,Forecast!J:J)) -> 149000 | G36: =IFERROR(VLOOKUP(Opex_VE[[#This Row],[Fecha]],Historia!A:C,3,0),_xlfn.XLOOKUP(Opex_VE[[#This Row],[dia]],Forecast!I:I,Forecast!K:K)) -> 59600 | H36: =+Opex_VE[[#This Row],[MG]]-Opex_VE[[#This Row],[Opex]] -> -68278.967 | I36: =IFERROR(VLOOKUP(Opex_VE[[#This Row],[Fecha]],Historia!A:D,4,0),"Forecast") -> Histórico | J36: =+K36/0.4 -> 319697.42 | K36: =+Opex_VE[[#This Row],[Arriendo]]+Opex_VE[[#This Row],[Servicios publicos]]+Opex_VE[[#This Row],[Nomina]] -> 127878.97 | L36: =+VLOOKUP(Opex_VE[[#This Row],[Fecha]],Opex!$B:$Y,OPEX_SALES!L$1,1) -> 55000 | M36: =+SUM(Opex_VE[[#This Row],[Internet]:[Electricidad]]) -> 22878.967 | N36: =+VLOOKUP(Opex_VE[[#This Row],[Fecha]],Opex!$B:$Y,OPEX_SALES!N$1,1) -> 0 | O36: =+VLOOKUP(Opex_VE[[#This Row],[Fecha]],Opex!$B:$Y,OPEX_SALES!O$1,1) -> 8243.9667 | P36: =+VLOOKUP(Opex_VE[[#This Row],[Fecha]],Opex!$B:$Y,OPEX_SALES!P$1,1) -> 4000 | Q36: =+VLOOKUP(Opex_VE[[#This Row],[Fecha]],Opex!$B:$Y,OPEX_SALES!Q$1,1) -> 10635 | R36: =+SUM(Opex_VE[[#This Row],[Cajero]:[Domiciliario]]) -> 50000 | S36: 30000 | T36: 20000 | U36: 0
A37: 46100 | B37: =+B30+1 -> 4 | C37: =+TEXT(Opex_VE[[#This Row],[Fecha]],"ddd") -> jue | E37: A) Día hábil | F37: =IFERROR(VLOOKUP(Opex_VE[[#This Row],[Fecha]],Historia!A:B,2,0),_xlfn.XLOOKUP(Opex_VE[[#This Row],[dia]],Forecast!I:I,Forecast!J:J)) -> 388900 | G37: =IFERROR(VLOOKUP(Opex_VE[[#This Row],[Fecha]],Historia!A:C,3,0),_xlfn.XLOOKUP(Opex_VE[[#This Row],[dia]],Forecast!I:I,Forecast!K:K)) -> 155560 | H37: =+Opex_VE[[#This Row],[MG]]-Opex_VE[[#This Row],[Opex]] -> 27681.033 | I37: =IFERROR(VLOOKUP(Opex_VE[[#This Row],[Fecha]],Historia!A:D,4,0),"Forecast") -> Histórico | J37: =+K37/0.4 -> 319697.42 | K37: =+Opex_VE[[#This Row],[Arriendo]]+Opex_VE[[#This Row],[Servicios publicos]]+Opex_VE[[#This Row],[Nomina]] -> 127878.97 | L37: =+VLOOKUP(Opex_VE[[#This Row],[Fecha]],Opex!$B:$Y,OPEX_SALES!L$1,1) -> 55000 | M37: =+SUM(Opex_VE[[#This Row],[Internet]:[Electricidad]]) -> 22878.967 | N37: =+VLOOKUP(Opex_VE[[#This Row],[Fecha]],Opex!$B:$Y,OPEX_SALES!N$1,1) -> 0 | O37: =+VLOOKUP(Opex_VE[[#This Row],[Fecha]],Opex!$B:$Y,OPEX_SALES!O$1,1) -> 8243.9667 | P37: =+VLOOKUP(Opex_VE[[#This Row],[Fecha]],Opex!$B:$Y,OPEX_SALES!P$1,1) -> 4000 | Q37: =+VLOOKUP(Opex_VE[[#This Row],[Fecha]],Opex!$B:$Y,OPEX_SALES!Q$1,1) -> 10635 | R37: =+SUM(Opex_VE[[#This Row],[Cajero]:[Domiciliario]]) -> 50000 | S37: 30000 | T37: 20000 | U37: 0
... A369: 46432 | B369: =+B362+1 -> 51 | C369: =+TEXT(Opex_VE[[#This Row],[Fecha]],"ddd") -> dom | E369: D) Domingo | F369: =IFERROR(VLOOKUP(Opex_VE[[#This Row],[Fecha]],Historia!A:B,2,0),_xlfn.XLOOKUP(Opex_VE[[#This Row],[dia]],Forecast!I:I,Forecast!J:J)) -> 168750 | G369: =IFERROR(VLOOKUP(Opex_VE[[#This Row],[Fecha]],Historia!A:C,3,0),_xlfn.XLOOKUP(Opex_VE[[#This Row],[dia]],Forecast!I:I,Forecast!K:K)) -> 67500 | H369: =+Opex_VE[[#This Row],[MG]]-Opex_VE[[#This Row],[Opex]] -> -153878.97 | I369: =IFERROR(VLOOKUP(Opex_VE[[#This Row],[Fecha]],Historia!A:D,4,0),"Forecast") -> Forecast | J369: =+K369/0.4 -> 553447.42 | K369: =+Opex_VE[[#This Row],[Arriendo]]+Opex_VE[[#This Row],[Servicios publicos]]+Opex_VE[[#This Row],[Nomina]] -> 221378.97 | L369: =+VLOOKUP(Opex_VE[[#This Row],[Fecha]],Opex!$B:$Y,OPEX_SALES!L$1,1) -> 55000 | M369: =+SUM(Opex_VE[[#This Row],[Internet]:[Electricidad]]) -> 26378.967 | N369: =+VLOOKUP(Opex_VE[[#This Row],[Fecha]],Opex!$B:$Y,OPEX_SALES!N$1,1) -> 3500 | O369: =+VLOOKUP(Opex_VE[[#This Row],[Fecha]],Opex!$B:$Y,OPEX_SALES!O$1,1) -> 8243.9667 | P369: =+VLOOKUP(Opex_VE[[#This Row],[Fecha]],Opex!$B:$Y,OPEX_SALES!P$1,1) -> 4000 | Q369: =+VLOOKUP(Opex_VE[[#This Row],[Fecha]],Opex!$B:$Y,OPEX_SALES!Q$1,1) -> 10635 | R369: =+SUM(Opex_VE[[#This Row],[Cajero]:[Domiciliario]]) -> 140000 | S369: 70000 | T369: 70000 | U369: 0

Sheet Opex
B1: 1 | C1: =+B1+1 -> 2 | D1: =+C1+1 -> 3 | E1: =+D1+1 -> 4 | F1: =+E1+1 -> 5 | G1: =+F1+1 -> 6 | H1: =+G1+1 -> 7 | I1: =+H1+1 -> 8 | J1: =+I1+1 -> 9 | ... W1: =+V1+1 -> 22 | X1: 23 | Y1: 24
A2: Tipo | B2: Fecha | C2: fecha_fin | D2: Mes | E2: Cuentas x Pagar | F2: Día C x P | G2: Arriendo | H2: No. Días Arriendo | I2: Día Arriendo | J2: Gas | K2: No. Días Gas | L2: Consumo (m3) | M2: Costo prom. Gas | N2: Día Gas | O2: Agua | P2: Dìa Agua | Q2: Energia | R2: Financiació Energia | S2: No. Días Energia | T2: Consumo (KhW | U2: Costo prom. Energia | V2: Fecha corte enega | W2: Día Energia | X2: Internet | Y2: Día internet
A3: Histórico | B3: 46068 | C3: 46095 | D3: =+TEXT(B3,"mmmm") -> febrero | F3: =+Opex[[#This Row],[Cuentas x Pagar]]/31 -> 0 | G3: 1650000 | H3: =+Opex[[#This Row],[fecha_fin]]-Opex[[#This Row],[Fecha]] -> 27 | I3: =IFERROR(Opex[[#This Row],[Arriendo]]/Opex[[#This Row],[No. Días Arriendo]],0) -> 61111.111 | J3: 0 | K3: 0 | L3: 0 | M3: =IFERROR(Opex[[#This Row],[Gas]]/Opex[[#This Row],[Consumo (m3)]],0) -> 0 | N3: =IFERROR(Opex[[#This Row],[Gas]]/Opex[[#This Row],[No. Días Arriendo]],0) -> 0 | P3: =IFERROR(Opex[[#This Row],[Agua]]/Opex[[#This Row],[No. Días Arriendo]],0) -> 0 | S3: =+Z3 -> 0 | U3: =IFERROR(Opex[[#This Row],[Energia]]/Opex[[#This Row],[Consumo (KhW]],0) -> 0 | W3: =IFERROR(Opex[[#This Row],[Energia]]/Opex[[#This Row],[No. Días Arriendo]],0) -> 0 | X3: 0 | Y3: =+Opex[[#This Row],[Internet]]/Opex[[#This Row],[No. Días Arriendo]] -> 0
A4: Forecast | B4: =+C3+1 -> 46096 | C4: 46126 | D4: =+TEXT(B4,"mmmm") -> marzo | F4: =+Opex[[#This Row],[Cuentas x Pagar]]/31 -> 0 | G4: 1650000 | H4: =+Opex[[#This Row],[fecha_fin]]-Opex[[#This Row],[Fecha]] -> 30 | I4: =IFERROR(Opex[[#This Row],[Arriendo]]/Opex[[#This Row],[No. Días Arriendo]],0) -> 55000 | J4: 247319 | K4: =+#REF! -> #REF! | L4: =+AVERAGE(#REF!/#REF!,#REF!/#REF!,#REF!/#REF!)*Opex[[#This Row],[No. Días Gas]] -> #REF! | M4: =+AVERAGE(#REF!) -> #REF! | N4: =IFERROR(Opex[[#This Row],[Gas]]/Opex[[#This Row],[No. Días Arriendo]],0) -> 8243.9667 | O4: 120000 | P4: =IFERROR(Opex[[#This Row],[Agua]]/Opex[[#This Row],[No. Días Arriendo]],0) -> 4000 | Q4: 319050 | R4: 264247 | S4: =+#REF! -> #REF! | T4: =+AVERAGE(#REF!/#REF!,#REF!/#REF!) -> #REF! | U4: =+AVERAGE(#REF!) -> #REF! | V4: Nd | W4: =IFERROR(Opex[[#This Row],[Energia]]/Opex[[#This Row],[No. Días Arriendo]],0) -> 10635 | X4: 0 | Y4: =+Opex[[#This Row],[Internet]]/Opex[[#This Row],[No. Días Arriendo]] -> 0
A5: Forecast | B5: =+C4+1 -> 46127 | C5: 46156 | D5: =+TEXT(B5,"mmmm") -> abril | F5: =+Opex[[#This Row],[Cuentas x Pagar]]/31 -> 0 | G5: 1650000 | H5: =+Opex[[#This Row],[fecha_fin]]-Opex[[#This Row],[Fecha]] -> 29 | I5: =IFERROR(Opex[[#This Row],[Arriendo]]/Opex[[#This Row],[No. Días Arriendo]],0) -> 56896.552 | J5: 247319 | K5: =+H4 -> 30 | L5: =+AVERAGE(#REF!/#REF!,#REF!/#REF!,L4/K4)*Opex[[#This Row],[No. Días Gas]] -> #REF! | M5: =+AVERAGE(M4:M4) -> #REF! | N5: =IFERROR(Opex[[#This Row],[Gas]]/Opex[[#This Row],[No. Días Arriendo]],0) -> 8528.2414 | O5: 120000 | P5: =IFERROR(Opex[[#This Row],[Agua]]/Opex[[#This Row],[No. Días Arriendo]],0) -> 4137.931 | Q5: =+AVERAGE(Q4:Q4) -> 319050 | R5: 264247 | S5: =+#REF! -> #REF! | T5: =+AVERAGE(#REF!/#REF!,#REF!/#REF!,#REF!/U4) -> #REF! | U5: =+AVERAGE(U4:U4) -> #REF! | V5: Nd | W5: =IFERROR(Opex[[#This Row],[Energia]]/Opex[[#This Row],[No. Días Arriendo]],0) -> 11001.724 | X5: 105000 | Y5: =+Opex[[#This Row],[Internet]]/Opex[[#This Row],[No. Días Arriendo]] -> 3620.6897
A6: Forecast | B6: =+C5+1 -> 46157 | C6: 46187 | D6: =+TEXT(B6,"mmmm") -> mayo | F6: =+Opex[[#This Row],[Cuentas x Pagar]]/31 -> 0 | G6: 1650000 | H6: =+Opex[[#This Row],[fecha_fin]]-Opex[[#This Row],[Fecha]] -> 30 | I6: =IFERROR(Opex[[#This Row],[Arriendo]]/Opex[[#This Row],[No. Días Arriendo]],0) -> 55000 | J6: 247319 | K6: =+H5 -> 29 | L6: =+AVERAGE(#REF!/#REF!,L4/K4,L5/K5)*Opex[[#This Row],[No. Días Gas]] -> #REF! | M6: =+AVERAGE(M4:M5) -> #REF! | N6: =IFERROR(Opex[[#This Row],[Gas]]/Opex[[#This Row],[No. Días Arriendo]],0) -> 8243.9667 | O6: 120000 | P6: =IFERROR(Opex[[#This Row],[Agua]]/Opex[[#This Row],[No. Días Arriendo]],0) -> 4000 | Q6: =+AVERAGE(Q4:Q5) -> 319050 | R6: 264247 | S6: =+#REF! -> #REF! | T6: =+AVERAGE(#REF!/#REF!,#REF!/U4,#REF!/U5) -> #REF! | U6: =+AVERAGE(U4:U5) -> #REF! | V6: Nd | W6: =IFERROR(Opex[[#This Row],[Energia]]/Opex[[#This Row],[No. Días Arriendo]],0) -> 10635 | X6: 105000 | Y6: =+Opex[[#This Row],[Internet]]/Opex[[#This Row],[No. Días Arriendo]] -> 3500
A7: Forecast | B7: =+C6+1 -> 46188 | C7: 46217 | D7: =+TEXT(B7,"mmmm") -> junio | F7: =+Opex[[#This Row],[Cuentas x Pagar]]/31 -> 0 | G7: 1650000 | H7: =+Opex[[#This Row],[fecha_fin]]-Opex[[#This Row],[Fecha]] -> 29 | I7: =IFERROR(Opex[[#This Row],[Arriendo]]/Opex[[#This Row],[No. Días Arriendo]],0) -> 56896.552 | J7: 247319 | K7: =+H6 -> 30 | L7: =+AVERAGE(L4/K4,L5/K5,L6/K6)*Opex[[#This Row],[No. Días Gas]] -> #REF! | M7: =+AVERAGE(M4:M6) -> #REF! | N7: =IFERROR(Opex[[#This Row],[Gas]]/Opex[[#This Row],[No. Días Arriendo]],0) -> 8528.2414 | O7: 120000 | P7: =IFERROR(Opex[[#This Row],[Agua]]/Opex[[#This Row],[No. Días Arriendo]],0) -> 4137.931 | Q7: =+AVERAGE(Q5:Q6) -> 319050 | R7: 264247 | S7: =+#REF! -> #REF! | T7: =+AVERAGE(#REF!/U4,#REF!/U5,#REF!/U6) -> #REF! | U7: =+AVERAGE(U4:U6) -> #REF! | V7: Nd | W7: =IFERROR(Opex[[#This Row],[Energia]]/Opex[[#This Row],[No. Días Arriendo]],0) -> 11001.724 | X7: 105000 | Y7: =+Opex[[#This Row],[Internet]]/Opex[[#This Row],[No. Días Arriendo]] -> 3620.6897
A8: Forecast | B8: =+C7+1 -> 46218 | C8: 46248 | D8: =+TEXT(B8,"mmmm") -> julio | F8: =+Opex[[#This Row],[Cuentas x Pagar]]/31 -> 0 | G8: 1650000 | H8: =+Opex[[#This Row],[fecha_fin]]-Opex[[#This Row],[Fecha]] -> 30 | I8: =IFERROR(Opex[[#This Row],[Arriendo]]/Opex[[#This Row],[No. Días Arriendo]],0) -> 55000 | J8: 247319 | K8: =+H7 -> 29 | L8: =+AVERAGE(L5/K5,L6/K6,L7/K7)*Opex[[#This Row],[No. Días Gas]] -> #REF! | M8: =+AVERAGE(M5:M7) -> #REF! | N8: =IFERROR(Opex[[#This Row],[Gas]]/Opex[[#This Row],[No. Días Arriendo]],0) -> 8243.9667 | O8: 120000 | P8: =IFERROR(Opex[[#This Row],[Agua]]/Opex[[#This Row],[No. Días Arriendo]],0) -> 4000 | Q8: =+AVERAGE(Q6:Q7) -> 319050 | R8: 0 | S8: =+#REF! -> #REF! | T8: =+AVERAGE(#REF!/U5,#REF!/U6,#REF!/U7) -> #REF! | U8: =+AVERAGE(U5:U7) -> #REF! | V8: Nd | W8: =IFERROR(Opex[[#This Row],[Energia]]/Opex[[#This Row],[No. Días Arriendo]],0) -> 10635 | X8: 105000 | Y8: =+Opex[[#This Row],[Internet]]/Opex[[#This Row],[No. Días Arriendo]] -> 3500
A9: Forecast | B9: =+C8+1 -> 46249 | C9: 46279 | D9: =+TEXT(B9,"mmmm") -> agosto | F9: =+Opex[[#This Row],[Cuentas x Pagar]]/31 -> 0 | G9: 1650000 | H9: =+Opex[[#This Row],[fecha_fin]]-Opex[[#This Row],[Fecha]] -> 30 | I9: =IFERROR(Opex[[#This Row],[Arriendo]]/Opex[[#This Row],[No. Días Arriendo]],0) -> 55000 | J9: 247319 | K9: =+H8 -> 30 | L9: =+AVERAGE(L6/K6,L7/K7,L8/K8)*Opex[[#This Row],[No. Días Gas]] -> #REF! | M9: =+AVERAGE(M6:M8) -> #REF! | N9: =IFERROR(Opex[[#This Row],[Gas]]/Opex[[#This Row],[No. Días Arriendo]],0) -> 8243.9667 | O9: 120000 | P9: =IFERROR(Opex[[#This Row],[Agua]]/Opex[[#This Row],[No. Días Arriendo]],0) -> 4000 | Q9: =+AVERAGE(Q7:Q8) -> 319050 | R9: 0 | S9: =+#REF! -> #REF! | T9: =+AVERAGE(#REF!/U6,#REF!/U7,#REF!/U8) -> #REF! | U9: =+AVERAGE(U6:U8) -> #REF! | V9: Nd | W9: =IFERROR(Opex[[#This Row],[Energia]]/Opex[[#This Row],[No. Días Arriendo]],0) -> 10635 | X9: 105000 | Y9: =+Opex[[#This Row],[Internet]]/Opex[[#This Row],[No. Días Arriendo]] -> 3500
A10: Forecast | B10: =+C9+1 -> 46280 | C10: 46309 | D10: =+TEXT(B10,"mmmm") -> septiembre | F10: =+Opex[[#This Row],[Cuentas x Pagar]]/31 -> 0 | G10: 1650000 | H10: =+Opex[[#This Row],[fecha_fin]]-Opex[[#This Row],[Fecha]] -> 29 | I10: =IFERROR(Opex[[#This Row],[Arriendo]]/Opex[[#This Row],[No. Días Arriendo]],0) -> 56896.552 | J10: 247319 | K10: =+H9 -> 30 | L10: =+AVERAGE(L7/K7,L8/K8,L9/K9)*Opex[[#This Row],[No. Días Gas]] -> #REF! | M10: =+AVERAGE(M7:M9) -> #REF! | N10: =IFERROR(Opex[[#This Row],[Gas]]/Opex[[#This Row],[No. Días Arriendo]],0) -> 8528.2414 | O10: 120000 | P10: =IFERROR(Opex[[#This Row],[Agua]]/Opex[[#This Row],[No. Días Arriendo]],0) -> 4137.931 | Q10: =+AVERAGE(Q8:Q9) -> 319050 | R10: 0 | S10: =+#REF! -> #REF! | T10: =+AVERAGE(#REF!/U7,#REF!/U8,#REF!/U9) -> #REF! | U10: =+AVERAGE(U7:U9) -> #REF! | V10: Nd | W10: =IFERROR(Opex[[#This Row],[Energia]]/Opex[[#This Row],[No. Días Arriendo]],0) -> 11001.724 | X10: 105000 | Y10: =+Opex[[#This Row],[Internet]]/Opex[[#This Row],[No. Días Arriendo]] -> 3620.6897
A11: Forecast | B11: =+C10+1 -> 46310 | C11: 46340 | D11: =+TEXT(B11,"mmmm") -> octubre | F11: =+Opex[[#This Row],[Cuentas x Pagar]]/31 -> 0 | G11: 1650000 | H11: =+Opex[[#This Row],[fecha_fin]]-Opex[[#This Row],[Fecha]] -> 30 | I11: =IFERROR(Opex[[#This Row],[Arriendo]]/Opex[[#This Row],[No. Días Arriendo]],0) -> 55000 | J11: 247319 | K11: =+H10 -> 29 | L11: =+AVERAGE(L8/K8,L9/K9,L10/K10)*Opex[[#This Row],[No. Días Gas]] -> #REF! | M11: =+AVERAGE(M8:M10) -> #REF! | N11: =IFERROR(Opex[[#This Row],[Gas]]/Opex[[#This Row],[No. Días Arriendo]],0) -> 8243.9667 | O11: 120000 | P11: =IFERROR(Opex[[#This Row],[Agua]]/Opex[[#This Row],[No. Días Arriendo]],0) -> 4000 | Q11: =+AVERAGE(Q9:Q10) -> 319050 | R11: 0 | S11: =+#REF! -> #REF! | T11: =+AVERAGE(#REF!/U8,#REF!/U9,#REF!/U10) -> #REF! | U11: =+AVERAGE(U8:U10) -> #REF! | V11: Nd | W11: =IFERROR(Opex[[#This Row],[Energia]]/Opex[[#This Row],[No. Días Arriendo]],0) -> 10635 | X11: 105000 | Y11: =+Opex[[#This Row],[Internet]]/Opex[[#This Row],[No. Días Arriendo]] -> 3500
A12: Forecast | B12: =+C11+1 -> 46341 | C12: 46370 | D12: =+TEXT(B12,"mmmm") -> noviembre | F12: =+Opex[[#This Row],[Cuentas x Pagar]]/31 -> 0 | G12: 1650000 | H12: =+Opex[[#This Row],[fecha_fin]]-Opex[[#This Row],[Fecha]] -> 29 | I12: =IFERROR(Opex[[#This Row],[Arriendo]]/Opex[[#This Row],[No. Días Arriendo]],0) -> 56896.552 | J12: 247319 | K12: =+H11 -> 30 | L12: =+AVERAGE(L9/K9,L10/K10,L11/K11)*Opex[[#This Row],[No. Días Gas]] -> #REF! | M12: =+AVERAGE(M9:M11) -> #REF! | N12: =IFERROR(Opex[[#This Row],[Gas]]/Opex[[#This Row],[No. Días Arriendo]],0) -> 8528.2414 | O12: 120000 | P12: =IFERROR(Opex[[#This Row],[Agua]]/Opex[[#This Row],[No. Días Arriendo]],0) -> 4137.931 | Q12: =+AVERAGE(Q10:Q11) -> 319050 | R12: 0 | S12: =+#REF! -> #REF! | T12: =+AVERAGE(#REF!/U9,#REF!/U10,#REF!/U11) -> #REF! | U12: =+AVERAGE(U9:U11) -> #REF! | V12: Nd | W12: =IFERROR(Opex[[#This Row],[Energia]]/Opex[[#This Row],[No. Días Arriendo]],0) -> 11001.724 | X12: 105000 | Y12: =+Opex[[#This Row],[Internet]]/Opex[[#This Row],[No. Días Arriendo]] -> 3620.6897
A13: Forecast | B13: =+C12+1 -> 46371 | C13: 46401 | D13: =+TEXT(B13,"mmmm") -> diciembre | F13: =+Opex[[#This Row],[Cuentas x Pagar]]/31 -> 0 | G13: 1650000 | H13: =+Opex[[#This Row],[fecha_fin]]-Opex[[#This Row],[Fecha]] -> 30 | I13: =IFERROR(Opex[[#This Row],[Arriendo]]/Opex[[#This Row],[No. Días Arriendo]],0) -> 55000 | J13: 247319 | K13: =+H12 -> 29 | L13: =+AVERAGE(L10/K10,L11/K11,L12/K12)*Opex[[#This Row],[No. Días Gas]] -> #REF! | M13: =+AVERAGE(M10:M12) -> #REF! | N13: =IFERROR(Opex[[#This Row],[Gas]]/Opex[[#This Row],[No. Días Arriendo]],0) -> 8243.9667 | O13: 120000 | P13: =IFERROR(Opex[[#This Row],[Agua]]/Opex[[#This Row],[No. Días Arriendo]],0) -> 4000 | Q13: =+AVERAGE(Q11:Q12) -> 319050 | R13: 0 | S13: =+#REF! -> #REF! | T13: =+AVERAGE(#REF!/U10,#REF!/U11,#REF!/U12) -> #REF! | U13: =+AVERAGE(U10:U12) -> #REF! | V13: Nd | W13: =IFERROR(Opex[[#This Row],[Energia]]/Opex[[#This Row],[No. Días Arriendo]],0) -> 10635 | X13: 105000 | Y13: =+Opex[[#This Row],[Internet]]/Opex[[#This Row],[No. Días Arriendo]] -> 3500
A14: Forecast | B14: =+C13+1 -> 46402 | C14: 46432 | D14: =+TEXT(B14,"mmmm") -> enero | F14: =+Opex[[#This Row],[Cuentas x Pagar]]/31 -> 0 | G14: 1650000 | H14: =+Opex[[#This Row],[fecha_fin]]-Opex[[#This Row],[Fecha]] -> 30 | I14: =IFERROR(Opex[[#This Row],[Arriendo]]/Opex[[#This Row],[No. Días Arriendo]],0) -> 55000 | J14: 247319 | K14: =+H13 -> 30 | L14: =+AVERAGE(L11/K11,L12/K12,L13/K13)*Opex[[#This Row],[No. Días Gas]] -> #REF! | M14: =+AVERAGE(M11:M13) -> #REF! | N14: =IFERROR(Opex[[#This Row],[Gas]]/Opex[[#This Row],[No. Días Arriendo]],0) -> 8243.9667 | O14: 120000 | P14: =IFERROR(Opex[[#This Row],[Agua]]/Opex[[#This Row],[No. Días Arriendo]],0) -> 4000 | Q14: =+AVERAGE(Q12:Q13) -> 319050 | R14: 0 | S14: =+#REF! -> #REF! | T14: =+AVERAGE(#REF!/U11,#REF!/U12,#REF!/U13) -> #REF! | U14: =+AVERAGE(U11:U13) -> #REF! | V14: Nd | W14: =IFERROR(Opex[[#This Row],[Energia]]/Opex[[#This Row],[No. Días Arriendo]],0) -> 10635 | X14: 105000 | Y14: =+Opex[[#This Row],[Internet]]/Opex[[#This Row],[No. Días Arriendo]] -> 3500

Sheet sales
A1: Fecha | B1: Hora | C1: Tipo día | D1: nombre_producto | E1: cantidad | F1: No. Semana de operación | G1: Tipo día2 | H1: Día | I1: MG | J1: Venta | K1: Caja | L1: Bancos | M1: costo_venta | N1: %MG
A2: =[1]sales!A7 -> 46076 | B2: =[1]sales!B7 -> 0.69208333 | C2: Normal | D2: =[1]sales!D7 -> Chorizo con papa/arepa | E2: =+[1]sales!G7 -> 2 | F2: =+_xlfn.XLOOKUP(sales[[#This Row],[Fecha]],OPEX_SALES!A:A,OPEX_SALES!B:B) -> 1 | G2: =+_xlfn.XLOOKUP(sales[[#This Row],[Fecha]],OPEX_SALES!A:A,OPEX_SALES!E:E) -> A) Día hábil | H2: =+TEXT(sales[[#This Row],[Fecha]],"ddd") -> lun | I2: =+sales[[#This Row],[Venta]]-sales[[#This Row],[costo_venta]] -> 7320 | J2: =[1]sales!K7 -> 16000 | K2: =[1]sales!I7 -> 16000 | L2: =[1]sales!J7 -> 0 | M2: =[1]sales!L7*sales[[#This Row],[cantidad]] -> 8680 | N2: =+(sales[[#This Row],[Venta]]-sales[[#This Row],[costo_venta]])/sales[[#This Row],[Venta]] -> 0.4575
A3: =[1]sales!A8 -> 46076 | B3: =[1]sales!B8 -> 0.70967593 | C3: Normal | D3: =[1]sales!D8 -> Chorizo con papa/arepa | E3: =+[1]sales!G8 -> 1 | F3: =+_xlfn.XLOOKUP(sales[[#This Row],[Fecha]],OPEX_SALES!A:A,OPEX_SALES!B:B) -> 1 | G3: =+_xlfn.XLOOKUP(sales[[#This Row],[Fecha]],OPEX_SALES!A:A,OPEX_SALES!E:E) -> A) Día hábil | H3: =+TEXT(sales[[#This Row],[Fecha]],"ddd") -> lun | I3: =+sales[[#This Row],[Venta]]-sales[[#This Row],[costo_venta]] -> 3660 | J3: =[1]sales!K8 -> 8000 | K3: =[1]sales!I8 -> 0 | M3: =[1]sales!L8*sales[[#This Row],[cantidad]] -> 4340 | N3: =+(sales[[#This Row],[Venta]]-sales[[#This Row],[costo_venta]])/sales[[#This Row],[Venta]] -> 0.4575
A4: =[1]sales!A9 -> 46076 | B4: =[1]sales!B9 -> 0.71737269 | C4: Normal | D4: =[1]sales!D9 -> Chorizo con papa/arepa | E4: =+[1]sales!G9 -> 2 | F4: =+_xlfn.XLOOKUP(sales[[#This Row],[Fecha]],OPEX_SALES!A:A,OPEX_SALES!B:B) -> 1 | G4: =+_xlfn.XLOOKUP(sales[[#This Row],[Fecha]],OPEX_SALES!A:A,OPEX_SALES!E:E) -> A) Día hábil | H4: =+TEXT(sales[[#This Row],[Fecha]],"ddd") -> lun | I4: =+sales[[#This Row],[Venta]]-sales[[#This Row],[costo_venta]] -> 7320 | J4: =[1]sales!K9 -> 16000 | K4: =[1]sales!I9 -> 16000 | L4: =[1]sales!J9 -> 0 | M4: =[1]sales!L9*sales[[#This Row],[cantidad]] -> 8680 | N4: =+(sales[[#This Row],[Venta]]-sales[[#This Row],[costo_venta]])/sales[[#This Row],[Venta]] -> 0.4575
A5: =[1]sales!A10 -> 46076 | B5: =[1]sales!B10 -> 0.71737269 | C5: Normal | D5: =[1]sales!D10 -> BEBIDA - Coca Cola | E5: =+[1]sales!G10 -> 2 | F5: =+_xlfn.XLOOKUP(sales[[#This Row],[Fecha]],OPEX_SALES!A:A,OPEX_SALES!B:B) -> 1 | G5: =+_xlfn.XLOOKUP(sales[[#This Row],[Fecha]],OPEX_SALES!A:A,OPEX_SALES!E:E) -> A) Día hábil | H5: =+TEXT(sales[[#This Row],[Fecha]],"ddd") -> lun | I5: =+sales[[#This Row],[Venta]]-sales[[#This Row],[costo_venta]] -> 3600 | J5: =[1]sales!K10 -> 6000 | K5: =[1]sales!I10 -> 6000 | L5: =[1]sales!J10 -> 0 | M5: =[1]sales!L10*sales[[#This Row],[cantidad]] -> 2400 | N5: =+(sales[[#This Row],[Venta]]-sales[[#This Row],[costo_venta]])/sales[[#This Row],[Venta]] -> 0.6
A6: =[1]sales!A11 -> 46076 | B6: =[1]sales!B11 -> 0.72047454 | C6: Normal | D6: =[1]sales!D11 -> Chorizo con papa/arepa | E6: =+[1]sales!G11 -> 3 | F6: =+_xlfn.XLOOKUP(sales[[#This Row],[Fecha]],OPEX_SALES!A:A,OPEX_SALES!B:B) -> 1 | G6: =+_xlfn.XLOOKUP(sales[[#This Row],[Fecha]],OPEX_SALES!A:A,OPEX_SALES!E:E) -> A) Día hábil | H6: =+TEXT(sales[[#This Row],[Fecha]],"ddd") -> lun | I6: =+sales[[#This Row],[Venta]]-sales[[#This Row],[costo_venta]] -> 10980 | J6: =[1]sales!K11 -> 24000 | K6: =[1]sales!I11 -> 0 | L6: =[1]sales!J11 -> 24000 | M6: =[1]sales!L11*sales[[#This Row],[cantidad]] -> 13020 | N6: =+(sales[[#This Row],[Venta]]-sales[[#This Row],[costo_venta]])/sales[[#This Row],[Venta]] -> 0.4575
A7: =[1]sales!A12 -> 46076 | B7: =[1]sales!B12 -> 0.75028935 | C7: Normal | D7: =[1]sales!D12 -> Chorizo con papa/arepa | E7: =+[1]sales!G12 -> 2 | F7: =+_xlfn.XLOOKUP(sales[[#This Row],[Fecha]],OPEX_SALES!A:A,OPEX_SALES!B:B) -> 1 | G7: =+_xlfn.XLOOKUP(sales[[#This Row],[Fecha]],OPEX_SALES!A:A,OPEX_SALES!E:E) -> A) Día hábil | H7: =+TEXT(sales[[#This Row],[Fecha]],"ddd") -> lun | I7: =+sales[[#This Row],[Venta]]-sales[[#This Row],[costo_venta]] -> 7320 | J7: =[1]sales!K12 -> 16000 | K7: =[1]sales!I12 -> 16000 | L7: =[1]sales!J12 -> 0 | M7: =[1]sales!L12*sales[[#This Row],[cantidad]] -> 8680 | N7: =+(sales[[#This Row],[Venta]]-sales[[#This Row],[costo_venta]])/sales[[#This Row],[Venta]] -> 0.4575
A8: =[1]sales!A13 -> 46076 | B8: =[1]sales!B13 -> 0.75028935 | C8: Normal | D8: =[1]sales!D13 -> BEBIDA - Botella de Agua | E8: =+[1]sales!G13 -> 2 | F8: =+_xlfn.XLOOKUP(sales[[#This Row],[Fecha]],OPEX_SALES!A:A,OPEX_SALES!B:B) -> 1 | G8: =+_xlfn.XLOOKUP(sales[[#This Row],[Fecha]],OPEX_SALES!A:A,OPEX_SALES!E:E) -> A) Día hábil | H8: =+TEXT(sales[[#This Row],[Fecha]],"ddd") -> lun | I8: =+sales[[#This Row],[Venta]]-sales[[#This Row],[costo_venta]] -> 4166.66 | J8: =[1]sales!K13 -> 7000 | K8: =[1]sales!I13 -> 7000 | L8: =[1]sales!J13 -> 0 | M8: =[1]sales!L13*sales[[#This Row],[cantidad]] -> 2833.34 | N8: =+(sales[[#This Row],[Venta]]-sales[[#This Row],[costo_venta]])/sales[[#This Row],[Venta]] -> 0.59523714
A9: =[1]sales!A14 -> 46076 | B9: =[1]sales!B14 -> 0.75196759 | C9: Normal | D9: =[1]sales!D14 -> Chorizo con papa/arepa | E9: =+[1]sales!G14 -> 2 | F9: =+_xlfn.XLOOKUP(sales[[#This Row],[Fecha]],OPEX_SALES!A:A,OPEX_SALES!B:B) -> 1 | G9: =+_xlfn.XLOOKUP(sales[[#This Row],[Fecha]],OPEX_SALES!A:A,OPEX_SALES!E:E) -> A) Día hábil | H9: =+TEXT(sales[[#This Row],[Fecha]],"ddd") -> lun | I9: =+sales[[#This Row],[Venta]]-sales[[#This Row],[costo_venta]] -> 7320 | J9: =[1]sales!K14 -> 16000 | K9: =[1]sales!I14 -> 16000 | L9: =[1]sales!J14 -> 0 | M9: =[1]sales!L14*sales[[#This Row],[cantidad]] -> 8680 | N9: =+(sales[[#This Row],[Venta]]-sales[[#This Row],[costo_venta]])/sales[[#This Row],[Venta]] -> 0.4575
A10: =[1]sales!A15 -> 46076 | B10: =[1]sales!B15 -> 0.75196759 | C10: Normal | D10: =[1]sales!D15 -> BEBIDA - Postobón | E10: =+[1]sales!G15 -> 1 | F10: =+_xlfn.XLOOKUP(sales[[#This Row],[Fecha]],OPEX_SALES!A:A,OPEX_SALES!B:B) -> 1 | G10: =+_xlfn.XLOOKUP(sales[[#This Row],[Fecha]],OPEX_SALES!A:A,OPEX_SALES!E:E) -> A) Día hábil | H10: =+TEXT(sales[[#This Row],[Fecha]],"ddd") -> lun | I10: =+sales[[#This Row],[Venta]]-sales[[#This Row],[costo_venta]] -> 1866.67 | J10: =[1]sales!K15 -> 3000 | K10: =[1]sales!I15 -> 3000 | L10: =[1]sales!J15 -> 0 | M10: =[1]sales!L15*sales[[#This Row],[cantidad]] -> 1133.33 | N10: =+(sales[[#This Row],[Venta]]-sales[[#This Row],[costo_venta]])/sales[[#This Row],[Venta]] -> 0.62222333
A11: =[1]sales!A16 -> 46076 | B11: =[1]sales!B16 -> 0.78722222 | C11: Normal | D11: =[1]sales!D16 -> Chorizo con papa/arepa | E11: =+[1]sales!G16 -> 1 | F11: =+_xlfn.XLOOKUP(sales[[#This Row],[Fecha]],OPEX_SALES!A:A,OPEX_SALES!B:B) -> 1 | G11: =+_xlfn.XLOOKUP(sales[[#This Row],[Fecha]],OPEX_SALES!A:A,OPEX_SALES!E:E) -> A) Día hábil | H11: =+TEXT(sales[[#This Row],[Fecha]],"ddd") -> lun | I11: =+sales[[#This Row],[Venta]]-sales[[#This Row],[costo_venta]] -> 3660 | J11: =[1]sales!K16 -> 8000 | K11: =[1]sales!I16 -> 8000 | L11: =[1]sales!J16 -> 0 | M11: =[1]sales!L16*sales[[#This Row],[cantidad]] -> 4340 | N11: =+(sales[[#This Row],[Venta]]-sales[[#This Row],[costo_venta]])/sales[[#This Row],[Venta]] -> 0.4575
A12: =[1]sales!A17 -> 46076 | B12: =[1]sales!B17 -> 0.79547454 | C12: Normal | D12: =[1]sales!D17 -> Chorizo con papa/arepa | E12: =+[1]sales!G17 -> 2 | F12: =+_xlfn.XLOOKUP(sales[[#This Row],[Fecha]],OPEX_SALES!A:A,OPEX_SALES!B:B) -> 1 | G12: =+_xlfn.XLOOKUP(sales[[#This Row],[Fecha]],OPEX_SALES!A:A,OPEX_SALES!E:E) -> A) Día hábil | H12: =+TEXT(sales[[#This Row],[Fecha]],"ddd") -> lun | I12: =+sales[[#This Row],[Venta]]-sales[[#This Row],[costo_venta]] -> 7320 | J12: =[1]sales!K17 -> 16000 | K12: =[1]sales!I17 -> 16000 | L12: =[1]sales!J17 -> 0 | M12: =[1]sales!L17*sales[[#This Row],[cantidad]] -> 8680 | N12: =+(sales[[#This Row],[Venta]]-sales[[#This Row],[costo_venta]])/sales[[#This Row],[Venta]] -> 0.4575
A13: =[1]sales!A18 -> 46076 | B13: =[1]sales!B18 -> 0.79547454 | C13: Normal | D13: =[1]sales!D18 -> BEBIDA - Coca Cola | E13: =+[1]sales!G18 -> 2 | F13: =+_xlfn.XLOOKUP(sales[[#This Row],[Fecha]],OPEX_SALES!A:A,OPEX_SALES!B:B) -> 1 | G13: =+_xlfn.XLOOKUP(sales[[#This Row],[Fecha]],OPEX_SALES!A:A,OPEX_SALES!E:E) -> A) Día hábil | H13: =+TEXT(sales[[#This Row],[Fecha]],"ddd") -> lun | I13: =+sales[[#This Row],[Venta]]-sales[[#This Row],[costo_venta]] -> 3600 | J13: =[1]sales!K18 -> 6000 | K13: =[1]sales!I18 -> 6000 | L13: =[1]sales!J18 -> 0 | M13: =[1]sales!L18*sales[[#This Row],[cantidad]] -> 2400 | N13: =+(sales[[#This Row],[Venta]]-sales[[#This Row],[costo_venta]])/sales[[#This Row],[Venta]] -> 0.6
A14: =[1]sales!A19 -> 46076 | B14: =[1]sales!B19 -> 0.81828704 | C14: Normal | D14: =[1]sales!D19 -> Chorizo con papa/arepa | E14: =+[1]sales!G19 -> 3 | F14: =+_xlfn.XLOOKUP(sales[[#This Row],[Fecha]],OPEX_SALES!A:A,OPEX_SALES!B:B) -> 1 | G14: =+_xlfn.XLOOKUP(sales[[#This Row],[Fecha]],OPEX_SALES!A:A,OPEX_SALES!E:E) -> A) Día hábil | H14: =+TEXT(sales[[#This Row],[Fecha]],"ddd") -> lun | I14: =+sales[[#This Row],[Venta]]-sales[[#This Row],[costo_venta]] -> 10980 | J14: =[1]sales!K19 -> 24000 | K14: =[1]sales!I19 -> 24000 | L14: =[1]sales!J19 -> 0 | M14: =[1]sales!L19*sales[[#This Row],[cantidad]] -> 13020 | N14: =+(sales[[#This Row],[Venta]]-sales[[#This Row],[costo_venta]])/sales[[#This Row],[Venta]] -> 0.4575
A15: =[1]sales!A20 -> 46076 | B15: =[1]sales!B20 -> 0.84164352 | C15: Normal | D15: =[1]sales!D20 -> Chorizo con papa/arepa | E15: =+[1]sales!G20 -> 1 | F15: =+_xlfn.XLOOKUP(sales[[#This Row],[Fecha]],OPEX_SALES!A:A,OPEX_SALES!B:B) -> 1 | G15: =+_xlfn.XLOOKUP(sales[[#This Row],[Fecha]],OPEX_SALES!A:A,OPEX_SALES!E:E) -> A) Día hábil | H15: =+TEXT(sales[[#This Row],[Fecha]],"ddd") -> lun | I15: =+sales[[#This Row],[Venta]]-sales[[#This Row],[costo_venta]] -> 3660 | J15: =[1]sales!K20 -> 8000 | K15: =[1]sales!I20 -> 8000 | L15: =[1]sales!J20 -> 0 | M15: =[1]sales!L20*sales[[#This Row],[cantidad]] -> 4340 | N15: =+(sales[[#This Row],[Venta]]-sales[[#This Row],[costo_venta]])/sales[[#This Row],[Venta]] -> 0.4575
... A448: =[1]sales!A453 -> 46101 | B448: =[1]sales!B453 -> 0.7947338 | C448: Normal | D448: =[1]sales!D453 -> Chorizo con papa/arepa | E448: =+[1]sales!G453 -> 2 | F448: =+_xlfn.XLOOKUP(sales[[#This Row],[Fecha]],OPEX_SALES!A:A,OPEX_SALES!B:B) -> 4 | G448: =+_xlfn.XLOOKUP(sales[[#This Row],[Fecha]],OPEX_SALES!A:A,OPEX_SALES!E:E) -> B) Viernes | H448: =+TEXT(sales[[#This Row],[Fecha]],"ddd") -> vie | I448: =+sales[[#This Row],[Venta]]-sales[[#This Row],[costo_venta]] -> 7320 | J448: =[1]sales!K453 -> 16000 | K448: =[1]sales!I453 -> 0 | L448: =[1]sales!J453 -> 16000 | M448: =[1]sales!L453*sales[[#This Row],[cantidad]] -> 8680 | N448: =+(sales[[#This Row],[Venta]]-sales[[#This Row],[costo_venta]])/sales[[#This Row],[Venta]] -> 0.4575

Sheet MP
C1: chorizo | D1: papa
A2: nombre_producto | B2: Costo | C2: 3500 | D2: 300
A3: Chorizo con papa/arepa | B3: =+SUMPRODUCT(C3:D3,C$2:D$2) -> 3500 | C3: 1 | D3: 0
A4: Chorizo solo | B4: =+SUMPRODUCT(C4:D4,C$2:D$2) -> 3500 | C4: 1
A5: Bandeja Choriboni - 25 | B5: =+SUMPRODUCT(C5:D5,C$2:D$2) -> 3500 | C5: 1
A6: Bandeja Choriboni - 30 | B6: =+SUMPRODUCT(C6:D6,C$2:D$2) -> 3500 | C6: 1
A7: Bandeja Choriboni - 35 | B7: =+SUMPRODUCT(C7:D7,C$2:D$2) -> 3500 | C7: 1
A8: BEBIDA - Aguila | B8: =+SUMPRODUCT(C8:D8,C$2:D$2) -> 0
A9: BEBIDA - Botella de Agua | B9: =+SUMPRODUCT(C9:D9,C$2:D$2) -> 0
A10: BEBIDA - Coca Cola | B10: =+SUMPRODUCT(C10:D10,C$2:D$2) -> 0
A11: BEBIDA - Coca Cola ZERO | B11: =+SUMPRODUCT(C11:D11,C$2:D$2) -> 0
A12: BEBIDA - Jugo Hit | B12: =+SUMPRODUCT(C12:D12,C$2:D$2) -> 0
A13: BEBIDA - Postobón | B13: =+SUMPRODUCT(C13:D13,C$2:D$2) -> 0
A14: CARNES - Carne asada - 20 | B14: =+SUMPRODUCT(C14:D14,C$2:D$2) -> 0
A15: CARNES - Carne asada 23 | B15: =+SUMPRODUCT(C15:D15,C$2:D$2) -> 0
A16: CARNES - Carne Asada de 40 | B16: =+SUMPRODUCT(C16:D16,C$2:D$2) -> 0
A17: CARNES - Costillas BBQ - 50 | B17: =+SUMPRODUCT(C17:D17,C$2:D$2) -> 0
A18: CARNES - Media carne | B18: =+SUMPRODUCT(C18:D18,C$2:D$2) -> 0
A19: CARNES - Mojarra | B19: =+SUMPRODUCT(C19:D19,C$2:D$2) -> 0
A20: chorixo solo | B20: =+SUMPRODUCT(C20:D20,C$2:D$2) -> 3500 | C20: 1
A21: Ham. combo | B21: =+SUMPRODUCT(C21:D21,C$2:D$2) -> 0
A22: Ham. Doble combo - ELIMINAR | B22: =+SUMPRODUCT(C22:D22,C$2:D$2) -> 0
A23: Ham. sencilla | B23: =+SUMPRODUCT(C23:D23,C$2:D$2) -> 0
A24: Parrillada de 30 | B24: =+SUMPRODUCT(C24:D24,C$2:D$2) -> 0
A25: Parrillada de 35 | B25: =+SUMPRODUCT(C25:D25,C$2:D$2) -> 0
A26: Parrillada de 40 | B26: =+SUMPRODUCT(C26:D26,C$2:D$2) -> 0
A27: Parrillada de 48 | B27: =+SUMPRODUCT(C27:D27,C$2:D$2) -> 0
A28: Parrillada de 60 | B28: =+SUMPRODUCT(C28:D28,C$2:D$2) -> 0
A29: Parrillada de 70 | B29: =+SUMPRODUCT(C29:D29,C$2:D$2) -> 0
A30: PROMO pedazo de carne | B30: =+SUMPRODUCT(C30:D30,C$2:D$2) -> 0
A31: PROMO: promo vecino de jenesano | B31: =+SUMPRODUCT(C31:D31,C$2:D$2) -> 0
A32: Propina - Gustavo | B32: =+SUMPRODUCT(C32:D32,C$2:D$2) -> 0
A33: Tinto | B33: =+SUMPRODUCT(C33:D33,C$2:D$2) -> 0
A34: z. MP - Chorizo CRUDO | B34: =+SUMPRODUCT(C34:D34,C$2:D$2) -> 3500 | C34: 1
A35: z. MP - Hamb. CRUDA | B35: =+SUMPRODUCT(C35:D35,C$2:D$2) -> 0

Sheet Historia
A1: Etiquetas de fila | B1: Suma de Venta | C1: Suma de MG
A2: 46076 | B2: 225000 | C2: 90000 | D2: Histórico
A3: 46077 | B3: 221500 | C3: 88600 | D3: Histórico
A4: 46078 | B4: 390500 | C4: 156200 | D4: Histórico
A5: 46079 | B5: 209000 | C5: 83600 | D5: Histórico
A6: 46080 | B6: 248500 | C6: 99400 | D6: Histórico
A7: 46081 | B7: 504000 | C7: 201600 | D7: Histórico
A8: 46083 | B8: 60000 | C8: 24000 | D8: Histórico
A9: 46084 | B9: 169000 | C9: 67600 | D9: Histórico
A10: 46085 | B10: 344000 | C10: 137600 | D10: Histórico
A11: 46086 | B11: 259000 | C11: 103600 | D11: Histórico
A12: 46088 | B12: 298500 | C12: 119400 | D12: Histórico
A13: 46089 | B13: 219500 | C13: 87800 | D13: Histórico
... A26: 46103 | B26: 11000 | C26: 4400 | D26: Histórico
D27: Histórico
D28: Histórico
D29: Histórico
D30: Histórico
D31: Histórico
D32: Histórico
D33: Histórico
D34: Histórico
D35: Histórico
D36: Histórico
D37: Histórico
D38: Histórico
... D150: Histórico

Sheet products
A1: nombre_producto | B1: precio_producto | C1: costo_producto
A2: Chorizo | B2: 8000 | C2: =3500+8000 -> 11500
A3: Hit | B3: 4500 | C3: 2416.6667
A4: Coca cola | B4: 3000 | C4: 1200
A5: Agua | B5: 3000 | C5: 1200
A6: Postobon | B6: 3000 | C6: 1166.6667 | F6: agua | G6: 33000 | H6: 24 | I6: =+G6/H6 -> 1375
A7: Chori- CRUDO | B7: 4500 | C7: 3500 | F7: hit | G7: 29000 | H7: 12 | I7: =+G7/H7 -> 2416.6667
A8: parri tres carnes | B8: 35000 | C8: 25000 | F8: postobon | G8: 35000 | H8: 30 | I8: =+G8/H8 -> 1166.6667
A9: carne + chorizo | B9: 25000 | C9: 15000 | F9: coca cola | G9: 36000 | H9: 30 | I9: =+G9/H9 -> 1200
A10: tinto | B10: 2000 | C10: 800
A11: parri 48 | B11: 48000 | C11: 30000
A12: parri 70 | B12: 70000 | C12: 45000
A13: parri 40 | B13: 40000 | C13: 25000

Sheet Forecast
D1: Marzo | I1: Forecast | N1: Target
A3: Suma de Venta | B3: Semana | J3: =+AVERAGE(J5:J11) -> 247125 | O3: =+AVERAGE(O5:O11) -> #DIV/0!
A4: Día | B4: 1 | C4: 2 | D4: 3 | E4: 4 | I4: Día | J4: Forecast | K4: MG estim | L4: ∆% | N4: Día | P4: ∆%
A5: lun | B5: 225000 | C5: 60000 | D5: 248500 | E5: 124000 | I5: lun | J5: =+AVERAGE(B5:E5) -> 164375 | K5: =+J5*0.4 -> 65750 | L5: =+J5/D5-1 -> -0.33853119 | N5: lun | P5: =+O5/J5-1 -> -1
A6: mar | B6: 221500 | C6: 169000 | D6: 94000 | E6: 314000 | I6: mar | J6: =+AVERAGE(B6:E6) -> 199625 | K6: =+J6*0.4 -> 79850 | L6: =+J6/D6-1 -> 1.1236702 | N6: mar | P6: =+O6/J6-1 -> -1
A7: mié | B7: 390500 | C7: 344000 | D7: 473500 | E7: 149000 | I7: mié | J7: =+AVERAGE(B7:E7) -> 339250 | K7: =+J7*0.4 -> 135700 | L7: =+J7/C7-1 -> -0.01380814 | N7: mié | P7: =+O7/J7-1 -> -1
A8: jue | B8: 209000 | C8: 259000 | D8: 243000 | E8: 388900 | I8: jue | J8: =+AVERAGE(B8:E8) -> 274975 | K8: =+J8*0.4 -> 109990 | L8: =+J8/C8-1 -> 0.061679537 | N8: jue | P8: =+O8/J8-1 -> -1
A9: vie | B9: 248500 | D9: 132500 | E9: 172700 | I9: vie | J9: =+AVERAGE(B9:E9) -> 184566.67 | K9: =+J9*0.4 -> 73826.667 | L9: =+J9/B9-1 -> -0.257277 | N9: vie | P9: =+O9/J9-1 -> -1
A10: sáb | B10: 504000 | C10: 298500 | D10: 392500 | I10: sáb | J10: =+AVERAGE(B10:D10) -> 398333.33 | K10: =+J10*0.4 -> 159333.33 | L10: =+J10/C10-1 -> 0.33445003 | N10: sáb | P10: =+O10/J10-1 -> -1
A11: dom | C11: 219500 | D11: 118000 | E11: 11000 | I11: dom | J11: =+AVERAGE(B11:D11) -> 168750 | K11: =+J11*0.4 -> 67500 | L11: =+J11/C11-1 -> -0.23120729 | N11: dom | P11: =+O11/J11-1 -> -1
A12: Total general | B12: 1798500 | C12: 1350000 | D12: 1702000 | E12: 1159600 | I12: Total general | J12: =+AVERAGE(B12:D12) -> 1616833.3 | K12: =+J12*0.4 -> 646733.33 | L12: =+J12/C12-1 -> 0.19765432 | N12: Total general | P12: =+O12/J12-1 -> -1
C13: =+C12/B12-1 -> -0.24937448 | D13: =+D12/C12-1 -> 0.26074074 | E13: =+E12/D12-1 -> -0.3186839
A16: Día | B16: 1 | C16: 2 | D16: 3 | E16: 4
A17: lun | B17: 0 | C17: =+C5/B5-1 -> -0.73333333 | D17: =+D5/C5-1 -> 3.1416667 | E17: =+E5/D5-1 -> -0.50100604
A18: mar | B18: 0 | C18: =+C6/B6-1 -> -0.23702032 | D18: =+D6/C6-1 -> -0.44378698 | E18: =+E6/D6-1 -> 2.3404255
A19: mié | B19: 0 | C19: =+C7/B7-1 -> -0.1190781 | D19: =+D7/C7-1 -> 0.37645349 | E19: =+E7/D7-1 -> -0.68532207
A20: jue | B20: 0 | C20: =+C8/B8-1 -> 0.23923445 | D20: =+D8/C8-1 -> -0.061776062 | E20: =+E8/D8-1 -> 0.60041152
A21: vie | B21: 0 | C21: =+C9/B9-1 -> -1 | D21: =+D9/C9-1 -> #DIV/0! | E21: =+E9/D9-1 -> 0.30339623
A22: sáb | B22: 0 | C22: =+C10/B10-1 -> -0.4077381 | D22: =+D10/C10-1 -> 0.31490787 | E22: =+E10/D10-1 -> -1
A23: dom | B23: 0 | C23: =+C11/B11-1 -> #DIV/0! | D23: =+D11/C11-1 -> -0.46241458 | E23: =+E11/D11-1 -> -0.90677966
A24: Total general | B24: 0 | C24: =+C12/B12-1 -> -0.24937448 | D24: =+D12/C12-1 -> 0.26074074 | E24: =+E12/D12-1 -> -0.3186839
A26: Día | B26: 1 | C26: 2 | D26: 3 | E26: 3
A27: lun | C27: =+C5-B5 -> -165000 | D27: =+D5-C5 -> 188500 | E27: =+E5-D5 -> -124500
A28: mar | C28: =+C6-B6 -> -52500 | D28: =+D6-C6 -> -75000 | E28: =+E6-D6 -> 220000
A29: mié | C29: =+C7-B7 -> -46500 | D29: =+D7-C7 -> 129500 | E29: =+E7-D7 -> -324500
A30: jue | C30: =+C8-B8 -> 50000 | D30: =+D8-C8 -> -16000 | E30: =+E8-D8 -> 145900
A31: vie | C31: =+C9-B9 -> -248500 | D31: =+D9-C9 -> 132500 | E31: =+E9-D9 -> 40200
A32: sáb | C32: =+C10-B10 -> -205500 | D32: =+D10-C10 -> 94000 | E32: =+E10-D10 -> -392500
A33: dom | B33: 0 | C33: =+C11-B11 -> 219500 | D33: =+D11-C11 -> -101500 | E33: =+E11-D11 -> -107000
A34: Total general | B34: 0 | C34: =+C12-B12 -> -448500 | D34: =+D12-C12 -> 352000 | E34: =+E12-D12 -> -542400

Sheet Activos
B4: Tipo de obligación | C4: Proveedor | D4: Nombre proveedor | E4: Valor | F4: Plan B | H4: Tipo de gasto | I4: Valor | K4: Activo | L4: Patrimonio | M4: =+M5+M6 -> 18150000 | N4: =+M4/$K$5 -> 0.61570257
B5: Pasivo de corto plazo | C5: FINANCIERO | D5: Gota x Gota | E5: 350000 | F5: 0 | H5: Mes de Arriendo Marzo | I5: 1000000 | K5: =+M4+M7 -> 29478519 | L5: Planta y Equipo | M5: =+Planta_y_Equipo[[#Totals],[Valor]] -> 16020000 | N5: =+M5/$M$4 -> 0.88264463
B6: Pasivo de corto plazo | C6: ARRIENDO | D6: Arredatario | E6: 0 | F6: 0 | H6: Arriendo Apto. Marzo | I6: =550000/2 -> 275000 | L6: Inventario (Stock) | M6: =+Stock_Actual[[#Totals],[Valor]] -> 2130000 | N6: =+M6/$M$4 -> 0.11735537
B7: Pasivo de corto plazo | C7: Carne de cerdo | D7: Diego | E7: 1088000 | F7: 0 | H7: Acarreo | I7: 200000 | L7: Pasivo Total | M7: =+M8+M9 -> 11328519 | N7: =+M7/$K$5 -> 0.38429743 | O7: =+M7/M4 -> 0.62416083 | P7: =+M4-M7 -> 6821481
B8: Pasivo de corto plazo | C8: Carne de res | D8: Vecino | E8: 380000 | F8: 0 | H8: Publidad tarjeteria | I8: 100000 | L8: Pasivo de corto plazo | M8: =+SUMIF(B5:B23,L8,E5:E23) -> 4728920 | N8: =+M8/$M$7 -> 0.41743497
B9: Pasivo de corto plazo | C9: Carne de Pollo | D9: Nd | E9: 750000 | F9: 0 | H9: Total | I9: =SUBTOTAL(109,Gastos_entrada[Valor]) -> 1575000 | L9: Pasivo de largo plazo | M9: =+SUMIF(B5:B23,L9,E5:E23) -> 6599599 | N9: =+M9/$M$7 -> 0.58256503
B10: Pasivo de corto plazo | C10: NOMINA | D10: Nomina | E10: 150000 | F10: 0
B11: Pasivo de corto plazo | C11: PUBLICIDAD | D11: Nd | E11: 400000 | F11: =+E11 -> 400000 | M11: Ideal | N11: Actual
B12: Pasivo de corto plazo | C12: Pintura, local | D12: Nd | E12: 370000 | F12: 0 | L12: Nivel de Endeudamiento (NE) | M12: =+M15/K5 -> 0.15604583 | N12: =+M7/K5 -> 0.38429743 | O12: Nivel de endeudamiento crítico
B13: Pasivo de corto plazo | C13: Vitrina, ollas | D13: Vitrina, ollas | E13: 180000 | F13: 0 | L13: Autonomía | M13: =M15/M4 -> 0.25344353 | N13: =+M7/M4 -> 0.62416083 | O13: El 70% del patrimonio esta comprometido con deudas
B14: Pasivo de corto plazo | C14: CODENSA | D14: enel - 6451508-5 | E14: 1060920 | F14: =+E14 -> 1060920
B15: Pasivo de corto plazo | C15: Arriendo Apto. | D15: Sandra | E15: 0 | F15: =+E15 -> 0 | L15: Meta ideal deuda | M15: =$I$54 -> 4600000
B16: Pasivo de corto plazo | C16: Contingencia: Gas | D16: Ladron de Gas | E16: 0 | F16: 0 | L16: Meta a Pagar | M16: =+M7-M15 -> 6728519
B17: Pasivo de corto plazo | C17: Contingencia: Licuadora | D17: Licuadora | E17: 0 | F17: 0
B18: Pasivo de largo plazo | C18: FINANCIERO | D18: Saul | E18: 3000000 | F18: 0
B19: Pasivo de largo plazo | C19: Carne de cerdo | D19: Martin | E19: 300000 | F19: 0
B20: Pasivo de largo plazo | C20: Carne de cerdo | D20: Sarmiento | E20: 350000 | F20: 0
B21: Pasivo de largo plazo | C21: Carne de res | D21: Leornardo | E21: 1350000 | F21: 100000
B22: Pasivo de largo plazo | C22: Menudo y prestamo | D22: Hector | E22: 0 | F22: 0
B23: Pasivo de largo plazo | C23: Mercado | D23: Orlando | E23: 1599599 | F23: =+SUM(F5:F22) -> 1560920
B24: Total general | E24: 11328519
B34: Inversion Proyecto | C34: Origen Equipo | D34: Valor | H34: Materia Prima | I34: Valor
B35: Horno de pollos | C35: Nuevo | D35: 10000000 | H35: Carne | I35: 200000
B36: Bicicleta - Parrilla | C36: Propio | D36: 1800000 | H36: Pollo | I36: =50*20000 -> 1000000 | K36: 50 pollos
B37: olla arrocera | C37: Antiguo | D37: 600000 | H37: Hamburguesa | I37: 0 | K37: 25.000 a 10 cada
B38: Nevera | C38: Antiguo | D38: 600000 | H38: Bebidas | I38: 280000 | K38: 49 gaseosas litro y media
B39: Mesas 4 meseras | C39: Antiguo | D39: 500000 | H39: Sazón | I39: 300000 | K39: gaseosas pequeñas 50
B40: Estufa | C40: Nuevo | D40: 480000 | H40: Cerdo | I40: 0
B41: Campana | C41: Nuevo | D41: 320000 | H41: Mercado y Hamburguesa | I41: 200000 | K41: Sason para un mes | L41: 200000
B42: Licuadrora | C42: Nuevo | D42: 200000 | H42: Pescado | I42: 150000
B43: olla espres | C43: Antiguo | D43: 200000 | H43: Total | I43: =SUBTOTAL(109,Stock_Actual[Valor]) -> 2130000
B44: Platos, cubiertos, Tablas bajijas de plasticos | C44: Antiguo | D44: 200000
B45: Extractor | C45: Antiguo | D45: 200000
B46: Equipo de sonido | C46: Antiguo | D46: 150000 | H46: Materia Prima | I46: Valor
B47: Platero | C47: Nuevo | D47: 120000 | H47: Carne | I47: 1500000
B48: Mesa para lavar pollo | C48: Antiguo | D48: 120000 | H48: Pollo | I48: =50*20000 -> 1000000
B49: Otras ollas | C49: Antiguo | D49: 100000 | H49: Bebidas | I49: 800000 | K49: 50 pollos un millon | M49: 60.000 por millar
B50: Mesa para dejar ollas | C50: Antiguo | D50: 90000 | H50: Sazón | I50: 300000 | M50: 35000 por millar
B51: Bascula | C51: Nuevo | D51: 70000 | H51: Cerdo | I51: 500000
B52: Mesa madera | C52: Antiguo | D52: 70000 | H52: Mercado y Hamburguesa | I52: 200000
B53: Botes de basura | C53: Antiguo | D53: =35000*2 -> 70000 | H53: Pescado | I53: 300000
B54: Bicicleta | C54: Antiguo | D54: 70000 | H54: Total | I54: =SUBTOTAL(109,Stock_Ideal[Valor]) -> 4600000
B55: Mesa bajita de metal | C55: Antiguo | D55: 60000
B56: Total | D56: =SUBTOTAL(109,Planta_y_Equipo[Valor]) -> 16020000

Sheet Ingresos
A2: Tipo día | B2: (Todas) | W2: Venta | X2: Promedio Venta | AQ2: Tipo día | AR2: (Todas)
W3: 6010100 | X3: 13445.414
A4: Fecha | B4: Día | C4: Venta | AJ4: Fecha | AK4: Día | AL4: Venta | AQ4: Fecha | AR4: Día
A5: 46076 | B5: lun | C5: 225000 | AJ5: 46076 | AK5: lun | AL5: 225000 | AQ5: 46076 | AR5: lun
A6: 46077 | B6: mar | C6: 221500 | W6: Tendencia | X6: Ventas | Y6: Rentabilidad | Z6: Gastos | AA6: Utilidad trabajo | AB6: E (Renta) | AC6: Target MC | AD6: Target Ventas | AJ6: 46077 | AK6: mar | AL6: 221500 | AQ6: 46077 | AR6: mar
A7: 46078 | B7: mié | C7: 390500 | W7: Días trascurridos | X7: =+SUBTOTAL(3,B5:B1048576) -> 25 | AJ7: 46078 | AK7: mié | AL7: 390500 | AQ7: 46078 | AR7: mié
A8: 46079 | B8: jue | C8: 209000 | W8: Rentabilidad x día | X8: =+SUBTOTAL(9,D5:D1048576)/SUBTOTAL(3,B5:B1048576) -> 0 | Y8: =+SUBTOTAL(9,E5:E1048576)/SUBTOTAL(3,B5:B1048576) -> 0 | Z8: =+SUBTOTAL(9,F5:F1048576)/SUBTOTAL(3,B5:B1048576) -> 0 | AA8: =+Y8-Z8 -> 0 | AB8: =+AB9/30 -> 53333.333 | AC8: =+AB8+Z8 -> 53333.333 | AD8: =+AD9/30 -> 177777.78 | AF8: 143241 | AJ8: 46079 | AK8: jue | AL8: 209000 | AQ8: 46079 | AR8: jue
A9: 46080 | B9: vie | C9: 248500 | W9: Rentabilidad x mes | X9: =+X8*30 -> 0 | Y9: =+Y8*30 -> 0 | Z9: =+Z8*30 -> 0 | AA9: =+AA8*30 -> 0 | AB9: =+(20000*30)+1000000 -> 1600000 | AC9: =+AB9+Z9 -> 1600000 | AD9: =(AC9*100)/30 -> 5333333.3 | AF9: 174333.33 | AG9: =+AF9/AF8 -> 1.2170631 | AH9: =+AF9-AF8 -> 31092.333 | AJ9: 46080 | AK9: vie | AL9: 248500 | AQ9: 46080 | AR9: vie
A10: 46081 | B10: sáb | C10: 504000 | AJ10: 46081 | AK10: sáb | AL10: 504000 | AQ10: 46081 | AR10: sáb
A11: 46085 | B11: mié | C11: 344000 | X11: Ventas | Y11: Rentabilidad | Z11: Gastos | AA11: Ganacia / Nomina | AB11: % Target | AC11: Target Día | AD11: Target % | AJ11: 46085 | AK11: mié | AL11: 344000 | AQ11: 46085 | AR11: mié
A12: 46086 | B12: jue | C12: 259000 | W12: lunes | X12: =+AVERAGEIF($C$5:$C$1048576,$W12,$D$5:$D$1048576) -> #DIV/0! | Y12: =+AVERAGEIF($C$5:$C$1048576,W12,$E$5:$E$1048576) -> #DIV/0! | Z12: =+AVERAGEIF($C$5:$C$1048576,W12,$F$5:$F$1048576) -> #DIV/0! | AA12: =+Y12-Z12 -> #DIV/0! | AB12: =+X12/$X$20 -> #DIV/0! | AC12: =+AB12*$AD$8 -> #DIV/0! | AD12: =+AC12/X12-1 -> #DIV/0! | AJ12: 46086 | AK12: jue | AL12: 259000 | AQ12: 46086 | AR12: jue
A13: 46083 | B13: lun | C13: 60000 | W13: martes | X13: =+AVERAGEIF($C$5:$C$1048576,$W13,$D$5:$D$1048576) -> #DIV/0! | Y13: =+AVERAGEIF($C$5:$C$1048576,W13,$E$5:$E$1048576) -> #DIV/0! | Z13: =+AVERAGEIF($C$5:$C$1048576,W13,$F$5:$F$1048576) -> #DIV/0! | AA13: =+Y13-Z13 -> #DIV/0! | AB13: =+X13/$X$20 -> #DIV/0! | AC13: =+AB13*$AD$8 -> #DIV/0! | AD13: =+AC13/X13-1 -> #DIV/0! | AJ13: 46083 | AK13: lun | AL13: 60000 | AQ13: 46083 | AR13: lun
A14: 46084 | B14: mar | C14: 169000 | W14: miércoles | X14: =+AVERAGEIF($C$5:$C$1048576,$W14,$D$5:$D$1048576) -> #DIV/0! | Y14: =+AVERAGEIF($C$5:$C$1048576,W14,$E$5:$E$1048576) -> #DIV/0! | Z14: =+AVERAGEIF($C$5:$C$1048576,W14,$F$5:$F$1048576) -> #DIV/0! | AA14: =+Y14-Z14 -> #DIV/0! | AB14: =+X14/$X$20 -> #DIV/0! | AC14: =+AB14*$AD$8 -> #DIV/0! | AD14: =+AC14/X14-1 -> #DIV/0! | AJ14: 46084 | AK14: mar | AL14: 169000 | AQ14: 46084 | AR14: mar
A15: 46088 | B15: sáb | C15: 298500 | W15: jueves | X15: =+AVERAGEIF($C$5:$C$1048576,$W15,$D$5:$D$1048576) -> #DIV/0! | Y15: =+AVERAGEIF($C$5:$C$1048576,W15,$E$5:$E$1048576) -> #DIV/0! | Z15: =+AVERAGEIF($C$5:$C$1048576,W15,$F$5:$F$1048576) -> #DIV/0! | AA15: =+Y15-Z15 -> #DIV/0! | AB15: =+X15/$X$20 -> #DIV/0! | AC15: =+AB15*$AD$8 -> #DIV/0! | AD15: =+AC15/X15-1 -> #DIV/0! | AJ15: 46088 | AK15: sáb | AL15: 298500 | AQ15: 46088 | AR15: sáb
A16: 46089 | B16: dom | C16: 219500 | W16: viernes | X16: =+AVERAGEIF($C$5:$C$1048576,$W16,$D$5:$D$1048576) -> #DIV/0! | Y16: =+AVERAGEIF($C$5:$C$1048576,W16,$E$5:$E$1048576) -> #DIV/0! | Z16: =+AVERAGEIF($C$5:$C$1048576,W16,$F$5:$F$1048576) -> #DIV/0! | AA16: =+Y16-Z16 -> #DIV/0! | AB16: =+X16/$X$20 -> #DIV/0! | AC16: =+AB16*$AD$8 -> #DIV/0! | AD16: =+AC16/X16-1 -> #DIV/0! | AJ16: 46089 | AK16: dom | AL16: 219500 | AQ16: 46089 | AR16: dom
A17: 46090 | B17: lun | C17: 248500 | W17: sábado | X17: =+AVERAGEIF($C$5:$C$1048576,$W17,$D$5:$D$1048576) -> #DIV/0! | Y17: =+AVERAGEIF($C$5:$C$1048576,W17,$E$5:$E$1048576) -> #DIV/0! | Z17: =+AVERAGEIF($C$5:$C$1048576,W17,$F$5:$F$1048576) -> #DIV/0! | AA17: =+Y17-Z17 -> #DIV/0! | AB17: =+X17/$X$20 -> #DIV/0! | AC17: =+AB17*$AD$8 -> #DIV/0! | AD17: =+AC17/X17-1 -> #DIV/0! | AJ17: 46090 | AK17: lun | AL17: 248500 | AQ17: 46090 | AR17: lun
A18: 46091 | B18: mar | C18: 94000 | W18: domingo | X18: =+AVERAGEIF($C$5:$C$1048576,$W18,$D$5:$D$1048576) -> #DIV/0! | Y18: =+AVERAGEIF($C$5:$C$1048576,W18,$E$5:$E$1048576) -> #DIV/0! | Z18: =+AVERAGEIF($C$5:$C$1048576,W18,$F$5:$F$1048576) -> #DIV/0! | AA18: =+Y18-Z18 -> #DIV/0! | AB18: =+X18/$X$20 -> #DIV/0! | AC18: =+AB18*$AD$8 -> #DIV/0! | AD18: =+AC18/X18-1 -> #DIV/0! | AJ18: 46091 | AK18: mar | AL18: 94000 | AQ18: 46091 | AR18: mar
A19: 46092 | B19: mié | C19: 473500 | AJ19: 46092 | AK19: mié | AL19: 473500 | AQ19: 46092 | AR19: mié
A20: 46093 | B20: jue | C20: 243000 | X20: =+AVERAGE(X12:X18) -> #DIV/0! | Y20: =+AVERAGE(Y12:Y18) -> #DIV/0! | Z20: =+AVERAGE(Z12:Z18) -> #DIV/0! | AC20: =+AVERAGE(AC12:AC18) -> #DIV/0! | AD20: =+AC20/X20-1 -> #DIV/0! | AJ20: 46093 | AK20: jue | AL20: 243000 | AQ20: 46093 | AR20: jue
A21: 46094 | B21: vie | C21: 132500 | X21: =+AVERAGE(X12:X15) -> #DIV/0! | Y21: =+AVERAGE(Y12:Y15) -> #DIV/0! | Z21: =+AVERAGE(Z12:Z15) -> #DIV/0! | AJ21: 46094 | AK21: vie | AL21: 132500 | AQ21: 46094 | AR21: vie
A22: 46095 | B22: sáb | C22: 392500 | AJ22: 46095 | AK22: sáb | AL22: 392500 | AQ22: 46095 | AR22: sáb
A23: 46096 | B23: dom | C23: 118000 | AB23: =15000*30 -> 450000 | AJ23: 46096 | AK23: dom | AL23: 118000 | AQ23: 46096 | AR23: dom
A24: 46097 | B24: lun | C24: 124000 | AJ24: 46097 | AK24: lun | AL24: 124000 | AQ24: 46097 | AR24: lun
A25: 46098 | B25: mar | C25: 314000 | AJ25: 46098 | AK25: mar | AL25: 314000 | AQ25: 46098 | AR25: mar
A26: 46099 | B26: mié | C26: 149000 | AJ26: 46099 | AK26: mié | AL26: 149000 | AQ26: 46099 | AR26: mié
A27: 46100 | B27: jue | C27: 388900 | AJ27: 46100 | AK27: jue | AL27: 388900 | AQ27: 46100 | AR27: jue
A28: 46101 | B28: vie | C28: 172700 | AJ28: 46101 | AK28: vie | AL28: 172700 | AQ28: 46101 | AR28: vie
A29: 46103 | B29: dom | C29: 11000 | AJ29: 46103 | AK29: dom | AL29: 11000 | AQ29: 46103 | AR29: dom

Sheet Cuentas x Pagar
A5: Nombre proveedor | B5: Descripción | C5: Estado Tesoreria | D5: Saldo nuevo admón
A6: José Gustavo | B6: Chorizos | C6: Congelado
A7: Gaseosa | B7: Gaseosas, Coca Cola, Hit y Agua | C7: Pagar Urgente
B8: Total

Sheet Opex (2)
B1: Tipo | C1: Fecha | D1: Mes | E1: Arriendo | F1: No. Días Arriendo | G1: Día Arriendo | H1: Gas | I1: No. Días Gas | J1: Consumo (m3) | K1: Costo prom. Gas | L1: Día Gas | M1: Agua | N1: Dìa Agua | O1: Energia | P1: Financiació Energia | Q1: No. Días Energia | R1: Consumo (KhW | S1: Costo prom. Energia | T1: Fecha corte enega | U1: Día Energia
B2: Histórico | C2: 43624 | D2: =+TEXT(C2,"mmmm") -> junio | E2: 1000000 | G2: =IFERROR(Opex9[[#This Row],[Arriendo]]/Opex9[[#This Row],[No. Días Arriendo]],0) -> 0 | H2: 430 | I2: 0 | J2: 0 | K2: =IFERROR(Opex9[[#This Row],[Gas]]/Opex9[[#This Row],[Consumo (m3)]],0) -> 0 | L2: =IFERROR(Opex9[[#This Row],[Gas]]/Opex9[[#This Row],[No. Días Arriendo]],0) -> 0 | N2: =IFERROR(Opex9[[#This Row],[Agua]]/Opex9[[#This Row],[No. Días Arriendo]],0) -> 0 | Q2: =+X2 -> 0 | S2: =IFERROR(Opex9[[#This Row],[Energia]]/Opex9[[#This Row],[Consumo (KhW]],0) -> 0 | U2: =IFERROR(Opex9[[#This Row],[Energia]]/Opex9[[#This Row],[No. Días Arriendo]],0) -> 0
B3: Histórico | C3: 43654 | D3: =+TEXT(C3,"mmmm") -> julio | E3: 1000000 | G3: =IFERROR(Opex9[[#This Row],[Arriendo]]/Opex9[[#This Row],[No. Días Arriendo]],0) -> 0 | H3: 88870 | I3: =+F2 -> 0 | J3: 112 | K3: =IFERROR(Opex9[[#This Row],[Gas]]/Opex9[[#This Row],[Consumo (m3)]],0) -> 793.48214 | L3: =IFERROR(Opex9[[#This Row],[Gas]]/Opex9[[#This Row],[No. Días Arriendo]],0) -> 0 | N3: =IFERROR(Opex9[[#This Row],[Agua]]/Opex9[[#This Row],[No. Días Arriendo]],0) -> 0 | Q3: =+X3 -> 0 | S3: =IFERROR(Opex9[[#This Row],[Energia]]/Opex9[[#This Row],[Consumo (KhW]],0) -> 0 | U3: =IFERROR(Opex9[[#This Row],[Energia]]/Opex9[[#This Row],[No. Días Arriendo]],0) -> 0
B4: Histórico | C4: 43685 | D4: =+TEXT(C4,"mmmm") -> agosto | E4: 1000000 | G4: =IFERROR(Opex9[[#This Row],[Arriendo]]/Opex9[[#This Row],[No. Días Arriendo]],0) -> 0 | H4: 201040 | I4: =+F3 -> 0 | J4: 233 | K4: =IFERROR(Opex9[[#This Row],[Gas]]/Opex9[[#This Row],[Consumo (m3)]],0) -> 862.83262 | L4: =IFERROR(Opex9[[#This Row],[Gas]]/Opex9[[#This Row],[No. Días Arriendo]],0) -> 0 | N4: =IFERROR(Opex9[[#This Row],[Agua]]/Opex9[[#This Row],[No. Días Arriendo]],0) -> 0 | Q4: =+X4 -> 0 | S4: =IFERROR(Opex9[[#This Row],[Energia]]/Opex9[[#This Row],[Consumo (KhW]],0) -> 0 | U4: =IFERROR(Opex9[[#This Row],[Energia]]/Opex9[[#This Row],[No. Días Arriendo]],0) -> 0
B5: Histórico | C5: 43715 | D5: =+TEXT(C5,"mmmm") -> septiembre | E5: 1000000 | G5: =IFERROR(Opex9[[#This Row],[Arriendo]]/Opex9[[#This Row],[No. Días Arriendo]],0) -> 0 | H5: 177990 | I5: =+F4 -> 0 | J5: 209 | K5: =IFERROR(Opex9[[#This Row],[Gas]]/Opex9[[#This Row],[Consumo (m3)]],0) -> 851.62679 | L5: =IFERROR(Opex9[[#This Row],[Gas]]/Opex9[[#This Row],[No. Días Arriendo]],0) -> 0 | N5: =IFERROR(Opex9[[#This Row],[Agua]]/Opex9[[#This Row],[No. Días Arriendo]],0) -> 0 | Q5: =+X5 -> 0 | S5: =IFERROR(Opex9[[#This Row],[Energia]]/Opex9[[#This Row],[Consumo (KhW]],0) -> 0 | U5: =IFERROR(Opex9[[#This Row],[Energia]]/Opex9[[#This Row],[No. Días Arriendo]],0) -> 0
B6: Histórico | C6: 43745 | D6: =+TEXT(C6,"mmmm") -> octubre | E6: 1000000 | G6: =IFERROR(Opex9[[#This Row],[Arriendo]]/Opex9[[#This Row],[No. Días Arriendo]],0) -> 0 | H6: 174280 | I6: =+F5 -> 0 | J6: 201 | K6: =IFERROR(Opex9[[#This Row],[Gas]]/Opex9[[#This Row],[Consumo (m3)]],0) -> 867.06468 | L6: =IFERROR(Opex9[[#This Row],[Gas]]/Opex9[[#This Row],[No. Días Arriendo]],0) -> 0 | N6: =IFERROR(Opex9[[#This Row],[Agua]]/Opex9[[#This Row],[No. Días Arriendo]],0) -> 0 | Q6: =+X6 -> 0 | S6: =IFERROR(Opex9[[#This Row],[Energia]]/Opex9[[#This Row],[Consumo (KhW]],0) -> 0 | U6: =IFERROR(Opex9[[#This Row],[Energia]]/Opex9[[#This Row],[No. Días Arriendo]],0) -> 0
B7: Histórico | C7: 43777 | D7: =+TEXT(C7,"mmmm") -> noviembre | E7: 1000000 | G7: =IFERROR(Opex9[[#This Row],[Arriendo]]/Opex9[[#This Row],[No. Días Arriendo]],0) -> 0 | H7: 181790 | I7: =+F6 -> 0 | J7: 201 | K7: =IFERROR(Opex9[[#This Row],[Gas]]/Opex9[[#This Row],[Consumo (m3)]],0) -> 904.42786 | L7: =IFERROR(Opex9[[#This Row],[Gas]]/Opex9[[#This Row],[No. Días Arriendo]],0) -> 0 | N7: =IFERROR(Opex9[[#This Row],[Agua]]/Opex9[[#This Row],[No. Días Arriendo]],0) -> 0 | Q7: =+X7 -> 0 | R7: 805 | S7: =IFERROR(Opex9[[#This Row],[Energia]]/Opex9[[#This Row],[Consumo (KhW]],0) -> 0 | U7: =IFERROR(Opex9[[#This Row],[Energia]]/Opex9[[#This Row],[No. Días Arriendo]],0) -> 0
B8: Histórico | C8: 43806 | D8: =+TEXT(C8,"mmmm") -> diciembre | E8: 1000000 | F8: 31 | G8: =IFERROR(Opex9[[#This Row],[Arriendo]]/Opex9[[#This Row],[No. Días Arriendo]],0) -> 32258.065 | H8: 161900 | I8: =+F7 -> 0 | J8: 187 | K8: =IFERROR(Opex9[[#This Row],[Gas]]/Opex9[[#This Row],[Consumo (m3)]],0) -> 865.7754 | L8: =IFERROR(Opex9[[#This Row],[Gas]]/Opex9[[#This Row],[No. Días Arriendo]],0) -> 5222.5806 | M8: 150000 | N8: =IFERROR(Opex9[[#This Row],[Agua]]/Opex9[[#This Row],[No. Días Arriendo]],0) -> 4838.7097 | O8: 0 | Q8: =+X8 -> 29 | R8: 742 | S8: =IFERROR(Opex9[[#This Row],[Energia]]/Opex9[[#This Row],[Consumo (KhW]],0) -> 0 | T8: 21Nov -20Dic | U8: =IFERROR(Opex9[[#This Row],[Energia]]/Opex9[[#This Row],[No. Días Arriendo]],0) -> 0 | V8: 43790 | W8: 43819 | X8: =+W8-V8 -> 29 | Z8: =+Opex9[[#This Row],[Día Energia]]+Opex9[[#This Row],[Día Gas]]+Opex9[[#This Row],[Día Arriendo]] -> 37480.645
B9: Histórico | C9: 43839 | D9: =+TEXT(C9,"mmmm") -> enero | E9: 1000000 | F9: 31 | G9: =IFERROR(Opex9[[#This Row],[Arriendo]]/Opex9[[#This Row],[No. Días Arriendo]],0) -> 32258.065 | H9: 152570 | I9: =+F8 -> 31 | J9: 168 | K9: =IFERROR(Opex9[[#This Row],[Gas]]/Opex9[[#This Row],[Consumo (m3)]],0) -> 908.15476 | L9: =IFERROR(Opex9[[#This Row],[Gas]]/Opex9[[#This Row],[No. Días Arriendo]],0) -> 4921.6129 | M9: 150000 | N9: =IFERROR(Opex9[[#This Row],[Agua]]/Opex9[[#This Row],[No. Días Arriendo]],0) -> 4838.7097 | O9: 0 | Q9: =+X9 -> 33 | R9: 775 | S9: =IFERROR(Opex9[[#This Row],[Energia]]/Opex9[[#This Row],[Consumo (KhW]],0) -> 0 | T9: 20Dic-22Ene | U9: =IFERROR(Opex9[[#This Row],[Energia]]/Opex9[[#This Row],[No. Días Arriendo]],0) -> 0 | V9: 43819 | W9: 43852 | X9: =+W9-V9 -> 33 | Z9: =+Opex9[[#This Row],[Día Energia]]+Opex9[[#This Row],[Día Gas]]+Opex9[[#This Row],[Día Arriendo]] -> 37179.677
B10: Histórico | C10: 43868 | D10: =+TEXT(C10,"mmmm") -> febrero | E10: 1000000 | F10: 29 | G10: =IFERROR(Opex9[[#This Row],[Arriendo]]/Opex9[[#This Row],[No. Días Arriendo]],0) -> 34482.759 | H10: 155100 | I10: =+F9 -> 31 | J10: 183 | K10: =IFERROR(Opex9[[#This Row],[Gas]]/Opex9[[#This Row],[Consumo (m3)]],0) -> 847.54098 | L10: =IFERROR(Opex9[[#This Row],[Gas]]/Opex9[[#This Row],[No. Días Arriendo]],0) -> 5348.2759 | M10: 150000 | N10: =IFERROR(Opex9[[#This Row],[Agua]]/Opex9[[#This Row],[No. Días Arriendo]],0) -> 5172.4138 | O10: 0 | Q10: =+X10 -> 30 | R10: 521 | S10: =IFERROR(Opex9[[#This Row],[Energia]]/Opex9[[#This Row],[Consumo (KhW]],0) -> 0 | T10: 22Ene-20Feb | U10: =IFERROR(Opex9[[#This Row],[Energia]]/Opex9[[#This Row],[No. Días Arriendo]],0) -> 0 | V10: 43851 | W10: 43881 | X10: =+W10-V10 -> 30 | Z10: =+Opex9[[#This Row],[Día Energia]]+Opex9[[#This Row],[Día Gas]]+Opex9[[#This Row],[Día Arriendo]] -> 39831.034
B11: Histórico | C11: 43897 | D11: =+TEXT(C11,"mmmm") -> marzo | E11: 1000000 | F11: 31 | G11: =IFERROR(Opex9[[#This Row],[Arriendo]]/Opex9[[#This Row],[No. Días Arriendo]],0) -> 32258.065 | H11: 224724 | I11: =+F10 -> 29 | J11: 239 | K11: =IFERROR(Opex9[[#This Row],[Gas]]/Opex9[[#This Row],[Consumo (m3)]],0) -> 940.26778 | L11: =IFERROR(Opex9[[#This Row],[Gas]]/Opex9[[#This Row],[No. Días Arriendo]],0) -> 7249.1613 | M11: 150000 | N11: =IFERROR(Opex9[[#This Row],[Agua]]/Opex9[[#This Row],[No. Días Arriendo]],0) -> 4838.7097 | O11: 0 | Q11: =+X11 -> 28 | R11: 608 | S11: =IFERROR(Opex9[[#This Row],[Energia]]/Opex9[[#This Row],[Consumo (KhW]],0) -> 0 | T11: 20Feb-19Mar | U11: =IFERROR(Opex9[[#This Row],[Energia]]/Opex9[[#This Row],[No. Días Arriendo]],0) -> 0 | V11: 43881 | W11: 43909 | X11: =+W11-V11 -> 28 | Z11: =+Opex9[[#This Row],[Día Energia]]+Opex9[[#This Row],[Día Gas]]+Opex9[[#This Row],[Día Arriendo]] -> 39507.226
B12: Histórico | C12: 43928 | D12: =+TEXT(C12,"mmmm") -> abril | E12: 500000 | F12: 30 | G12: =IFERROR(Opex9[[#This Row],[Arriendo]]/Opex9[[#This Row],[No. Días Arriendo]],0) -> 16666.667 | H12: 102730 | I12: =+F11 -> 31 | J12: 110 | K12: =IFERROR(Opex9[[#This Row],[Gas]]/Opex9[[#This Row],[Consumo (m3)]],0) -> 933.90909 | L12: =IFERROR(Opex9[[#This Row],[Gas]]/Opex9[[#This Row],[No. Días Arriendo]],0) -> 3424.3333 | M12: 150000 | N12: =IFERROR(Opex9[[#This Row],[Agua]]/Opex9[[#This Row],[No. Días Arriendo]],0) -> 5000 | O12: 0 | Q12: =+X12 -> 33 | R12: 757 | S12: =IFERROR(Opex9[[#This Row],[Energia]]/Opex9[[#This Row],[Consumo (KhW]],0) -> 0 | T12: 19Mar-21Abr | U12: =IFERROR(Opex9[[#This Row],[Energia]]/Opex9[[#This Row],[No. Días Arriendo]],0) -> 0 | V12: 43909 | W12: 43942 | X12: =+W12-V12 -> 33 | Z12: =+Opex9[[#This Row],[Día Energia]]+Opex9[[#This Row],[Día Gas]]+Opex9[[#This Row],[Día Arriendo]] -> 20091
B13: Histórico | C13: 43959 | D13: =+TEXT(C13,"mmmm") -> mayo | E13: 500000 | F13: 31 | G13: =IFERROR(Opex9[[#This Row],[Arriendo]]/Opex9[[#This Row],[No. Días Arriendo]],0) -> 16129.032 | H13: 220770 | I13: =+F12 -> 30 | J13: 221 | K13: =IFERROR(Opex9[[#This Row],[Gas]]/Opex9[[#This Row],[Consumo (m3)]],0) -> 998.95928 | L13: =IFERROR(Opex9[[#This Row],[Gas]]/Opex9[[#This Row],[No. Días Arriendo]],0) -> 7121.6129 | M13: 70000 | N13: =IFERROR(Opex9[[#This Row],[Agua]]/Opex9[[#This Row],[No. Días Arriendo]],0) -> 2258.0645 | O13: 0 | P13: 0 | Q13: =+X13 -> 29 | R13: 713 | S13: =IFERROR(Opex9[[#This Row],[Energia]]/Opex9[[#This Row],[Consumo (KhW]],0) -> 0 | T13: 21Abr-20May | U13: =IFERROR(Opex9[[#This Row],[Energia]]/Opex9[[#This Row],[No. Días Arriendo]],0) -> 0 | V13: 43942 | W13: 43971 | X13: =+W13-V13 -> 29 | Z13: =+Opex9[[#This Row],[Día Energia]]+Opex9[[#This Row],[Día Gas]]+Opex9[[#This Row],[Día Arriendo]] -> 23250.645
B14: Forecast | C14: 43990 | D14: =+TEXT(C14,"mmmm") -> junio | E14: 500000 | F14: 30 | G14: =IFERROR(Opex9[[#This Row],[Arriendo]]/Opex9[[#This Row],[No. Días Arriendo]],0) -> 16666.667 | H14: 234638 | I14: =+F13 -> 31 | J14: =+AVERAGE(J11/I11,J12/I12,J13/I13)*Opex9[[#This Row],[No. Días Gas]] -> 197.94981 | K14: =+AVERAGE(K11:K13) -> 957.71205 | L14: =IFERROR(Opex9[[#This Row],[Gas]]/Opex9[[#This Row],[No. Días Arriendo]],0) -> 7821.2667 | M14: 70000 | N14: =IFERROR(Opex9[[#This Row],[Agua]]/Opex9[[#This Row],[No. Días Arriendo]],0) -> 2333.3333 | O14: 220800 | P14: 109770 | Q14: =+X14 -> 30 | R14: =+AVERAGE($O$11/S11,$O$12/S12,$O$13/S13) -> #DIV/0! | S14: =+AVERAGE(S11:S13) -> 0 | T14: 21May-20Jun | U14: =IFERROR(Opex9[[#This Row],[Energia]]/Opex9[[#This Row],[No. Días Arriendo]],0) -> 7360 | V14: 43971 | W14: 44001 | X14: =+W14-V14 -> 30 | Z14: =+Opex9[[#This Row],[Día Energia]]+Opex9[[#This Row],[Día Gas]]+Opex9[[#This Row],[Día Arriendo]] -> 31847.933
B15: Forecast | C15: 44020 | D15: =+TEXT(C15,"mmmm") -> julio | E15: 500000 | F15: 31 | G15: =IFERROR(Opex9[[#This Row],[Arriendo]]/Opex9[[#This Row],[No. Días Arriendo]],0) -> 16129.032 | H15: =+Opex9[[#This Row],[Consumo (m3)]]*Opex9[[#This Row],[Costo prom. Gas]] -> 166695.26 | I15: =+F14 -> 30 | J15: =+AVERAGE(J12/I12,J13/I13,J14/I14)*Opex9[[#This Row],[No. Días Gas]] -> 173.00531 | K15: =+AVERAGE(K12:K14) -> 963.52681 | L15: =IFERROR(Opex9[[#This Row],[Gas]]/Opex9[[#This Row],[No. Días Arriendo]],0) -> 5377.2664 | M15: 110000 | N15: =IFERROR(Opex9[[#This Row],[Agua]]/Opex9[[#This Row],[No. Días Arriendo]],0) -> 3548.3871 | O15: 220800 | P15: 367415 | Q15: =+X15 -> 30 | R15: =+AVERAGE($O$11/S12,$O$12/S13,$O$13/S14) -> #DIV/0! | S15: =+AVERAGE(S12:S14) -> 0 | T15: Nd | U15: =IFERROR(Opex9[[#This Row],[Energia]]/Opex9[[#This Row],[No. Días Arriendo]],0) -> 7122.5806 | V15: =+V14+30 -> 44001 | W15: =+V16 -> 44031 | X15: =+W15-V15 -> 30 | Z15: =+Opex9[[#This Row],[Día Energia]]+Opex9[[#This Row],[Día Gas]]+Opex9[[#This Row],[Día Arriendo]] -> 28628.879
B16: Forecast | C16: 44051 | D16: =+TEXT(C16,"mmmm") -> agosto | E16: 500000 | F16: 31 | G16: =IFERROR(Opex9[[#This Row],[Arriendo]]/Opex9[[#This Row],[No. Días Arriendo]],0) -> 16129.032 | H16: =+Opex9[[#This Row],[Consumo (m3)]]*Opex9[[#This Row],[Costo prom. Gas]] -> 196330.97 | I16: =+F15 -> 31 | J16: =+AVERAGE(J13/I13,J14/I14,J15/I15)*Opex9[[#This Row],[No. Días Gas]] -> 201.69621 | K16: =+AVERAGE(K13:K15) -> 973.39938 | L16: =IFERROR(Opex9[[#This Row],[Gas]]/Opex9[[#This Row],[No. Días Arriendo]],0) -> 6333.257 | M16: 110000 | N16: =IFERROR(Opex9[[#This Row],[Agua]]/Opex9[[#This Row],[No. Días Arriendo]],0) -> 3548.3871 | O16: =+O15 -> 220800 | P16: 367415 | Q16: =+X16 -> 30 | R16: =+AVERAGE($O$11/S13,$O$12/S14,$O$13/S15) -> #DIV/0! | S16: =+AVERAGE(S13:S15) -> 0 | T16: Nd | U16: =IFERROR(Opex9[[#This Row],[Energia]]/Opex9[[#This Row],[No. Días Arriendo]],0) -> 7122.5806 | V16: =+V15+30 -> 44031 | W16: =+V17 -> 44061 | X16: =+W16-V16 -> 30 | Z16: =+Opex9[[#This Row],[Día Energia]]+Opex9[[#This Row],[Día Gas]]+Opex9[[#This Row],[Día Arriendo]] -> 29584.87
B17: Forecast | C17: 44082 | D17: =+TEXT(C17,"mmmm") -> septiembre | E17: 500000 | F17: 30 | G17: =IFERROR(Opex9[[#This Row],[Arriendo]]/Opex9[[#This Row],[No. Días Arriendo]],0) -> 16666.667 | H17: =+Opex9[[#This Row],[Consumo (m3)]]*Opex9[[#This Row],[Costo prom. Gas]] -> 186034.6 | I17: =+F16 -> 31 | J17: =+AVERAGE(J14/I14,J15/I15,J16/I16)*Opex9[[#This Row],[No. Días Gas]] -> 192.80606 | K17: =+AVERAGE(K14:K16) -> 964.87941 | L17: =IFERROR(Opex9[[#This Row],[Gas]]/Opex9[[#This Row],[No. Días Arriendo]],0) -> 6201.1532 | M17: 110000 | N17: =IFERROR(Opex9[[#This Row],[Agua]]/Opex9[[#This Row],[No. Días Arriendo]],0) -> 3666.6667 | O17: =+O16 -> 220800 | P17: 0 | Q17: =+X17 -> 30 | R17: =+AVERAGE($O$11/S14,$O$12/S15,$O$13/S16) -> #DIV/0! | S17: =+AVERAGE(S14:S16) -> 0 | T17: Nd | U17: =IFERROR(Opex9[[#This Row],[Energia]]/Opex9[[#This Row],[No. Días Arriendo]],0) -> 7360 | V17: =+V16+30 -> 44061 | W17: =+V18 -> 44091 | X17: =+W17-V17 -> 30 | Z17: =+Opex9[[#This Row],[Día Energia]]+Opex9[[#This Row],[Día Gas]]+Opex9[[#This Row],[Día Arriendo]] -> 30227.82
B18: Forecast | C18: 44112 | D18: =+TEXT(C18,"mmmm") -> octubre | E18: 500000 | F18: 31 | G18: =IFERROR(Opex9[[#This Row],[Arriendo]]/Opex9[[#This Row],[No. Días Arriendo]],0) -> 16129.032 | H18: =+Opex9[[#This Row],[Consumo (m3)]]*Opex9[[#This Row],[Costo prom. Gas]] -> 178874.3 | I18: =+F17 -> 30 | J18: =+AVERAGE(J15/I15,J16/I16,J17/I17)*Opex9[[#This Row],[No. Días Gas]] -> 184.92724 | K18: =+AVERAGE(K15:K17) -> 967.26853 | L18: =IFERROR(Opex9[[#This Row],[Gas]]/Opex9[[#This Row],[No. Días Arriendo]],0) -> 5770.1386 | M18: 110000 | N18: =IFERROR(Opex9[[#This Row],[Agua]]/Opex9[[#This Row],[No. Días Arriendo]],0) -> 3548.3871 | O18: =+O17 -> 220800 | P18: 0 | Q18: =+X18 -> 30 | R18: =+AVERAGE($O$11/S15,$O$12/S16,$O$13/S17) -> #DIV/0! | S18: =+AVERAGE(S15:S17) -> 0 | T18: Nd | U18: =IFERROR(Opex9[[#This Row],[Energia]]/Opex9[[#This Row],[No. Días Arriendo]],0) -> 7122.5806 | V18: =+V17+30 -> 44091 | W18: =+V19 -> 44121 | X18: =+W18-V18 -> 30 | Z18: =+Opex9[[#This Row],[Día Energia]]+Opex9[[#This Row],[Día Gas]]+Opex9[[#This Row],[Día Arriendo]] -> 29021.751
B19: Forecast | C19: 44143 | D19: =+TEXT(C19,"mmmm") -> noviembre | E19: 500000 | F19: 30 | G19: =IFERROR(Opex9[[#This Row],[Arriendo]]/Opex9[[#This Row],[No. Días Arriendo]],0) -> 16666.667 | H19: =+Opex9[[#This Row],[Consumo (m3)]]*Opex9[[#This Row],[Costo prom. Gas]] -> 189052.26 | I19: =+F18 -> 31 | J19: =+AVERAGE(J16/I16,J17/I17,J18/I18)*Opex9[[#This Row],[No. Días Gas]] -> 195.19792 | K19: =+AVERAGE(K16:K18) -> 968.51577 | L19: =IFERROR(Opex9[[#This Row],[Gas]]/Opex9[[#This Row],[No. Días Arriendo]],0) -> 6301.742 | M19: 110000 | N19: =IFERROR(Opex9[[#This Row],[Agua]]/Opex9[[#This Row],[No. Días Arriendo]],0) -> 3666.6667 | O19: =+O18 -> 220800 | P19: 0 | Q19: =+X19 -> 30 | R19: =+AVERAGE($O$11/S16,$O$12/S17,$O$13/S18) -> #DIV/0! | S19: =+AVERAGE(S16:S18) -> 0 | T19: Nd | U19: =IFERROR(Opex9[[#This Row],[Energia]]/Opex9[[#This Row],[No. Días Arriendo]],0) -> 7360 | V19: =+V18+30 -> 44121 | W19: =+V20 -> 44151 | X19: =+W19-V19 -> 30 | Z19: =+Opex9[[#This Row],[Día Energia]]+Opex9[[#This Row],[Día Gas]]+Opex9[[#This Row],[Día Arriendo]] -> 30328.409
B20: Forecast | C20: 44173 | D20: =+TEXT(C20,"mmmm") -> diciembre | E20: 500000 | F20: 31 | G20: =IFERROR(Opex9[[#This Row],[Arriendo]]/Opex9[[#This Row],[No. Días Arriendo]],0) -> 16129.032 | H20: =+Opex9[[#This Row],[Consumo (m3)]]*Opex9[[#This Row],[Costo prom. Gas]] -> 180619.48 | I20: =+F19 -> 30 | J20: =+AVERAGE(J17/I17,J18/I18,J19/I19)*Opex9[[#This Row],[No. Días Gas]] -> 186.80498 | K20: =+AVERAGE(K17:K19) -> 966.88791 | L20: =IFERROR(Opex9[[#This Row],[Gas]]/Opex9[[#This Row],[No. Días Arriendo]],0) -> 5826.4348 | M20: 110000 | N20: =IFERROR(Opex9[[#This Row],[Agua]]/Opex9[[#This Row],[No. Días Arriendo]],0) -> 3548.3871 | O20: =+O19 -> 220800 | P20: 0 | Q20: =+X20 -> 30 | R20: =+AVERAGE($O$11/S17,$O$12/S18,$O$13/S19) -> #DIV/0! | S20: =+AVERAGE(S17:S19) -> 0 | T20: Nd | U20: =IFERROR(Opex9[[#This Row],[Energia]]/Opex9[[#This Row],[No. Días Arriendo]],0) -> 7122.5806 | V20: =+V19+30 -> 44151 | W20: =+V21 -> 44181 | X20: =+W20-V20 -> 30 | Z20: =+Opex9[[#This Row],[Día Energia]]+Opex9[[#This Row],[Día Gas]]+Opex9[[#This Row],[Día Arriendo]] -> 29078.048
V21: =+V20+30 -> 44181
H23: 2 dia | I23: 240000 | J23: =20000*5 -> 100000 | K23: =+J23*4 -> 400000
