Workbook

Sheet sales
A2: nombre_transaccion | B2: VENTA
A4: fecha | B4: id_factura | C4: nombre_producto | D4: precio_producto | E4: tipo_cuenta | F4: cantidad | G4: Recuento de id_item | H4: valor_factura
A5: 46076.692 | B5: 2 | C5: Chorizo | D5: 8000 | E5: EFECTIVO | F5: 2 | G5: 1 | H5: =+D5*F5 -> 16000
A6: 46076.71 | B6: 3 | C6: Chorizo | D6: 8000 | E6: NEQUI | F6: 1 | G6: 1 | H6: =+D6*F6 -> 8000
A7: 46076.717 | B7: 4 | C7: Chorizo | D7: 8000 | E7: EFECTIVO | F7: 2 | G7: 1 | H7: =+D7*F7 -> 16000
A8: 46076.717 | B8: 4 | C8: Coca cola | D8: 3000 | E8: EFECTIVO | F8: 2 | G8: 1 | H8: =+D8*F8 -> 6000
A9: 46076.72 | B9: 5 | C9: Chorizo | D9: 8000 | E9: NEQUI | F9: 3 | G9: 1 | H9: =+D9*F9 -> 24000
A10: 46076.75 | B10: 6 | C10: Agua | D10: 3000 | E10: EFECTIVO | F10: 2 | G10: 1 | H10: =+D10*F10 -> 6000
A11: 46076.75 | B11: 6 | C11: Chorizo | D11: 8000 | E11: EFECTIVO | F11: 2 | G11: 1 | H11: =+D11*F11 -> 16000
A12: 46076.752 | B12: 7 | C12: Chorizo | D12: 8000 | E12: EFECTIVO | F12: 2 | G12: 1 | H12: =+D12*F12 -> 16000
A13: 46076.752 | B13: 7 | C13: Postobon | D13: 3000 | E13: EFECTIVO | F13: 1 | G13: 1 | H13: =+D13*F13 -> 3000
A14: 46076.787 | B14: 8 | C14: Chorizo | D14: 8000 | E14: EFECTIVO | F14: 1 | G14: 1 | H14: =+D14*F14 -> 8000
A15: 46076.795 | B15: 9 | C15: Chorizo | D15: 8000 | E15: EFECTIVO | F15: 2 | G15: 1 | H15: =+D15*F15 -> 16000
A16: 46076.795 | B16: 9 | C16: Coca cola | D16: 3000 | E16: EFECTIVO | F16: 2 | G16: 1 | H16: =+D16*F16 -> 6000
... A124: 46081.799 | B124: 93 | C124: Chori- CRUDO | D124: 4500 | E124: NEQUI | F124: 4 | G124: 1 | H124: =+D124*F124 -> 18000

Sheet sales_BI
A1: =sales!A4 -> fecha | B1: =sales!B4 -> id_factura | C1: =sales!C4 -> nombre_producto | D1: =sales!D4 -> precio_producto | E1: =sales!E4 -> tipo_cuenta | F1: =sales!F4 -> cantidad | G1: =sales!G4 -> Recuento de id_item | H1: =sales!H4 -> valor_factura
A2: =sales!A5 -> 46076.692 | B2: =sales!B5 -> 2 | C2: =sales!C5 -> Chorizo | D2: =sales!D5 -> 8000 | E2: =sales!E5 -> EFECTIVO | F2: =sales!F5 -> 2 | G2: =sales!G5 -> 1 | H2: =sales!H5 -> 16000
A3: =sales!A6 -> 46076.71 | B3: =sales!B6 -> 3 | C3: =sales!C6 -> Chorizo | D3: =sales!D6 -> 8000 | E3: =sales!E6 -> NEQUI | F3: =sales!F6 -> 1 | G3: =sales!G6 -> 1 | H3: =sales!H6 -> 8000
A4: =sales!A7 -> 46076.717 | B4: =sales!B7 -> 4 | C4: =sales!C7 -> Chorizo | D4: =sales!D7 -> 8000 | E4: =sales!E7 -> EFECTIVO | F4: =sales!F7 -> 2 | G4: =sales!G7 -> 1 | H4: =sales!H7 -> 16000
A5: =sales!A8 -> 46076.717 | B5: =sales!B8 -> 4 | C5: =sales!C8 -> Coca cola | D5: =sales!D8 -> 3000 | E5: =sales!E8 -> EFECTIVO | F5: =sales!F8 -> 2 | G5: =sales!G8 -> 1 | H5: =sales!H8 -> 6000
A6: =sales!A9 -> 46076.72 | B6: =sales!B9 -> 5 | C6: =sales!C9 -> Chorizo | D6: =sales!D9 -> 8000 | E6: =sales!E9 -> NEQUI | F6: =sales!F9 -> 3 | G6: =sales!G9 -> 1 | H6: =sales!H9 -> 24000
A7: =sales!A10 -> 46076.75 | B7: =sales!B10 -> 6 | C7: =sales!C10 -> Agua | D7: =sales!D10 -> 3000 | E7: =sales!E10 -> EFECTIVO | F7: =sales!F10 -> 2 | G7: =sales!G10 -> 1 | H7: =sales!H10 -> 6000
A8: =sales!A11 -> 46076.75 | B8: =sales!B11 -> 6 | C8: =sales!C11 -> Chorizo | D8: =sales!D11 -> 8000 | E8: =sales!E11 -> EFECTIVO | F8: =sales!F11 -> 2 | G8: =sales!G11 -> 1 | H8: =sales!H11 -> 16000
A9: =sales!A12 -> 46076.752 | B9: =sales!B12 -> 7 | C9: =sales!C12 -> Chorizo | D9: =sales!D12 -> 8000 | E9: =sales!E12 -> EFECTIVO | F9: =sales!F12 -> 2 | G9: =sales!G12 -> 1 | H9: =sales!H12 -> 16000
A10: =sales!A13 -> 46076.752 | B10: =sales!B13 -> 7 | C10: =sales!C13 -> Postobon | D10: =sales!D13 -> 3000 | E10: =sales!E13 -> EFECTIVO | F10: =sales!F13 -> 1 | G10: =sales!G13 -> 1 | H10: =sales!H13 -> 3000
A11: =sales!A14 -> 46076.787 | B11: =sales!B14 -> 8 | C11: =sales!C14 -> Chorizo | D11: =sales!D14 -> 8000 | E11: =sales!E14 -> EFECTIVO | F11: =sales!F14 -> 1 | G11: =sales!G14 -> 1 | H11: =sales!H14 -> 8000
A12: =sales!A15 -> 46076.795 | B12: =sales!B15 -> 9 | C12: =sales!C15 -> Chorizo | D12: =sales!D15 -> 8000 | E12: =sales!E15 -> EFECTIVO | F12: =sales!F15 -> 2 | G12: =sales!G15 -> 1 | H12: =sales!H15 -> 16000
... A121: =sales!A124 -> 46081.799 | B121: =sales!B124 -> 93 | C121: =sales!C124 -> Chori- CRUDO | D121: =sales!D124 -> 4500 | E121: =sales!E124 -> NEQUI | F121: =sales!F124 -> 4 | G121: =sales!G124 -> 1 | H121: =sales!H124 -> 18000

Sheet Informe
A2: Suma de entrada | H2: Suma de egreso | I2: Etiquetas de columna
B3: BASE | C3: VENTA | F3: Total general | I3: EFECTIVO | M3: NEQUI | N3: Total general
A4: Etiquetas de fila | B4: EFECTIVO | C4: EFECTIVO | D4: DaviPlata | E4: NEQUI | H4: Etiquetas de fila | I4: BASE | J4: GASTO | K4: RETIRO | L4: VENTA | M4: VENTA | P4: EFECTIVO
A5: 23-feb | B5: 73700 | C5: 192000 | E5: 32000 | F5: 297700 | H5: 23-feb | I5: 0 | J5: 60000 | K5: 100 | L5: 0 | M5: 0 | N5: 60100 | P5: =+SUM(B5:C5)-N5 -> 205600
A6: 24-feb | B6: 205600 | C6: 213000 | E6: 8000 | F6: 426600 | H6: 24-feb | I6: 0 | J6: 103000 | L6: 0 | M6: 0 | N6: 103000 | P6: =+SUM(B6:C6)-N6 -> 315600
A7: 25-feb | C7: 344000 | E7: 46500 | F7: 390500 | H7: 25-feb | J7: 226700 | L7: 0 | M7: 0 | N7: 226700 | P7: =+SUM(B7:C7)-N7 -> 117300 | Q7: =+SUM(P6:P7) -> 432900
A8: 26-feb | C8: 84000 | E8: 125000 | F8: 209000 | H8: 26-feb | J8: 84000 | L8: 0 | M8: 0 | N8: 84000 | P8: =+SUM(B8:C8)-N8 -> 0 | Q8: =$Q$7-20000-7900 -> 405000
A9: 27-feb | B9: 405000 | C9: 186000 | D9: 11000 | E9: 51000 | F9: 653000 | H9: 27-feb | I9: 0 | J9: 240000 | K9: 307900 | L9: 0 | M9: 0 | N9: 547900 | P9: =+SUM(B9:C9)-N9 -> 43100 | Q9: =+P9-20000-10000 -> 13100
A10: 28-feb | B10: 125000 | C10: 456500 | E10: 47000 | F10: 628500 | H10: 28-feb | I10: 0 | J10: 96400 | K10: 350000 | L10: 0 | M10: 0 | N10: 446400 | P10: =+SUM(B10:C10)-N10 -> 135100
A11: Total general | B11: 809300 | C11: 1475500 | D11: 11000 | E11: 309500 | F11: 2605300 | H11: Total general | I11: 0 | J11: 810100 | K11: 658000 | L11: 0 | M11: 0 | N11: 1468100

Sheet historial de venta
A2: nombre_transaccion | B2: VENTA | K2: nombre_transaccion | L2: VENTA
A4: fecha (día) | B4: fecha | C4: id_factura | D4: nombre_producto | E4: precio_producto | F4: tipo_cuenta | G4: cantidad | H4: Recuento de id_item | I4: Valor venta | K4: Suma de valor_total | L4: tipo_cuenta
A5: 23-feb | B5: 46076.692 | C5: 2 | D5: Chorizo | E5: 8000 | F5: EFECTIVO | G5: 2 | H5: 1 | I5: =+E5*G5 -> 16000 | K5: fecha (día) | L5: DaviPlata | M5: EFECTIVO | N5: NEQUI | O5: Total general
A6: 23-feb | B6: 46076.71 | C6: 3 | D6: Chorizo | E6: 8000 | F6: NEQUI | G6: 1 | H6: 1 | I6: =+E6*G6 -> 8000 | K6: 23-feb | M6: 192000 | N6: 32000 | O6: 224000
A7: 23-feb | B7: 46076.717 | C7: 4 | D7: Chorizo | E7: 8000 | F7: EFECTIVO | G7: 2 | H7: 1 | I7: =+E7*G7 -> 16000 | K7: 24-feb | M7: 213000 | N7: 8000 | O7: 221000
A8: 23-feb | D8: Coca cola | E8: 3000 | F8: EFECTIVO | G8: 2 | H8: 1 | I8: =+E8*G8 -> 6000 | K8: 25-feb | M8: 344000 | N8: 46500 | O8: 390500
A9: 23-feb | B9: 46076.72 | C9: 5 | D9: Chorizo | E9: 8000 | F9: NEQUI | G9: 3 | H9: 1 | I9: =+E9*G9 -> 24000 | K9: 26-feb | M9: 84000 | N9: 125000 | O9: 209000
A10: 23-feb | B10: 46076.75 | C10: 6 | D10: Agua | E10: 3000 | F10: EFECTIVO | G10: 2 | H10: 1 | I10: =+E10*G10 -> 6000 | K10: 27-feb | L10: 11000 | M10: 186000 | N10: 51000 | O10: 248000
A11: 23-feb | D11: Chorizo | E11: 8000 | F11: EFECTIVO | G11: 2 | H11: 1 | I11: =+E11*G11 -> 16000 | K11: 28-feb | M11: 456500 | N11: 47000 | O11: 503500
A12: 23-feb | B12: 46076.752 | C12: 7 | D12: Chorizo | E12: 8000 | F12: EFECTIVO | G12: 2 | H12: 1 | I12: =+E12*G12 -> 16000 | K12: Total general | L12: 11000 | M12: 1475500 | N12: 309500 | O12: 1796000
A13: 23-feb | D13: Postobon | E13: 3000 | F13: EFECTIVO | G13: 1 | H13: 1 | I13: =+E13*G13 -> 3000
A14: 23-feb | B14: 46076.787 | C14: 8 | D14: Chorizo | E14: 8000 | F14: EFECTIVO | G14: 1 | H14: 1 | I14: =+E14*G14 -> 8000
A15: 23-feb | B15: 46076.795 | C15: 9 | D15: Chorizo | E15: 8000 | F15: EFECTIVO | G15: 2 | H15: 1 | I15: =+E15*G15 -> 16000
A16: 23-feb | D16: Coca cola | E16: 3000 | F16: EFECTIVO | G16: 2 | H16: 1 | I16: =+E16*G16 -> 6000
A17: 23-feb | B17: 46076.818 | C17: 10 | D17: Chorizo | E17: 8000 | F17: EFECTIVO | G17: 3 | H17: 1 | I17: =+E17*G17 -> 24000
A18: 23-feb | B18: 46076.842 | C18: 11 | D18: Chorizo | E18: 8000 | F18: EFECTIVO | G18: 1 | H18: 1 | I18: =+E18*G18 -> 8000
A19: 23-feb | B19: 46076.844 | C19: 12 | D19: Chorizo | E19: 8000 | F19: EFECTIVO | G19: 1 | H19: 1 | I19: =+E19*G19 -> 8000
A20: 23-feb | B20: 46076.846 | C20: 13 | D20: Chorizo | E20: 8000 | F20: EFECTIVO | G20: 1 | H20: 1 | I20: =+E20*G20 -> 8000
A21: 23-feb | D21: Postobon | E21: 3000 | F21: EFECTIVO | G21: 1 | H21: 1 | I21: =+E21*G21 -> 3000
A22: 23-feb | B22: 46076.85 | C22: 14 | D22: Chorizo | E22: 8000 | F22: EFECTIVO | G22: 3 | H22: 1 | I22: =+E22*G22 -> 24000
A23: 23-feb | B23: 46076.853 | C23: 15 | D23: Chorizo | E23: 8000 | F23: EFECTIVO | G23: 1 | H23: 1 | I23: =+E23*G23 -> 8000
A24: 24-feb | B24: 46077.649 | C24: 16 | D24: Chorizo | E24: 8000 | F24: EFECTIVO | G24: 5 | H24: 1 | I24: =+E24*G24 -> 40000
A25: 24-feb | B25: 46077.649 | C25: 17 | D25: Chorizo | E25: 8000 | F25: EFECTIVO | G25: 3 | H25: 1 | I25: =+E25*G25 -> 24000
A26: 24-feb | B26: 46077.74 | C26: 18 | D26: Chorizo | E26: 8000 | F26: EFECTIVO | G26: 1 | H26: 1 | I26: =+E26*G26 -> 8000
A27: 24-feb | B27: 46077.76 | C27: 19 | D27: Chorizo | E27: 8000 | F27: EFECTIVO | G27: 1 | H27: 1 | I27: =+E27*G27 -> 8000
A28: 24-feb | B28: 46077.774 | C28: 20 | D28: Chorizo | E28: 8000 | F28: EFECTIVO | G28: 2 | H28: 1 | I28: =+E28*G28 -> 16000
A29: 24-feb | B29: 46077.775 | C29: 21 | D29: Chorizo | E29: 8000 | F29: EFECTIVO | G29: 1 | H29: 1 | I29: =+E29*G29 -> 8000
A30: 24-feb | B30: 46077.78 | C30: 22 | D30: Chori- CRUDO | E30: 4500 | F30: EFECTIVO | G30: 2 | H30: 1 | I30: =+E30*G30 -> 9000
A31: 24-feb | D31: Chorizo | E31: 8000 | F31: EFECTIVO | G31: 1 | H31: 1 | I31: =+E31*G31 -> 8000
A32: 24-feb | B32: 46077.797 | C32: 23 | D32: Chorizo | E32: 8000 | F32: EFECTIVO | G32: 1 | H32: 1 | I32: =+E32*G32 -> 8000
A33: 24-feb | B33: 46077.834 | C33: 24 | D33: Chorizo | E33: 8000 | F33: NEQUI | G33: 1 | H33: 1 | I33: =+E33*G33 -> 8000
A34: 24-feb | B34: 46077.837 | C34: 25 | D34: Chorizo | E34: 8000 | F34: EFECTIVO | G34: 1 | H34: 1 | I34: =+E34*G34 -> 8000
A35: 24-feb | B35: 46077.847 | C35: 26 | D35: Agua | E35: 3000 | F35: EFECTIVO | G35: 1 | H35: 1 | I35: =+E35*G35 -> 3000
A36: 24-feb | D36: Chorizo | E36: 8000 | F36: EFECTIVO | G36: 3 | H36: 1 | I36: =+E36*G36 -> 24000
A37: 24-feb | D37: Postobon | E37: 3000 | F37: EFECTIVO | G37: 1 | H37: 1 | I37: =+E37*G37 -> 3000
A38: 24-feb | B38: 46077.85 | C38: 27 | D38: Chorizo | E38: 8000 | F38: EFECTIVO | G38: 4 | H38: 1 | I38: =+E38*G38 -> 32000
A39: 24-feb | D39: Coca cola | E39: 3000 | F39: EFECTIVO | G39: 2 | H39: 1 | I39: =+E39*G39 -> 6000
A40: 24-feb | B40: 46077.868 | C40: 28 | D40: Chorizo | E40: 8000 | F40: EFECTIVO | G40: 1 | H40: 1 | I40: =+E40*G40 -> 8000
A41: 25-feb | B41: 46078.578 | C41: 29 | D41: Chorizo | E41: 8000 | F41: EFECTIVO | G41: 1 | H41: 1 | I41: =+E41*G41 -> 8000
A42: 25-feb | B42: 46078.58 | C42: 30 | D42: Chorizo | E42: 8000 | F42: EFECTIVO | G42: 1 | H42: 1 | I42: =+E42*G42 -> 8000
A43: 25-feb | B43: 46078.587 | C43: 31 | D43: Chorizo | E43: 8000 | F43: EFECTIVO | G43: 1 | H43: 1 | I43: =+E43*G43 -> 8000
A44: 25-feb | B44: 46078.591 | C44: 32 | D44: parri tres carnes | E44: 35000 | F44: EFECTIVO | G44: 1 | H44: 1 | I44: =+E44*G44 -> 35000
A45: 25-feb | B45: 46078.601 | C45: 34 | D45: parri tres carnes | E45: 35000 | F45: EFECTIVO | G45: 1 | H45: 1 | I45: =+E45*G45 -> 35000
A46: 25-feb | B46: 46078.601 | C46: 35 | D46: Chorizo | E46: 8000 | F46: EFECTIVO | G46: 2 | H46: 1 | I46: =+E46*G46 -> 16000
A47: 25-feb | B47: 46078.695 | C47: 36 | D47: Chorizo | E47: 8000 | F47: EFECTIVO | G47: 1 | H47: 1 | I47: =+E47*G47 -> 8000
A48: 25-feb | B48: 46078.695 | C48: 37 | D48: Chorizo | E48: 8000 | F48: NEQUI | G48: 1 | H48: 1 | I48: =+E48*G48 -> 8000
A49: 25-feb | B49: 46078.762 | C49: 38 | D49: Chorizo | E49: 8000 | F49: EFECTIVO | G49: 1 | H49: 1 | I49: =+E49*G49 -> 8000
A50: 25-feb | B50: 46078.764 | C50: 39 | D50: Chorizo | E50: 8000 | F50: EFECTIVO | G50: 1 | H50: 1 | I50: =+E50*G50 -> 8000
A51: 25-feb | B51: 46078.768 | C51: 41 | D51: Chorizo | E51: 8000 | F51: EFECTIVO | G51: 1 | H51: 1 | I51: =+E51*G51 -> 8000
... A53: 25-feb | B53: 46078.774 | C53: 43 | D53: Coca cola | E53: 3000 | F53: EFECTIVO | G53: 2 | H53: 1 | I53: =+E53*G53 -> 6000
A54: 25-feb | D54: Postobon | E54: 3000 | F54: EFECTIVO | G54: 1 | H54: 1 | I54: =+E54*G54 -> 3000
A55: 25-feb | B55: 46078.778 | C55: 44 | D55: Chorizo | E55: 8000 | F55: EFECTIVO | G55: 3 | H55: 1 | I55: =+E55*G55 -> 24000
A56: 25-feb | B56: 46078.799 | C56: 45 | D56: Chorizo | E56: 8000 | F56: NEQUI | G56: 1 | H56: 1 | I56: =+E56*G56 -> 8000
A57: 25-feb | B57: 46078.8 | C57: 46 | D57: Chorizo | E57: 8000 | F57: EFECTIVO | G57: 1 | H57: 1 | I57: =+E57*G57 -> 8000
A58: 25-feb | D58: Coca cola | E58: 3000 | F58: EFECTIVO | G58: 1 | H58: 1 | I58: =+E58*G58 -> 3000
A59: 25-feb | B59: 46078.807 | C59: 47 | D59: Chori- CRUDO | E59: 4500 | F59: NEQUI | G59: 5 | H59: 1 | I59: =+E59*G59 -> 22500
A60: 25-feb | B60: 46078.819 | C60: 48 | D60: parri tres carnes | E60: 35000 | F60: EFECTIVO | G60: 1 | H60: 1 | I60: =+E60*G60 -> 35000
A61: 25-feb | D61: Postobon | E61: 3000 | F61: EFECTIVO | G61: 1 | H61: 1 | I61: =+E61*G61 -> 3000
A62: 25-feb | B62: 46078.82 | C62: 49 | D62: Chorizo | E62: 8000 | F62: EFECTIVO | G62: 2 | H62: 1 | I62: =+E62*G62 -> 16000
A63: 25-feb | B63: 46078.833 | C63: 50 | D63: Chorizo | E63: 8000 | F63: EFECTIVO | G63: 2 | H63: 1 | I63: =+E63*G63 -> 16000
A64: 25-feb | B64: 46078.838 | C64: 51 | D64: Chorizo | E64: 8000 | F64: EFECTIVO | G64: 4 | H64: 1 | I64: =+E64*G64 -> 32000
A65: 25-feb | B65: 46078.842 | C65: 52 | D65: Chorizo | E65: 8000 | F65: NEQUI | G65: 1 | H65: 1 | I65: =+E65*G65 -> 8000
A66: 25-feb | B66: 46078.848 | C66: 53 | D66: Chorizo | E66: 8000 | F66: EFECTIVO | G66: 2 | H66: 1 | I66: =+E66*G66 -> 16000
A67: 26-feb | B67: 46079.557 | C67: 54 | D67: Chori- CRUDO | E67: 4500 | F67: EFECTIVO | G67: 2 | H67: 1 | I67: =+E67*G67 -> 9000
A68: 26-feb | B68: 46079.561 | C68: 55 | D68: Chorizo | E68: 8000 | F68: EFECTIVO | G68: 2 | H68: 1 | I68: =+E68*G68 -> 16000
A69: 26-feb | B69: 46079.634 | C69: 56 | D69: carne + chorizo | E69: 25000 | F69: NEQUI | G69: 1 | H69: 1 | I69: =+E69*G69 -> 25000
A70: 26-feb | B70: 46079.728 | C70: 57 | D70: Chorizo | E70: 8000 | F70: NEQUI | G70: 5 | H70: 1 | I70: =+E70*G70 -> 40000
A71: 26-feb | D71: Postobon | E71: 3000 | F71: NEQUI | G71: 3 | H71: 1 | I71: =+E71*G71 -> 9000
A72: 26-feb | B72: 46079.753 | C72: 58 | D72: Chorizo | E72: 8000 | F72: EFECTIVO | G72: 1 | H72: 1 | I72: =+E72*G72 -> 8000
A73: 26-feb | B73: 46079.763 | C73: 59 | D73: Chorizo | E73: 8000 | F73: NEQUI | G73: 1 | H73: 1 | I73: =+E73*G73 -> 8000
A74: 26-feb | B74: 46079.764 | C74: 60 | D74: Chorizo | E74: 8000 | F74: EFECTIVO | G74: 1 | H74: 1 | I74: =+E74*G74 -> 8000
A75: 26-feb | B75: 46079.774 | C75: 61 | D75: Chorizo | E75: 8000 | F75: NEQUI | G75: 1 | H75: 1 | I75: =+E75*G75 -> 8000
A76: 26-feb | B76: 46079.795 | C76: 62 | D76: Chorizo | E76: 8000 | F76: EFECTIVO | G76: 2 | H76: 1 | I76: =+E76*G76 -> 16000
A77: 26-feb | B77: 46079.812 | C77: 63 | D77: Chorizo | E77: 8000 | F77: NEQUI | G77: 2 | H77: 1 | I77: =+E77*G77 -> 16000
A78: 26-feb | D78: Coca cola | E78: 3000 | F78: NEQUI | G78: 1 | H78: 1 | I78: =+E78*G78 -> 3000
A79: 26-feb | B79: 46079.814 | C79: 64 | D79: Chorizo | E79: 8000 | F79: EFECTIVO | G79: 1 | H79: 1 | I79: =+E79*G79 -> 8000
A80: 26-feb | B80: 46079.815 | C80: 65 | D80: Chorizo | E80: 8000 | F80: EFECTIVO | G80: 1 | H80: 1 | I80: =+E80*G80 -> 8000
A81: 26-feb | B81: 46079.844 | C81: 66 | D81: Chorizo | E81: 8000 | F81: EFECTIVO | G81: 1 | H81: 1 | I81: =+E81*G81 -> 8000
A82: 26-feb | D82: Postobon | E82: 3000 | F82: EFECTIVO | G82: 1 | H82: 1 | I82: =+E82*G82 -> 3000
A83: 26-feb | B83: 46079.844 | C83: 67 | D83: Chorizo | E83: 8000 | F83: NEQUI | G83: 1 | H83: 1 | I83: =+E83*G83 -> 8000
A84: 26-feb | B84: 46079.844 | C84: 68 | D84: Chorizo | E84: 8000 | F84: NEQUI | G84: 1 | H84: 1 | I84: =+E84*G84 -> 8000
A85: 27-feb | B85: 46080.63 | C85: 69 | D85: Chorizo | E85: 8000 | F85: NEQUI | G85: 1 | H85: 1 | I85: =+E85*G85 -> 8000
A86: 27-feb | D86: Postobon | E86: 3000 | F86: NEQUI | G86: 1 | H86: 1 | I86: =+E86*G86 -> 3000
A87: 27-feb | B87: 46080.631 | C87: 70 | D87: Chorizo | E87: 8000 | F87: EFECTIVO | G87: 1 | H87: 1 | I87: =+E87*G87 -> 8000
A88: 27-feb | B88: 46080.716 | C88: 71 | D88: Chorizo | E88: 8000 | F88: EFECTIVO | G88: 1 | H88: 1 | I88: =+E88*G88 -> 8000
A89: 27-feb | D89: parri tres carnes | E89: 35000 | F89: EFECTIVO | G89: 1 | H89: 1 | I89: =+E89*G89 -> 35000
A90: 27-feb | D90: tinto | E90: 2000 | F90: EFECTIVO | G90: 1 | H90: 1 | I90: =+E90*G90 -> 2000
A91: 27-feb | B91: 46080.725 | C91: 72 | D91: Chorizo | E91: 8000 | F91: EFECTIVO | G91: 3 | H91: 1 | I91: =+E91*G91 -> 24000
A92: 27-feb | D92: Coca cola | E92: 3000 | F92: EFECTIVO | G92: 2 | H92: 1 | I92: =+E92*G92 -> 6000
A93: 27-feb | D93: parri tres carnes | E93: 35000 | F93: EFECTIVO | G93: 1 | H93: 1 | I93: =+E93*G93 -> 35000
A94: 27-feb | B94: 46080.742 | C94: 73 | D94: Chorizo | E94: 8000 | F94: EFECTIVO | G94: 2 | H94: 1 | I94: =+E94*G94 -> 16000
A95: 27-feb | D95: Coca cola | E95: 3000 | F95: EFECTIVO | G95: 1 | H95: 1 | I95: =+E95*G95 -> 3000
A96: 27-feb | B96: 46080.761 | C96: 74 | D96: Chorizo | E96: 8000 | F96: NEQUI | G96: 3 | H96: 1 | I96: =+E96*G96 -> 24000
A97: 27-feb | B97: 46080.824 | C97: 75 | D97: Agua | E97: 3000 | F97: DaviPlata | G97: 1 | H97: 1 | I97: =+E97*G97 -> 3000
A98: 27-feb | D98: Chorizo | E98: 8000 | F98: DaviPlata | G98: 1 | H98: 1 | I98: =+E98*G98 -> 8000
A99: 27-feb | B99: 46080.836 | C99: 76 | D99: Chorizo | E99: 8000 | F99: NEQUI | G99: 2 | H99: 1 | I99: =+E99*G99 -> 16000
A100: 27-feb | B100: 46080.837 | C100: 77 | D100: Chorizo | E100: 8000 | F100: EFECTIVO | G100: 4 | H100: 1 | I100: =+E100*G100 -> 32000
A101: 27-feb | D101: Coca cola | E101: 3000 | F101: EFECTIVO | G101: 3 | H101: 1 | I101: =+E101*G101 -> 9000
A102: 27-feb | B102: 46080.839 | C102: 78 | D102: Chorizo | E102: 8000 | F102: EFECTIVO | G102: 1 | H102: 1 | I102: =+E102*G102 -> 8000
A103: 28-feb | B103: 46081.79 | C103: 79 | D103: Chori- CRUDO | E103: 4500 | F103: EFECTIVO | G103: 6 | H103: 1 | I103: =+E103*G103 -> 27000
...

Sheet urls
A1: url_DigiLivo | B1: https://argentina-infrasonic-halina.ngrok-free.dev
A2: url_Choriboni | B2: https://subformative-marylee-solvently.ngrok-free.dev
A3: url_Local | B3: http://localhost:5000
