Workbook
Name empleados: [1]Empleados!$A$6:$H$17
Name fDate: '[2]Previsión de ventas'!$D$3
Name fYear: '[2]Previsión de ventas'!$I$2
Name THE: [1]HorasExtras!$A$13:$P$24

Sheet Scotiabank_Platino
C3: Valor del préstamo | D3: =2670000+850000 -> 3520000 | F3: Resumen:
C4: TNA (30/360) | D4: 0.1043 | F4: Valor préstamo | G4: =D3 -> 3520000
C5: Años | D5: 2 | F5: Suma de Cuotas | G5: =SUM($D$14:$D$400) -> 3915111.1 | N5: Equivalencias TASAS efectiVas
C6: Frecuencia de Pago | D6: Mensual | F6: Suma de Interés | G6: =SUM($E$14:$E$400) -> 395111.08 | N6: Anual | O6: =360/360 -> 1
C7: Interés equivalente | D7: =((1+EFFECT(D4,D8))^VLOOKUP(D6,$N$6:$O$11,2,0))-1 -> 0.0086916667 | N7: Semestral | O7: =180/360 -> 0.5
C8: N° de pagos por año | D8: =IF(D6="Mensual",12,IF(D6="Bimensual",6,IF(D6="Trimestral",4,IF(D6="Cuatrimestral",3,IF(D6="Semestral",2,1))))) -> 12 | N8: Cuatrimestral | O8: =120/360 -> 0.33333333
C9: N° Total de Cuotas | D9: =D5*D8 -> 24 | N9: Trimestral | O9: =90/360 -> 0.25
N10: Bimensual | O10: =60/360 -> 0.16666667
N11: Mensual | O11: =30/360 -> 0.083333333
C12: Número de Cuota | D12: CUOTA A PAGAR | E12: INTERÉS | F12: CAPITAL AMORTIZADO | G12: CAPITAL VIVO
C13: 0 | G13: =D3 -> 3520000
C14: =IF(OR(C13=$D$9,C13=""),"",IF(ISNUMBER(C13),C13+1,1)) -> 1 | D14: =IF(C14>$D$9,"",PMT($D$7,$D$9,$D$3)*-1) -> 163129.63 | E14: =IF(C14>$D$9,"",$D$7*G13) -> 30594.667 | F14: =IF(C14>$D$9,"",D14-E14) -> 132534.96 | G14: =IF(C14>$D$9,"",G13-F14) -> 3387465
C15: =IF(OR(C14=$D$9,C14=""),"",IF(ISNUMBER(C14),C14+1,1)) -> 2 | D15: =IF(C15>$D$9,"",PMT($D$7,$D$9,$D$3)*-1) -> 163129.63 | E15: =IF(C15>$D$9,"",$D$7*G14) -> 29442.717 | F15: =IF(C15>$D$9,"",D15-E15) -> 133686.91 | G15: =IF(C15>$D$9,"",G14-F15) -> 3253778.1
C16: =IF(OR(C15=$D$9,C15=""),"",IF(ISNUMBER(C15),C15+1,1)) -> 3 | D16: =IF(C16>$D$9,"",PMT($D$7,$D$9,$D$3)*-1) -> 163129.63 | E16: =IF(C16>$D$9,"",$D$7*G15) -> 28280.755 | F16: =IF(C16>$D$9,"",D16-E16) -> 134848.87 | G16: =IF(C16>$D$9,"",G15-F16) -> 3118929.3
C17: =IF(OR(C16=$D$9,C16=""),"",IF(ISNUMBER(C16),C16+1,1)) -> 4 | D17: =IF(C17>$D$9,"",PMT($D$7,$D$9,$D$3)*-1) -> 163129.63 | E17: =IF(C17>$D$9,"",$D$7*G16) -> 27108.693 | F17: =IF(C17>$D$9,"",D17-E17) -> 136020.94 | G17: =IF(C17>$D$9,"",G16-F17) -> 2982908.3
C18: =IF(OR(C17=$D$9,C17=""),"",IF(ISNUMBER(C17),C17+1,1)) -> 5 | D18: =IF(C18>$D$9,"",PMT($D$7,$D$9,$D$3)*-1) -> 163129.63 | E18: =IF(C18>$D$9,"",$D$7*G17) -> 25926.445 | F18: =IF(C18>$D$9,"",D18-E18) -> 137203.18 | G18: =IF(C18>$D$9,"",G17-F18) -> 2845705.1
C19: =IF(OR(C18=$D$9,C18=""),"",IF(ISNUMBER(C18),C18+1,1)) -> 6 | D19: =IF(C19>$D$9,"",PMT($D$7,$D$9,$D$3)*-1) -> 163129.63 | E19: =IF(C19>$D$9,"",$D$7*G18) -> 24733.92 | F19: =IF(C19>$D$9,"",D19-E19) -> 138395.71 | G19: =IF(C19>$D$9,"",G18-F19) -> 2707309.4
C20: =IF(OR(C19=$D$9,C19=""),"",IF(ISNUMBER(C19),C19+1,1)) -> 7 | D20: =IF(C20>$D$9,"",PMT($D$7,$D$9,$D$3)*-1) -> 163129.63 | E20: =IF(C20>$D$9,"",$D$7*G19) -> 23531.031 | F20: =IF(C20>$D$9,"",D20-E20) -> 139598.6 | G20: =IF(C20>$D$9,"",G19-F20) -> 2567710.8
C21: =IF(OR(C20=$D$9,C20=""),"",IF(ISNUMBER(C20),C20+1,1)) -> 8 | D21: =IF(C21>$D$9,"",PMT($D$7,$D$9,$D$3)*-1) -> 163129.63 | E21: =IF(C21>$D$9,"",$D$7*G20) -> 22317.687 | F21: =IF(C21>$D$9,"",D21-E21) -> 140811.94 | G21: =IF(C21>$D$9,"",G20-F21) -> 2426898.9
C22: =IF(OR(C21=$D$9,C21=""),"",IF(ISNUMBER(C21),C21+1,1)) -> 9 | D22: =IF(C22>$D$9,"",PMT($D$7,$D$9,$D$3)*-1) -> 163129.63 | E22: =IF(C22>$D$9,"",$D$7*G21) -> 21093.796 | F22: =IF(C22>$D$9,"",D22-E22) -> 142035.83 | G22: =IF(C22>$D$9,"",G21-F22) -> 2284863.1
C23: =IF(OR(C22=$D$9,C22=""),"",IF(ISNUMBER(C22),C22+1,1)) -> 10 | D23: =IF(C23>$D$9,"",PMT($D$7,$D$9,$D$3)*-1) -> 163129.63 | E23: =IF(C23>$D$9,"",$D$7*G22) -> 19859.268 | F23: =IF(C23>$D$9,"",D23-E23) -> 143270.36 | G23: =IF(C23>$D$9,"",G22-F23) -> 2141592.7
C24: =IF(OR(C23=$D$9,C23=""),"",IF(ISNUMBER(C23),C23+1,1)) -> 11 | D24: =IF(C24>$D$9,"",PMT($D$7,$D$9,$D$3)*-1) -> 163129.63 | E24: =IF(C24>$D$9,"",$D$7*G23) -> 18614.01 | F24: =IF(C24>$D$9,"",D24-E24) -> 144515.62 | G24: =IF(C24>$D$9,"",G23-F24) -> 1997077.1
C25: =IF(OR(C24=$D$9,C24=""),"",IF(ISNUMBER(C24),C24+1,1)) -> 12 | D25: =IF(C25>$D$9,"",PMT($D$7,$D$9,$D$3)*-1) -> 163129.63 | E25: =IF(C25>$D$9,"",$D$7*G24) -> 17357.928 | F25: =IF(C25>$D$9,"",D25-E25) -> 145771.7 | G25: =IF(C25>$D$9,"",G24-F25) -> 1851305.4
... C121: =IF(OR(C120=$D$9,C120=""),"",IF(ISNUMBER(C120),C120+1,1)) | D121: =IF(C121>$D$9,"",PMT($D$7,$D$9,$D$3)*-1) | E121: =IF(C121>$D$9,"",$D$7*G120) | F121: =IF(C121>$D$9,"",D121-E121) | G121: =IF(C121>$D$9,"",G120-F121)

Sheet Bancolombia
C3: Valor del préstamo | D3: =3000000+650000+1200000 -> 4850000 | F3: Resumen:
C4: TNA (30/360) | D4: 0.2892 | F4: Valor préstamo | G4: =D3 -> 4850000
C5: Años | D5: 2 | F5: Suma de Cuotas | G5: =SUM($D$14:$D$400) -> 6443717.7 | N5: Equivalencias TASAS efectiVas
C6: Frecuencia de Pago | D6: Mensual | F6: Suma de Interés | G6: =SUM($E$14:$E$400) -> 1593717.7 | J6: 143000 | N6: Anual | O6: =360/360 -> 1
C7: Interés equivalente | D7: =((1+EFFECT(D4,D8))^VLOOKUP(D6,$N$6:$O$11,2,0))-1 -> 0.0241 | N7: Semestral | O7: =180/360 -> 0.5
C8: N° de pagos por año | D8: =IF(D6="Mensual",12,IF(D6="Bimensual",6,IF(D6="Trimestral",4,IF(D6="Cuatrimestral",3,IF(D6="Semestral",2,1))))) -> 12 | N8: Cuatrimestral | O8: =120/360 -> 0.33333333
C9: N° Total de Cuotas | D9: =D5*D8 -> 24 | N9: Trimestral | O9: =90/360 -> 0.25
N10: Bimensual | O10: =60/360 -> 0.16666667
N11: Mensual | O11: =30/360 -> 0.083333333
C12: Número de Cuota | D12: CUOTA A PAGAR | E12: INTERÉS | F12: CAPITAL AMORTIZADO | G12: CAPITAL VIVO
C13: 0 | G13: =D3 -> 4850000
C14: =IF(OR(C13=$D$9,C13=""),"",IF(ISNUMBER(C13),C13+1,1)) -> 1 | D14: =IF(C14>$D$9,"",PMT($D$7,$D$9,$D$3)*-1) -> 268488.24 | E14: =IF(C14>$D$9,"",$D$7*G13) -> 116885 | F14: =IF(C14>$D$9,"",D14-E14) -> 151603.24 | G14: =IF(C14>$D$9,"",G13-F14) -> 4698396.8
C15: =IF(OR(C14=$D$9,C14=""),"",IF(ISNUMBER(C14),C14+1,1)) -> 2 | D15: =IF(C15>$D$9,"",PMT($D$7,$D$9,$D$3)*-1) -> 268488.24 | E15: =IF(C15>$D$9,"",$D$7*G14) -> 113231.36 | F15: =IF(C15>$D$9,"",D15-E15) -> 155256.88 | G15: =IF(C15>$D$9,"",G14-F15) -> 4543139.9
C16: =IF(OR(C15=$D$9,C15=""),"",IF(ISNUMBER(C15),C15+1,1)) -> 3 | D16: =IF(C16>$D$9,"",PMT($D$7,$D$9,$D$3)*-1) -> 268488.24 | E16: =IF(C16>$D$9,"",$D$7*G15) -> 109489.67 | F16: =IF(C16>$D$9,"",D16-E16) -> 158998.57 | G16: =IF(C16>$D$9,"",G15-F16) -> 4384141.3
C17: =IF(OR(C16=$D$9,C16=""),"",IF(ISNUMBER(C16),C16+1,1)) -> 4 | D17: =IF(C17>$D$9,"",PMT($D$7,$D$9,$D$3)*-1) -> 268488.24 | E17: =IF(C17>$D$9,"",$D$7*G16) -> 105657.81 | F17: =IF(C17>$D$9,"",D17-E17) -> 162830.43 | G17: =IF(C17>$D$9,"",G16-F17) -> 4221310.9
C18: =IF(OR(C17=$D$9,C17=""),"",IF(ISNUMBER(C17),C17+1,1)) -> 5 | D18: =IF(C18>$D$9,"",PMT($D$7,$D$9,$D$3)*-1) -> 268488.24 | E18: =IF(C18>$D$9,"",$D$7*G17) -> 101733.59 | F18: =IF(C18>$D$9,"",D18-E18) -> 166754.65 | G18: =IF(C18>$D$9,"",G17-F18) -> 4054556.2
C19: =IF(OR(C18=$D$9,C18=""),"",IF(ISNUMBER(C18),C18+1,1)) -> 6 | D19: =IF(C19>$D$9,"",PMT($D$7,$D$9,$D$3)*-1) -> 268488.24 | E19: =IF(C19>$D$9,"",$D$7*G18) -> 97714.805 | F19: =IF(C19>$D$9,"",D19-E19) -> 170773.43 | G19: =IF(C19>$D$9,"",G18-F19) -> 3883782.8
C20: =IF(OR(C19=$D$9,C19=""),"",IF(ISNUMBER(C19),C19+1,1)) -> 7 | D20: =IF(C20>$D$9,"",PMT($D$7,$D$9,$D$3)*-1) -> 268488.24 | E20: =IF(C20>$D$9,"",$D$7*G19) -> 93599.166 | F20: =IF(C20>$D$9,"",D20-E20) -> 174889.07 | G20: =IF(C20>$D$9,"",G19-F20) -> 3708893.7
C21: =IF(OR(C20=$D$9,C20=""),"",IF(ISNUMBER(C20),C20+1,1)) -> 8 | D21: =IF(C21>$D$9,"",PMT($D$7,$D$9,$D$3)*-1) -> 268488.24 | E21: =IF(C21>$D$9,"",$D$7*G20) -> 89384.339 | F21: =IF(C21>$D$9,"",D21-E21) -> 179103.9 | G21: =IF(C21>$D$9,"",G20-F21) -> 3529789.8
C22: =IF(OR(C21=$D$9,C21=""),"",IF(ISNUMBER(C21),C21+1,1)) -> 9 | D22: =IF(C22>$D$9,"",PMT($D$7,$D$9,$D$3)*-1) -> 268488.24 | E22: =IF(C22>$D$9,"",$D$7*G21) -> 85067.935 | F22: =IF(C22>$D$9,"",D22-E22) -> 183420.3 | G22: =IF(C22>$D$9,"",G21-F22) -> 3346369.5
C23: =IF(OR(C22=$D$9,C22=""),"",IF(ISNUMBER(C22),C22+1,1)) -> 10 | D23: =IF(C23>$D$9,"",PMT($D$7,$D$9,$D$3)*-1) -> 268488.24 | E23: =IF(C23>$D$9,"",$D$7*G22) -> 80647.506 | F23: =IF(C23>$D$9,"",D23-E23) -> 187840.73 | G23: =IF(C23>$D$9,"",G22-F23) -> 3158528.8
C24: =IF(OR(C23=$D$9,C23=""),"",IF(ISNUMBER(C23),C23+1,1)) -> 11 | D24: =IF(C24>$D$9,"",PMT($D$7,$D$9,$D$3)*-1) -> 268488.24 | E24: =IF(C24>$D$9,"",$D$7*G23) -> 76120.544 | F24: =IF(C24>$D$9,"",D24-E24) -> 192367.69 | G24: =IF(C24>$D$9,"",G23-F24) -> 2966161.1
C25: =IF(OR(C24=$D$9,C24=""),"",IF(ISNUMBER(C24),C24+1,1)) -> 12 | D25: =IF(C25>$D$9,"",PMT($D$7,$D$9,$D$3)*-1) -> 268488.24 | E25: =IF(C25>$D$9,"",$D$7*G24) -> 71484.483 | F25: =IF(C25>$D$9,"",D25-E25) -> 197003.76 | G25: =IF(C25>$D$9,"",G24-F25) -> 2769157.4
... C121: =IF(OR(C120=$D$9,C120=""),"",IF(ISNUMBER(C120),C120+1,1)) | D121: =IF(C121>$D$9,"",PMT($D$7,$D$9,$D$3)*-1) | E121: =IF(C121>$D$9,"",$D$7*G120) | F121: =IF(C121>$D$9,"",D121-E121) | G121: =IF(C121>$D$9,"",G120-F121)

Sheet Inicio

Sheet Inversión sociedad
D3: Aporte socios | E3: Caja menor
A4: Edwin | B4: Scotiabank | C4: losa, Trompo, empleados | D4: =2600000-E4 -> 2350000 | E4: 250000 | F4: =+SUM(D4:D9) -> 8460000 | G4: =+F4/$F$18 -> 0.37666963 | J4: 7000000 | K4: Aporte
B5: Bancolombia | C5: empleados, deudas, otros | D5: 3000000
B6: Bancolombia | C6: Mercado y otros | D6: 650000 | J6: 960000 | K6: nomina
B7: sueldo | C7: honorarios contrucción | D7: 960000 | J7: 600000
B8: Scotiabank | C8: caja electronica y seguridad | D8: 800000
B9: American | C9: hugo | D9: 700000 | J9: =+SUM(J4:J7) -> 8560000
A10: Hector | C10: Arriendo | D10: 2500000 | F10: =+SUM(D10:D13) -> 12500000 | G10: =+F10/$F$18 -> 0.55654497 | J10: 1000000 | K10: Cámaras
C11: locativas local | D11: =10000000-D10-D13 -> 5900000 | J11: 1000000 | K11: Caja electronica
C12: Moto | D12: 2500000 | J12: 500000 | K12: Software
C13: honorarios Papá (Manutención) | D13: =1000000+600000 -> 1600000 | J13: =+SUM(J10:J12) -> 2500000
A14: Papá | C14: Gestión del local | F14: =+SUM(D14:D17) -> 1500000 | G14: =+F14/$F$18 -> 0.066785396
C15: Experiencia, Sason | J15: =+J9+J13 -> 11060000
C16: Administrador (comisión 33% del negocio)
C17: Bicicleta, Parrilla | D17: 1500000
F18: =+SUM(F4:F17) -> 22460000 | G18: =+SUM(G4:G17) -> 1
A21: Papá | C21: Ahorro servicios | D21: 600000

Sheet Flujo de caja
G1: 20 | H1: 10
E2: Mes | F2: Promedio diario | G2: Dìa habil | H2: Fines de semana
G3: =+E4-H3 -> 8750000 | H3: =+H4*H1 -> 10000000
A4: INGRESOS | E4: =+E6/C6 -> 18750000 | F4: =+E4/30 -> 625000 | G4: =+G3/$G$1 -> 437500 | H4: 1000000
A5: Costos | B5: %Costo | C5: 0.6 | E5: =+$E$4*C5 -> 11250000 | F5: =+E5/30 -> 375000 | G5: =+G4*$C$5 -> 262500 | H5: =+H4*$C$5 -> 600000
A6: GASTOS | C6: 0.4 | E6: =+SUM(E7:E1048576)-E26 -> 7500000 | F6: =+E6/30 -> 250000 | G6: =+G4*$C$6 -> 175000 | H6: =+H4*$C$6 -> 400000
A7: Arriendo | E7: 2500000
A8: Servicios | B8: Agua | E8: 1500000
B9: Luz
B10: Gas | I10: Inventario | J10: Veces | K10: Dias
A11: Nomina | B11: Cocinera y dos meseros | D11: 3 trabajadores | E11: =1000000+600000+900000 -> 2500000 | I11: =1000000*6 -> 6000000 | J11: =+E4/I11 -> 3.125 | K11: =+I11/E4*30 -> 9.6
A12: Financieros | E12: 1000000
A14: Financieros | B14: ScotiaBank | C14: Visa/platinum | D14: 5300000
B15: ScotiaBank | C15: Master Card / Clasica | D15: 1500000 | I15: =+I11/K11 -> 625000
B16: ScotiaBank | C16: Visa Clasica | D16: 1500000
B17: Bancolombia | C17: Visa Clasica | D17: 4000000
B18: Bancolombia | C18: American Express /Otra | D18: 3000000
B19: Banco de Bogotá | C19: Visa Clasica | D19: 500000 | G19: =+E4*12 -> 225000000
B20: Falabella | D20: 3800000
B21: Codensa | D21: 2000000 | G21: =+G19*0.3 -> 67500000
D22: =+SUM(D14:D21) -> 21600000
C23: Polular | D23: 500000
A26: Servicios | B26: Adecuaciones del local | E26: 16000000
D28: =+E5+E26 -> 27250000
D30: =+E11/D28 -> 0.091743119

Sheet Ventas
B4: Politica implantada | C4: FECHA | D4: Dia | E4: Dia semanal | F4: Tipo Dìa | G4: No. de semana | H4: Vendedor | I4: Id. Client por dìa | J4: Producto | K4: Q | L4: Precio item | M4: Ventas | N4: Detalle | O4: Gastos | P4: Hay soportes
B5: Se implanto el sistema de facturación; | C5: 43730 | D5: =+DAY(Ventas[[#This Row],[FECHA]]) -> 22 | E5: =+TEXT(C5,"dddd") -> domingo | F5: Fds y Festivo | G5: 0 | M5: 572000 | X5: No. | Y5: Ventas | Z5: Venta promedio
B6: se cerro la negociación con rapiexpress; Se entrevisto a un sabatino; Se hizo arreglos del trompo por lo cual no se vendio platos de parrilla | C6: 43731 | D6: =+DAY(Ventas[[#This Row],[FECHA]]) -> 23 | E6: =+TEXT(C6,"dddd") -> lunes | F6: Día hábil | G6: 1 | H6: Yusmeidy | I6: 1 | J6: Ejecutivo | K6: 1 | L6: 12000 | M6: =+Ventas[[#This Row],[Precio item]]*Ventas[[#This Row],[Q]] -> 12000 | W6: lunes | X6: =+COUNTIF($E$5:$E$322,W6) -> 46 | Y6: =+SUMIF($E$6:$E$322,W6,$M$6:$M$322) -> 1550710 | Z6: =+Y6/X6 -> 33711.087
C7: 43731 | D7: =+DAY(Ventas[[#This Row],[FECHA]]) -> 23 | E7: =+TEXT(C7,"dddd") -> lunes | F7: Día hábil | G7: 1 | H7: Yusmeidy | I7: 1 | J7: Tè | K7: 1 | L7: 2000 | M7: =+Ventas[[#This Row],[Precio item]]*Ventas[[#This Row],[Q]] -> 2000 | W7: martes | X7: =+COUNTIF($E$5:$E$322,W7) -> 26 | Y7: =+SUMIF($E$6:$E$322,W7,$M$6:$M$322) -> 1058100 | Z7: =+Y7/X7 -> 40696.154
C8: 43731 | D8: =+DAY(Ventas[[#This Row],[FECHA]]) -> 23 | E8: =+TEXT(C8,"dddd") -> lunes | F8: Día hábil | G8: 1 | H8: Yusmeidy | I8: 1 | J8: Jugo Hit | K8: 1 | L8: 2000 | M8: =+Ventas[[#This Row],[Precio item]]*Ventas[[#This Row],[Q]] -> 2000 | R8: 600000 | W8: miércoles | X8: =+COUNTIF($E$5:$E$322,W8) -> 28 | Y8: =+SUMIF($E$6:$E$322,W8,$M$6:$M$322) -> 791500 | Z8: =+Y8/X8 -> 28267.857
C9: 43731 | D9: =+DAY(Ventas[[#This Row],[FECHA]]) -> 23 | E9: =+TEXT(C9,"dddd") -> lunes | F9: Día hábil | G9: 1 | H9: Yusmeidy | I9: 2 | J9: Sopa | K9: 1 | L9: 6000 | M9: =+Ventas[[#This Row],[Precio item]]*Ventas[[#This Row],[Q]] -> 6000 | W9: jueves | X9: =+COUNTIF($E$5:$E$322,W9) -> 19 | Y9: =+SUMIF($E$6:$E$322,W9,$M$6:$M$322) -> 638500 | Z9: =+Y9/X9 -> 33605.263
C10: 43731 | D10: =+DAY(Ventas[[#This Row],[FECHA]]) -> 23 | E10: =+TEXT(C10,"dddd") -> lunes | F10: Día hábil | G10: 1 | H10: Yusmeidy | I10: 3 | J10: Ejecutivo | K10: 2 | L10: 12000 | M10: =+Ventas[[#This Row],[Precio item]]*Ventas[[#This Row],[Q]] -> 24000 | W10: viernes | X10: =+COUNTIF($E$5:$E$322,W10) -> 22 | Y10: =+SUMIF($E$6:$E$322,W10,$M$6:$M$322) -> 1269400 | Z10: =+Y10/X10 -> 57700
C11: 43731 | D11: =+DAY(Ventas[[#This Row],[FECHA]]) -> 23 | E11: =+TEXT(C11,"dddd") -> lunes | F11: Día hábil | G11: 1 | H11: Yusmeidy | I11: 3 | J11: Gaseosa 350 | K11: 2 | L11: 2000 | M11: =+Ventas[[#This Row],[Precio item]]*Ventas[[#This Row],[Q]] -> 4000 | W11: sábado | X11: =+COUNTIF($E$5:$E$322,W11) -> 70 | Y11: =+SUMIF($E$6:$E$322,W11,$M$6:$M$322) -> 2826300 | Z11: =+Y11/X11 -> 40375.714
C12: 43731 | D12: =+DAY(Ventas[[#This Row],[FECHA]]) -> 23 | E12: =+TEXT(C12,"dddd") -> lunes | F12: Día hábil | G12: 1 | H12: Yusmeidy | I12: 4 | J12: Ejecutivo | K12: 1 | L12: 10000 | M12: =+Ventas[[#This Row],[Precio item]]*Ventas[[#This Row],[Q]] -> 10000 | N12: El señor José lo dejo en $ 10.000 | W12: domingo | X12: =+COUNTIF($E$5:$E$322,W12) -> 107 | Y12: =+SUMIF($E$6:$E$322,W12,$M$6:$M$322) -> 3287100 | Z12: =+Y12/X12 -> 30720.561
C13: 43731 | D13: =+DAY(Ventas[[#This Row],[FECHA]]) -> 23 | E13: =+TEXT(C13,"dddd") -> lunes | F13: Día hábil | G13: 1 | H13: Yusmeidy | I13: 5 | J13: Ejecutivo | K13: 2 | L13: 10000 | M13: =+Ventas[[#This Row],[Precio item]]*Ventas[[#This Row],[Q]] -> 20000 | N13: Sin nota
C14: 43731 | D14: =+DAY(Ventas[[#This Row],[FECHA]]) -> 23 | E14: =+TEXT(C14,"dddd") -> lunes | F14: Día hábil | G14: 1 | H14: Yusmeidy | I14: 6 | J14: Ejecutivo | K14: 4 | L14: 10000 | M14: =+Ventas[[#This Row],[Precio item]]*Ventas[[#This Row],[Q]] -> 40000
C15: 43731 | D15: =+DAY(Ventas[[#This Row],[FECHA]]) -> 23 | E15: =+TEXT(C15,"dddd") -> lunes | F15: Día hábil | G15: 1 | H15: Yusmeidy | I15: 7 | J15: Caderita | K15: 1 | L15: 22000 | M15: =+Ventas[[#This Row],[Precio item]]*Ventas[[#This Row],[Q]] -> 22000 | Q15: bajo revisiòn | S15: cita medica
C16: 43732 | D16: =+DAY(Ventas[[#This Row],[FECHA]]) -> 24 | E16: =+TEXT(C16,"dddd") -> martes | F16: Día hábil | G16: 1 | H16: Yusmeidy | I16: 1 | J16: Medias carnes | K16: 1 | L16: 15000 | M16: =+Ventas[[#This Row],[Precio item]]*Ventas[[#This Row],[Q]] -> 15000
C17: 43732 | D17: =+DAY(Ventas[[#This Row],[FECHA]]) -> 24 | E17: =+TEXT(C17,"dddd") -> martes | F17: Día hábil | G17: 1 | H17: Yusmeidy | I17: 2 | J17: Carne llanera | K17: 2 | L17: 22000 | M17: =+Ventas[[#This Row],[Precio item]]*Ventas[[#This Row],[Q]] -> 44000
C18: 43732 | D18: =+DAY(Ventas[[#This Row],[FECHA]]) -> 24 | E18: =+TEXT(C18,"dddd") -> martes | F18: Día hábil | G18: 1 | H18: Yusmeidy | I18: 2 | J18: Sopa | K18: 3 | L18: 4000 | M18: =+Ventas[[#This Row],[Precio item]]*Ventas[[#This Row],[Q]] -> 12000
C19: 43732 | D19: =+DAY(Ventas[[#This Row],[FECHA]]) -> 24 | E19: =+TEXT(C19,"dddd") -> martes | F19: Día hábil | G19: 1 | H19: Yusmeidy | I19: 2 | J19: Gaseosa litro y medio | K19: 1 | L19: 4000 | M19: =+Ventas[[#This Row],[Precio item]]*Ventas[[#This Row],[Q]] -> 4000
C20: 43732 | D20: =+DAY(Ventas[[#This Row],[FECHA]]) -> 24 | E20: =+TEXT(C20,"dddd") -> martes | F20: Día hábil | G20: 1 | H20: Yusmeidy | I20: 3 | J20: Carne llanera | K20: 1 | L20: 25000 | M20: =+Ventas[[#This Row],[Precio item]]*Ventas[[#This Row],[Q]] -> 25000
C21: 43732 | D21: =+DAY(Ventas[[#This Row],[FECHA]]) -> 24 | E21: =+TEXT(C21,"dddd") -> martes | F21: Día hábil | G21: 1 | H21: Yusmeidy | I21: 3 | J21: Gaseosa 350 | K21: 1 | L21: 2000 | M21: =+Ventas[[#This Row],[Precio item]]*Ventas[[#This Row],[Q]] -> 2000
C22: 43732 | D22: =+DAY(Ventas[[#This Row],[FECHA]]) -> 24 | E22: =+TEXT(C22,"dddd") -> martes | F22: Día hábil | G22: 1 | H22: Yusmeidy | I22: 4 | J22: Carne llanera | K22: 1 | L22: 25000 | M22: =+Ventas[[#This Row],[Precio item]]*Ventas[[#This Row],[Q]] -> 25000
C23: 43732 | D23: =+DAY(Ventas[[#This Row],[FECHA]]) -> 24 | E23: =+TEXT(C23,"dddd") -> martes | F23: Día hábil | G23: 1 | H23: Yusmeidy | I23: 4 | J23: Cerbeza | K23: 3 | L23: 3000 | M23: =+Ventas[[#This Row],[Precio item]]*Ventas[[#This Row],[Q]] -> 9000 | N23: No dice que marca es?
C24: 43732 | D24: =+DAY(Ventas[[#This Row],[FECHA]]) -> 24 | E24: =+TEXT(C24,"dddd") -> martes | F24: Día hábil | G24: 1 | H24: Yusmeidy | I24: 5 | J24: Media carne | K24: 1 | L24: 15000 | M24: =+Ventas[[#This Row],[Precio item]]*Ventas[[#This Row],[Q]] -> 15000
C25: 43732 | D25: =+DAY(Ventas[[#This Row],[FECHA]]) -> 24 | E25: =+TEXT(C25,"dddd") -> martes | F25: Día hábil | G25: 1 | H25: Yusmeidy | I25: 6 | J25: Ejecutivo | K25: 2 | L25: 10000 | M25: =+Ventas[[#This Row],[Precio item]]*Ventas[[#This Row],[Q]] -> 20000
C26: 43732 | D26: =+DAY(Ventas[[#This Row],[FECHA]]) -> 24 | E26: =+TEXT(C26,"dddd") -> martes | F26: Día hábil | G26: 1 | H26: Yusmeidy | I26: 7 | J26: Carne llanera | K26: 2 | L26: 25000 | M26: =+Ventas[[#This Row],[Precio item]]*Ventas[[#This Row],[Q]] -> 50000
C27: 43732 | D27: =+DAY(Ventas[[#This Row],[FECHA]]) -> 24 | E27: =+TEXT(C27,"dddd") -> martes | F27: Día hábil | G27: 1 | H27: Yusmeidy | I27: 7 | J27: Gaseosa 350 | K27: 3 | L27: 2000 | M27: =+Ventas[[#This Row],[Precio item]]*Ventas[[#This Row],[Q]] -> 6000
C28: 43732 | D28: =+DAY(Ventas[[#This Row],[FECHA]]) -> 24 | E28: =+TEXT(C28,"dddd") -> martes | F28: Día hábil | G28: 1 | H28: Yusmeidy | I28: 8 | J28: Ejecutivo | K28: 1 | L28: 10000 | M28: =+Ventas[[#This Row],[Precio item]]*Ventas[[#This Row],[Q]] -> 10000
C29: 43732 | D29: =+DAY(Ventas[[#This Row],[FECHA]]) -> 24 | E29: =+TEXT(C29,"dddd") -> martes | F29: Día hábil | G29: 1 | H29: Yusmeidy | I29: 9 | J29: Ejecutivo | K29: 2 | L29: 10000 | M29: =+Ventas[[#This Row],[Precio item]]*Ventas[[#This Row],[Q]] -> 20000
C30: 43732 | D30: =+DAY(Ventas[[#This Row],[FECHA]]) -> 24 | E30: =+TEXT(C30,"dddd") -> martes | F30: Día hábil | G30: 1 | H30: Yusmeidy | I30: 9 | J30: Agua | K30: 1 | L30: 2000 | M30: =+Ventas[[#This Row],[Precio item]]*Ventas[[#This Row],[Q]] -> 2000
C31: 43732 | D31: =+DAY(Ventas[[#This Row],[FECHA]]) -> 24 | E31: =+TEXT(C31,"dddd") -> martes | F31: Día hábil | G31: 1 | H31: Yusmeidy | I31: 10 | J31: Cerbeza | K31: 9 | L31: 3000 | M31: =+Ventas[[#This Row],[Precio item]]*Ventas[[#This Row],[Q]] -> 27000
C32: 43732 | D32: =+DAY(Ventas[[#This Row],[FECHA]]) -> 24 | E32: =+TEXT(C32,"dddd") -> martes | F32: Día hábil | G32: 1 | H32: Yusmeidy | I32: 11 | J32: Sopa especial | K32: 2 | L32: 15000 | M32: =+Ventas[[#This Row],[Precio item]]*Ventas[[#This Row],[Q]] -> 30000 | N32: dice que la sopa pequeña vale, lo mismo que la grande
C33: 43732 | D33: =+DAY(Ventas[[#This Row],[FECHA]]) -> 24 | E33: =+TEXT(C33,"dddd") -> martes | F33: Día hábil | G33: 1 | H33: Yusmeidy | I33: 11 | J33: Cerbeza | K33: 2 | L33: 3000 | M33: =+Ventas[[#This Row],[Precio item]]*Ventas[[#This Row],[Q]] -> 6000
C34: 43732 | D34: =+DAY(Ventas[[#This Row],[FECHA]]) -> 24 | E34: =+TEXT(C34,"dddd") -> martes | F34: Día hábil | G34: 1 | H34: Yusmeidy | I34: 11 | J34: Gaseosa litro y medio | K34: 1 | L34: 4000 | M34: =+Ventas[[#This Row],[Precio item]]*Ventas[[#This Row],[Q]] -> 4000
C35: 43732 | D35: =+DAY(Ventas[[#This Row],[FECHA]]) -> 24 | E35: =+TEXT(C35,"dddd") -> martes | F35: Día hábil | G35: 1 | H35: Yusmeidy | I35: 12 | J35: Ejecutivo | K35: 2 | L35: 10000 | M35: =+Ventas[[#This Row],[Precio item]]*Ventas[[#This Row],[Q]] -> 20000
C36: 43732 | D36: =+DAY(Ventas[[#This Row],[FECHA]]) -> 24 | E36: =+TEXT(C36,"dddd") -> martes | F36: Día hábil | G36: 1 | H36: Yusmeidy | I36: 13 | J36: Cerbeza | K36: 11 | L36: 3000 | M36: =+Ventas[[#This Row],[Precio item]]*Ventas[[#This Row],[Q]] -> 33000
C37: 43732 | D37: =+DAY(Ventas[[#This Row],[FECHA]]) -> 24 | E37: =+TEXT(C37,"dddd") -> martes | F37: Día hábil | G37: 1 | H37: Yusmeidy | I37: 13 | J37: Agua | K37: 1 | L37: 2000 | M37: =+Ventas[[#This Row],[Precio item]]*Ventas[[#This Row],[Q]] -> 2000
C38: 43732 | D38: =+DAY(Ventas[[#This Row],[FECHA]]) -> 24 | E38: =+TEXT(C38,"dddd") -> martes | F38: Día hábil | G38: 1 | H38: Yusmeidy | I38: 14 | J38: Sopa | K38: 2 | L38: 6000 | M38: =+Ventas[[#This Row],[Precio item]]*Ventas[[#This Row],[Q]] -> 12000 | N38: Changua
B39: Se le pago a Hugo por arreglos locativos | C39: 43733 | D39: =+DAY(Ventas[[#This Row],[FECHA]]) -> 25 | E39: =+TEXT(C39,"dddd") -> miércoles | F39: Día hábil | G39: 1 | H39: Yusmeidy | I39: 1 | J39: Picada | K39: 1 | L39: 25000 | M39: =+Ventas[[#This Row],[Precio item]]*Ventas[[#This Row],[Q]] -> 25000 | N39: ¿Cuántas personas?
C40: 43733 | D40: =+DAY(Ventas[[#This Row],[FECHA]]) -> 25 | E40: =+TEXT(C40,"dddd") -> miércoles | F40: Día hábil | G40: 1 | H40: Yusmeidy | I40: 2 | J40: Ejecutivo | K40: 2 | L40: 10000 | M40: =+Ventas[[#This Row],[Precio item]]*Ventas[[#This Row],[Q]] -> 20000
C41: 43733 | D41: =+DAY(Ventas[[#This Row],[FECHA]]) -> 25 | E41: =+TEXT(C41,"dddd") -> miércoles | F41: Día hábil | G41: 1 | H41: Yusmeidy | I41: 3 | J41: Ejecutivo | K41: 1 | L41: 10000 | M41: =+Ventas[[#This Row],[Precio item]]*Ventas[[#This Row],[Q]] -> 10000
C42: 43733 | D42: =+DAY(Ventas[[#This Row],[FECHA]]) -> 25 | E42: =+TEXT(C42,"dddd") -> miércoles | F42: Día hábil | G42: 1 | H42: Yusmeidy | I42: 4 | J42: Sopa | K42: 1 | L42: 5000 | M42: =+Ventas[[#This Row],[Precio item]]*Ventas[[#This Row],[Q]] -> 5000
C43: 43733 | D43: =+DAY(Ventas[[#This Row],[FECHA]]) -> 25 | E43: =+TEXT(C43,"dddd") -> miércoles | F43: Día hábil | G43: 1 | H43: Yusmeidy | I43: 5 | J43: Picada | K43: 1 | L43: 20000 | M43: =+Ventas[[#This Row],[Precio item]]*Ventas[[#This Row],[Q]] -> 20000
C44: 43733 | D44: =+DAY(Ventas[[#This Row],[FECHA]]) -> 25 | E44: =+TEXT(C44,"dddd") -> miércoles | F44: Día hábil | G44: 1 | H44: Yusmeidy | I44: 5 | J44: Sopa | K44: 2 | L44: 4000 | M44: =+Ventas[[#This Row],[Precio item]]*Ventas[[#This Row],[Q]] -> 8000
C45: 43733 | D45: =+DAY(Ventas[[#This Row],[FECHA]]) -> 25 | E45: =+TEXT(C45,"dddd") -> miércoles | F45: Día hábil | G45: 1 | H45: Yusmeidy | I45: 5 | J45: Jugo Hit | K45: 2 | L45: 2000 | M45: =+Ventas[[#This Row],[Precio item]]*Ventas[[#This Row],[Q]] -> 4000
C46: 43733 | D46: =+DAY(Ventas[[#This Row],[FECHA]]) -> 25 | E46: =+TEXT(C46,"dddd") -> miércoles | F46: Día hábil | G46: 1 | H46: Yusmeidy | I46: 6 | J46: Media carne | K46: 1 | L46: 15000 | M46: =+Ventas[[#This Row],[Precio item]]*Ventas[[#This Row],[Q]] -> 15000
C47: 43733 | D47: =+DAY(Ventas[[#This Row],[FECHA]]) -> 25 | E47: =+TEXT(C47,"dddd") -> miércoles | F47: Día hábil | G47: 1 | H47: Yusmeidy | I47: 6 | J47: Gaseosa 350 | K47: 1 | L47: 2000 | M47: =+Ventas[[#This Row],[Precio item]]*Ventas[[#This Row],[Q]] -> 2000
C48: 43733 | D48: =+DAY(Ventas[[#This Row],[FECHA]]) -> 25 | E48: =+TEXT(C48,"dddd") -> miércoles | F48: Día hábil | G48: 1 | H48: Yusmeidy | I48: 7 | J48: Picada | K48: 1 | L48: 80000 | M48: =+Ventas[[#This Row],[Precio item]]*Ventas[[#This Row],[Q]] -> 80000
C49: 43733 | D49: =+DAY(Ventas[[#This Row],[FECHA]]) -> 25 | E49: =+TEXT(C49,"dddd") -> miércoles | F49: Día hábil | G49: 1 | H49: Yusmeidy | I49: 7 | J49: Bagre | K49: 1 | L49: 25000 | M49: =+Ventas[[#This Row],[Precio item]]*Ventas[[#This Row],[Q]] -> 25000
C50: 43733 | D50: =+DAY(Ventas[[#This Row],[FECHA]]) -> 25 | E50: =+TEXT(C50,"dddd") -> miércoles | F50: Día hábil | G50: 1 | H50: Yusmeidy | I50: 7 | J50: Sopa | K50: 1 | L50: 5000 | M50: =+Ventas[[#This Row],[Precio item]]*Ventas[[#This Row],[Q]] -> 5000
C51: 43733 | D51: =+DAY(Ventas[[#This Row],[FECHA]]) -> 25 | E51: =+TEXT(C51,"dddd") -> miércoles | F51: Día hábil | G51: 1 | H51: Yusmeidy | I51: 7 | J51: Jugo Hit | K51: 1 | L51: 2000 | M51: =+Ventas[[#This Row],[Precio item]]*Ventas[[#This Row],[Q]] -> 2000
... C54: 43733 | D54: =+DAY(Ventas[[#This Row],[FECHA]]) -> 25 | E54: =+TEXT(C54,"dddd") -> miércoles | F54: Día hábil | G54: 1 | H54: Yusmeidy | I54: 9 | J54: Carne llanera | K54: 1 | L54: 25000 | M54: =+Ventas[[#This Row],[Precio item]]*Ventas[[#This Row],[Q]] -> 25000
C55: 43733 | D55: =+DAY(Ventas[[#This Row],[FECHA]]) -> 25 | E55: =+TEXT(C55,"dddd") -> miércoles | F55: Día hábil | G55: 1 | H55: Yusmeidy | I55: 9 | J55: Ejecutivo | K55: 1 | L55: 8000 | M55: =+Ventas[[#This Row],[Precio item]]*Ventas[[#This Row],[Q]] -> 8000 | N55: a 8?
C56: 43733 | D56: =+DAY(Ventas[[#This Row],[FECHA]]) -> 25 | E56: =+TEXT(C56,"dddd") -> miércoles | F56: Día hábil | G56: 1 | H56: Yusmeidy | I56: 10 | J56: Ejecutivo | K56: 3 | L56: 10000 | M56: =+Ventas[[#This Row],[Precio item]]*Ventas[[#This Row],[Q]] -> 30000
C57: 43733 | D57: =+DAY(Ventas[[#This Row],[FECHA]]) -> 25 | E57: =+TEXT(C57,"dddd") -> miércoles | F57: Día hábil | G57: 1 | H57: Yusmeidy | I57: 11 | J57: Carne llanera | K57: 1 | L57: 24000 | M57: =+Ventas[[#This Row],[Precio item]]*Ventas[[#This Row],[Q]] -> 24000
C58: 43733 | D58: =+DAY(Ventas[[#This Row],[FECHA]]) -> 25 | E58: =+TEXT(C58,"dddd") -> miércoles | F58: Día hábil | G58: 1 | H58: Yusmeidy | I58: 11 | J58: Gaseosa | K58: 1 | L58: 2000 | M58: =+Ventas[[#This Row],[Precio item]]*Ventas[[#This Row],[Q]] -> 2000
C59: 43733 | D59: =+DAY(Ventas[[#This Row],[FECHA]]) -> 25 | E59: =+TEXT(C59,"dddd") -> miércoles | F59: Día hábil | G59: 1 | H59: Yusmeidy | I59: 12 | J59: Ejecutivo | K59: 4 | L59: 10000 | M59: =+Ventas[[#This Row],[Precio item]]*Ventas[[#This Row],[Q]] -> 40000
C60: 43733 | D60: =+DAY(Ventas[[#This Row],[FECHA]]) -> 25 | E60: =+TEXT(C60,"dddd") -> miércoles | F60: Día hábil | G60: 1 | H60: Yusmeidy | I60: 13 | J60: Media carne | K60: 1 | L60: 15000 | M60: =+Ventas[[#This Row],[Precio item]]*Ventas[[#This Row],[Q]] -> 15000
C61: 43733 | D61: =+DAY(Ventas[[#This Row],[FECHA]]) -> 25 | E61: =+TEXT(C61,"dddd") -> miércoles | F61: Día hábil | G61: 1 | H61: Yusmeidy | I61: 14 | J61: Ejecutivo | K61: 1 | L61: 10000 | M61: =+Ventas[[#This Row],[Precio item]]*Ventas[[#This Row],[Q]] -> 10000
C62: 43733 | D62: =+DAY(Ventas[[#This Row],[FECHA]]) -> 25 | E62: =+TEXT(C62,"dddd") -> miércoles | F62: Día hábil | G62: 1 | H62: Yusmeidy | I62: 15 | J62: Ejecutivo | K62: 1 | L62: 10000 | M62: =+Ventas[[#This Row],[Precio item]]*Ventas[[#This Row],[Q]] -> 10000
C63: 43733 | D63: =+DAY(Ventas[[#This Row],[FECHA]]) -> 25 | E63: =+TEXT(C63,"dddd") -> miércoles | F63: Día hábil | G63: 1 | H63: Yusmeidy | I63: 16 | J63: Huevos con arroz | K63: 1 | L63: 4500 | M63: =+Ventas[[#This Row],[Precio item]]*Ventas[[#This Row],[Q]] -> 4500
C64: 43733 | D64: =+DAY(Ventas[[#This Row],[FECHA]]) -> 25 | E64: =+TEXT(C64,"dddd") -> miércoles | F64: Día hábil | G64: 1 | H64: Yusmeidy | I64: 17 | J64: Sopa | K64: 1 | L64: 6000 | M64: =+Ventas[[#This Row],[Precio item]]*Ventas[[#This Row],[Q]] -> 6000
B65: Redacción del contrato - Definir frecuencia de pago empleados - Se llega a la conclusión de que la hora pico de ventas es poco después del medio día - En la mañana y tardes no es frecuente de la venta ¿Por qué los clientes irian de en la tarde, noche | C65: 43734 | D65: =+DAY(Ventas[[#This Row],[FECHA]]) -> 26 | E65: =+TEXT(C65,"dddd") -> jueves | F65: Día hábil | G65: 1 | H65: Yusmeidy | I65: 1 | J65: Carne llanera | K65: 1 | L65: 25000 | M65: =+Ventas[[#This Row],[Precio item]]*Ventas[[#This Row],[Q]] -> 25000
C66: 43734 | D66: =+DAY(Ventas[[#This Row],[FECHA]]) -> 26 | E66: =+TEXT(C66,"dddd") -> jueves | F66: Día hábil | G66: 1 | H66: Yusmeidy | I66: 1 | J66: Gaseosa 350 | K66: 1 | L66: 2000 | M66: =+Ventas[[#This Row],[Precio item]]*Ventas[[#This Row],[Q]] -> 2000
C67: 43734 | D67: =+DAY(Ventas[[#This Row],[FECHA]]) -> 26 | E67: =+TEXT(C67,"dddd") -> jueves | F67: Día hábil | G67: 1 | H67: Yusmeidy | I67: 2 | J67: Ejecutivo | K67: 2 | L67: 10000 | M67: =+Ventas[[#This Row],[Precio item]]*Ventas[[#This Row],[Q]] -> 20000
C68: 43734 | D68: =+DAY(Ventas[[#This Row],[FECHA]]) -> 26 | E68: =+TEXT(C68,"dddd") -> jueves | F68: Día hábil | G68: 1 | H68: Yusmeidy | I68: 3 | J68: Ejecutivo | K68: 8 | L68: 9000 | M68: =+Ventas[[#This Row],[Precio item]]*Ventas[[#This Row],[Q]] -> 72000
C69: 43734 | D69: =+DAY(Ventas[[#This Row],[FECHA]]) -> 26 | E69: =+TEXT(C69,"dddd") -> jueves | F69: Día hábil | G69: 1 | H69: Yusmeidy | I69: 3 | J69: Sopa | K69: 2 | L69: 4000 | M69: =+Ventas[[#This Row],[Precio item]]*Ventas[[#This Row],[Q]] -> 8000
C70: 43734 | D70: =+DAY(Ventas[[#This Row],[FECHA]]) -> 26 | E70: =+TEXT(C70,"dddd") -> jueves | F70: Día hábil | G70: 1 | H70: Yusmeidy | I70: 4 | J70: Ejecutivo | K70: 2 | L70: 10000 | M70: =+Ventas[[#This Row],[Precio item]]*Ventas[[#This Row],[Q]] -> 20000
C71: 43734 | D71: =+DAY(Ventas[[#This Row],[FECHA]]) -> 26 | E71: =+TEXT(C71,"dddd") -> jueves | F71: Día hábil | G71: 1 | H71: Yusmeidy | I71: 5 | J71: Picada | K71: 1 | L71: 20000 | M71: =+Ventas[[#This Row],[Precio item]]*Ventas[[#This Row],[Q]] -> 20000
C72: 43734 | D72: =+DAY(Ventas[[#This Row],[FECHA]]) -> 26 | E72: =+TEXT(C72,"dddd") -> jueves | F72: Día hábil | G72: 1 | H72: Yusmeidy | I72: 5 | J72: Cerbeza | K72: 1 | L72: 3000 | M72: =+Ventas[[#This Row],[Precio item]]*Ventas[[#This Row],[Q]] -> 3000
C73: 43734 | D73: =+DAY(Ventas[[#This Row],[FECHA]]) -> 26 | E73: =+TEXT(C73,"dddd") -> jueves | F73: Día hábil | G73: 1 | H73: Yusmeidy | I73: 6 | J73: Ejecutivo | K73: 1 | L73: 10000 | M73: =+Ventas[[#This Row],[Precio item]]*Ventas[[#This Row],[Q]] -> 10000
C74: 43734 | D74: =+DAY(Ventas[[#This Row],[FECHA]]) -> 26 | E74: =+TEXT(C74,"dddd") -> jueves | F74: Día hábil | G74: 1 | H74: Yusmeidy | I74: 6 | J74: Cerbeza | K74: 1 | L74: 3000 | M74: =+Ventas[[#This Row],[Precio item]]*Ventas[[#This Row],[Q]] -> 3000
C75: 43734 | D75: =+DAY(Ventas[[#This Row],[FECHA]]) -> 26 | E75: =+TEXT(C75,"dddd") -> jueves | F75: Día hábil | G75: 1 | H75: Yusmeidy | I75: 7 | J75: Picada con Refajo | K75: 1 | L75: 70000 | M75: =+Ventas[[#This Row],[Precio item]]*Ventas[[#This Row],[Q]] -> 70000
C76: 43734 | D76: =+DAY(Ventas[[#This Row],[FECHA]]) -> 26 | E76: =+TEXT(C76,"dddd") -> jueves | F76: Día hábil | G76: 1 | H76: Yusmeidy | I76: 8 | J76: Media carne | K76: 1 | L76: 15000 | M76: =+Ventas[[#This Row],[Precio item]]*Ventas[[#This Row],[Q]] -> 15000
C77: 43734 | D77: =+DAY(Ventas[[#This Row],[FECHA]]) -> 26 | E77: =+TEXT(C77,"dddd") -> jueves | F77: Día hábil | G77: 1 | H77: Yusmeidy | I77: 8 | J77: gaseosa | K77: 1 | L77: 2000 | M77: =+Ventas[[#This Row],[Precio item]]*Ventas[[#This Row],[Q]] -> 2000
C78: 43734 | D78: =+DAY(Ventas[[#This Row],[FECHA]]) -> 26 | E78: =+TEXT(C78,"dddd") -> jueves | F78: Día hábil | G78: 1 | H78: Yusmeidy | I78: 9 | J78: Media carne | K78: 1 | L78: 12000 | M78: =+Ventas[[#This Row],[Precio item]]*Ventas[[#This Row],[Q]] -> 12000 | N78: El señor José lo dejo en $ 12.000
C79: 43734 | D79: =+DAY(Ventas[[#This Row],[FECHA]]) -> 26 | E79: =+TEXT(C79,"dddd") -> jueves | F79: Día hábil | G79: 1 | H79: Yusmeidy | I79: 10 | J79: Carne llanera | K79: 1 | L79: 25000 | M79: =+Ventas[[#This Row],[Precio item]]*Ventas[[#This Row],[Q]] -> 25000
C80: 43734 | D80: =+DAY(Ventas[[#This Row],[FECHA]]) -> 26 | E80: =+TEXT(C80,"dddd") -> jueves | F80: Día hábil | G80: 1 | H80: Yusmeidy | I80: 10 | J80: Jugo Hit | K80: 1 | L80: 2000 | M80: =+Ventas[[#This Row],[Precio item]]*Ventas[[#This Row],[Q]] -> 2000
C81: 43734 | D81: =+DAY(Ventas[[#This Row],[FECHA]]) -> 26 | E81: =+TEXT(C81,"dddd") -> jueves | F81: Día hábil | G81: 1 | H81: Yusmeidy | I81: 10 | J81: Sopa | K81: 1 | L81: 6000 | M81: =+Ventas[[#This Row],[Precio item]]*Ventas[[#This Row],[Q]] -> 6000
B82: Reunión: Temas a tratar - Pago - Frecuencia de inventario | C82: 43735 | D82: =+DAY(Ventas[[#This Row],[FECHA]]) -> 27 | E82: =+TEXT(C82,"dddd") -> viernes | F82: Fds y Festivo | G82: 1 | H82: Yusmeidy | I82: 1 | J82: Combo Hamburguesa | K82: 2 | L82: 12500 | M82: =+Ventas[[#This Row],[Precio item]]*Ventas[[#This Row],[Q]] -> 25000
C83: 43735 | D83: =+DAY(Ventas[[#This Row],[FECHA]]) -> 27 | E83: =+TEXT(C83,"dddd") -> viernes | F83: Fds y Festivo | G83: 1 | H83: Yusmeidy | I83: 2 | J83: Medias carnes | K83: 2 | L83: 15000 | M83: =+Ventas[[#This Row],[Precio item]]*Ventas[[#This Row],[Q]] -> 30000
C84: 43735 | D84: =+DAY(Ventas[[#This Row],[FECHA]]) -> 27 | E84: =+TEXT(C84,"dddd") -> viernes | F84: Fds y Festivo | G84: 1 | H84: Yusmeidy | I84: 2 | J84: Cerbeza | K84: 2 | L84: 3500 | M84: =+Ventas[[#This Row],[Precio item]]*Ventas[[#This Row],[Q]] -> 7000
C85: 43735 | D85: =+DAY(Ventas[[#This Row],[FECHA]]) -> 27 | E85: =+TEXT(C85,"dddd") -> viernes | F85: Fds y Festivo | G85: 1 | H85: Yusmeidy | I85: 3 | J85: Sopa | K85: 1 | L85: 5000 | M85: =+Ventas[[#This Row],[Precio item]]*Ventas[[#This Row],[Q]] -> 5000
C86: 43735 | D86: =+DAY(Ventas[[#This Row],[FECHA]]) -> 27 | E86: =+TEXT(C86,"dddd") -> viernes | F86: Fds y Festivo | G86: 1 | H86: Yusmeidy | I86: 4 | J86: Ejecutivo | K86: 3 | L86: 10000 | M86: =+Ventas[[#This Row],[Precio item]]*Ventas[[#This Row],[Q]] -> 30000
C87: 43735 | D87: =+DAY(Ventas[[#This Row],[FECHA]]) -> 27 | E87: =+TEXT(C87,"dddd") -> viernes | F87: Fds y Festivo | G87: 1 | H87: Yusmeidy | I87: 4 | J87: Gaseosa 350 Coca Cola | K87: 2 | L87: 2500 | M87: =+Ventas[[#This Row],[Precio item]]*Ventas[[#This Row],[Q]] -> 5000
C88: 43735 | D88: =+DAY(Ventas[[#This Row],[FECHA]]) -> 27 | E88: =+TEXT(C88,"dddd") -> viernes | F88: Fds y Festivo | G88: 1 | H88: Yusmeidy | I88: 5 | J88: Ejecutivo | K88: 3 | L88: 10000 | M88: =+Ventas[[#This Row],[Precio item]]*Ventas[[#This Row],[Q]] -> 30000
C89: 43735 | D89: =+DAY(Ventas[[#This Row],[FECHA]]) -> 27 | E89: =+TEXT(C89,"dddd") -> viernes | F89: Fds y Festivo | G89: 1 | H89: Yusmeidy | I89: 6 | J89: Ejecutivo | K89: 1 | L89: 10000 | M89: =+Ventas[[#This Row],[Precio item]]*Ventas[[#This Row],[Q]] -> 10000
C90: 43735 | D90: =+DAY(Ventas[[#This Row],[FECHA]]) -> 27 | E90: =+TEXT(C90,"dddd") -> viernes | F90: Fds y Festivo | G90: 1 | H90: Yusmeidy | I90: 7 | J90: Ejecutivo | K90: 3 | L90: 10000 | M90: =+Ventas[[#This Row],[Precio item]]*Ventas[[#This Row],[Q]] -> 30000
C91: 43735 | D91: =+DAY(Ventas[[#This Row],[FECHA]]) -> 27 | E91: =+TEXT(C91,"dddd") -> viernes | F91: Fds y Festivo | G91: 1 | H91: Yusmeidy | I91: 8 | J91: Ejecutivo | K91: 1 | L91: 10000 | M91: =+Ventas[[#This Row],[Precio item]]*Ventas[[#This Row],[Q]] -> 10000
C92: 43735 | D92: =+DAY(Ventas[[#This Row],[FECHA]]) -> 27 | E92: =+TEXT(C92,"dddd") -> viernes | F92: Fds y Festivo | G92: 1 | H92: Yusmeidy | I92: 9 | J92: Picada | K92: 1 | L92: 45000 | M92: =+Ventas[[#This Row],[Precio item]]*Ventas[[#This Row],[Q]] -> 45000
C93: 43735 | D93: =+DAY(Ventas[[#This Row],[FECHA]]) -> 27 | E93: =+TEXT(C93,"dddd") -> viernes | F93: Fds y Festivo | G93: 1 | H93: Yusmeidy | I93: 9 | J93: Cerbeza | K93: 3 | L93: 3000 | M93: =+Ventas[[#This Row],[Precio item]]*Ventas[[#This Row],[Q]] -> 9000
C94: 43735 | D94: =+DAY(Ventas[[#This Row],[FECHA]]) -> 27 | E94: =+TEXT(C94,"dddd") -> viernes | F94: Fds y Festivo | G94: 1 | H94: Yusmeidy | I94: 9 | J94: Gaseosa | K94: 1 | L94: 2000 | M94: =+Ventas[[#This Row],[Precio item]]*Ventas[[#This Row],[Q]] -> 2000
... C101: 43735 | D101: =+DAY(Ventas[[#This Row],[FECHA]]) -> 27 | E101: =+TEXT(C101,"dddd") -> viernes | F101: Fds y Festivo | G101: 1 | H101: Yusmeidy | I101: 15 | J101: Sopa | K101: 2 | L101: 4000 | M101: =+Ventas[[#This Row],[Precio item]]*Ventas[[#This Row],[Q]] -> 8000
B102: Inducción de los dos meseros Carta Menú- Los Tunos Parrilla Promocionando la hamburguesa artesanal | C102: 43736 | D102: 28 | E102: =+TEXT(C102,"dddd") -> sábado | F102: Fds y Festivo | G102: 1 | H102: Stefania | I102: 1 | J102: Picada | K102: 1 | L102: 30000 | M102: =+Ventas[[#This Row],[Precio item]]*Ventas[[#This Row],[Q]] -> 30000
C103: 43736 | D103: 28 | E103: =+TEXT(C103,"dddd") -> sábado | F103: Fds y Festivo | G103: 1 | H103: Stefania | I103: 1 | J103: Andina | K103: 3 | L103: 3000 | M103: =+Ventas[[#This Row],[Precio item]]*Ventas[[#This Row],[Q]] -> 9000
C104: 43736 | D104: 28 | E104: =+TEXT(C104,"dddd") -> sábado | F104: Fds y Festivo | G104: 1 | H104: Julían | I104: 2 | J104: hamburguesa | K104: 1 | L104: 8000 | M104: =+Ventas[[#This Row],[Precio item]]*Ventas[[#This Row],[Q]] -> 8000
C105: 43736 | D105: 28 | E105: =+TEXT(C105,"dddd") -> sábado | F105: Fds y Festivo | G105: 1 | H105: Julían | I105: 2 | J105: Arroz chino estandar | K105: 1 | L105: 12000 | M105: =+Ventas[[#This Row],[Precio item]]*Ventas[[#This Row],[Q]] -> 12000 | N105: un pésimo arroz chino causado por el desorden de la cocina
C106: 43736 | D106: 28 | E106: =+TEXT(C106,"dddd") -> sábado | F106: Fds y Festivo | G106: 1 | H106: Julían | I106: 2 | J106: Gaseosa 350 | K106: 1 | L106: 2000 | M106: =+Ventas[[#This Row],[Precio item]]*Ventas[[#This Row],[Q]] -> 2000
C107: 43736 | D107: 28 | E107: =+TEXT(C107,"dddd") -> sábado | F107: Fds y Festivo | G107: 1 | H107: Stefania | I107: 3 | J107: Gasoesa 350 Coca cola | K107: 1 | L107: 2500 | M107: =+Ventas[[#This Row],[Precio item]]*Ventas[[#This Row],[Q]] -> 2500
C108: 43736 | D108: 28 | E108: =+TEXT(C108,"dddd") -> sábado | F108: Fds y Festivo | G108: 1 | H108: Stefania | I108: 3 | J108: Sopa | K108: 1 | L108: 6000 | M108: =+Ventas[[#This Row],[Precio item]]*Ventas[[#This Row],[Q]] -> 6000 | N108: Mazamorra
C109: 43736 | D109: 28 | E109: =+TEXT(C109,"dddd") -> sábado | F109: Fds y Festivo | G109: 1 | H109: Stefania | I109: 3 | J109: Picada | K109: 1 | L109: 10000 | M109: =+Ventas[[#This Row],[Precio item]]*Ventas[[#This Row],[Q]] -> 10000
C110: 43736 | D110: 28 | E110: =+TEXT(C110,"dddd") -> sábado | F110: Fds y Festivo | G110: 1 | H110: Julían | I110: 4 | J110: Sopa | K110: 2 | L110: 3000 | M110: =+Ventas[[#This Row],[Precio item]]*Ventas[[#This Row],[Q]] -> 6000 | N110: Changua
C111: 43736 | D111: 28 | E111: =+TEXT(C111,"dddd") -> sábado | F111: Fds y Festivo | G111: 1 | H111: Julían | I111: 4 | J111: Tinto | K111: 2 | L111: 1000 | M111: =+Ventas[[#This Row],[Precio item]]*Ventas[[#This Row],[Q]] -> 2000
...

Sheet Clientes institucionales
C6: 900551266 CONSORCIO CCC ITUANGO

Sheet Revenue Forecasting
D1: Nombre cliente | E1: Turistas | K1: Turistas | L1: Domicilios
D2: Producto | E2: (Todas) | K2: Clientes de la zona | L2: Eventos
D4: Suma de Ventas | E4: Mes
D5: Día | E5: dic | F5: nov | G5: oct | H5: sep | AB5: Nov | AC5: oct | AD5: sep
D6: 1 | E6: 1500000 | F6: 370000 | G6: 229800 | AB6: Sin hist | AC6: NO REALIZADO
D7: 2 | E7: 250000 | F7: 500000 | G7: 238000 | AB7: Sin hist | AC7: NO REALIZADO
D8: 3 | E8: 120000 | F8: 1700000 | G8: 238000 | AB8: Sin hist | AC8: NO REALIZADO
D9: 4 | E9: 180000 | F9: 600000 | G9: 420500 | AB9: Sin hist | AC9: NO REALIZADO
D10: 5 | E10: 250000 | F10: 194000 | G10: 1210300 | AB10: Sin hist | AC10: NO REALIZADO
D11: 6 | E11: 220000 | F11: 627000 | G11: 1345600 | AB11: Sin hist | AC11: NO REALIZADO
D12: 7 | E12: 900000 | F12: 332500 | G12: 603500 | AC12: NO REALIZADO
D13: 8 | E13: 1200000 | F13: 342000 | G13: 426300 | AC13: NO REALIZADO
D14: 9 | E14: 140000 | F14: 1552000 | G14: 134000 | AC14: NO REALIZADO
D15: 10 | E15: 0 | F15: 1690000 | G15: 85500 | AC15: NO REALIZADO
D16: 11 | E16: 220000 | F16: 700000 | G16: 427900 | AC16: NO REALIZADO
D17: 12 | E17: 400000 | F17: 122000 | G17: 664500 | AC17: NO REALIZADO
D18: 13 | E18: 350000 | F18: 165000 | G18: 1283500 | AC18: NO REALIZADO
D19: 14 | E19: 900000 | F19: 61000 | G19: 622000 | AC19: completo
D20: 15 | E20: 800000 | F20: 235000 | G20: 227000 | AC20: completo
D21: 16 | E21: 207200 | F21: 811500 | G21: 385300 | AC21: completo
D22: 17 | E22: 157500 | F22: 1300900 | G22: 250800 | AC22: completo
D23: 18 | E23: 220000 | F23: 350000 | G23: 363500 | AC23: completo
... D26: 21 | E26: 450000 | F26: 216500 | G26: 350000 | AC26: Sin hist
D27: 22 | E27: 638500 | F27: 186000 | G27: 380000 | H27: 572000 | AC27: Sin hist | AD27: Sin hist
D28: 23 | E28: 308500 | F28: 587500 | G28: 550000 | H28: 142000 | AC28: Sin hist | AD28: completo
D29: 24 | E29: 604000 | F29: 960000 | G29: 380000 | H29: 393000 | AC29: Sin hist | AD29: completo
D30: 25 | E30: 589500 | F30: 500000 | G30: 1200000 | H30: 419500 | AC30: Sin hist | AD30: completo
D31: 26 | E31: 120500 | F31: 400000 | G31: 655000 | H31: 315000 | AC31: Sin hist | AD31: completo
D32: 27 | E32: 82500 | F32: 210000 | G32: 1200000 | H32: 421000 | AC32: Sin hist | AD32: completo
D33: 28 | E33: 824000 | F33: 200000 | G33: 300000 | H33: 951500 | AC33: Sin hist | AD33: completo
D34: 29 | E34: 720000 | F34: 400000 | G34: 220000 | H34: 658000 | AC34: Sin hist | AD34: completo
D35: 30 | E35: 149500 | F35: 900000 | G35: 320000 | H35: 183210 | AC35: Sin hist | AD35: NO REALIZADO
D36: 31 | E36: 448500 | G36: 370000
D37: Total general | E37: 13745700 | F37: 16752900 | G37: 17351500 | H37: 4055210 | AC37: 11855040 | AD37: 4055210
D38: =+D6 -> 1 | E38: =+E6 -> 1500000 | F38: =+F6 -> 370000 | G38: =+G6 -> 229800 | H38: =+H6 -> 0
D39: =+D7 -> 2 | E39: =+E7 -> 250000 | F39: =+F7 -> 500000 | G39: =+G7 -> 238000 | H39: =+H7 -> 0 | K39: =+E5 -> dic | L39: D | M39: D% | N39: =+F5 -> nov | O39: D | P39: D% | Q39: =+G5 -> oct | R39: D | S39: D% | T39: =+H5 -> sep | V39: ¿Qué afecta las ventas?
D40: =+D8 -> 3 | E40: =+E8 -> 120000 | F40: =+F8 -> 1700000 | G40: =+G8 -> 238000 | H40: =+H8 -> 0 | K40: =+AVERAGE(E39:E42) -> 200000 | L40: =+K40-N40 -> -79857.143 | M40: =+K40/N40-1 -> -0.28534967 | N40: =+AVERAGE(F42:F44,F49:F51,F55:F58,F62:F65) -> 279857.14 | O40: =+N40-Q40 -> -36153.968 | P40: =+N40/Q40-1 -> -0.11440727 | Q40: =+AVERAGE(G38:G40,G44:G47,G52:G54,G58:G61,G65:G68) -> 316011.11 | R40: =+Q40-T40 -> 25469.111 | S40: =+Q40/T40-1 -> 0.087660686 | T40: =+AVERAGE(H60:H63,H67) -> 290542 | V40: el humo
D41: =+D9 -> 4 | E41: =+E9 -> 180000 | F41: =+F9 -> 600000 | G41: =+G9 -> 420500 | H41: =+H9 -> 0 | K41: =+AVERAGE(E43) -> 220000 | L41: =+K41-N41 -> -86600 | M41: =+K41/N41-1 -> -0.28245271 | N41: =+AVERAGE(F38,F45,F52,F59,F66) -> 306600 | O41: =+N41-Q41 -> -296375 | P41: =+N41/Q41-1 -> -0.49152121 | Q41: =+AVERAGE(G41,G48,G55,G62) -> 602975 | R41: =+Q41-T41 -> 181975 | S41: =+Q41/T41-1 -> 0.43224466 | T41: =+H64 -> 421000 | V41: factura electronica
D42: =+D10 -> 5 | E42: =+E10 -> 250000 | F42: =+F10 -> 194000 | G42: =+G10 -> 1210300 | H42: =+H10 -> 0 | K42: =+AVERAGE(E44) -> 900000 | L42: =+K42-N42 -> 29800 | M42: =+K42/N42-1 -> 0.034245001 | N42: =+AVERAGE(F39,F46,F53,F60,F67) -> 870200 | O42: =+N42-Q42 -> 57750 | P42: =+N42/Q42-1 -> 0.071081297 | Q42: =+AVERAGE(G42,G49,G56,G63) -> 812450 | R42: =+Q42-T42 -> -139050 | S42: =+Q42/T42-1 -> -0.14613768 | T42: =+H65 -> 951500 | V42: vandedero
D43: =+D11 -> 6 | E43: =+E11 -> 220000 | F43: =+F11 -> 627000 | G43: =+G11 -> 1345600 | H43: =+H11 -> 0 | K43: =+AVERAGE(E45) -> 1200000 | L43: =+K43-N43 -> -212725 | M43: =+K43/N43-1 -> -0.15057778 | N43: =+AVERAGE(F40,F47,F54,F61) -> 1412725 | O43: =+N43-Q43 -> 67825 | P43: =+N43/Q43-1 -> 0.050431259 | Q43: =+AVERAGE(G43,G50,G57,G64) -> 1344900 | R43: =+Q43-T43 -> 729900 | S43: =+Q43/T43-1 -> 1.1868293 | T43: =+AVERAGE(H59,H66) -> 615000 | V43: aviso publicidad
D44: =+D12 -> 7 | E44: =+E12 -> 900000 | F44: =+F12 -> 332500 | G44: =+G12 -> 603500 | H44: =+H12 -> 0 | K44: =+AVERAGE(F41,F48) -> 650000 | L44: =+K44-N44 -> 0 | M44: =+K44/N44-1 -> 0 | N44: =+AVERAGE(F41,F48) -> 650000 | O44: =+N44-Q44 -> 28000 | P44: =+N44/Q44-1 -> 0.045016077 | Q44: =+G51 -> 622000
D45: =+D13 -> 8 | E45: =+E13 -> 1200000 | F45: =+F13 -> 342000 | G45: =+G13 -> 426300 | H45: =+H13 -> 0
D46: =+D14 -> 9 | E46: =+E14 -> 140000 | F46: =+F14 -> 1552000 | G46: =+G14 -> 134000 | H46: =+H14 -> 0
D47: =+D15 -> 10 | E47: =+E15 -> 0 | F47: =+F15 -> 1690000 | G47: =+G15 -> 85500 | H47: =+H15 -> 0 | J47: FDS | K47: =+SUM(K41:K43) -> 2320000 | L47: =+K47-N47 -> -269525 | M47: =+K47/N47-1 -> -0.1040828 | N47: =+SUM(N41:N43) -> 2589525 | O47: =+N47-Q47 -> -170800 | P47: =+N47/Q47-1 -> -0.061876772 | Q47: =+SUM(Q41:Q43) -> 2760325 | R47: =+Q47-T47 -> 772825 | S47: =+Q47/T47-1 -> 0.38884277 | T47: =+SUM(T41:T43) -> 1987500
D48: =+D16 -> 11 | E48: =+E16 -> 220000 | F48: =+F16 -> 700000 | G48: =+G16 -> 427900 | H48: =+H16 -> 0
D49: =+D17 -> 12 | E49: =+E17 -> 400000 | F49: =+F17 -> 122000 | G49: =+G17 -> 664500 | H49: =+H17 -> 0
D50: =+D18 -> 13 | E50: =+E18 -> 350000 | F50: =+F18 -> 165000 | G50: =+G18 -> 1283500 | H50: =+H18 -> 0
D51: =+D19 -> 14 | E51: =+E19 -> 900000 | F51: =+F19 -> 61000 | G51: =+G19 -> 622000 | H51: =+H19 -> 0
D52: =+D20 -> 15 | E52: =+E20 -> 800000 | F52: =+F20 -> 235000 | G52: =+G20 -> 227000 | H52: =+H20 -> 0
A53: 0 | D53: =+D21 -> 16 | E53: =+E21 -> 207200 | F53: =+F21 -> 811500 | G53: =+G21 -> 385300 | H53: =+H21 -> 0
A54: 0 | D54: =+D22 -> 17 | E54: =+E22 -> 157500 | F54: =+F22 -> 1300900 | G54: =+G22 -> 250800 | H54: =+H22 -> 0
A55: 0 | D55: =+D23 -> 18 | E55: =+E23 -> 220000 | F55: =+F23 -> 350000 | G55: =+G23 -> 363500 | H55: =+H23 -> 0 | K55: 332000
A56: 0 | D56: =+D24 -> 19 | E56: =+E24 -> 445500 | F56: =+F24 -> 220000 | G56: =+G24 -> 720000 | H56: =+H24 -> 0
A57: 0 | D57: =+D25 -> 20 | E57: =+E25 -> 350000 | F57: =+F25 -> 320000 | G57: =+G25 -> 1550500 | H57: =+H25 -> 0
A58: 0 | D58: =+D26 -> 21 | E58: =+E26 -> 450000 | F58: =+F26 -> 216500 | G58: =+G26 -> 350000 | H58: =+H26 -> 0
A59: 0 | D59: =+D27 -> 22 | E59: =+E27 -> 638500 | F59: =+F27 -> 186000 | G59: =+G27 -> 380000 | H59: =+H27 -> 572000
A60: 0 | D60: =+D28 -> 23 | E60: =+E28 -> 308500 | F60: =+F28 -> 587500 | G60: =+G28 -> 550000 | H60: =+H28 -> 142000
A61: 0 | D61: =+D29 -> 24 | E61: =+E29 -> 604000 | F61: =+F29 -> 960000 | G61: =+G29 -> 380000 | H61: =+H29 -> 393000
A62: 0 | D62: =+D30 -> 25 | E62: =+E30 -> 589500 | F62: =+F30 -> 500000 | G62: =+G30 -> 1200000 | H62: =+H30 -> 419500
A63: 0 | D63: =+D31 -> 26 | E63: =+E31 -> 120500 | F63: =+F31 -> 400000 | G63: =+G31 -> 655000 | H63: =+H31 -> 315000
A64: 0 | D64: =+D32 -> 27 | E64: =+E32 -> 82500 | F64: =+F32 -> 210000 | G64: =+G32 -> 1200000 | H64: =+H32 -> 421000
A65: 0 | D65: =+D33 -> 28 | E65: =+E33 -> 824000 | F65: =+F33 -> 200000 | G65: =+G33 -> 300000 | H65: =+H33 -> 951500
A66: 0 | D66: =+D34 -> 29 | E66: =+E34 -> 720000 | F66: =+F34 -> 400000 | G66: =+G34 -> 220000 | H66: =+H34 -> 658000
A67: 0 | D67: =+D35 -> 30 | E67: =+E35 -> 149500 | F67: =+F35 -> 900000 | G67: =+G35 -> 320000 | H67: =+H35 -> 183210
D68: =+D36 -> 31 | E68: =+E36 -> 448500 | G68: =+G36 -> 370000
D70: Acumulado | E70: =+E37 -> 13745700
D71: Estimado | E71: =+SUM(E38:E68) -> 13745700 | F71: =+F37 -> 16752900 | G71: =+G37 -> 17351500
E72: =+E71/F71-1 -> -0.17950325
E73: =+E71-F71 -> -3007200
D78: Producto | E78: (Todas)
D79: FECHA | E79: oct
D80: Dia | E80: 13
D82: Id Client | E82: Suma de Ventas
D83: 1 | E83: 106500
D84: 2 | E84: 31000
D85: 3 | E85: 20000
D86: 4 | E86: 30000
D87: 5 | E87: 41000
D88: 6 | E88: 50000
D89: 7 | E89: 52000
D90: 8 | E90: 69000
D91: 9 | E91: 67000
D92: 10 | E92: 70000
D93: 11 | E93: 144000
D94: 12 | E94: 70500
... D103: 21 | E103: 47000
D104: Total general | E104: 1283500

Sheet Clima
A1: FECHA | B1: Dia | C1: Dia semanal | D1: Estado clima
A2: 43730 | B2: =+DAY(A2) -> 22 | C2: =+TEXT(A2,"dddd") -> domingo
A3: =+A2+1 -> 43731 | B3: =+DAY(A3) -> 23 | C3: =+TEXT(A3,"dddd") -> lunes
A4: =+A3+1 -> 43732 | B4: =+DAY(A4) -> 24 | C4: =+TEXT(A4,"dddd") -> martes
A5: =+A4+1 -> 43733 | B5: =+DAY(A5) -> 25 | C5: =+TEXT(A5,"dddd") -> miércoles
A6: =+A5+1 -> 43734 | B6: =+DAY(A6) -> 26 | C6: =+TEXT(A6,"dddd") -> jueves
A7: =+A6+1 -> 43735 | B7: =+DAY(A7) -> 27 | C7: =+TEXT(A7,"dddd") -> viernes
A8: =+A7+1 -> 43736 | B8: =+DAY(A8) -> 28 | C8: =+TEXT(A8,"dddd") -> sábado
A9: =+A8+1 -> 43737 | B9: =+DAY(A9) -> 29 | C9: =+TEXT(A9,"dddd") -> domingo
A10: =+A9+1 -> 43738 | B10: =+DAY(A10) -> 30 | C10: =+TEXT(A10,"dddd") -> lunes
A11: =+A10+1 -> 43739 | B11: =+DAY(A11) -> 1 | C11: =+TEXT(A11,"dddd") -> martes
A12: =+A11+1 -> 43740 | B12: =+DAY(A12) -> 2 | C12: =+TEXT(A12,"dddd") -> miércoles
A13: =+A12+1 -> 43741 | B13: =+DAY(A13) -> 3 | C13: =+TEXT(A13,"dddd") -> jueves
A14: =+A13+1 -> 43742 | B14: =+DAY(A14) -> 4 | C14: =+TEXT(A14,"dddd") -> viernes
... A30: =+A29+1 -> 43758 | B30: =+DAY(A30) -> 20 | C30: =+TEXT(A30,"dddd") -> domingo
A31: =+A30+1 -> 43759 | B31: =+DAY(A31) -> 21 | C31: =+TEXT(A31,"dddd") -> lunes | D31: Llovio levemente
A32: =+A31+1 -> 43760 | B32: =+DAY(A32) -> 22 | C32: =+TEXT(A32,"dddd") -> martes
A33: =+A32+1 -> 43761 | B33: =+DAY(A33) -> 23 | C33: =+TEXT(A33,"dddd") -> miércoles
A34: =+A33+1 -> 43762 | B34: =+DAY(A34) -> 24 | C34: =+TEXT(A34,"dddd") -> jueves
A35: =+A34+1 -> 43763 | B35: =+DAY(A35) -> 25 | C35: =+TEXT(A35,"dddd") -> viernes

Sheet Modelo Econométrico
F2: Y (Ventas los tunos parrilla) | G2: = | H2: aX1 | I2: X2 | J2: X3 | K2: X4
D3: Precio de mercado
K4: X5
B5: Y
B6: =
B7: X1 | C7: Precio
B8: X2 | C8: Servicio
B9: X3 | C9: Clima
B10: X4 | C10: Precios compentencia
B11: X5 | C11: Servicio compentencia
B12: x6 | C12: Instalaciones | D12: el daño de hugo

Sheet Bono Yery
D4: 43773 | E4: 4 | F4: =+TEXT(D4,"dddd") -> lunes | G4: si
D5: 43774 | E5: 5 | F5: =+TEXT(D5,"dddd") -> martes | G5: si
D6: 43775 | E6: 6 | F6: =+TEXT(D6,"dddd") -> miércoles | G6: si
D7: 43776 | E7: 7 | F7: =+TEXT(D7,"dddd") -> jueves | G7: no
D8: 43777 | E8: 16 | F8: =+TEXT(D8,"dddd") -> viernes | G8: no
D9: 43778 | E9: 17 | F9: =+TEXT(D9,"dddd") -> sábado | G9: no | H9: No hay copias de Alenis | I9: Se me quedaron
D10: 43779 | E10: 18 | F10: =+TEXT(D10,"dddd") -> domingo | G10: Si
D11: 43780 | E11: 19 | F11: =+TEXT(D11,"dddd") -> lunes
D12: 43781 | E12: 20 | F12: =+TEXT(D12,"dddd") -> martes

Sheet Revenue Forecasting (2)
D1: Nombre cliente | E1: Turistas | H1: Turistas | I1: Domicilios
D2: Producto | E2: (Todas) | H2: Clientes de la zona | I2: Eventos
D4: Día | E4: Máx. de Id. Client por dìa
D5: 1 | H5: Día | I5: oct | J5: sep
A6: Viernes (18) | D6: 2 | H6: 1 | I6: NO REALIZADO
A7: Viernes (18) | D7: 3 | H7: 2 | I7: NO REALIZADO
A8: Sabàdo 19 | D8: 4 | H8: 3 | I8: NO REALIZADO
A9: Sabàdo 19 | D9: 5 | H9: 4 | I9: NO REALIZADO
A10: Sabàdo 19 | D10: 6 | H10: 5 | I10: NO REALIZADO
A11: Domingo 20 | D11: 7 | H11: 6 | I11: NO REALIZADO
A12: Domingo 20 | D12: 8 | H12: 7 | I12: NO REALIZADO
A13: Domingo 20 | D13: 9 | H13: 8 | I13: NO REALIZADO
A14: Lunes 21 | D14: 10 | H14: 9 | I14: NO REALIZADO
A15: Lunes 21 | D15: 11 | H15: 10 | I15: NO REALIZADO
A16: Lunes 21 | D16: 12 | H16: 11 | I16: NO REALIZADO
A17: Martes 22 | D17: 13 | E17: 21 | H17: 12 | I17: NO REALIZADO
A18: Martes 22 | D18: 14 | E18: 14 | H18: 13 | I18: NO REALIZADO
A19: Martes 23 | D19: 15 | E19: 19 | H19: 14 | I19: NO REALIZADO
A20: Miercoles 24 | D20: 16 | E20: 19 | H20: 15 | I20: completo
A21: Miercoles 24 | D21: 17 | E21: 14 | H21: 16 | I21: NO REALIZADO
A22: Miercoles 24 | D22: 18 | E22: 15 | H22: 17 | I22: completo
A23: Jueves 25 | D23: 19 | H23: 18 | I23: completo
A24: Jueves 25 | C24: sab | D24: 20 | E24: 36 | H24: 19 | I24: SE QUEDO
D25: 21 | H25: 20 | I25: NO REALIZADO
D26: 22 | H26: 21 | I26: Sin hist
D27: 23 | E27: 7 | H27: 22 | J27: Sin hist
D28: 24 | E28: 14 | H28: 23 | J28: completo
D29: 25 | E29: 17 | H29: 24 | J29: completo
D30: 26 | E30: 10 | H30: 25 | J30: completo
D31: 27 | E31: 15 | H31: 26 | J31: completo
D32: 28 | E32: 29 | H32: 27 | J32: completo
D33: 29 | E33: 19 | H33: 28 | J33: completo
D34: 30 | H34: 29 | J34: completo
D35: 31 | H35: 30 | J35: NO REALIZADO
D36: Total general | E36: 36 | H36: 31
H37: Total general | I37: 11855040 | J37: 4055210
D38: =+D6 -> 2 | E38: =+E6 -> 0 | F38: =+F6 -> 0
D39: =+D7 -> 3 | E39: =+E7 -> 0 | F39: =+F7 -> 0 | H39: D | I39: D% | J39: =+E5 -> 0 | K39: =+F5 -> 0
D40: =+D8 -> 4 | E40: =+E8 -> 0 | F40: =+F8 -> 0 | H40: =+J40-K40 -> 4.3636364 | I40: =+J40/K40-1 -> #DIV/0! | J40: =+AVERAGE(E38:E40,E44:E47,E52:E54,E58) -> 4.3636364 | K40: =+AVERAGE(F60:F63) -> 0
D41: =+D9 -> 5 | E41: =+E9 -> 0 | F41: =+F9 -> 0 | H41: =+J41-K41 -> 0 | I41: =+J41/K41-1 -> #DIV/0! | J41: =+AVERAGE(E41,E48,E55) -> 0 | K41: =+F64 -> 0
D42: =+D10 -> 6 | E42: =+E10 -> 0 | F42: =+F10 -> 0 | H42: =+J42-K42 -> 19 | I42: =+J42/K42-1 -> #DIV/0! | J42: =+AVERAGE(E42,E49,E56) -> 19 | K42: =+F65 -> 0
D43: =+D11 -> 7 | E43: =+E11 -> 0 | F43: =+F11 -> 0 | H43: =+J43-K43 -> 8.25 | I43: =+J43/K43-1 -> #DIV/0! | J43: =+AVERAGE(E43,E50,E51,E57) -> 8.25 | K43: =+AVERAGE(F59,F66) -> 0
D44: =+D12 -> 8 | E44: =+E12 -> 0 | F44: =+F12 -> 0
D45: =+D13 -> 9 | E45: =+E13 -> 0 | F45: =+F13 -> 0
D46: =+D14 -> 10 | E46: =+E14 -> 0 | F46: =+F14 -> 0 | H46: Dia hábil | I46: =#REF! -> #REF! | K46: Mensual
D47: =+D15 -> 11 | E47: =+E15 -> 0 | F47: =+F15 -> 0 | H47: Dia fds | I47: =#REF! -> #REF! | K47: =#REF! -> #REF!
D48: =+D16 -> 12 | E48: =+E16 -> 0 | F48: =+F16 -> 0
D49: =+D17 -> 13 | E49: =+E17 -> 21 | F49: =+F17 -> 0
D50: =+D18 -> 14 | E50: =+E18 -> 14 | F50: =+F18 -> 0
D51: =+D19 -> 15 | E51: =+E19 -> 19 | F51: =+F19 -> 0 | K51: ¿Qué afecta las ventas?
D52: =+D20 -> 16 | E52: =+E20 -> 19 | F52: =+F20 -> 0 | K52: el humo
A53: 0 | D53: =+D21 -> 17 | E53: =+E21 -> 14 | F53: =+F21 -> 0 | K53: factura electronica
A54: 0 | D54: =+D22 -> 18 | E54: =+E22 -> 15 | F54: =+F22 -> 0 | K54: vandedero
A55: 0 | D55: =+D23 -> 19 | E55: =+E23 -> 0 | F55: =+F23 -> 0 | K55: aviso publicidad
A56: 0 | D56: =+D24 -> 20 | E56: =+E24 -> 36 | F56: =+F24 -> 0
A57: 0 | D57: =+D25 -> 21 | E57: =+E25 -> 0 | F57: =+F25 -> 0
A58: 0 | D58: =+D26 -> 22 | E58: =+E26 -> 0 | F58: =+F26 -> 0
A59: 0 | D59: =+D27 -> 23 | E59: =+$J$40 -> 4.3636364 | F59: =+F27 -> 0
A60: 0 | D60: =+D28 -> 24 | E60: =+$J$40 -> 4.3636364 | F60: =+F28 -> 0
A61: 0 | D61: =+D29 -> 25 | E61: =+$J$40 -> 4.3636364 | F61: =+F29 -> 0
A62: 0 | D62: =+D30 -> 26 | E62: =+$J$41 -> 0 | F62: =+F30 -> 0
A63: 0 | D63: =+D31 -> 27 | E63: =+$J$42 -> 19 | F63: =+F31 -> 0
A64: 0 | D64: =+D32 -> 28 | E64: =+$J$43 -> 8.25 | F64: =+F32 -> 0
A65: 0 | D65: =+D33 -> 29 | E65: =+$J$40 -> 4.3636364 | F65: =+F33 -> 0
A66: 0 | D66: =+D34 -> 30 | E66: =+$J$40 -> 4.3636364 | F66: =+F34 -> 0
A67: 0 | D67: =+D35 -> 31 | E67: =+$J$40 -> 4.3636364 | F67: =+F35 -> 0
D68: =+D36 -> Total general | E68: =+$J$40 -> 4.3636364
D70: Acumulado | E70: =+E37 -> 0 | F70: =+F37 -> 0
D72: Estimado | E72: =+SUM(E38:E68) -> 195.79545 | F72: =+F70 -> 0
E73: 23681750
E74: =+E72-E73 -> -23681554

Sheet Anàlisis de ingreso
F1: Análisis de ingresos por día semanal | W1: Noviembre
I2: Mes | V2: Nomina | W2: ='PE (2)'!K2 -> 2310000
D3: Inicio de operación | E3: Fecha actual | F3: Venta | I3: sep | J3: oct | K3: nov | L3: dic | M3: Total general | V3: Arriendo | W3: ='PE (2)'!K3 -> 2500000
D4: 43730 | E4: 43830 | F4: 51905310 | H4: Ventas | I4: 4055210 | J4: 17351500 | K4: 16752900 | L4: 13745700 | M4: 51905310 | S4: No. de semana | T4: (Todas) | V4: Financieros | W4: ='PE (2)'!K4 -> 0
S5: Dia semanal | T5: (Varios elementos) | V5: Servicios | W5: ='PE (2)'!K5 -> 780000
A6: Semana | C6: 23-29 sep | D6: 30 Sep al 6 Oct | E6: 7-13 Oct | F6: 14-20 Oct | G6: 21-27 Oct | H6: 28 Oct -3Nov | I6: 4-10Nov | J6: 11-17Nov | K6: 18-24Nov | L6: 25Nov-1Dic | M6: 1-8Dic | N6: 9-15Dic | O6: 16-22Dic | P6: 22-28Dic | Q6: 29Dic-4Ene | W6: =+SUM(W2:W5) -> 5590000
B7: Semana | S7: Día | T7: Valor | U7: 0.3 | V7: =100%-U7 -> 0.7
A8: Día | B8: 0 | C8: 1 | D8: 2 | E8: 3 | F8: 4 | G8: 5 | H8: 6 | I8: 7 | J8: 8 | K8: 9 | L8: 10 | M8: 11 | N8: 12 | O8: 13 | P8: 14 | Q8: 15 | S8: oct | T8: 11041300 | U8: =+$U$7*T8 -> 3312390 | V8: =+T8-U8 -> 7728910
A9: lunes | C9: 142000 | D9: 183210 | E9: 603500 | F9: 622000 | G9: 350000 | H9: 300000 | I9: 600000 | J9: 700000 | K9: 350000 | L9: 500000 | M9: 250000 | N9: 140000 | O9: 207200 | P9: 308500 | Q9: 149500 | S9: nov | T9: 11534900 | U9: =+$U$7*T9 -> 3460470 | V9: =+T9-U9 -> 8074430 | W9: =+V9-W6 -> 2484430
A10: martes | C10: 393000 | D10: 229800 | E10: 426300 | F10: 227000 | G10: 380000 | H10: 220000 | I10: 194000 | J10: 122000 | K10: 220000 | L10: 400000 | M10: 120000 | N10: 0 | O10: 157500 | P10: 604000 | Q10: 448500 | S10: Total general | T10: 22576200 | U10: =+$U$7*T10 -> 6772860 | V10: =+T10-U10 -> 15803340
A11: miércoles | C11: 419500 | D11: 238000 | E11: 134000 | F11: 385300 | G11: 550000 | H11: 320000 | I11: 627000 | J11: 165000 | K11: 320000 | L11: 210000 | M11: 180000 | N11: 220000 | O11: 220000 | P11: 589500
A12: jueves | C12: 315000 | D12: 238000 | E12: 85500 | F12: 250800 | G12: 380000 | H12: 370000 | I12: 332500 | J12: 61000 | K12: 216500 | L12: 200000 | M12: 250000 | N12: 400000 | O12: 445500 | P12: 120500
A13: viernes | C13: 421000 | D13: 420500 | E13: 427900 | F13: 363500 | G13: 1200000 | H13: 370000 | I13: 342000 | J13: 235000 | K13: 186000 | L13: 400000 | M13: 220000 | N13: 350000 | O13: 350000 | P13: 82500
A14: sábado | C14: 951500 | D14: 1210300 | E14: 664500 | F14: 720000 | G14: 655000 | H14: 500000 | I14: 1552000 | J14: 811500 | K14: 587500 | L14: 900000 | M14: 900000 | N14: 900000 | O14: 450000 | P14: 824000
A15: domingo | B15: 572000 | C15: 658000 | D15: 1345600 | E15: 1283500 | F15: 1550500 | G15: 1200000 | H15: 1700000 | I15: 1690000 | J15: 1300900 | K15: 960000 | L15: 1500000 | M15: 1200000 | N15: 800000 | O15: 638500 | P15: 720000
A16: Total general | B16: 572000 | C16: 3300000 | D16: 3865410 | E16: 3625200 | F16: 4119100 | G16: 4715000 | H16: 3780000 | I16: 5337500 | J16: 3395400 | K16: 2840000 | L16: 4110000 | M16: 3120000 | N16: 2810000 | O16: 2468700 | P16: 3249000 | Q16: 598000 | S16: No. de semana | T16: (Todas)
C17: % | D17: =+D16/C16-1 -> 0.17133636 | E17: =+E16/D16-1 -> -0.062143472 | F17: =+F16/E16-1 -> 0.13624076 | G17: =+G16/F16-1 -> 0.14466752 | H17: =+H16/G16-1 -> -0.19830329 | I17: =+I16/H16-1 -> 0.41203704 | J17: =+J16/I16-1 -> -0.36385948 | K17: =+K16/J16-1 -> -0.16357425 | ... P17: =+P16/O16-1 -> 0.31607729
S18: Día | T18: Valor | U18: 0.6 | V18: 0.4
C19: =+SUM(C13:C15) -> 2030500 | D19: =+SUM(D13:D15) -> 2976400 | E19: =+SUM(E13:E15) -> 2375900 | F19: =+SUM(F13:F15) -> 2634000 | G19: =+SUM(G13:G15) -> 3055000 | H19: =+SUM(H13:H15) -> 2570000 | I19: =+SUM(I13:I15) -> 3584000 | J19: =+SUM(J13:J15) -> 2347400 | ... O19: =+SUM(O13:O15) -> 1438500 | S19: oct | T19: 17351500
S20: nov | T20: 16752900
A21: Variación relativa | C21: 23-29 sep | D21: 30 Sep al 6 Oct | E21: 7-13 Oct | F21: 14-20 Oct | G21: 21-27 Oct | H21: 28 Oct -3Nov | I21: 4-10Nov | J21: 11-17Nov | K21: 18-24Nov | L21: 25Nov-1Dic | M21: 1-8Dic | N21: 9-15Dic | O21: 16-22Dic | P21: 22-28Dic | Q21: 29Dic-4Ene | S21: Total general | T21: 34104400
A22: Día | B22: 0 | C22: 1 | D22: 2 | E22: 3 | F22: 4 | G22: 5 | H22: 6 | I22: 7 | J22: 8 | K22: 9 | L22: 10 | M22: 11 | N22: 12 | O22: 12 | P22: 14 | Q22: 15
A23: lunes | B23: - | D23: =+D9/C9-1 -> 0.29021127 | E23: =+E9/D9-1 -> 2.2940342 | F23: =+F9/E9-1 -> 0.030654515 | G23: =+G9/F9-1 -> -0.43729904 | H23: =+H9/G9-1 -> -0.14285714 | I23: =+I9/H9-1 -> 1 | J23: =+J9/I9-1 -> 0.16666667 | K23: =+K9/J9-1 -> -0.5 | ... Q23: =+Q9/P9-1 -> -0.51539708
A24: martes | B24: - | D24: =+D10/C10-1 -> -0.41526718 | E24: =+E10/D10-1 -> 0.85509138 | F24: =+F10/E10-1 -> -0.46751114 | G24: =+G10/F10-1 -> 0.67400881 | H24: =+H10/G10-1 -> -0.42105263 | I24: =+I10/H10-1 -> -0.11818182 | J24: =+J10/I10-1 -> -0.37113402 | K24: =+K10/J10-1 -> 0.80327869 | ... N24: =+N10/M10-1 -> -1 | O24: =IFERROR(O10/N10-1,"Abierto") -> Abierto | P24: =+P10/O10-1 -> 2.8349206 | Q24: =+Q10/P10-1 -> -0.25745033
A25: miércoles | B25: - | D25: =+D11/C11-1 -> -0.43265793 | E25: =+E11/D11-1 -> -0.43697479 | F25: =+F11/E11-1 -> 1.8753731 | G25: =+G11/F11-1 -> 0.42745912 | H25: =+H11/G11-1 -> -0.41818182 | I25: =+I11/H11-1 -> 0.959375 | J25: =+J11/I11-1 -> -0.73684211 | K25: =+K11/J11-1 -> 0.93939394 | ... P25: =+P11/O11-1 -> 1.6795455
A26: jueves | B26: - | D26: =+D12/C12-1 -> -0.24444444 | E26: =+E12/D12-1 -> -0.6407563 | F26: =+F12/E12-1 -> 1.9333333 | G26: =+G12/F12-1 -> 0.51515152 | H26: =+H12/G12-1 -> -0.026315789 | I26: =+I12/H12-1 -> -0.10135135 | J26: =+J12/I12-1 -> -0.81654135 | K26: =+K12/J12-1 -> 2.5491803 | ... P26: =+P12/O12-1 -> -0.7295174
A27: viernes | B27: - | D27: =+D13/C13-1 -> -0.0011876485 | E27: =+E13/D13-1 -> 0.017598098 | F27: =+F13/E13-1 -> -0.15050245 | G27: =+G13/F13-1 -> 2.301238 | H27: =+H13/G13-1 -> -0.69166667 | I27: =+I13/H13-1 -> -0.075675676 | J27: =+J13/I13-1 -> -0.3128655 | K27: =+K13/J13-1 -> -0.20851064 | ... P27: =+P13/O13-1 -> -0.76428571
A28: sábado | B28: - | D28: =+D14/C14-1 -> 0.27199159 | E28: =+E14/D14-1 -> -0.45096257 | F28: =+F14/E14-1 -> 0.083521445 | G28: =+G14/F14-1 -> -0.090277778 | H28: =+H14/G14-1 -> -0.23664122 | I28: =+I14/H14-1 -> 2.104 | J28: =+J14/I14-1 -> -0.47712629 | K28: =+K14/J14-1 -> -0.27603204 | ... P28: =+P14/O14-1 -> 0.83111111
A29: domingo | B29: - | C29: =+C15/B15-1 -> 0.15034965 | D29: =+D15/C15-1 -> 1.0449848 | E29: =+E15/D15-1 -> -0.046150416 | F29: =+F15/E15-1 -> 0.20802493 | G29: =+G15/F15-1 -> -0.22605611 | H29: =+H15/G15-1 -> 0.41666667 | I29: =+I15/H15-1 -> -0.0058823529 | J29: =+J15/I15-1 -> -0.23023669 | ... P29: =+P15/O15-1 -> 0.12764291
A30: Total general | B30: - | D30: =+D16/C16-1 -> 0.17133636 | E30: =+E16/D16-1 -> -0.062143472 | F30: =+F16/E16-1 -> 0.13624076 | G30: =+G16/F16-1 -> 0.14466752 | H30: =+H16/G16-1 -> -0.19830329 | I30: =+I16/H16-1 -> 0.41203704 | J30: =+J16/I16-1 -> -0.36385948 | K30: =+K16/J16-1 -> -0.16357425 | ... P30: =+P16/O16-1 -> 0.31607729
C34: 23-29 sep | D34: 30 Sep al 6 Oct | E34: 7-13 Oct | F34: 14-20 Oct | G34: 21-27 Oct | H34: 28 Oct -3Nov | I34: 4-10Nov | J34: 11-17Nov | K34: 18-24Nov | L34: 25Nov-1Dic | M34: 1-8Dic | N34: 9-15Dic | O34: 16-22Dic | P34: 22-28Dic | Q34: 29Dic-4Ene
A35: Día | B35: 0 | C35: 1 | D35: 2 | E35: 3 | F35: 4 | G35: 5 | H35: 6 | I35: 7 | J35: 8 | K35: 9 | L35: 10 | M35: 11 | N35: 12 | O35: 13 | P35: 14 | Q35: 15
A36: lunes | B36: - | C36: =+C9-B9 -> 142000 | D36: =+D9-C9 -> 41210 | E36: =+E9-D9 -> 420290 | F36: =+F9-E9 -> 18500 | G36: =+G9-F9 -> -272000 | H36: =+H9-G9 -> -50000 | I36: =+I9-H9 -> 300000 | J36: =+J9-I9 -> 100000 | ... O36: =+O9-N9 -> 67200
A37: martes | B37: - | C37: =+C10-B10 -> 393000 | D37: =+D10-C10 -> -163200 | E37: =+E10-D10 -> 196500 | F37: =+F10-E10 -> -199300 | G37: =+G10-F10 -> 153000 | H37: =+H10-G10 -> -160000 | I37: =+I10-H10 -> -26000 | J37: =+J10-I10 -> -72000 | ... O37: =+O10-N10 -> 157500
A38: miércoles | B38: - | C38: =+C11-B11 -> 419500 | D38: =+D11-C11 -> -181500 | E38: =+E11-D11 -> -104000 | F38: =+F11-E11 -> 251300 | G38: =+G11-F11 -> 164700 | H38: =+H11-G11 -> -230000 | I38: =+I11-H11 -> 307000 | J38: =+J11-I11 -> -462000 | ... O38: =+O11-N11 -> 0
A39: jueves | B39: - | C39: =+C12-B12 -> 315000 | D39: =+D12-C12 -> -77000 | E39: =+E12-D12 -> -152500 | F39: =+F12-E12 -> 165300 | G39: =+G12-F12 -> 129200 | H39: =+H12-G12 -> -10000 | I39: =+I12-H12 -> -37500 | J39: =+J12-I12 -> -271500 | ... O39: =+O12-N12 -> 45500
A40: viernes | B40: - | C40: =+C13-B13 -> 421000 | D40: =+D13-C13 -> -500 | E40: =+E13-D13 -> 7400 | F40: =+F13-E13 -> -64400 | G40: =+G13-F13 -> 836500 | H40: =+H13-G13 -> -830000 | I40: =+I13-H13 -> -28000 | J40: =+J13-I13 -> -107000 | ... O40: =+O13-N13 -> 0
A41: sábado | B41: - | C41: =+C14-B14 -> 951500 | D41: =+D14-C14 -> 258800 | E41: =+E14-D14 -> -545800 | F41: =+F14-E14 -> 55500 | G41: =+G14-F14 -> -65000 | H41: =+H14-G14 -> -155000 | I41: =+I14-H14 -> 1052000 | J41: =+J14-I14 -> -740500 | ... O41: =+O14-N14 -> -450000
A42: domingo | B42: - | C42: =+C15-B15 -> 86000 | D42: =+D15-C15 -> 687600 | E42: =+E15-D15 -> -62100 | F42: =+F15-E15 -> 267000 | G42: =+G15-F15 -> -350500 | H42: =+H15-G15 -> 500000 | I42: =+I15-H15 -> -10000 | J42: =+J15-I15 -> -389100 | ... O42: =+O15-N15 -> -161500
A43: Total general | B43: - | C43: =+C16-B16 -> 2728000 | D43: =+D16-C16 -> 565410 | E43: =+E16-D16 -> -240210 | F43: =+F16-E16 -> 493900 | G43: =+G16-F16 -> 595900 | H43: =+H16-G16 -> -935000 | I43: =+I16-H16 -> 1557500 | J43: =+J16-I16 -> -1942100 | ... O43: =+O16-N16 -> -341300

Sheet Anàlisis de producto
A1: Máx. de Id. Client por dìa | B1: Semana
A2: Día | B2: 0 | C2: 1 | D2: 4
A3: lunes | C3: 7 | D3: 14
A4: martes | C4: 14 | D4: 19
A5: miércoles | C5: 17 | D5: 19
A6: jueves | C6: 10 | D6: 14
A7: viernes | C7: 15 | D7: 15
A8: sábado | C8: 29
A9: domingo | C9: 19 | D9: 36
A10: Total general | C10: 29 | D10: 36
A14: Cuenta de Id. Client por dìa | B14: Semana
A15: Día | B15: 1 | C15: 3 | D15: 4
A16: lunes
A17: Picada | D17: 11
A18: martes
A19: Picada | D19: 1
A20: miércoles
A21: Picada | B21: 3 | D21: 7
A22: jueves
A23: Picada | B23: 1 | D23: 1
A24: Picada con Refajo | B24: 1
A25: viernes
A26: Picada | B26: 2 | D26: 5
A27: sábado
A28: Picada | B28: 12
A29: Picada con Refajo | B29: 1
A30: domingo
A31: Canasta de picada mixta | B31: 1
A32: Canasta de picada mixta + Carne Parrila | B32: 1
A33: Canasta de picada mixta + Carne Parrila + 1/4 de Gallina | B33: 1
A34: Picada | B34: 8 | C34: 17 | D34: 23
A35: Total general | B35: 31 | C35: 17 | D35: 48

Sheet OPEX_deuda
B1: Septiembre | I1: Octubre | Q1: Noviembre | Y1: Diciembre
D2: Inversiòn | E2: Viernes | F2: Dia fds | G2: Mensual | K2: Inversiòn | L2: Saldo actual | M2: Viernes | N2: Dia fds | O2: Mensual | S2: Inversiòn | T2: Saldo actual | U2: Viernes | V2: Dia fds | W2: Mensual | AA2: Inversiòn | AB2: Saldo actual | AC2: Viernes | AD2: Dia fds | AE2: Mensual
E3: 1 | F3: 4 | G3: =+E3+F3 -> 5 | M3: 4 | N3: 9 | O3: =+M3+N3 -> 13 | U3: 5 | V3: 11 | W3: =+U3+V3 -> 16 | AC3: 4 | AD3: 10 | AE3: =+AC3+AD3 -> 14
B4: Arriendo | C4: Arriendo | E4: =+G4/G3 -> 300000 | G4: 1500000 | I4: Arriendo | J4: Arriendo | M4: =+O4/O3 -> 192307.69 | O4: 2500000 | Q4: Arriendo | R4: Arriendo | U4: =+W4/W3 -> 156250 | W4: 2500000 | Y4: Arriendo | Z4: Arriendo | AC4: =+AE4/AE3 -> 178571.43 | AE4: 2500000
B5: Servicios | C5: Agua | I5: Servicios | J5: Agua | M5: =+O5/O3 -> 23076.923 | O5: 300000 | Q5: Servicios | R5: Agua | U5: =+W5/W3 -> 12500 | W5: 200000 | Y5: Servicios | Z5: Agua | AC5: =+AE5/30 -> 5000 | AE5: 150000
C6: Luz | J6: Luz | M6: =+O6/O3 -> 19230.769 | O6: 250000 | R6: Luz | U6: =+W6/W3 -> 15625 | W6: 250000 | Z6: Luz | AC6: =+AE6/30 -> 8333.3333 | AE6: 250000
C7: Gas | J7: Gas | M7: =+O7/O3 -> 19230.769 | O7: 250000 | R7: Gas | U7: =+W7/W3 -> 20625 | W7: 330000 | Z7: Gas | AC7: =+AE7/30 -> 8333.3333 | AE7: 250000
C8: Telefonía, internet y televisión | J8: Telefonía, internet y televisión | R8: Telefonía, internet y televisión | Z8: Telefonía, internet y televisión
B9: Nomina | C9: Ayudante de cocina senior (Señora Rosa) | E9: 35000 | F9: 35000 | G9: =+(E9*E3)+(F9*F3) -> 175000 | I9: Nomina | J9: Ayudante de cocina senior (Señora Rosa) | M9: 35000 | N9: 35000 | O9: =+(M9*M3)+(N9*N3) -> 455000 | Q9: Nomina | R9: Ayudante de cocina senior (Señora Rosa) | U9: 35000 | V9: 35000 | W9: =+(U9*U3)+(V9*V3) -> 560000 | X9: 10000 | Y9: Nomina | Z9: Ayudante de cocina senior (Señora Rosa) | AC9: 35000 | AD9: 35000 | AE9: =+(AC9*AC3)+(AD9*AD3) -> 490000
C10: Ayudante de cocina Junior (Yeri) | E10: 25000 | F10: 30000 | G10: =+(E10*E3)+(F10*F3) -> 145000 | J10: Ayudante de cocina Junior (Yeri) | M10: 25000 | N10: 30000 | O10: =+(M10*M3)+(N10*N3) -> 370000 | R10: Ayudante de cocina Junior (Henry) | U10: 25000 | V10: 30000 | W10: =+(U10*U3)+(V10*V3) -> 455000 | X10: 10000 | Z10: Ayudante de cocina Junior (Janeth) | AC10: 25000 | AD10: 30000 | AE10: =+(AC10*AC3)+(AD10*AD3) -> 400000
C11: Mesero (a) fijo (Yusmeidy y Alines) | E11: 25000 | F11: 30000 | G11: =+(E11*E3)+(F11*F3) -> 145000 | J11: Mesero (a) fijo (Yusmeidy y Alines) | M11: 25000 | N11: 30000 | O11: =+(M11*M3)+(N11*N3) -> 370000 | R11: Mesero (a) fijo (Yusmeidy) | U11: 25000 | V11: 30000 | W11: =+(U11*U3)+(V11*V3) -> 455000 | X11: 10000 | Z11: Mesero (a) fijo (Mauricio) | AC11: 25000 | AD11: 30000 | AE11: =+(AC11*AC3)+(AD11*AD3) -> 400000
C12: Mesero (a) sabatino (Stefania) | E12: 0 | F12: 35000 | G12: =+(E12*0)+(F12*F3) -> 140000 | J12: Mesero (a) sabatino (Stefania) | M12: 0 | N12: 35000 | O12: =+(M12*0)+(N12*N3) -> 315000 | R12: Mesero (a) sabatino (Stefania) | U12: 0 | V12: 35000 | W12: =+(U12*0)+(V12*V3) -> 385000 | Z12: Mesero (a) sabatino (Yuly y Danda) | AC12: 0 | AD12: 35000 | AE12: =+(AC12*0)+(AD12*AD3) -> 350000
C13: Chef- Cocinero sabatino (Eduardo e Ingacio) | E13: 50000 | F13: 50000 | G13: =+(E13*8)+(F13*5) -> 650000 | J13: Chef- Cocinero sabatino (Eduardo e Ingacio) | M13: 30000 | N13: 60000 | O13: =+(M13*8)+(N13*5) -> 540000 | R13: Chef- Cocinero sabatino | U13: 0 | V13: 0 | W13: =+(U13*20)+(V13*10) -> 0 | Z13: Chef- Cocinero sabatino | AC13: 0 | AD13: 0 | AE13: =+(AC13*20)+(AD13*10) -> 0
C14: Banderero y domiciliario (Rolando y Manuel) | E14: 25000 | F14: 25000 | G14: =+(E14*E3)+(F14*F3) -> 125000 | J14: Banderero y domiciliario (Rolando y Manuel) | M14: 25000 | N14: 25000 | O14: =+(M14*M3)+(N14*N3) -> 325000 | R14: Banderero y domiciliario (Manuel) | U14: 25000 | V14: 30000 | W14: =+(U14*U3)+(V14*V3) -> 455000 | X14: 10000 | Z14: Banderero y domiciliario (Manuel) | AC14: 25000 | AD14: 25000 | AE14: =+(AC14*AC3)+(AD14*AD3) -> 350000
C15: Asistente administrativo y mercadeo | G15: =+(E15*20)+(F15*10) -> 0 | J15: Asistente administrativo y mercadeo | O15: =+(M15*20)+(N15*10) -> 0 | R15: Asistente administrativo y mercadeo | W15: =+(U15*20)+(V15*10) -> 0 | Z15: Asistente administrativo y mercadeo | AE15: =+(AC15*20)+(AD15*10) -> 0
C16: Parrillero, Jefe de compras, jefe de tesorería, jefe de personal | E16: 0 | F16: 0 | G16: =+(E16*20)+(F16*10) -> 0 | J16: Parrillero, Jefe de compras, jefe de tesorería, jefe de personal | M16: 0 | N16: 0 | O16: =+(M16*20)+(N16*10) -> 0 | R16: Parrillero, Jefe de compras, jefe de tesorería, jefe de personal | W16: =+(U16*20)+(V16*10) -> 0 | X16: =+SUM(X9:X14,U9:U14) -> 150000 | Z16: Parrillero, Jefe de compras, jefe de tesorería, jefe de personal | AC16: 0 | AD16: 0 | AE16: =+(AC16*20)+(AD16*10) -> 0
C17: Caja, Jefe de contabilidad Administrador, jefe de compras, Auditor interno, Facturación Investigador de mercados, analista de negocios (datos), Gerente comercial | E17: 0 | F17: 0 | G17: =+(E17*20)+(F17*10) -> 0 | J17: Caja, Jefe de contabilidad Administrador, jefe de compras, Auditor interno, Facturación Investigador de mercados, analista de negocios (datos), Gerente comercial | M17: 0 | N17: 0 | O17: =+(M17*20)+(N17*10) -> 0 | R17: Caja, Jefe de contabilidad Administrador, jefe de compras, Auditor interno, Facturación Investigador de mercados, analista de negocios (datos), Gerente comercial | U17: 0 | V17: 0 | W17: =+(U17*20)+(V17*10) -> 0 | Z17: Caja, Jefe de contabilidad Administrador, jefe de compras, Auditor interno, Facturación Investigador de mercados, analista de negocios (datos), Gerente comercial | AC17: 0 | AD17: 0 | AE17: =+(AC17*20)+(AD17*10) -> 0
B18: Financieros | C18: ScotiaBank | D18: =2600000+67500+824000 -> 3491500 | I18: Financieros | J18: ScotiaBank | K18: =2600000+67500+824000 -> 3491500 | L18: 3439103.3 | M18: =+O18/O3 -> 9846.1538 | O18: 128000 | Q18: Financieros | R18: ScotiaBank | S18: =2600000+67500+824000 -> 3491500 | T18: 3439103.3 | U18: =+W18/W3 -> 0 | Y18: Financieros | Z18: ScotiaBank | AC18: =+AE18/AE3 -> 0
C19: Bancolombia (American Express) | D19: 1242548.5 | J19: Bancolombia (American Express) | K19: 1242548.5 | L19: 1198874 | M19: =+O19/O3 -> 7605.7692 | O19: 98875 | R19: Bancolombia (American Express) | S19: 1242548.5 | T19: 1198874 | U19: =+W19/W3 -> 0 | Z19: Bancolombia (American Express) | AC19: =+AE19/AE3 -> 0
C20: Bancolombia (Visa) | D20: 3737029.6 | J20: Bancolombia (Visa) | K20: 3737029.6 | L20: 3299796 | M20: =+O20/O3 -> 42346.308 | O20: 550502 | R20: Bancolombia (Visa) | S20: 3737029.6 | T20: 3299796 | U20: =+W20/W3 -> 0 | Z20: Bancolombia (Visa) | AC20: =+AE20/AE3 -> 0
C21: Banco Hector (cuantos meses) | E21: =+G21/30 -> 0 | G21: 0 | J21: Banco Hector (cuantos meses) | M21: =+O21/O3 -> 0 | R21: Banco Hector (cuantos meses) | U21: =+W21/W3 -> 0 | Z21: Banco Hector (cuantos meses) | AC21: =+AE21/AE3 -> 42857.143 | AE21: 600000
B23: Gastos Fijos y Variables | C23: 0.4 | E23: =+SUM(E4:F8,E18:F21,E9:E17) -> 460000 | F23: =+SUM(E4:F8,E18:F21,F9:F17) -> 505000 | G23: =+SUM(G4:G21) -> 2880000 | I23: Gastos Fijos y Variables | J23: 0.4 | M23: =+SUM(M4:N8,M18:N21,M9:M17) -> 453644.38 | N23: =+SUM(M4:N8,M18:N21,N9:N17) -> 528644.38 | O23: =+SUM(O4:O21) -> 6452377 | Q23: Gastos Fijos y Variables | R23: 0.4 | U23: =+SUM(U4:V8,U18:V21,U9:U17) -> 315000 | V23: =+SUM(U4:V8,U18:V21,V9:V17) -> 365000 | W23: =+SUM(W4:W21) -> 5590000 | Y23: Gastos Fijos y Variables | Z23: 0.4 | AC23: =+SUM(AC4:AD8,AC18:AD21,AC9:AC17) -> 353095.24 | AD23: =+SUM(AC4:AD8,AC18:AD21,AD9:AD17) -> 398095.24 | AE23: =+SUM(AE4:AE21) -> 5740000
B24: Costos Variables | C24: 0.6 | E24: =+E$25*$R24 -> 690000 | F24: =+F$25*$R24 -> 757500 | G24: =+G$25*C24 -> 4320000 | I24: Costos Variables | J24: 0.6 | M24: =+M$25*$R24 -> 680466.58 | N24: =+N$25*$R24 -> 792966.58 | O24: =+O$25*J24 -> 9678565.5 | Q24: Costos Variables | R24: 0.6 | U24: =+U$25*$R24 -> 472500 | V24: =+V$25*$R24 -> 547500 | W24: =+W$25*R24 -> 8385000 | Y24: Costos Variables | Z24: 0.6 | AC24: =+AC$25*$R24 -> 529642.86 | AD24: =+AD$25*$R24 -> 597142.86 | AE24: =+AE$25*Z24 -> 8610000
E25: =(E23/40)*100 -> 1150000 | F25: =(F23/40)*100 -> 1262500 | G25: =(G23/40)*100 -> 7200000 | M25: =(M23/40)*100 -> 1134111 | N25: =(N23/40)*100 -> 1321611 | O25: =(O23/40)*100 -> 16130942 | U25: =(U23/40)*100 -> 787500 | V25: =(V23/40)*100 -> 912500 | W25: =(W23/40)*100 -> 13975000 | AC25: =(AC23/40)*100 -> 882738.1 | AD25: =(AD23/40)*100 -> 995238.1 | AE25: =(AE23/40)*100 -> 14350000
M27: Dìas habiles | N27: 22 | O27: =+N27*U25 -> 17325000
F28: Venta Real | G28: 4055210 | M28: Fin Semana | N28: 9 | O28: =+N28*V25 -> 8212500
F29: 60% Mercancia en uso y a crédito | G29: =+G28*60% -> 2433126 | O29: =+SUM(O27:O28) -> 25537500
F30: Gastos 40% | G30: =+G29-G28 -> -1622084 | M30: Gastos Fijo diario prom. | O30: =+O29/31 -> 823790.32
F31: Aporte Edwin Mercado | G31: 900000
G32: =+G31+G30 -> -722084
F33: Aporte Carne Hector | G33: =+G32 -> -722084

Sheet OPEX (3)
B1: Septiembre | I1: Octubre | Q1: Noviembre | Y1: Diciembre
D2: Inversiòn | E2: Viernes | F2: Dia fds | G2: Mensual | K2: Inversiòn | L2: Saldo actual | M2: Viernes | N2: Dia fds | O2: Mensual | S2: Inversiòn | T2: Saldo actual | U2: Viernes | V2: Dia fds | W2: Mensual | AA2: Inversiòn | AB2: Saldo actual | AC2: Viernes | AD2: Dia fds | AE2: Mensual
E3: 0 | F3: 3 | G3: =+E3+F3 -> 3 | M3: 0 | N3: 9 | O3: =+M3+N3 -> 9 | U3: 0 | V3: 11 | W3: =+U3+V3 -> 11 | AC3: 0 | AD3: 10 | AE3: =+AC3+AD3 -> 10
B4: Arriendo | C4: Arriendo | E4: =+G4/G3 -> 500000 | G4: 1500000 | I4: Arriendo | J4: Arriendo | M4: =+O4/O3 -> 277777.78 | O4: 2500000 | Q4: Arriendo | R4: Arriendo | U4: =+W4/W3 -> 227272.73 | W4: 2500000 | Y4: Arriendo | Z4: Arriendo | AC4: =+AE4/AE3 -> 250000 | AE4: 2500000
B5: Servicios | C5: Agua | I5: Servicios | J5: Agua | M5: =+O5/O3 -> 33333.333 | O5: 300000 | Q5: Servicios | R5: Agua | U5: =+W5/W3 -> 27272.727 | W5: 300000 | Y5: Servicios | Z5: Agua | AC5: =+AE5/30 -> 10000 | AE5: 300000
C6: Luz | J6: Luz | M6: =+O6/O3 -> 27777.778 | O6: 250000 | R6: Luz | U6: =+W6/W3 -> 22727.273 | W6: 250000 | Z6: Luz | AC6: =+AE6/30 -> 8333.3333 | AE6: 250000
C7: Gas | J7: Gas | M7: =+O7/O3 -> 27777.778 | O7: 250000 | R7: Gas | U7: =+W7/W3 -> 22727.273 | W7: 250000 | Z7: Gas | AC7: =+AE7/30 -> 8333.3333 | AE7: 250000
C8: Telefonía, internet y televisión | J8: Telefonía, internet y televisión | R8: Telefonía, internet y televisión | Z8: Telefonía, internet y televisión
B9: Nomina | C9: Ayudante de cocina senior (Señora Rosa) | F9: 35000 | G9: =+(E9*E3)+(F9*F3) -> 105000 | I9: Nomina | J9: Ayudante de cocina senior (Señora Rosa) | N9: 35000 | O9: =+(M9*M3)+(N9*N3) -> 315000 | Q9: Nomina | R9: Ayudante de cocina senior (Señora Rosa) | V9: 35000 | W9: =+(U9*U3)+(V9*V3) -> 385000 | X9: 10000 | Y9: Nomina | Z9: Ayudante de cocina senior (Señora Rosa) | AD9: 35000 | AE9: =+(AC9*AC3)+(AD9*AD3) -> 350000
C10: Ayudante de cocina Junior (Yeri) | F10: 30000 | G10: =+(E10*E3)+(F10*F3) -> 90000 | J10: Ayudante de cocina Junior (Yeri) | N10: 30000 | O10: =+(M10*M3)+(N10*N3) -> 270000 | R10: Ayudante de cocina Junior (Henry) | V10: 30000 | W10: =+(U10*U3)+(V10*V3) -> 330000 | X10: 10000 | Z10: Ayudante de cocina Junior (Henry) | AD10: 30000 | AE10: =+(AC10*AC3)+(AD10*AD3) -> 300000
C11: Mesero (a) fijo (Yusmeidy y Alines) | F11: 30000 | G11: =+(E11*E3)+(F11*F3) -> 90000 | J11: Mesero (a) fijo (Yusmeidy y Alines) | N11: 30000 | O11: =+(M11*M3)+(N11*N3) -> 270000 | R11: Mesero (a) fijo (Yusmeidy) | V11: 30000 | W11: =+(U11*U3)+(V11*V3) -> 330000 | X11: 10000 | Z11: Mesero (a) fijo (Yusmeidy) | AD11: 30000 | AE11: =+(AC11*AC3)+(AD11*AD3) -> 300000
C12: Mesero (a) sabatino (Stefania) | F12: 35000 | G12: =+(E12*0)+(F12*F3) -> 105000 | J12: Mesero (a) sabatino (Stefania) | N12: 35000 | O12: =+(M12*0)+(N12*N$3) -> 315000 | R12: Mesero (a) sabatino (Stefania) | V12: 35000 | W12: =+(U12*0)+(V12*V3) -> 385000 | Z12: Mesero (a) sabatino (Stefania) | AD12: 35000 | AE12: =+(AC12*0)+(AD12*AD3) -> 350000
C13: Chef- Cocinero sabatino (Eduardo e Ingacio) | F13: 50000 | G13: =+(E13*8)+(F13*5) -> 250000 | J13: Chef- Cocinero sabatino (Eduardo e Ingacio) | N13: 60000 | O13: =+(M13*0)+(N13*N$3) -> 540000 | R13: Chef- Cocinero sabatino | V13: 0 | W13: =+(U13*20)+(V13*10) -> 0 | Z13: Chef- Cocinero sabatino | AD13: 0 | AE13: =+(AC13*20)+(AD13*10) -> 0
C14: Banderero y domiciliario (Rolando y Manuel) | F14: 25000 | G14: =+(E14*E3)+(F14*F3) -> 75000 | J14: Banderero y domiciliario (Rolando y Manuel) | N14: 25000 | O14: =+(M14*M3)+(N14*N3) -> 225000 | R14: Banderero y domiciliario (Manuel) | V14: 30000 | W14: =+(U14*U3)+(V14*V3) -> 330000 | X14: 10000 | Z14: Banderero y domiciliario (Manuel) | AD14: 25000 | AE14: =+(AC14*AC3)+(AD14*AD3) -> 250000
C15: Asistente administrativo y mercadeo | G15: =+(E15*20)+(F15*10) -> 0 | J15: Asistente administrativo y mercadeo | O15: =+(M15*20)+(N15*10) -> 0 | R15: Asistente administrativo y mercadeo | W15: =+(U15*20)+(V15*10) -> 0 | Z15: Asistente administrativo y mercadeo | AE15: =+(AC15*20)+(AD15*10) -> 0
C16: Parrillero, Jefe de compras, jefe de tesorería, jefe de personal | E16: 0 | F16: 0 | G16: =+(E16*20)+(F16*10) -> 0 | J16: Parrillero, Jefe de compras, jefe de tesorería, jefe de personal | M16: 0 | N16: 0 | O16: =+(M16*20)+(N16*10) -> 0 | R16: Parrillero, Jefe de compras, jefe de tesorería, jefe de personal | W16: =+(U16*20)+(V16*10) -> 0 | X16: =+SUM(X9:X14,U9:U14) -> 40000 | Z16: Parrillero, Jefe de compras, jefe de tesorería, jefe de personal | AC16: 0 | AD16: 0 | AE16: =+(AC16*20)+(AD16*10) -> 0
C17: Caja, Jefe de contabilidad Administrador, jefe de compras, Auditor interno, Facturación Investigador de mercados, analista de negocios (datos), Gerente comercial | E17: 0 | F17: 0 | G17: =+(E17*20)+(F17*10) -> 0 | J17: Caja, Jefe de contabilidad Administrador, jefe de compras, Auditor interno, Facturación Investigador de mercados, analista de negocios (datos), Gerente comercial | M17: 0 | N17: 0 | O17: =+(M17*20)+(N17*10) -> 0 | R17: Caja, Jefe de contabilidad Administrador, jefe de compras, Auditor interno, Facturación Investigador de mercados, analista de negocios (datos), Gerente comercial | U17: 0 | V17: 0 | W17: =+(U17*20)+(V17*10) -> 0 | Z17: Caja, Jefe de contabilidad Administrador, jefe de compras, Auditor interno, Facturación Investigador de mercados, analista de negocios (datos), Gerente comercial | AC17: 0 | AD17: 0 | AE17: =+(AC17*20)+(AD17*10) -> 0
B18: Financieros | C18: ScotiaBank | D18: =2600000+67500+824000 -> 3491500 | I18: Financieros | J18: ScotiaBank | K18: =2600000+67500+824000 -> 3491500 | L18: 3439103.3 | M18: =+O18/O3 -> 14222.222 | O18: 128000 | Q18: Financieros | R18: ScotiaBank | S18: =2600000+67500+824000 -> 3491500 | T18: 3439103.3 | U18: =+W18/W3 -> 18566.182 | W18: 204228 | Y18: Financieros | Z18: ScotiaBank | AC18: =+AE18/AE3 -> 20422.8 | AE18: 204228
C19: Bancolombia (American Express) | D19: 1242548.5 | J19: Bancolombia (American Express) | K19: 1242548.5 | L19: 1198874 | M19: =+O19/O3 -> 10986.111 | O19: 98875 | R19: Bancolombia (American Express) | S19: 1242548.5 | T19: 1198874 | U19: =+W19/W3 -> 8988.6364 | W19: 98875 | Z19: Bancolombia (American Express) | AC19: =+AE19/AE3 -> 9887.5 | AE19: 98875
C20: Bancolombia (Visa) | D20: 3737029.6 | J20: Bancolombia (Visa) | K20: 3737029.6 | L20: 3299796 | M20: =+O20/O3 -> 61166.889 | O20: 550502 | R20: Bancolombia (Visa) | S20: 3737029.6 | T20: 3299796 | U20: =+W20/W3 -> 50045.636 | W20: 550502 | Z20: Bancolombia (Visa) | AC20: =+AE20/AE3 -> 20246.2 | AE20: 202462
C21: Banco Hector (cuantos meses) | E21: =+G21/30 -> 0 | G21: 0 | J21: Banco Hector (cuantos meses) | M21: =+O21/O3 -> 66666.667 | O21: 600000 | R21: Banco Hector (cuantos meses) | U21: =+W21/W3 -> 54545.455 | W21: 600000 | Z21: Banco Hector (cuantos meses) | AC21: =+AE21/AE3 -> 60000 | AE21: 600000
B23: Gastos Fijos y Variables | C23: 0.4 | E23: =+SUM(E4:F8,E18:F21,E9:E17) -> 500000 | F23: =+SUM(E4:F8,E18:F21,F9:F17) -> 705000 | G23: =+SUM(G4:G21) -> 2215000 | I23: Gastos Fijos y Variables | J23: 0.4 | M23: =+SUM(M4:N8,M18:N21,M9:M17) -> 519708.56 | N23: =+SUM(M4:N8,M18:N21,N9:N17) -> 734708.56 | O23: =+SUM(O4:O21) -> 6612377 | Q23: Gastos Fijos y Variables | R23: 0.4 | U23: =+SUM(U4:V8,U18:V21,U9:U17) -> 432145.91 | V23: =+SUM(U4:V8,U18:V21,V9:V17) -> 592145.91 | W23: =+SUM(W4:W21) -> 6513605 | Y23: Gastos Fijos y Variables | Z23: 0.4 | AC23: =+SUM(AC4:AD8,AC18:AD21,AC9:AC17) -> 387223.17 | AD23: =+SUM(AC4:AD8,AC18:AD21,AD9:AD17) -> 542223.17 | AE23: =+SUM(AE4:AE21) -> 5955565
B24: Costos Variables | C24: 0.6 | E24: =+E$25*$R24 -> 750000 | F24: =+F$25*$R24 -> 1057500 | G24: =+G$25*C24 -> 3322500 | I24: Costos Variables | J24: 0.6 | M24: =+M$25*$R24 -> 779562.83 | N24: =+N$25*$R24 -> 1102062.8 | O24: =+O$25*J24 -> 9918565.5 | Q24: Costos Variables | R24: 0.6 | U24: =+U$25*$R24 -> 648218.86 | V24: =+V$25*$R24 -> 888218.86 | W24: =+W$25*R24 -> 9770407.5 | Y24: Costos Variables | Z24: 0.6 | AC24: =+AC$25*$R24 -> 580834.75 | AD24: =+AD$25*$R24 -> 813334.75 | AE24: =+AE$25*Z24 -> 8933347.5
E25: =(E23/40)*100 -> 1250000 | F25: =(F23/40)*100 -> 1762500 | G25: =(G23/40)*100 -> 5537500 | M25: =(M23/40)*100 -> 1299271.4 | N25: =(N23/40)*100 -> 1836771.4 | O25: =(O23/40)*100 -> 16530942 | U25: =(U23/40)*100 -> 1080364.8 | V25: =(V23/40)*100 -> 1480364.8 | W25: =(W23/40)*100 -> 16284012 | AC25: =(AC23/40)*100 -> 968057.92 | AD25: =(AD23/40)*100 -> 1355557.9 | AE25: =(AE23/40)*100 -> 14888912
M27: Dìas habiles | N27: 22 | O27: =+N27*U25 -> 23768025
M28: Fin Semana | N28: 9 | O28: =+N28*V25 -> 13323283
O29: =+SUM(O27:O28) -> 37091308
M30: Gastos Fijo diario prom. | O30: =+O29/31 -> 1196493.8

Sheet OPEX
B1: Septiembre | I1: Octubre | O1: Noviembre | U1: Diciembre | AA1: Enero de 2020
D2: Inversiòn | E2: Dia hábil | F2: Dia fds | G2: Mensual | K2: Dia hábil | L2: Dia fds | M2: Mensual | Q2: Dia hábil | R2: Dia fds | S2: Mensual | W2: Dia hábil | X2: Dia fds | Y2: Mensual | AC2: Dia hábil | AD2: Dia fds | AE2: Mensual
E3: 5 | F3: 4 | G3: =+E3+F3 -> 9 | K3: =31-L3 -> 18 | L3: 13 | M3: =+K3+L3 -> 31 | Q3: =30-R3 -> 14 | R3: 16 | S3: =+Q3+R3 -> 30 | W3: =31-X3 -> 17 | X3: 14 | Y3: =+W3+X3 -> 31 | AC3: =31-AD3 -> 16 | AD3: 15 | AE3: =+AC3+AD3 -> 31
B4: Arriendo | C4: Arriendo | E4: =+G4/G3 -> 166666.67 | G4: 1500000 | I4: Arriendo | J4: Arriendo | K4: =+M4/M3 -> 80645.161 | M4: 2500000 | O4: Arriendo | P4: Arriendo | Q4: =+S4/S3 -> 83333.333 | S4: 2500000 | U4: Arriendo | V4: Arriendo | W4: =+Y4/Y3 -> 80645.161 | Y4: 2500000 | AA4: Arriendo | AB4: Arriendo | AC4: =+AE4/AE3 -> 80645.161 | AE4: 2500000
B5: Servicios | C5: Agua | I5: Servicios | J5: Agua | K5: =+M5/M3 -> 9677.4194 | M5: 300000 | O5: Servicios | P5: Agua | Q5: =+S5/S3 -> 10000 | S5: 300000 | U5: Servicios | V5: Agua | W5: =+Y5/30 -> 10000 | Y5: 300000 | AA5: Servicios | AB5: Agua | AD5: =+AE5/30 -> 10000 | AE5: 300000
C6: Luz | J6: Luz | K6: =+M6/M3 -> 8064.5161 | M6: 250000 | P6: Luz | Q6: =+S6/S3 -> 8333.3333 | S6: 250000 | V6: Luz | W6: =+Y6/30 -> 8333.3333 | Y6: 250000 | AB6: Luz | AD6: =+AE6/30 -> 8333.3333 | AE6: 250000
C7: Gas | J7: Gas | K7: =+M7/M3 -> 8064.5161 | M7: 250000 | P7: Gas | Q7: =+S7/S3 -> 8333.3333 | S7: 250000 | V7: Gas | W7: =+Y7/30 -> 7666.6667 | Y7: 230000 | AB7: Gas | AD7: =+AE7/30 -> 7666.6667 | AE7: 230000
C8: Telefonía, internet y televisión | J8: Telefonía, internet y televisión | P8: Telefonía, internet y televisión | V8: Telefonía, internet y televisión | AB8: Telefonía, internet y televisión
B9: Nomina | C9: Ayudante de cocina senior (Señora Rosa) | E9: 35000 | F9: 35000 | G9: =+(E9*E3)+(F9*F3) -> 315000 | I9: Nomina | J9: Ayudante de cocina senior (Señora Rosa) | K9: 35000 | L9: 35000 | M9: =+(K9*K3)+(L9*L3) -> 1085000 | O9: Nomina | P9: Ayudante de cocina senior (Señora Rosa) | Q9: 35000 | R9: 35000 | S9: =+(Q9*Q3)+(R9*R3) -> 1050000 | U9: Nomina | V9: Ayudante de cocina senior (Señora Rosa) | W9: 35000 | X9: 35000 | Y9: =+(W9*W3)+(X9*X3) -> 1085000 | AA9: Nomina | AB9: Ayudante de cocina senior - Viernes, Sábado, Domingo | AD9: 37000 | AE9: =+(AC9*AC3)+(AD9*(AD3-4)) -> 407000 | AF9: 9 am - 9pm
C10: Ayudante de cocina Junior (Yeri) | E10: 25000 | F10: 30000 | G10: =+(E10*E3)+(F10*F3) -> 245000 | J10: Ayudante de cocina Junior (Yeri) | K10: 25000 | L10: 30000 | M10: =+(K10*K3)+(L10*L3) -> 840000 | P10: Ayudante de cocina Junior (Henry) | Q10: 25000 | R10: 30000 | S10: =+(Q10*Q3)+(R10*R3) -> 830000 | V10: Ayudante de cocina Junior | X10: 35000 | Y10: =+(W10*W3)+(X10*X3) -> 490000 | AB10: Ayudante de cocina Junior - Viernes, Sábado, Domingo (Edwin) | AD10: 0 | AE10: =+(AC10*AC3)+(AD10*AD3) -> 0
C11: Mesero (a) fijo (Yusmeidy y Alines) | E11: 25000 | F11: 30000 | G11: =+(E11*E3)+(F11*F3) -> 245000 | J11: Mesero (a) fijo (Yusmeidy y Alines) | K11: 25000 | L11: 30000 | M11: =+(K11*K3)+(L11*L3) -> 840000 | P11: Mesero (a) fijo (Yusmeidy y otras) | Q11: 25000 | R11: 30000 | S11: =+(Q11*Q3)+(R11*R3) -> 830000 | V11: Mesero (a) fijo (Mauricio) | W11: 25000 | X11: 30000 | Y11: =+(W11*W3)+(X11*X3) -> 845000 | AB11: Mesero (a) fijo (Mauricio) - Viernes, Sábado, Domingo | AD11: 37000 | AE11: =+(AD11*4) -> 148000
C12: Mesero (a) sabatino (Stefania) | E12: 0 | F12: 35000 | G12: =+(E12*0)+(F12*F3) -> 140000 | J12: Mesero (a) sabatino (Stefania) | K12: 0 | L12: 35000 | M12: =+(K12*0)+(L12*L3) -> 455000 | P12: Mesero (a) sabatino (Stefania) | Q12: 0 | R12: 35000 | S12: =+(Q12*0)+(R12*R3) -> 560000 | V12: Mesero (a) sabatino (Meseras) | W12: 0 | X12: 35000 | Y12: =+(W12*0)+(X12*X3) -> 490000 | AB12: Mesero (a) sabatino (Stefania) - Sábado y Domingo | AD12: 37000 | AE12: =(AD12*(AD3-2)) -> 481000
C13: Chef- Cocinero sabatino (Eduardo e Ingacio) | F13: 50000 | G13: =+(E13*8)+(F13*5) -> 250000 | J13: Chef- Cocinero sabatino (Eduardo e Ingacio) | K13: 30000 | L13: 60000 | M13: =+(K13*8)+(L13*5) -> 540000 | P13: Chef- Cocinero sabatino | Q13: 0 | R13: 0 | S13: =+(Q13*20)+(R13*10) -> 0 | V13: Chef- Cocinero sabatino | W13: 0 | X13: 0 | Y13: =+(W13*20)+(X13*10) -> 0 | AB13: Chef- Cocinero sabatino | AD13: 0 | AE13: =+(AC13*20)+(AD13*10) -> 0
C14: Banderero y domiciliario (Rolando y Manuel) | E14: 25000 | F14: 25000 | G14: =+(E14*E3)+(F14*F3) -> 225000 | J14: Banderero y domiciliario (Rolando y Manuel) | K14: 25000 | L14: 25000 | M14: =+(K14*K3)+(L14*L3) -> 775000 | P14: Banderero y domiciliario (Manuel) | Q14: 25000 | R14: 30000 | S14: =+(Q14*Q3)+(R14*R3) -> 830000 | V14: Banderero y domiciliario (Manuel) | W14: 25000 | X14: 25000 | Y14: =+(W14*W3)+(X14*X3) -> 775000 | AB14: Banderero y domiciliario (Manuel) - Sábado y Domingo | AD14: 28000 | AE14: 0 | AF14: 11: 30 a 4: pm
C15: Cajero | G15: =+(E15*20)+(F15*10) -> 0 | J15: Cajero | M15: =+(K15*20)+(L15*10) -> 0 | P15: Administrador | S15: =+(Q15*20)+(R15*10) -> 0 | V15: Administrador | Y15: =+(W15*20)+(X15*10) -> 0 | AB15: Administrador | AD15: 0 | AE15: =+(AC15*AC3)+(AD15*AD3) -> 0
C16: Parrillero | J16: Parrillero | K16: 0 | L16: 0 | M16: =+(K16*20)+(L16*10) -> 0 | P16: Parrillero | Q16: 0 | R16: 0 | S16: =+(Q16*20)+(R16*10) -> 0 | V16: Parrillero | W16: 0 | X16: 0 | Y16: =+(W16*20)+(X16*10) -> 0 | AB16: Parrillero | AC16: 0 | AD16: 33000 | AE16: =+(AC16*AC3)+(AD16*AD3) -> 495000
B17: Financieros | C17: ScotiaBank | D17: =2600000+67500+824000 -> 3491500 | I17: Financieros | J17: ScotiaBank | K17: =+M17/M3 -> 4129.0323 | M17: 128000 | O17: Financieros | P17: ScotiaBank | Q17: =+S17/S3 -> 0 | U17: Financieros | V17: ScotiaBank | W17: =+Y17/Y3 -> 0 | AA17: Financieros | AB17: ScotiaBank | AC17: =+AE17/AE3 -> 0
C18: Bancolombia (American Express) | D18: 1242548.5 | J18: Bancolombia (American Express) | K18: =+M18/M3 -> 3189.5161 | M18: 98875 | P18: Bancolombia (American Express) | Q18: =+S18/S3 -> 0 | V18: Bancolombia (American Express) | W18: =+Y18/Y3 -> 0 | AB18: Bancolombia (American Express) | AC18: =+AE18/AE3 -> 0
C19: Bancolombia (Visa) | D19: 3737029.6 | J19: Bancolombia (Visa) | K19: =+M19/M3 -> 17758.129 | M19: 550502 | P19: Bancolombia (Visa) | Q19: =+S19/S3 -> 0 | V19: Bancolombia (Visa) | W19: =+Y19/Y3 -> 0 | AB19: Bancolombia (Visa) | AC19: =+AE19/AE3 -> 0
C20: Banco Hector (cuantos meses) | E20: =+G20/30 -> 0 | G20: 0 | J20: Banco Hector (cuantos meses) | K20: =+M20/M3 -> 0 | P20: Banco Hector (cuantos meses) | Q20: =+S20/S3 -> 0 | V20: Banco Hector (cuantos meses) | W20: =+Y20/Y3 -> 19354.839 | Y20: 600000 | AB20: Banco Hector (cuantos meses)
C22: Gastos | E22: Lunes a Jueves | F22: Fines de Semana | G22: Mes | J22: Gastos | K22: Lunes a Jueves | L22: Fines de Semana | M22: Mes | P22: Gastos | Q22: Lunes a Jueves | R22: Fines de Semana | S22: Mes | V22: Gastos | W22: Lunes a Jueves | X22: Fines de Semana | Y22: Mes | AB22: Gastos | AC22: Lunes a Jueves | AD22: Fines de Semana | AE22: Mes
C23: Arriendo | E23: =+E4 -> 166666.67 | F23: =+E4 -> 166666.67 | G23: =+G4 -> 1500000 | J23: Arriendo | K23: =+K4 -> 80645.161 | L23: =+K4 -> 80645.161 | M23: =+M4 -> 2500000 | P23: Arriendo | Q23: =+Q4 -> 83333.333 | R23: =+Q4 -> 83333.333 | S23: =+S4 -> 2500000 | V23: Arriendo | W23: =+W4 -> 80645.161 | X23: =+W4 -> 80645.161 | Y23: =(((Y4/31)*22)/31)*22 -> 1259105.1 | AB23: Arriendo | AC23: =+AC4 -> 80645.161 | AD23: =+AC4 -> 80645.161 | AE23: =(((AE4/31)*22)/31)*22 -> 1259105.1
C24: Servicios | E24: 0 | F24: 0 | G24: 0 | J24: Servicios | K24: =+SUM(K5:L7) -> 25806.452 | L24: =+SUM(K5:L8) -> 25806.452 | M24: =+SUM(M5:M8) -> 800000 | P24: Servicios | Q24: =+SUM(Q5:R7) -> 26666.667 | R24: =+SUM(Q5:R8) -> 26666.667 | S24: =+SUM(S5:S8) -> 800000 | V24: Servicios | W24: =+SUM(W5:X8) -> 26000 | X24: =+SUM(X5:Y8) -> 780000 | Y24: =((+SUM(Y5:Z8))/31)*22 -> 553548.39 | AB24: Servicios | AC24: =+SUM(AC5:AC8) -> 0 | AD24: =+SUM(AD5:AD8) -> 26000 | AE24: =+SUM(AE5:AE8) -> 780000
C25: Nomina | E25: =+SUM(E9:E14) -> 110000 | F25: =+SUM(F9:F14) -> 205000 | G25: =+SUM(G9:G14) -> 1420000 | J25: Nomina | K25: =+SUM(K9:K14) -> 140000 | L25: =+SUM(L9:L14) -> 215000 | M25: =+SUM(M9:M14) -> 4535000 | P25: Nomina | Q25: =+SUM(Q9:Q14) -> 110000 | R25: =+SUM(R9:R14) -> 160000 | S25: =+SUM(S9:S14) -> 4100000 | V25: Nomina | W25: =+SUM(W9:W14) -> 85000 | X25: =+SUM(X9:X14) -> 160000 | Y25: =((+SUM(Y9:Y14))/31)*22 -> 2615161.3 | AB25: Nomina | AC25: =+SUM(AC9:AC14) -> 0 | AD25: =+SUM(AD9:AD14) -> 139000 | AE25: =((+SUM(AE9:AE14))/31)*22 -> 735225.81
C26: Financieros | E26: 0 | F26: 0 | G26: 0 | J26: Financieros | K26: =+SUM(K17:L20) -> 25076.677 | L26: =+SUM(K17:L20) -> 25076.677 | M26: =+SUM(M17:M20) -> 777377 | P26: Financieros | Q26: =+SUM(Q17:R20) -> 0 | R26: =+SUM(Q17:R20) -> 0 | S26: =+SUM(S17:S20) -> 0 | V26: Financieros | W26: =+SUM(W17:X20) -> 19354.839 | X26: =+SUM(W17:X20) -> 19354.839 | Y26: =((+SUM(Y17:Y20))/31)*22 -> 425806.45 | AB26: Financieros | AC26: =+SUM(AC17:AD20) -> 0 | AD26: =+SUM(AC17:AD20) -> 0 | AE26: =((+SUM(AE17:AE20))/31)*22 -> 0
C27: Total gastos | E27: =+SUM(E4:F8,E17:F20,E9:E16) -> 276666.67 | F27: =+SUM(E4:F8,E17:F20,F9:F16) -> 371666.67 | G27: =+SUM(G4:G20) -> 2920000 | J27: Total gastos | K27: =+SUM(K4:L8,K17:L20,K9:K16) -> 271528.29 | L27: =+SUM(K4:L8,K17:L20,L9:L16) -> 346528.29 | M27: =+SUM(M4:M20) -> 8612377 | P27: Total gastos | Q27: =+SUM(Q4:R8,Q17:R20,Q9:Q16) -> 220000 | R27: =+SUM(Q4:R8,Q17:R20,R9:R16) -> 270000 | S27: =+SUM(S4:S20) -> 7400000 | V27: Total gastos | W27: =+SUM(W4:X8,W17:X20,W9:W16) -> 211000 | X27: =+SUM(W4:X8,W17:X20,X9:X16) -> 286000 | Y27: =((+SUM(Y4:Y20))/31)*31 -> 7565000 | AB27: Total gastos | AC27: =+SUM(AC4:AD8,AC17:AD20,AC9:AC16) -> 106645.16 | AD27: =+SUM(AC4:AD8,AC17:AD20,AD9:AD16) -> 278645.16 | AE27: =((+SUM(AE4:AE20))/31)*22 -> 3414258.1
C29: Ventas | E29: Lunes a Jueves | F29: Fines de Semana | G29: Mes | J29: Ventas | K29: Lunes a Jueves | L29: Fines de Semana | M29: Mes | P29: Ventas | Q29: Lunes a Jueves | R29: Fines de Semana | S29: Mes | V29: Ventas | W29: Lunes a Jueves | X29: Fines de Semana | Y29: Mes | AB29: Ventas | AC29: Lunes a Jueves | AD29: Fines de Semana | AE29: Mes
B30: 0.6 | C30: Costo de mecancia | E30: =+E32*$B$30 -> 174325.2 | F30: =+F32*$B$30 -> 390375 | G30: =+G32*$B$30 -> 2433126 | J30: Costo de mecancia | K30: =+K32*$B$30 -> 189606.67 | L30: =+L32*$B$30 -> 538306.15 | M30: =+M32*$B$30 -> 10410900 | P30: Costo de mecancia | Q30: =+Q32*$B$30 -> 167914.29 | R30: =+R32*$B$30 -> 481308.75 | S30: =+S32*$B$30 -> 10051740 | V30: Costo de mecancia | W30: =+W32*$B$30 -> 126748 | X30: =+X32*$B$30 -> 396637.5 | Y30: =+Y32*$B$30 -> 8247420 | AB30: Costo de mecancia | AC30: 0 | AD30: =+AD32*$B$30 -> 396637.5 | AE30: =+AE32*$B$30 -> 5949562.5
B31: 0.4 | C31: Ganancia mercancia para pagar gastos | E31: =+E32*$B$31 -> 116216.8 | F31: =+F32*$B$31 -> 260250 | G31: =+G32*$B$31 -> 1622084 | J31: Ganancia mercancia para pagar gastos | K31: =+K32*$B$31 -> 126404.44 | L31: =+L32*$B$31 -> 358870.77 | M31: =+M32*$B$31 -> 6940600 | P31: Ganancia mercancia para pagar gastos | Q31: =+Q32*$B$31 -> 111942.86 | R31: =+R32*$B$31 -> 320872.5 | S31: =+S32*$B$31 -> 6701160 | V31: Ganancia mercancia para pagar gastos | W31: =+W32*$B$31 -> 84498.667 | X31: =+X32*$B$31 -> 264425 | Y31: =+Y32*$B$31 -> 5498280 | AB31: Ganancia mercancia para pagar gastos | AC31: 0 | AD31: =+AD32*$B$31 -> 264425 | AE31: =+AE32*$B$31 -> 3966375
B32: 1 | C32: Total venta | E32: =+AVERAGE('Anàlisis de ingreso'!C9:C12,'Anàlisis de ingreso'!D9) -> 290542 | F32: =+AVERAGE('Anàlisis de ingreso'!B15,'Anàlisis de ingreso'!C13:C15) -> 650625 | G32: 4055210 | J32: Total venta | K32: =+AVERAGE('Anàlisis de ingreso'!D10:D12,'Anàlisis de ingreso'!E9:E12,'Anàlisis de ingreso'!F10:F12,'Anàlisis de ingreso'!G9:G12,'Anàlisis de ingreso'!H9:H12) -> 316011.11 | L32: =+AVERAGE('Anàlisis de ingreso'!D13:G15,'Anàlisis de ingreso'!F9) -> 897176.92 | M32: 17351500 | P32: Total venta | Q32: =+AVERAGE('Anàlisis de ingreso'!I10:L12,'Anàlisis de ingreso'!L9,'Anàlisis de ingreso'!K9) -> 279857.14 | R32: =+AVERAGE('Anàlisis de ingreso'!H13:K15,'Anàlisis de ingreso'!L13:L14,'Anàlisis de ingreso'!I9:J9) -> 802181.25 | S32: 16752900 | V32: Total venta | W32: =+AVERAGE('Anàlisis de ingreso'!M9:O12,'Anàlisis de ingreso'!P12,'Anàlisis de ingreso'!P9,'Anàlisis de ingreso'!Q9) -> 211246.67 | X32: =+AVERAGE('Anàlisis de ingreso'!L15,'Anàlisis de ingreso'!M13:P15,'Anàlisis de ingreso'!P11,'Anàlisis de ingreso'!P10,'Anàlisis de ingreso'!Q10) -> 661062.5 | Y32: 13745700 | AB32: Total venta | AC32: 0 | AD32: =+X32 -> 661062.5 | AE32: =+AD32*AD3 -> 9915937.5
Z33: =+Y30/31 -> 266045.81
F34: Pérdida/Ganancia mensual | G34: =+G31-G27 -> -1297916 | L34: Pérdida/Ganancia mensual | M34: =+M31-M27 -> -1671777 | R34: Pérdida/Ganancia mensual | S34: =+S31-S27 -> -698840 | X34: Pérdida/Ganancia mensual | Y34: =+Y31-Y27 -> -2066720 | AD34: Pérdida/Ganancia mensual | AE34: =+AE31-AE27 -> 552116.94
G35: 0 | L35: Prestamo Hector | M35: 0 | R35: Prestamo Hector | S35: 0 | X35: Prestamo Hector | Y35: 0 | AD35: Prestamo Hector | AE35: 0
G36: =+SUM(G34:G35) -> -1297916 | M36: =+SUM(M34:M35) -> -1671777 | S36: =+SUM(S34:S35) -> -698840 | Y36: =+SUM(Y34:Y35) -> -2066720 | AE36: =+SUM(AE34:AE35) -> 552116.94
E39: Pérdida acumulada sin abrir los días hábiles | F39: =+E23*E3 -> 833333.33 | K39: Pérdida acumulada sin abrir los días hábiles | L39: =+K23*K3 -> 1451612.9 | Q39: Pérdida acumulada sin abrir los días hábiles | R39: =+Q23*Q3 -> 1166666.7 | W39: Pérdida acumulada sin abrir los días hábiles | X39: =+W23*W3 -> 1370967.7
E40: Pérdida acumulada abriendo los días hábiles | F40: =(E31-E27)*E3 -> -802249.33 | K40: Pérdida acumulada abriendo los días hábiles | L40: =(K31-K27)*K3 -> -2612229.2 | Q40: Pérdida acumulada abriendo los días hábiles | R40: =(Q31-Q27)*Q3 -> -1512800 | W40: Pérdida acumulada abriendo los días hábiles | X40: =(W31-W27)*W3 -> -2150522.7
F41: =+F39+F40 -> 31084 | L41: =+L39+L40 -> -1160616.3 | R41: =+R39+R40 -> -346133.33 | X41: =+X39+X40 -> -779554.92
L43: Optimo | M43: =+M36-L41 -> -511160.68 | R43: Optimo | S43: =+S36-R41 -> -352706.67 | X43: Optimo | Y43: =+Y36-X41 -> -1287165.1

Sheet Forecast Mes
M1: Enero
M2: Nomina | N2: =+SUM(OPEX!O9:O16) -> 0 | O2: =+N2-A2 -> 0 | P2: =+N2/A2-1 -> #DIV/0!
M3: Arriendo | N3: =OPEX!$AE$4 -> 2500000 | O3: =+N3-A3 -> 2500000 | P3: =+N3/A3-1 -> #DIV/0!
M4: Financieros | N4: =+SUM(OPEX!O17:O20) -> 0 | O4: =+N4-A4 -> 0 | P4: =+N4/A4-1 -> #DIV/0!
M5: Servicios | N5: =+SUM(OPEX!O5:O8) -> 0 | O5: =+N5-A9 -> #VALUE! | P5: =+N5/A9-1 -> #VALUE!
N6: =+SUM(N2:N5) -> 2500000 | O6: =+N6-A11 -> 2456169 | P6: =+N6/A11-1 -> 56.037257
A9: Fecha | B9: Dia de la semana | C9: Rentabilidad para cubrir costos fijos | D9: Costo mercancia | E9: Budget ventas | F9: Costo mercancia | G9: Ventas | J9: NOMINA | L9: ARRIENDO | N9: FINANCIERO | P9: EFECTIVO | Q9: SALDO
J10: CANCELADO | K10: POR PAGAR | L10: CANCELADO | M10: POR PAGAR | N10: CANCELADO | O10: POR PAGAR
A11: 43831 | B11: =+TEXT(A11,"dddd") -> miércoles | C11: =+D11*60% -> 237982.5 | D11: =+E11*60% -> 396637.5 | E11: =OPEX!$AD$32 -> 661062.5 | F11: =+G11*60% -> 396637.5 | G11: =OPEX!$AD$32 -> 661062.5 | J11: 0 | M11: =$N$3/31 -> 80645.161 | P11: =+E11-SUM(J11,L11,N11) -> 661062.5 | Q11: =+J11-SUM(K11:O11) -> -80645.161
A12: =+A11+1 -> 43832 | B12: =+TEXT(A12,"dddd") -> jueves | C12: =+D12*60% -> 0 | D12: =+E12*60% -> 0 | F12: =+G12*60% -> 0 | M12: =$N$3/31 -> 80645.161 | O12: 0 | P12: =+E12-SUM(J12:O12) -> -80645.161 | Q12: =+E12-SUM(J12:O12)+Q11 -> -161290.32
A13: =+A12+1 -> 43833 | B13: =+TEXT(A13,"dddd") -> viernes | C13: =+D13*60% -> 237982.5 | D13: =+E13*60% -> 396637.5 | E13: =OPEX!$AD$32 -> 661062.5 | F13: =+G13*60% -> 396637.5 | G13: =OPEX!$AD$32 -> 661062.5 | M13: =$N$3/31 -> 80645.161 | P13: =+E13-SUM(J13:O13) -> 580417.34 | Q13: =+E13-SUM(J13:O13)+Q12 -> 419127.02
A14: =+A13+1 -> 43834 | B14: =+TEXT(A14,"dddd") -> sábado | C14: =+D14*60% -> 237982.5 | D14: =+E14*60% -> 396637.5 | E14: =OPEX!$AD$32 -> 661062.5 | F14: =+G14*60% -> 396637.5 | G14: =OPEX!$AD$32 -> 661062.5 | M14: =$N$3/31 -> 80645.161 | P14: =+E14-SUM(J14:O14) -> 580417.34 | Q14: =+E14-SUM(J14:O14)+Q13 -> 999544.35
A15: =+A14+1 -> 43835 | B15: =+TEXT(A15,"dddd") -> domingo | C15: =+D15*60% -> 237982.5 | D15: =+E15*60% -> 396637.5 | E15: =OPEX!$AD$32 -> 661062.5 | F15: =+G15*60% -> 396637.5 | G15: =OPEX!$AD$32 -> 661062.5 | M15: =$N$3/31 -> 80645.161 | P15: =+E15-SUM(J15:O15) -> 580417.34 | Q15: =+E15-SUM(J15:O15)+Q14 -> 1579961.7
A16: =+A15+1 -> 43836 | B16: =+TEXT(A16,"dddd") -> lunes | C16: =+D16*60% -> 237982.5 | D16: =+E16*60% -> 396637.5 | E16: =OPEX!$AD$32 -> 661062.5 | F16: =+G16*60% -> 396637.5 | G16: =OPEX!$AD$32 -> 661062.5 | M16: =$N$3/31 -> 80645.161 | P16: =+E16-SUM(J16:O16) -> 580417.34 | Q16: =+E16-SUM(J16:O16)+Q15 -> 2160379
A17: =+A16+1 -> 43837 | B17: =+TEXT(A17,"dddd") -> martes | C17: =+D17*60% -> 0 | D17: =+E17*60% -> 0 | F17: =+G17*60% -> 0 | M17: =$N$3/31 -> 80645.161 | P17: =+E17-SUM(J17:O17) -> -80645.161 | Q17: =+E17-SUM(J17:O17)+Q16 -> 2079733.9
A18: =+A17+1 -> 43838 | B18: =+TEXT(A18,"dddd") -> miércoles | C18: =+D18*60% -> 0 | D18: =+E18*60% -> 0 | F18: =+G18*60% -> 0 | J18: 0 | M18: =$N$3/31 -> 80645.161 | P18: =+E18-SUM(J18:O18) -> -80645.161 | Q18: =+E18-SUM(J18:O18)+Q17 -> 1999088.7
A19: =+A18+1 -> 43839 | B19: =+TEXT(A19,"dddd") -> jueves | C19: =+D19*60% -> 0 | D19: =+E19*60% -> 0 | F19: =+G19*60% -> 0 | J19: 0 | M19: =$N$3/31 -> 80645.161 | P19: =+E19-SUM(J19:O19) -> -80645.161 | Q19: =+E19-SUM(J19:O19)+Q18 -> 1918443.5
A20: =+A19+1 -> 43840 | B20: =+TEXT(A20,"dddd") -> viernes | C20: =+D20*60% -> 237982.5 | D20: =+E20*60% -> 396637.5 | E20: =OPEX!$AD$32 -> 661062.5 | F20: =+G20*60% -> 396637.5 | G20: =OPEX!$AD$32 -> 661062.5 | M20: =$N$3/31 -> 80645.161 | P20: =+E20-SUM(J20:O20) -> 580417.34 | Q20: =+E20-SUM(J20:O20)+Q19 -> 2498860.9
A21: =+A20+1 -> 43841 | B21: =+TEXT(A21,"dddd") -> sábado | C21: =+D21*60% -> 237982.5 | D21: =+E21*60% -> 396637.5 | E21: =OPEX!$AD$32 -> 661062.5 | F21: =+G21*60% -> 396637.5 | G21: =OPEX!$AD$32 -> 661062.5 | M21: =$N$3/31 -> 80645.161 | P21: =+E21-SUM(J21:O21) -> 580417.34 | Q21: =+E21-SUM(J21:O21)+Q20 -> 3079278.2
A22: =+A21+1 -> 43842 | B22: =+TEXT(A22,"dddd") -> domingo | C22: =+D22*60% -> 237982.5 | D22: =+E22*60% -> 396637.5 | E22: =OPEX!$AD$32 -> 661062.5 | F22: =+G22*60% -> 396637.5 | G22: =OPEX!$AD$32 -> 661062.5 | M22: =$N$3/31 -> 80645.161 | P22: =+E22-SUM(J22:O22) -> 580417.34 | Q22: =+E22-SUM(J22:O22)+Q21 -> 3659695.6
A23: =+A22+1 -> 43843 | B23: =+TEXT(A23,"dddd") -> lunes | C23: =+D23*60% -> 0 | D23: =+E23*60% -> 0 | F23: =+G23*60% -> 0 | M23: =$N$3/31 -> 80645.161 | P23: =+E23-SUM(J23:O23) -> -80645.161 | Q23: =+E23-SUM(J23:O23)+Q22 -> 3579050.4
A24: =+A23+1 -> 43844 | B24: =+TEXT(A24,"dddd") -> martes | C24: =+D24*60% -> 0 | D24: =+E24*60% -> 0 | F24: =+G24*60% -> 0 | M24: =$N$3/31 -> 80645.161 | P24: =+E24-SUM(J24:O24) -> -80645.161 | Q24: =+E24-SUM(J24:O24)+Q23 -> 3498405.2
A25: =+A24+1 -> 43845 | B25: =+TEXT(A25,"dddd") -> miércoles | C25: =+D25*60% -> 0 | D25: =+E25*60% -> 0 | F25: =+G25*60% -> 0 | M25: =$N$3/31 -> 80645.161 | P25: =+E25-SUM(J25:O25) -> -80645.161 | Q25: =+E25-SUM(J25:O25)+Q24 -> 3417760.1
A26: =+A25+1 -> 43846 | B26: =+TEXT(A26,"dddd") -> jueves | C26: =+D26*60% -> 0 | D26: =+E26*60% -> 0 | F26: =+G26*60% -> 0 | M26: =$N$3/31 -> 80645.161 | P26: =+E26-SUM(J26:O26) -> -80645.161 | Q26: =+E26-SUM(J26:O26)+Q25 -> 3337114.9
A27: =+A26+1 -> 43847 | B27: =+TEXT(A27,"dddd") -> viernes | C27: =+D27*60% -> 237982.5 | D27: =+E27*60% -> 396637.5 | E27: =OPEX!$AD$32 -> 661062.5 | F27: =+G27*60% -> 396637.5 | G27: =OPEX!$AD$32 -> 661062.5 | M27: =$N$3/31 -> 80645.161 | P27: =+E27-SUM(J27:O27) -> 580417.34 | Q27: =+E27-SUM(J27:O27)+Q26 -> 3917532.3
A28: =+A27+1 -> 43848 | B28: =+TEXT(A28,"dddd") -> sábado | C28: =+D28*60% -> 237982.5 | D28: =+E28*60% -> 396637.5 | E28: =OPEX!$AD$32 -> 661062.5 | F28: =+G28*60% -> 396637.5 | G28: =OPEX!$AD$32 -> 661062.5 | M28: =$N$3/31 -> 80645.161 | P28: =+E28-SUM(J28:O28) -> 580417.34 | Q28: =+E28-SUM(J28:O28)+Q27 -> 4497949.6
A29: =+A28+1 -> 43849 | B29: =+TEXT(A29,"dddd") -> domingo | C29: =+D29*60% -> 237982.5 | D29: =+E29*60% -> 396637.5 | E29: =OPEX!$AD$32 -> 661062.5 | F29: =+G29*60% -> 396637.5 | G29: =OPEX!$AD$32 -> 661062.5 | M29: =$N$3/31 -> 80645.161 | P29: =+E29-SUM(J29:O29) -> 580417.34 | Q29: =+E29-SUM(J29:O29)+Q28 -> 5078366.9
A30: =+A29+1 -> 43850 | B30: =+TEXT(A30,"dddd") -> lunes | C30: =+D30*60% -> 0 | D30: =+E30*60% -> 0 | F30: =+G30*60% -> 0 | M30: =$N$3/31 -> 80645.161 | P30: =+E30-J30-L30-N30 -> 0 | Q30: =+E30-SUM(J30:O30)+Q29 -> 4997721.8
A31: =+A30+1 -> 43851 | B31: =+TEXT(A31,"dddd") -> martes | C31: =+D31*60% -> 0 | D31: =+E31*60% -> 0 | F31: =+G31*60% -> 0 | M31: =$N$3/31 -> 80645.161 | Q31: =+E31-SUM(J31:O31)+Q30 -> 4917076.6
A32: =+A31+1 -> 43852 | B32: =+TEXT(A32,"dddd") -> miércoles | C32: =+D32*60% -> 0 | D32: =+E32*60% -> 0 | F32: =+G32*60% -> 0 | M32: =$N$3/31 -> 80645.161 | Q32: =+E32-SUM(J32:O32)+Q31 -> 4836431.5
A33: =+A32+1 -> 43853 | B33: =+TEXT(A33,"dddd") -> jueves | C33: =+D33*60% -> 0 | D33: =+E33*60% -> 0 | F33: =+G33*60% -> 0 | M33: =$N$3/31 -> 80645.161 | Q33: =+E33-SUM(J33:O33)+Q32 -> 4755786.3
A34: =+A33+1 -> 43854 | B34: =+TEXT(A34,"dddd") -> viernes | C34: =+D34*60% -> 237982.5 | D34: =+E34*60% -> 396637.5 | E34: =OPEX!$AD$32 -> 661062.5 | F34: =+G34*60% -> 396637.5 | G34: =OPEX!$AD$32 -> 661062.5 | M34: =$N$3/31 -> 80645.161 | Q34: =+E34-SUM(J34:O34)+Q33 -> 5336203.6
A35: =+A34+1 -> 43855 | B35: =+TEXT(A35,"dddd") -> sábado | C35: =+D35*60% -> 237982.5 | D35: =+E35*60% -> 396637.5 | E35: =OPEX!$AD$32 -> 661062.5 | F35: =+G35*60% -> 396637.5 | G35: =OPEX!$AD$32 -> 661062.5 | M35: =$N$3/31 -> 80645.161 | Q35: =+E35-SUM(J35:O35)+Q34 -> 5916621
A36: =+A35+1 -> 43856 | B36: =+TEXT(A36,"dddd") -> domingo | C36: =+D36*60% -> 237982.5 | D36: =+E36*60% -> 396637.5 | E36: =OPEX!$AD$32 -> 661062.5 | F36: =+G36*60% -> 396637.5 | G36: =OPEX!$AD$32 -> 661062.5 | M36: =$N$3/31 -> 80645.161 | Q36: =+E36-SUM(J36:O36)+Q35 -> 6497038.3
A37: =+A36+1 -> 43857 | B37: =+TEXT(A37,"dddd") -> lunes | C37: =+D37*60% -> 0 | D37: =+E37*60% -> 0 | F37: =+G37*60% -> 0 | M37: =$N$3/31 -> 80645.161 | Q37: =+E37-SUM(J37:O37)+Q36 -> 6416393.1
A38: =+A37+1 -> 43858 | B38: =+TEXT(A38,"dddd") -> martes | C38: =+D38*60% -> 0 | D38: =+E38*60% -> 0 | F38: =+G38*60% -> 0 | M38: =$N$3/31 -> 80645.161 | Q38: =+E38-SUM(J38:O38)+Q37 -> 6335748
A39: =+A38+1 -> 43859 | B39: =+TEXT(A39,"dddd") -> miércoles | C39: =+D39*60% -> 0 | D39: =+E39*60% -> 0 | F39: =+G39*60% -> 0 | M39: =$N$3/31 -> 80645.161 | Q39: =+E39-SUM(J39:O39)+Q38 -> 6255102.8
A40: =+A39+1 -> 43860 | B40: =+TEXT(A40,"dddd") -> jueves | C40: =+D40*60% -> 0 | D40: =+E40*60% -> 0 | F40: =+G40*60% -> 0 | M40: =$N$3/31 -> 80645.161 | Q40: =+E40-SUM(J40:O40)+Q39 -> 6174457.7
A41: =+A40+1 -> 43861 | B41: =+TEXT(A41,"dddd") -> viernes | C41: =+D41*60% -> 237982.5 | D41: =+E41*60% -> 396637.5 | E41: =OPEX!$AD$32 -> 661062.5 | F41: =+G41*60% -> 396637.5 | G41: =OPEX!$AD$32 -> 661062.5 | M41: =$N$3/31 -> 80645.161 | Q41: =+E41-SUM(J41:O41)+Q40 -> 6754875

Sheet PE
B1: Septiembre | F1: Octubre | J1: Noviembre | P1: Diciembre
B2: Nomina | C2: =+SUM(OPEX!G9:G16) -> 1420000 | F2: Nomina | G2: =+SUM(OPEX!M9:M16) -> 4535000 | J2: Nomina | K2: =+SUM(OPEX!S9:S16) -> 4100000 | L2: =+K2-G2 -> -435000 | M2: =+K2/G2-1 -> -0.095920617 | P2: Nomina | Q2: =+SUM(OPEX!Y9:Y16) -> 3685000 | R2: =+Q2-K2 -> -415000 | S2: =+Q2/K2-1 -> -0.10121951
B3: Arriendo | C3: =+OPEX!G4 -> 1500000 | F3: Arriendo | G3: =OPEX!$M$4 -> 2500000 | J3: Arriendo | K3: =OPEX!$M$4 -> 2500000 | L3: =+K3-G3 -> 0 | M3: =+K3/G3-1 -> 0 | P3: Arriendo | Q3: =+OPEX!Y4 -> 2500000 | R3: =+Q3-K3 -> 0 | S3: =+Q3/K3-1 -> 0
B4: Financieros | C4: =+SUM(OPEX!G17:G20) -> 0 | F4: Financieros | G4: =+SUM(OPEX!M17:M20) -> 777377 | J4: Financieros | K4: =+SUM(OPEX!S17:S20) -> 0 | L4: =+K4-G4 -> -777377 | M4: =+K4/G4-1 -> -1 | P4: Financieros | Q4: =+SUM(OPEX!Y17:Y20) -> 600000 | R4: =+Q4-K4 -> 600000 | S4: =+Q4/K4-1 -> #DIV/0!
B5: Servicios | C5: =+SUM(OPEX!G5:G8) -> 0 | F5: Servicios | G5: =+SUM(OPEX!M5:M8) -> 800000 | J5: Servicios | K5: =+SUM(OPEX!S5:S7) -> 800000 | L5: =+K5-G5 -> 0 | M5: =+K5/G5-1 -> 0 | P5: Servicios | Q5: =+SUM(OPEX!Y5:Y8) -> 780000 | R5: =+Q5-K5 -> -20000 | S5: =+Q5/K5-1 -> -0.025
C6: =+SUM(C2:C5) -> 2920000 | G6: =+SUM(G2:G5) -> 8612377 | K6: =+SUM(K2:K5) -> 7400000 | L6: =+K6-G6 -> -1212377 | M6: =+K6/G6-1 -> -0.14077147 | Q6: =+SUM(Q2:Q5) -> 7565000 | R6: =+Q6-K6 -> 165000 | S6: =+Q6/K6-1 -> 0.022297297
A8: 0.4 | B8: Gasto Fijos Prom. Diario | C8: =+C6/OPEX!G3 -> 324444.44 | D8: =+C8/C$23 -> 0.54547567 | F8: Gasto Fijos Prom. Diario | G8: =+G6/OPEX!M3 -> 277818.61 | H8: =+G8/G$23 -> 0.45272836 | J8: Gasto Fijos Prom. Diario | K8: =+K6/OPEX!S3 -> 246666.67 | L8: =+K8/K$23 -> 0.42402649 | P8: Gasto Fijos Prom. Diario | Q8: =+Q6/OPEX!Y3 -> 244032.26 | R8: =+Q8/Q$23 -> 0.47842139
A22: 0.6 | B22: Costos Variables | C22: =+(B26*$A$22)/OPEX!G3 -> 270347.33 | D22: =+C22/C$23 -> 0.45452433 | F22: Costos Variables | G22: =+(F26*$A$22)/OPEX!M3 -> 335835.48 | H22: =+G22/G$23 -> 0.54727164 | J22: Costos Variables | K22: =+(J26*$A$22)/M26 -> 335058 | L22: =+K22/K$23 -> 0.57597351 | P22: Costos Variables | Q22: =+(P26*$A$22)/OPEX!Y3 -> 266045.81 | R22: =+Q22/Q$23 -> 0.52157861
B23: Punto de Eq. | C23: =+C8+C22 -> 594791.78 | F23: Punto de Eq. | G23: =+G8+G22 -> 613654.1 | J23: Punto de Eq. | K23: =+K8+K22 -> 581724.67 | P23: Punto de Eq. | Q23: =+Q8+Q22 -> 510078.06
A25: Mes | B25: Total Ventas | E25: Mes | F25: Total Ventas | I25: Mes | J25: Total Ventas | M25: Hoy | O25: Mes | P25: Total Ventas | S25: Hoy
A26: sep | B26: 4055210 | C26: =+B26/OPEX!G3 -> 450578.89 | E26: oct | F26: 17351500 | G26: =+F26/OPEX!M3 -> 559725.81 | I26: nov | J26: 16752900 | K26: =+J26/M26 -> 558430 | M26: 30 | O26: dic | P26: 13745700 | Q26: =+P26/S26 -> 443409.68 | S26: 31
B27: Ganacia /Pérdida | C27: =+C26-C23 -> -144212.89 | F27: Ganacia /Pérdida | G27: =+G26-G23 -> -53928.29 | J27: Ganacia /Pérdida | K27: =+K26-K23 -> -23294.667 | P27: Ganacia /Pérdida | Q27: =+Q26-Q23 -> -66668.387
B28: Saldo del mes | C28: =+C27*OPEX!G3 -> -1297916 | F28: Saldo del mes | G28: =+G27*OPEX!M3 -> -1671777 | J28: Saldo del mes | K28: =+K27*M26 -> -698840 | P28: Saldo del mes | Q28: =+Q27*S26 -> -2066720
A32: =+C32/B26 -> 0.6 | B32: Total costos variables | C32: =+C22*OPEX!G3 -> 2433126 | E32: =+G32/F26 -> 0.6 | F32: Total costos variables | G32: =+G22*OPEX!M3 -> 10410900 | I32: =+K32/J26 -> 0.6 | J32: Total costos variables | K32: =+K22*M26 -> 10051740 | O32: =+Q32/P26 -> 0.6 | P32: Total costos variables | Q32: =+Q22*S26 -> 8247420
B33: Total gastos fijos | C33: =+C6 -> 2920000 | F33: Total gastos fijos | G33: =+G6 -> 8612377 | J33: Total gastos fijos | K33: =+(K6/OPEX!S3)*M26 -> 7400000 | P33: Total gastos fijos | Q33: =+(Q6/OPEX!Y3)*S26 -> 7565000
B34: Total Gastos de Operación | C34: =+C32+C33 -> 5353126 | F34: Total Gastos de Operación | G34: =+G32+G33 -> 19023277 | J34: Total Gastos de Operación | K34: =+K32+K33 -> 17451740 | P34: Total Gastos de Operación | Q34: =+Q32+Q33 -> 15812420
B36: Ganancia / Pérdida | C36: =+B26-C34 -> -1297916 | F36: Ganancia / Pérdida | G36: =+F26-G34 -> -1671777 | J36: Ganancia / Pérdida | K36: =+J26-K34 -> -698840 | P36: Ganancia / Pérdida | Q36: =P26-Q34 -> -2066720

Sheet PE (2)
B1: Septiembre | F1: Octubre | J1: Noviembre | P1: Diciembre
B2: Nomina | C2: =+SUM(OPEX_deuda!G9:G17) -> 1380000 | F2: Nomina | G2: =+SUM(OPEX_deuda!O9:O17) -> 2375000 | J2: Nomina | K2: =+SUM(OPEX_deuda!W9:W17) -> 2310000 | L2: =+K2-G2 -> -65000 | M2: =+K2/G2-1 -> -0.027368421 | P2: Nomina | Q2: =+SUM(OPEX_deuda!AE9:AE17) -> 1990000 | R2: =+Q2-K2 -> -320000 | S2: =+Q2/K2-1 -> -0.13852814
B3: Arriendo | C3: =+OPEX_deuda!G4 -> 1500000 | F3: Arriendo | G3: =+OPEX_deuda!O4 -> 2500000 | J3: Arriendo | K3: =+OPEX_deuda!W4 -> 2500000 | L3: =+K3-G3 -> 0 | M3: =+K3/G3-1 -> 0 | P3: Arriendo | Q3: =+SUM(OPEX_deuda!AE4) -> 2500000 | R3: =+Q3-K3 -> 0 | S3: =+Q3/K3-1 -> 0
B4: Financieros | C4: =+SUM(OPEX!G17:G20) -> 0 | F4: Financieros | G4: =+SUM(OPEX_deuda!O18:O21) -> 777377 | J4: Financieros | K4: =+SUM(OPEX_deuda!W18:W21) -> 0 | L4: =+K4-G4 -> -777377 | M4: =+K4/G4-1 -> -1 | P4: Financieros | Q4: =+SUM(OPEX_deuda!AE18:AE21) -> 600000 | R4: =+Q4-K4 -> 600000 | S4: =+Q4/K4-1 -> #DIV/0!
B5: Servicios | C5: =+SUM(OPEX!G5:G8) -> 0 | F5: Servicios | G5: =+SUM(OPEX_deuda!O5:O8) -> 800000 | J5: Servicios | K5: =+SUM(OPEX_deuda!W5:W8) -> 780000 | L5: =+K5-G5 -> -20000 | M5: =+K5/G5-1 -> -0.025 | P5: Servicios | Q5: =+SUM(OPEX_deuda!AE5:AE7) -> 650000 | R5: =+Q5-K5 -> -130000 | S5: =+Q5/K5-1 -> -0.16666667
C6: =+SUM(C2:C5) -> 2880000 | G6: =+SUM(G2:G5) -> 6452377 | K6: =+SUM(K2:K5) -> 5590000 | L6: =+K6-G6 -> -862377 | M6: =+K6/G6-1 -> -0.13365261 | Q6: =+SUM(Q2:Q5) -> 5740000 | R6: =+Q6-K6 -> 150000 | S6: =+Q6/K6-1 -> 0.026833631
K7: =(K6/OPEX_deuda!W3)*M28 -> 5590000
A8: 0.4 | B8: Gasto Fijos Prom. Diario | C8: =+C6/OPEX_deuda!G3 -> 576000 | D8: =+C8/C$24 -> 0.64842958 | F8: Gasto Fijos Prom. Diario | G8: =+G6/OPEX_deuda!O3 -> 496336.69 | H8: =+G8/G$24 -> 0.4797179 | J8: Gasto Fijos Prom. Diario | K8: =+K7/M28 -> 349375 | P8: Gasto Fijos Prom. Diario | Q8: =+Q6/OPEX_deuda!AE3 -> 410000 | R8: =+Q8/Q$24 -> 0.50704026
A9: Mes | B9: Gasto Fijos Prom. Diario | C9: =+C6/OPEX!G3 -> 320000 | D9: =+C9/C$24 -> 0.36023866 | F9: Gasto Fijos Prom. Diario | G9: =+G6/OPEX!M3 -> 208141.19 | H9: =+G9/G$24 -> 0.20117202 | J9: Gasto Fijos Prom. Diario | K9: =+K6/OPEX!S3 -> 186333.33 | L9: =+K9/K$24 -> 0.2243132 | P9: Gasto Fijos Prom. Diario | Q9: =+Q6/OPEX!Y3 -> 185161.29 | R9: =+Q9/Q$24 -> 0.22898593
A23: 0.6 | B23: Costos Variables | C23: =+($A$23*B28)/OPEX_deuda!G3 -> 312300 | D23: =+C23/C$24 -> 0.35157042 | F23: Costos Variables | G23: =+($A$23*F28)/OPEX_deuda!O3 -> 538306.15 | H23: =+G23/G$24 -> 0.5202821 | J23: Costos Variables | K23: =+($A$23*J28)/M28 -> 481308.75 | L23: =+K23/K$24 -> 0.57941274 | P23: Costos Variables | Q23: =+($A$23*P28)/OPEX_deuda!AE3 -> 398614.29 | R23: =+Q23/Q$24 -> 0.49295974
B24: Punto de Eq. | C24: =+C8+C23 -> 888300 | F24: Punto de Eq. | G24: =+G8+G23 -> 1034642.8 | J24: Punto de Eq. | K24: =+K8+K23 -> 830683.75 | L24: Punto de Eq. | M24: =+K23+K9 -> 667642.08 | P24: Punto de Eq. | Q24: =+Q8+Q23 -> 808614.29
A25: Tipo Dìa | B25: Fds y Festivo | E25: Tipo Dìa | F25: Fds y Festivo | I25: Tipo Dìa | J25: Fds y Festivo | O25: Tipo Dìa | P25: Fds y Festivo
A27: Mes | B27: Total Ventas | E27: Mes | F27: Total Ventas | I27: Mes | J27: Total Ventas | M27: Hoy | O27: Mes | P27: Total Ventas | S27: Hoy
A28: sep | B28: 2602500 | C28: =+B28/OPEX_deuda!G3 -> 520500 | E28: oct | F28: 11663300 | G28: =+F28/OPEX_deuda!O3 -> 897176.92 | I28: nov | J28: 12834900 | K28: =+J28/OPEX_deuda!W3 -> 802181.25 | M28: 16 | O28: dic | P28: 9301000 | Q28: =+P28/S28 -> 930100 | S28: 10
B29: Ganacia /Pérdida | C29: =+C28-C24 -> -367800 | F29: Ganacia /Pérdida | G29: =+G28-G24 -> -137465.92 | J29: Ganacia /Pérdida | K29: =+K28-K24 -> -28502.5 | P29: Ganacia /Pérdida | Q29: =+Q28-Q24 -> 121485.71
B30: Saldo del mes | C30: =+C29*OPEX_deuda!G3 -> -1839000 | F30: Saldo del mes | G30: =+G29*OPEX_deuda!O3 -> -1787057 | J30: Saldo del mes | K30: =+K29*M28 -> -456040 | P30: Saldo del mes | Q30: =+Q29*S28 -> 1214857.1
B31: Costo de oportunidad | C31: =+C30-PE!C28 -> -541084 | F31: Costo de oportunidad | G31: =+G30-PE!G28 -> -115280 | J31: Costo de oportunidad | K31: =+K30-PE!K28 -> 242800 | P31: Costo de oportunidad | Q31: =+Q30-PE!Q28 -> 3281577.1
S32: Dias (mes)
A33: =+C33/B28 -> 0.6 | B33: Total costos variables | C33: =+C23*OPEX_deuda!G3 -> 1561500 | E33: =+G33/F28 -> 0.6 | F33: Total costos variables | G33: =+G23*OPEX_deuda!O3 -> 6997980 | I33: Mes | J33: Total costos variables | K33: =+K23*M28 -> 7700940 | M33: Dias (mes) | O33: Mes | P33: Total costos variables | Q33: =+Q23*S28 -> 3986142.9 | S33: =PE!$M$26 -> 30
B34: Total gastos fijos | C34: =+C6 -> 2880000 | F34: Total gastos fijos | G34: =+G6 -> 6452377 | I34: Mes | J34: Total gastos fijos | K34: =(K6/OPEX!S3)*M34 -> 5590000 | M34: =PE!$M$26 -> 30 | O34: Mes | P34: Total gastos fijos | Q34: =(Q6/OPEX!W3)*S34 -> 0
B35: Total Gastos de Operación | C35: =+C33+C34 -> 4441500 | F35: Total Gastos de Operación | G35: =+G33+G34 -> 13450357 | J35: Total Gastos de Operación | K35: =+K33+K34 -> 13290940 | P35: Total Gastos de Operación | Q35: =+Q33+Q34 -> 3986142.9
B37: Ganancia / Pérdida | C37: =+B28-C35 -> -1839000 | F37: Ganancia / Pérdida | G37: =+F28-G35 -> -1787057 | J37: Ganancia / Pérdida | K37: =+J28-K35 -> -456040 | P37: Ganancia / Pérdida | Q37: =+P28-Q35 -> 5314857.1

Sheet Profitability
D1: Mes | K1: sep | L1: oct | M1: nov | N1: TOTAL
D2: sep | E2: oct | F2: nov | J2: lunes | K2: =+SUMIFS($J$14:$J$83,$C$14:$C$83,K$1,$E$14:$E$83,$J2) -> -864373.56 | L2: =+SUMIFS($J$14:$J$83,$C$14:$C$83,L$1,$E$14:$E$83,$J2) -> -579116.39 | M2: =+SUMIFS($J$14:$J$83,$C$14:$C$83,M$1,$E$14:$E$83,$J2) -> -176898.67 | N2: =+SUM(K2:M2) -> -1620388.6
C3: INGRESOS | D3: 4055210 | E3: 17351500 | F3: 16752900 | J3: martes | K3: =+SUMIFS($J$14:$J$83,$C$14:$C$83,K$1,$E$14:$E$83,$J3) -> -201791.78 | L3: =+SUMIFS($J$14:$J$83,$C$14:$C$83,L$1,$E$14:$E$83,$J3) -> -1585170.5 | M3: =+SUMIFS($J$14:$J$83,$C$14:$C$83,M$1,$E$14:$E$83,$J3) -> -1390898.7 | N3: =+SUM(K3:M3) -> -3177860.9
B4: 0.4 | C4: Gastos Fijos y Variables | D4: =OPEX!G27 -> 2920000 | E4: =OPEX!M22 -> Mes | J4: miércoles | K4: =+SUMIFS($J$14:$J$83,$C$14:$C$83,K$1,$E$14:$E$83,$J4) -> -175291.78 | L4: =+SUMIFS($J$14:$J$83,$C$14:$C$83,L$1,$E$14:$E$83,$J4) -> -1440970.5 | M4: =+SUMIFS($J$14:$J$83,$C$14:$C$83,M$1,$E$14:$E$83,$J4) -> -1004898.7 | N4: =+SUM(K4:M4) -> -2621160.9
B5: 0.6 | C5: Costos Variables | D5: =OPEX!#REF! -> #REF! | E5: =OPEX!#REF! -> #REF! | J5: jueves | K5: =+SUMIFS($J$14:$J$83,$C$14:$C$83,K$1,$E$14:$E$83,$J5) -> -279791.78 | L5: =+SUMIFS($J$14:$J$83,$C$14:$C$83,L$1,$E$14:$E$83,$J5) -> -1743970.5 | M5: =+SUMIFS($J$14:$J$83,$C$14:$C$83,M$1,$E$14:$E$83,$J5) -> -1516898.7 | N5: =+SUM(K5:M5) -> -3540660.9
D6: =OPEX!#REF! -> #REF! | E6: =OPEX!#REF! -> #REF! | J6: viernes | K6: =+SUMIFS($J$14:$J$83,$C$14:$C$83,K$1,$E$14:$E$83,$J6) -> -173791.78 | L6: =+SUMIFS($J$14:$J$83,$C$14:$C$83,L$1,$E$14:$E$83,$J6) -> -42716.387 | M6: =+SUMIFS($J$14:$J$83,$C$14:$C$83,M$1,$E$14:$E$83,$J6) -> -1375623.3 | N6: =+SUM(K6:M6) -> -1592131.5
D7: =+D3-D6 -> #REF! | E7: =+E3-E6 -> #REF! | J7: sábado | K7: =+SUMIFS($J$14:$J$83,$C$14:$C$83,K$1,$E$14:$E$83,$J7) -> 356708.22 | L7: =+SUMIFS($J$14:$J$83,$C$14:$C$83,L$1,$E$14:$E$83,$J7) -> 795183.61 | M7: =+SUMIFS($J$14:$J$83,$C$14:$C$83,M$1,$E$14:$E$83,$J7) -> 1442376.7 | N7: =+SUM(K7:M7) -> 2594268.5
J8: domingo | K8: =+SUMIFS($J$14:$J$83,$C$14:$C$83,K$1,$E$14:$E$83,$J8) -> 40416.444 | L8: =+SUMIFS($J$14:$J$83,$C$14:$C$83,L$1,$E$14:$E$83,$J8) -> 2924983.6 | M8: =+SUMIFS($J$14:$J$83,$C$14:$C$83,M$1,$E$14:$E$83,$J8) -> 3324001.3 | N8: =+SUM(K8:M8) -> 6289401.4 | P8: 650000 | Q8: Prestamo Edwin
J9: TOTAL | K9: =+SUM(K2:K8) -> -1297916 | L9: =+SUM(L2:L8) -> -1671777 | M9: =+SUM(M2:M8) -> -698840 | N9: =+SUM(N2:N8) -> -3668533 | P9: 4800000 | Q9: Mercancia Hector
C10: sep | G10: =+SUMIF($C$14:$C$66,$C10,G$14:G$66) -> 2920000 | H10: =+SUMIF($C$14:$C$66,$C10,H$14:H$66) -> 2433126 | K10: =+K9-'Profitability (2-Mensualizado)'!K9 -> 541084 | L10: =+L9-'Profitability (2-Mensualizado)'!L9 -> 115280 | M10: =+M9-'Profitability (2-Mensualizado)'!M9 -> -242800 | N10: =+N9-'Profitability (2-Mensualizado)'!N9 -> 413564 | P10: =+P8+P9 -> 5450000
C11: oct | G11: =+SUMIF($C$14:$C$66,$C11,G$14:G$66) -> 8612377 | H11: =+SUMIF($C$14:$C$66,$C11,H$14:H$66) -> 10410900
C12: nov | G12: =+SUMIF($C$14:$C$66,$C12,G$14:G$66) -> 3206666.7 | H12: =+SUMIF($C$14:$C$66,$C12,H$14:H$66) -> 4355754
C13: Mes | D13: Dia | E13: Día de Semana | F13: INGRESOS TOTALES | G13: GASTOS FIJOS | H13: ESTIMACIÓN COSTO MATERIA PRIMA (COSTO VARIABLE) | I13: PRESUPUESTO DE VENTAS | J13: GAP | K13: Saldo actual | L13: Dìa de semanal | M13: Análisis gastos fijos | N13: Mes
C14: sep | D14: 22 | E14: domingo | F14: 572000 | G14: =PE!$C$8 -> 324444.44 | H14: =PE!$C$22 -> 270347.33 | I14: =+G14+H14 -> 594791.78 | J14: =+F14-I14 -> -22791.778 | K14: =+J14 -> -22791.778 | L14: =+E14 -> domingo | M14: =+F14-G14 -> 247555.56 | N14: =+C14 -> sep
C15: sep | D15: 23 | E15: lunes | F15: 142000 | G15: =PE!$C$8 -> 324444.44 | H15: =PE!$C$22 -> 270347.33 | I15: =+G15+H15 -> 594791.78 | J15: =+F15-I15 -> -452791.78 | K15: =+J15+K14 -> -475583.56 | L15: =+E15 -> lunes | M15: =+F15-G15 -> -182444.44 | N15: =+C15 -> sep
C16: sep | D16: 24 | E16: martes | F16: 393000 | G16: =PE!$C$8 -> 324444.44 | H16: =PE!$C$22 -> 270347.33 | I16: =+G16+H16 -> 594791.78 | J16: =+F16-I16 -> -201791.78 | K16: =+J16+K15 -> -677375.33 | L16: =+E16 -> martes | M16: =+F16-G16 -> 68555.556 | N16: =+C16 -> sep
C17: sep | D17: 25 | E17: miércoles | F17: 419500 | G17: =PE!$C$8 -> 324444.44 | H17: =PE!$C$22 -> 270347.33 | I17: =+G17+H17 -> 594791.78 | J17: =+F17-I17 -> -175291.78 | K17: =+J17+K16 -> -852667.11 | L17: =+E17 -> miércoles | M17: =+F17-G17 -> 95055.556 | N17: =+C17 -> sep
C18: sep | D18: 26 | E18: jueves | F18: 315000 | G18: =PE!$C$8 -> 324444.44 | H18: =PE!$C$22 -> 270347.33 | I18: =+G18+H18 -> 594791.78 | J18: =+F18-I18 -> -279791.78 | K18: =+J18+K17 -> -1132458.9 | L18: =+E18 -> jueves | M18: =+F18-G18 -> -9444.4444 | N18: =+C18 -> sep
C19: sep | D19: 27 | E19: viernes | F19: 421000 | G19: =PE!$C$8 -> 324444.44 | H19: =PE!$C$22 -> 270347.33 | I19: =+G19+H19 -> 594791.78 | J19: =+F19-I19 -> -173791.78 | K19: =+J19+K18 -> -1306250.7 | L19: =+E19 -> viernes | M19: =+F19-G19 -> 96555.556 | N19: =+C19 -> sep
C20: sep | D20: 28 | E20: sábado | F20: 951500 | G20: =PE!$C$8 -> 324444.44 | H20: =PE!$C$22 -> 270347.33 | I20: =+G20+H20 -> 594791.78 | J20: =+F20-I20 -> 356708.22 | K20: =+J20+K19 -> -949542.44 | L20: =+E20 -> sábado | M20: =+F20-G20 -> 627055.56 | N20: =+C20 -> sep
C21: sep | D21: 29 | E21: domingo | F21: 658000 | G21: =PE!$C$8 -> 324444.44 | H21: =PE!$C$22 -> 270347.33 | I21: =+G21+H21 -> 594791.78 | J21: =+F21-I21 -> 63208.222 | K21: =+J21+K20 -> -886334.22 | L21: =+E21 -> domingo | M21: =+F21-G21 -> 333555.56 | N21: =+C21 -> sep
C22: sep | D22: 30 | E22: lunes | F22: 183210 | G22: =PE!$C$8 -> 324444.44 | H22: =PE!$C$22 -> 270347.33 | I22: =+G22+H22 -> 594791.78 | J22: =+F22-I22 -> -411581.78 | K22: =+J22+K21 -> -1297916 | L22: =+E22 -> lunes | M22: =+F22-G22 -> -141234.44 | N22: =+C22 -> sep
C23: oct | D23: 1 | E23: martes | F23: 229800 | G23: =PE!$G$8 -> 277818.61 | H23: =PE!$G$22 -> 335835.48 | I23: =+G23+H23 -> 613654.1 | J23: =+F23-I23 -> -383854.1 | K23: =+J23+K22 -> -1681770.1 | L23: =+E23 -> martes | M23: =+F23-G23 -> -48018.613 | N23: =+C23 -> oct
C24: oct | D24: 2 | E24: miércoles | F24: 238000 | G24: =PE!$G$8 -> 277818.61 | H24: =PE!$G$22 -> 335835.48 | I24: =+G24+H24 -> 613654.1 | J24: =+F24-I24 -> -375654.1 | K24: =+J24+K23 -> -2057424.2 | L24: =+E24 -> miércoles | M24: =+F24-G24 -> -39818.613 | N24: =+C24 -> oct
C25: oct | D25: 3 | E25: jueves | F25: 238000 | G25: =PE!$G$8 -> 277818.61 | H25: =PE!$G$22 -> 335835.48 | I25: =+G25+H25 -> 613654.1 | J25: =+F25-I25 -> -375654.1 | K25: =+J25+K24 -> -2433078.3 | L25: =+E25 -> jueves | M25: =+F25-G25 -> -39818.613 | N25: =+C25 -> oct
C26: oct | D26: 4 | E26: viernes | F26: 420500 | G26: =PE!$G$8 -> 277818.61 | H26: =PE!$G$22 -> 335835.48 | I26: =+G26+H26 -> 613654.1 | J26: =+F26-I26 -> -193154.1 | K26: =+J26+K25 -> -2626232.4 | L26: =+E26 -> viernes | M26: =+F26-G26 -> 142681.39 | N26: =+C26 -> oct
C27: oct | D27: 5 | E27: sábado | F27: 1210300 | G27: =PE!$G$8 -> 277818.61 | H27: =PE!$G$22 -> 335835.48 | I27: =+G27+H27 -> 613654.1 | J27: =+F27-I27 -> 596645.9 | K27: =+J27+K26 -> -2029586.5 | L27: =+E27 -> sábado | M27: =+F27-G27 -> 932481.39 | N27: =+C27 -> oct
C28: oct | D28: 6 | E28: domingo | F28: 1345600 | G28: =PE!$G$8 -> 277818.61 | H28: =PE!$G$22 -> 335835.48 | I28: =+G28+H28 -> 613654.1 | J28: =+F28-I28 -> 731945.9 | K28: =+J28+K27 -> -1297640.6 | L28: =+E28 -> domingo | M28: =+F28-G28 -> 1067781.4 | N28: =+C28 -> oct
C29: oct | D29: 7 | E29: lunes | F29: 603500 | G29: =PE!$G$8 -> 277818.61 | H29: =PE!$G$22 -> 335835.48 | I29: =+G29+H29 -> 613654.1 | J29: =+F29-I29 -> -10154.097 | K29: =+J29+K28 -> -1307794.7 | L29: =+E29 -> lunes | M29: =+F29-G29 -> 325681.39 | N29: =+C29 -> oct
C30: oct | D30: 8 | E30: martes | F30: 426300 | G30: =PE!$G$8 -> 277818.61 | H30: =PE!$G$22 -> 335835.48 | I30: =+G30+H30 -> 613654.1 | J30: =+F30-I30 -> -187354.1 | K30: =+J30+K29 -> -1495148.8 | L30: =+E30 -> martes | M30: =+F30-G30 -> 148481.39 | N30: =+C30 -> oct
C31: oct | D31: 9 | E31: miércoles | F31: 134000 | G31: =PE!$G$8 -> 277818.61 | H31: =PE!$G$22 -> 335835.48 | I31: =+G31+H31 -> 613654.1 | J31: =+F31-I31 -> -479654.1 | K31: =+J31+K30 -> -1974802.9 | L31: =+E31 -> miércoles | M31: =+F31-G31 -> -143818.61 | N31: =+C31 -> oct
C32: oct | D32: 10 | E32: jueves | F32: 85500 | G32: =PE!$G$8 -> 277818.61 | H32: =PE!$G$22 -> 335835.48 | I32: =+G32+H32 -> 613654.1 | J32: =+F32-I32 -> -528154.1 | K32: =+J32+K31 -> -2502957 | L32: =+E32 -> jueves | M32: =+F32-G32 -> -192318.61 | N32: =+C32 -> oct
C33: oct | D33: 11 | E33: viernes | F33: 427900 | G33: =PE!$G$8 -> 277818.61 | H33: =PE!$G$22 -> 335835.48 | I33: =+G33+H33 -> 613654.1 | J33: =+F33-I33 -> -185754.1 | K33: =+J33+K32 -> -2688711.1 | L33: =+E33 -> viernes | M33: =+F33-G33 -> 150081.39 | N33: =+C33 -> oct
C34: oct | D34: 12 | E34: sábado | F34: 664500 | G34: =PE!$G$8 -> 277818.61 | H34: =PE!$G$22 -> 335835.48 | I34: =+G34+H34 -> 613654.1 | J34: =+F34-I34 -> 50845.903 | K34: =+J34+K33 -> -2637865.2 | L34: =+E34 -> sábado | M34: =+F34-G34 -> 386681.39 | N34: =+C34 -> oct
... C53: oct | D53: 31 | E53: jueves | F53: 370000 | G53: =PE!$G$8 -> 277818.61 | H53: =PE!$G$22 -> 335835.48 | I53: =+G53+H53 -> 613654.1 | J53: =+F53-I53 -> -243654.1 | K53: =+J53+K52 -> -2969693 | L53: =+E53 -> jueves | M53: =+F53-G53 -> 92181.387 | N53: =+C53 -> oct
C54: nov | D54: 1 | E54: viernes | F54: 370000 | G54: =PE!$K$8 -> 246666.67 | H54: =PE!$K$22 -> 335058 | I54: =+G54+H54 -> 581724.67 | J54: =+F54-I54 -> -211724.67 | K54: =+J54+K53 -> -3181417.7 | L54: =+E54 -> viernes | M54: =+F54-G54 -> 123333.33 | N54: =+C54 -> nov
C55: nov | D55: 2 | E55: sábado | F55: 500000 | G55: =PE!$K$8 -> 246666.67 | H55: =PE!$K$22 -> 335058 | I55: =+G55+H55 -> 581724.67 | J55: =+F55-I55 -> -81724.667 | K55: =+J55+K54 -> -3263142.3 | L55: =+E55 -> sábado | M55: =+F55-G55 -> 253333.33 | N55: =+C55 -> nov
C56: nov | D56: 3 | E56: domingo | F56: 1700000 | G56: =PE!$K$8 -> 246666.67 | H56: =PE!$K$22 -> 335058 | I56: =+G56+H56 -> 581724.67 | J56: =+F56-I56 -> 1118275.3 | K56: =+J56+K55 -> -2144867 | L56: =+E56 -> domingo | M56: =+F56-G56 -> 1453333.3 | N56: =+C56 -> nov
C57: nov | D57: 4 | E57: lunes | F57: 600000 | G57: =PE!$K$8 -> 246666.67 | H57: =PE!$K$22 -> 335058 | I57: =+G57+H57 -> 581724.67 | J57: =+F57-I57 -> 18275.333 | K57: =+J57+K56 -> -2126591.7 | L57: =+E57 -> lunes | M57: =+F57-G57 -> 353333.33 | N57: =+C57 -> nov
C58: nov | D58: 5 | E58: martes | F58: 194000 | G58: =PE!$K$8 -> 246666.67 | H58: =PE!$K$22 -> 335058 | I58: =+G58+H58 -> 581724.67 | J58: =+F58-I58 -> -387724.67 | K58: =+J58+K57 -> -2514316.3 | L58: =+E58 -> martes | M58: =+F58-G58 -> -52666.667 | N58: =+C58 -> nov
C59: nov | D59: 6 | E59: miércoles | F59: 627000 | G59: =PE!$K$8 -> 246666.67 | H59: =PE!$K$22 -> 335058 | I59: =+G59+H59 -> 581724.67 | J59: =+F59-I59 -> 45275.333 | K59: =+J59+K58 -> -2469041 | L59: =+E59 -> miércoles | M59: =+F59-G59 -> 380333.33 | N59: =+C59 -> nov
C60: nov | D60: 7 | E60: jueves | F60: 332500 | G60: =PE!$K$8 -> 246666.67 | H60: =PE!$K$22 -> 335058 | I60: =+G60+H60 -> 581724.67 | J60: =+F60-I60 -> -249224.67 | K60: =+J60+K59 -> -2718265.7 | L60: =+E60 -> jueves | M60: =+F60-G60 -> 85833.333 | N60: =+C60 -> nov
C61: nov | D61: 8 | E61: viernes | F61: 342000 | G61: =PE!$K$8 -> 246666.67 | H61: =PE!$K$22 -> 335058 | I61: =+G61+H61 -> 581724.67 | J61: =+F61-I61 -> -239724.67 | K61: =+J61+K60 -> -2957990.3 | L61: =+E61 -> viernes | M61: =+F61-G61 -> 95333.333 | N61: =+C61 -> nov
C62: nov | D62: 9 | E62: sábado | F62: 1552000 | G62: =PE!$K$8 -> 246666.67 | H62: =PE!$K$22 -> 335058 | I62: =+G62+H62 -> 581724.67 | J62: =+F62-I62 -> 970275.33 | K62: =+J62+K61 -> -1987715 | L62: =+E62 -> sábado | M62: =+F62-G62 -> 1305333.3 | N62: =+C62 -> nov
C63: nov | D63: 10 | E63: domingo | F63: 1690000 | G63: =PE!$K$8 -> 246666.67 | H63: =PE!$K$22 -> 335058 | I63: =+G63+H63 -> 581724.67 | J63: =+F63-I63 -> 1108275.3 | K63: =+J63+K62 -> -879439.67 | L63: =+E63 -> domingo | M63: =+F63-G63 -> 1443333.3 | N63: =+C63 -> nov
C64: nov | D64: 11 | E64: lunes | F64: 700000 | G64: =PE!$K$8 -> 246666.67 | H64: =PE!$K$22 -> 335058 | I64: =+G64+H64 -> 581724.67 | J64: =+F64-I64 -> 118275.33 | K64: =+J64+K63 -> -761164.33 | L64: =+E64 -> lunes | M64: =+F64-G64 -> 453333.33 | N64: =+C64 -> nov
C65: nov | D65: 12 | E65: martes | F65: 122000 | G65: =PE!$K$8 -> 246666.67 | H65: =PE!$K$22 -> 335058 | I65: =+G65+H65 -> 581724.67 | J65: =+F65-I65 -> -459724.67 | K65: =+J65+K64 -> -1220889 | L65: =+E65 -> martes | M65: =+F65-G65 -> -124666.67 | N65: =+C65 -> nov
... C83: nov | D83: 30 | E83: sábado | F83: 900000 | G83: =PE!$K$8 -> 246666.67 | H83: =PE!$K$22 -> 335058 | I83: =+G83+H83 -> 581724.67 | J83: =+F83-I83 -> 318275.33 | K83: =+J83+K82 -> -3668533 | L83: =+E83 -> sábado | M83: =+F83-G83 -> 653333.33 | N83: =+C83 -> nov

Sheet PE (3)
B1: Septiembre | F1: Octubre | J1: Noviembre | P1: Diciembre
B2: Nomina | C2: =+SUM('OPEX (3)'!G9:G17) -> 715000 | F2: Nomina | G2: =+SUM('OPEX (3)'!O9:O17) -> 1935000 | J2: Nomina | K2: =+SUM('OPEX (3)'!W9:W17) -> 1760000 | L2: =+K2-G2 -> -175000 | M2: =+K2/G2-1 -> -0.090439276 | P2: Nomina | Q2: =+SUM('OPEX (3)'!AE9:AE17) -> 1550000 | R2: =+Q2-K2 -> -210000 | S2: =+Q2/K2-1 -> -0.11931818
B3: Arriendo | C3: =+OPEX_deuda!G4 -> 1500000 | F3: Arriendo | G3: =+OPEX_deuda!O4 -> 2500000 | J3: Arriendo | K3: =+OPEX_deuda!W4 -> 2500000 | L3: =+K3-G3 -> 0 | M3: =+K3/G3-1 -> 0 | P3: Arriendo | Q3: =+SUM(OPEX_deuda!AE4) -> 2500000 | R3: =+Q3-K3 -> 0 | S3: =+Q3/K3-1 -> 0
B4: Financieros | C4: =+SUM(OPEX!G17:G20) -> 0 | F4: Financieros | G4: =+SUM(OPEX_deuda!O18:O21) -> 777377 | J4: Financieros | K4: =+SUM(OPEX_deuda!W18:W21) -> 0 | L4: =+K4-G4 -> -777377 | M4: =+K4/G4-1 -> -1 | P4: Financieros | Q4: =+SUM(OPEX_deuda!AE18:AE21) -> 600000 | R4: =+Q4-K4 -> 600000 | S4: =+Q4/K4-1 -> #DIV/0!
B5: Servicios | C5: =+SUM(OPEX!G5:G8) -> 0 | F5: Servicios | G5: =+SUM(OPEX_deuda!O5:O8) -> 800000 | J5: Servicios | K5: =+SUM(OPEX_deuda!W5:W8) -> 780000 | L5: =+K5-G5 -> -20000 | M5: =+K5/G5-1 -> -0.025 | P5: Servicios | Q5: =+SUM(OPEX_deuda!AE18:AE21) -> 600000 | R5: =+Q5-K5 -> -180000 | S5: =+Q5/K5-1 -> -0.23076923
C6: =+SUM(C2:C5) -> 2215000 | G6: =+SUM(G2:G5) -> 6012377 | K6: =+SUM(K2:K5) -> 5040000 | L6: =+K6-G6 -> -972377 | M6: =+K6/G6-1 -> -0.16172921 | Q6: =+SUM(Q2:Q5) -> 5250000 | R6: =+Q6-K6 -> 210000 | S6: =+Q6/K6-1 -> 0.041666667
A8: 0.4 | B8: Gasto Fijos Prom. Diario | C8: =+C6/'OPEX (3)'!G3 -> 738333.33 | D8: =+C8/C$23 -> 0.62856494 | F8: Gasto Fijos Prom. Diario | G8: =+G6/'OPEX (3)'!O3 -> 668041.89 | H8: =+G8/G$23 -> 0.51995712 | J8: Gasto Fijos Prom. Diario | K8: =+K6/'OPEX (3)'!W3 -> 458181.82 | L8: =+K8/K$23 -> 0.32109934 | P8: Gasto Fijos Prom. Diario | Q8: =+Q6/'OPEX (3)'!AE3 -> 525000 | R8: =+Q8/Q$23 -> 0.48607331
A22: 0.6 | B22: Costos Variables | C22: =(B28*$A$22)/'OPEX (3)'!G3 -> 436300 | D22: =+C22/C$23 -> 0.37143506 | F22: Costos Variables | G22: =(F28*$A$22)/'OPEX (3)'!O3 -> 616760 | H22: =+G22/G$23 -> 0.48004288 | J22: Costos Variables | K22: =(J28*$A$22)/M28 -> 968734.29 | L22: =+K22/K$23 -> 0.67890066 | P22: Costos Variables | Q22: =(P28*$A$22)/'OPEX (3)'!AE3 -> 555084 | R22: =+Q22/Q$23 -> 0.51392669
B23: Punto de Eq. | C23: =+C8+C22 -> 1174633.3 | F23: Punto de Eq. | G23: =+G8+G22 -> 1284801.9 | J23: Punto de Eq. | K23: =+K8+K22 -> 1426916.1 | P23: Punto de Eq. | Q23: =+Q22+Q8 -> 1080084
A24: Dia semanal | B24: (Varios elementos) | E24: Dia semanal | F24: (Varios elementos) | I24: Dia semanal | J24: (Varios elementos)
A25: Tipo Dìa | B25: Fds y Festivo | E25: Tipo Dìa | F25: Fds y Festivo | I25: Tipo Dìa | J25: Fds y Festivo
A27: Mes | B27: Total Ventas | E27: Mes | F27: Total Ventas | I27: Mes | J27: Total Ventas | M27: Hoy | O27: Mes | P27: Forescast
A28: sep | B28: 2181500 | C28: =+B28/'OPEX (3)'!G3 -> 727166.67 | E28: oct | F28: 9251400 | G28: =+F28/'OPEX (3)'!O3 -> 1027933.3 | I28: nov | J28: 11301900 | K28: =+J28/M28 -> 1614557.1 | M28: 7 | O28: nov | P28: =+F28 -> 9251400
B29: Ganacia /Pérdida | C29: =+C28-C23 -> -447466.67 | F29: Ganacia /Pérdida | G29: =+G28-G23 -> -256868.56 | J29: Ganacia /Pérdida | K29: =+K28-K23 -> 187641.04
B30: Saldo del mes | C30: =+C29*'OPEX (3)'!G3 -> -1342400 | F30: Saldo del mes | G30: =+G29*'OPEX (3)'!O3 -> -2311817 | J30: Saldo del mes | K30: =+K29*M28 -> 1313487.3
B31: Costo de oportunidad | C31: =+C30-PE!C28 -> -44484 | F31: Costo de oportunidad | G31: =+G30-PE!G28 -> -640040 | J31: Costo de oportunidad | K31: =+K30-PE!K28 -> 2012327.3
A33: =+C33/B27 -> #VALUE! | B33: Total costos variables | C33: =+C22*'OPEX (3)'!G3 -> 1308900 | E33: =+G33/F27 -> #VALUE! | F33: Total costos variables | G33: =+G22*'OPEX (3)'!O3 -> 5550840 | I33: =+K33/J27 -> #VALUE! | J33: Total costos variables | K33: =+K22*M28 -> 6781140
B34: Total gastos fijos | C34: =+C6 -> 2215000 | F34: Total gastos fijos | G34: =+G6 -> 6012377 | J34: Total gastos fijos | K34: =+(K6/'OPEX (3)'!W3)*M28 -> 3207272.7
B35: Total Gastos de Operación | C35: =+C33+C34 -> 3523900 | F35: Total Gastos de Operación | G35: =+G33+G34 -> 11563217 | J35: Total Gastos de Operación | K35: =+K33+K34 -> 9988412.7
B37: Ganancia / Pérdida | C37: =+B28-C35 -> -1342400 | F37: Ganancia / Pérdida | G37: =+F28-G35 -> -2311817 | J37: Ganancia / Pérdida | K37: =+J28-K35 -> 1313487.3

Sheet PE (0)
B1: Septiembre | F1: Octubre | J1: Noviembre | P1: Diciembre
B2: Nomina | C2: =+SUM(OPEX!G9:G16) -> 1420000 | F2: Nomina | G2: =+SUM(OPEX!M9:M16) -> 4535000 | J2: Nomina | K2: =+SUM(OPEX!S9:S16) -> 4100000 | L2: =+K2-G2 -> -435000 | M2: =+K2/G2-1 -> -0.095920617 | P2: Nomina | Q2: =+SUM(OPEX!Y9:Y16) -> 3685000 | R2: =+Q2-K2 -> -415000 | S2: =+Q2/K2-1 -> -0.10121951
B3: Arriendo | C3: =+OPEX!G4 -> 1500000 | F3: Arriendo | G3: =OPEX!$M$4 -> 2500000 | J3: Arriendo | K3: =OPEX!$M$4 -> 2500000 | L3: =+K3-G3 -> 0 | M3: =+K3/G3-1 -> 0 | P3: Arriendo | Q3: =+OPEX!Y4 -> 2500000 | R3: =+Q3-K3 -> 0 | S3: =+Q3/K3-1 -> 0
B4: Financieros | C4: =+SUM(OPEX!G17:G20) -> 0 | F4: Financieros | G4: =+SUM(OPEX!M17:M20) -> 777377 | J4: Financieros | K4: =+SUM(OPEX!S17:S20) -> 0 | L4: =+K4-G4 -> -777377 | M4: =+K4/G4-1 -> -1 | P4: Financieros | Q4: =+SUM(OPEX!Y17:Y20) -> 600000 | R4: =+Q4-K4 -> 600000 | S4: =+Q4/K4-1 -> #DIV/0!
B5: Servicios | C5: =+SUM(OPEX!G5:G8) -> 0 | F5: Servicios | G5: =+SUM(OPEX!M5:M8) -> 800000 | J5: Servicios | K5: =+SUM(OPEX!S5:S7) -> 800000 | L5: =+K5-G5 -> 0 | M5: =+K5/G5-1 -> 0 | P5: Servicios | Q5: =+SUM(OPEX!Y5:Y8) -> 780000 | R5: =+Q5-K5 -> -20000 | S5: =+Q5/K5-1 -> -0.025
C6: =+SUM(C2:C5) -> 2920000 | G6: =+SUM(G2:G5) -> 8612377 | K6: =+SUM(K2:K5) -> 7400000 | L6: =+K6-G6 -> -1212377 | M6: =+K6/G6-1 -> -0.14077147 | Q6: =+SUM(Q2:Q5) -> 7565000 | R6: =+Q6-K6 -> 165000 | S6: =+Q6/K6-1 -> 0.022297297
A8: 0.4 | B8: Gasto Fijos Prom. Diario | C8: =+C6/OPEX!G3 -> 324444.44 | F8: Gasto Fijos Prom. Diario | G8: =+G6/OPEX!M3 -> 277818.61 | J8: Gasto Fijos Prom. Diario | K8: =+K6/OPEX!S3 -> 246666.67 | P8: Gasto Fijos Prom. Diario | Q8: =+Q6/OPEX!Y3 -> 244032.26
A22: 0.6 | B22: Costos Variables | C22: =+C$23*$A$22 -> 486666.67 | F22: Costos Variables | G22: =+G$23*$A$22 -> 416727.92 | J22: Costos Variables | K22: =+K$23*$A$22 -> 370000 | P22: Costos Variables | Q22: =+Q$23*$A$22 -> 366048.39
B23: Punto de Eq. | C23: =+C8/40*100 -> 811111.11 | F23: Punto de Eq. | G23: =+G8/40*100 -> 694546.53 | J23: Punto de Eq. | K23: =+K8/40*100 -> 616666.67 | P23: Punto de Eq. | Q23: =+Q8/40*100 -> 610080.65
A25: Mes | B25: Total Ventas | E25: Mes | F25: Total Ventas | I25: Mes | J25: Total Ventas | M25: Hoy
A26: sep | B26: 4055210 | C26: =+B26/OPEX!G3 -> 450578.89 | E26: oct | F26: 17351500 | G26: =+F26/OPEX!M3 -> 559725.81 | I26: nov | J26: 16752900 | K26: =+J26/M26 -> 1047056.2 | M26: 16
B27: Ganacia /Pérdida | C27: =+C26-C23 -> -360532.22 | F27: Ganacia /Pérdida | G27: =+G26-G23 -> -134820.73 | J27: Ganacia /Pérdida | K27: =+K26-K23 -> 430389.58
B28: Saldo del mes | C28: =+C27*OPEX!G3 -> -3244790 | F28: Saldo del mes | G28: =+G27*OPEX!M3 -> -4179442.5 | J28: Saldo del mes | K28: =+K27*M26 -> 6886233.3

Sheet No. Dias
A1: Mes | B1: # Días | C1: # Días habiles | D1: # Días viernes | E1: # Días sábados | F1: # Días Domingos | G1: # Días Festivos
A2: Enero | B2: 31
A3: Febrero | B3: 28
A4: Marzo | B4: 31
A5: Abril | B5: 30
A6: Mayo | B6: 31
A7: Junio | B7: 30
A8: Julio | B8: 31
A9: Agosto | B9: 31
A10: septiembre | B10: 30
A11: octubre | B11: 31
A12: noviembre | B12: 30
A13: diciembre | B13: 31
A15: Dia semanal
A16: lunes | B16: Hábil
A17: martes | B17: Hábil
A18: miércoles | B18: Hábil
A19: jueves | B19: Hábil
A20: viernes | B20: Hábil
A21: sábado | B21: Fds
A22: domingo | B22: Fds

Sheet Profitability (0)
D1: Mes | K1: sep | L1: oct | M1: nov | N1: TOTAL
D2: sep | E2: oct | F2: nov | J2: lunes | K2: =+SUMIFS($J$14:$J$83,$C$14:$C$83,K$1,$E$14:$E$83,$J2) -> -1297012.2 | L2: =+SUMIFS($J$14:$J$83,$C$14:$C$83,L$1,$E$14:$E$83,$J2) -> -902686.13 | M2: =+SUMIFS($J$14:$J$83,$C$14:$C$83,M$1,$E$14:$E$83,$J2) -> 66666.667 | N2: =+SUM(K2:M2) -> -2133031.7
C3: INGRESOS | D3: 4055210 | E3: 17351500 | F3: 16752900 | J3: martes | K3: =+SUMIFS($J$14:$J$83,$C$14:$C$83,K$1,$E$14:$E$83,$J3) -> -418111.11 | L3: =+SUMIFS($J$14:$J$83,$C$14:$C$83,L$1,$E$14:$E$83,$J3) -> -1989632.7 | M3: =+SUMIFS($J$14:$J$83,$C$14:$C$83,M$1,$E$14:$E$83,$J3) -> -917333.33 | N3: =+SUM(K3:M3) -> -3325077.1
B4: 0.4 | C4: Gastos Fijos y Variables | D4: =OPEX!G27 -> 2920000 | E4: =OPEX!M22 -> Mes | J4: miércoles | K4: =+SUMIFS($J$14:$J$83,$C$14:$C$83,K$1,$E$14:$E$83,$J4) -> -391611.11 | L4: =+SUMIFS($J$14:$J$83,$C$14:$C$83,L$1,$E$14:$E$83,$J4) -> -1845432.7 | M4: =+SUMIFS($J$14:$J$83,$C$14:$C$83,M$1,$E$14:$E$83,$J4) -> -441333.33 | N4: =+SUM(K4:M4) -> -2678377.1
B5: 0.6 | C5: Costos Variables | D5: =OPEX!#REF! -> #REF! | E5: =OPEX!#REF! -> #REF! | J5: jueves | K5: =+SUMIFS($J$14:$J$83,$C$14:$C$83,K$1,$E$14:$E$83,$J5) -> -496111.11 | L5: =+SUMIFS($J$14:$J$83,$C$14:$C$83,L$1,$E$14:$E$83,$J5) -> -2148432.7 | M5: =+SUMIFS($J$14:$J$83,$C$14:$C$83,M$1,$E$14:$E$83,$J5) -> -284166.67 | N5: =+SUM(K5:M5) -> -2928710.4
D6: =OPEX!#REF! -> #REF! | E6: =OPEX!#REF! -> #REF! | J6: viernes | K6: =+SUMIFS($J$14:$J$83,$C$14:$C$83,K$1,$E$14:$E$83,$J6) -> -390111.11 | L6: =+SUMIFS($J$14:$J$83,$C$14:$C$83,L$1,$E$14:$E$83,$J6) -> -366286.13 | M6: =+SUMIFS($J$14:$J$83,$C$14:$C$83,M$1,$E$14:$E$83,$J6) -> -521333.33 | N6: =+SUM(K6:M6) -> -1277730.6
D7: =+D3-D6 -> #REF! | E7: =+E3-E6 -> #REF! | J7: sábado | K7: =+SUMIFS($J$14:$J$83,$C$14:$C$83,K$1,$E$14:$E$83,$J7) -> 140388.89 | L7: =+SUMIFS($J$14:$J$83,$C$14:$C$83,L$1,$E$14:$E$83,$J7) -> 471613.87 | M7: =+SUMIFS($J$14:$J$83,$C$14:$C$83,M$1,$E$14:$E$83,$J7) -> 818666.67 | N7: =+SUM(K7:M7) -> 1430669.4
J8: domingo | K8: =+SUMIFS($J$14:$J$83,$C$14:$C$83,K$1,$E$14:$E$83,$J8) -> -392222.22 | L8: =+SUMIFS($J$14:$J$83,$C$14:$C$83,L$1,$E$14:$E$83,$J8) -> 2601413.9 | M8: =+SUMIFS($J$14:$J$83,$C$14:$C$83,M$1,$E$14:$E$83,$J8) -> 2156666.7 | N8: =+SUM(K8:M8) -> 4365858.3
J9: TOTAL | K9: =+SUM(K2:K8) -> -3244790 | L9: =+SUM(L2:L8) -> -4179442.5 | M9: =+SUM(M2:M8) -> 877833.33 | N9: =+SUM(N2:N8) -> -6546399.2
C10: sep | G10: =+SUMIF($C$14:$C$66,$C10,G$14:G$66) -> 2920000 | H10: =+SUMIF($C$14:$C$66,$C10,H$14:H$66) -> 4380000
C11: oct | G11: =+SUMIF($C$14:$C$66,$C11,G$14:G$66) -> 8612377 | H11: =+SUMIF($C$14:$C$66,$C11,H$14:H$66) -> 12918566
C12: nov | G12: =+SUMIF($C$14:$C$66,$C12,G$14:G$66) -> 3206666.7 | H12: =+SUMIF($C$14:$C$66,$C12,H$14:H$66) -> 4810000
C13: Mes | D13: Dia | E13: Día de Semana | F13: INGRESOS TOTALES | G13: GASTOS FIJOS | H13: ESTIMACIÓN COSTO MATERIA PRIMA (COSTO VARIABLE) | I13: PRESUPUESTO DE VENTAS | J13: GAP | K13: Saldo actual | L13: Dìa de semanal | M13: Análisis gastos fijos | N13: Mes
C14: sep | D14: 22 | E14: domingo | F14: 572000 | G14: ='PE (0)'!$C$8 -> 324444.44 | H14: ='PE (0)'!$C$22 -> 486666.67 | I14: =+G14+H14 -> 811111.11 | J14: =+F14-I14 -> -239111.11 | K14: =+J14 -> -239111.11 | L14: =+E14 -> domingo | M14: =+F14-G14 -> 247555.56 | N14: =+C14 -> sep
C15: sep | D15: 23 | E15: lunes | F15: 142000 | G15: ='PE (0)'!$C$8 -> 324444.44 | H15: ='PE (0)'!$C$22 -> 486666.67 | I15: =+G15+H15 -> 811111.11 | J15: =+F15-I15 -> -669111.11 | K15: =+J15+K14 -> -908222.22 | L15: =+E15 -> lunes | M15: =+F15-G15 -> -182444.44 | N15: =+C15 -> sep
C16: sep | D16: 24 | E16: martes | F16: 393000 | G16: ='PE (0)'!$C$8 -> 324444.44 | H16: ='PE (0)'!$C$22 -> 486666.67 | I16: =+G16+H16 -> 811111.11 | J16: =+F16-I16 -> -418111.11 | K16: =+J16+K15 -> -1326333.3 | L16: =+E16 -> martes | M16: =+F16-G16 -> 68555.556 | N16: =+C16 -> sep
C17: sep | D17: 25 | E17: miércoles | F17: 419500 | G17: ='PE (0)'!$C$8 -> 324444.44 | H17: ='PE (0)'!$C$22 -> 486666.67 | I17: =+G17+H17 -> 811111.11 | J17: =+F17-I17 -> -391611.11 | K17: =+J17+K16 -> -1717944.4 | L17: =+E17 -> miércoles | M17: =+F17-G17 -> 95055.556 | N17: =+C17 -> sep
C18: sep | D18: 26 | E18: jueves | F18: 315000 | G18: ='PE (0)'!$C$8 -> 324444.44 | H18: ='PE (0)'!$C$22 -> 486666.67 | I18: =+G18+H18 -> 811111.11 | J18: =+F18-I18 -> -496111.11 | K18: =+J18+K17 -> -2214055.6 | L18: =+E18 -> jueves | M18: =+F18-G18 -> -9444.4444 | N18: =+C18 -> sep
C19: sep | D19: 27 | E19: viernes | F19: 421000 | G19: ='PE (0)'!$C$8 -> 324444.44 | H19: ='PE (0)'!$C$22 -> 486666.67 | I19: =+G19+H19 -> 811111.11 | J19: =+F19-I19 -> -390111.11 | K19: =+J19+K18 -> -2604166.7 | L19: =+E19 -> viernes | M19: =+F19-G19 -> 96555.556 | N19: =+C19 -> sep
C20: sep | D20: 28 | E20: sábado | F20: 951500 | G20: ='PE (0)'!$C$8 -> 324444.44 | H20: ='PE (0)'!$C$22 -> 486666.67 | I20: =+G20+H20 -> 811111.11 | J20: =+F20-I20 -> 140388.89 | K20: =+J20+K19 -> -2463777.8 | L20: =+E20 -> sábado | M20: =+F20-G20 -> 627055.56 | N20: =+C20 -> sep
C21: sep | D21: 29 | E21: domingo | F21: 658000 | G21: ='PE (0)'!$C$8 -> 324444.44 | H21: ='PE (0)'!$C$22 -> 486666.67 | I21: =+G21+H21 -> 811111.11 | J21: =+F21-I21 -> -153111.11 | K21: =+J21+K20 -> -2616888.9 | L21: =+E21 -> domingo | M21: =+F21-G21 -> 333555.56 | N21: =+C21 -> sep
C22: sep | D22: 30 | E22: lunes | F22: 183210 | G22: ='PE (0)'!$C$8 -> 324444.44 | H22: ='PE (0)'!$C$22 -> 486666.67 | I22: =+G22+H22 -> 811111.11 | J22: =+F22-I22 -> -627901.11 | K22: =+J22+K21 -> -3244790 | L22: =+E22 -> lunes | M22: =+F22-G22 -> -141234.44 | N22: =+C22 -> sep
C23: oct | D23: 1 | E23: martes | F23: 229800 | G23: ='PE (0)'!$G$8 -> 277818.61 | H23: ='PE (0)'!$G$22 -> 416727.92 | I23: =+G23+H23 -> 694546.53 | J23: =+F23-I23 -> -464746.53 | K23: =+J23+K22 -> -3709536.5 | L23: =+E23 -> martes | M23: =+F23-G23 -> -48018.613 | N23: =+C23 -> oct
C24: oct | D24: 2 | E24: miércoles | F24: 238000 | G24: ='PE (0)'!$G$8 -> 277818.61 | H24: ='PE (0)'!$G$22 -> 416727.92 | I24: =+G24+H24 -> 694546.53 | J24: =+F24-I24 -> -456546.53 | K24: =+J24+K23 -> -4166083.1 | L24: =+E24 -> miércoles | M24: =+F24-G24 -> -39818.613 | N24: =+C24 -> oct
C25: oct | D25: 3 | E25: jueves | F25: 238000 | G25: ='PE (0)'!$G$8 -> 277818.61 | H25: ='PE (0)'!$G$22 -> 416727.92 | I25: =+G25+H25 -> 694546.53 | J25: =+F25-I25 -> -456546.53 | K25: =+J25+K24 -> -4622629.6 | L25: =+E25 -> jueves | M25: =+F25-G25 -> -39818.613 | N25: =+C25 -> oct
C26: oct | D26: 4 | E26: viernes | F26: 420500 | G26: ='PE (0)'!$G$8 -> 277818.61 | H26: ='PE (0)'!$G$22 -> 416727.92 | I26: =+G26+H26 -> 694546.53 | J26: =+F26-I26 -> -274046.53 | K26: =+J26+K25 -> -4896676.1 | L26: =+E26 -> viernes | M26: =+F26-G26 -> 142681.39 | N26: =+C26 -> oct
C27: oct | D27: 5 | E27: sábado | F27: 1210300 | G27: ='PE (0)'!$G$8 -> 277818.61 | H27: ='PE (0)'!$G$22 -> 416727.92 | I27: =+G27+H27 -> 694546.53 | J27: =+F27-I27 -> 515753.47 | K27: =+J27+K26 -> -4380922.7 | L27: =+E27 -> sábado | M27: =+F27-G27 -> 932481.39 | N27: =+C27 -> oct
C28: oct | D28: 6 | E28: domingo | F28: 1345600 | G28: ='PE (0)'!$G$8 -> 277818.61 | H28: ='PE (0)'!$G$22 -> 416727.92 | I28: =+G28+H28 -> 694546.53 | J28: =+F28-I28 -> 651053.47 | K28: =+J28+K27 -> -3729869.2 | L28: =+E28 -> domingo | M28: =+F28-G28 -> 1067781.4 | N28: =+C28 -> oct
C29: oct | D29: 7 | E29: lunes | F29: 603500 | G29: ='PE (0)'!$G$8 -> 277818.61 | H29: ='PE (0)'!$G$22 -> 416727.92 | I29: =+G29+H29 -> 694546.53 | J29: =+F29-I29 -> -91046.532 | K29: =+J29+K28 -> -3820915.7 | L29: =+E29 -> lunes | M29: =+F29-G29 -> 325681.39 | N29: =+C29 -> oct
C30: oct | D30: 8 | E30: martes | F30: 426300 | G30: ='PE (0)'!$G$8 -> 277818.61 | H30: ='PE (0)'!$G$22 -> 416727.92 | I30: =+G30+H30 -> 694546.53 | J30: =+F30-I30 -> -268246.53 | K30: =+J30+K29 -> -4089162.3 | L30: =+E30 -> martes | M30: =+F30-G30 -> 148481.39 | N30: =+C30 -> oct
C31: oct | D31: 9 | E31: miércoles | F31: 134000 | G31: ='PE (0)'!$G$8 -> 277818.61 | H31: ='PE (0)'!$G$22 -> 416727.92 | I31: =+G31+H31 -> 694546.53 | J31: =+F31-I31 -> -560546.53 | K31: =+J31+K30 -> -4649708.8 | L31: =+E31 -> miércoles | M31: =+F31-G31 -> -143818.61 | N31: =+C31 -> oct
C32: oct | D32: 10 | E32: jueves | F32: 85500 | G32: ='PE (0)'!$G$8 -> 277818.61 | H32: ='PE (0)'!$G$22 -> 416727.92 | I32: =+G32+H32 -> 694546.53 | J32: =+F32-I32 -> -609046.53 | K32: =+J32+K31 -> -5258755.3 | L32: =+E32 -> jueves | M32: =+F32-G32 -> -192318.61 | N32: =+C32 -> oct
C33: oct | D33: 11 | E33: viernes | F33: 427900 | G33: ='PE (0)'!$G$8 -> 277818.61 | H33: ='PE (0)'!$G$22 -> 416727.92 | I33: =+G33+H33 -> 694546.53 | J33: =+F33-I33 -> -266646.53 | K33: =+J33+K32 -> -5525401.9 | L33: =+E33 -> viernes | M33: =+F33-G33 -> 150081.39 | N33: =+C33 -> oct
C34: oct | D34: 12 | E34: sábado | F34: 664500 | G34: ='PE (0)'!$G$8 -> 277818.61 | H34: ='PE (0)'!$G$22 -> 416727.92 | I34: =+G34+H34 -> 694546.53 | J34: =+F34-I34 -> -30046.532 | K34: =+J34+K33 -> -5555448.4 | L34: =+E34 -> sábado | M34: =+F34-G34 -> 386681.39 | N34: =+C34 -> oct
... C53: oct | D53: 31 | E53: jueves | F53: 370000 | G53: ='PE (0)'!$G$8 -> 277818.61 | H53: ='PE (0)'!$G$22 -> 416727.92 | I53: =+G53+H53 -> 694546.53 | J53: =+F53-I53 -> -324546.53 | K53: =+J53+K52 -> -7424232.5 | L53: =+E53 -> jueves | M53: =+F53-G53 -> 92181.387 | N53: =+C53 -> oct
C54: nov | D54: 1 | E54: viernes | F54: 370000 | G54: ='PE (0)'!$K$8 -> 246666.67 | H54: ='PE (0)'!$K$22 -> 370000 | I54: =+G54+H54 -> 616666.67 | J54: =+F54-I54 -> -246666.67 | K54: =+J54+K53 -> -7670899.2 | L54: =+E54 -> viernes | M54: =+F54-G54 -> 123333.33 | N54: =+C54 -> nov
C55: nov | D55: 2 | E55: sábado | F55: 500000 | G55: ='PE (0)'!$K$8 -> 246666.67 | H55: ='PE (0)'!$K$22 -> 370000 | I55: =+G55+H55 -> 616666.67 | J55: =+F55-I55 -> -116666.67 | K55: =+J55+K54 -> -7787565.8 | L55: =+E55 -> sábado | M55: =+F55-G55 -> 253333.33 | N55: =+C55 -> nov
C56: nov | D56: 3 | E56: domingo | F56: 1700000 | G56: ='PE (0)'!$K$8 -> 246666.67 | H56: ='PE (0)'!$K$22 -> 370000 | I56: =+G56+H56 -> 616666.67 | J56: =+F56-I56 -> 1083333.3 | K56: =+J56+K55 -> -6704232.5 | L56: =+E56 -> domingo | M56: =+F56-G56 -> 1453333.3 | N56: =+C56 -> nov
C57: nov | D57: 4 | E57: lunes | F57: 600000 | G57: ='PE (0)'!$K$8 -> 246666.67 | H57: ='PE (0)'!$K$22 -> 370000 | I57: =+G57+H57 -> 616666.67 | J57: =+F57-I57 -> -16666.667 | K57: =+J57+K56 -> -6720899.2 | L57: =+E57 -> lunes | M57: =+F57-G57 -> 353333.33 | N57: =+C57 -> nov
C58: nov | D58: 5 | E58: martes | F58: 194000 | G58: ='PE (0)'!$K$8 -> 246666.67 | H58: ='PE (0)'!$K$22 -> 370000 | I58: =+G58+H58 -> 616666.67 | J58: =+F58-I58 -> -422666.67 | K58: =+J58+K57 -> -7143565.8 | L58: =+E58 -> martes | M58: =+F58-G58 -> -52666.667 | N58: =+C58 -> nov
C59: nov | D59: 6 | E59: miércoles | F59: 627000 | G59: ='PE (0)'!$K$8 -> 246666.67 | H59: ='PE (0)'!$K$22 -> 370000 | I59: =+G59+H59 -> 616666.67 | J59: =+F59-I59 -> 10333.333 | K59: =+J59+K58 -> -7133232.5 | L59: =+E59 -> miércoles | M59: =+F59-G59 -> 380333.33 | N59: =+C59 -> nov
C60: nov | D60: 7 | E60: jueves | F60: 332500 | G60: ='PE (0)'!$K$8 -> 246666.67 | H60: ='PE (0)'!$K$22 -> 370000 | I60: =+G60+H60 -> 616666.67 | J60: =+F60-I60 -> -284166.67 | K60: =+J60+K59 -> -7417399.2 | L60: =+E60 -> jueves | M60: =+F60-G60 -> 85833.333 | N60: =+C60 -> nov
C61: nov | D61: 8 | E61: viernes | F61: 342000 | G61: ='PE (0)'!$K$8 -> 246666.67 | H61: ='PE (0)'!$K$22 -> 370000 | I61: =+G61+H61 -> 616666.67 | J61: =+F61-I61 -> -274666.67 | K61: =+J61+K60 -> -7692065.8 | L61: =+E61 -> viernes | M61: =+F61-G61 -> 95333.333 | N61: =+C61 -> nov
C62: nov | D62: 9 | E62: sábado | F62: 1552000 | G62: ='PE (0)'!$K$8 -> 246666.67 | H62: ='PE (0)'!$K$22 -> 370000 | I62: =+G62+H62 -> 616666.67 | J62: =+F62-I62 -> 935333.33 | K62: =+J62+K61 -> -6756732.5 | L62: =+E62 -> sábado | M62: =+F62-G62 -> 1305333.3 | N62: =+C62 -> nov
C63: nov | D63: 10 | E63: domingo | F63: 1690000 | G63: ='PE (0)'!$K$8 -> 246666.67 | H63: ='PE (0)'!$K$22 -> 370000 | I63: =+G63+H63 -> 616666.67 | J63: =+F63-I63 -> 1073333.3 | K63: =+J63+K62 -> -5683399.2 | L63: =+E63 -> domingo | M63: =+F63-G63 -> 1443333.3 | N63: =+C63 -> nov
C64: nov | D64: 11 | E64: lunes | F64: 700000 | G64: ='PE (0)'!$K$8 -> 246666.67 | H64: ='PE (0)'!$K$22 -> 370000 | I64: =+G64+H64 -> 616666.67 | J64: =+F64-I64 -> 83333.333 | K64: =+J64+K63 -> -5600065.8 | L64: =+E64 -> lunes | M64: =+F64-G64 -> 453333.33 | N64: =+C64 -> nov
C65: nov | D65: 12 | E65: martes | F65: 122000 | G65: ='PE (0)'!$K$8 -> 246666.67 | H65: ='PE (0)'!$K$22 -> 370000 | I65: =+G65+H65 -> 616666.67 | J65: =+F65-I65 -> -494666.67 | K65: =+J65+K64 -> -6094732.5 | L65: =+E65 -> martes | M65: =+F65-G65 -> -124666.67 | N65: =+C65 -> nov
C66: nov | D66: 13 | E66: miércoles | F66: 165000 | G66: ='PE (0)'!$K$8 -> 246666.67 | H66: ='PE (0)'!$K$22 -> 370000 | I66: =+G66+H66 -> 616666.67 | J66: =+F66-I66 -> -451666.67 | K66: =+J66+K65 -> -6546399.2 | L66: =+E66 -> miércoles | M66: =+F66-G66 -> -81666.667 | N66: =+C66 -> nov
C67: nov | D67: 14 | E67: jueves | F67: 61000
C68: nov | D68: 15 | E68: viernes | F68: 235000
C69: nov | D69: 16 | E69: sábado | F69: 811500
C70: nov | D70: 17 | E70: domingo | F70: 1300900
C71: nov | D71: 18 | E71: lunes | F71: 350000
C72: nov | D72: 19 | E72: martes | F72: 220000
C73: nov | D73: 20 | E73: miércoles | F73: 320000
C74: nov | D74: 21 | E74: jueves | F74: 216500
C75: nov | D75: 22 | E75: viernes | F75: 186000
C76: nov | D76: 23 | E76: sábado | F76: 587500
C77: nov | D77: 24 | E77: domingo | F77: 960000
C78: nov | D78: 25 | E78: lunes | F78: 500000
... C83: nov | D83: 30 | E83: sábado | F83: 900000

Sheet Profitability (2-Mensualizado)
D1: Mes | K1: sep | L1: oct | M1: nov | N1: TOTAL
D2: sep | E2: oct | F2: nov | J2: Lunes | K2: =+SUMIFS($J$13:$J$82,$C$13:$C$82,K$1,$E$13:$E$82,$J2) -> -640000 | L2: =+SUMIFS($J$13:$J$82,$C$13:$C$82,L$1,$E$13:$E$82,$J2) -> -583764.77 | M2: =+SUMIFS($J$13:$J$82,$C$13:$C$82,M$1,$E$13:$E$82,$J2) -> -225333.33 | N2: =+SUM(K2:M2) -> -1449098.1
C3: INGRESOS | D3: 4055210 | E3: 17351500 | F3: 16752900 | J3: Martes | K3: =+SUMIFS($J$13:$J$82,$C$13:$C$82,K$1,$E$13:$E$82,$J3) -> -320000 | L3: =+SUMIFS($J$13:$J$82,$C$13:$C$82,L$1,$E$13:$E$82,$J3) -> -1040706 | M3: =+SUMIFS($J$13:$J$82,$C$13:$C$82,M$1,$E$13:$E$82,$J3) -> -745333.33 | N3: =+SUM(K3:M3) -> -2106039.3
B4: 0.4 | C4: Gastos Fijos y Variables | D4: =OPEX!G27 -> 2920000 | E4: =OPEX!M22 -> Mes | J4: Miércoles | K4: =+SUMIFS($J$13:$J$82,$C$13:$C$82,K$1,$E$13:$E$82,$J4) -> -320000 | L4: =+SUMIFS($J$13:$J$82,$C$13:$C$82,L$1,$E$13:$E$82,$J4) -> -1040706 | M4: =+SUMIFS($J$13:$J$82,$C$13:$C$82,M$1,$E$13:$E$82,$J4) -> -745333.33 | N4: =+SUM(K4:M4) -> -2106039.3
B5: 0.6 | C5: Costos Variables | D5: =OPEX!#REF! -> #REF! | E5: =OPEX!#REF! -> #REF! | J5: Jueves | K5: =+SUMIFS($J$13:$J$82,$C$13:$C$82,K$1,$E$13:$E$82,$J5) -> -320000 | L5: =+SUMIFS($J$13:$J$82,$C$13:$C$82,L$1,$E$13:$E$82,$J5) -> -1040706 | M5: =+SUMIFS($J$13:$J$82,$C$13:$C$82,M$1,$E$13:$E$82,$J5) -> -745333.33 | N5: =+SUM(K5:M5) -> -2106039.3
D6: =OPEX!#REF! -> #REF! | E6: =OPEX!#REF! -> #REF! | J6: viernes | K6: =+SUMIFS($J$13:$J$82,$C$13:$C$82,K$1,$E$13:$E$82,$J6) -> -151600 | L6: =+SUMIFS($J$13:$J$82,$C$13:$C$82,L$1,$E$13:$E$82,$J6) -> 132195.23 | M6: =+SUMIFS($J$13:$J$82,$C$13:$C$82,M$1,$E$13:$E$82,$J6) -> -318466.67 | N6: =+SUM(K6:M6) -> -337871.44
D7: =+D3-D6 -> #REF! | E7: =+E3-E6 -> #REF! | I7: =+F8-I8 -> 43020.513 | J7: sábado | K7: =+SUMIFS($J$13:$J$82,$C$13:$C$82,K$1,$E$13:$E$82,$J7) -> 60600 | L7: =+SUMIFS($J$13:$J$82,$C$13:$C$82,L$1,$E$13:$E$82,$J7) -> 467355.23 | M7: =+SUMIFS($J$13:$J$82,$C$13:$C$82,M$1,$E$13:$E$82,$J7) -> 808733.33 | N7: =+SUM(K7:M7) -> 1336688.6
F8: =+SUBTOTAL(101,F53:F65) -> 573384.62 | G8: =+SUBTOTAL(101,G53:G65) -> 186333.33 | H8: =+SUBTOTAL(101,H53:H65) -> 344030.77 | I8: =+SUBTOTAL(101,I53:I65) -> 530364.1 | J8: domingo | K8: =+SUMIFS($J$13:$J$82,$C$13:$C$82,K$1,$E$13:$E$82,$J8) -> -148000 | L8: =+SUMIFS($J$13:$J$82,$C$13:$C$82,L$1,$E$13:$E$82,$J8) -> 1319275.2 | M8: =+SUMIFS($J$13:$J$82,$C$13:$C$82,M$1,$E$13:$E$82,$J8) -> 1515026.7 | N8: =+SUM(K8:M8) -> 2686301.9
D9: (Todas) | I9: =+F11-I11 -> 559266.67 | J9: TOTAL | K9: =+SUM(K2:K8) -> -1839000 | L9: =+SUM(L2:L8) -> -1787057 | M9: =+SUM(M2:M8) -> -456040 | N9: =+SUM(N2:N8) -> -4082097
K10: =+K9-Profitability!K9 -> -541084 | L10: =+L9-Profitability!L9 -> -115280 | M10: =+M9-Profitability!M9 -> 242800 | N10: =+N9-Profitability!N9 -> -413564
F11: =+SUBTOTAL(9,F53:F65) -> 7454000 | G11: =+SUBTOTAL(9,G53:G65) -> 2422333.3 | H11: =+SUBTOTAL(9,H53:H65) -> 4472400 | I11: =+SUBTOTAL(9,I53:I65) -> 6894733.3 | J11: =+SUBTOTAL(9,J53:J65) -> 559266.67
C12: Mes | D12: Dia | E12: Día de Semana | F12: INGRESOS TOTALES | G12: GASTOS FIJOS | H12: COSTO MATERIA PRIMA (COSTO VARIABLE) | I12: PRESUPUESTO DE VENTAS | J12: GAP | K12: Saldo actual | L12: Dìa de semanal | M12: Análisis gastos fijos | N12: Mes
C13: =+Profitability!C14 -> sep | D13: =DAY(Profitability!D14) -> 22 | E13: =+Profitability!E14 -> domingo | F13: =Profitability!$F$14 -> 572000 | G13: ='PE (2)'!$C$9 -> 320000 | H13: =+F13*60% -> 343200 | I13: =+G13+H13 -> 663200 | J13: =+F13-I13 -> -91200 | K13: =+J13 -> -91200 | L13: =+E13 -> domingo | M13: =+F13-G13 -> 252000 | N13: =+C13 -> sep
C14: =+Profitability!C15 -> sep | D14: =DAY(Profitability!D15) -> 23 | E14: =+Profitability!E15 -> lunes | G14: ='PE (2)'!$C$9 -> 320000 | I14: =+G14+H14 -> 320000 | J14: =+F14-I14 -> -320000 | K14: =+J14 -> -320000 | L14: =+E14 -> lunes | M14: =+F14-G14 -> -320000 | N14: =+C14 -> sep
C15: =+Profitability!C16 -> sep | D15: =DAY(Profitability!D16) -> 24 | E15: =+Profitability!E16 -> martes | G15: ='PE (2)'!$C$9 -> 320000 | I15: =+G15+H15 -> 320000 | J15: =+F15-I15 -> -320000 | K15: =+J15 -> -320000 | L15: =+E15 -> martes | M15: =+F15-G15 -> -320000 | N15: =+C15 -> sep
C16: =+Profitability!C17 -> sep | D16: =DAY(Profitability!D17) -> 25 | E16: =+Profitability!E17 -> miércoles | G16: ='PE (2)'!$C$9 -> 320000 | I16: =+G16+H16 -> 320000 | J16: =+F16-I16 -> -320000 | K16: =+J16 -> -320000 | L16: =+E16 -> miércoles | M16: =+F16-G16 -> -320000 | N16: =+C16 -> sep
C17: =+Profitability!C18 -> sep | D17: =DAY(Profitability!D18) -> 26 | E17: =+Profitability!E18 -> jueves | G17: ='PE (2)'!$C$9 -> 320000 | I17: =+G17+H17 -> 320000 | J17: =+F17-I17 -> -320000 | K17: =+J17 -> -320000 | L17: =+E17 -> jueves | M17: =+F17-G17 -> -320000 | N17: =+C17 -> sep
C18: =+Profitability!C19 -> sep | D18: =DAY(Profitability!D19) -> 27 | E18: =+Profitability!E19 -> viernes | F18: =+Profitability!F19 -> 421000 | G18: ='PE (2)'!$C$9 -> 320000 | H18: =+F18*60% -> 252600 | I18: =+G18+H18 -> 572600 | J18: =+F18-I18 -> -151600 | K18: =+J18 -> -151600 | L18: =+E18 -> viernes | M18: =+F18-G18 -> 101000 | N18: =+C18 -> sep
C19: =+Profitability!C20 -> sep | D19: =DAY(Profitability!D20) -> 28 | E19: =+Profitability!E20 -> sábado | F19: =+Profitability!F20 -> 951500 | G19: ='PE (2)'!$C$9 -> 320000 | H19: =+F19*60% -> 570900 | I19: =+G19+H19 -> 890900 | J19: =+F19-I19 -> 60600 | K19: =+J19 -> 60600 | L19: =+E19 -> sábado | M19: =+F19-G19 -> 631500 | N19: =+C19 -> sep
C20: =+Profitability!C21 -> sep | D20: =DAY(Profitability!D21) -> 29 | E20: =+Profitability!E21 -> domingo | F20: =+Profitability!F21 -> 658000 | G20: ='PE (2)'!$C$9 -> 320000 | H20: =+F20*60% -> 394800 | I20: =+G20+H20 -> 714800 | J20: =+F20-I20 -> -56800 | K20: =+J20 -> -56800 | L20: =+E20 -> domingo | M20: =+F20-G20 -> 338000 | N20: =+C20 -> sep
C21: =+Profitability!C22 -> sep | D21: =DAY(Profitability!D22) -> 30 | E21: =+Profitability!E22 -> lunes | G21: ='PE (2)'!$C$9 -> 320000 | I21: =+G21+H21 -> 320000 | J21: =+F21-I21 -> -320000 | K21: =+J21 -> -320000 | L21: =+E21 -> lunes | M21: =+F21-G21 -> -320000 | N21: =+C21 -> sep
C22: =+Profitability!C23 -> oct | D22: =DAY(Profitability!D23) -> 1 | E22: =+Profitability!E23 -> martes | G22: ='PE (2)'!$G$9 -> 208141.19 | I22: =+G22+H22 -> 208141.19 | J22: =+F22-I22 -> -208141.19 | K22: =+J22 -> -208141.19 | L22: =+E22 -> martes | M22: =+F22-G22 -> -208141.19 | N22: =+C22 -> oct
C23: =+Profitability!C24 -> oct | D23: =DAY(Profitability!D24) -> 2 | E23: =+Profitability!E24 -> miércoles | G23: ='PE (2)'!$G$9 -> 208141.19 | I23: =+G23+H23 -> 208141.19 | J23: =+F23-I23 -> -208141.19 | K23: =+J23 -> -208141.19 | L23: =+E23 -> miércoles | M23: =+F23-G23 -> -208141.19 | N23: =+C23 -> oct
C24: =+Profitability!C25 -> oct | D24: =DAY(Profitability!D25) -> 3 | E24: =+Profitability!E25 -> jueves | G24: ='PE (2)'!$G$9 -> 208141.19 | I24: =+G24+H24 -> 208141.19 | J24: =+F24-I24 -> -208141.19 | K24: =+J24 -> -208141.19 | L24: =+E24 -> jueves | M24: =+F24-G24 -> -208141.19 | N24: =+C24 -> oct
C25: =+Profitability!C26 -> oct | D25: =DAY(Profitability!D26) -> 4 | E25: =+Profitability!E26 -> viernes | F25: =+Profitability!F26 -> 420500 | G25: ='PE (2)'!$G$9 -> 208141.19 | H25: =+F25*60% -> 252300 | I25: =+G25+H25 -> 460441.19 | J25: =+F25-I25 -> -39941.194 | K25: =+J25 -> -39941.194 | L25: =+E25 -> viernes | M25: =+F25-G25 -> 212358.81 | N25: =+C25 -> oct
C26: =+Profitability!C27 -> oct | D26: =DAY(Profitability!D27) -> 5 | E26: =+Profitability!E27 -> sábado | F26: =+Profitability!F27 -> 1210300 | G26: ='PE (2)'!$G$9 -> 208141.19 | H26: =+F26*60% -> 726180 | I26: =+G26+H26 -> 934321.19 | J26: =+F26-I26 -> 275978.81 | K26: =+J26 -> 275978.81 | L26: =+E26 -> sábado | M26: =+F26-G26 -> 1002158.8 | N26: =+C26 -> oct
C27: =+Profitability!C28 -> oct | D27: =DAY(Profitability!D28) -> 6 | E27: =+Profitability!E28 -> domingo | F27: =+Profitability!F28 -> 1345600 | G27: ='PE (2)'!$G$9 -> 208141.19 | H27: =+F27*60% -> 807360 | I27: =+G27+H27 -> 1015501.2 | J27: =+F27-I27 -> 330098.81 | K27: =+J27 -> 330098.81 | L27: =+E27 -> domingo | M27: =+F27-G27 -> 1137458.8 | N27: =+C27 -> oct
C28: =+Profitability!C29 -> oct | D28: =DAY(Profitability!D29) -> 7 | E28: =+Profitability!E29 -> lunes | G28: ='PE (2)'!$G$9 -> 208141.19 | I28: =+G28+H28 -> 208141.19 | J28: =+F28-I28 -> -208141.19 | K28: =+J28 -> -208141.19 | L28: =+E28 -> lunes | M28: =+F28-G28 -> -208141.19 | N28: =+C28 -> oct
C29: =+Profitability!C30 -> oct | D29: =DAY(Profitability!D30) -> 8 | E29: =+Profitability!E30 -> martes | G29: ='PE (2)'!$G$9 -> 208141.19 | I29: =+G29+H29 -> 208141.19 | J29: =+F29-I29 -> -208141.19 | K29: =+J29 -> -208141.19 | L29: =+E29 -> martes | M29: =+F29-G29 -> -208141.19 | N29: =+C29 -> oct
C30: =+Profitability!C31 -> oct | D30: =DAY(Profitability!D31) -> 9 | E30: =+Profitability!E31 -> miércoles | G30: ='PE (2)'!$G$9 -> 208141.19 | I30: =+G30+H30 -> 208141.19 | J30: =+F30-I30 -> -208141.19 | K30: =+J30 -> -208141.19 | L30: =+E30 -> miércoles | M30: =+F30-G30 -> -208141.19 | N30: =+C30 -> oct
C31: =+Profitability!C32 -> oct | D31: =DAY(Profitability!D32) -> 10 | E31: =+Profitability!E32 -> jueves | G31: ='PE (2)'!$G$9 -> 208141.19 | I31: =+G31+H31 -> 208141.19 | J31: =+F31-I31 -> -208141.19 | K31: =+J31 -> -208141.19 | L31: =+E31 -> jueves | M31: =+F31-G31 -> -208141.19 | N31: =+C31 -> oct
C32: =+Profitability!C33 -> oct | D32: =DAY(Profitability!D33) -> 11 | E32: =+Profitability!E33 -> viernes | F32: =+Profitability!F33 -> 427900 | G32: ='PE (2)'!$G$9 -> 208141.19 | H32: =+F32*60% -> 256740 | I32: =+G32+H32 -> 464881.19 | J32: =+F32-I32 -> -36981.194 | K32: =+J32 -> -36981.194 | L32: =+E32 -> viernes | M32: =+F32-G32 -> 219758.81 | N32: =+C32 -> oct
C33: =+Profitability!C34 -> oct | D33: =DAY(Profitability!D34) -> 12 | E33: =+Profitability!E34 -> sábado | F33: =+Profitability!F34 -> 664500 | G33: ='PE (2)'!$G$9 -> 208141.19 | H33: =+F33*60% -> 398700 | I33: =+G33+H33 -> 606841.19 | J33: =+F33-I33 -> 57658.806 | K33: =+J33 -> 57658.806 | L33: =+E33 -> sábado | M33: =+F33-G33 -> 456358.81 | N33: =+C33 -> oct
C34: =+Profitability!C35 -> oct | D34: =DAY(Profitability!D35) -> 13 | E34: =+Profitability!E35 -> domingo | F34: =+Profitability!F35 -> 1283500 | G34: ='PE (2)'!$G$9 -> 208141.19 | H34: =+F34*60% -> 770100 | I34: =+G34+H34 -> 978241.19 | J34: =+F34-I34 -> 305258.81 | K34: =+J34 -> 305258.81 | L34: =+E34 -> domingo | M34: =+F34-G34 -> 1075358.8 | N34: =+C34 -> oct
C35: =+Profitability!C36 -> oct | D35: =DAY(Profitability!D36) -> 14 | E35: =+Profitability!E36 -> lunes | F35: =+Profitability!F36 -> 622000 | G35: ='PE (2)'!$G$9 -> 208141.19 | H35: =+F35*60% -> 373200 | I35: =+G35+H35 -> 581341.19 | J35: =+F35-I35 -> 40658.806 | K35: =+J35 -> 40658.806 | L35: =+E35 -> lunes | M35: =+F35-G35 -> 413858.81 | N35: =+C35 -> oct
C36: =+Profitability!C37 -> oct | D36: =DAY(Profitability!D37) -> 15 | E36: =+Profitability!E37 -> martes | G36: ='PE (2)'!$G$9 -> 208141.19 | I36: =+G36+H36 -> 208141.19 | J36: =+F36-I36 -> -208141.19 | K36: =+J36 -> -208141.19 | L36: =+E36 -> martes | M36: =+F36-G36 -> -208141.19 | N36: =+C36 -> oct
C37: =+Profitability!C38 -> oct | D37: =DAY(Profitability!D38) -> 16 | E37: =+Profitability!E38 -> miércoles | G37: ='PE (2)'!$G$9 -> 208141.19 | I37: =+G37+H37 -> 208141.19 | J37: =+F37-I37 -> -208141.19 | K37: =+J37 -> -208141.19 | L37: =+E37 -> miércoles | M37: =+F37-G37 -> -208141.19 | N37: =+C37 -> oct
C38: =+Profitability!C39 -> oct | D38: =DAY(Profitability!D39) -> 17 | E38: =+Profitability!E39 -> jueves | G38: ='PE (2)'!$G$9 -> 208141.19 | I38: =+G38+H38 -> 208141.19 | J38: =+F38-I38 -> -208141.19 | K38: =+J38 -> -208141.19 | L38: =+E38 -> jueves | M38: =+F38-G38 -> -208141.19 | N38: =+C38 -> oct
C39: =+Profitability!C40 -> oct | D39: =DAY(Profitability!D40) -> 18 | E39: =+Profitability!E40 -> viernes | F39: =+Profitability!F40 -> 363500 | G39: ='PE (2)'!$G$9 -> 208141.19 | H39: =+F39*60% -> 218100 | I39: =+G39+H39 -> 426241.19 | J39: =+F39-I39 -> -62741.194 | K39: =+J39 -> -62741.194 | L39: =+E39 -> viernes | M39: =+F39-G39 -> 155358.81 | N39: =+C39 -> oct
C40: =+Profitability!C41 -> oct | D40: =DAY(Profitability!D41) -> 19 | E40: =+Profitability!E41 -> sábado | F40: =+Profitability!F41 -> 720000 | G40: ='PE (2)'!$G$9 -> 208141.19 | H40: =+F40*60% -> 432000 | I40: =+G40+H40 -> 640141.19 | J40: =+F40-I40 -> 79858.806 | K40: =+J40 -> 79858.806 | L40: =+E40 -> sábado | M40: =+F40-G40 -> 511858.81 | N40: =+C40 -> oct
C41: =+Profitability!C42 -> oct | D41: =DAY(Profitability!D42) -> 20 | E41: =+Profitability!E42 -> domingo | F41: =+Profitability!F42 -> 1550500 | G41: ='PE (2)'!$G$9 -> 208141.19 | H41: =+F41*60% -> 930300 | I41: =+G41+H41 -> 1138441.2 | J41: =+F41-I41 -> 412058.81 | K41: =+J41 -> 412058.81 | L41: =+E41 -> domingo | M41: =+F41-G41 -> 1342358.8 | N41: =+C41 -> oct
C42: =+Profitability!C43 -> oct | D42: =DAY(Profitability!D43) -> 21 | E42: =+Profitability!E43 -> lunes | G42: ='PE (2)'!$G$9 -> 208141.19 | I42: =+G42+H42 -> 208141.19 | J42: =+F42-I42 -> -208141.19 | K42: =+J42 -> -208141.19 | L42: =+E42 -> lunes | M42: =+F42-G42 -> -208141.19 | N42: =+C42 -> oct
C43: =+Profitability!C44 -> oct | D43: =DAY(Profitability!D44) -> 22 | E43: =+Profitability!E44 -> martes | G43: ='PE (2)'!$G$9 -> 208141.19 | I43: =+G43+H43 -> 208141.19 | J43: =+F43-I43 -> -208141.19 | K43: =+J43 -> -208141.19 | L43: =+E43 -> martes | M43: =+F43-G43 -> -208141.19 | N43: =+C43 -> oct
C44: =+Profitability!C45 -> oct | D44: =DAY(Profitability!D45) -> 23 | E44: =+Profitability!E45 -> miércoles | G44: ='PE (2)'!$G$9 -> 208141.19 | I44: =+G44+H44 -> 208141.19 | J44: =+F44-I44 -> -208141.19 | K44: =+J44 -> -208141.19 | L44: =+E44 -> miércoles | M44: =+F44-G44 -> -208141.19 | N44: =+C44 -> oct
C45: =+Profitability!C46 -> oct | D45: =DAY(Profitability!D46) -> 24 | E45: =+Profitability!E46 -> jueves | G45: ='PE (2)'!$G$9 -> 208141.19 | I45: =+G45+H45 -> 208141.19 | J45: =+F45-I45 -> -208141.19 | K45: =+J45 -> -208141.19 | L45: =+E45 -> jueves | M45: =+F45-G45 -> -208141.19 | N45: =+C45 -> oct
C46: =+Profitability!C47 -> oct | D46: =DAY(Profitability!D47) -> 25 | E46: =+Profitability!E47 -> viernes | F46: =+Profitability!F47 -> 1200000 | G46: ='PE (2)'!$G$9 -> 208141.19 | H46: =+F46*60% -> 720000 | I46: =+G46+H46 -> 928141.19 | J46: =+F46-I46 -> 271858.81 | K46: =+J46 -> 271858.81 | L46: =+E46 -> viernes | M46: =+F46-G46 -> 991858.81 | N46: =+C46 -> oct
C47: =+Profitability!C48 -> oct | D47: =DAY(Profitability!D48) -> 26 | E47: =+Profitability!E48 -> sábado | F47: =+Profitability!F48 -> 655000 | G47: ='PE (2)'!$G$9 -> 208141.19 | H47: =+F47*60% -> 393000 | I47: =+G47+H47 -> 601141.19 | J47: =+F47-I47 -> 53858.806 | K47: =+J47 -> 53858.806 | L47: =+E47 -> sábado | M47: =+F47-G47 -> 446858.81 | N47: =+C47 -> oct
C48: =+Profitability!C49 -> oct | D48: =DAY(Profitability!D49) -> 27 | E48: =+Profitability!E49 -> domingo | F48: =+Profitability!F49 -> 1200000 | G48: ='PE (2)'!$G$9 -> 208141.19 | H48: =+F48*60% -> 720000 | I48: =+G48+H48 -> 928141.19 | J48: =+F48-I48 -> 271858.81 | K48: =+J48 -> 271858.81 | L48: =+E48 -> domingo | M48: =+F48-G48 -> 991858.81 | N48: =+C48 -> oct
C49: =+Profitability!C50 -> oct | D49: =DAY(Profitability!D50) -> 28 | E49: =+Profitability!E50 -> lunes | G49: ='PE (2)'!$G$9 -> 208141.19 | I49: =+G49+H49 -> 208141.19 | J49: =+F49-I49 -> -208141.19 | K49: =+J49 -> -208141.19 | L49: =+E49 -> lunes | M49: =+F49-G49 -> -208141.19 | N49: =+C49 -> oct
C50: =+Profitability!C51 -> oct | D50: =DAY(Profitability!D51) -> 29 | E50: =+Profitability!E51 -> martes | G50: ='PE (2)'!$G$9 -> 208141.19 | I50: =+G50+H50 -> 208141.19 | J50: =+F50-I50 -> -208141.19 | K50: =+J50 -> -208141.19 | L50: =+E50 -> martes | M50: =+F50-G50 -> -208141.19 | N50: =+C50 -> oct
C51: =+Profitability!C52 -> oct | D51: =DAY(Profitability!D52) -> 30 | E51: =+Profitability!E52 -> miércoles | G51: ='PE (2)'!$G$9 -> 208141.19 | I51: =+G51+H51 -> 208141.19 | J51: =+F51-I51 -> -208141.19 | K51: =+J51 -> -208141.19 | L51: =+E51 -> miércoles | M51: =+F51-G51 -> -208141.19 | N51: =+C51 -> oct
C52: =+Profitability!C53 -> oct | D52: =DAY(Profitability!D53) -> 31 | E52: =+Profitability!E53 -> jueves | G52: ='PE (2)'!$G$9 -> 208141.19 | I52: =+G52+H52 -> 208141.19 | J52: =+F52-I52 -> -208141.19 | K52: =+J52 -> -208141.19 | L52: =+E52 -> jueves | M52: =+F52-G52 -> -208141.19 | N52: =+C52 -> oct
C53: =+Profitability!C54 -> nov | D53: =DAY(Profitability!D54) -> 1 | E53: =+Profitability!E54 -> viernes | F53: =+Profitability!F54 -> 370000 | G53: ='PE (2)'!$K$9 -> 186333.33 | H53: =+F53*60% -> 222000 | I53: =+G53+H53 -> 408333.33 | J53: =+F53-I53 -> -38333.333 | K53: =+J53 -> -38333.333 | L53: =+E53 -> viernes | M53: =+F53-G53 -> 183666.67 | N53: =+C53 -> nov
C54: =+Profitability!C55 -> nov | D54: =DAY(Profitability!D55) -> 2 | E54: =+Profitability!E55 -> sábado | F54: =+Profitability!F55 -> 500000 | G54: ='PE (2)'!$K$9 -> 186333.33 | H54: =+F54*60% -> 300000 | I54: =+G54+H54 -> 486333.33 | J54: =+F54-I54 -> 13666.667 | K54: =+J54 -> 13666.667 | L54: =+E54 -> sábado | M54: =+F54-G54 -> 313666.67 | N54: =+C54 -> nov
C55: =+Profitability!C56 -> nov | D55: =DAY(Profitability!D56) -> 3 | E55: =+Profitability!E56 -> domingo | F55: =+Profitability!F56 -> 1700000 | G55: ='PE (2)'!$K$9 -> 186333.33 | H55: =+F55*60% -> 1020000 | I55: =+G55+H55 -> 1206333.3 | J55: =+F55-I55 -> 493666.67 | K55: =+J55 -> 493666.67 | L55: =+E55 -> domingo | M55: =+F55-G55 -> 1513666.7 | N55: =+C55 -> nov
C56: =+Profitability!C57 -> nov | D56: =DAY(Profitability!D57) -> 4 | E56: =+Profitability!E57 -> lunes | F56: =+Profitability!F57 -> 600000 | G56: ='PE (2)'!$K$9 -> 186333.33 | H56: =+F56*60% -> 360000 | I56: =+G56+H56 -> 546333.33 | J56: =+F56-I56 -> 53666.667 | K56: =+J56 -> 53666.667 | L56: =+E56 -> lunes | M56: =+F56-G56 -> 413666.67 | N56: =+C56 -> nov
C57: =+Profitability!C58 -> nov | D57: =DAY(Profitability!D58) -> 5 | E57: =+Profitability!E58 -> martes | F57: 0 | G57: ='PE (2)'!$K$9 -> 186333.33 | H57: 0 | I57: =+G57+H57 -> 186333.33 | J57: =+F57-I57 -> -186333.33 | K57: =+J57 -> -186333.33 | L57: =+E57 -> martes | M57: =+F57-G57 -> -186333.33 | N57: =+C57 -> nov
C58: =+Profitability!C59 -> nov | D58: =DAY(Profitability!D59) -> 6 | E58: =+Profitability!E59 -> miércoles | F58: 0 | G58: ='PE (2)'!$K$9 -> 186333.33 | H58: 0 | I58: =+G58+H58 -> 186333.33 | J58: =+F58-I58 -> -186333.33 | K58: =+J58 -> -186333.33 | L58: =+E58 -> miércoles | M58: =+F58-G58 -> -186333.33 | N58: =+C58 -> nov
C59: =+Profitability!C60 -> nov | D59: =DAY(Profitability!D60) -> 7 | E59: =+Profitability!E60 -> jueves | F59: 0 | G59: ='PE (2)'!$K$9 -> 186333.33 | H59: 0 | I59: =+G59+H59 -> 186333.33 | J59: =+F59-I59 -> -186333.33 | K59: =+J59 -> -186333.33 | L59: =+E59 -> jueves | M59: =+F59-G59 -> -186333.33 | N59: =+C59 -> nov
C60: =+Profitability!C61 -> nov | D60: =DAY(Profitability!D61) -> 8 | E60: =+Profitability!E61 -> viernes | F60: =+Profitability!F61 -> 342000 | G60: ='PE (2)'!$K$9 -> 186333.33 | H60: =+F60*60% -> 205200 | I60: =+G60+H60 -> 391533.33 | J60: =+F60-I60 -> -49533.333 | K60: =+J60 -> -49533.333 | L60: =+E60 -> viernes | M60: =+F60-G60 -> 155666.67 | N60: =+C60 -> nov
C61: =+Profitability!C62 -> nov | D61: =DAY(Profitability!D62) -> 9 | E61: =+Profitability!E62 -> sábado | F61: =+Profitability!F62 -> 1552000 | G61: ='PE (2)'!$K$9 -> 186333.33 | H61: =+F61*60% -> 931200 | I61: =+G61+H61 -> 1117533.3 | J61: =+F61-I61 -> 434466.67 | K61: =+J61 -> 434466.67 | L61: =+E61 -> sábado | M61: =+F61-G61 -> 1365666.7 | N61: =+C61 -> nov
C62: =+Profitability!C63 -> nov | D62: =DAY(Profitability!D63) -> 10 | E62: =+Profitability!E63 -> domingo | F62: =+Profitability!F63 -> 1690000 | G62: ='PE (2)'!$K$9 -> 186333.33 | H62: =+F62*60% -> 1014000 | I62: =+G62+H62 -> 1200333.3 | J62: =+F62-I62 -> 489666.67 | K62: =+J62 -> 489666.67 | L62: =+E62 -> domingo | M62: =+F62-G62 -> 1503666.7 | N62: =+C62 -> nov
C63: =+Profitability!C64 -> nov | D63: =DAY(Profitability!D64) -> 11 | E63: =+Profitability!E64 -> lunes | F63: =+Profitability!F64 -> 700000 | G63: ='PE (2)'!$K$9 -> 186333.33 | H63: =+F63*60% -> 420000 | I63: =+G63+H63 -> 606333.33 | J63: =+F63-I63 -> 93666.667 | K63: =+J63 -> 93666.667 | L63: =+E63 -> lunes | M63: =+F63-G63 -> 513666.67 | N63: =+C63 -> nov
C64: =+Profitability!C65 -> nov | D64: =DAY(Profitability!D65) -> 12 | E64: =+Profitability!E65 -> martes | F64: 0 | G64: ='PE (2)'!$K$9 -> 186333.33 | H64: =+F64*60% -> 0 | I64: =+G64+H64 -> 186333.33 | J64: =+F64-I64 -> -186333.33 | K64: =+J64 -> -186333.33 | L64: =+E64 -> martes | M64: =+F64-G64 -> -186333.33 | N64: =+C64 -> nov
C65: =+Profitability!C66 -> nov | D65: =DAY(Profitability!D66) -> 13 | E65: =+Profitability!E66 -> miércoles | F65: 0 | G65: ='PE (2)'!$K$9 -> 186333.33 | H65: =+F65*60% -> 0 | I65: =+G65+H65 -> 186333.33 | J65: =+F65-I65 -> -186333.33 | K65: =+J65 -> -186333.33 | L65: =+E65 -> miércoles | M65: =+F65-G65 -> -186333.33 | N65: =+C65 -> nov
C66: =+Profitability!C67 -> nov | D66: =DAY(Profitability!D67) -> 14 | E66: =+Profitability!E67 -> jueves | F66: 0 | G66: ='PE (2)'!$K$9 -> 186333.33 | H66: =+F66*60% -> 0 | I66: =+G66+H66 -> 186333.33 | J66: =+F66-I66 -> -186333.33 | K66: =+J66 -> -186333.33 | L66: =+E66 -> jueves | M66: =+F66-G66 -> -186333.33 | N66: =+C66 -> nov
C67: =+Profitability!C68 -> nov | D67: =DAY(Profitability!D68) -> 15 | E67: =+Profitability!E68 -> viernes | F67: =+Profitability!F68 -> 235000 | G67: ='PE (2)'!$K$9 -> 186333.33 | H67: =+F67*60% -> 141000 | I67: =+G67+H67 -> 327333.33 | J67: =+F67-I67 -> -92333.333 | K67: =+J67 -> -92333.333 | L67: =+E67 -> viernes | M67: =+F67-G67 -> 48666.667 | N67: =+C67 -> nov
C68: =+Profitability!C69 -> nov | D68: =DAY(Profitability!D69) -> 16 | E68: =+Profitability!E69 -> sábado | F68: =+Profitability!F69 -> 811500 | G68: ='PE (2)'!$K$9 -> 186333.33 | H68: =+F68*60% -> 486900 | I68: =+G68+H68 -> 673233.33 | J68: =+F68-I68 -> 138266.67 | K68: =+J68 -> 138266.67 | L68: =+E68 -> sábado | M68: =+F68-G68 -> 625166.67 | N68: =+C68 -> nov
C69: =+Profitability!C70 -> nov | D69: =DAY(Profitability!D70) -> 17 | E69: =+Profitability!E70 -> domingo | F69: =+Profitability!F70 -> 1300900 | G69: ='PE (2)'!$K$9 -> 186333.33 | H69: =+F69*60% -> 780540 | I69: =+G69+H69 -> 966873.33 | J69: =+F69-I69 -> 334026.67 | K69: =+J69 -> 334026.67 | L69: =+E69 -> domingo | M69: =+F69-G69 -> 1114566.7 | N69: =+C69 -> nov
C70: =+Profitability!C71 -> nov | D70: =DAY(Profitability!D71) -> 18 | E70: =+Profitability!E71 -> lunes | F70: 0 | G70: ='PE (2)'!$K$9 -> 186333.33 | H70: =+F70*60% -> 0 | I70: =+G70+H70 -> 186333.33 | J70: =+F70-I70 -> -186333.33 | K70: =+J70 -> -186333.33 | L70: =+E70 -> lunes | M70: =+F70-G70 -> -186333.33 | N70: =+C70 -> nov
C71: =+Profitability!C72 -> nov | D71: =DAY(Profitability!D72) -> 19 | E71: =+Profitability!E72 -> martes | F71: 0 | G71: ='PE (2)'!$K$9 -> 186333.33 | H71: =+F71*60% -> 0 | I71: =+G71+H71 -> 186333.33 | J71: =+F71-I71 -> -186333.33 | K71: =+J71 -> -186333.33 | L71: =+E71 -> martes | M71: =+F71-G71 -> -186333.33 | N71: =+C71 -> nov
C72: =+Profitability!C73 -> nov | D72: =DAY(Profitability!D73) -> 20 | E72: =+Profitability!E73 -> miércoles | F72: 0 | G72: ='PE (2)'!$K$9 -> 186333.33 | H72: =+F72*60% -> 0 | I72: =+G72+H72 -> 186333.33 | J72: =+F72-I72 -> -186333.33 | K72: =+J72 -> -186333.33 | L72: =+E72 -> miércoles | M72: =+F72-G72 -> -186333.33 | N72: =+C72 -> nov
C73: =+Profitability!C74 -> nov | D73: =DAY(Profitability!D74) -> 21 | E73: =+Profitability!E74 -> jueves | F73: 0 | G73: ='PE (2)'!$K$9 -> 186333.33 | H73: =+F73*60% -> 0 | I73: =+G73+H73 -> 186333.33 | J73: =+F73-I73 -> -186333.33 | K73: =+J73 -> -186333.33 | L73: =+E73 -> jueves | M73: =+F73-G73 -> -186333.33 | N73: =+C73 -> nov
C74: =+Profitability!C75 -> nov | D74: =DAY(Profitability!D75) -> 22 | E74: =+Profitability!E75 -> viernes | F74: =+Profitability!F75 -> 186000 | G74: ='PE (2)'!$K$9 -> 186333.33 | H74: =+F74*60% -> 111600 | I74: =+G74+H74 -> 297933.33 | J74: =+F74-I74 -> -111933.33 | K74: =+J74 -> -111933.33 | L74: =+E74 -> viernes | M74: =+F74-G74 -> -333.33333 | N74: =+C74 -> nov
C75: =+Profitability!C76 -> nov | D75: =DAY(Profitability!D76) -> 23 | E75: =+Profitability!E76 -> sábado | F75: =+Profitability!F76 -> 587500 | G75: ='PE (2)'!$K$9 -> 186333.33 | H75: =+F75*60% -> 352500 | I75: =+G75+H75 -> 538833.33 | J75: =+F75-I75 -> 48666.667 | K75: =+J75 -> 48666.667 | L75: =+E75 -> sábado | M75: =+F75-G75 -> 401166.67 | N75: =+C75 -> nov
C76: =+Profitability!C77 -> nov | D76: =DAY(Profitability!D77) -> 24 | E76: =+Profitability!E77 -> domingo | F76: =+Profitability!F77 -> 960000 | G76: ='PE (2)'!$K$9 -> 186333.33 | H76: =+F76*60% -> 576000 | I76: =+G76+H76 -> 762333.33 | J76: =+F76-I76 -> 197666.67 | K76: =+J76 -> 197666.67 | L76: =+E76 -> domingo | M76: =+F76-G76 -> 773666.67 | N76: =+C76 -> nov
C77: =+Profitability!C78 -> nov | D77: =DAY(Profitability!D78) -> 25 | E77: =+Profitability!E78 -> lunes | F77: 0 | G77: ='PE (2)'!$K$9 -> 186333.33 | H77: =+F77*60% -> 0 | I77: =+G77+H77 -> 186333.33 | J77: =+F77-I77 -> -186333.33 | K77: =+J77 -> -186333.33 | L77: =+E77 -> lunes | M77: =+F77-G77 -> -186333.33 | N77: =+C77 -> nov
C78: =+Profitability!C79 -> nov | D78: =DAY(Profitability!D79) -> 26 | E78: =+Profitability!E79 -> martes | F78: 0 | G78: ='PE (2)'!$K$9 -> 186333.33 | H78: =+F78*60% -> 0 | I78: =+G78+H78 -> 186333.33 | J78: =+F78-I78 -> -186333.33 | K78: =+J78 -> -186333.33 | L78: =+E78 -> martes | M78: =+F78-G78 -> -186333.33 | N78: =+C78 -> nov
C79: =+Profitability!C80 -> nov | D79: =DAY(Profitability!D80) -> 27 | E79: =+Profitability!E80 -> miércoles | F79: 0 | G79: ='PE (2)'!$K$9 -> 186333.33 | H79: =+F79*60% -> 0 | I79: =+G79+H79 -> 186333.33 | J79: =+F79-I79 -> -186333.33 | K79: =+J79 -> -186333.33 | L79: =+E79 -> miércoles | M79: =+F79-G79 -> -186333.33 | N79: =+C79 -> nov
C80: =+Profitability!C81 -> nov | D80: =DAY(Profitability!D81) -> 28 | E80: =+Profitability!E81 -> jueves | F80: 0 | G80: ='PE (2)'!$K$9 -> 186333.33 | H80: =+F80*60% -> 0 | I80: =+G80+H80 -> 186333.33 | J80: =+F80-I80 -> -186333.33 | K80: =+J80 -> -186333.33 | L80: =+E80 -> jueves | M80: =+F80-G80 -> -186333.33 | N80: =+C80 -> nov
C81: =+Profitability!C82 -> nov | D81: =DAY(Profitability!D82) -> 29 | E81: =+Profitability!E82 -> viernes | F81: =+Profitability!F82 -> 400000 | G81: ='PE (2)'!$K$9 -> 186333.33 | H81: =+F81*60% -> 240000 | I81: =+G81+H81 -> 426333.33 | J81: =+F81-I81 -> -26333.333 | K81: =+J81 -> -26333.333 | L81: =+E81 -> viernes | M81: =+F81-G81 -> 213666.67 | N81: =+C81 -> nov
C82: =+Profitability!C83 -> nov | D82: =DAY(Profitability!D83) -> 30 | E82: =+Profitability!E83 -> sábado | F82: =+Profitability!F83 -> 900000 | G82: ='PE (2)'!$K$9 -> 186333.33 | H82: =+F82*60% -> 540000 | I82: =+G82+H82 -> 726333.33 | J82: =+F82-I82 -> 173666.67 | K82: =+J82 -> 173666.67 | L82: =+E82 -> sábado | M82: =+F82-G82 -> 713666.67 | N82: =+C82 -> nov

Sheet Profitability  (2)
D1: Mes | K1: sep | L1: oct | M1: nov | N1: TOTAL
D2: sep | E2: oct | F2: nov | J2: Lunes | K2: =+SUMIFS($J$12:$J$81,$C$12:$C$81,K$1,$E$12:$E$81,$J2) -> 0 | L2: =+SUMIFS($J$12:$J$81,$C$12:$C$81,L$1,$E$12:$E$81,$J2) -> -412642.85 | M2: =+SUMIFS($J$12:$J$81,$C$12:$C$81,M$1,$E$12:$E$81,$J2) -> -361367.5 | N2: =+SUM(K2:M2) -> -774010.35
C3: INGRESOS | D3: 4055210 | E3: 17351500 | F3: 16752900 | J3: viernes | K3: =+SUMIFS($J$12:$J$81,$C$12:$C$81,K$1,$E$12:$E$81,$J3) -> -467300 | L3: =+SUMIFS($J$12:$J$81,$C$12:$C$81,L$1,$E$12:$E$81,$J3) -> -1726671.4 | M3: =+SUMIFS($J$12:$J$81,$C$12:$C$81,M$1,$E$12:$E$81,$J3) -> -949367.5 | N3: =+SUM(K3:M3) -> -3143338.9
B4: 0.4 | C4: Gastos Fijos y Variables | D4: =OPEX!G27 -> 2920000 | E4: =OPEX!M22 -> Mes | J4: sábado | K4: =+SUMIFS($J$12:$J$81,$C$12:$C$81,K$1,$E$12:$E$81,$J4) -> 63200 | L4: =+SUMIFS($J$12:$J$81,$C$12:$C$81,L$1,$E$12:$E$81,$J4) -> -888771.38 | M4: =+SUMIFS($J$12:$J$81,$C$12:$C$81,M$1,$E$12:$E$81,$J4) -> 390632.5 | N4: =+SUM(K4:M4) -> -434938.88
B5: 0.6 | C5: Costos Variables | D5: =OPEX!#REF! -> #REF! | E5: =OPEX!#REF! -> #REF! | J5: domingo | K5: =+SUMIFS($J$12:$J$81,$C$12:$C$81,K$1,$E$12:$E$81,$J5) -> -546600 | L5: =+SUMIFS($J$12:$J$81,$C$12:$C$81,L$1,$E$12:$E$81,$J5) -> 1241028.6 | M5: =+SUMIFS($J$12:$J$81,$C$12:$C$81,M$1,$E$12:$E$81,$J5) -> 1728632.5 | N5: =+SUM(K5:M5) -> 2423061.1
D6: =OPEX!#REF! -> #REF! | E6: =OPEX!#REF! -> #REF! | J6: TOTAL | K6: =+SUM(K2:K5) -> -950700 | L6: =+SUM(L2:L5) -> -1787057 | M6: =+SUM(M2:M5) -> 808530 | N6: =+SUM(N2:N5) -> -1929227 | O6: =+N6-'Profitability (2-Mensualizado)'!N9 -> 2152870
D7: =+D3-D6 -> #REF! | E7: =+E3-E6 -> #REF!
C9: Tipo Dìa | D9: Fds y Festivo
G10: =+G12/I12 -> 0.64842958 | H10: =+H12/I12 -> 0.35157042
C11: Mes | D11: Dia | E11: Día de Semana | F11: INGRESOS TOTALES | G11: GASTOS FIJOS | H11: COSTO MATERIA PRIMA (COSTO VARIABLE) | I11: PRESUPUESTO DE VENTAS | J11: GAP | K11: Saldo actual | L11: Dìa de semanal | M11: Análisis gastos fijos | N11: Mes
C12: sep | D12: 22 | E12: domingo | F12: 572000 | G12: ='PE (2)'!$C$8 -> 576000 | H12: ='PE (2)'!$C$23 -> 312300 | I12: =+G12+H12 -> 888300 | J12: =+F12-I12 -> -316300 | K12: =+J12 -> -316300 | L12: =+E12 -> domingo | M12: =+F12-G12 -> -4000 | N12: =+C12 -> sep
C13: sep | D13: 27 | E13: viernes | F13: 421000 | G13: ='PE (2)'!$C$8 -> 576000 | H13: ='PE (2)'!$C$23 -> 312300 | I13: =+G13+H13 -> 888300 | J13: =+F13-I13 -> -467300 | K13: =+J13+K12 -> -783600 | L13: =+E13 -> viernes | M13: =+F13-G13 -> -155000 | N13: =+C13 -> sep
C14: sep | D14: 28 | E14: sábado | F14: 951500 | G14: ='PE (2)'!$C$8 -> 576000 | H14: ='PE (2)'!$C$23 -> 312300 | I14: =+G14+H14 -> 888300 | J14: =+F14-I14 -> 63200 | K14: =+J14+K13 -> -720400 | L14: =+E14 -> sábado | M14: =+F14-G14 -> 375500 | N14: =+C14 -> sep
C15: sep | D15: 29 | E15: domingo | F15: 658000 | G15: ='PE (2)'!$C$8 -> 576000 | H15: ='PE (2)'!$C$23 -> 312300 | I15: =+G15+H15 -> 888300 | J15: =+F15-I15 -> -230300 | K15: =+J15+K14 -> -950700 | L15: =+E15 -> domingo | M15: =+F15-G15 -> 82000 | N15: =+C15 -> sep
C16: oct | D16: 4 | E16: viernes | F16: 420500 | G16: ='PE (2)'!$G$8 -> 496336.69 | H16: ='PE (2)'!$G$23 -> 538306.15 | I16: =+G16+H16 -> 1034642.8 | J16: =+F16-I16 -> -614142.85 | K16: =+J16+K15 -> -1564842.8 | L16: =+E16 -> viernes | M16: =+F16-G16 -> -75836.692 | N16: =+C16 -> oct
C17: oct | D17: 5 | E17: sábado | F17: 1210300 | G17: ='PE (2)'!$G$8 -> 496336.69 | H17: ='PE (2)'!$G$23 -> 538306.15 | I17: =+G17+H17 -> 1034642.8 | J17: =+F17-I17 -> 175657.15 | K17: =+J17+K16 -> -1389185.7 | L17: =+E17 -> sábado | M17: =+F17-G17 -> 713963.31 | N17: =+C17 -> oct
C18: oct | D18: 6 | E18: domingo | F18: 1345600 | G18: ='PE (2)'!$G$8 -> 496336.69 | H18: ='PE (2)'!$G$23 -> 538306.15 | I18: =+G18+H18 -> 1034642.8 | J18: =+F18-I18 -> 310957.15 | K18: =+J18+K17 -> -1078228.5 | L18: =+E18 -> domingo | M18: =+F18-G18 -> 849263.31 | N18: =+C18 -> oct
C19: oct | D19: 11 | E19: viernes | F19: 427900 | G19: ='PE (2)'!$G$8 -> 496336.69 | H19: ='PE (2)'!$G$23 -> 538306.15 | I19: =+G19+H19 -> 1034642.8 | J19: =+F19-I19 -> -606742.85 | K19: =+J19+K18 -> -1684971.4 | L19: =+E19 -> viernes | M19: =+F19-G19 -> -68436.692 | N19: =+C19 -> oct
C20: oct | D20: 12 | E20: sábado | F20: 664500 | G20: ='PE (2)'!$G$8 -> 496336.69 | H20: ='PE (2)'!$G$23 -> 538306.15 | I20: =+G20+H20 -> 1034642.8 | J20: =+F20-I20 -> -370142.85 | K20: =+J20+K19 -> -2055114.2 | L20: =+E20 -> sábado | M20: =+F20-G20 -> 168163.31 | N20: =+C20 -> oct
C21: oct | D21: 13 | E21: domingo | F21: 1283500 | G21: ='PE (2)'!$G$8 -> 496336.69 | H21: ='PE (2)'!$G$23 -> 538306.15 | I21: =+G21+H21 -> 1034642.8 | J21: =+F21-I21 -> 248857.15 | K21: =+J21+K20 -> -1806257.1 | L21: =+E21 -> domingo | M21: =+F21-G21 -> 787163.31 | N21: =+C21 -> oct
C22: oct | D22: 14 | E22: lunes | F22: 622000 | G22: ='PE (2)'!$G$8 -> 496336.69 | H22: ='PE (2)'!$G$23 -> 538306.15 | I22: =+G22+H22 -> 1034642.8 | J22: =+F22-I22 -> -412642.85 | K22: =+J22+K21 -> -2218899.9 | L22: =+E22 -> lunes | M22: =+F22-G22 -> 125663.31 | N22: =+C22 -> oct
C23: oct | D23: 18 | E23: viernes | F23: 363500 | G23: ='PE (2)'!$G$8 -> 496336.69 | H23: ='PE (2)'!$G$23 -> 538306.15 | I23: =+G23+H23 -> 1034642.8 | J23: =+F23-I23 -> -671142.85 | K23: =+J23+K22 -> -2890042.8 | L23: =+E23 -> viernes | M23: =+F23-G23 -> -132836.69 | N23: =+C23 -> oct
C24: oct | D24: 19 | E24: sábado | F24: 720000 | G24: ='PE (2)'!$G$8 -> 496336.69 | H24: ='PE (2)'!$G$23 -> 538306.15 | I24: =+G24+H24 -> 1034642.8 | J24: =+F24-I24 -> -314642.85 | K24: =+J24+K23 -> -3204685.6 | L24: =+E24 -> sábado | M24: =+F24-G24 -> 223663.31 | N24: =+C24 -> oct
C25: oct | D25: 20 | E25: domingo | F25: 1550500 | G25: ='PE (2)'!$G$8 -> 496336.69 | H25: ='PE (2)'!$G$23 -> 538306.15 | I25: =+G25+H25 -> 1034642.8 | J25: =+F25-I25 -> 515857.15 | K25: =+J25+K24 -> -2688828.5 | L25: =+E25 -> domingo | M25: =+F25-G25 -> 1054163.3 | N25: =+C25 -> oct
C26: oct | D26: 25 | E26: viernes | F26: 1200000 | G26: ='PE (2)'!$G$8 -> 496336.69 | H26: ='PE (2)'!$G$23 -> 538306.15 | I26: =+G26+H26 -> 1034642.8 | J26: =+F26-I26 -> 165357.15 | K26: =+J26+K25 -> -2523471.3 | L26: =+E26 -> viernes | M26: =+F26-G26 -> 703663.31 | N26: =+C26 -> oct
C27: oct | D27: 26 | E27: sábado | F27: 655000 | G27: ='PE (2)'!$G$8 -> 496336.69 | H27: ='PE (2)'!$G$23 -> 538306.15 | I27: =+G27+H27 -> 1034642.8 | J27: =+F27-I27 -> -379642.85 | K27: =+J27+K26 -> -2903114.2 | L27: =+E27 -> sábado | M27: =+F27-G27 -> 158663.31 | N27: =+C27 -> oct
C28: oct | D28: 27 | E28: domingo | F28: 1200000 | G28: ='PE (2)'!$G$8 -> 496336.69 | H28: ='PE (2)'!$G$23 -> 538306.15 | I28: =+G28+H28 -> 1034642.8 | J28: =+F28-I28 -> 165357.15 | K28: =+J28+K27 -> -2737757 | L28: =+E28 -> domingo | M28: =+F28-G28 -> 703663.31 | N28: =+C28 -> oct
C29: nov | D29: 1 | E29: viernes | F29: 370000 | G29: ='PE (2)'!$K$8 -> 349375 | H29: ='PE (2)'!$K$23 -> 481308.75 | I29: =+G29+H29 -> 830683.75 | J29: =+F29-I29 -> -460683.75 | K29: =+J29+K28 -> -3198440.8 | L29: =+E29 -> viernes | M29: =+F29-G29 -> 20625 | N29: =+C29 -> nov
C30: nov | D30: 2 | E30: sábado | F30: 500000 | G30: ='PE (2)'!$K$8 -> 349375 | H30: ='PE (2)'!$K$23 -> 481308.75 | I30: =+G30+H30 -> 830683.75 | J30: =+F30-I30 -> -330683.75 | K30: =+J30+K29 -> -3529124.5 | L30: =+E30 -> sábado | M30: =+F30-G30 -> 150625 | N30: =+C30 -> nov
C31: nov | D31: 3 | E31: domingo | F31: 1700000 | G31: ='PE (2)'!$K$8 -> 349375 | H31: ='PE (2)'!$K$23 -> 481308.75 | I31: =+G31+H31 -> 830683.75 | J31: =+F31-I31 -> 869316.25 | K31: =+J31+K30 -> -2659808.2 | L31: =+E31 -> domingo | M31: =+F31-G31 -> 1350625 | N31: =+C31 -> nov
C32: nov | D32: 4 | E32: lunes | F32: 600000 | G32: ='PE (2)'!$K$8 -> 349375 | H32: ='PE (2)'!$K$23 -> 481308.75 | I32: =+G32+H32 -> 830683.75 | J32: =+F32-I32 -> -230683.75 | K32: =+J32+K31 -> -2890492 | L32: =+E32 -> lunes | M32: =+F32-G32 -> 250625 | N32: =+C32 -> nov
C33: nov | D33: 8 | E33: viernes | F33: 342000 | G33: ='PE (2)'!$K$8 -> 349375 | H33: ='PE (2)'!$K$23 -> 481308.75 | I33: =+G33+H33 -> 830683.75 | J33: =+F33-I33 -> -488683.75 | K33: =+J33+K32 -> -3379175.8 | L33: =+E33 -> viernes | M33: =+F33-G33 -> -7375 | N33: =+C33 -> nov
C34: nov | D34: 9 | E34: sábado | F34: 1552000 | G34: ='PE (2)'!$K$8 -> 349375 | H34: ='PE (2)'!$K$23 -> 481308.75 | I34: =+G34+H34 -> 830683.75 | J34: =+F34-I34 -> 721316.25 | K34: =+J34+K33 -> -2657859.5 | L34: =+E34 -> sábado | M34: =+F34-G34 -> 1202625 | N34: =+C34 -> nov
C35: nov | D35: 10 | E35: domingo | F35: 1690000 | G35: ='PE (2)'!$K$8 -> 349375 | H35: ='PE (2)'!$K$23 -> 481308.75 | I35: =+G35+H35 -> 830683.75 | J35: =+F35-I35 -> 859316.25 | K35: =+J35+K34 -> -1798543.2 | L35: =+E35 -> domingo | M35: =+F35-G35 -> 1340625 | N35: =+C35 -> nov
C36: nov | D36: 11 | E36: lunes | F36: 700000 | G36: ='PE (2)'!$K$8 -> 349375 | H36: ='PE (2)'!$K$23 -> 481308.75 | I36: =+G36+H36 -> 830683.75 | J36: =+F36-I36 -> -130683.75 | K36: =+J36+K35 -> -1929227 | L36: =+E36 -> lunes | M36: =+F36-G36 -> 350625 | N36: =+C36 -> nov
C37: nov | D37: 15 | E37: viernes | F37: 235000
C38: nov | D38: 16 | E38: sábado | F38: 811500
C39: nov | D39: 17 | E39: domingo | F39: 1300900
C40: nov | D40: 22 | E40: viernes | F40: 186000
C41: nov | D41: 23 | E41: sábado | F41: 587500
C42: nov | D42: 24 | E42: domingo | F42: 960000
C43: nov | D43: 29 | E43: viernes | F43: 400000
C44: nov | D44: 30 | E44: sábado | F44: 900000

Sheet _x0009_Profitability (3)
D1: Mes | K1: sep | L1: oct | M1: nov | N1: TOTAL
D2: sep | E2: oct | F2: nov | J2: Lunes | K2: =+SUMIFS($J$12:$J$81,$C$12:$C$81,K$1,$E$12:$E$81,$J2) -> 0 | L2: =+SUMIFS($J$12:$J$81,$C$12:$C$81,L$1,$E$12:$E$81,$J2) -> -662801.89 | M2: =+SUMIFS($J$12:$J$81,$C$12:$C$81,M$1,$E$12:$E$81,$J2) -> -1553832.2 | N2: =+SUM(K2:M2) -> -2216634.1
C3: INGRESOS | D3: 4055210 | E3: 17351500 | F3: 16752900 | J3: sábado | K3: =+SUMIFS($J$12:$J$81,$C$12:$C$81,K$1,$E$12:$E$81,$J3) -> -223133.33 | L3: =+SUMIFS($J$12:$J$81,$C$12:$C$81,L$1,$E$12:$E$81,$J3) -> -1889407.6 | M3: =+SUMIFS($J$12:$J$81,$C$12:$C$81,M$1,$E$12:$E$81,$J3) -> -801832.21 | N3: =+SUM(K3:M3) -> -2914373.1
B4: 0.4 | C4: Gastos Fijos y Variables | D4: =OPEX!G27 -> 2920000 | E4: =OPEX!M22 -> Mes | J4: domingo | K4: =+SUMIFS($J$12:$J$81,$C$12:$C$81,K$1,$E$12:$E$81,$J4) -> -1119266.7 | L4: =+SUMIFS($J$12:$J$81,$C$12:$C$81,L$1,$E$12:$E$81,$J4) -> 240392.44 | M4: =+SUMIFS($J$12:$J$81,$C$12:$C$81,M$1,$E$12:$E$81,$J4) -> 536167.79 | N4: =+SUM(K4:M4) -> -342706.43
B5: 0.6 | C5: Costos Variables | D5: =OPEX!#REF! -> #REF! | E5: =OPEX!#REF! -> #REF! | J5: TOTAL | K5: =+SUM(K2:K4) -> -1342400 | L5: =+SUM(L2:L4) -> -2311817 | M5: =+SUM(M2:M4) -> -1819496.6 | N5: =+SUM(N2:N4) -> -5473713.6
D6: =OPEX!#REF! -> #REF! | E6: =OPEX!#REF! -> #REF!
D7: =+D3-D6 -> #REF! | E7: =+E3-E6 -> #REF!
C9: Tipo Dìa | D9: Fds y Festivo
G10: =+G12/I12 -> 0.62856494 | H10: =+H12/I12 -> 0.37143506
C11: Mes | D11: Dia | E11: Día de Semana | F11: INGRESOS TOTALES | G11: GASTOS FIJOS | H11: COSTO MATERIA PRIMA (COSTO VARIABLE) | I11: PRESUPUESTO DE VENTAS | J11: GAP | K11: Saldo actual | L11: Dìa de semanal | M11: Análisis gastos fijos | N11: Mes
C12: sep | D12: 22 | E12: domingo | F12: 572000 | G12: ='PE (3)'!$C$8 -> 738333.33 | H12: ='PE (3)'!$C$22 -> 436300 | I12: =+G12+H12 -> 1174633.3 | J12: =+F12-I12 -> -602633.33 | K12: =+J12 -> -602633.33 | L12: =+E12 -> domingo | M12: =+F12-G12 -> -166333.33 | N12: =+C12 -> sep
C13: sep | D13: 28 | E13: sábado | F13: 951500 | G13: ='PE (3)'!$C$8 -> 738333.33 | H13: ='PE (3)'!$C$22 -> 436300 | I13: =+G13+H13 -> 1174633.3 | J13: =+F13-I13 -> -223133.33 | K13: =+J13+K12 -> -825766.67 | L13: =+E13 -> sábado | M13: =+F13-G13 -> 213166.67 | N13: =+C13 -> sep
C14: sep | D14: 29 | E14: domingo | F14: 658000 | G14: ='PE (3)'!$C$8 -> 738333.33 | H14: ='PE (3)'!$C$22 -> 436300 | I14: =+G14+H14 -> 1174633.3 | J14: =+F14-I14 -> -516633.33 | K14: =+J14+K13 -> -1342400 | L14: =+E14 -> domingo | M14: =+F14-G14 -> -80333.333 | N14: =+C14 -> sep
C15: oct | D15: 5 | E15: sábado | F15: 1210300 | G15: ='PE (3)'!$G$8 -> 668041.89 | H15: ='PE (3)'!$G$22 -> 616760 | I15: =+G15+H15 -> 1284801.9 | J15: =+F15-I15 -> -74501.889 | K15: =+J15+K14 -> -1416901.9 | L15: =+E15 -> sábado | M15: =+F15-G15 -> 542258.11 | N15: =+C15 -> oct
C16: oct | D16: 6 | E16: domingo | F16: 1345600 | G16: ='PE (3)'!$G$8 -> 668041.89 | H16: ='PE (3)'!$G$22 -> 616760 | I16: =+G16+H16 -> 1284801.9 | J16: =+F16-I16 -> 60798.111 | K16: =+J16+K15 -> -1356103.8 | L16: =+E16 -> domingo | M16: =+F16-G16 -> 677558.11 | N16: =+C16 -> oct
C17: oct | D17: 12 | E17: sábado | F17: 664500 | G17: ='PE (3)'!$G$8 -> 668041.89 | H17: ='PE (3)'!$G$22 -> 616760 | I17: =+G17+H17 -> 1284801.9 | J17: =+F17-I17 -> -620301.89 | K17: =+J17+K16 -> -1976405.7 | L17: =+E17 -> sábado | M17: =+F17-G17 -> -3541.8889 | N17: =+C17 -> oct
C18: oct | D18: 13 | E18: domingo | F18: 1283500 | G18: ='PE (3)'!$G$8 -> 668041.89 | H18: ='PE (3)'!$G$22 -> 616760 | I18: =+G18+H18 -> 1284801.9 | J18: =+F18-I18 -> -1301.8889 | K18: =+J18+K17 -> -1977707.6 | L18: =+E18 -> domingo | M18: =+F18-G18 -> 615458.11 | N18: =+C18 -> oct
C19: oct | D19: 14 | E19: lunes | F19: 622000 | G19: ='PE (3)'!$G$8 -> 668041.89 | H19: ='PE (3)'!$G$22 -> 616760 | I19: =+G19+H19 -> 1284801.9 | J19: =+F19-I19 -> -662801.89 | K19: =+J19+K18 -> -2640509.4 | L19: =+E19 -> lunes | M19: =+F19-G19 -> -46041.889 | N19: =+C19 -> oct
C20: oct | D20: 19 | E20: sábado | F20: 720000 | G20: ='PE (3)'!$G$8 -> 668041.89 | H20: ='PE (3)'!$G$22 -> 616760 | I20: =+G20+H20 -> 1284801.9 | J20: =+F20-I20 -> -564801.89 | K20: =+J20+K19 -> -3205311.3 | L20: =+E20 -> sábado | M20: =+F20-G20 -> 51958.111 | N20: =+C20 -> oct
C21: oct | D21: 20 | E21: domingo | F21: 1550500 | G21: ='PE (3)'!$G$8 -> 668041.89 | H21: ='PE (3)'!$G$22 -> 616760 | I21: =+G21+H21 -> 1284801.9 | J21: =+F21-I21 -> 265698.11 | K21: =+J21+K20 -> -2939613.2 | L21: =+E21 -> domingo | M21: =+F21-G21 -> 882458.11 | N21: =+C21 -> oct
C22: oct | D22: 26 | E22: sábado | F22: 655000 | G22: ='PE (3)'!$G$8 -> 668041.89 | H22: ='PE (3)'!$G$22 -> 616760 | I22: =+G22+H22 -> 1284801.9 | J22: =+F22-I22 -> -629801.89 | K22: =+J22+K21 -> -3569415.1 | L22: =+E22 -> sábado | M22: =+F22-G22 -> -13041.889 | N22: =+C22 -> oct
C23: oct | D23: 27 | E23: domingo | F23: 1200000 | G23: ='PE (3)'!$G$8 -> 668041.89 | H23: ='PE (3)'!$G$22 -> 616760 | I23: =+G23+H23 -> 1284801.9 | J23: =+F23-I23 -> -84801.889 | K23: =+J23+K22 -> -3654217 | L23: =+E23 -> domingo | M23: =+F23-G23 -> 531958.11 | N23: =+C23 -> oct
C24: nov | D24: 2 | E24: sábado | F24: 500000 | G24: ='PE (3)'!$K$8 -> 458181.82 | H24: ='PE (3)'!$K$22 -> 968734.29 | I24: =+G24+H24 -> 1426916.1 | J24: =+F24-I24 -> -926916.1 | K24: =+J24+K23 -> -4581133.1 | L24: =+E24 -> sábado | M24: =+F24-G24 -> 41818.182 | N24: =+C24 -> nov
C25: nov | D25: 3 | E25: domingo | F25: 1700000 | G25: ='PE (3)'!$K$8 -> 458181.82 | H25: ='PE (3)'!$K$22 -> 968734.29 | I25: =+G25+H25 -> 1426916.1 | J25: =+F25-I25 -> 273083.9 | K25: =+J25+K24 -> -4308049.2 | L25: =+E25 -> domingo | M25: =+F25-G25 -> 1241818.2 | N25: =+C25 -> nov
C26: nov | D26: 4 | E26: lunes | F26: 600000 | G26: ='PE (3)'!$K$8 -> 458181.82 | H26: ='PE (3)'!$K$22 -> 968734.29 | I26: =+G26+H26 -> 1426916.1 | J26: =+F26-I26 -> -826916.1 | K26: =+J26+K25 -> -5134965.3 | L26: =+E26 -> lunes | M26: =+F26-G26 -> 141818.18 | N26: =+C26 -> nov
C27: nov | D27: 9 | E27: sábado | F27: 1552000 | G27: ='PE (3)'!$K$8 -> 458181.82 | H27: ='PE (3)'!$K$22 -> 968734.29 | I27: =+G27+H27 -> 1426916.1 | J27: =+F27-I27 -> 125083.9 | K27: =+J27+K26 -> -5009881.4 | L27: =+E27 -> sábado | M27: =+F27-G27 -> 1093818.2 | N27: =+C27 -> nov
C28: nov | D28: 10 | E28: domingo | F28: 1690000 | G28: ='PE (3)'!$K$8 -> 458181.82 | H28: ='PE (3)'!$K$22 -> 968734.29 | I28: =+G28+H28 -> 1426916.1 | J28: =+F28-I28 -> 263083.9 | K28: =+J28+K27 -> -4746797.5 | L28: =+E28 -> domingo | M28: =+F28-G28 -> 1231818.2 | N28: =+C28 -> nov
C29: nov | D29: 11 | E29: lunes | F29: 700000 | G29: ='PE (3)'!$K$8 -> 458181.82 | H29: ='PE (3)'!$K$22 -> 968734.29 | I29: =+G29+H29 -> 1426916.1 | J29: =+F29-I29 -> -726916.1 | K29: =+J29+K28 -> -5473713.6 | L29: =+E29 -> lunes | M29: =+F29-G29 -> 241818.18 | N29: =+C29 -> nov
C30: nov | D30: 16 | E30: sábado | F30: 811500
C31: nov | D31: 17 | E31: domingo | F31: 1300900
C32: nov | D32: 23 | E32: sábado | F32: 587500
C33: nov | D33: 24 | E33: domingo | F33: 960000
C34: nov | D34: 30 | E34: sábado | F34: 900000

Sheet Expetures Forecasting 
A1: Gastos del negocio sin incluir costo de la mercancia | G1: Futuro
C2: Dia hábil | D2: Dia fds | E2: Mensual | I2: Dia hábil | J2: Dia fds | K2: Mensual
A3: Arriendo | B3: Arriendo | C3: =+E3/30 -> 83333.333 | E3: 2500000 | G3: Arriendo | H3: Arriendo | I3: =+K3/30 -> 83333.333 | K3: 2500000
A4: Servicios | B4: Agua | C4: =+E4/30 -> 10000 | E4: 300000 | G4: Servicios | H4: Agua | I4: =+K4/30 -> 26666.667 | K4: 800000
B5: Luz | C5: =+E5/30 -> 8333.3333 | E5: 250000 | H5: Luz | I5: =+K5/30 -> 8333.3333 | K5: 250000
B6: Gas | C6: =+E6/30 -> 8333.3333 | E6: 250000 | H6: Gas | I6: =+K6/30 -> 8333.3333 | K6: 250000
B7: Telefonía, internet y televisión | H7: Telefonía, internet y televisión | I7: =+K7/30 -> 4666.6667 | K7: 140000
A8: Nomina | B8: Ayudante de cocina senior | C8: 35000 | D8: 35000 | E8: =+(C8*20)+(D8*10) -> 1050000 | G8: Nomina | H8: Ayudante de cocina senior | I8: 30000 | J8: 35000 | K8: =+(I8*20)+(J8*10) -> 950000
B9: Ayudante de cocina Junior | C9: 25000 | D9: 25000 | E9: =+(C9*20)+(D9*10) -> 750000 | H9: Ayudante de cocina Junior | I9: 25000 | J9: 30000 | K9: =+(I9*20)+(J9*10) -> 800000
B10: Mesero (a) fijo | C10: 25000 | D10: 25000 | E10: =+(C10*20)+(D10*10) -> 750000 | H10: Mesero (a) fijo | I10: 25000 | J10: 30000 | K10: =+(I10*20)+(J10*10) -> 800000
B11: Mesero (a) sabatino | C11: 0 | D11: 35000 | E11: =+(C11*20)+(D11*10) -> 350000 | H11: Mesero (a) sabatino | I11: 0 | J11: 35000 | K11: =+(I11*20)+(J11*10) -> 350000
B12: Chef- Cocinero sabatino | C12: 0 | D12: 35000 | E12: =+(C12*20)+(D12*10) -> 350000 | H12: Chef- Cocinero sabatino | I12: 0 | J12: 45000 | K12: =+(I12*20)+(J12*10) -> 450000
B13: Banderero | C13: 15000 | D13: 15000 | E13: =+(C13*20)+(D13*10) -> 450000 | H13: Banderero | I13: 15000 | J13: 15000 | K13: =+(I13*20)+(J13*10) -> 450000
B14: Asistente administrativo y mercadeo | E14: =+(C14*20)+(D14*10) -> 0 | H14: Asistente administrativo y mercadeo | I14: 35000 | J14: 35000 | K14: =+(I14*20)+(J14*10) -> 1050000
B15: Parrillero, Jefe de compras, jefe de tesorería, jefe de personal | C15: 50000 | D15: 50000 | E15: =+(C15*20)+(D15*10) -> 1500000 | H15: Parrillero, Jefe de compras, jefe de tesorería, jefe de personal | I15: =60000+50000 -> 110000 | J15: =80000+50000 -> 130000 | K15: =+(I15*20)+(J15*10) -> 3500000
B16: Caja, Jefe de contabilidad Administrador, jefe de compras, Auditor interno, Facturación Investigador de mercados, analista de negocios (datos), Gerente comercial | C16: 0 | D16: 0 | E16: =+(C16*20)+(D16*10) -> 0 | H16: Caja, Jefe de contabilidad Administrador, jefe de compras, Auditor interno, Facturación Investigador de mercados, analista de negocios (datos), Gerente comercial | I16: =35000 -> 35000 | J16: =35000 -> 35000 | K16: =+(I16*20)+(J16*10) -> 1050000
A17: Financieros | B17: ScotiaBank | C17: =+E17/30 -> 4166.6667 | E17: 125000 | G17: Financieros | H17: ScotiaBank | I17: =+K17/30 -> 4166.6667 | K17: 125000
B18: Bancolombia | C18: =+E18/30 -> 8256.6667 | E18: 247700 | H18: Bancolombia | I18: =+K18/30 -> 8256.6667 | K18: 247700
B19: Banco Hector (cuantos meses) | C19: =+E19/30 -> 20000 | E19: 600000 | H19: Banco Hector | I19: =+K19/30 -> 16666.667 | K19: 500000
C21: =+SUM(C3:D7,C17:D19,C8:C16) -> 292423.33 | D21: =+SUM(C3:D7,C17:D19,D8:D16) -> 362423.33 | E21: =+SUM(E3:E19) -> 9472700 | F21: 0.4 | G21: Costos | I21: =+SUM(I3:I19) -> 435423.33 | J21: =+SUM(J3:J19) -> 390000 | K21: =+SUM(K3:K19) -> 14212700 | L21: 0.4
C22: =+C$24*$F22 -> 36552.917 | D22: =+D$24*$F22 -> 45302.917 | E22: =+E$24*$F22 -> 1184087.5 | F22: 0.05 | G22: Ganancia | I22: =+I$24*$F22 -> 54427.917 | J22: =+J$24*$F22 -> 48750 | K22: =+K$24*$F22 -> 1776587.5 | L22: 0.05
C23: =+C$24*$F23 -> 402082.08 | D23: =+D$24*$F23 -> 498332.08 | E23: =+E$24*$F23 -> 13024963 | F23: 0.55 | G23: Mercancia | I23: =+I$24*$F23 -> 598707.08 | J23: =+J$24*$F23 -> 536250 | K23: =+K$24*$F23 -> 19542462 | L23: 0.55
C24: =(C21/40)*100 -> 731058.33 | D24: =(D21/40)*100 -> 906058.33 | E24: =(E21/40)*100 -> 23681750 | I24: =(I21/40)*100 -> 1088558.3 | J24: =(J21/40)*100 -> 975000 | K24: =(K21/40)*100 -> 35531750
E27: 15910250
E29: =+E27-E21 -> 6437550

Sheet Análisis por producto
A1: FECHA | B1: All | E1: FECHA | F1: (Varios elementos)
A3: Etiquetas de fila | B3: Suma de Ventas | C3: Recuento distinto de Id. Client por dìa | E3: Suma de Ventas | F3: Etiquetas de columna
A4: lunes | B4: 4350710 | C4: 15 | E4: Etiquetas de fila | F4: lunes | G4: martes | H4: miércoles | I4: jueves | J4: viernes | K4: sábado | L4: domingo | M4: Total general
A5: (en blanco) | B5: 3586710 | C5: 1 | E5: Picada | H5: 125000 | I5: 20000 | J5: 105000 | K5: 370000 | L5: 215000 | M5: 835000
A6: Picada | B6: 475000 | C6: 11 | E6: Ejecutivo | F6: 106000 | G6: 70000 | H6: 148000 | I6: 122000 | J6: 220000 | K6: 62500 | L6: 32000 | M6: 760500
A7: Ejecutivo | B7: 130000 | C7: 6 | E7: Carne llanera | G7: 144000 | H7: 49000 | I7: 50000 | K7: 50000 | M7: 293000
A8: Sopa | B8: 49500 | C8: 5 | E8: Picada con Refajo | I8: 70000 | K8: 100000 | M8: 170000
A9: Arroz chino premium | B9: 22000 | C9: 1 | E9: Sopa | F9: 6000 | G9: 24000 | H9: 24000 | I9: 14000 | J9: 13000 | K9: 54000 | L9: 27000 | M9: 162000
A10: Caderita | B10: 22000 | C10: 1 | E10: Cerbeza | G10: 75000 | I10: 6000 | J10: 16000 | M10: 97000
A11: Gaseosa litro y medio Coca Cola | B11: 17500 | C11: 3 | E11: Media carne | G11: 15000 | H11: 30000 | I11: 27000 | K11: 15000 | M11: 87000
A12: Refajo | B12: 16000 | C12: 2 | E12: hamburguesa | K12: 40000 | L12: 24000 | M12: 64000
A13: Gaseosa 350 | B13: 10000 | C13: 4 | E13: Combo Hamburguesa | J13: 25000 | K13: 12000 | L13: 25000 | M13: 62000
A14: Gaseosa litro y medio | B14: 4000 | C14: 1 | E14: Parrilla 4 carnes | L14: 60000 | M14: 60000
